Workbook

Sheet About the Company
B1: AMBUJA CEMENTS LIMITED
B2: Cement & Building Materials | Part of The Adani Group | BSE: 500425 | NSE: AMBUJACEM | www.ambujacement.com
B4: ◆ COMPANY OVERVIEW
B5: Company Name | C5: Ambuja Cements Limited | D5: Formerly Known As | E5: Ambuja Cements India Ltd. / Gujarat Ambuja Cements Ltd.
B6: CIN | C6: L26942GJ1981PLC004717 | D6: Stock Exchange(s) | E6: BSE (500425) | NSE (AMBUJACEM)
B7: Incorporated | C7: 1981, Gujarat | D7: Listing Year | E7: Listed on BSE & NSE; part of CNX Nifty 50 index
B8: Registered Office | C8: Adani Corporate House, Shantigram, S.G. Highway, Ahmedabad – 382213 | D8: Market Cap | E8: ₹1,32,602 crore (as on 31 March 2025)
B9: Reporting Period | C9: FY 2024-25 (April 1, 2024 – March 31, 2025) | D9: Report Type | E9: 7th Integrated Annual Report (IFRS Foundation IR Framework)
B10: ◆ PARENT / PROMOTER STRUCTURE
B11: Ultimate Parent Group | C11: Adani Group — Founded 1988 by Gautam Adani, HQ Ahmedabad; India's largest diversified infrastructure conglomerate
B12: Direct Parent Entity | C12: Holderind Investments Ltd. (Promoter) — 47.72% stake; Harmonia Trade and Investment Ltd. — 19.23%; Adani Enterprises Ltd. (Promoter Group) — 0.35%
B13: Total Promoter Holding | C13: 67.33% held by Adani promoter group (as on 31 March 2025)
B14: Adani Group Position | C14: Ambuja Cements is the cement and building materials flagship within the Adani Portfolio's 'Materials, Metals & Mining' vertical; sits alongside ACC, Sanghi, and Orient Cement under Adani's cement umbrella targeting 140 MTPA by FY 2027-28
B15: ◆ NATURE OF BUSINESS
B16: Primary Business | C16: Manufacturing and marketing of cement and building materials — one of India's largest cement producers
B17: Industry / Sector | C17: Cement & Building Materials | Construction Materials | Consumer discretionary / Industrials
B18: Product Portfolio | C18: Ambuja Cement (flagship) | Ambuja Plus (high-strength) | Ambuja Compocem (dense concrete) | Ambuja Kawach (water-repellent) | Ambuja Cool Walls (eco-friendly, 5°C cooler) | Ready-Mix Concrete | Blended Cement (>82% of portfolio); 4 products GRIHA-certified
B19: Blended Cement Mix | C19: Over 82% of portfolio is blended cement; Clinker Factor at 64%
B20: Geographic Presence | C20: Present in 31 States and UTs across 635+ districts in India; 1,10,000+ channel partners
B21: Manufacturing Network | C21: 24 Integrated Plants | 22 Grinding Units | 11 Bulk Cement Terminals | 102 Ready-Mix Concrete Plants | 11 Captive Ships
B22: ◆ SUBSIDIARIES & KEY GROUP ENTITIES
B23: Entity | C23: Type / Stake | D23: HQ / Location | E23: Nature of Business
B24: ACC Limited | C24: Subsidiary — 50.05% stake | D24: Mumbai, India | E24: India's one of largest cement producers; fully integrated with Ambuja under Adani Cement umbrella
B25: Sanghi Industries Limited | C25: Subsidiary — 58.08% stake | D25: Gujarat, India | E25: Cement manufacturing; large integrated plant at Sanghipuram, Gujarat; key addition post-acquisition
B26: Orient Cement Limited | C26: Subsidiary — 46.66% stake (w.e.f. April 2025) | D26: Hyderabad, India | E26: Cement manufacturing — acquisition completed April 2025; added 8.5 MTPA capacity
B27: Ambuja Cements (Rajasthan) Ltd. | C27: Wholly Owned Subsidiary | D27: Rajasthan, India | E27: Cement plant operations; limestone mining in Rajasthan
B28: Chemical Limes Mundwa Pvt. Ltd. | C28: Wholly Owned Subsidiary | D28: Rajasthan, India | E28: Limestone mining and lime products
B29: M.G.T. Cements Pvt. Ltd. | C29: Wholly Owned Subsidiary | D29: India | E29: Cement grinding operations
B30: Dang Cement Industries Pvt. Ltd. | C30: Wholly Owned Subsidiary | D30: India | E30: Cement plant operations
B31: Dirk India Pvt. Ltd. | C31: Subsidiary | D31: India | E31: Specialty construction chemicals and products
B32: Ambuja Shipping Services Ltd. | C32: Subsidiary | D32: India | E32: Captive maritime logistics — operates 11 captive ships for coastal cement dispatch
B33: ◆ KEY FINANCIAL HIGHLIGHTS — FY 2024-25 (Consolidated)
B34: Revenue from Operations | C34: ₹37,699 Crore | D34: Adj. EBITDA | E34: ₹8,645 Crore
B35: Profit After Tax (PAT) | C35: ₹5,158 Crore | D35: Market Capitalisation | E35: ₹1,32,602 Crore (as on 31 Mar 2025)
B36: Debt Status | C36: Debt-free (despite significant capex in FY25) | D36: Cement Capacity (FY25) | E36: 88.9 MTPA during FY25 → 100+ MTPA post Orient acquisition (April 2025)
B37: Tax Contribution | C37: ₹16,648 Crore paid to national exchequer | D37: Global Rank | E37: 9th largest cement company globally after crossing 100 MTPA milestone
B38: ◆ OPERATIONAL HIGHLIGHTS — FY 2024-25
B39: Cement Capacity Target | C39: 118 MTPA by FY2026 | 140 MTPA by FY2028 | D39: Plants of the Future | E39: Digital transformation programme across all plants — AI, IoT, automation, advanced analytics
B40: Integrated Units | C40: 24 Integrated Plants | 22 Grinding Units | 11 Bulk Terminals | 102 RMC Plants | D40: Captive Ships | E40: 11 captive ships for bulk sea-freight dispatch; strategic coastal logistics
B41: Distribution Network | C41: 1,10,000+ channel partners across India; 31 States & UTs; 635+ districts | D41: Ready-Mix Concrete | E41: 102 RMC plants serving urban infra and institutional customers
B42: Key Growth Milestones | C42: Crossed 100 MTPA in just 30 months after Holcim acquisition (Aug 2022) — fastest growing cement business in India | D42: Acquisitions (FY25) | E42: Orient Cement (46.66% stake, Apr 2025 completion); adding 8.5 MTPA; Farakka expansion +2.4 MTPA
B43: ◆ ESG & SUSTAINABILITY
B44: Net Zero Commitment | C44: Net Zero by 2050; near-term 2030 targets validated by Science Based Targets initiative (SBTi)
B45: Water Positive | C45: India's first water-positive cement company — 12x water positive in FY 2024-25
B46: Renewable Energy | C46: 28% renewable and green energy consumption; targeting 60% by FY2027-28; 1 GW renewable project underway
B47: Circular Economy | C47: 8.1 MTPA of waste-derived resources used; Thermal Substitution Rate 9%; Plastic Negative 11x
B48: AFID Membership | C48: World's first cement company to join AFID (Alliance for Industry Decarbonization) — an IRENA initiative
B49: CSR | C49: ₹50.27 Crore CSR spent; 3.48 million lives impacted; 1.5 million trees planted cumulatively
B50: Scope 1 Emissions | C50: 537 kg/tonne of cementitious material; target 440 kg by 2030 (SBTi validated)
B51: ◆ BRAND, RECOGNITION & CERTIFICATIONS
B52: Brand Rankings | C52: India's Most Trusted Cement Brand (TRA Research) | Iconic Brand of India (Economic Times) — 3rd consecutive year
B53: Governance Rating | C53: 'Good' rating in Indian Corporate Governance Scorecard 2024 by IIAS | 100% Board Committees chaired by Independent Directors
B54: ESG Awards FY25 | C54: Golden Peacock Award 2024 (ESG excellence) | Arogya World Healthy Workplace Gold Award | 5-Star rating for RKBA Limestone Mine | ICC International OHS Platinum Award (Nalagarh, Sankrail, Bhatapara) | CII Energy Efficient Award | IconSWM-CE Excellence Award
B55: Product Certifications | C55: Ambuja Cement, Ambuja Plus, Ambuja Compocem & Ambuja Kawach enlisted in GRIHA Green Product Catalogue
B56: ◆ STRATEGIC PRIORITIES
B57: Capacity Leadership | C57: Scale to 140 MTPA by FY2027-28 via organic (greenfield/brownfield) + inorganic (acquisitions) growth | D57: Cost Leadership | E57: Becoming most cost-efficient cement manufacturer; streamlining logistics, optimising dispatch, self-reliant coal/limestone
B58: Digital Transformation | C58: AI, IoT, automation across value chain; NexGen Sales & Reward Platform; Plants of the Future programme | D58: Sustainability & ESG | E58: 60% green power by FY2027-28; Net Zero by 2050; zero-carbon RDH™ technology with Finland's Coolbrook

Sheet Promoter
A1: Ambuja Cements Limited — Promoter Shareholding Pattern (Q4 FY2024-25)
A2: Category of Shareholder | B2: No. of Shareholders | C2: Shares Held | D2: Stake %
A3: A1) Indian Promoters
A4: Any Other (specify) | B4: 1 | C4: 87,00,000 | D4: 0.35%
A5: Adani Enterprises Limited | B5: 1 | C5: 87,00,000 | D5: 0.35%
A6: Sub Total A1 — Indian | B6: 1 | C6: 87,00,000 | D6: 0.35%
A7: A2) Foreign Promoters
A8: Any Other (specify) | B8: 3 | C8: 1,66,33,81,052 | D8: 66.98%
A9: Endeavour Trade and Investment Limited | B9: 1 | C9: 7,02,442 | D9: 0.03%
A10: Harmonia Trade and Investment Ltd | B10: 1 | C10: 47,74,78,249 | D10: 19.23%
A11: Holderind Investments Ltd | B11: 1 | C11: 1,18,52,00,361 | D11: 47.72%
A12: Sub Total A2 — Foreign | B12: 3 | C12: 1,66,33,81,052 | D12: 66.98%
A13: TOTAL PROMOTER (A = A1 + A2) | B13: 4 | C13: 1,67,20,81,052 | D13: 67.33%

Sheet Public
A1: Ambuja Cements Limited — Public Shareholding Detail (Q4 FY2024-25)
A2: Category of Shareholder | B2: No. of Shareholders | C2: Shares Held | D2: Stake %
A3: B1) Domestic Institutional Investors (DII)
A4: Mutual Funds | B4: 53 | C4: 21,68,21,219 | D4: 8.73%
A5: Mirae Asset Large Cap Fund | B5: 1 | C5: 3,29,82,563 | D5: 1.33%
A6: Mirae Asset Large Cap Fund (SIP Tranche) | B6: 1 | C6: 4,34,16,130 | D6: 1.75%
A7: HDFC Large Cap Fund | B7: 1 | C7: 5,15,40,443 | D7: 2.08%
A8: Alternate Investment Funds | B8: 12 | C8: 8,46,032 | D8: 0.03%
A9: Banks | B9: 17 | C9: 1,27,315 | D9: 0.01%
A10: Insurance Companies | B10: 21 | C10: 21,96,57,802 | D10: 8.84%
A11: Life Insurance Corporation of India | B11: 1 | C11: 18,07,93,420 | D11: 7.28%
A12: Provident Funds / Pension Funds | B12: 1 | C12: 4,99,24,778 | D12: 2.01%
A13: NPS Trust — SBI Pension Fund (State Govt) | B13: 1 | C13: 4,99,24,778 | D13: 2.01%
A14: Sovereign Wealth Funds | B14: 2 | C14: 51,53,529 | D14: 0.21%
A15: NBFCs (RBI Registered) | B15: 8 | C15: 67,668 | D15: 0.00%
... A17: Sub Total B1 — DII | B17: 119 | C17: 49,26,19,343 | D17: 19.84%
A18: B2) Foreign Institutional Investors (FII)
A19: FPI — Category I | B19: 455 | C19: 14,00,84,991 | D19: 5.64%
A20: FPI — Category II | B20: 27 | C20: 46,63,938 | D20: 0.19%
A21: Foreign Institutional Investors (Other) | B21: 9 | C21: 61,275 | D21: 0.00%
A22: Sub Total B2 — FII | B22: 491 | C22: 14,48,10,204 | D22: 5.83%
A23: B3) Central Government / President of India
A24: Central Government / President of India | B24: 1 | C24: 37,747 | D24: 0.00%
A25: Sub Total B3 | B25: 1 | C25: 37,747 | D25: 0.00%
A26: B4) Non-Institutions (Retail & Others)
A27: IEPF | B27: 1 | C27: 50,34,848 | D27: 0.20%
A28: Resident Individuals (up to ₹2 lakh capital) | B28: 5,91,674 | C28: 11,36,89,930 | D28: 4.58%
A29: Resident Individuals (above ₹2 lakh capital) | B29: 39 | C29: 2,28,56,436 | D29: 0.92%
A30: Non-Resident Indians (NRIs) | B30: 12,527 | C30: 1,12,51,148 | D30: 0.45%
A31: Bodies Corporate | B31: 1,771 | C31: 1,64,41,809 | D31: 0.66%
A32: Any Other (Trusts, Clearing Members, HUF etc.) | B32: 6,788 | C32: 46,36,597 | D32: 0.19%
A33: Foreign Nationals | B33: 5 | C33: 18,459 | D33: 0.00%
A34: Sub Total B4 — Retail & Others | B34: 6,12,805 | C34: 17,39,29,227 | D34: 7.00%
A35: TOTAL PUBLIC (B = B1 + B2 + B3 + B4) | B35: 6,13,416 | C35: 81,13,96,521 | D35: 32.67%

Sheet Consolidated P&L
A1: AMBUJA CEMENTS LIMITED
A2: Consolidated Statement of Profit and Loss
A3: (₹ in Crore)
A4: Particulars | B4: Dec 31, 2019 | C4: Dec 31, 2020 | D4: Dec 31, 2021 | E4: Mar 31, 2023 (15 months) | F4: Mar 31, 2024 | G4: Mar 31, 2025
A5: INCOME
A6: a) Revenue from operations | B6: 27103.55 | C6: 24516.17 | D6: 28965.46 | E6: 38937.03 | F6: 33159.64 | G6: 33697.7
A7: b) Government grants incl. duty credits | B7: - | C7: - | D7: - | E7: - | F7: - | G7: 1347.06
A8: c) Other income | B8: 580.74 | C8: 449.59 | D8: 352.44 | E8: 737.71 | F8: 1166.4 | G8: 2654.25
A9: Total Income | B9: 27684.29 | C9: 24965.76 | D9: 29317.9 | E9: 39674.74 | F9: 34326.04 | G9: 37699.01
A10: EXPENSES
A11: a) Cost of materials consumed | B11: 3231.22 | C11: 2532.87 | D11: 3183.41 | E11: 4749.65 | F11: 4321.96 | G11: 5708.07
A12: b) Purchase of stock-in-trade | B12: 308.82 | C12: 334.92 | D12: 309.21 | E12: 481.12 | F12: 576.83 | G12: 763.66
A13: c) Changes in inventories of FG, WIP | B13: 143.64 | C13: 256.45 | D13: -530.34 | E13: -119.86 | F13: 23.99 | G13: 55.69
A14: d) Employee benefits expense | B14: 1570.75 | C14: 1540.4 | D14: 1529.15 | E14: 1856.53 | F14: 1352.79 | G14: 1403.41
A15: e) Finance costs | B15: 169.87 | C15: 140.22 | D15: 145.66 | E15: 194.9 | F15: 276.38 | G15: 215.94
A16: f) Depreciation and amortisation expense | B16: 1152.52 | C16: 1161.78 | D16: 1152.49 | E16: 1644.67 | F16: 1623.38 | G16: 2478.34
A17: g) Power and fuel | B17: 5722.19 | C17: 4827.64 | D17: 6787.52 | E17: 11761.9 | F17: 8109.31 | G17: 8347.84
A18: h) Freight and forwarding expense | B18: 7127.97 | C18: 6271.54 | D18: 7132.9 | E18: 9523.72 | F18: 8000.64 | G18: 8301.19
A19: i) Other expenses | B19: 4410.44 | C19: 3768.92 | D19: 4387.84 | E19: 5608.5 | F19: 4388.97 | G19: 4515.13
A20: Sub-total | B20: 23837.42 | C20: 20834.74 | D20: 24097.84 | E20: 35701.13 | F20: 28674.25 | G20: 31789.27
A21: j) Self/Captive consumption of cement | B21: -8.47 | C21: -22.14 | D21: -44.63 | E21: -46.9 | F21: -14.36 | G21: -20.88
A22: Total Expenses | B22: 23828.95 | C22: 20812.6 | D22: 24053.21 | E22: 35654.23 | F22: 28659.89 | G22: 31768.39
... A25: 5 Profit before exceptional items and tax (3+4) | B25: 3875.31 | C25: 4167.6 | D25: 5284.92 | E25: 4048.53 | F25: 5689.05 | G25: 5943.84
A26: 6 Exceptional items Expense / (Income) | B26: - | C26: 176.01 | D26: 120.45 | E26: 319.04 | F26: -211.57 | G26: 21.47
A27: 7 Profit before tax (5-6) | B27: 3875.31 | C27: 3991.59 | D27: 5164.47 | E27: 3729.49 | F27: 5900.62 | G27: 5922.37
A28: TAX EXPENSE
A29: a) Current tax (net) | B29: 1264.7 | C29: 1200.42 | D29: 1326.98 | E29: 770.6 | F29: 1260.11 | G29: 1274.53
A30: b) Tax adjustments - earlier years (net) | B30: - | C30: - | D30: - | E30: - | F30: -266.89 | G30: -769.87
A31: c) Deferred tax charge / (credit) | B31: -172.55 | C31: -315.67 | D31: 126.45 | E31: -65.49 | F31: 169.39 | G31: 259.3
A32: Total tax expense (8) | B32: 1092.15 | C32: 884.75 | D32: 1453.43 | E32: 705.11 | F32: 1162.61 | G32: 763.96
A33: 9 Profit after tax / for the year (7-8) | B33: 2783.16 | C33: 3106.84 | D33: 3711.04 | E33: 3024.38 | F33: 4738.01 | G33: 5158.41
A34: OTHER COMPREHENSIVE INCOME
A35: a) Remeasurement gains/(losses) on defined benefit plans | B35: -82.78 | C35: -15.39 | D35: 14.86 | E35: 38.61 | F35: 40.29 | G35: -52.29
A36: b) Share of remeasurement - JV/associates | B36: 0.18 | C36: -0.05 | D36: - | E36: -0.07 | F36: -0.17 | G36: -0.02
A37: Income tax effect on above | B37: 28.92 | C37: -6.18 | D37: -3.75 | E37: -9.67 | F37: -10.15 | G37: 12.43
A38: Foreign currency translation reserve | B38: - | C38: - | D38: - | E38: - | F38: - | G38: 0.25
A39: Total OCI (net of tax) (10) | B39: -53.68 | C39: -21.62 | D39: 11.11 | E39: 28.87 | F39: 29.97 | G39: -39.63
A40: 11 Total comprehensive income for the year (9+10) | B40: 2729.48 | C40: 3085.22 | D40: 3722.15 | E40: 3053.25 | F40: 4767.98 | G40: 5118.78
A41: ATTRIBUTABLE TO
A42: 12 Profit for the year attributable to:
A43: - Owners of the Company | B43: 2095 | C43: 2365.44 | D43: 2780.38 | E43: 2583.4 | F43: 3576.79 | G43: 4167.43
A44: - Non-controlling interest | B44: 688.16 | C44: 741.4 | D44: 930.66 | E44: 440.98 | F44: 1161.22 | G44: 990.98
A45: 13 Other comprehensive income attributable to:
A46: - Owners of the Company | B46: -29.09 | C46: -14.34 | D46: 8.4 | E46: 13.41 | F46: 15.52 | G46: -22.32
A47: - Non-controlling interest | B47: -24.59 | C47: -7.28 | D47: 2.71 | E47: 15.46 | F47: 14.45 | G47: -17.31
A48: 14 Total comprehensive income attributable to:
A49: - Owners of the Company | B49: 2065.91 | C49: 2351.1 | D49: 2788.78 | E49: 2596.81 | F49: 3592.31 | G49: 4145.11
A50: - Non-controlling interest | B50: 663.57 | C50: 734.12 | D50: 933.37 | E50: 456.44 | F50: 1175.67 | G50: 973.67
A51: EARNINGS PER SHARE (₹2 face value)
A52: 15 Basic EPS (₹) | B52: 10.55 | C52: 11.91 | D52: 14 | E52: 13.01 | F52: 17.99 | G52: 17
A53: Diluted EPS (₹) | B53: 10.55 | C53: 11.91 | D53: 14 | E53: 12.64 | F53: 16.67 | G53: 16.96
A55: Source: Ambuja Cements Limited Annual Reports (2020, 2021, 2022-23, 2023-24, 2024-25)
A56: Note: Dec 2019/2020/2021 = calendar year-end | Mar 2023 = 15-month period (Jan 2022–Mar 2023) | Mar 2024 = as originally reported in 2023-24 Annual Report

Sheet DCF Valuation
C1: 1 | D1: 2 | E1: 3 | F1: 4 | G1: 5 | H1: 6 | I1: 7 | J1: 8 | K1: 9 | L1: 10
A2: INR Cr | B2: LTM | C2: Y1E | D2: Y2E | E2: Y3E | F2: Y4E | G2: Y5E | H2: Y6E | I2: Y7E | J2: Y8E | K2: Y9E | L2: Y10E | N2: Terminal Year | P2: Terminal growth rate % | Q2: 0.055
A3: Sales | B3: ='Growth Scenario'!B18 -> 33697.7 | C3: ='Growth Scenario'!C18 -> 35911.189 | D3: ='Growth Scenario'!D18 -> 38238.101 | E3: ='Growth Scenario'!E18 -> 40681.741 | F3: ='Growth Scenario'!F18 -> 43245.323 | G3: ='Growth Scenario'!G18 -> 45931.946 | H3: ='Growth Scenario'!H18 -> 48744.58 | I3: ='Growth Scenario'!I18 -> 51686.043 | ... L3: ='Growth Scenario'!L18 -> 61308.959 | N3: =L3*(1+$Q$2) -> 64680.952 | P3: Cost of Capital % | Q3: =Wacc!E27 -> 0.13506582
A4: Sales Growth | C4: ='Growth Scenario'!C19 -> 0.065686654 | D4: ='Growth Scenario'!D19 -> 0.064796283 | E4: ='Growth Scenario'!E19 -> 0.063905911 | F4: ='Growth Scenario'!F19 -> 0.063015539 | G4: ='Growth Scenario'!G19 -> 0.062125167 | H4: ='Growth Scenario'!H19 -> 0.061234796 | I4: ='Growth Scenario'!I19 -> 0.060344424 | J4: ='Growth Scenario'!J19 -> 0.059454052 | ... L4: ='Growth Scenario'!L19 -> 0.057673309 | N4: =$Q$2 -> 0.055 | P4: Terminal reinvestment rate % | Q4: =Q2*Q3 -> 0.0074286202
A5: EBIT | C5: =C3*C6 -> 5156.8963 | D5: =D3*D6 -> 5491.044 | E5: =E3*E6 -> 5841.9541 | F5: =F3*F6 -> 6210.088 | G5: =G3*G6 -> 6595.8908 | H5: =H3*H6 -> 6999.7888 | I5: =I3*I6 -> 7422.187 | J5: =J3*J6 -> 7863.4661 | ... L5: =L3*L6 -> 8804.0511 | N5: =N6*N3 -> 9288.2739
A6: EBIT Margin % | C6: =MEDIAN(Assumptions!B29:F29) -> 0.14360138 | D6: =C6 -> 0.14360138 | E6: =D6 -> 0.14360138 | F6: =E6 -> 0.14360138 | G6: =F6 -> 0.14360138 | H6: =G6 -> 0.14360138 | I6: =H6 -> 0.14360138 | J6: =I6 -> 0.14360138 | K6: =J6 -> 0.14360138 | L6: =K6 -> 0.14360138 | N6: =L6 -> 0.14360138 | P6: Enterprise value = Equity Value + Minority interest
A7: Less: Tax on EBIT | C7: =Assumptions!$B$35*'DCF Valuation'!C5 -> 1289.2241 | D7: =Assumptions!$B$35*'DCF Valuation'!D5 -> 1372.761 | E7: =Assumptions!$B$35*'DCF Valuation'!E5 -> 1460.4885 | F7: =Assumptions!$B$35*'DCF Valuation'!F5 -> 1552.522 | G7: =Assumptions!$B$35*'DCF Valuation'!G5 -> 1648.9727 | H7: =Assumptions!$B$35*'DCF Valuation'!H5 -> 1749.9472 | I7: =Assumptions!$B$35*'DCF Valuation'!I5 -> 1855.5468 | J7: =Assumptions!$B$35*'DCF Valuation'!J5 -> 1965.8665 | ... L7: =Assumptions!$B$35*'DCF Valuation'!L5 -> 2201.0128 | N7: =Assumptions!$B$35*N5 -> 2322.0685
A8: EBIT(1-T) | C8: =C5-C7 -> 3867.6722 | D8: =D5-D7 -> 4118.283 | E8: =E5-E7 -> 4381.4656 | F8: =F5-F7 -> 4657.566 | G8: =G5-G7 -> 4946.9181 | H8: =H5-H7 -> 5249.8416 | I8: =I5-I7 -> 5566.6403 | J8: =J5-J7 -> 5897.5996 | ... L8: =L5-L7 -> 6603.0383 | N8: =N5-N7 -> 6966.2054
A9: Less: Net Capital Expenditure | C9: =C3*'Fixed Asset Scheduled'!$B$11 -> 2202.5304 | D9: =D3*'Fixed Asset Scheduled'!$B$11 -> 2345.2461 | E9: =E3*'Fixed Asset Scheduled'!$B$11 -> 2495.1212 | F9: =F3*'Fixed Asset Scheduled'!$B$11 -> 2652.3526 | G9: =G3*'Fixed Asset Scheduled'!$B$11 -> 2817.1305 | H9: =H3*'Fixed Asset Scheduled'!$B$11 -> 2989.6369 | I9: =I3*'Fixed Asset Scheduled'!$B$11 -> 3170.0448 | J9: =J3*'Fixed Asset Scheduled'!$B$11 -> 3358.5168 | ... L9: =L3*'Fixed Asset Scheduled'!$B$11 -> 3760.2443
A10: Non Cash Working Capital | B10: ='Change in working capital'!F5 -> 3078.85 | C10: ='Change in working capital'!$B$9*'DCF Valuation'!C3 -> 1790.424 | D10: ='Change in working capital'!$B$9*'DCF Valuation'!D3 -> 1906.4368 | E10: ='Change in working capital'!$B$9*'DCF Valuation'!E3 -> 2028.2694 | F10: ='Change in working capital'!$B$9*'DCF Valuation'!F3 -> 2156.0819 | G10: ='Change in working capital'!$B$9*'DCF Valuation'!G3 -> 2290.0288 | H10: ='Change in working capital'!$B$9*'DCF Valuation'!H3 -> 2430.2582 | I10: ='Change in working capital'!$B$9*'DCF Valuation'!I3 -> 2576.9108 | J10: ='Change in working capital'!$B$9*'DCF Valuation'!J3 -> 2730.1186 | ... L10: ='Change in working capital'!$B$9*'DCF Valuation'!L3 -> 3056.6805
A11: Less: Change in Working Capital | C11: =C10-B10 -> -1288.426 | D11: =D10-C10 -> 116.01282 | E11: =E10-D10 -> 121.83258 | F11: =F10-E10 -> 127.81249 | G11: =G10-F10 -> 133.94695 | H11: =H10-G10 -> 140.22945 | I11: =I10-H10 -> 146.65253 | J11: =J10-I10 -> 153.20779 | ... L11: =L10-K10 -> 166.67611
A12: Reinvestment | C12: =C9+C11 -> 914.10433 | D12: =D9+D11 -> 2461.259 | E12: =E9+E11 -> 2616.9538 | F12: =F9+F11 -> 2780.1651 | G12: =G9+G11 -> 2951.0774 | H12: =H9+H11 -> 3129.8663 | I12: =I9+I11 -> 3316.6973 | J12: =J9+J11 -> 3511.7246 | ... L12: =L9+L11 -> 3926.9204 | N12: =N8*N14 -> 51.749294
A13: Free Cash Flow To Firm (FCFF) | C13: =C8-C12 -> 2953.5679 | D13: =D8-(D12) -> 1657.024 | E13: =E8-(E12) -> 1764.5118 | F13: =F8-(F12) -> 1877.4009 | G13: =G8-(G12) -> 1995.8406 | H13: =H8-(H12) -> 2119.9753 | I13: =I8-(I12) -> 2249.9429 | J13: =J8-(J12) -> 2385.875 | K13: =K8-(K12) -> 2527.895 | L13: =L8-(L12) -> 2676.1179 | N13: =N8-N12 -> 6914.4561
A14: Implied Reinvestment rate % | C14: =C13/C8 -> 0.76365517 | D14: =D13/D8 -> 0.40235798 | E14: =E13/E8 -> 0.40272182 | F14: =F13/F8 -> 0.40308627 | G14: =G13/G8 -> 0.40345132 | H14: =H13/H8 -> 0.40381699 | I14: =I13/I8 -> 0.40418328 | J14: =J13/J8 -> 0.40455018 | ... L14: =L13/L8 -> 0.40528583 | N14: =$Q$4 -> 0.0074286202
A16: Terminal Value | L16: =N13/($Q$3-$Q$2) -> 86359.647
A18: Present Value Interest Factor(PVIF) | C18: =1/(1+$Q$3)^C1 -> 0.88100618 | D18: =1/(1+$Q$3)^D1 -> 0.77617188 | E18: =1/(1+$Q$3)^E1 -> 0.68381222 | F18: =1/(1+$Q$3)^F1 -> 0.60244279 | G18: =1/(1+$Q$3)^G1 -> 0.53075582 | H18: =1/(1+$Q$3)^H1 -> 0.46759916 | I18: =1/(1+$Q$3)^I1 -> 0.41195774 | J18: =1/(1+$Q$3)^J1 -> 0.36293732 | ... L18: =1/(1+$Q$3)^L1 -> 0.28170174
A20: Present value of FCFF | C20: =SUMPRODUCT(C18:L18,C13:L13) -> 11631.437
A21: Present value of Terminal value | C21: =L16*L18 -> 24327.663
A23: Value of operating assets | C23: =C20+C21 -> 35959.1
A24: Add: Cash | C24: ='Consolidated Balance sheet'!G26+'Consolidated Balance sheet'!G27 -> 6172.16
A25: Less: Debt | C25: ='Consolidated Balance sheet'!G47+'Consolidated Balance sheet'!G56+'Consolidated Balance sheet'!G48+'Consolidated Balance sheet'!G57 -> 788.5
A26: Less: Minority Interest (NCI - Book Value) | C26: ='Consolidated Balance sheet'!G42 -> 10368.17
A27: Equity Value | C27: =C23+C24-C25-C26 -> 30974.59
A29: No. of Shares outstanding (Cr) | C29: ='Consolidated Balance sheet'!G38/2 -> 246.31
A30: intrinsic value per share | C30: =C27/C29 -> 125.7545
A32: Note: TV uses Terminal FCFF (reinvestment-adjusted). Cash includes bank balances. Debt includes lease liabilities. NCI at book value.

Sheet Consolidated Balance sheet
A1: AMBUJA CEMENTS LIMITED
A2: Consolidated Balance Sheet
A3: Particulars | B3: Dec 31, 2019 | C3: Dec 31, 2020 | D3: Dec 31, 2021 | E3: Mar 31, 2023 | F3: Mar 31, 2024 | G3: Mar 31, 2025
A4: ASSETS
A5: 1 Non-current assets
A6: a) Property, plant and equipment | B6: 12605.99 | C6: 11885.36 | D6: 13661.89 | E6: 14729.35 | F6: 19956.67 | G6: 24656.29
A7: b) Right-of-use assets | B7: - | C7: 503.87 | D7: 497.87 | E7: 588.15 | F7: 758.34 | G7: 1464.76
A8: c) Capital work-in-progress | B8: 1554.43 | C8: 2421.85 | D8: 2196.38 | E8: 2525.87 | F8: 2658.45 | G8: 9820.4
A9: d) Goodwill | B9: 7881.49 | C9: 7876.11 | D9: 7869.69 | E9: 7869.69 | F9: 8219.27 | G9: 10856.07
A10: e) Other intangible assets | B10: 213.86 | C10: 220.63 | D10: 224.11 | E10: 364.3 | F10: 3454.19 | G10: 5600.63
A11: Other intangible assets under development | B11: - | C11: - | D11: - | E11: - | F11: - | G11: 65.31
A12: f) Investments in associates and joint ventures | B12: 145.87 | C12: 154.6 | D12: 170.51 | E12: 186.05 | F12: 62.26 | G12: 60.39
A13: g) Financial assets | B13: - | C13: - | D13: - | E13: - | F13: - | G13: -
A14: i) Investments | B14: 3.7 | C14: 12.7 | D14: 27.6 | E14: 27.6 | F14: 27.6 | G14: 28.96
A15: ii) Loans | B15: 208.63 | C15: 212.28 | D15: 11.56 | E15: 9.89 | F15: 11.58 | G15: 4.95
A16: iii) Other financial assets | B16: 841.68 | C16: 1184.09 | D16: 1255.12 | E16: 3133.72 | F16: 1167.39 | G16: 3721.7
A17: h) Non-current tax assets (net) | B17: 1041.99 | C17: 1100.29 | D17: 1125.86 | E17: 1128.08 | F17: 1250.36 | G17: 1748.48
A18: i) Deferred tax assets (net) | B18: 4.16 | C18: 2.91 | D18: 2.91 | E18: - | F18: 36.94 | G18: 4.37
A19: j) Other non-current assets | B19: 1361.53 | C19: 1341.18 | D19: 1141.36 | E19: 1909.39 | F19: 2842.6 | G19: 3195.95
A20: Total - Non-current assets | B20: 25863.33 | C20: 26915.87 | D20: 28184.86 | E20: 32472.09 | F20: 40445.65 | G20: 61228.26
A21: 2 Current assets
A22: a) Inventories | B22: 2096.5 | C22: 1648.58 | D22: 2738.04 | E22: 3272.79 | F22: 3608.55 | G22: 4248.01
A23: b) Financial assets | B23: - | C23: - | D23: - | E23: - | F23: - | G23: -
A24: i) Investments | B24: - | C24: - | D24: - | E24: - | F24: 758.69 | G24: 1822.16
A25: ii) Trade receivables | B25: 1068.56 | C25: 561.13 | D25: 645.83 | E25: 1154.36 | F25: 1213.14 | G25: 1590.3
A26: iii) Cash and cash equivalents | B26: 9011.88 | C26: 8571.56 | D26: 11358.49 | E26: 543.87 | F26: 3007.1 | G26: 5043.32
A27: iv) Bank balances other than cash and cash equivalents | B27: 342.67 | C27: 364.07 | D27: 335.8 | E27: 2417.17 | F27: 8061.77 | G27: 1128.84
A28: v) Loans | B28: 32.28 | C28: 62.06 | D28: 9.91 | E28: 8.61 | F28: 6.24 | G28: 7.7
A29: vi) Other financial assets | B29: 496.62 | C29: 346.35 | D29: 474.25 | E29: 7901.58 | F29: 5715 | G29: 1888.24
A30: c) Current tax assets (net) | B30: - | C30: 71.26 | D30: - | E30: - | F30: - | G30: 16.18
A31: d) Other current assets | B31: 1235.25 | C31: 1153.69 | D31: 1434.66 | E31: 3948.86 | F31: 2459.74 | G31: 3965.63
A32: Sub-total | B32: 14283.76 | C32: 12778.7 | D32: 16996.98 | E32: 19247.24 | F32: 24830.23 | G32: 19710.38
A33: e) Non-current assets classified as held for sale | B33: 35.25 | C33: 26.13 | D33: 25.44 | E33: 2.13 | F33: 21.93 | G33: 6.77
A34: Total - Current assets | B34: 14319.01 | C34: 12804.83 | D34: 17022.42 | E34: 19249.37 | F34: 24852.16 | G34: 19717.15
A35: TOTAL - ASSETS | B35: 40182.34 | C35: 39720.7 | D35: 45207.28 | E35: 51721.46 | F35: 65297.81 | G35: 80945.41
A36: EQUITY AND LIABILITIES
A37: Equity | B37: - | C37: - | D37: - | E37: - | F37: - | G37: -
A38: a) Equity share capital | B38: 397.13 | C38: 397.13 | D38: 397.13 | E38: 397.13 | F38: 439.54 | G38: 492.62
A39: b) Other equity | B39: 23680.86 | C39: 22360.47 | D39: 24956.61 | E39: 26301.04 | F39: 38235.87 | G39: 52950.63
A40: c) Money received against share warrants | B40: - | C40: - | D40: - | E40: 5000.03 | F40: 2779.65 | G40: -
A41: Equity attributable to owners of the Company | B41: 24077.99 | C41: 22757.6 | D41: 25353.74 | E41: 31698.2 | F41: 41455.06 | G41: 53443.25
A42: d) Non-controlling interest | B42: 5736.76 | C42: 6340.89 | D42: 7145.03 | E42: 7058.35 | F42: 9390.84 | G42: 10368.17
A43: Total Equity | B43: 29814.75 | C43: 29098.49 | D43: 32498.77 | E43: 38756.55 | F43: 50845.9 | G43: 63811.42
A44: Liabilities | B44: - | C44: - | D44: - | E44: - | F44: - | G44: -
A45: 1 Non-current liabilities
A46: a) Financial liabilities | B46: - | C46: - | D46: - | E46: - | F46: - | G46: -
A47: i) Borrowings | B47: 35.28 | C47: 43.6 | D47: 43.5 | E47: 34.22 | F47: 18.91 | G47: 14.39
A48: ii) Lease liabilities | B48: - | C48: 380.75 | D48: 362.52 | E48: 414.5 | F48: 499.05 | G48: 457.54
A49: iii) Other financial liabilities | B49: 0.62 | C49: 0.13 | D49: 0.13 | E49: - | F49: - | G49: -
A50: b) Provisions | B50: 288.82 | C50: 271.41 | D50: 281.54 | E50: 264.88 | F50: 255.97 | G50: 254.08
A51: c) Deferred tax liabilities (net) | B51: 936.73 | C51: 626 | D51: 756.19 | E51: 700.37 | F51: 1549.1 | G51: 2407.57
A52: d) Other non-current liabilities | B52: 35.83 | C52: 40.05 | D52: 36.74 | E52: 37.27 | F52: - | G52: 155.15
A53: Total - Non-current liabilities | B53: 1297.28 | C53: 1361.81 | D53: 1480.62 | E53: 1451.24 | F53: 2323.03 | G53: 3288.73
A54: 2 Current liabilities
A55: a) Financial liabilities | B55: - | C55: - | D55: - | E55: - | F55: - | G55: -
A56: i) Borrowings | B56: - | C56: - | D56: - | E56: 13.49 | F56: 17.87 | G56: 12.43
A57: ia) Lease liabilities | B57: - | C57: 46.38 | D57: 67.11 | E57: 60.52 | F57: 163.18 | G57: 304.14
A58: ii) Trade payables | B58: - | C58: - | D58: - | E58: - | F58: - | G58: -
A59: - Micro and small enterprises | B59: 12.37 | C59: 8.76 | D59: 34.95 | E59: 51.22 | F59: 717.42 | G59: 472.59
A60: - Others | B60: 2320.51 | C60: 2204.65 | D60: 2877.87 | E60: 2722.69 | F60: 2391.33 | G60: 2286.87
A61: iii) Other financial liabilities | B61: 1719.63 | C61: 1794.06 | D61: 2008.86 | E61: 2121.13 | F61: 2389.52 | G61: 4935.99
A62: b) Other current liabilities | B62: 3658.72 | C62: 3910.9 | D62: 4305.87 | E62: 4732.7 | F62: 3751.65 | G62: 3057.19
A63: c) Provisions | B63: 109.89 | C63: 21.14 | D63: 24.64 | E63: 14.64 | F63: 42.97 | G63: 55.09
A64: d) Current tax liabilities (net) | B64: 1249.19 | C64: 1320.89 | D64: 1908.59 | E64: 1797.28 | F64: 2654.94 | G64: 2720.96
A65: Total - Current liabilities | B65: 9070.31 | C65: 9260.4 | D65: 11227.89 | E65: 11513.67 | F65: 12128.88 | G65: 13845.26
A66: Total Liabilities | B66: 10367.59 | C66: 10622.21 | D66: 12708.51 | E66: 12964.91 | F66: 14451.91 | G66: 17133.99
A67: TOTAL - EQUITY AND LIABILITIES | B67: 40182.34 | C67: 39720.7 | D67: 45207.28 | E67: 51721.46 | F67: 65297.81 | G67: 80945.41
A68: Source: Ambuja Cements Limited Annual Reports (2020, 2021, 2022-23, 2023-24, 2024-25)
A69: Note: FY2019 figures from 2020 Annual Report | FY Dec 2021 restated per 2022-23 report | Mar 2023 = 15-month period (Jan 2022 - Mar 2023)

Sheet Consolidated Cash Flow
A1: AMBUJA CEMENTS LIMITED
A2: Consolidated Statement of Cash Flows
A3: (₹ in Crore)
A4: Particulars | B4: Dec 31, 2020 | C4: Dec 31, 2021 | D4: Mar 31, 2023 (15 months) | E4: Mar 31, 2024 | F4: Mar 31, 2025
A5: A) CASH FLOWS FROM OPERATING ACTIVITIES
A6: Profit before tax | B6: 3991.59 | C6: 5164.47 | D6: 3729.49 | E6: 5900.62 | F6: 5922.37
A7: Adjustments to reconcile profit before tax to net cash flows: | B7: - | C7: - | D7: - | E7: - | F7: -
A8: Depreciation and amortisation expense | B8: 1161.78 | C8: 1152.49 | D8: 1644.67 | E8: 1623.38 | F8: 2478.34
A9: Exceptional item / Provision for restructuring cost | B9: 176.01 | C9: 113.11 | D9: 147.13 | E9: - | F9: -
A10: Exceptional Items - Expense / (Income) | B10: - | C10: - | D10: - | E10: -211.57 | F10: 21.47
A11: Expected credit loss on non current financial assets | B11: 128.92 | C11: - | D11: - | E11: - | F11: -
A12: (Gain) / Loss on PP&E sold, discarded and written off (net) | B12: 32.86 | C12: 25.27 | D12: -96.09 | E12: -115.81 | F12: -35.79
A13: Loss on buy back of shares of joint venture | B13: 0.26 | C13: - | D13: - | E13: - | F13: -
A14: Gain on sale of current financial assets measured at FVTPL | B14: -26.65 | C14: -17.8 | D14: -52.25 | E14: -46.31 | F14: -116.72
A15: Gain on sale of investment in subsidiary company | B15: -12.91 | C15: - | D15: -16.52 | E15: - | F15: -
A16: Net gain on fair valuation of liquid mutual fund measured at FVTPL | B16: -0.47 | C16: -0.37 | D16: -0.21 | E16: -16.76 | F16: -27.19
A17: Finance costs | B17: 140.22 | C17: 142.32 | D17: 190.54 | E17: 276.38 | F17: 215.94
A18: Interest income | B18: -401.42 | C18: -302.3 | D18: -538.26 | E18: -936.9 | F18: -2433.91
A19: Provision for slow and non moving spares (net) | B19: 25.39 | C19: 29.85 | D19: -2.57 | E19: -6.05 | F19: 17.56
A20: Impairment loss / (Reversal) on trade receivable (net) | B20: 51.48 | C20: -8.79 | D20: 7.22 | E20: 18.8 | F20: 9.37
A21: Discounting income on interest free loan / Unwinding of discounting charge | B21: -3.25 | C21: 3.34 | D21: - | E21: - | F21: -
A22: Unrealised exchange (gain) / loss (net) | B22: 8.29 | C22: 3.36 | D22: 37.44 | E22: 2.47 | F22: 6.16
A23: Fair value movement in derivative instruments | B23: 1.3 | C23: 5.92 | D23: -7.31 | E23: 5.46 | F23: 0.47
A24: Interest on income tax written back | B24: -5.77 | C24: - | D24: - | E24: - | F24: -
A25: Provisions no longer required written back | B25: -11.86 | C25: -18.53 | D25: -46.84 | E25: -110.01 | F25: -
A26: Compensation Expenses under Employees Stock Options Scheme | B26: 3.66 | C26: 8.01 | D26: 2.94 | E26: - | F26: -
A27: Inventories written off | B27: 1.66 | C27: 2.4 | D27: - | E27: - | F27: -
A28: Impairment of goodwill in subsidiary company | B28: - | C28: 6.42 | D28: - | E28: - | F28: -
A29: Provisions / (Reversal) for doubtful advances (net) | B29: - | C29: -0.13 | D29: - | E29: - | F29: -
A30: Bad debts and claims written off / written back (net) | B30: 1.07 | C30: - | D30: - | E30: - | F30: -
A31: Unrealised share of profit in associates and joint ventures | B31: -14.44 | C31: -20.23 | D31: -28.02 | E31: -22.9 | F31: -13.22
A32: Other non cash items | B32: -2.41 | C32: -0.63 | D32: -25.04 | E32: 6.49 | F32: -26.1
A33: Operating profit before working capital changes | B33: 5245.31 | C33: 6288.18 | D33: 4946.32 | E33: 6367.29 | F33: 6018.75
A34: Changes in Working Capital | B34: - | C34: - | D34: - | E34: - | F34: -
A35: Decrease / (Increase) in Trade receivables, loans & advances and other assets | B35: 244.5 | C35: -268.03 | D35: - | E35: - | F35: -
A36: Decrease / (Increase) in Inventories | B36: 420.49 | C36: -1121.71 | D36: - | E36: - | F36: -
A37: (Increase) / Decrease in Inventories | B37: - | C37: - | D37: -466.99 | E37: -228.29 | F37: -512.89
A38: (Increase) / Decrease in Trade Receivables | B38: - | C38: - | D38: -547.07 | E38: 24.35 | F38: -382.32
A39: (Increase) / Decrease in Other Financial Assets | B39: - | C39: - | D39: - | E39: - | F39: -305.02
A40: (Increase) / Decrease in Other Assets | B40: - | C40: - | D40: -2720.44 | E40: 975.24 | F40: -995.13
A41: Increase / (Decrease) in Trade payables, other liabilities and provisions | B41: 92.24 | C41: 1058.33 | D41: - | E41: - | F41: -
A42: Increase / (Decrease) in Trade Payables | B42: - | C42: - | D42: -27.76 | E42: 102.98 | F42: -576.29
A43: Increase / (Decrease) in Provisions | B43: - | C43: - | D43: -1.76 | E43: 45.83 | F43: -70.04
A44: Increase / (Decrease) in Other Financial Liabilities | B44: - | C44: - | D44: - | E44: - | F44: -506.44
A45: Increase / (Decrease) in Other Liabilities | B45: - | C45: - | D45: 291.11 | E45: -726.02 | F45: -53.09
A46: Cash generated from operations | B46: 6002.54 | C46: 5956.77 | D46: 1473.41 | E46: 6561.38 | F46: 2617.53
A47: Direct taxes paid (net of refunds) | B47: -1170.17 | C47: -647.61 | D47: -738.49 | E47: -915.56 | F47: -380.18
A48: Net cash flow from operating activities (A) | B48: 4832.37 | C48: 5309.16 | D48: 734.92 | E48: 5645.82 | F48: 2237.35
A49: B) CASH FLOWS FROM INVESTING ACTIVITIES
A50: Purchase of PP&E, intangibles etc. (incl. CWIP and capital advances) | B50: -1733.65 | C50: -2334.1 | D50: -4231.78 | E50: -4482.46 | F50: -8687.05
A51: Proceeds from sale of PP&E and other intangible assets | B51: 8.33 | C51: 37.76 | D51: 165.85 | E51: 521.32 | F51: 95.56
A52: Inter corporate deposits given | B52: -0.02 | C52: -0.02 | D52: -0.05 | E52: -2340.61 | F52: -
A53: Inter corporate deposits received back | B53: - | C53: - | D53: - | E53: 255 | F53: 5.17
A54: Proceeds from sale of investment in Subsidiary Company | B54: 20 | C54: - | D54: - | E54: 46.05 | F54: 61
A55: Proceeds from buyback of shares of joint venture | B55: 2.24 | C55: - | D55: - | E55: - | F55: -
A56: Payment received against loans given to joint venture | B56: - | C56: 0.12 | D56: - | E56: - | F56: -
A57: Gain on sale of current financial assets (FVTPL) | B57: 26.65 | C57: 8.26 | D57: 52.25 | E57: - | F57: -
A58: Investments in bank deposits (original maturity >3 months, ≤12 months) | B58: -15438.05 | C58: -15710.06 | D58: - | E58: - | F58: -
A59: Redemption of bank deposits (original maturity >3 months, ≤12 months) | B59: 15423.65 | C59: 15730.72 | D59: - | E59: - | F59: -
A60: (Investment) / Redemption in bank and margin money deposits (>3 months) | B60: - | C60: - | D60: -10914.28 | E60: -927.24 | F60: 9142.18
A61: Investments in bank deposits (original maturity >12 months) | B61: -31.65 | C61: -24.27 | D61: - | E61: - | F61: -
A62: Redemption of bank deposits (original maturity >12 months) | B62: 20.42 | C62: 7.4 | D62: - | E62: - | F62: -
A63: Purchase of non current investment / Investment in equity shares | B63: -9 | C63: -14.9 | D63: - | E63: - | F63: -
A64: Investment in certificate of deposits | B64: -750 | C64: - | D64: - | E64: - | F64: -
A65: Redemption of certificate of deposits | B65: 750 | C65: 9.54 | D65: - | E65: - | F65: -
A66: Investments in government securities (net) | B66: - | C66: - | D66: - | E66: -751.33 | F66: -1041.57
A67: Payment made towards acquisition of Subsidiary Companies | B67: - | C67: - | D67: - | E67: -2354.27 | F67: -3897.55
A68: Payment made towards acquisition of Business Unit | B68: - | C68: - | D68: - | E68: - | F68: -413.75
A69: Proceeds due to adjustment of purchase consideration paid earlier | B69: - | C69: - | D69: - | E69: - | F69: 1.56
A70: Investment in optionally convertible debentures | B70: - | C70: - | D70: - | E70: - | F70: -3910
A71: Proceeds from sale of units of mutual funds (net) | B71: - | C71: - | D71: - | E71: 53.47 | F71: 116.72
A72: Dividend received from joint venture and associates | B72: 2.79 | C72: 4.31 | D72: 12.39 | E72: 26.04 | F72: 15.07
A73: Interest received | B73: 390.98 | C73: 278.31 | D73: 434.87 | E73: 1003.6 | F73: 981.56
A74: Net cash used in investing activities (B) | B74: -1317.31 | C74: -2007.05 | D74: -14480.75 | E74: -8950.43 | F74: -7531.1
A75: C) CASH FLOWS FROM FINANCING ACTIVITIES
A76: Proceeds from non-current borrowings | B76: 8.47 | C76: - | D76: - | E76: - | F76: 9.72
A77: Repayment of non-current borrowings | B77: -5.86 | C77: - | D77: -3.58 | E77: -24.05 | F77: -1180.83
A78: Interest paid / Finance Costs Paid | B78: -86.4 | C78: -107.21 | D78: -127.5 | E78: -234.08 | F78: -175.79
A79: Repayment / Payment of principal portion of lease liabilities | B79: -41.05 | C79: -54.08 | D79: -142.91 | E79: -129.25 | F79: -837.17
A80: Interest portion of lease repayment | B80: -26.61 | C80: -24.59 | D80: - | E80: - | F80: -
A81: Net movement in earmarked balances with banks | B81: -8.84 | C81: 3.54 | D81: 0.45 | E81: - | F81: -
A82: Money received against share warrants | B82: - | C82: - | D82: 5000.03 | E82: 6660.96 | F82: 8339.09
A83: Dividend paid on equity shares | B83: -3664.61 | C83: -202.1 | D83: -1251.42 | E83: -496.41 | F83: -492.63
A84: Dividend paid to Non-controlling Interest | B84: -131.32 | C84: -131.32 | D84: -544.06 | E84: -88.4 | F84: -70.35
A85: Net cash used in / generated from financing activities (C) | B85: -3956.22 | C85: -515.76 | D85: 2931.01 | E85: 5688.77 | F85: 5592.04
A86: Net increase / (decrease) in cash and cash equivalents (A + B + C) | B86: -441.16 | C86: 2786.35 | D86: -10814.82 | E86: 2384.16 | F86: 298.29
A87: Cash and cash equivalents | B87: - | C87: - | D87: - | E87: - | F87: -
A88: Cash and cash equivalents at the end of the year | B88: 8571.56 | C88: 11358.49 | D88: 543.87 | E88: 3007.1 | F88: 5043.32
A89: Cash and cash equivalents related to entity held for sale (end) | B89: 0.47 | C89: 0.26 | D89: - | E89: - | F89: -
A90: Transfer on sale of investment in subsidiary | B90: 0.01 | C90: - | D90: 0.27 | E90: - | F90: -
A91: Adjustment for fair value gain on liquid mutual funds measured at FVTPL | B91: -0.47 | C91: -0.37 | D91: -0.21 | E91: -9.4 | F91: -2.42
A92: Closing cash and cash equivalents (net) | B92: 8571.57 | C92: 11358.38 | D92: 543.93 | E92: 2997.7 | F92: 5040.9
A93: Cash and cash equivalents at the beginning of the year | B93: 9011.88 | C93: 8571.56 | D93: 11358.49 | E93: 543.87 | F93: 3007.1
A94: Cash and cash equivalents related to entity held for sale (beginning) | B94: 0.85 | C94: 0.47 | D94: 0.26 | E94: - | F94: 1735.51
A95: Opening cash and cash equivalents (net) | B95: 9012.73 | C95: 8572.03 | D95: 11358.75 | E95: 613.54 | F95: 4742.61
A96: Net increase / (decrease) in cash and cash equivalents | B96: -441.16 | C96: 2786.35 | D96: -10814.82 | E96: 2384.16 | F96: 298.29

Sheet Wacc
B2: Capital Structure
B3: Total Debt | C3: ='Consolidated Balance sheet'!G47+'Consolidated Balance sheet'!G56 -> 26.82 | D3: (Borrowings + Lease Liabilities)
B4: Total Equity | C4: ='Relative Valuations'!C3*G4 -> 107637.47 | D4: no of shares outstanding | F4: CMP (Rs.): | G4: 437 | H4: Source: BSE/NSE (FY2025)
B5: Total Mix (Debt + Equity) | C5: =C4+C3 -> 107664.29 | D5: equity share capital/face valueper share
B6: % of Debt | C6: =C3/C5 -> 0.00024910767
B7: % of Equity | C7: =C4/C5 -> 0.99975089
B8: Debt to Equity | C8: =C3/C4 -> 0.00024916974
B10: Cost of Equity (CAPM)
B11: Risk-free Rate (Rf) | C11: 0.0625 | E11: Source: RBI 10-year Government Securities yield (FY2025)
B12: Beta (β) | C12: =BETA!H3 -> 1.0923358
B13: Market Risk Premium (Rm - Rf) | C13: 0.065 | E13: Source: India Equity Risk Premium (Damodaran estimate)
B14: Cost of Equity [Ke = Rf + β×(Rm-Rf)] | C14: =C11+(C12*C13) -> 0.13350183
B16: Cost of Debt
B17: Finance Cost (FY2025) | C17: ='Consolidated P&L'!G15 -> 215.94
B18: Total Debt (FY2025) | C18: =C3 -> 26.82
B19: Pre-tax Cost of Debt [Kd = FC/Debt] | C19: =IFERROR(C17/C18,0) -> 8.0514541
B20: Tax Rate | C20: =Assumptions!G34 -> 0.20363462
B21: Post-tax Cost of Debt [Kd*(1-T)] | C21: =C19*(1-C20) -> 6.4118994
B23: WACC
B24: Source | C24: Weight | D24: Cost | E24: Weighted Cost
B25: Debt | C25: =C6 -> 0.00024910767 | D25: =C21 -> 6.4118994 | E25: =D25*C25 -> 0.0015972533
B26: Equity | C26: =C7 -> 0.99975089 | D26: =C14 -> 0.13350183 | E26: =C26*D26 -> 0.13346857
B27: WACC | C27: =SUM(C25:C26) -> 1 | D27: (Check: weights = 100%) | E27: =E25+E26 -> 0.13506582 | G27: wacc = we*ke+wd*kd

Sheet BETA
A1: Date | B1: Close Price (Ambuja Cement) | C1: Date | D1: Close Price (Nifty) | F1: Rm Ambuja Cement) | G1: Rm Nifty | H1: Beta | I1: Covariance
A2: 43922 | B2: 156.64999389648438 | C2: 43922 | D2: 8253.7998046875
A3: 43924 | B3: 153 | C3: 43924 | D3: 8083.7998046875 | F3: =(B3-B2)/B2 -> -0.023300313 | G3: =(D3-D2)/D2 -> -0.020596574 | H3: =SLOPE(F3:F1515,G3:G1515) -> 1.0923358 | I3: =_xlfn.COVARIANCE.S(F3:F1515,G3:G1515)/_xlfn.VAR.S(G3:G1515) -> 1.0923358
A4: 43928 | B4: 159 | C4: 43928 | D4: 8792.2001953125 | F4: =(B4-B3)/B3 -> 0.039215686 | G4: =(D4-D3)/D3 -> 0.087632105
A5: 43929 | B5: 149.6999969482422 | C5: 43929 | D5: 8748.75 | F5: =(B5-B4)/B4 -> -0.058490585 | G5: =(D5-D4)/D4 -> -0.0049419024
A6: 43930 | B6: 158.8000030517578 | C6: 43930 | D6: 9111.9004 | F6: =(B6-B5)/B5 -> 0.060788285 | G6: =(D6-D5)/D5 -> 0.041508832 | I6: SUMMARY OUTPUT
A7: 43934 | B7: 165 | C7: 43934 | D7: 8993.8496 | F7: =(B7-B6)/B6 -> 0.039042801 | G7: =(D7-D6)/D6 -> -0.012955671
A8: 43936 | B8: 168.5500030517578 | C8: 43936 | D8: 8925.2998046875 | F8: =(B8-B7)/B7 -> 0.02151517 | G8: =(D8-D7)/D7 -> -0.0076218536 | I8: Regression Statistics
A9: 43937 | B9: 169.6999969482422 | C9: 43937 | D9: 8992.7998046875 | F9: =(B9-B8)/B8 -> 0.0068228649 | G9: =(D9-D8)/D8 -> 0.0075627712 | I9: Multiple R | J9: 0.5115617
A10: 43938 | B10: 172.9499969482422 | C10: 43938 | D10: 9266.75 | F10: =(B10-B9)/B9 -> 0.019151444 | G10: =(D10-D9)/D9 -> 0.030463282 | I10: R Square | J10: 0.26169537
A11: 43941 | B11: 170.3000030517578 | C11: 43941 | D11: 9261.8496 | F11: =(B11-B10)/B10 -> -0.015322312 | G11: =(D11-D10)/D10 -> -0.00052881438 | I11: Adjusted R Square | J11: 0.26120675
A12: 43942 | B12: 167.5500030517578 | C12: 43942 | D12: 8981.4501953125 | F12: =(B12-B11)/B11 -> -0.016147974 | G12: =(D12-D11)/D11 -> -0.030274667 | I12: Standard Error | J12: 0.018030476
A13: 43943 | B13: 176.5 | C13: 43943 | D13: 9187.2998046875 | F13: =(B13-B12)/B12 -> 0.053416871 | G13: =(D13-D12)/D12 -> 0.022919418 | I13: Observations | J13: 1513
A14: 43944 | B14: 171.4499969482422 | C14: 43944 | D14: 9313.9004 | F14: =(B14-B13)/B13 -> -0.028611915 | G14: =(D14-D13)/D13 -> 0.013779956
A15: 43945 | B15: 167.9499969482422 | C15: 43945 | D15: 9154.4004 | F15: =(B15-B14)/B14 -> -0.020414115 | G15: =(D15-D14)/D14 -> -0.017124942 | I15: ANOVA
A16: 43948 | B16: 172.3000030517578 | C16: 43948 | D16: 9282.2998046875 | F16: =(B16-B15)/B15 -> 0.025900602 | G16: =(D16-D15)/D15 -> 0.013971359 | J16: df | K16: SS | L16: MS | M16: F | N16: Significance F
A17: 43949 | B17: 167.6999969482422 | C17: 43949 | D17: 9380.9004 | F17: =(B17-B16)/B16 -> -0.026697655 | G17: =(D17-D16)/D16 -> 0.010622431 | I17: Regression | J17: 1 | K17: 0.17411625 | L17: 0.17411625 | M17: 535.5807 | N17: 1.1337563e-101
A18: 43950 | B18: 169.5 | C18: 43950 | D18: 9553.3496 | F18: =(B18-B17)/B17 -> 0.010733471 | G18: =(D18-D17)/D17 -> 0.018383014 | I18: Residual | J18: 1511 | K18: 0.49122317 | L18: 0.00032509806
A19: 43951 | B19: 171.64999389648438 | C19: 43951 | D19: 9859.9004 | F19: =(B19-B18)/B18 -> 0.01268433 | G19: =(D19-D18)/D18 -> 0.032088303 | I19: Total | J19: 1512 | K19: 0.66533942
A20: 43955 | B20: 162.35000610351562 | C20: 43955 | D20: 9293.5 | F20: =(B20-B19)/B19 -> -0.054179948 | G20: =(D20-D19)/D19 -> -0.057444839
A21: 43956 | B21: 164.8000030517578 | C21: 43956 | D21: 9205.5996 | F21: =(B21-B20)/B20 -> 0.015090834 | G21: =(D21-D20)/D20 -> -0.0094582655 | J21: Coefficients | K21: Standard Error | L21: t Stat | M21: P-value | N21: Lower 95% | O21: Upper 95% | P21: Lower 95.0% | Q21: Upper 95.0%
A22: 43957 | B22: 167.85000610351562 | C22: 43957 | D22: 9270.9004 | F22: =(B22-B21)/B21 -> 0.0185073 | G22: =(D22-D21)/D21 -> 0.0070935935 | I22: Intercept | J22: 8.2113966e-05 | K22: 0.00046486634 | L22: 0.17663995 | M22: 0.85981489 | N22: -0.00082973773 | O22: 0.00099396566 | P22: -0.00082973773 | Q22: 0.00099396566
A23: 43958 | B23: 168.60000610351562 | C23: 43958 | D23: 9199.0498046875 | F23: =(B23-B22)/B22 -> 0.0044682751 | G23: =(D23-D22)/D22 -> -0.0077501195 | I23: X Variable 1 | J23: 1.0923358 | K23: 0.047200184 | L23: 23.142617 | M23: 1.1337563e-101 | N23: 0.99975095 | O23: 1.1849206 | P23: 0.99975095 | Q23: 1.1849206
A24: 43959 | B24: 169.35000610351562 | C24: 43959 | D24: 9251.5 | F24: =(B24-B23)/B23 -> 0.0044483984 | G24: =(D24-D23)/D23 -> 0.0057016971
A25: 43962 | B25: 173.9499969482422 | C25: 43962 | D25: 9239.2001953125 | F25: =(B25-B24)/B24 -> 0.027162626 | G25: =(D25-D24)/D24 -> -0.001329493
A26: 43963 | B26: 175.1999969482422 | C26: 43963 | D26: 9196.5498046875 | F26: =(B26-B25)/B25 -> 0.0071859731 | G26: =(D26-D25)/D25 -> -0.0046162427
A27: 43964 | B27: 183 | C27: 43964 | D27: 9383.5498046875 | F27: =(B27-B26)/B26 -> 0.044520566 | G27: =(D27-D26)/D26 -> 0.020333713
A28: 43965 | B28: 182.5 | C28: 43965 | D28: 9142.75 | F28: =(B28-B27)/B27 -> -0.0027322404 | G28: =(D28-D27)/D27 -> -0.025661909
A29: 43966 | B29: 181.8000030517578 | C29: 43966 | D29: 9136.8496 | F29: =(B29-B28)/B28 -> -0.0038355997 | G29: =(D29-D28)/D28 -> -0.00064536279
A30: 43969 | B30: 172.14999389648438 | C30: 43969 | D30: 8823.25 | F30: =(B30-B29)/B29 -> -0.053080357 | G30: =(D30-D29)/D29 -> -0.03432251
A31: 43970 | B31: 174.60000610351562 | C31: 43970 | D31: 8879.0996 | F31: =(B31-B30)/B30 -> 0.014231846 | G31: =(D31-D30)/D30 -> 0.0063298228
A32: 43971 | B32: 179.64999389648438 | C32: 43971 | D32: 9066.5498046875 | F32: =(B32-B31)/B31 -> 0.028923182 | G32: =(D32-D31)/D31 -> 0.021111397
A33: 43972 | B33: 181 | C33: 43972 | D33: 9106.25 | F33: =(B33-B32)/B32 -> 0.007514646 | G33: =(D33-D32)/D32 -> 0.0043787545
A34: 43973 | B34: 186.9499969482422 | C34: 43973 | D34: 9039.25 | F34: =(B34-B33)/B33 -> 0.032872911 | G34: =(D34-D33)/D33 -> -0.0073575841
A35: 43977 | B35: 188.5500030517578 | C35: 43977 | D35: 9029.0498046875 | F35: =(B35-B34)/B34 -> 0.0085584709 | G35: =(D35-D34)/D34 -> -0.0011284338
A36: 43978 | B36: 187.4499969482422 | C36: 43978 | D36: 9314.9501953125 | F36: =(B36-B35)/B35 -> -0.0058340286 | G36: =(D36-D35)/D35 -> 0.031664505
A37: 43979 | B37: 191.3000030517578 | C37: 43979 | D37: 9490.0996 | F37: =(B37-B36)/B36 -> 0.020538843 | G37: =(D37-D36)/D36 -> 0.018803044
A38: 43980 | B38: 191.5500030517578 | C38: 43980 | D38: 9580.2998046875 | F38: =(B38-B37)/B37 -> 0.0013068479 | G38: =(D38-D37)/D37 -> 0.0095046627
A39: 43983 | B39: 188.9499969482422 | C39: 43983 | D39: 9826.1504 | F39: =(B39-B38)/B38 -> -0.013573511 | G39: =(D39-D38)/D38 -> 0.025662097
A40: 43984 | B40: 191.1999969482422 | C40: 43984 | D40: 9979.0996 | F40: =(B40-B39)/B39 -> 0.011907912 | G40: =(D40-D39)/D39 -> 0.015565528
A41: 43985 | B41: 187.75 | C41: 43985 | D41: 10061.5498046875 | F41: =(B41-B40)/B40 -> -0.018043917 | G41: =(D41-D40)/D40 -> 0.008262288
A42: 43986 | B42: 186.75 | C42: 43986 | D42: 10029.099609375 | F42: =(B42-B41)/B41 -> -0.0053262317 | G42: =(D42-D41)/D41 -> -0.0032251687
A43: 43987 | B43: 195.10000610351562 | C43: 43987 | D43: 10142.150390625 | F43: =(B43-B42)/B42 -> 0.044712215 | G43: =(D43-D42)/D42 -> 0.011272276
A44: 43990 | B44: 191.4499969482422 | C44: 43990 | D44: 10167.4501953125 | F44: =(B44-B43)/B43 -> -0.018708401 | G44: =(D44-D43)/D43 -> 0.0024945208
A45: 43991 | B45: 187.8000030517578 | C45: 43991 | D45: 10046.650390625 | F45: =(B45-B44)/B44 -> -0.019064998 | G45: =(D45-D44)/D44 -> -0.011881032
A46: 43992 | B46: 192 | C46: 43992 | D46: 10116.150390625 | F46: =(B46-B45)/B45 -> 0.022364201 | G46: =(D46-D45)/D45 -> 0.0069177285
A47: 43993 | B47: 189.5 | C47: 43993 | D47: 9902 | F47: =(B47-B46)/B46 -> -0.013020833 | G47: =(D47-D46)/D46 -> -0.021169158
A48: 43994 | B48: 193.6999969482422 | C48: 43994 | D48: 9972.9004 | F48: =(B48-B47)/B47 -> 0.022163572 | G48: =(D48-D47)/D47 -> 0.0071602091
A49: 43997 | B49: 191.5 | C49: 43997 | D49: 9813.7001953125 | F49: =(B49-B48)/B48 -> -0.011357754 | G49: =(D49-D48)/D48 -> -0.015963279
A50: 43998 | B50: 190.60000610351562 | C50: 43998 | D50: 9914 | F50: =(B50-B49)/B49 -> -0.004699707 | G50: =(D50-D49)/D49 -> 0.010220386
A51: 43999 | B51: 187.14999389648438 | C51: 43999 | D51: 9881.1504 | F51: =(B51-B50)/B50 -> -0.018100798 | G51: =(D51-D50)/D50 -> -0.0033134567
A52: 44000 | B52: 187.35000610351562 | C52: 44000 | D52: 10091.650390625 | F52: =(B52-B51)/B51 -> 0.0010687268 | G52: =(D52-D51)/D51 -> 0.021303188
A53: 44001 | B53: 190.8000030517578 | C53: 44001 | D53: 10244.400390625 | F53: =(B53-B52)/B52 -> 0.018414715 | G53: =(D53-D52)/D52 -> 0.015136275
A54: 44004 | B54: 191.10000610351562 | C54: 44004 | D54: 10311.2001953125 | F54: =(B54-B53)/B53 -> 0.001572343 | G54: =(D54-D53)/D53 -> 0.0065206164
A55: 44005 | B55: 193.25 | C55: 44005 | D55: 10471 | F55: =(B55-B54)/B54 -> 0.011250622 | G55: =(D55-D54)/D54 -> 0.015497692
A56: 44006 | B56: 188.6999969482422 | C56: 44006 | D56: 10305.2998046875 | F56: =(B56-B55)/B55 -> -0.023544647 | G56: =(D56-D55)/D55 -> -0.015824677
A57: 44007 | B57: 186.25 | C57: 44007 | D57: 10288.900390625 | F57: =(B57-B56)/B56 -> -0.012983556 | G57: =(D57-D56)/D56 -> -0.0015913573
A58: 44008 | B58: 188 | C58: 44008 | D58: 10383 | F58: =(B58-B57)/B57 -> 0.0093959732 | G58: =(D58-D57)/D57 -> 0.0091457401
A59: 44011 | B59: 187.5500030517578 | C59: 44011 | D59: 10312.400390625 | F59: =(B59-B58)/B58 -> -0.0023936008 | G59: =(D59-D58)/D58 -> -0.0067995386
A60: 44012 | B60: 193.60000610351562 | C60: 44012 | D60: 10302.099609375 | F60: =(B60-B59)/B59 -> 0.03225808 | G60: =(D60-D59)/D59 -> -0.00099887328
A61: 44013 | B61: 192.1999969482422 | C61: 44013 | D61: 10430.0498046875 | F61: =(B61-B60)/B60 -> -0.007231452 | G61: =(D61-D60)/D60 -> 0.012419817
A62: 44014 | B62: 193.6999969482422 | C62: 44014 | D62: 10551.7001953125 | F62: =(B62-B61)/B61 -> 0.0078043706 | G62: =(D62-D61)/D61 -> 0.011663453
A63: 44015 | B63: 195.8000030517578 | C63: 44015 | D63: 10607.349609375 | F63: =(B63-B62)/B62 -> 0.010841539 | G63: =(D63-D62)/D62 -> 0.005273976
A64: 44018 | B64: 193.89999389648438 | C64: 44018 | D64: 10763.650390625 | F64: =(B64-B63)/B63 -> -0.009703826 | G64: =(D64-D63)/D63 -> 0.01473514
A65: 44019 | B65: 193.25 | C65: 44019 | D65: 10799.650390625 | F65: =(B65-B64)/B64 -> -0.0033522121 | G65: =(D65-D64)/D64 -> 0.0033445902
A66: 44020 | B66: 195.5500030517578 | C66: 44020 | D66: 10705.75 | F66: =(B66-B65)/B65 -> 0.011901698 | G66: =(D66-D65)/D65 -> -0.0086947621
A67: 44021 | B67: 202 | C67: 44021 | D67: 10813.4501953125 | F67: =(B67-B66)/B66 -> 0.032983875 | G67: =(D67-D66)/D66 -> 0.010060033
A68: 44022 | B68: 197.1999969482422 | C68: 44022 | D68: 10768.0498046875 | F68: =(B68-B67)/B67 -> -0.023762391 | G68: =(D68-D67)/D67 -> -0.0041985111
A69: 44025 | B69: 198.4499969482422 | C69: 44025 | D69: 10802.7001953125 | F69: =(B69-B68)/B68 -> 0.0063387425 | G69: =(D69-D68)/D68 -> 0.0032178891
A70: 44026 | B70: 190.5 | C70: 44026 | D70: 10607.349609375 | F70: =(B70-B69)/B69 -> -0.040060454 | G70: =(D70-D69)/D69 -> -0.018083496
A71: 44027 | B71: 188.64999389648438 | C71: 44027 | D71: 10618.2001953125 | F71: =(B71-B70)/B70 -> -0.0097113181 | G71: =(D71-D70)/D70 -> 0.0010229309
A72: 44028 | B72: 192.5 | C72: 44028 | D72: 10739.9501953125 | F72: =(B72-B71)/B71 -> 0.020408196 | G72: =(D72-D71)/D71 -> 0.011466162
A73: 44029 | B73: 193.4499969482422 | C73: 44029 | D73: 10901.7001953125 | F73: =(B73-B72)/B72 -> 0.0049350491 | G73: =(D73-D72)/D72 -> 0.015060591
A74: 44032 | B74: 195.6999969482422 | C74: 44032 | D74: 11022.2001953125 | F74: =(B74-B73)/B73 -> 0.011630913 | G74: =(D74-D73)/D73 -> 0.011053322
A75: 44033 | B75: 204.9499969482422 | C75: 44033 | D75: 11162.25 | F75: =(B75-B74)/B74 -> 0.047266225 | G75: =(D75-D74)/D74 -> 0.012706157
A76: 44034 | B76: 200.89999389648438 | C76: 44034 | D76: 11132.599609375 | F76: =(B76-B75)/B75 -> -0.019760932 | G76: =(D76-D75)/D75 -> -0.0026563095
A77: 44035 | B77: 197.9499969482422 | C77: 44035 | D77: 11215.4501953125 | F77: =(B77-B76)/B76 -> -0.014683908 | G77: =(D77-D76)/D76 -> 0.0074421599
A78: 44036 | B78: 200.9499969482422 | C78: 44036 | D78: 11194.150390625 | F78: =(B78-B77)/B77 -> 0.015155342 | G78: =(D78-D77)/D77 -> -0.0018991484
A79: 44039 | B79: 207.14999389648438 | C79: 44039 | D79: 11131.7998046875 | F79: =(B79-B78)/B78 -> 0.030853431 | G79: =(D79-D78)/D78 -> -0.0055699257
A80: 44040 | B80: 216.6999969482422 | C80: 44040 | D80: 11300.5498046875 | F80: =(B80-B79)/B79 -> 0.046101875 | G80: =(D80-D79)/D79 -> 0.015159274
A81: 44041 | B81: 215.60000610351562 | C81: 44041 | D81: 11202.849609375 | F81: =(B81-B80)/B80 -> -0.0050761 | G81: =(D81-D80)/D80 -> -0.0086456143
A82: 44042 | B82: 221.25 | C82: 44042 | D82: 11102.150390625 | F82: =(B82-B81)/B81 -> 0.026205908 | G82: =(D82-D81)/D81 -> -0.0089887147
A83: 44043 | B83: 220.10000610351562 | C83: 44043 | D83: 11073.4501953125 | F83: =(B83-B82)/B82 -> -0.0051977125 | G83: =(D83-D82)/D82 -> -0.0025851024
A84: 44046 | B84: 221.14999389648438 | C84: 44046 | D84: 10891.599609375 | F84: =(B84-B83)/B83 -> 0.0047705032 | G84: =(D84-D83)/D83 -> -0.016422216
A85: 44047 | B85: 221.5500030517578 | C85: 44047 | D85: 11095.25 | F85: =(B85-B84)/B84 -> 0.0018087686 | G85: =(D85-D84)/D84 -> 0.018697932
A86: 44048 | B86: 220.89999389648438 | C86: 44048 | D86: 11101.650390625 | F86: =(B86-B85)/B85 -> -0.0029339163 | G86: =(D86-D85)/D85 -> 0.00057685862
A87: 44049 | B87: 222.9499969482422 | C87: 44049 | D87: 11200.150390625 | F87: =(B87-B86)/B86 -> 0.0092802314 | G87: =(D87-D86)/D86 -> 0.0088725547
A88: 44050 | B88: 219.5500030517578 | C88: 44050 | D88: 11214.0498046875 | F88: =(B88-B87)/B87 -> -0.015250029 | G88: =(D88-D87)/D87 -> 0.0012410024
A89: 44053 | B89: 221.85000610351562 | C89: 44053 | D89: 11270.150390625 | F89: =(B89-B88)/B88 -> 0.010475987 | G89: =(D89-D88)/D88 -> 0.0050027053
A90: 44054 | B90: 222.75 | C90: 44054 | D90: 11322.5 | F90: =(B90-B89)/B89 -> 0.0040567675 | G90: =(D90-D89)/D89 -> 0.0046449788
A91: 44055 | B91: 221.8000030517578 | C91: 44055 | D91: 11308.400390625 | F91: =(B91-B90)/B90 -> -0.0042648572 | G91: =(D91-D90)/D90 -> -0.0012452735
A92: 44056 | B92: 222 | C92: 44056 | D92: 11300.4501953125 | F92: =(B92-B91)/B91 -> 0.00090169948 | G92: =(D92-D91)/D91 -> -0.00070303447
A93: 44057 | B93: 220.75 | C93: 44057 | D93: 11178.400390625 | F93: =(B93-B92)/B92 -> -0.0056306306 | G93: =(D93-D92)/D92 -> -0.010800437
A94: 44060 | B94: 219.35000610351562 | C94: 44060 | D94: 11247.099609375 | F94: =(B94-B93)/B93 -> -0.0063419882 | G94: =(D94-D93)/D93 -> 0.006145711
A95: 44061 | B95: 228.1999969482422 | C95: 44061 | D95: 11385.349609375 | F95: =(B95-B94)/B94 -> 0.040346435 | G95: =(D95-D94)/D94 -> 0.012292058
A96: 44062 | B96: 226.9499969482422 | C96: 44062 | D96: 11408.400390625 | F96: =(B96-B95)/B95 -> -0.0054776513 | G96: =(D96-D95)/D95 -> 0.0020246002
A97: 44063 | B97: 225.35000610351562 | C97: 44063 | D97: 11312.2001953125 | F97: =(B97-B96)/B96 -> -0.0070499708 | G97: =(D97-D96)/D96 -> -0.0084324
A98: 44064 | B98: 225.9499969482422 | C98: 44064 | D98: 11371.599609375 | F98: =(B98-B97)/B97 -> 0.0026624843 | G98: =(D98-D97)/D97 -> 0.0052509161
A99: 44067 | B99: 224.1999969482422 | C99: 44067 | D99: 11466.4501953125 | F99: =(B99-B98)/B98 -> -0.0077450764 | G99: =(D99-D98)/D98 -> 0.0083410065
A100: 44068 | B100: 222.35000610351562 | C100: 44068 | D100: 11472.25 | F100: =(B100-B99)/B99 -> -0.0082515204 | G100: =(D100-D99)/D99 -> 0.00050580647
...

Sheet Consolidated Quaterly Result
C1: Consolidated Quarterly Results (Rs. Crores)
D2: Quarter ended | G2: Years
C3: Particulars | D3: 46082 | E3: 45992 | F3: 45901 | G3: 46082 | H3: 45717
C4: Net Sales | D4: 10915.47 | E4: 10276.65 | F4: 9174.49 | G4: 40655.68 | H4: 35044.76
C5: Other Income | D5: 233.89 | E5: 87.32 | F5: 257.04 | G5: 834.34 | H5: 2654.24
C6: Total Income | D6: 11149.36 | E6: 10363.97 | F6: 9431.53 | G6: 41490.02 | H6: 37699
C7: Expenditure | D7: -10525.09 | E7: -9941.46 | F7: -8375.59 | G7: -37910.76 | H7: -31768.39
C8: Cost of Materials Consumed | D8: -1626.55 | E8: -1741.51 | F8: -1607.92 | G8: -6511.54 | H8: -5708.07
C9: Finance Costs | D9: -20.8 | E9: -58.85 | F9: -76.82 | G9: -223.61 | H9: -215.94
C10: Other Expenses | D10: -7051.01 | E10: -6634.82 | F10: -5699.98 | G10: -25771.59 | H10: -21143.28
C11: Employee benefit expense | D11: -395.9 | E11: -383.88 | F11: -405.13 | G11: -1602.65 | H11: -1403.41
C12: Purchases of stock-in-trade | D12: -162.77 | E12: -247.61 | F12: -81.39 | G12: -609.25 | H12: -763.66
C13: Changes in inventories of finished goods, work-in-progress and stock-in-trade | D13: -215.33 | E13: 84.24 | F13: 380.8 | G13: 378.29 | H13: -55.69
C14: Depreciation and amortisation expense | D14: -1052.73 | E14: -959.03 | F14: -885.15 | G14: -3570.41 | H14: -2478.34
... C25: Income Attributable to Consolidated Group | D25: 1857.43 | E25: 366.97 | F25: 2302.28 | G25: 5637.08 | H25: 5158.41
C26: EPS after Extraordinary items (in Rs) | D26: - | E26: - | F26: - | G26: - | H26: -
C27: Exceptional Item | D27: -102.51 | E27: -15.23 | F27: -222.8 | G27: -300.54 | H27: -21.47
C28: Profit after Interest but before Exceptional Items | D28: 624.27 | E28: 422.51 | F28: 1055.94 | G28: 3579.26 | H28: 5930.61
C29: Net Profit Loss for the period from continuing operations | D29: 1851.06 | E29: 361.84 | F29: 2297.89 | G29: 5617.03 | H29: 5145.19
C30: Profit (loss) from discontinuing operations before tax | D30: 0 | E30: 0 | F30: 0 | G30: 0 | H30: 0
C31: Tax expense of discontinuing operations | D31: 0 | E31: 0 | F31: 0 | G31: 0 | H31: 0
C32: Net profit (loss) from discontinuing operation after tax | D32: 0 | E32: 0 | F32: 0 | G32: 0 | H32: 0
C33: Other Comprehensive Income Net of Taxes | D33: 41.32 | E33: -4.58 | F33: 42.26 | G33: 74.13 | H33: -39.63
C34: Any Other Comprehensive Item | D34: 0 | E34: 0 | F34: 0 | G34: 0 | H34: 0
C35: Total Comprehensive Income for the Period | D35: 1898.75 | E35: 362.39 | F35: 2344.54 | G35: 5711.21 | H35: 5118.78
C36: Total Amount of items that will not be reclassified to profit and loss | D36: 0 | E36: 0 | F36: 0 | G36: 0 | H36: 0
C37: Income tax relating to items that will not be reclassified to profit or loss | D37: 0 | E37: 0 | F37: 0 | G37: 0 | H37: 0
C38: Total Amount of items that will be reclassified to profit and loss | D38: 0 | E38: 0 | F38: 0 | G38: 0 | H38: 0
... C45: Diluted for discontinued & continuing operation | D45: 0 | E45: 0 | F45: 0 | G45: 0 | H45: 0

Sheet Peers
E2: Ambuja Cement | J2: Ultra tech Cement
E3: Metric | F3: 45352 | G3: 45717 | H3: 46082 | J3: Metric | K3: 45352 | L3: 45717 | M3: 46082
E4: Debtor Days | F4: 13 | G4: 16 | H4: 17 | J4: Debtor Days | K4: 22 | L4: 28 | M4: 25
E5: Inventory Days | F5: 238 | G5: 238 | H5: 246 | J5: Inventory Days | K5: 255 | L5: 255 | M5: 206
E6: Days Payable | F6: 196 | G6: 167 | H6: 227 | J6: Days Payable | K6: 260 | L6: 248 | M6: 217
E7: Cash Conversion Cycle | F7: 56 | G7: 86 | H7: 37 | J7: Cash Conversion Cycle | K7: 17 | L7: 35 | M7: 13
E8: Working Capital Days | F8: 8 | G8: -25 | H8: -3 | J8: Working Capital Days | K8: -52 | L8: -64 | M8: -41
E9: ROCE % | F9: 0.13 | G9: 0.11 | H9: 0.06 | J9: ROCE % | K9: 0.15 | L9: 0.11 | M9: 0.13
E13: Shree Cement | J13: J.K Cement
E14: Metric | F14: 45352 | G14: 45717 | H14: 46082 | J14: Metric | K14: 45352 | L14: 45717 | M14: 46082
E15: Debtor Days | F15: 23 | G15: 27 | H15: 32 | J15: Debtor Days | K15: 18 | L15: 24 | M15: 20
E16: Inventory Days | F16: 670 | G16: 444 | H16: 469 | J16: Inventory Days | K16: 235 | L16: 213 | M16: 249
E17: Days Payable | F17: 229 | G17: 247 | H17: 274 | J17: Days Payable | K17: 185 | L17: 199 | M17: 198
E18: Cash Conversion Cycle | F18: 464 | G18: 223 | H18: 227 | J18: Cash Conversion Cycle | K18: 68 | L18: 38 | M18: 71
E19: Working Capital Days | F19: 7 | G19: -8 | H19: 135 | J19: Working Capital Days | K19: 2 | L19: -23 | M19: -21
E20: ROCE % | F20: 0.15 | G20: 0.07 | H20: 0.1 | J20: ROCE % | K20: 0.16 | L20: 0.14 | M20: 0.15

Sheet Ratio Analysis
A1: Ratio Analysis- Ambuja
A2: Years | B2: 43800 | C2: 44166 | D2: 44531 | E2: 44986 | F2: 45352 | G2: 45717 | H2: Trends | I2: Mean | J2: Median
A4: Sales Growth | C4: =('Consolidated P&L'!C6-'Consolidated P&L'!B6)/'Consolidated P&L'!B6 -> -0.095462771 | D4: =('Consolidated P&L'!D6-'Consolidated P&L'!C6)/'Consolidated P&L'!C6 -> 0.18148389 | E4: =('Consolidated P&L'!E6-'Consolidated P&L'!D6)/'Consolidated P&L'!D6 -> 0.34425726 | F4: =('Consolidated P&L'!F6-'Consolidated P&L'!E6)/'Consolidated P&L'!E6 -> -0.14837778 | G4: =('Consolidated P&L'!G6-'Consolidated P&L'!F6)/'Consolidated P&L'!F6 -> 0.016226352 | I4: =AVERAGE(C4:G4) -> 0.059625392 | J4: =MEDIAN(C4:G4) -> 0.016226352
A5: EBITDA Growth | D5: =(Assumptions!C9-Assumptions!B9)/Assumptions!B9 -> 0.23725426 | E5: =(Assumptions!D9-Assumptions!C9)/Assumptions!C9 -> -0.17683112 | F5: =(Assumptions!E9-Assumptions!D9)/Assumptions!D9 -> 0.25804113 | G5: =(Assumptions!F9-Assumptions!E9)/Assumptions!E9 -> -0.27915397 | I5: =AVERAGE(D5:G5) -> 0.0098275739 | J5: =MEDIAN(D5:G5) -> 0.030211572
A6: EBIT Growth | D6: =(Assumptions!C11-Assumptions!B11)/Assumptions!B11 -> 0.31181034 | E6: =(Assumptions!D11-Assumptions!C11)/Assumptions!C11 -> -0.31565761 | F6: =(Assumptions!E11-Assumptions!D11)/Assumptions!D11 -> 0.38794742 | G6: =(Assumptions!F11-Assumptions!E11)/Assumptions!E11 -> -0.55386967 | I6: =AVERAGE(D6:G6) -> -0.042442382 | J6: =MEDIAN(D6:G6) -> -0.0019236348
A7: Net Profit Growth | D7: =(Assumptions!C17-Assumptions!B17)/Assumptions!B17 -> 0.17541768 | E7: =(Assumptions!D17-Assumptions!C17)/Assumptions!C17 -> -0.070846431 | F7: =(Assumptions!E17-Assumptions!D17)/Assumptions!D17 -> 0.38452814 | G7: =(Assumptions!F17-Assumptions!E17)/Assumptions!E17 -> 0.1651313 | I7: =AVERAGE(D7:G7) -> 0.16355767 | J7: =MEDIAN(D7:G7) -> 0.17027449
A8: Dividend Growth | D8: =('Consolidated Cash Flow'!C83-'Consolidated Cash Flow'!B83)/'Consolidated Cash Flow'!B83 -> -0.94485088 | E8: =('Consolidated Cash Flow'!D83-'Consolidated Cash Flow'!C83)/'Consolidated Cash Flow'!C83 -> 5.1920831 | F8: =('Consolidated Cash Flow'!E83-'Consolidated Cash Flow'!D83)/'Consolidated Cash Flow'!D83 -> -0.60332263 | G8: =('Consolidated Cash Flow'!F83-'Consolidated Cash Flow'!E83)/'Consolidated Cash Flow'!E83 -> -0.0076146734 | I8: =AVERAGE(D8:G8) -> 0.90907374 | J8: =MEDIAN(D8:G8) -> -0.30546865
A9: Gross Margin | B9: =('Consolidated P&L'!B6-('Consolidated P&L'!B11+'Consolidated P&L'!B12+'Consolidated P&L'!B13+'Consolidated P&L'!B17+'Consolidated P&L'!B18)-'Consolidated P&L'!B14)/'Consolidated P&L'!B6 -> 0.33202145 | C9: =('Consolidated P&L'!C6-('Consolidated P&L'!C11+'Consolidated P&L'!C12+'Consolidated P&L'!C13+'Consolidated P&L'!C17+'Consolidated P&L'!C18)-'Consolidated P&L'!C14)/'Consolidated P&L'!C6 -> 0.35700315 | D9: =('Consolidated P&L'!D6-('Consolidated P&L'!D11+'Consolidated P&L'!D12+'Consolidated P&L'!D13+'Consolidated P&L'!D17+'Consolidated P&L'!D18)-'Consolidated P&L'!D14)/'Consolidated P&L'!D6 -> 0.36435154 | E9: =('Consolidated P&L'!E6-('Consolidated P&L'!E11+'Consolidated P&L'!E12+'Consolidated P&L'!E13+'Consolidated P&L'!E17+'Consolidated P&L'!E18)-'Consolidated P&L'!E14)/'Consolidated P&L'!E6 -> 0.27439098 | F9: =('Consolidated P&L'!F6-('Consolidated P&L'!F11+'Consolidated P&L'!F12+'Consolidated P&L'!F13+'Consolidated P&L'!F17+'Consolidated P&L'!F18)-'Consolidated P&L'!F14)/'Consolidated P&L'!F6 -> 0.32491668 | G9: =('Consolidated P&L'!G6-('Consolidated P&L'!G11+'Consolidated P&L'!G12+'Consolidated P&L'!G13+'Consolidated P&L'!G17+'Consolidated P&L'!G18)-'Consolidated P&L'!G14)/'Consolidated P&L'!G6 -> 0.27057752 | I9: =AVERAGE(B9:G9) -> 0.32054355 | J9: =MEDIAN(B9:G9) -> 0.32846906
A10: EBITDA Margin | B10: =('Consolidated P&L'!B6-'Consolidated P&L'!B22+'Consolidated P&L'!B15+'Consolidated P&L'!B16)/'Consolidated P&L'!B6 -> 0.16960841 | C10: =Assumptions!B9/'Consolidated P&L'!C6 -> 0.20327115 | D10: =Assumptions!C9/'Consolidated P&L'!D6 -> 0.21286629 | E10: =Assumptions!D9/'Consolidated P&L'!E6 -> 0.13035072 | F10: =Assumptions!E9/'Consolidated P&L'!F6 -> 0.19255788 | G10: =Assumptions!F9/'Consolidated P&L'!G6 -> 0.13658825 | I10: =AVERAGE(B10:G10) -> 0.17420712 | J10: =MEDIAN(B10:G10) -> 0.18108314
A11: EBIT Margin | B11: =('Consolidated P&L'!B6-'Consolidated P&L'!B22+'Consolidated P&L'!B15)/'Consolidated P&L'!B6 -> 0.12708557 | C11: =Assumptions!B11/'Consolidated P&L'!C6 -> 0.15588283 | D11: =Assumptions!C11/'Consolidated P&L'!D6 -> 0.17307787 | E11: =Assumptions!D11/'Consolidated P&L'!E6 -> 0.088111497 | F11: =Assumptions!E11/'Consolidated P&L'!F6 -> 0.14360138 | G11: =Assumptions!F11/'Consolidated P&L'!G6 -> 0.063041988 | I11: =AVERAGE(B11:G11) -> 0.12513352 | J11: =MEDIAN(B11:G11) -> 0.13534347
A12: EBT Margin | B12: ='Consolidated P&L'!B27/'Consolidated P&L'!B6 -> 0.14298164 | C12: ='Consolidated P&L'!C27/'Consolidated P&L'!C6 -> 0.16281458 | D12: ='Consolidated P&L'!D27/'Consolidated P&L'!D6 -> 0.17829753 | E12: ='Consolidated P&L'!E27/'Consolidated P&L'!E6 -> 0.095782601 | F12: ='Consolidated P&L'!F27/'Consolidated P&L'!F6 -> 0.17794584 | G12: ='Consolidated P&L'!G27/'Consolidated P&L'!G6 -> 0.17574998 | I12: =AVERAGE(B12:G12) -> 0.15559536 | J12: =MEDIAN(B12:G12) -> 0.16928228
A13: Net Profit Margin | B13: =('Consolidated P&L'!B33-'Consolidated P&L'!B44)/'Consolidated P&L'!B6 -> 0.077296148 | C13: =Assumptions!B17/'Consolidated P&L'!C6 -> 0.096484891 | D13: =Assumptions!C17/'Consolidated P&L'!D6 -> 0.095989499 | E13: =Assumptions!D17/'Consolidated P&L'!E6 -> 0.066348152 | F13: =Assumptions!E17/'Consolidated P&L'!F6 -> 0.10786577 | G13: =Assumptions!F17/'Consolidated P&L'!G6 -> 0.12367105 | I13: =AVERAGE(B13:G13) -> 0.094609252 | J13: =MEDIAN(B13:G13) -> 0.096237195
A15: Sales Expenses%Sales | B15: ='Consolidated P&L'!B22/'Consolidated P&L'!B6 -> 0.87918188 | C15: ='Consolidated P&L'!C22/'Consolidated P&L'!C6 -> 0.84893358 | D15: ='Consolidated P&L'!D22/'Consolidated P&L'!D6 -> 0.83041008 | E15: ='Consolidated P&L'!E22/'Consolidated P&L'!E6 -> 0.91568951 | F15: ='Consolidated P&L'!F22/'Consolidated P&L'!F6 -> 0.8643004 | G15: ='Consolidated P&L'!G22/'Consolidated P&L'!G6 -> 0.94274654 | I15: =AVERAGE(B15:G15) -> 0.88021033 | J15: =MEDIAN(B15:G15) -> 0.87174114
A16: Depriciation%Sales | B16: ='Consolidated P&L'!B16/'Consolidated P&L'!B6 -> 0.042522843 | C16: ='Consolidated P&L'!C16/'Consolidated P&L'!C6 -> 0.047388316 | D16: ='Consolidated P&L'!D16/'Consolidated P&L'!D6 -> 0.039788424 | E16: ='Consolidated P&L'!E16/'Consolidated P&L'!E6 -> 0.042239226 | F16: ='Consolidated P&L'!F16/'Consolidated P&L'!F6 -> 0.048956503 | G16: ='Consolidated P&L'!G16/'Consolidated P&L'!G6 -> 0.073546266 | I16: =AVERAGE(B16:G16) -> 0.049073596 | J16: =MEDIAN(B16:G16) -> 0.044955579
A17: Operating Income%Sales | B17: =('Consolidated P&L'!B6-'Consolidated P&L'!B22+'Consolidated P&L'!B15)/'Consolidated P&L'!B6 -> 0.12708557 | C17: =Assumptions!B11/'Consolidated P&L'!C6 -> 0.15588283 | D17: =Assumptions!C11/'Consolidated P&L'!D6 -> 0.17307787 | E17: =Assumptions!D11/'Consolidated P&L'!E6 -> 0.088111497 | F17: =Assumptions!E11/'Consolidated P&L'!F6 -> 0.14360138 | G17: =Assumptions!F11/'Consolidated P&L'!G6 -> 0.063041988 | I17: =AVERAGE(B17:G17) -> 0.12513352 | J17: =MEDIAN(B17:G17) -> 0.13534347
A19: Return on Capital Employed | B19: =('Consolidated P&L'!B6-'Consolidated P&L'!B22+'Consolidated P&L'!B15)/('Consolidated Balance sheet'!B35-'Consolidated Balance sheet'!B65) -> 0.11071184 | C19: =Assumptions!B11/('Consolidated Balance sheet'!C35-'Consolidated Balance sheet'!C65) -> 0.12546331 | D19: =Assumptions!C11/('Consolidated Balance sheet'!D35-'Consolidated Balance sheet'!D65) -> 0.14753885 | E19: =Assumptions!D11/('Consolidated Balance sheet'!E35-'Consolidated Balance sheet'!E65) -> 0.085326749 | F19: =Assumptions!E11/('Consolidated Balance sheet'!F35-'Consolidated Balance sheet'!F65) -> 0.08955926 | G19: =Assumptions!F11/('Consolidated Balance sheet'!G35-'Consolidated Balance sheet'!G65) -> 0.031659691 | I19: =AVERAGE(B19:G19) -> 0.098376615 | J19: =MEDIAN(B19:G19) -> 0.10013555
A20: Retained Earning % | C20: =(Assumptions!B17+('Consolidated Cash Flow'!B83))/Assumptions!B17 -> -0.54922974 | D20: =(Assumptions!C17+('Consolidated Cash Flow'!C83))/Assumptions!C17 -> 0.92731209 | E20: =(Assumptions!D17+('Consolidated Cash Flow'!D83))/Assumptions!D17 -> 0.51559186 | F20: =(Assumptions!E17+('Consolidated Cash Flow'!E83))/Assumptions!E17 -> 0.86121355 | G20: =(Assumptions!F17+('Consolidated Cash Flow'!F83))/Assumptions!F17 -> 0.88179046 | I20: =AVERAGE(C20:G20) -> 0.52733564 | J20: =MEDIAN(C20:G20) -> 0.86121355
A21: Return on Equity % | B21: =('Consolidated P&L'!B33-'Consolidated P&L'!B44)/'Consolidated Balance sheet'!B41 -> 0.087008924 | C21: =Assumptions!B17/'Consolidated Balance sheet'!C41 -> 0.10394066 | D21: =Assumptions!C17/'Consolidated Balance sheet'!D41 -> 0.10966351 | E21: =Assumptions!D17/'Consolidated Balance sheet'!E41 -> 0.081499896 | F21: =Assumptions!E17/'Consolidated Balance sheet'!F41 -> 0.086281144 | G21: =Assumptions!F17/'Consolidated Balance sheet'!G41 -> 0.077978603 | I21: =AVERAGE(B21:G21) -> 0.091062122 | J21: =MEDIAN(B21:G21) -> 0.086645034
A22: Self Sustained Growth Rate | C22: =C21*C20 -> -0.057087303 | D22: =D21*D20 -> 0.10169229 | E22: =E21*E20 -> 0.042020683 | F22: =F21*F20 -> 0.07430649 | G22: =G21*G20 -> 0.068760788 | I22: =AVERAGE(C22:G22) -> 0.045938591 | J22: =MEDIAN(C22:G22) -> 0.068760788
A23: Interest Coverage Ratio | B23: =('Consolidated P&L'!B6-'Consolidated P&L'!B22+'Consolidated P&L'!B15)/'Consolidated P&L'!B15 -> 20.277094 | C23: =Assumptions!B11/'Consolidated P&L'!C15 -> 27.254671 | D23: =Assumptions!C11/'Consolidated P&L'!D15 -> 34.417685 | E23: =Assumptions!D11/'Consolidated P&L'!E15 -> 17.602873 | F23: =Assumptions!E11/'Consolidated P&L'!F15 -> 17.229069 | G23: =Assumptions!F11/'Consolidated P&L'!G15 -> 9.837779 | I23: =AVERAGE(B23:G23) -> 21.103195 | J23: =MEDIAN(B23:G23) -> 18.939984
A25: Debtor Turnover Ratio | B25: ='Consolidated P&L'!B6/'Consolidated Balance sheet'!B25 -> 25.364556 | C25: ='Consolidated P&L'!C6/'Consolidated Balance sheet'!C25 -> 43.690713 | D25: ='Consolidated P&L'!D6/'Consolidated Balance sheet'!D25 -> 44.849976 | E25: ='Consolidated P&L'!E6/'Consolidated Balance sheet'!E25 -> 33.730405 | F25: ='Consolidated P&L'!F6/'Consolidated Balance sheet'!F25 -> 27.333729 | G25: ='Consolidated P&L'!G6/'Consolidated Balance sheet'!G25 -> 21.189524 | I25: =AVERAGE(B25:G25) -> 32.693151 | J25: =MEDIAN(B25:G25) -> 30.532067
A26: Creditor Turnover Ratio | B26: ='Consolidated P&L'!B6/('Consolidated Balance sheet'!B59+'Consolidated Balance sheet'!B60) -> 11.618064 | C26: ='Consolidated P&L'!C6/('Consolidated Balance sheet'!C59+'Consolidated Balance sheet'!C60) -> 11.076199 | D26: ='Consolidated P&L'!D6/('Consolidated Balance sheet'!D59+'Consolidated Balance sheet'!D60) -> 9.9441297 | E26: ='Consolidated P&L'!E6/('Consolidated Balance sheet'!E59+'Consolidated Balance sheet'!E60) -> 14.036876 | F26: ='Consolidated P&L'!F6/('Consolidated Balance sheet'!F59+'Consolidated Balance sheet'!F60) -> 10.666551 | G26: ='Consolidated P&L'!G6/('Consolidated Balance sheet'!G59+'Consolidated Balance sheet'!G60) -> 12.211701 | I26: =AVERAGE(B26:G26) -> 11.592253 | J26: =MEDIAN(B26:G26) -> 11.347132
A27: Inventory Turnover | B27: =IF('Consolidated Balance sheet'!B22=0,"",('Consolidated P&L'!B6/'Consolidated Balance sheet'!B22)) -> 12.927999 | C27: =IF('Consolidated Balance sheet'!C22=0,"",('Consolidated P&L'!C6/'Consolidated Balance sheet'!C22)) -> 14.871083 | D27: =IF('Consolidated Balance sheet'!D22=0,"",('Consolidated P&L'!D6/'Consolidated Balance sheet'!D22)) -> 10.578903 | E27: =IF('Consolidated Balance sheet'!E22=0,"",('Consolidated P&L'!E6/'Consolidated Balance sheet'!E22)) -> 11.897198 | F27: =IF('Consolidated Balance sheet'!F22=0,"",('Consolidated P&L'!F6/'Consolidated Balance sheet'!F22)) -> 9.1891868 | G27: =IF('Consolidated Balance sheet'!G22=0,"",'Consolidated P&L'!G6/'Consolidated Balance sheet'!G22) -> 7.9325849 | I27: =IFERROR(AVERAGE(B27:G27),"") -> 11.232826 | J27: =IFERROR(MEDIAN(B27:G27),"") -> 11.23805
A28: Fixed Asset Turnover | B28: ='Consolidated P&L'!B6/('Consolidated Balance sheet'!B6+'Consolidated Balance sheet'!B8) -> 1.9140357 | C28: ='Consolidated P&L'!C6/('Consolidated Balance sheet'!C6+'Consolidated Balance sheet'!C8) -> 1.7135535 | D28: ='Consolidated P&L'!D6/('Consolidated Balance sheet'!D6+'Consolidated Balance sheet'!D8) -> 1.8265208 | E28: ='Consolidated P&L'!E6/('Consolidated Balance sheet'!E6+'Consolidated Balance sheet'!E8) -> 2.2565363 | F28: ='Consolidated P&L'!F6/('Consolidated Balance sheet'!F6+'Consolidated Balance sheet'!F8) -> 1.4662597 | G28: ='Consolidated P&L'!G6/('Consolidated Balance sheet'!G6+'Consolidated Balance sheet'!G8) -> 0.97740531 | I28: =AVERAGE(B28:G28) -> 1.6923852 | J28: =MEDIAN(B28:G28) -> 1.7700372
A29: Capital Turnover Ratio | B29: ='Consolidated P&L'!B6/('Consolidated Balance sheet'!B43+'Consolidated Balance sheet'!B47+IF(ISNUMBER('Consolidated Balance sheet'!B56),'Consolidated Balance sheet'!B56,0)) -> 0.90799071 | C29: ='Consolidated P&L'!C6/('Consolidated Balance sheet'!C43+'Consolidated Balance sheet'!C47+IF(ISNUMBER('Consolidated Balance sheet'!C56),'Consolidated Balance sheet'!C56,0)) -> 0.84126327 | D29: ='Consolidated P&L'!D6/('Consolidated Balance sheet'!D43+'Consolidated Balance sheet'!D47+IF(ISNUMBER('Consolidated Balance sheet'!D56),'Consolidated Balance sheet'!D56,0)) -> 0.89008726 | E29: ='Consolidated P&L'!E6/('Consolidated Balance sheet'!E43+'Consolidated Balance sheet'!E47+IF(ISNUMBER('Consolidated Balance sheet'!E56),'Consolidated Balance sheet'!E56,0)) -> 1.0034215 | F29: ='Consolidated P&L'!F6/('Consolidated Balance sheet'!F43+'Consolidated Balance sheet'!F47+IF(ISNUMBER('Consolidated Balance sheet'!F56),'Consolidated Balance sheet'!F56,0)) -> 0.65168816 | G29: ='Consolidated P&L'!G6/('Consolidated Balance sheet'!G43+'Consolidated Balance sheet'!G47+IF(ISNUMBER('Consolidated Balance sheet'!G56),'Consolidated Balance sheet'!G56,0)) -> 0.52786073 | I29: =AVERAGE(B29:G29) -> 0.80371861 | J29: =MEDIAN(B29:G29) -> 0.86567527
A31: (In days)
A32: Debtors Day | B32: ='Consolidated Balance sheet'!B25/'Consolidated P&L'!B6*365 -> 14.390159 | C32: ='Consolidated Balance sheet'!C25/'Consolidated P&L'!C6*365 -> 8.3541781 | D32: ='Consolidated Balance sheet'!D25/'Consolidated P&L'!D6*365 -> 8.1382429 | E32: ='Consolidated Balance sheet'!E25/'Consolidated P&L'!E6*365 -> 10.821098 | F32: ='Consolidated Balance sheet'!F25/'Consolidated P&L'!F6*365 -> 13.353465 | G32: ='Consolidated Balance sheet'!G25/'Consolidated P&L'!G6*365 -> 17.225493 | I32: =AVERAGE(B32:G32) -> 12.047106 | J32: =MEDIAN(B32:G32) -> 12.087281
A33: Payable Days | B33: =('Consolidated Balance sheet'!B59+'Consolidated Balance sheet'!B60)/'Consolidated P&L'!B6*365 -> 31.416593 | C33: =('Consolidated Balance sheet'!C59+'Consolidated Balance sheet'!C60)/'Consolidated P&L'!C6*365 -> 32.953542 | D33: =('Consolidated Balance sheet'!D59+'Consolidated Balance sheet'!D60)/'Consolidated P&L'!D6*365 -> 36.705072 | E33: =('Consolidated Balance sheet'!E59+'Consolidated Balance sheet'!E60)/'Consolidated P&L'!E6*365 -> 26.002937 | F33: =('Consolidated Balance sheet'!F59+'Consolidated Balance sheet'!F60)/'Consolidated P&L'!F6*365 -> 34.219121 | G33: =('Consolidated Balance sheet'!G59+'Consolidated Balance sheet'!G60)/'Consolidated P&L'!G6*365 -> 29.889366 | I33: =AVERAGE(B33:G33) -> 31.864439 | J33: =MEDIAN(B33:G33) -> 32.185068
A34: Inventory Days | B34: =IF('Consolidated Balance sheet'!B22=0,0,'Consolidated Balance sheet'!B22/'Consolidated P&L'!B6*365) -> 28.233294 | C34: =IF('Consolidated Balance sheet'!C22=0,0,'Consolidated Balance sheet'!C22/'Consolidated P&L'!C6*365) -> 24.544278 | D34: =IF('Consolidated Balance sheet'!D22=0,0,'Consolidated Balance sheet'!D22/'Consolidated P&L'!D6*365) -> 34.502632 | E34: =IF('Consolidated Balance sheet'!E22=0,0,'Consolidated Balance sheet'!E22/'Consolidated P&L'!E6*365) -> 30.679493 | F34: =IF('Consolidated Balance sheet'!F22=0,0,'Consolidated Balance sheet'!F22/'Consolidated P&L'!F6*365) -> 39.720599 | G34: =IF('Consolidated Balance sheet'!G22=0,0,'Consolidated Balance sheet'!G22/'Consolidated P&L'!G6*365) -> 46.012744 | I34: =AVERAGE(B34:G34) -> 33.94884 | J34: =MEDIAN(B34:G34) -> 32.591063
A35: Cash Conversion Cycle | B35: =B32+B34-B33 -> 11.20686 | C35: =C32+C34-C33 -> -0.055086092 | D35: =D32+D34-D33 -> 5.9358025 | E35: =E32+E34-E33 -> 15.497654 | F35: =F32+F34-F33 -> 18.854942 | G35: =G32+G34-G33 -> 33.348871 | I35: =AVERAGE(B35:G35) -> 14.131507 | J35: =MEDIAN(B35:G35) -> 13.352257
A37: CFO/Sales | C37: ='Consolidated Cash Flow'!B48/'Consolidated P&L'!C6 -> 0.1971095 | D37: ='Consolidated Cash Flow'!C48/'Consolidated P&L'!D6 -> 0.18329279 | E37: ='Consolidated Cash Flow'!D48/'Consolidated P&L'!E6 -> 0.018874578 | F37: ='Consolidated Cash Flow'!E48/'Consolidated P&L'!F6 -> 0.1702618 | G37: ='Consolidated Cash Flow'!F48/'Consolidated P&L'!G6 -> 0.066394739 | I37: =AVERAGE(C37:G37) -> 0.12718668 | J37: =MEDIAN(C37:G37) -> 0.1702618
A38: CFO/Total Assets | C38: ='Consolidated Cash Flow'!B48/'Consolidated Balance sheet'!C35 -> 0.12165873 | D38: ='Consolidated Cash Flow'!C48/'Consolidated Balance sheet'!D35 -> 0.11744038 | E38: ='Consolidated Cash Flow'!D48/'Consolidated Balance sheet'!E35 -> 0.014209189 | F38: ='Consolidated Cash Flow'!E48/'Consolidated Balance sheet'!F35 -> 0.086462624 | G38: ='Consolidated Cash Flow'!F48/'Consolidated Balance sheet'!G35 -> 0.027640233 | I38: =AVERAGE(C38:G38) -> 0.073482231 | J38: =MEDIAN(C38:G38) -> 0.086462624
A39: CFO/Total Debt | C39: =IF('Consolidated Balance sheet'!C47+IF(ISNUMBER('Consolidated Balance sheet'!C56),'Consolidated Balance sheet'!C56,0)=0,"",'Consolidated Cash Flow'!B48/('Consolidated Balance sheet'!C47+IF(ISNUMBER('Consolidated Balance sheet'!C56),'Consolidated Balance sheet'!C56,0))) -> 110.83417 | D39: =IF('Consolidated Balance sheet'!D47+IF(ISNUMBER('Consolidated Balance sheet'!D56),'Consolidated Balance sheet'!D56,0)=0,"",'Consolidated Cash Flow'!C48/('Consolidated Balance sheet'!D47+IF(ISNUMBER('Consolidated Balance sheet'!D56),'Consolidated Balance sheet'!D56,0))) -> 122.04966 | E39: =IF('Consolidated Balance sheet'!E47+'Consolidated Balance sheet'!E56=0,"",'Consolidated Cash Flow'!D48/('Consolidated Balance sheet'!E47+'Consolidated Balance sheet'!E56)) -> 15.403899 | F39: =IF('Consolidated Balance sheet'!F47+'Consolidated Balance sheet'!F56=0,"",'Consolidated Cash Flow'!E48/('Consolidated Balance sheet'!F47+'Consolidated Balance sheet'!F56)) -> 153.50245 | G39: =IF('Consolidated Balance sheet'!G47+'Consolidated Balance sheet'!G56=0,"",'Consolidated Cash Flow'!F48/('Consolidated Balance sheet'!G47+'Consolidated Balance sheet'!G56)) -> 83.420955 | I39: =IFERROR(AVERAGE(C39:G39),"") -> 97.042226 | J39: =IFERROR(MEDIAN(C39:G39),"") -> 110.83417

Sheet Fixed Asset Scheduled
A1: Particular | B1: Dec 31, 2020 | C1: Dec 31, 2021 | D1: Mar 31, 2023 | E1: Mar 31, 2024 | F1: Mar 31, 2025
A2: Beginning balance | B2: ='Consolidated Balance sheet'!B6 -> 12605.99 | C2: =B6 -> 11885.36 | D2: =C6 -> 13661.89 | E2: =D6 -> 14729.35 | F2: =E6 -> 19956.67
A3: Add: Net Purchases | B3: =B6+B5-B2 -> 441.15 | C3: =C6+C5-C2 -> 2929.02 | D3: =D6+D5-D2 -> 2712.13 | E3: =E6+E5-E2 -> 6850.7 | F3: =F6+F5-F2 -> 7177.96
A4: Total Fixed Assets | B4: =B2+B3 -> 13047.14 | C4: =C2+C3 -> 14814.38 | D4: =D2+D3 -> 16374.02 | E4: =E2+E3 -> 21580.05 | F4: =F2+F3 -> 27134.63
A5: Less: Depreciation | B5: =Assumptions!B10 -> 1161.78 | C5: =Assumptions!C10 -> 1152.49 | D5: =Assumptions!D10 -> 1644.67 | E5: =Assumptions!E10 -> 1623.38 | F5: =Assumptions!F10 -> 2478.34
A6: Closing Balance(Fixed Asests ) | B6: ='Consolidated Balance sheet'!C6 -> 11885.36 | C6: ='Consolidated Balance sheet'!D6 -> 13661.89 | D6: ='Consolidated Balance sheet'!E6 -> 14729.35 | E6: ='Consolidated Balance sheet'!F6 -> 19956.67 | F6: ='Consolidated Balance sheet'!G6 -> 24656.29
A8: Net Capital expenditure | B8: =B3-B5 -> -720.63 | C8: =C3-C5 -> 1776.53 | D8: =D3-D5 -> 1067.46 | E8: =E3-E5 -> 5227.32 | F8: =F3-F5 -> 4699.62
A9: Net Capital expenditure / Sales percentage | B9: =B8/Assumptions!B3 -> -0.029394069 | C9: =C8/Assumptions!C3 -> 0.061332705 | D9: =D8/Assumptions!D3 -> 0.027415034 | E9: =E8/Assumptions!E3 -> 0.15764104 | F9: =F8/Assumptions!F3 -> 0.13946412
A11: Median Capital expenditure /Sales percentage | B11: =MEDIAN(B9:F9) -> 0.061332705
A12: Average Capital expenditure /Sales percentage | B12: =AVERAGE(B9:F9) -> 0.071291765

Sheet Change in working capital
A1: Particular | B1: Dec 31, 2020 | C1: Dec 31, 2021 | D1: Mar 31, 2023 | E1: Mar 31, 2024 | F1: Mar 31, 2025
A2: Inventory | B2: ='Consolidated Balance sheet'!C22 -> 1648.58 | C2: ='Consolidated Balance sheet'!D22 -> 2738.04 | D2: ='Consolidated Balance sheet'!E22 -> 3272.79 | E2: ='Consolidated Balance sheet'!F22 -> 3608.55 | F2: ='Consolidated Balance sheet'!G22 -> 4248.01
A3: Trade Receivables | B3: ='Consolidated Balance sheet'!C25 -> 561.13 | C3: ='Consolidated Balance sheet'!D25 -> 645.83 | D3: ='Consolidated Balance sheet'!E25 -> 1154.36 | E3: ='Consolidated Balance sheet'!F25 -> 1213.14 | F3: ='Consolidated Balance sheet'!G25 -> 1590.3
A4: Trade Payable | B4: ='Consolidated Balance sheet'!C59+'Consolidated Balance sheet'!C60 -> 2213.41 | C4: ='Consolidated Balance sheet'!D59+'Consolidated Balance sheet'!D60 -> 2912.82 | D4: ='Consolidated Balance sheet'!E59+'Consolidated Balance sheet'!E60 -> 2773.91 | E4: ='Consolidated Balance sheet'!F59+'Consolidated Balance sheet'!F60 -> 3108.75 | F4: ='Consolidated Balance sheet'!G59+'Consolidated Balance sheet'!G60 -> 2759.46
A5: Non Cash working Capital | B5: =B2+B3-B4 -> -3.7 | C5: =C2+C3-C4 -> 471.05 | D5: =D2+D3-D4 -> 1653.24 | E5: =E2+E3-E4 -> 1712.94 | F5: =F2+F3-F4 -> 3078.85
A6: Change in Working Capital | C6: =C5-B5 -> 474.75 | D6: =D5-C5 -> 1182.19 | E6: =E5-D5 -> 59.7 | F6: =F5-E5 -> 1365.91
A7: change in working Capital /percentage of sales | C7: =C6/Assumptions!C3 -> 0.016390211 | D7: =D6/Assumptions!D3 -> 0.030361586 | E7: =E6/Assumptions!E3 -> 0.0018003814 | F7: =F6/Assumptions!F3 -> 0.04053422
A9: Median Non Cash working Capital /Sales percentage | B9: =MEDIAN(B5:F5)/MEDIAN(Assumptions!B3:F3) -> 0.049856995
A10: Average Non Cash working Capital /Sales percentage | B10: =AVERAGE(B5:F5)/AVERAGE(Assumptions!B3:F3) -> 0.043398754

Sheet FCFF
A1: Particular | B1: Dec 31, 2020 | C1: Dec 31, 2021 | D1: Mar 31, 2023 | E1: Mar 31, 2024 | F1: Mar 31, 2025
A2: EBIT | B2: =Assumptions!B11 -> 3821.65 | C2: =Assumptions!C11 -> 5013.28 | D2: =Assumptions!D11 -> 3430.8 | E2: =Assumptions!E11 -> 4761.77 | F2: =Assumptions!F11 -> 2124.37
A3: Less: Tax on EBIT | B3: =B2*Assumptions!$G$34 -> 778.22024 | C3: =C2*Assumptions!$G$34 -> 1020.8774 | D3: =D2*Assumptions!$G$34 -> 698.62965 | E3: =E2*Assumptions!$G$34 -> 969.66121 | F3: =F2*Assumptions!$G$34 -> 432.59527
A4: EBIT * (1- Tax) NOPAT | B4: =B2-B3 -> 3043.4298 | C4: =C2-C3 -> 3992.4026 | D4: =D2-D3 -> 2732.1704 | E4: =E2-E3 -> 3792.1088 | F4: =F2-F3 -> 1691.7747
A5: Less: Net Capital expenditure | C5: ='Fixed Asset Scheduled'!C8 -> 1776.53 | D5: ='Fixed Asset Scheduled'!D8 -> 1067.46 | E5: ='Fixed Asset Scheduled'!E8 -> 5227.32 | F5: ='Fixed Asset Scheduled'!F8 -> 4699.62
A6: Less: Net Change in working Capital | C6: ='Change in working capital'!C6 -> 474.75 | D6: ='Change in working capital'!D6 -> 1182.19 | E6: ='Change in working capital'!E6 -> 59.7 | F6: ='Change in working capital'!F6 -> 1365.91
A7: Reinvestment | C7: =C5+C6 -> 2251.28 | D7: =D5+D6 -> 2249.65 | E7: =E5+E6 -> 5287.02 | F7: =F5+F6 -> 6065.53
A8: Free Cash Flow | C8: =C4-C7 -> 1741.1226 | D8: =D4-D7 -> 482.52035 | E8: =E4-E7 -> -1494.9112 | F8: =F4-F7 -> -4373.7553
A10: Reinvestment Rate | C10: =IF(C4=0,"",C7/C4) -> 0.56389102 | D10: =IF(D4=0,"",D7/D4) -> 0.82339302 | E10: =IF(E4=0,"",E7/E4) -> 1.3942163 | F10: =IF(F4=0,"",F7/F4) -> 3.585306
A12: Median Reinvestment rate /Sales percentage | B12: =MEDIAN(C10:F10) -> 1.1088047
A13: Average Reinvestment rate /Sales percentage | B13: =AVERAGE(C10:F10) -> 1.5917016

Sheet Assumptions
A1: Ambuja Cement
A2: Particulars (in RS Cr.) | B2: Dec 20 | C2: Dec 21 | D2: Mar 23 | E2: Mar 24 | F2: Mar 25
A3: Revenue from operations | B3: ='Consolidated P&L'!C6 -> 24516.17 | C3: ='Consolidated P&L'!D6 -> 28965.46 | D3: ='Consolidated P&L'!E6 -> 38937.03 | E3: ='Consolidated P&L'!F6 -> 33159.64 | F3: ='Consolidated P&L'!G6 -> 33697.7
A4: Revenue growth in % | B4: =(B3-'Consolidated P&L'!B6)/'Consolidated P&L'!B6 -> -0.095462771 | C4: =(C3-'Consolidated P&L'!C6)/'Consolidated P&L'!C6 -> 0.18148389 | D4: =(D3-'Consolidated P&L'!D6)/'Consolidated P&L'!D6 -> 0.34425726 | E4: =(E3-'Consolidated P&L'!E6)/'Consolidated P&L'!E6 -> -0.14837778 | F4: =(F3-'Consolidated P&L'!F6)/'Consolidated P&L'!F6 -> 0.016226352
A5: Less: Material cost | B5: ='Consolidated P&L'!C12+'Consolidated P&L'!C13+'Consolidated P&L'!C11+'Consolidated P&L'!C17+'Consolidated P&L'!C18 -> 14223.42 | C5: ='Consolidated P&L'!D12+'Consolidated P&L'!D13+'Consolidated P&L'!D11+'Consolidated P&L'!D17+'Consolidated P&L'!D18 -> 16882.7 | D5: ='Consolidated P&L'!E12+'Consolidated P&L'!E13+'Consolidated P&L'!E11+'Consolidated P&L'!E17+'Consolidated P&L'!E18 -> 26396.53 | E5: ='Consolidated P&L'!F12+'Consolidated P&L'!F13+'Consolidated P&L'!F11+'Consolidated P&L'!F17+'Consolidated P&L'!F18 -> 21032.73 | F5: ='Consolidated P&L'!G12+'Consolidated P&L'!G13+'Consolidated P&L'!G11+'Consolidated P&L'!G17+'Consolidated P&L'!G18 -> 23176.45
A6: Less: Employee costs | B6: ='Consolidated P&L'!C14 -> 1540.4 | C6: ='Consolidated P&L'!D14 -> 1529.15 | D6: ='Consolidated P&L'!E14 -> 1856.53 | E6: ='Consolidated P&L'!F14 -> 1352.79 | F6: ='Consolidated P&L'!G14 -> 1403.41
A7: Less: Other Expenses | B7: ='Consolidated P&L'!C19 -> 3768.92 | C7: ='Consolidated P&L'!D19 -> 4387.84 | D7: ='Consolidated P&L'!E19 -> 5608.5 | E7: ='Consolidated P&L'!F19 -> 4388.97 | F7: ='Consolidated P&L'!G19 -> 4515.13
A8: Total Expenses | B8: =B5+B6+B7 -> 19532.74 | C8: =C5+C6+C7 -> 22799.69 | D8: =D5+D6+D7 -> 33861.56 | E8: =E5+E6+E7 -> 26774.49 | F8: =F5+F6+F7 -> 29094.99
A9: EBITDA | B9: =B3-B8 -> 4983.43 | C9: =C3-C8 -> 6165.77 | D9: =D3-D8 -> 5075.47 | E9: =E3-E8 -> 6385.15 | F9: =F3-F8 -> 4602.71
A10: Less: Depreciation And Amortization | B10: ='Consolidated P&L'!C16 -> 1161.78 | C10: ='Consolidated P&L'!D16 -> 1152.49 | D10: ='Consolidated P&L'!E16 -> 1644.67 | E10: ='Consolidated P&L'!F16 -> 1623.38 | F10: ='Consolidated P&L'!G16 -> 2478.34
A11: EBIT | B11: =B9-B10 -> 3821.65 | C11: =C9-C10 -> 5013.28 | D11: =D9-D10 -> 3430.8 | E11: =E9-E10 -> 4761.77 | F11: =F9-F10 -> 2124.37
A12: ADD: Non operating income/ Other Income | B12: ='Consolidated P&L'!C8 -> 449.59 | C12: ='Consolidated P&L'!D8 -> 352.44 | D12: ='Consolidated P&L'!E8 -> 737.71 | E12: ='Consolidated P&L'!F8 -> 1166.4 | F12: ='Consolidated P&L'!G8 -> 2654.25
A13: Less: Interest Expenses | B13: ='Consolidated P&L'!C15 -> 140.22 | C13: ='Consolidated P&L'!D15 -> 145.66 | D13: ='Consolidated P&L'!E15 -> 194.9 | E13: ='Consolidated P&L'!F15 -> 276.38 | F13: ='Consolidated P&L'!G15 -> 215.94
A14: EBT | B14: ='Consolidated P&L'!C27 -> 3991.59 | C14: ='Consolidated P&L'!D27 -> 5164.47 | D14: ='Consolidated P&L'!E27 -> 3729.49 | E14: ='Consolidated P&L'!F27 -> 5900.62 | F14: ='Consolidated P&L'!G27 -> 5922.37
A15: Less: TAX | B15: ='Consolidated P&L'!C32 -> 884.75 | C15: ='Consolidated P&L'!D32 -> 1453.43 | D15: ='Consolidated P&L'!E32 -> 705.11 | E15: ='Consolidated P&L'!F32 -> 1162.61 | F15: ='Consolidated P&L'!G32 -> 763.96
A16: Less:Non Controlling Interest/Minority Interest | B16: ='Consolidated P&L'!C44 -> 741.4 | C16: ='Consolidated P&L'!D44 -> 930.66 | D16: ='Consolidated P&L'!E44 -> 440.98 | E16: ='Consolidated P&L'!F44 -> 1161.22 | F16: ='Consolidated P&L'!G44 -> 990.98
A17: Net Profit- Pat | B17: =B14-B15-B16 -> 2365.44 | C17: =C14-C15-C16 -> 2780.38 | D17: =D14-D15-D16 -> 2583.4 | E17: =E14-E15-E16 -> 3576.79 | F17: =F14-F15-F16 -> 4167.43
A23: Historical Growth
A24: Average Growth | B24: =AVERAGE(B4:F4) -> 0.059625392
A25: CAGR | B25: =(F3/B3)^(1/5)-1 -> 0.065686654 | C25: =_xlfn.RRI(5,B3,F3) -> 0.065686654 | D25: RRI
A27: Margins
A28: EBITDA | B28: =C9/C3 -> 0.21286629 | C28: =B9/B3 -> 0.20327115 | D28: =D9/D3 -> 0.13035072 | E28: =E9/E3 -> 0.19255788 | F28: =F9/F3 -> 0.13658825
A29: EBIT | B29: =C11/C3 -> 0.17307787 | C29: =B11/B3 -> 0.15588283 | D29: =D11/D3 -> 0.088111497 | E29: =E11/E3 -> 0.14360138 | F29: =F11/F3 -> 0.063041988 | G29: =AVERAGE(B29:F29) -> 0.12474311
A30: EBT | B30: =C14/C3 -> 0.17829753 | C30: =B14/B3 -> 0.16281458 | D30: =D14/D3 -> 0.095782601 | E30: =E14/E3 -> 0.17794584 | F30: =F14/F3 -> 0.17574998
A31: Net Proftt | B31: =C17/C3 -> 0.095989499 | C31: =B17/B3 -> 0.096484891 | D31: =D17/D3 -> 0.066348152 | E31: =E17/E3 -> 0.10786577 | F31: =F17/F3 -> 0.12367105
A33: Tax Rate
A34: Effective tax rate | B34: =C15/C14 -> 0.28142868 | C34: =B15/B14 -> 0.22165353 | D34: =D15/D14 -> 0.18906338 | E34: =E15/E14 -> 0.19703184 | F34: =F15/F14 -> 0.12899566 | G34: =AVERAGE(B34:F34) -> 0.20363462 | H34: Effective tax rate
A35: Marginal Tax rate | B35: 0.25 | C35: =B35 -> 0.25 | D35: =C35 -> 0.25 | E35: =D35 -> 0.25 | F35: =E35 -> 0.25
A37: Return On Capital
A38: EBIT*(1-T) | B38: =C11*(1-B35) -> 3759.96 | C38: =B11*(1-C35) -> 2866.2375 | D38: =D11*(1-D35) -> 2573.1 | E38: =E11*(1-E35) -> 3571.3275 | F38: =F11*(1-F35) -> 1593.2775
A39: Book Equity | B39: ='Consolidated Balance sheet'!D43 -> 32498.77 | C39: ='Consolidated Balance sheet'!C43 -> 29098.49 | D39: ='Consolidated Balance sheet'!E43 -> 38756.55 | E39: ='Consolidated Balance sheet'!F43 -> 50845.9 | F39: ='Consolidated Balance sheet'!G43 -> 63811.42
A40: Book Debt | B40: ='Consolidated Balance sheet'!D47+0 -> 43.5 | C40: ='Consolidated Balance sheet'!C47+0 -> 43.6 | D40: ='Consolidated Balance sheet'!E47+'Consolidated Balance sheet'!E56 -> 47.71 | E40: ='Consolidated Balance sheet'!F47+'Consolidated Balance sheet'!F56 -> 36.78 | F40: ='Consolidated Balance sheet'!G47+'Consolidated Balance sheet'!G56 -> 26.82
A41: Cash and Cash equivalents | B41: ='Consolidated Balance sheet'!D26 -> 11358.49 | C41: ='Consolidated Balance sheet'!C26 -> 8571.56 | D41: ='Consolidated Balance sheet'!E26 -> 543.87 | E41: ='Consolidated Balance sheet'!F26 -> 3007.1 | F41: ='Consolidated Balance sheet'!G26 -> 5043.32
A42: Capital Employed | B42: =B39+B40-B41 -> 21183.78 | C42: =C39+C40-C41 -> 20570.53 | D42: =D39+D40-D41 -> 38260.39 | E42: =E39+E40-E41 -> 47875.58 | F42: =F39+F40-F41 -> 58794.92
A44: Pre-Tax Return on capital | B44: =C11/B42 -> 0.23665654 | C44: =B11/C42 -> 0.18578277 | D44: =D11/D42 -> 0.08966976 | E44: =E11/E42 -> 0.099461354 | F44: =F11/F42 -> 0.036131863
A45: Post Tax return On capital | B45: =B38/B42 -> 0.1774924 | C45: =C38/C42 -> 0.13933708 | D45: =D38/D42 -> 0.06725232 | E45: =E38/E42 -> 0.074596015 | F45: =F38/F42 -> 0.027098897
A47: Growth In EBIT | B47: =FCFF!B12*Assumptions!F45 -> 0.030047384

Sheet Growth Scenario
A1: Scenario 1: High Growth
A2: INR Cr. | B2: LTM | C2: Y1E | D2: Y2E | E2: Y3E | F2: Y4W | G2: Y5E | H2: Y6E | I2: Y7E | J2: Y8E | K2: Y9E | L2: Y10E
A3: Sales | B3: =Assumptions!F3 -> 33697.7 | C3: =B3*(1+C4) -> 35911.189 | D3: =C3*(1+D4) -> 38238.101 | E3: =D3*(1+E4) -> 40681.741 | F3: =E3*(1+F4) -> 43245.323 | G3: =F3*(1+G4) -> 45931.946 | H3: =G3*(1+H4) -> 48744.58 | I3: =H3*(1+I4) -> 51686.043 | J3: =I3*(1+J4) -> 54758.988 | ... L3: =K3*(1+L4) -> 61308.959 | M3: =Assumptions!B25 -> 0.065686654 | P3: Risk free rate
A4: Sales Growth % | C4: =M3 -> 0.065686654 | D4: =C4+$O$4 -> 0.064796283 | E4: =D4+$O$4 -> 0.063905911 | F4: =E4+$O$4 -> 0.063015539 | G4: =F4+$O$4 -> 0.062125167 | H4: =G4+$O$4 -> 0.061234796 | I4: =H4+$O$4 -> 0.060344424 | J4: =I4+$O$4 -> 0.059454052 | K4: =J4+$O$4 -> 0.05856368 | L4: =K4+$O$4 -> 0.057673309 | M4: 0.0737 | N4: =M3-M4 -> -0.0080133457 | O4: =N4/9 -> -0.00089037175 | P4: =M4 -> 0.0737
A6: Scenario 2: Average Growth
A7: INR Cr. | B7: LTM | C7: Y1E | D7: Y2E | E7: Y3E | F7: Y4W | G7: Y5E | H7: Y6E | I7: Y7E | J7: Y8E | K7: Y9E | L7: Y10E | M7: Average rate | N7: =Assumptions!B24 -> 0.059625392
A8: Sales | B8: =B3 -> 33697.7 | C8: =B8*(1+C9) -> 35706.939 | D8: =C8*(1+D9) -> 37780.139 | E8: =D8*(1+E9) -> 39914.63 | F8: =E8*(1+F9) -> 42107.294 | G8: =F8*(1+G9) -> 44354.561 | H8: =G8*(1+H9) -> 46652.401 | I8: =H8*(1+I9) -> 48996.325 | J8: =I8*(1+J9) -> 51381.392 | ... L8: =K8*(1+L9) -> 56252.94 | N8: =M4 -> 0.0737 | O8: =N7-N8 -> -0.014074608 | P8: =O8/9 -> -0.0015638453
A9: Sales Growth % | C9: =N7 -> 0.059625392 | D9: =C9+$P$8 -> 0.058061547 | E9: =D9+$P$8 -> 0.056497701 | F9: =E9+$P$8 -> 0.054933856 | G9: =F9+$P$8 -> 0.053370011 | H9: =G9+$P$8 -> 0.051806165 | I9: =H9+$P$8 -> 0.05024232 | J9: =I9+$P$8 -> 0.048678475 | K9: =J9+$P$8 -> 0.047114629 | L9: =K9+$P$8 -> 0.045550784
A11: Scenario 3: EBIT Growth
A12: INR Cr. | B12: LTM | C12: Y1E | D12: Y2E | E12: Y3E | F12: Y4W | G12: Y5E | H12: Y6E | I12: Y7E | J12: Y8E | K12: Y9E | L12: Y10E | N12: =Assumptions!B47 -> 0.030047384
A13: Sales | B13: =B8 -> 33697.7 | C13: =B13*(1+C14) -> 34710.228 | D13: =C13*(1+D14) -> 35584.825 | E13: =D13*(1+E14) -> 36308.862 | F13: =E13*(1+F14) -> 36871.523 | G13: =F13*(1+G14) -> 37264.065 | H13: =G13*(1+H14) -> 37480.045 | I13: =H13*(1+I14) -> 37515.488 | J13: =I13*(1+J14) -> 37369.003 | ... L13: =K13*(1+L14) -> 36537.877 | N13: =N8 -> 0.0737 | O13: =N12-N13 -> -0.043652616 | P13: =O13/9 -> -0.0048502907
A14: Sales Growth % | C14: =N12 -> 0.030047384 | D14: =C14+($P$13) -> 0.025197093 | E14: =D14+($P$13) -> 0.020346803 | F14: =E14+($P$13) -> 0.015496512 | G14: =F14+($P$13) -> 0.010646221 | H14: =G14+($P$13) -> 0.0057959308 | I14: =H14+($P$13) -> 0.00094564009 | J14: =I14+($P$13) -> -0.0039046506 | K14: =J14+($P$13) -> -0.0087549412 | L14: =K14+($P$13) -> -0.013605232 | P14: 0.00294
A16: Live Scenario | B16: 1
A17: INR Cr. | C17: Y1E | D17: Y2E | E17: Y3E | F17: Y4W | G17: Y5E | H17: Y6E | I17: Y7E | J17: Y8E | K17: Y9E | L17: Y10E
A18: Sales | B18: =B13 -> 33697.7 | C18: =B18*(1+C19) -> 35911.189 | D18: =C18*(1+D19) -> 38238.101 | E18: =D18*(1+E19) -> 40681.741 | F18: =E18*(1+F19) -> 43245.323 | G18: =F18*(1+G19) -> 45931.946 | H18: =G18*(1+H19) -> 48744.58 | I18: =H18*(1+I19) -> 51686.043 | J18: =I18*(1+J19) -> 54758.988 | ... L18: =K18*(1+L19) -> 61308.959
A19: Sales Growth % | C19: =CHOOSE($B$16,C4,C9,C14) -> 0.065686654 | D19: =CHOOSE($B$16,D4,D9,D14) -> 0.064796283 | E19: =CHOOSE($B$16,E4,E9,E14) -> 0.063905911 | F19: =CHOOSE($B$16,F4,F9,F14) -> 0.063015539 | G19: =CHOOSE($B$16,G4,G9,G14) -> 0.062125167 | H19: =CHOOSE($B$16,H4,H9,H14) -> 0.061234796 | I19: =CHOOSE($B$16,I4,I9,I14) -> 0.060344424 | J19: =CHOOSE($B$16,J4,J9,J14) -> 0.059454052 | ... L19: =CHOOSE($B$16,L4,L9,L14) -> 0.057673309

Sheet Forecasting
C3: Sales Forecasting | H3: EBITDA Forecasting | M3: Earning per share Forecasting
C4: Year Weight | D4: Year | E4: Sales | F4: Sales Growth | H4: Year Weight | I4: Year | J4: EBITDA | K4: EBITDA Growth | M4: Year Weight | N4: Year | O4: EPS | P4: EPS Growth
C5: 1 | D5: =DATE(2019,12,31) -> 43830 | E5: ='Consolidated P&L'!B6 -> 27103.55 | H5: 1 | I5: =DATE(2019,12,31) -> 43830 | J5: ='Consolidated P&L'!B6-('Consolidated P&L'!B11+'Consolidated P&L'!B12+'Consolidated P&L'!B13+'Consolidated P&L'!B17+'Consolidated P&L'!B18+'Consolidated P&L'!B14+'Consolidated P&L'!B19) -> 4588.52 | M5: 1 | N5: =DATE(2019,12,31) -> 43830 | O5: ='Consolidated P&L'!B52 -> 10.55
C6: =C5+1 -> 2 | D6: =D5+365 -> 44195 | E6: =Assumptions!B3 -> 24516.17 | F6: =(E6-E5)/E5 -> -0.095462771 | H6: =H5+1 -> 2 | I6: =I5+365 -> 44195 | J6: =Assumptions!B9 -> 4983.43 | K6: =(J6-J5)/J5 -> 0.086064788 | M6: =M5+1 -> 2 | N6: =N5+365 -> 44195 | O6: ='Consolidated P&L'!C52 -> 11.91 | P6: =(O6-O5)/O5 -> 0.12890995
C7: =C6+1 -> 3 | D7: =D6+365 -> 44560 | E7: =Assumptions!C3 -> 28965.46 | F7: =(E7-E6)/E6 -> 0.18148389 | H7: =H6+1 -> 3 | I7: =I6+365 -> 44560 | J7: =Assumptions!C9 -> 6165.77 | K7: =(J7-J6)/J6 -> 0.23725426 | M7: =M6+1 -> 3 | N7: =N6+365 -> 44560 | O7: ='Consolidated P&L'!D52 -> 14 | P7: =(O7-O6)/O6 -> 0.17548279
C8: =C7+1 -> 4 | D8: =D7+365 -> 44925 | E8: =Assumptions!D3 -> 38937.03 | F8: =(E8-E7)/E7 -> 0.34425726 | H8: =H7+1 -> 4 | I8: =I7+365 -> 44925 | J8: =Assumptions!D9 -> 5075.47 | K8: =(J8-J7)/J7 -> -0.17683112 | M8: =M7+1 -> 4 | N8: =N7+365 -> 44925 | O8: ='Consolidated P&L'!E52 -> 13.01 | P8: =(O8-O7)/O7 -> -0.070714286
C9: =C8+1 -> 5 | D9: =D8+365 -> 45290 | E9: =Assumptions!E3 -> 33159.64 | F9: =(E9-E8)/E8 -> -0.14837778 | H9: =H8+1 -> 5 | I9: =I8+365 -> 45290 | J9: =Assumptions!E9 -> 6385.15 | K9: =(J9-J8)/J8 -> 0.25804113 | M9: =M8+1 -> 5 | N9: =N8+365 -> 45290 | O9: ='Consolidated P&L'!F52 -> 17.99 | P9: =(O9-O8)/O8 -> 0.38278248
C10: =C9+1 -> 6 | D10: =D9+365 -> 45655 | E10: =Assumptions!F3 -> 33697.7 | F10: =(E10-E9)/E9 -> 0.016226352 | H10: =H9+1 -> 6 | I10: =I9+365 -> 45655 | J10: =Assumptions!F9 -> 4602.71 | K10: =(J10-J9)/J9 -> -0.27915397 | M10: =M9+1 -> 6 | N10: =N9+365 -> 45655 | O10: ='Consolidated P&L'!G52 -> 17 | P10: =(O10-O9)/O9 -> -0.055030573
C11: =C10+1 -> 7 | D11: =D10+365 -> 46020 | E11: =FORECAST(C11,$E$5:$E$10,$C$5:$C$10) -> 37950.531 | F11: =(E11-E10)/E10 -> 0.12620539 | H11: =H10+1 -> 7 | I11: =I10+365 -> 46020 | J11: =FORECAST(H11,$J$5:$J$10,$H$5:$H$10) -> 5618.756 | K11: =(J11-J10)/J10 -> 0.22074951 | M11: =M10+1 -> 7 | N11: =N10+365 -> 46020 | O11: =FORECAST(M11,$O$5:$O$10,$M$5:$M$10) -> 19.026667 | P11: =(O11-O10)/O10 -> 0.11921569
C12: =C11+1 -> 8 | D12: =D11+365 -> 46385 | E12: =FORECAST(C12,$E$5:$E$10,$C$5:$C$10) -> 39918.324 | F12: =(E12-E11)/E11 -> 0.051851508 | H12: =H11+1 -> 8 | I12: =I11+365 -> 46385 | J12: =FORECAST(H12,$J$5:$J$10,$H$5:$H$10) -> 5709.7791 | K12: =(J12-J11)/J11 -> 0.016199875 | M12: =M11+1 -> 8 | N12: =N11+365 -> 46385 | O12: =FORECAST(M12,$O$5:$O$10,$M$5:$M$10) -> 20.440952 | P12: =(O12-O11)/O11 -> 0.074331765
C13: =C12+1 -> 9 | D13: =D12+365 -> 46750 | E13: =FORECAST(C13,$E$5:$E$10,$C$5:$C$10) -> 41886.116 | F13: =(E13-E12)/E12 -> 0.049295464 | H13: =H12+1 -> 9 | I13: =I12+365 -> 46750 | J13: =FORECAST(H13,$J$5:$J$10,$H$5:$H$10) -> 5800.8023 | K13: =(J13-J12)/J12 -> 0.015941622 | M13: =M12+1 -> 9 | N13: =N12+365 -> 46750 | O13: =FORECAST(M13,$O$5:$O$10,$M$5:$M$10) -> 21.855238 | P13: =(O13-O12)/O12 -> 0.069188837
C14: =C13+1 -> 10 | D14: =D13+365 -> 47115 | E14: =FORECAST(C14,$E$5:$E$10,$C$5:$C$10) -> 43853.908 | F14: =(E14-E13)/E13 -> 0.046979584 | H14: =H13+1 -> 10 | I14: =I13+365 -> 47115 | J14: =FORECAST(H14,$J$5:$J$10,$H$5:$H$10) -> 5891.8254 | K14: =(J14-J13)/J13 -> 0.015691475 | M14: =M13+1 -> 10 | N14: =N13+365 -> 47115 | O14: =FORECAST(M14,$O$5:$O$10,$M$5:$M$10) -> 23.269524 | P14: =(O14-O13)/O13 -> 0.064711522

Sheet Relative Valuations
A1: Company | B1: Market Data | F1: Financial Data | J1: Valuation Ratios
B2: Price (₹) | C2: Shares (Cr.) | D2: Mkt Cap (Cr.) | E2: EV (Cr.) | F2: Revenue (Cr.) | G2: EBITDA (Cr.) | H2: EBIT (Cr.) | I2: EPS (₹) | J2: P/E | K2: EV/Sales | L2: EV/EBITDA | M2: EV/EBIT
A3: Ambuja Cements | B3: 416 | C3: ='Consolidated Balance sheet'!G38/2 -> 246.31 | D3: =B3*C3 -> 102464.96 | E3: =D3+'Consolidated Balance sheet'!G47+'Consolidated Balance sheet'!G48+'Consolidated Balance sheet'!G56+'Consolidated Balance sheet'!G57-'Consolidated Balance sheet'!G26-'Consolidated Balance sheet'!G27-'Consolidated Balance sheet'!G24 -> 95259.14 | F3: ='Consolidated P&L'!G6 -> 33697.7 | G3: =Assumptions!F9 -> 4602.71 | H3: =Assumptions!F11 -> 2124.37 | I3: ='Consolidated P&L'!G52 -> 17 | J3: =B3/I3 -> 24.470588 | K3: =E3/F3 -> 2.8268736 | L3: =E3/G3 -> 20.696316 | M3: =E3/H3 -> 44.841125
A4: UltraTech Cem. | B4: 10911 | C4: =295/10 -> 29.5 | D4: 321455.96 | E4: 344269 | F4: 88512 | G4: 17004 | H4: =10927+1872 -> 12799 | I4: 277.1 | J4: =B4/I4 -> 39.375677 | K4: =E4/F4 -> 3.8895178 | L4: =E4/G4 -> 20.246354 | M4: =E4/H4 -> 26.898117
A5: Shree Cement | B5: 23415 | C5: =36/10 -> 3.6 | D5: 84700.63 | E5: 86426 | F5: 20943 | G5: 4638 | H5: =2293+212 -> 2505 | I5: 483.24 | J5: =B5/I5 -> 48.454184 | K5: =E5/F5 -> 4.1267249 | L5: =E5/G5 -> 18.634325 | M5: =E5/H5 -> 34.501397
A6: J K Cements | B6: 4822 | C6: =77/10 -> 7.7 | D6: 37275.96 | E6: 43146 | F6: 13722 | G6: 2374 | H6: =1444+424 -> 1868 | I6: 128.45 | J6: =B6/I6 -> 37.539899 | K6: =E6/F6 -> 3.1442938 | L6: =E6/G6 -> 18.174389 | M6: =E6/H6 -> 23.09743
A7: Dalmia BharatLtd | B7: 1651.7 | C7: =38/2 -> 19 | D7: 31036.22 | E7: 38405 | F7: 14804 | G7: 3083 | H7: =1449+480 -> 1929 | I7: 60.73 | J7: =B7/I7 -> 27.197431 | K7: =E7/F7 -> 2.5942313 | L7: =E7/G7 -> 12.457022 | M7: =E7/H7 -> 19.909279
A8: ACC | B8: 1324.7 | C8: =188/10 -> 18.8 | D8: 24906.38 | E8: 24693 | F8: 25962 | G8: 2958 | H8: =2157+112 -> 2269 | I8: 113.8 | J8: =B8/I8 -> 11.640598 | K8: =E8/F8 -> 0.95112087 | L8: =E8/G8 -> 8.3478702 | M8: =E8/H8 -> 10.882768
A9: Peer Average | B9: =AVERAGE(B4:B8) -> 8424.88 | C9: =AVERAGE(C4:C8) -> 15.72 | D9: =AVERAGE(D4:D8) -> 99875.03 | E9: =AVERAGE(E4:E8) -> 107387.8 | F9: =AVERAGE(F4:F8) -> 32788.6 | G9: =AVERAGE(G4:G8) -> 6011.4 | H9: =AVERAGE(H4:H8) -> 4274 | I9: =AVERAGE(I4:I8) -> 212.664 | ... M9: =AVERAGE(M4:M8) -> 23.057798
A10: Peer Median | B10: =MEDIAN(B4:B8) -> 4822 | C10: =MEDIAN(C4:C8) -> 18.8 | D10: =MEDIAN(D4:D8) -> 37275.96 | E10: =MEDIAN(E4:E8) -> 43146 | F10: =MEDIAN(F4:F8) -> 20943 | G10: =MEDIAN(G4:G8) -> 3083 | H10: =MEDIAN(H4:H8) -> 2269 | I10: =MEDIAN(I4:I8) -> 128.45 | ... M10: =MEDIAN(M4:M8) -> 23.09743
A12: Ambuja — IMPLIED SHARE PRICE FROM PEER MULTIPLES
A13: Valuation Basis | B13: Peer Avg Multiple | C13: Peer Median Multiple | D13: Ambuja Actual | E13: Implied EV (Avg) | F13: Implied EV (Median) | G13: Implied Equity (Avg) | H13: Implied Equity (Median) | I13: Implied Price (Avg) ₹ | J13: Implied Price (Med) ₹ | K13: CMP ₹ | L13: Premium/Disc (vs Avg) | M13: Premium/Disc (vs Med)
A14: EV / Sales | B14: =K9 -> 2.9411777 | C14: =K10 -> 3.1442938 | D14: =K3 -> 2.8268736 | E14: =B14*F3 -> 99110.925 | F14: =C14*F3 -> 105955.47 | G14: =E14-(E3-D3) -> 106316.75 | H14: =F14-(E3-D3) -> 113161.29 | I14: =G14/C3 -> 431.63796 | J14: =H14/C3 -> 459.42629 | K14: =B3 -> 416 | L14: =(B3-I14)/I14 -> -0.036229338 | M14: =(B3-J14)/J14 -> -0.094522874
A15: EV / EBITDA | B15: =L9 -> 15.571992 | C15: =L10 -> 18.174389 | D15: =L3 -> 20.696316 | E15: =B15*G3 -> 71673.364 | F15: =C15*G3 -> 83651.443 | G15: =E15-(E3-D3) -> 78879.184 | H15: =F15-(E3-D3) -> 90857.263 | I15: =G15/C3 -> 320.24353 | J15: =H15/C3 -> 368.87363 | K15: =B3 -> 416 | L15: =(B3-I15)/I15 -> 0.29901141 | M15: =(B3-J15)/J15 -> 0.1277575
A16: P / E | B16: =J9 -> 32.841558 | C16: =J10 -> 37.539899 | D16: =J3 -> 24.470588 | E16: =B16*I3 -> 558.30648 | F16: =C16*I3 -> 638.17828 | G16: =E16*C3 -> 137516.47 | H16: =F16*C3 -> 157189.69 | I16: =E16 -> 558.30648 | J16: =F16 -> 638.17828 | K16: =K15 -> 416 | L16: =(B3-I16)/I16 -> -0.25488954 | M16: =(B3-J16)/J16 -> -0.34814453
O18: EV/Revenue | P18: EV/EBITDA | Q18: P/E Ratio
A19: Max | O19: =MAX(K4:K8) -> 4.1267249 | P19: =MAX(L4:L8) -> 20.246354 | Q19: =MAX(J4:J8) -> 48.454184
A20: 75th Percentile | O20: =QUARTILE(K4:K8,3) -> 3.8895178 | P20: =QUARTILE(L4:L8,3) -> 18.634325 | Q20: =QUARTILE(J4:J8,3) -> 39.375677
A21: Average | O21: =AVERAGE(K4:K8) -> 2.9411777 | P21: =AVERAGE(L4:L8) -> 15.571992 | Q21: =AVERAGE(J4:J8) -> 32.841558
A22: median | O22: =MEDIAN(K4:K8) -> 3.1442938 | P22: =MEDIAN(L4:L8) -> 18.174389 | Q22: =MEDIAN(J4:J8) -> 37.539899
A23: 25th Percentile | O23: =QUARTILE(K4:K8,1) -> 2.5942313 | P23: =QUARTILE(L4:L8,1) -> 12.457022 | Q23: =QUARTILE(J4:J8,1) -> 27.197431
A24: Min. | O24: =MIN(K4:K8) -> 0.95112087 | P24: =MIN(L4:L8) -> 8.3478702 | Q24: =MIN(J4:J8) -> 11.640598
A26: M&M Industry Comparable comps | O26: EV/Revenue | P26: EV/EBITDA | Q26: P/E Ratio
A27: Implied Enterprise Value | O27: =O21*F3 -> 99110.925 | P27: =P21*G3 -> 71673.364 | Q27: =Q21*I3*C3 -> 137516.47
A28: Net Debt | O28: =E3-D3 -> -7205.82 | P28: =E3-D3 -> -7205.82 | Q28: =E3-D3 -> -7205.82
A29: Implied Market Value | O29: =O27-O28 -> 106316.75 | P29: =P27-P28 -> 78879.184 | Q29: =Q27-Q28 -> 144722.29
A30: Share Outstanding | O30: =C3 -> 246.31 | P30: =C3 -> 246.31 | Q30: =C3 -> 246.31
A32: Implied Value per Share | O32: =O29/O30 -> 431.63796 | P32: =P29/P30 -> 320.24353 | Q32: =Q21*I3 -> 558.30648

Sheet Gordon Growth Model
A1: Gordon Growth Model (Dividend Discount Model) — Ambuja Cements
A2: Intrinsic Value = D1 / (Ke - g) where D1 = next year dividend, Ke = cost of equity, g = sustainable growth rate
A4: STEP 1: Historical Dividend Per Share
A5: Year | B5: FY22 (Dec21) | C5: FY23 (Mar23) | D5: FY24 (Mar24) | E5: FY25 (Mar25)
A6: Total Equity Dividend Paid (Rs Cr) | B6: =ABS('Consolidated Cash Flow'!C83) -> 202.1 | C6: =ABS('Consolidated Cash Flow'!D83) -> 1251.42 | D6: =ABS('Consolidated Cash Flow'!E83) -> 496.41 | E6: =ABS('Consolidated Cash Flow'!F83) -> 492.63
A7: Shares Outstanding (Cr) | B7: ='Consolidated Balance sheet'!D38/2 -> 198.565 | C7: ='Consolidated Balance sheet'!E38/2 -> 198.565 | D7: ='Consolidated Balance sheet'!F38/2 -> 219.77 | E7: ='Consolidated Balance sheet'!G38/2 -> 246.31
A8: Dividend Per Share - DPS (Rs) | B8: =B6/B7 -> 1.0178027 | C8: =C6/C7 -> 6.3023191 | D8: =D6/D7 -> 2.2587705 | E8: =E6/E7 -> 2.0000406
A10: STEP 2: Dividend Growth Rate (g)
A11: YoY DPS Growth | C11: =(C8-B8)/B8 -> 5.1920831 | D11: =(D8-C8)/C8 -> -0.64159693 | E11: =(E8-D8)/D8 -> -0.11454459
A12: Average Historical DPS Growth | B12: =AVERAGE(C11:E11) -> 1.4786472 | C12: (FY23 to FY25 average)
A14: Revenue CAGR (from Assumptions sheet) | B14: =Assumptions!B25 -> 0.065686654 | C14: (used as proxy for sustainable growth)
A16: Dividend Growth Rate Used (g) | B16: =G24 -> 0.08516559 | C16: DPS CAGR FY22-FY25 (conservative, based on actual dividend history)
F17: g= roe*retention ratio
A18: STEP 3: Cost of Equity (Ke) — from CAPM | F18: roe | G18: ='Consolidated P&L'!G33/('Consolidated Balance sheet'!G38+'Consolidated Balance sheet'!G39) -> 0.096521263
A19: Risk Free Rate (Rf) | B19: =Wacc!C11 -> 0.0625 | C19: RBI 10Y Gsec yield | F19: retention ratio
A20: Beta (β) | B20: =Wacc!C12 -> 1.0923358 | C20: Regression beta from Nifty50 vs Ambuja Cements | F20: dividend payout ratio formula | I20: dps/eps
A21: Market Risk Premium (Rm - Rf) | B21: =Wacc!C13 -> 0.065 | C21: India ERP (Damodaran) | I21: =E8/'Consolidated P&L'!G52 -> 0.11764945
A22: Cost of Equity Ke = Rf + β × (Rm - Rf) | B22: =Wacc!C14 -> 0.13350183 | F22: retention ratio | G22: 1-dpr | I22: =1-I21 -> 0.88235055
A24: STEP 4: Validity Check — Ke must be > g | F24: growth | G24: =G18*I22 -> 0.08516559
A25: Cost of Equity (Ke) | B25: =B22 -> 0.13350183
A26: Growth Rate (g) | B26: =B16 -> 0.08516559
A27: Ke - g (spread) | B27: =B25-B26 -> 0.048336235
A29: STEP 5: D1 — Expected Dividend Next Year
A30: D0 — Latest DPS (FY25) | B30: =E8 -> 2.0000406 | C30: FY25 actual dividend per share
A31: D1 = D0 × (1 + g) | B31: =B30*(1+B16) -> 2.1703752 | C31: Expected dividend in next year (D1)
A33: STEP 6: Intrinsic Value per Share
A34: Gordon Growth Model Formula: P = D1 / (Ke - g)
A35: Intrinsic Value (P) | B35: =B31/(B25-B26) -> 44.901619
A36: Current Market Price (CMP) | B36: ='Relative Valuations'!B3 -> 416 | C36: Ambuja CMP from Relative Valuation sheet
A37: Premium / (Discount) to Intrinsic Value | B37: =(B36-B35)/B35 -> 8.2646993 | C37: =IF(B36>B35,"Stock is OVERVALUED vs GGM","Stock is UNDERVALUED vs GGM") -> Stock is OVERVALUED vs GGM
A39: STEP 7: Sensitivity Analysis — Intrinsic Value at different g and Ke
A40: g ↓ / Ke → | B40: =B22-0.02 -> 0.11350183 | C40: =B22-0.01 -> 0.12350183 | D40: =B22 -> 0.13350183 | E40: =B22+0.01 -> 0.14350183 | F40: =B22+0.02 -> 0.15350183
A41: =B16-0.01 -> 0.07516559 | B41: =IFERROR(B31/(B22-0.02-(B16-0.01)),"") -> 56.614199 | C41: =IFERROR(B31/(B22-0.01-(B16-0.01)),"") -> 44.901619 | D41: =IFERROR(B31/(B22-(B16-0.01)),"") -> 37.204582 | E41: =IFERROR(B31/(B22+0.01-(B16-0.01)),"") -> 31.76024 | F41: =IFERROR(B31/(B22+0.02-(B16-0.01)),"") -> 27.705892
A42: =B16 -> 0.08516559 | B42: =IFERROR(B31/(B22-0.02-(B16)),"") -> 76.593634 | C42: =IFERROR(B31/(B22-0.01-(B16)),"") -> 56.614199 | D42: =IFERROR(B31/(B22-(B16)),"") -> 44.901619 | E42: =IFERROR(B31/(B22+0.01-(B16)),"") -> 37.204582 | F42: =IFERROR(B31/(B22+0.02-(B16)),"") -> 31.76024
A43: =B16+0.01 -> 0.09516559 | B43: =IFERROR(B31/(B22-0.02-(B16+0.01)),"") -> 118.36537 | C43: =IFERROR(B31/(B22-0.01-(B16+0.01)),"") -> 76.593634 | D43: =IFERROR(B31/(B22-(B16+0.01)),"") -> 56.614199 | E43: =IFERROR(B31/(B22+0.01-(B16+0.01)),"") -> 44.901619 | F43: =IFERROR(B31/(B22+0.02-(B16+0.01)),"") -> 37.204582
A44: =B16+0.02 -> 0.10516559 | B44: =IFERROR(B31/(B22-0.02-(B16+0.02)),"") -> 260.35436 | C44: =IFERROR(B31/(B22-0.01-(B16+0.02)),"") -> 118.36537 | D44: =IFERROR(B31/(B22-(B16+0.02)),"") -> 76.593634 | E44: =IFERROR(B31/(B22+0.01-(B16+0.02)),"") -> 56.614199 | F44: =IFERROR(B31/(B22+0.02-(B16+0.02)),"") -> 44.901619
A45: =B16+0.03 -> 0.11516559 | B45: =IFERROR(B31/(B22-0.02-(B16+0.03)),"") -> -1304.4965 | C45: =IFERROR(B31/(B22-0.01-(B16+0.03)),"") -> 260.35436 | D45: =IFERROR(B31/(B22-(B16+0.03)),"") -> 118.36537 | E45: =IFERROR(B31/(B22+0.01-(B16+0.03)),"") -> 76.593634 | F45: =IFERROR(B31/(B22+0.02-(B16+0.03)),"") -> 56.614199
A47: Note: Sensitivity shows negative values where g >= Ke — model breaks down mathematically.
A48: Ambuja's DPS CAGR (FY22-FY25) of ~25.3% significantly exceeds its Cost of Equity (~14.9%), driven by a one-off large dividend in FY23 (Mar 2023 = 15-month period). This makes GGM output unreliable.
A49: For a capital-intensive cement company with lumpy dividends, DCF is a more appropriate valuation method. Revenue CAGR (~6.6%) from Assumptions sheet is a better proxy for sustainable long-run growth.
