Workbook

Sheet About the Company
C2: DLF LIMITED
C4: Corporate Profile | Annual Report FY 2024-25 | Equity Research Note
A8: ABOUT THE COMPANY (DLF LIMITED)
A9: Business Overview, Chairman's Message & Key Corporate Facts
A11: MESSAGE FROM THE CHAIRMAN In his message to shareholders, Chairman Mr. Rajiv Singh noted that both the Residential and Rental businesses delivered strong growth in FY 2024-25, supported by record sales bookings on new launches such as The Dahlias and Privana, and continued capital investment in new office and retail build-outs across Gurugram, Chennai, Delhi and Goa. He reaffirmed the Company's commitment to good governance, transparency and sustainable, long-term value creation for all stakeholders, while reiterating DLF's vision of contributing to India's 'Viksit Bharat' goal by 2047. WHO WE ARE DLF Limited is one of India's largest and most reputed real estate development companies, with a track record spanning over six decades since its incorporation in 1963. Headquartered in Gurugram, Haryana, the Company has built and delivered a diversified portfolio of residential, commercial and retail developments across the country and is recognised as one of India's most trusted real estate brands. DLF is listed on both BSE Limited and the National Stock Exchange of India Limited. BUSINESS SEGMENTS / SERVICES OFFERED DLF's operations are organised around two core business verticals. The Development Business focuses on the design, construction and sale of residential products, including high-rise condominiums, low-rise independent floors, plotted developments and shop-cum-offices. The Rental (Annuity) Business comprises Offices, Retail and Hospitality assets, largely held and operated through DLF Cyber City Developers Limited (DCCDL), a 66.66%-owned subsidiary and joint venture platform with Reco Greens Pte. Limited, an affiliate of GIC, Singapore. KEY MARKETS / SEGMENTS SERVED Residential Real Estate: Super-luxury and luxury housing, plotted developments and independent floors across Gurugram, Delhi, Chennai, Goa and Panchkula. Commercial Offices: Grade-A office parks and business districts serving Global Capability Centres (GCCs), BFSI and technology occupiers. Retail: Shopping malls and lifestyle destinations, including DLF Promenade, DLF Mall of India and Midtown Plaza. Hospitality: Premium hotels and clubs, including The Lodhi, New Delhi, and DLF's golf and recreation clubs.
A34: KEY SUBSIDIARIES, JOINT VENTURES & ASSOCIATES
A35: S. No. | B35: Company Name | D35: Nature of Business | F35: Holding (%)
A36: 1 | B36: DLF Home Developers Limited | D36: Residential Real Estate Development | F36: 100.00
A37: 2 | B37: DLF Cyber City Developers Limited (DCCDL) | D37: Office, Retail & Hospitality (Rental Business / JV with GIC, Singapore) | F37: 66.66
A38: 3 | B38: DLF Universal Limited | D38: Real Estate Development | F38: 100.00
A39: 4 | B39: DLF Utilities Limited | D39: Utility & Infrastructure Services | F39: 100.00
A40: 5 | B40: DLF Projects Limited | D40: Project & Construction Management | F40: 100.00
A41: 6 | B41: DLF Property Developers Limited | D41: Real Estate Development | F41: 100.00
A42: 7 | B42: DLF Luxury Homes Limited | D42: Premium Residential Development | F42: 100.00
A43: 8 | B43: Lodhi Property Company Limited | D43: Hospitality (The Lodhi, New Delhi) | F43: 100.00
A44: 9 | B44: DLF Info City Hyderabad Limited | D44: IT Park / Commercial Development | F44: 100.00
A45: 10 | B45: DLF Info Park (Pune) Limited | D45: IT Park / Commercial Development | F45: 100.00
A46: 11 | B46: DLF Southern Towns Private Limited | D46: Residential Development (South India) | F46: 100.00
A47: 12 | B47: DLF Residential Partners Limited | D47: Residential Development | F47: 100.00
... A49: 14 | B49: DLF Homes Panchkula Private Limited | D49: Residential Development | F49: 99.94
A51: REGISTERED OFFICE & CORPORATE INFORMATION
A52: Registered Office | C52: Shopping Mall, 3rd Floor, Arjun Marg, Phase-I, DLF City, Gurugram – 122 002, Haryana, India
A53: Corporate Office | C53: DLF Gateway Tower, R Block, DLF City, Phase-III, Gurugram – 122 002, Haryana, India
A54: Corporate Identity Number (CIN) | C54: L70101HR1963PLC002484
A55: Listed At | C55: BSE Limited (BSE) and National Stock Exchange of India Limited (NSE)
A57: KEY OPERATING METRICS
A58: Metric | C58: Value | D58: Details
A59: Track Record | C59: 8 Decades | D59: Real estate operations since incorporation in 1963
A60: Real Estate Projects Developed | C60: 178 | D60: Across residential, commercial and retail segments
A61: Cumulative Area Developed | C61: 349 msf | D61: Since inception
A62: Development Potential | C62: 205 msf | D62: Combined Devco & Rentco pipeline
A63: Operational Rental Portfolio | C63: 45 msf | D63: Offices, Retail & Hospitality (through DCCDL)
A64: Pan-India Presence | C64: 132 locations | D64: Across India; no international operations (per BRSR disclosure)

Sheet Promoter
A1: DLF LIMITED | SHAREHOLDING PATTERN — PROMOTER & PROMOTER GROUP (CATEGORY A)
A2: Per Regulation 31, SEBI (LODR) Regulations, 2015 | Capital Structure Annexure — Equity Research
A4: Category of Shareholder | B4: Entity Type | C4: No. of Shareholders | D4: No. of Fully Paid-up Equity Shares Held | E4: Total Shares Held | F4: Shareholding (% of Total) | G4: Voting Rights Held (Class: Equity) | H4: Voting Rights (% of Total) | I4: Shares on Fully Diluted Basis | J4: Shareholding % (Diluted Basis) | K4: Shares Held in Dematerialised Form
A5: A5) Indian
A6: Individuals/Hindu undivided Family | C6: 5 | D6: 23531900 | E6: 23531900 | F6: 0.95 | G6: 23531900 | H6: 0.95 | I6: 23531900 | J6: 0.95 | K6: 23531900
A7: PIA SINGH | B7: Promoter Group | C7: 1 | D7: 21420500 | E7: 21420500 | F7: 0.87 | G7: 21420500 | H7: 0.87 | I7: 21420500 | J7: 0.87 | K7: 21420500
A8: RENUKA TALWAR | B8: Promoter Group | C8: 1 | D8: 1540000 | E8: 1540000 | F8: 0.06 | G8: 1540000 | H8: 0.06 | I8: 1540000 | J8: 0.06 | K8: 1540000
A9: RAJIV SINGH | B9: Promoter | C9: 1 | D9: 256320 | E9: 256320 | F9: 0.01 | G9: 256320 | H9: 0.01 | I9: 256320 | J9: 0.01 | K9: 256320
A10: KAVITA SINGH | B10: Promoter Group | C10: 1 | D10: 314080 | E10: 314080 | F10: 0.01 | G10: 314080 | H10: 0.01 | I10: 314080 | J10: 0.01 | K10: 314080
A11: ANUSHKA SINGH | B11: Promoter Group | C11: 1 | D11: 1000 | E11: 1000 | F11: 0 | G11: 1000 | H11: 0 | I11: 1000 | J11: 0 | K11: 1000
A12: K. P. SINGH (HUF) [KARTA- KUSHAL PAL SINGH] | B12: Promoter Group | C12: - | D12: - | E12: - | F12: 0 | G12: - | H12: 0 | I12: - | J12: 0 | K12: -
A13: Any Other (specify) | C13: 7 | D13: 1810103485 | E13: 1810103485 | F13: 73.13 | G13: 1810103485 | H13: 73.13 | I13: 1810103485 | J13: 73.13 | K13: 1810103485
A14: RAJDHANI INVESTMENTS AND AGENCIES PRIVATE LIMITED | B14: Promoter | C14: 1 | D14: 1523133505 | E14: 1523133505 | F14: 61.53 | G14: 1523133505 | H14: 61.53 | I14: 1523133505 | J14: 61.53 | K14: 1523133505
A15: UNIVERSAL MANAGEMENT AND SALES LLP | B15: Promoter Group | C15: 1 | D15: 5455560 | E15: 5455560 | F15: 0.22 | G15: 5455560 | H15: 0.22 | I15: 5455560 | J15: 0.22 | K15: 5455560
A16: JHANDEWALAN ANCILLARIES LLP | B16: Promoter Group | C16: 1 | D16: 47388000 | E16: 47388000 | F16: 1.91 | G16: 47388000 | H16: 1.91 | I16: 47388000 | J16: 1.91 | K16: 47388000
A17: BEVERLY BUILDERS LLP | B17: Promoter Group | C17: - | D17: - | E17: - | F17: 0 | G17: - | H17: 0 | I17: - | J17: 0 | K17: -
A18: PARVATI ESTATES LLP | B18: Promoter Group | C18: 1 | D18: 6380000 | E18: 6380000 | F18: 0.26 | G18: 6380000 | H18: 0.26 | I18: 6380000 | J18: 0.26 | K18: 6380000
A19: PREM TRADERS LLP | B19: Promoter Group | C19: 1 | D19: 90059200 | E19: 90059200 | F19: 3.64 | G19: 90059200 | H19: 3.64 | I19: 90059200 | J19: 3.64 | K19: 90059200
A20: RAISINA AGENCIES LLP | B20: Promoter Group | C20: 1 | D20: 65889120 | E20: 65889120 | F20: 2.66 | G20: 65889120 | H20: 2.66 | I20: 65889120 | J20: 2.66 | K20: 65889120
A21: MALLIKA HOUSING COMPANY LLP | B21: Promoter Group | C21: 1 | D21: 71798100 | E21: 71798100 | F21: 2.9 | G21: 71798100 | H21: 2.9 | I21: 71798100 | J21: 2.9 | K21: 71798100
A22: PREM'S WILL TRUST (TRUSTEE- KUSHAL PAL SINGH, RAJIV SINGH AND PIA SINGH) | B22: Promoter Group | C22: - | D22: - | E22: - | F22: 0 | G22: - | H22: 0 | I22: - | J22: 0 | K22: -
A23: REALEST BUILDERS AND SERVICES PRIVATE LIMITED | B23: Promoter Group | C23: - | D23: - | E23: - | F23: 0 | G23: - | H23: 0 | I23: - | J23: 0 | K23: -
A24: AGS BUILDTECH PRIVATE LIMITED | B24: Promoter Group | C24: - | D24: - | E24: - | F24: 0 | G24: - | H24: 0 | I24: - | J24: 0 | K24: -
A25: A.S.G. REALCON PRIVATE LIMITED | B25: Promoter Group | C25: - | D25: - | E25: - | F25: 0 | G25: - | H25: 0 | I25: - | J25: 0 | K25: -
A26: HITECH PROPERTY DEVELOPERS PRIVATE LIMITED | B26: Promoter Group | C26: - | D26: - | E26: - | F26: 0 | G26: - | H26: 0 | I26: - | J26: 0 | K26: -
A27: SIDHANT REAL ESTATE DEVELOPERS AND SERVICES PRIVATE LIMITED | B27: Promoter Group | C27: - | D27: - | E27: - | F27: 0 | G27: - | H27: 0 | I27: - | J27: 0 | K27: -
A28: TRINITY HOUSING AND CONSTRUCTION COMPANY | B28: Promoter Group | C28: - | D28: - | E28: - | F28: 0 | G28: - | H28: 0 | I28: - | J28: 0 | K28: -
A29: UTTAM BUILDERS AND DEVELOPERS PRIVATE LIMITED | B29: Promoter Group | C29: - | D29: - | E29: - | F29: 0 | G29: - | H29: 0 | I29: - | J29: 0 | K29: -
A30: UTTAM REAL ESTATES COMPANY | B30: Promoter Group | C30: - | D30: - | E30: - | F30: 0 | G30: - | H30: 0 | I30: - | J30: 0 | K30: -
A31: MADHUKAR HOUSING AND DEVELOPMENT COMPANY | B31: Promoter Group | C31: - | D31: - | E31: - | F31: 0 | G31: - | H31: 0 | I31: - | J31: 0 | K31: -
A32: RENKON PARTNERS | B32: Promoter Group | C32: - | D32: - | E32: - | F32: 0 | G32: - | H32: 0 | I32: - | J32: 0 | K32: -
A33: GENERAL MARKETING CORPORATION | B33: Promoter Group | C33: - | D33: - | E33: - | F33: 0 | G33: - | H33: 0 | I33: - | J33: 0 | K33: -
... A61: R.R. FAMILY TRUST (TRUSTEE – RENUKA TALWAR AND PIA SINGH) | B61: Promoter Group | C61: - | D61: - | E61: - | F61: 0 | G61: - | H61: 0 | I61: - | J61: 0 | K61: -
A62: Sub Total A1 | C62: 12 | D62: 1833635385 | E62: 1833635385 | F62: 74.08 | G62: 1833635385 | H62: 74.08 | I62: 1833635385 | J62: 74.08 | K62: 1833635385
A63: A6) Foreign
A64: Individuals (NonResident Individuals/ Foreign Individuals) | C64: 1 | D64: 1000 | E64: 1000 | F64: 0 | G64: 1000 | H64: 0 | I64: 1000 | J64: 0 | K64: 1000
A65: KUSHAL PAL SINGH | B65: Promoter | C65: - | D65: - | E65: - | F65: 0 | G65: - | H65: 0 | I65: - | J65: 0 | K65: -
A66: SAVITRI DEVI SINGH | B66: Promoter Group | C66: 1 | D66: 1000 | E66: 1000 | F66: 0 | G66: 1000 | H66: 0 | I66: 1000 | J66: 0 | K66: 1000
A67: Any Other (specify) | C67: - | D67: - | E67: - | F67: 0 | G67: - | H67: 0 | I67: - | J67: 0 | K67: -
A68: BECKON INVESTMENTS GROUP LIMITED | B68: Promoter Group | C68: - | D68: - | E68: - | F68: 0 | G68: - | H68: 0 | I68: - | J68: 0 | K68: -
A69: RENKON OVERSEAS DEVELOPMENT LIMITED | B69: Promoter Group | C69: - | D69: - | E69: - | F69: 0 | G69: - | H69: 0 | I69: - | J69: 0 | K69: -
A70: KRIS DEVELOPMENTS LIMITED | B70: Promoter Group | C70: - | D70: - | E70: - | F70: 0 | G70: - | H70: 0 | I70: - | J70: 0 | K70: -
A71: MOUGINS RIVIERA DEVELOPMENTS SCI | B71: Promoter Group | C71: - | D71: - | E71: - | F71: 0 | G71: - | H71: 0 | I71: - | J71: 0 | K71: -
A72: PERLSEE INVESTMENT LIMITED | B72: Promoter Group | C72: - | D72: - | E72: - | F72: 0 | G72: - | H72: 0 | I72: - | J72: 0 | K72: -
A73: INDALE SERVICES (BVI) LIMITED | B73: Promoter Group | C73: - | D73: - | E73: - | F73: 0 | G73: - | H73: 0 | I73: - | J73: 0 | K73: -
A74: RT VENTURES PTE. LTD. | B74: Promoter Group | C74: - | D74: - | E74: - | F74: 0 | G74: - | H74: 0 | I74: - | J74: 0 | K74: -
A75: RT ENTERPRISES FZCO | B75: Promoter Group | C75: - | D75: - | E75: - | F75: 0 | G75: - | H75: 0 | I75: - | J75: 0 | K75: -
A76: ALFA INVESTMENTS GLOBAL LTD | B76: Promoter Group | C76: - | D76: - | E76: - | F76: 0 | G76: - | H76: 0 | I76: - | J76: 0 | K76: -
A77: UNIMARK PROPERTIES | B77: Promoter Group | C77: - | D77: - | E77: - | F77: 0 | G77: - | H77: 0 | I77: - | J77: 0 | K77: -
A78: Sub Total A2 | C78: 1 | D78: 1000 | E78: 1000 | F78: 0 | G78: 1000 | H78: 0 | I78: 1000 | J78: 0 | K78: 1000
A79: A=A1+A2 | C79: 13 | D79: 1833636385 | E79: 1833636385 | F79: 74.08 | G79: 1833636385 | H79: 74.08 | I79: 1833636385 | J79: 74.08 | K79: 1833636385

Sheet Public
A1: DLF LIMITED | SHAREHOLDING PATTERN — PUBLIC SHAREHOLDING (CATEGORY B)
A2: Per Regulation 31, SEBI (LODR) Regulations, 2015 | Capital Structure Annexure — Equity Research
A4: Category & Name of Shareholder | B4: No. of Shareholders | C4: No. of Fully Paid-up Equity Shares Held | D4: Total Shares Held | E4: Shareholding (% of Total) | F4: No. of Voting Rights | G4: Voting Rights (% of Total) | H4: Shares on Fully Diluted Basis | I4: Shareholding % (Diluted Basis) | J4: Shares Held in Dematerialised Form | K4: Sub-Category I (No. of Shares) | L4: Sub-Category II (No. of Shares) | M4: Sub-Category III (No. of Shares)
A5: Institutions
A6: B2) Institutions (Domestic) | B6: 0 | C6: 0 | D6: - | E6: 0 | F6: - | G6: 0 | H6: - | I6: 0 | J6: - | K6: - | L6: - | M6: -
A7: Mutual Funds/ | B7: 42 | C7: 127406762 | D7: 127406762 | E7: 5.15 | F7: 127406762 | G7: 5.15 | H7: 127406762 | I7: 5.15 | J7: 127406762 | K7: - | L7: - | M7: -
A8: SBI EQUITY HYBRID FUND | B8: 1 | C8: 26622038 | D8: 26622038 | E8: 1.08 | F8: 26622038 | G8: 1.08 | H8: 26622038 | I8: 1.08 | J8: 26622038 | K8: - | L8: - | M8: -
A9: ICICI PRUDENTIAL LARGE CAP FUND | B9: 1 | C9: 35900187 | D9: 35900187 | E9: 1.45 | F9: 35900187 | G9: 1.45 | H9: 35900187 | I9: 1.45 | J9: 35900187 | K9: - | L9: - | M9: -
A10: Venture Capital Funds | B10: 0 | C10: 0 | D10: - | E10: 0 | F10: - | G10: 0 | H10: - | I10: 0 | J10: - | K10: - | L10: - | M10: -
A11: Alternate Investment Funds | B11: 15 | C11: 2032639 | D11: 2032639 | E11: 0.08 | F11: 2032639 | G11: 0.08 | H11: 2032639 | I11: 0.08 | J11: 2032639 | K11: - | L11: - | M11: -
A12: Banks | B12: 2 | C12: 465931 | D12: 465931 | E12: 0.02 | F12: 465931 | G12: 0.02 | H12: 465931 | I12: 0.02 | J12: 465931 | K12: - | L12: - | M12: -
A13: Insurance Companies | B13: 15 | C13: 22533357 | D13: 22533357 | E13: 0.91 | F13: 22533357 | G13: 0.91 | H13: 22533357 | I13: 0.91 | J13: 22533357 | K13: - | L13: - | M13: -
A14: Provident Funds/ Pension Funds | B14: 1 | C14: 18967466 | D14: 18967466 | E14: 0.77 | F14: 18967466 | G14: 0.77 | H14: 18967466 | I14: 0.77 | J14: 18967466 | K14: - | L14: - | M14: -
A15: Asset reconstruction companies | B15: 0 | C15: 0 | D15: - | E15: 0 | F15: - | G15: 0 | H15: - | I15: 0 | J15: - | K15: - | L15: - | M15: -
A16: Sovereign Wealth Funds | B16: 0 | C16: 0 | D16: - | E16: 0 | F16: - | G16: 0 | H16: - | I16: 0 | J16: - | K16: - | L16: - | M16: -
A17: NBFCs registered with RBI | B17: 2 | C17: 367540 | D17: 367540 | E17: 0.01 | F17: 367540 | G17: 0.01 | H17: 367540 | I17: 0.01 | J17: 367540 | K17: - | L17: - | M17: -
A18: Other Financial Institutions | B18: 0 | C18: 0 | D18: - | E18: 0 | F18: - | G18: 0 | H18: - | I18: 0 | J18: - | K18: - | L18: - | M18: -
A19: Any Other(Institutions (Domestic)) | B19: 0 | C19: 0 | D19: - | E19: 0 | F19: - | G19: 0 | H19: - | I19: 0 | J19: - | K19: - | L19: - | M19: -
A20: Sub Total B1 | B20: 77 | C20: 171773695 | D20: 171773695 | E20: 6.94 | F20: 171773695 | G20: 6.94 | H20: 171773695 | I20: 6.94 | J20: 171773695 | K20: - | L20: - | M20: -
A21: B17) Institutions (Foreign)
A22: Foreign Direct Investment | B22: 0 | C22: 0 | D22: - | E22: 0 | F22: - | G22: 0 | H22: - | I22: 0 | J22: - | K22: - | L22: - | M22: -
A23: Foreign Venture Capital Investors | B23: 0 | C23: 0 | D23: - | E23: 0 | F23: - | G23: 0 | H23: - | I23: 0 | J23: - | K23: - | L23: - | M23: -
A24: Sovereign Wealth Funds | B24: 0 | C24: 0 | D24: - | E24: 0 | F24: - | G24: 0 | H24: - | I24: 0 | J24: - | K24: - | L24: - | M24: -
A25: Foreign Portfolio Investors Category I | B25: 689 | C25: 326976953 | D25: 326976953 | E25: 13.21 | F25: 326976953 | G25: 13.21 | H25: 326976953 | I25: 13.21 | J25: 326976953 | K25: - | L25: - | M25: -
A26: INVESCO GLOBAL FUND | B26: 1 | C26: 32185164 | D26: 32185164 | E26: 1.3 | F26: 32185164 | G26: 1.3 | H26: 32185164 | I26: 1.3 | J26: 32185164 | K26: - | L26: - | M26: -
A27: Foreign Portfolio Investors Category II | B27: 37 | C27: 8194544 | D27: 8194544 | E27: 0.33 | F27: 8194544 | G27: 0.33 | H27: 8194544 | I27: 0.33 | J27: 8194544 | K27: - | L27: - | M27: -
A28: Overseas Depositories (holding DRs) (balancing figure) | B28: 0 | C28: 0 | D28: - | E28: 0 | F28: - | G28: 0 | H28: - | I28: 0 | J28: - | K28: - | L28: - | M28: -
A29: Any Other(Institutions (Foreign)) | B29: 0 | C29: 0 | D29: - | E29: 0 | F29: - | G29: 0 | H29: - | I29: 0 | J29: - | K29: - | L29: - | M29: -
A30: Sub Total B2 | B30: 726 | C30: 335171497 | D30: 335171497 | E30: 13.54 | F30: 335171497 | G30: 13.54 | H30: 335171497 | I30: 13.54 | J30: 335171497 | K30: - | L30: - | M30: -
A31: B27) Central Government/ State Government(s)/ President of India
A32: Central Government / President of India | B32: 0 | C32: 0 | D32: - | E32: 0 | F32: - | G32: 0 | H32: - | I32: 0 | J32: - | K32: - | L32: - | M32: -
A33: State Government / Governor | B33: 0 | C33: 0 | D33: - | E33: 0 | F33: - | G33: 0 | H33: - | I33: 0 | J33: - | K33: - | L33: - | M33: -
A34: Shareholding by Companies or Bodies Corporate where Central / State Government is a promoter | B34: 3 | C34: 2883 | D34: 2883 | E34: 0 | F34: 2883 | G34: 0 | H34: 2883 | I34: 0 | J34: 2883 | K34: - | L34: - | M34: -
A35: Sub Total B3 | B35: 3 | C35: 2883 | D35: 2883 | E35: 0 | F35: 2883 | G35: 0 | H35: 2883 | I35: 0 | J35: 2883 | K35: - | L35: - | M35: -
A36: B32) Non-Institutions
A37: Associate companies / Subsidiaries | B37: 0 | C37: 0 | D37: - | E37: 0 | F37: - | G37: 0 | H37: - | I37: 0 | J37: - | K37: - | L37: - | M37: -
A38: Directors and their relatives (excluding independent directors and nominee directors) | B38: 2 | C38: 357453 | D38: 357453 | E38: 0.01 | F38: 357453 | G38: 0.01 | H38: 357453 | I38: 0.01 | J38: 357453 | K38: - | L38: - | M38: -
A39: Key Managerial Personnel | B39: 1 | C39: 10254 | D39: 10254 | E39: 0 | F39: 10254 | G39: 0 | H39: 10254 | I39: 0 | J39: 10254 | K39: - | L39: - | M39: -
A40: Relatives of promoters (other than 'immediate relatives' of promoters disclosed under 'Promoter and Promoter Group' category) | B40: 0 | C40: 0 | D40: - | E40: 0 | F40: - | G40: 0 | H40: - | I40: 0 | J40: - | K40: - | L40: - | M40: -
A41: Trusts where any person belonging to 'Promoter and Promoter Group' category is 'trustee', 'beneficiary', or 'author of the trust' | B41: 0 | C41: 0 | D41: - | E41: 0 | F41: - | G41: 0 | H41: - | I41: 0 | J41: - | K41: - | L41: - | M41: -
A42: Investor Education and Protection Fund (IEPF) | B42: 1 | C42: 1583035 | D42: 1583035 | E42: 0.06 | F42: 1583035 | G42: 0.06 | H42: 1583035 | I42: 0.06 | J42: 1583035 | K42: - | L42: - | M42: -
A43: Resident Individuals holding nominal share capital up to Rs. 2 lakhs | B43: 487283 | C43: 63592078 | D43: 63592078 | E43: 2.57 | F43: 63592078 | G43: 2.57 | H43: 63592078 | I43: 2.57 | J43: 63420567 | K43: - | L43: - | M43: -
A44: Resident Individuals holding nominal share capital in excess of Rs. 2 lakhs | B44: 80 | C44: 49284296 | D44: 49284296 | E44: 1.99 | F44: 49284296 | G44: 1.99 | H44: 49284296 | I44: 1.99 | J44: 49284296 | K44: - | L44: - | M44: -
A45: Non Resident Indians (NRIs) | B45: 9273 | C45: 4759734 | D45: 4759734 | E45: 0.19 | F45: 4759734 | G45: 0.19 | H45: 4759734 | I45: 0.19 | J45: 4759734 | K45: - | L45: - | M45: -
A46: Foreign Nationals | B46: 1 | C46: 16000 | D46: 16000 | E46: 0 | F46: 16000 | G46: 0 | H46: 16000 | I46: 0 | J46: - | K46: - | L46: - | M46: -
A47: Foreign Companies | B47: 1 | C47: 10 | D47: 10 | E47: 0 | F47: 10 | G47: 0 | H47: 10 | I47: 0 | J47: 10 | K47: - | L47: - | M47: -
A48: Bodies Corporate | B48: 2303 | C48: 11262273 | D48: 11262273 | E48: 0.45 | F48: 11262273 | G48: 0.45 | H48: 11262273 | I48: 0.45 | J48: 11260273 | K48: - | L48: - | M48: -
A49: Any Other (specify) | B49: 6808 | C49: 3862113 | D49: 3862113 | E49: 0.16 | F49: 3862113 | G49: 0.16 | H49: 3862113 | I49: 0.16 | J49: 3862113 | K49: - | L49: - | M49: -
A50: Clearing Members | B50: 5 | C50: 2235 | D50: 2235 | E50: 0 | F50: 2235 | G50: 0 | H50: 2235 | I50: 0 | J50: 2235 | K50: - | L50: - | M50: -
A51: HUF | B51: 6781 | C51: 3837451 | D51: 3837451 | E51: 0.16 | F51: 3837451 | G51: 0.16 | H51: 3837451 | I51: 0.16 | J51: 3837451 | K51: - | L51: - | M51: -
A52: Trusts | B52: 22 | C52: 22427 | D52: 22427 | E52: 0 | F52: 22427 | G52: 0 | H52: 22427 | I52: 0 | J52: 22427 | K52: - | L52: - | M52: -
A53: Sub Total B4 | B53: 505753 | C53: 134727246 | D53: 134727246 | E53: 5.44 | F53: 134727246 | G53: 5.44 | H53: 134727246 | I53: 5.44 | J53: 134537735 | K53: - | L53: - | M53: -
A54: B=B1+B2+B3+B4 | B54: 506559 | C54: 641675321 | D54: 641675321 | E54: 25.92 | F54: 641675321 | G54: 25.92 | H54: 641675321 | I54: 25.92 | J54: 641485810 | K54: - | L54: -
A56: Note: '-' denotes nil holding for the category. Aggregate Public shareholding stood at 25.92% of total equity share capital as of the latest reporting period. Sub-category I/II/III columns (per Regulation 31, Table V) reflect nil disclosures for the period. Source: Company shareholding pattern disclosures filed with stock exchanges.

Sheet Consolidated P&L
A1: Consolidated Profit & Loss Account
A2: (Rs. Cr.) | B2: Mar 22 | C2: Mar 23 | D2: Mar 24 | E2: Mar 25 | F2: Mar 26
A3: INCOME
A4: Revenue From Operations [Gross] | B4: 5708.99 | C4: 5681.97 | D4: 6249.21 | E4: 7946.6 | F4: 8194.02
A5: Revenue From Operations [Net] | B5: 5708.99 | C5: 5681.97 | D5: 6249.21 | E5: 7946.6 | F5: 8194.02
A6: Other Operating Revenues | B6: 8.4 | C6: 12.86 | D6: 177.79 | E6: 47.06 | F6: 0
A7: Total Operating Revenues | B7: 5717.39 | C7: 5694.83 | D7: 6427 | E7: 7993.66 | F7: 8194.02
A8: Other Income | B8: 420.46 | C8: 317.31 | D8: 531.34 | E8: 1002.23 | F8: 1622.02
A9: Total Revenue | B9: 6137.84 | C9: 6012.14 | D9: 6958.34 | E9: 8995.89 | F9: 9816.04
A10: EXPENSES
A11: Cost Of Materials Consumed | B11: 0 | C11: 0 | D11: 0 | E11: 0 | F11: 4848.57
A12: Operating And Direct Expenses | B12: 2744.96 | C12: 2433.96 | D12: 2793.76 | E12: 4131.58 | F12: 0
A13: Employee Benefit Expenses | B13: 353.99 | C13: 547.88 | D13: 545.95 | E13: 591.96 | F13: 640.3
A14: Finance Costs | B14: 624.55 | C14: 392.14 | D14: 356.45 | E14: 397.2 | F14: 199.07
A15: Depreciation And Amortisation Expenses | B15: 149.44 | C15: 148.63 | D15: 147.95 | E15: 150.66 | F15: 142.41
A16: Other Expenses | B16: 875.88 | C16: 987.11 | D16: 963.69 | E16: 1161.48 | F16: 1256.79
A17: Total Expenses | B17: 4748.82 | C17: 4509.72 | D17: 4807.8 | E17: 6432.88 | F17: 7087.14
A18: Profit/Loss Before Exceptional, ExtraOrdinary Items And Tax | B18: 1389.03 | C18: 1502.42 | D18: 2150.55 | E18: 2563.01 | F18: 2728.9
A19: Exceptional Items | B19: -224.43 | C19: 0 | D19: 0 | E19: -302.39 | F19: 202.92
A20: Profit/Loss Before Tax | B20: 1164.59 | C20: 1502.42 | D20: 2150.55 | E20: 2260.62 | F20: 2931.82
A21: Tax Expenses-Continued Operations
A22: Current Tax | B22: 59.48 | C22: 56.88 | D22: 124.67 | E22: 89.45 | F22: 309.97
A23: Deferred Tax | B23: 261.5 | C23: 407.23 | D23: 384.05 | E23: -1110.89 | F23: 0
A24: Tax For Earlier Years | B24: 0 | C24: -62.61 | D24: 11.42 | E24: 587.55 | F24: 0
A25: Total Tax Expenses | B25: 320.97 | C25: 401.5 | D25: 520.13 | E25: -433.89 | F25: 309.97
A26: Profit/Loss After Tax And Before ExtraOrdinary Items | B26: 843.62 | C26: 1100.92 | D26: 1630.42 | E26: 2694.51 | F26: 2621.85
A27: Profit/Loss From Continuing Operations | B27: 843.62 | C27: 1100.92 | D27: 1630.42 | E27: 2694.51 | F27: 2621.85
A28: Profit/Loss For The Period | B28: 843.62 | C28: 1100.92 | D28: 1630.42 | E28: 2694.51 | F28: 2621.85
A29: Minority Interest | B29: 0.54 | C29: 1.88 | D29: 3.56 | E29: 0.8 | F29: 0
A30: Share Of Profit/Loss Of Associates | B30: 656.7 | C30: 933.03 | D30: 1093.13 | E30: 1672.31 | F30: 1792.83
A31: Consolidated Profit/Loss After MI And Associates | B31: 1500.85 | C31: 2035.83 | D31: 2727.11 | E31: 4367.62 | F31: 4414.68
A32: EARNINGS PER SHARE
A33: Basic EPS (Rs.) | B33: 6 | C33: 8 | D33: 11 | E33: 18 | F33: 18
A34: Diluted EPS (Rs.) | B34: 6 | C34: 8 | D34: 11 | E34: 18 | F34: 18
A35: DIVIDEND AND DIVIDEND PERCENTAGE
A36: Equity Share Dividend | B36: 495.06 | C36: 742.59 | D36: 990.12 | E36: 1237.66 | F36: 0

Sheet Consolidated Balance Sheet
A1: Consolidated Balance Sheet
A2: (Rs. Cr.) | B2: Mar 22 | C2: Mar 23 | D2: Mar 24 | E2: Mar 25 | F2: Mar 26
A3: EQUITIES AND LIABILITIES
A4: SHAREHOLDER'S FUNDS
A5: Equity Share Capital | B5: 495.06 | C5: 495.06 | D5: 495.06 | E5: 495.06 | F5: 495.06
A6: Total Share Capital | B6: 495.06 | C6: 495.06 | D6: 495.06 | E6: 495.06 | F6: 495.06
A7: Reserves and Surplus | B7: 35867.22 | C7: 37192.47 | D7: 38935.75 | E7: 42055.16 | F7: 44978.31
A8: Total Reserves and Surplus | B8: 35867.22 | C8: 37192.47 | D8: 38935.75 | E8: 42055.16 | F8: 44978.31
A9: Total Shareholders Funds | B9: 36362.28 | C9: 37687.53 | D9: 39430.81 | E9: 42550.22 | F9: 45473.37
A10: Minority Interest | B10: 19.47 | C10: 4.36 | D10: 0.8 | E10: 0 | F10: 0
A11: NON-CURRENT LIABILITIES
A12: Long Term Borrowings | B12: 2189.46 | C12: 1049.66 | D12: 2438.99 | E12: 1672.07 | F12: 0
A13: Deferred Tax Liabilities [Net] | B13: 2141.56 | C13: 2574.33 | D13: 2790.19 | E13: 1514.78 | F13: 2143.18
A14: Other Long Term Liabilities | B14: 1337.89 | C14: 1377.33 | D14: 1406.56 | E14: 1452.41 | F14: 1549.48
A15: Long Term Provisions | B15: 48.88 | C15: 50.01 | D15: 54 | E15: 52.89 | F15: 107.75
A16: Total Non-Current Liabilities | B16: 5717.79 | C16: 5051.33 | D16: 6689.73 | E16: 4692.16 | F16: 3800.41
A17: CURRENT LIABILITIES
A18: Short Term Borrowings | B18: 1770.54 | C18: 2053.43 | D18: 2159.73 | E18: 2181.96 | F18: 44.95
A19: Trade Payables | B19: 1528.73 | C19: 1643.7 | D19: 1787.82 | E19: 2261.03 | F19: 1719.59
A20: Other Current Liabilities | B20: 7059.5 | C20: 7451.88 | D20: 10118.82 | E20: 17748.64 | F20: 23757.07
A21: Short Term Provisions | B21: 45.09 | C21: 35.76 | D21: 74.68 | E21: 41.37 | F21: 79.38
A22: Total Current Liabilities | B22: 10403.85 | C22: 11184.76 | D22: 14141.05 | E22: 22233 | F22: 25600.99
A23: Total Capital And Liabilities | B23: 52503.4 | C23: 53927.99 | D23: 60262.4 | E23: 69475.37 | F23: 74874.77
A24: ASSETS
A25: NON-CURRENT ASSETS
A26: Tangible Assets | B26: 3771.75 | C26: 3699.49 | D26: 2799.41 | E26: 2427.8 | F26: 2955.79
A27: Intangible Assets | B27: 146.39 | C27: 141.65 | D27: 136.35 | E27: 130.23 | F27: 216.78
A28: Capital Work-In-Progress | B28: 81.05 | C28: 61.12 | D28: 68.1 | E28: 77.14 | F28: 158.72
A29: Intangible Assets Under Development | B29: 0 | C29: 0 | D29: 2.6 | E29: 8.55 | F29: 0
A30: Fixed Assets | B30: 3999.19 | C30: 3902.25 | D30: 3006.46 | E30: 2643.73 | F30: 3331.29
A31: Non-Current Investments | B31: 19536.42 | C31: 19010.41 | D31: 19756.88 | E31: 20980.61 | F31: 21119.22
A32: Deferred Tax Assets [Net] | B32: 1336.54 | C32: 1355.76 | D32: 1193.47 | E32: 1002.97 | F32: 1410.15
A33: Long Term Loans And Advances | B33: 229.92 | C33: 205.65 | D33: 204.67 | E33: 190.14 | F33: 663.31
A34: Other Non-Current Assets | B34: 2366.19 | C34: 2738.97 | D34: 2599.92 | E34: 2508.39 | F34: 6686.14
A35: Total Non-Current Assets | B35: 28412.52 | C35: 28157.3 | D35: 27705.66 | E35: 28270.08 | F35: 34154.36
A36: CURRENT ASSETS
A37: Current Investments | B37: 243.06 | C37: 470.72 | D37: 380.81 | E37: 355 | F37: 572.97
A38: Inventories | B38: 20106.99 | C38: 19361.23 | D38: 21154.13 | E38: 24621.48 | F38: 24717.48
A39: Trade Receivables | B39: 563.6 | C39: 549.23 | D39: 538.07 | E39: 802.21 | F39: 847.38
A40: Cash And Cash Equivalents | B40: 931.62 | C40: 2274.72 | D40: 4384.35 | E40: 4338.08 | F40: 7746.4
A41: Short Term Loans And Advances | B41: 687.86 | C41: 816.71 | D41: 957.58 | E41: 676.69 | F41: 448.39
A42: Other Current Assets | B42: 1557.74 | C42: 2298.08 | D42: 5141.79 | E42: 10411.82 | F42: 6387.79
A43: Total Current Assets | B43: 24090.88 | C43: 25770.69 | D43: 32556.73 | E43: 41205.29 | F43: 40720.41
A44: Total Assets | B44: 52503.4 | C44: 53927.99 | D44: 60262.4 | E44: 69475.37 | F44: 74874.77
A45: OTHER ADDITIONAL INFORMATION
A46: CONTINGENT LIABILITIES, COMMITMENTS
A47: Contingent Liabilities | B47: 9816.77 | C47: 9526.19 | D47: 14123.09 | E47: 9972.19 | F47: 0
A48: BONUS DETAILS
A49: Bonus Equity Share Capital | B49: 267.72 | C49: 267.72 | D49: 267.72 | E49: 267.72 | F49: 0
A50: NON-CURRENT INVESTMENTS
A51: Non-Current Investments Quoted Market Value | B51: 0 | C51: 0 | D51: 34.9 | E51: 41.89 | F51: 0
A52: Non-Current Investments Unquoted Book Value | B52: 0 | C52: 0 | D52: 408.91 | E52: 872.57 | F52: 0
A53: CURRENT INVESTMENTS
A54: Current Investments Unquoted Book Value | B54: 0 | C54: 0 | D54: 380.81 | E54: 355 | F54: 0

Sheet Cash flow Statement
A1: Consolidated Cash Flow
A2: (Rs. Cr.) | B2: Mar 22 | C2: Mar 23 | D2: Mar 24 | E2: Mar 25 | F2: Mar 26
A3: Net Profit Before Tax | B3: 1164.59 | C3: 1502.42 | D3: 2150.55 | E3: 2260.62 | F3: 2931.82
A4: Net Cash From Operating Activities | B4: 2831.82 | C4: 2375.26 | D4: 2538.81 | E4: 5235.22 | F4: 6347.37
A5: Net Cash (used in)/from Investing Activities | B5: 262.97 | C5: -462.62 | D5: -1528.67 | E5: -3543.05 | F5: 721.1
A6: Net Cash (used in)/from Financing Activities | B6: -3828.19 | C6: -2013.15 | D6: 176.61 | E6: -2402.56 | F6: -5546.76
A7: Net (decrease)/increase In Cash and Cash Equivalents | B7: -733.4 | C7: -100.51 | D7: 1186.75 | E7: -710.38 | F7: 1521.71
A8: Opening Cash & Cash Equivalents | B8: 1039.25 | C8: 307.86 | D8: 207.08 | E8: 1461.89 | F8: 751.51
A9: Closing Cash & Cash Equivalents | B9: 305.85 | C9: 207.35 | D9: 1393.83 | E9: 751.51 | F9: 2273.22

Sheet Beta
A1: Date | B1: NIFTY50_Close | C1: DLF_Close | E1: Rm nifty | F1: Rm Dlf | G1: slope | H1: covariance
A2: 43922 | B2: 8253.7998 | C2: 132.55
A3: 43924 | B3: 8083.7998 | C3: 132.10001 | E3: =(B3-B2)/B2 -> -0.020596574 | F3: =(C3-C2)/C2 -> -0.0033949222 | G3: =SLOPE(F3:F1532,E3:E1532) -> 1.5661234 | H3: =_xlfn.COVARIANCE.S(F3:F1532,E3:E1532)/_xlfn.VAR.S(E3:E1532) -> 1.5661234 | I3: SUMMARY OUTPUT
A4: 43928 | B4: 8792.2002 | C4: 141.55 | E4: =(B4-B3)/B3 -> 0.087632105 | F4: =(C4-C3)/C3 -> 0.071536688
A5: 43929 | B5: 8748.75 | C5: 138 | E5: =(B5-B4)/B4 -> -0.0049419024 | F5: =(C5-C4)/C4 -> -0.025079498 | I5: Regression Statistics
A6: 43930 | B6: 9111.9004 | C6: 149.10001 | E6: =(B6-B5)/B5 -> 0.041508832 | F6: =(C6-C5)/C5 -> 0.080434827 | I6: Multiple R | J6: 0.66199222
A7: 43934 | B7: 8993.8496 | C7: 139.75 | E7: =(B7-B6)/B6 -> -0.012955671 | F7: =(C7-C6)/C6 -> -0.062709629 | I7: R Square | J7: 0.4382337
A8: 43936 | B8: 8925.2998 | C8: 140.3 | E8: =(B8-B7)/B7 -> -0.0076218536 | F8: =(C8-C7)/C7 -> 0.0039356211 | I8: Adjusted R Square | J8: 0.43786605
A9: 43937 | B9: 8992.7998 | C9: 134 | E9: =(B9-B8)/B8 -> 0.0075627712 | F9: =(C9-C8)/C8 -> -0.044903798 | I9: Standard Error | J9: 0.017391265
A10: 43938 | B10: 9266.75 | C10: 136.89999 | E10: =(B10-B9)/B9 -> 0.030463282 | F10: =(C10-C9)/C9 -> 0.021641745 | I10: Observations | J10: 1530
A11: 43941 | B11: 9261.8496 | C11: 134.39999 | E11: =(B11-B10)/B10 -> -0.00052881438 | F11: =(C11-C10)/C10 -> -0.018261506
A12: 43942 | B12: 8981.4502 | C12: 132.64999 | E12: =(B12-B11)/B11 -> -0.030274667 | F12: =(C12-C11)/C11 -> -0.013020834 | I12: ANOVA
A13: 43943 | B13: 9187.2998 | C13: 133.55 | E13: =(B13-B12)/B12 -> 0.022919418 | F13: =(C13-C12)/C12 -> 0.0067848413 | J13: df | K13: SS | L13: MS | M13: F | N13: Significance F
A14: 43944 | B14: 9313.9004 | C14: 137 | E14: =(B14-B13)/B13 -> 0.013779956 | F14: =(C14-C13)/C13 -> 0.025832998 | I14: Regression | J14: 1 | K14: 0.36052535 | L14: 0.36052535 | M14: 1191.9923 | N14: 1.4097146e-193
A15: 43945 | B15: 9154.4004 | C15: 128.2 | E15: =(B15-B14)/B14 -> -0.017124942 | F15: =(C15-C14)/C14 -> -0.064233599 | I15: Residual | J15: 1528 | K15: 0.46215293 | L15: 0.0003024561
A16: 43948 | B16: 9282.2998 | C16: 133 | E16: =(B16-B15)/B15 -> 0.013971359 | F16: =(C16-C15)/C15 -> 0.037441522 | I16: Total | J16: 1529 | K16: 0.82267827
A17: 43949 | B17: 9380.9004 | C17: 138 | E17: =(B17-B16)/B16 -> 0.010622431 | F17: =(C17-C16)/C16 -> 0.037593985
A18: 43950 | B18: 9553.3496 | C18: 141.64999 | E18: =(B18-B17)/B17 -> 0.018383014 | F18: =(C18-C17)/C17 -> 0.026449231 | J18: Coefficients | K18: Standard Error | L18: t Stat | M18: P-value | N18: Lower 95% | O18: Upper 95% | P18: Lower 95.0% | Q18: Upper 95.0%
A19: 43951 | B19: 9859.9004 | C19: 146.85001 | E19: =(B19-B18)/B18 -> 0.032088303 | F19: =(C19-C18)/C18 -> 0.036710289 | I19: Intercept | J19: 8.9787125e-05 | K19: 0.00044586647 | L19: 0.20137671 | M19: 0.84043082 | N19: -0.00078478786 | O19: 0.00096436211 | P19: -0.00078478786 | Q19: 0.00096436211
A20: 43955 | B20: 9293.5 | C20: 133.05 | E20: =(B20-B19)/B19 -> -0.057444839 | F20: =(C20-C19)/C19 -> -0.093973459 | I20: X Variable 1 | J20: 1.5661234 | K20: 0.045361693 | L20: 34.525241 | M20: 1.4097146e-193 | N20: 1.4771456 | O20: 1.6551012 | P20: 1.4771456 | Q20: 1.6551012
A21: 43956 | B21: 9205.5996 | C21: 126.8 | E21: =(B21-B20)/B20 -> -0.0094582655 | F21: =(C21-C20)/C20 -> -0.04697482
A22: 43957 | B22: 9270.9004 | C22: 129.89999 | E22: =(B22-B21)/B21 -> 0.0070935935 | F22: =(C22-C21)/C21 -> 0.024447877
A23: 43958 | B23: 9199.0498 | C23: 129.14999 | E23: =(B23-B22)/B22 -> -0.0077501195 | F23: =(C23-C22)/C22 -> -0.0057736723
A24: 43959 | B24: 9251.5 | C24: 130.14999 | E24: =(B24-B23)/B23 -> 0.0057016971 | F24: =(C24-C23)/C23 -> 0.0077429349
A25: 43962 | B25: 9239.2002 | C25: 133.35001 | E25: =(B25-B24)/B24 -> -0.001329493 | F25: =(C25-C24)/C24 -> 0.02458711
A26: 43963 | B26: 9196.5498 | C26: 136.95 | E26: =(B26-B25)/B25 -> -0.0046162427 | F26: =(C26-C25)/C25 -> 0.026996556
A27: 43964 | B27: 9383.5498 | C27: 141.10001 | E27: =(B27-B26)/B26 -> 0.020333713 | F27: =(C27-C26)/C26 -> 0.030303098
A28: 43965 | B28: 9142.75 | C28: 137.05 | E28: =(B28-B27)/B27 -> -0.025661909 | F28: =(C28-C27)/C27 -> -0.028703068
A29: 43966 | B29: 9136.8496 | C29: 138.8 | E29: =(B29-B28)/B28 -> -0.00064536279 | F29: =(C29-C28)/C28 -> 0.012769062
A30: 43969 | B30: 8823.25 | C30: 132.45 | E30: =(B30-B29)/B29 -> -0.03432251 | F30: =(C30-C29)/C29 -> -0.045749323
A31: 43970 | B31: 8879.0996 | C31: 131.45 | E31: =(B31-B30)/B30 -> 0.0063298228 | F31: =(C31-C30)/C30 -> -0.007550019
A32: 43971 | B32: 9066.5498 | C32: 139.25 | E32: =(B32-B31)/B31 -> 0.021111397 | F32: =(C32-C31)/C31 -> 0.059338176
... A1532: 46185 | B1532: 23622.9 | C1532: 587.04999 | E1532: =(B1532-B1531)/B1531 -> 0.01991662 | F1532: =(C1532-C1531)/C1531 -> 0.042717563

Sheet Wacc
A1: Capital Structure
A2: Total Debt | B2: ='Consolidated Balance Sheet'!E12+'Consolidated Balance Sheet'!E18 -> 3854.03 | D2: Total Debt (FY2025) = Long Term Borrowings + Short Term Borrowings (Mar 25, Consolidated Balance Sheet)
A3: Total Equity | B3: =E6*606.05 -> 149620 | D3: Total Equity = Market Cap = (Total Share Capital / Face Value 2) x Current Price (Beta sheet latest close)
A4: Total Mix (Debt + Equity) | B4: =B2+B3 -> 153474.03
A5: % of Debt | B5: =B2/B4 -> 0.025111936 | C5: share outstanding | D5: mkt capitalisation/current share price
A6: % of Equity | B6: =B3/B4 -> 0.97488806 | D6: 149620/606.05 | E6: =149620/606.05 -> 246.87732
A7: Debt to Equity | B7: =B2/B3 -> 0.025758789
A9: Cost of Equity (CAPM)
A10: Risk-free Rate (Rf) | B10: 0.0625 | D10: Source: RBI 10-year Government Securities yield (FY2025)
A11: Beta (β) | B11: =Beta!G3 -> 1.5661234
A12: Market Risk Premium (Rm - Rf) | B12: 0.065 | D12: Source: India Equity Risk Premium (Damodaran estimate)
A13: Cost of Equity [Ke = Rf + β×(Rm-Rf)] | B13: =B10+B11*(B12) -> 0.16429802
A15: Cost of Debt
A16: Finance Cost (FY2025) | B16: ='Consolidated P&L'!E14 -> 397.2 | D16: Finance Costs, FY2025 / Mar 25 (Consolidated P&L)
A17: Total Debt (FY2025) | B17: =B2 -> 3854.03 | D17: Same as Total Debt (Capital Structure)
A18: Pre-tax Cost of Debt [Kd = FC/Debt] | B18: =IFERROR(B16/B17,0) -> 0.10306095
A19: Tax Rate | B19: =Assumptions!F15/Assumptions!F14 -> 0.11358789 | D19: Effective Tax Rate = Tax / EBT, FY2026 / Mar 26 (FY2025 excluded: one-off deferred tax credit distorts it to -16.9%)
A20: Post-tax Cost of Debt [Kd*(1-T)] | B20: =B18*(1-B19) -> 0.091354475
A22: WACC
A23: Source | B23: Weight | C23: Cost | D23: Weighted Cost
A24: Debt | B24: =B5 -> 0.025111936 | C24: =B20 -> 0.091354475 | D24: =B24*C24 -> 0.0022940877
A25: Equity | B25: =B6 -> 0.97488806 | C25: =B13 -> 0.16429802 | D25: =B25*C25 -> 0.16017218
A26: WACC | B26: =SUM(B24:B25) -> 1 | C26: (Check: weights = 100%) | D26: =SUM(D24:D25) -> 0.16246627 | F26: wacc = we*ke+wd*kd

Sheet Assumptions
A1: DLF
A2: Particulars (in RS Cr.) | B2: Mar 22 | C2: Mar 23 | D2: Mar 24 | E2: Mar 25 | F2: 46082
A3: Revenue from operations | B3: ='Consolidated P&L'!B7 -> 5717.39 | C3: ='Consolidated P&L'!C7 -> 5694.83 | D3: ='Consolidated P&L'!D7 -> 6427 | E3: ='Consolidated P&L'!E7 -> 7993.66 | F3: ='Consolidated P&L'!F7 -> 8194.02 | H3: Median of revenue growth
A4: Revenue growth in % | C4: =('Consolidated P&L'!C7-'Consolidated P&L'!B7)/'Consolidated P&L'!B7 -> -0.0039458564 | D4: =('Consolidated P&L'!D7-'Consolidated P&L'!C7)/'Consolidated P&L'!C7 -> 0.12856749 | E4: =('Consolidated P&L'!E7-'Consolidated P&L'!D7)/'Consolidated P&L'!D7 -> 0.24376225 | F4: =('Consolidated P&L'!F7-'Consolidated P&L'!E7)/'Consolidated P&L'!E7 -> 0.025064864 | G4: =AVERAGE(C4:F4) -> 0.098362188 | H4: =MEDIAN(C4:F4) -> 0.076816177
A5: Less: Material cost | B5: ='Consolidated P&L'!B12+'Consolidated P&L'!B11 -> 2744.96 | C5: ='Consolidated P&L'!C12+'Consolidated P&L'!C11 -> 2433.96 | D5: ='Consolidated P&L'!D12+'Consolidated P&L'!D11 -> 2793.76 | E5: ='Consolidated P&L'!E12+'Consolidated P&L'!E11 -> 4131.58 | F5: ='Consolidated P&L'!F12+'Consolidated P&L'!F11 -> 4848.57
A6: Less: Employee costs | B6: ='Consolidated P&L'!B13 -> 353.99 | C6: ='Consolidated P&L'!C13 -> 547.88 | D6: ='Consolidated P&L'!D13 -> 545.95 | E6: ='Consolidated P&L'!E13 -> 591.96 | F6: ='Consolidated P&L'!F13 -> 640.3
A7: Less: Other Expenses | B7: ='Consolidated P&L'!B16 -> 875.88 | C7: ='Consolidated P&L'!C16 -> 987.11 | D7: ='Consolidated P&L'!D16 -> 963.69 | E7: ='Consolidated P&L'!E16 -> 1161.48 | F7: ='Consolidated P&L'!F16 -> 1256.79
A8: Total Expenses | B8: =B5+B6+B7 -> 3974.83 | C8: =C5+C6+C7 -> 3968.95 | D8: =D5+D6+D7 -> 4303.4 | E8: =E5+E6+E7 -> 5885.02 | F8: =F5+F6+F7 -> 6745.66
A9: EBITDA | B9: =B3-B8 -> 1742.56 | C9: =C3-C8 -> 1725.88 | D9: =D3-D8 -> 2123.6 | E9: =E3-E8 -> 2108.64 | F9: =F3-F8 -> 1448.36
A10: Less: Depreciation And Amortization | B10: ='Consolidated P&L'!B15 -> 149.44 | C10: ='Consolidated P&L'!C15 -> 148.63 | D10: ='Consolidated P&L'!D15 -> 147.95 | E10: ='Consolidated P&L'!E15 -> 150.66 | F10: ='Consolidated P&L'!F15 -> 142.41
A11: EBIT | B11: =B9-B10 -> 1593.12 | C11: =C9-C10 -> 1577.25 | D11: =D9-D10 -> 1975.65 | E11: =E9-E10 -> 1957.98 | F11: =F9-F10 -> 1305.95
A12: ADD: Non operating income/ Other Income | B12: ='Consolidated P&L'!B8 -> 420.46 | C12: ='Consolidated P&L'!C8 -> 317.31 | D12: ='Consolidated P&L'!D8 -> 531.34 | E12: ='Consolidated P&L'!E8 -> 1002.23 | F12: ='Consolidated P&L'!F8 -> 1622.02
A13: Less: Interest Expenses | B13: ='Consolidated P&L'!B14 -> 624.55 | C13: ='Consolidated P&L'!C14 -> 392.14 | D13: ='Consolidated P&L'!D14 -> 356.45 | E13: ='Consolidated P&L'!E14 -> 397.2 | F13: ='Consolidated P&L'!F14 -> 199.07
A14: EBT | B14: =B11+B12-B13 -> 1389.03 | C14: =C11+C12-C13 -> 1502.42 | D14: =D11+D12-D13 -> 2150.54 | E14: =E11+E12-E13 -> 2563.01 | F14: =F11+F12-F13 -> 2728.9
A15: Less: TAX | B15: ='Consolidated P&L'!B25 -> 320.97 | C15: ='Consolidated P&L'!C25 -> 401.5 | D15: ='Consolidated P&L'!D25 -> 520.13 | E15: ='Consolidated P&L'!E25 -> -433.89 | F15: ='Consolidated P&L'!F25 -> 309.97
A16: Less:Non Controlling Interest/Minority Interest | B16: ='Consolidated P&L'!B29 -> 0.54 | C16: ='Consolidated P&L'!C29 -> 1.88 | D16: ='Consolidated P&L'!D29 -> 3.56 | E16: ='Consolidated P&L'!E29 -> 0.8 | F16: ='Consolidated P&L'!F29 -> 0
A17: Net Profit- Pat | B17: =B14-B15-B16 -> 1067.52 | C17: =C14-C15-C16 -> 1099.04 | D17: =D14-D15-D16 -> 1626.85 | E17: =E14-E15-E16 -> 2996.1 | F17: =F14-F15-F16 -> 2418.93
A21: Historical Growth
A22: Average Growth | B22: =AVERAGE(C4:F4) -> 0.098362188
A23: CAGR | B23: =(F3/B3)^(1/5)-1 -> 0.074632177 | C23: =_xlfn.RRI(5,B3,F3) -> 0.074632177 | D23: RRI
A25: Margins
A26: EBITDA | B26: =B9/B3 -> 0.30478243 | C26: =C9/C3 -> 0.30306085 | D26: =D9/D3 -> 0.33041855 | E26: =E9/E3 -> 0.26378905 | F26: =F9/F3 -> 0.17675817
A27: EBIT | B27: =B11/B3 -> 0.27864463 | C27: =C11/C3 -> 0.27696174 | D27: =D11/D3 -> 0.30739848 | E27: =E11/E3 -> 0.24494162 | F27: =F11/F3 -> 0.15937842
A28: EBT | B28: =B14/B3 -> 0.24294827 | C28: =C14/C3 -> 0.26382175 | D28: =D14/D3 -> 0.33461024 | E28: =E14/E3 -> 0.32063035 | F28: =F14/F3 -> 0.33303556
A29: Net Proftt | B29: =B17/B3 -> 0.18671457 | C29: =C17/C3 -> 0.19298908 | D29: =D17/D3 -> 0.25312743 | E29: =E17/E3 -> 0.37480954 | F29: =F17/F3 -> 0.29520675
A31: Tax Rate
A32: Effective tax rate | B32: =B15/B14 -> 0.23107492 | C32: =C15/C14 -> 0.26723553 | D32: =D15/D14 -> 0.24186018 | E32: =E15/E14 -> -0.16928923 | F32: =F15/F14 -> 0.11358789 | H32: Effective tax rate | I32: =AVERAGE(B32:F32) -> 0.13689386
A33: Marginal Tax rate | B33: 0.25 | C33: 0.25 | D33: 0.25 | E33: 0.25 | F33: 0.25 | I33: =AVERAGE(B33:F33) -> 0.25
A35: Return On Capital
A36: EBIT*(1-T) | B36: =B11*(1-B33) -> 1194.84 | C36: =C11*(1-C33) -> 1182.9375 | D36: =D11*(1-D33) -> 1481.7375 | E36: =E11*(1-E33) -> 1468.485 | F36: =F11*(1-F33) -> 979.4625
A37: Book Equity | B37: ='Consolidated Balance Sheet'!B9 -> 36362.28 | C37: ='Consolidated Balance Sheet'!C9 -> 37687.53 | D37: ='Consolidated Balance Sheet'!D9 -> 39430.81 | E37: ='Consolidated Balance Sheet'!E9 -> 42550.22 | F37: ='Consolidated Balance Sheet'!F9 -> 45473.37
A38: Book Debt | B38: ='Consolidated Balance Sheet'!B12+'Consolidated Balance Sheet'!B18 -> 3960 | C38: ='Consolidated Balance Sheet'!C12+'Consolidated Balance Sheet'!C18 -> 3103.09 | D38: ='Consolidated Balance Sheet'!D12+'Consolidated Balance Sheet'!D18 -> 4598.72 | E38: ='Consolidated Balance Sheet'!E12+'Consolidated Balance Sheet'!E18 -> 3854.03 | F38: ='Consolidated Balance Sheet'!F12+'Consolidated Balance Sheet'!F18 -> 44.95
A39: Cash and Cash equivalents | B39: ='Consolidated Balance Sheet'!B40 -> 931.62 | C39: ='Consolidated Balance Sheet'!C40 -> 2274.72 | D39: ='Consolidated Balance Sheet'!D40 -> 4384.35 | E39: ='Consolidated Balance Sheet'!E40 -> 4338.08 | F39: ='Consolidated Balance Sheet'!F40 -> 7746.4
A40: Capital Employed | B40: =B37+B38+B39 -> 41253.9 | C40: =C37+C38+C39 -> 43065.34 | D40: =D37+D38+D39 -> 48413.88 | E40: =E37+E38+E39 -> 50742.33 | F40: =F37+F38+F39 -> 53264.72
A42: Pre-Tax Return on capital | B42: =B11/B40 -> 0.03861744 | C42: =C11/C40 -> 0.03662458 | D42: =D11/D40 -> 0.040807512 | E42: =E11/E40 -> 0.038586718 | F42: =F11/F40 -> 0.024518105
A43: Post Tax return On capital | B43: =B36/B40 -> 0.02896308 | C43: =C36/C40 -> 0.027468435 | D43: =D36/D40 -> 0.030605634 | E43: =E36/E40 -> 0.028940039 | F43: =F36/F40 -> 0.018388579
A45: Growth In EBIT | C45: =FCFF!B12*F43 -> 0.0063714534

Sheet Ratio Analysis
A1: Ratio Analysis- DLF
A2: Years | B2: 44621 | C2: 44986 | D2: 45352 | E2: 45717 | F2: 46082 | G2: Trends | H2: Mean | I2: Median
A4: Sales Growth | C4: =('Consolidated P&L'!C7-'Consolidated P&L'!B7)/'Consolidated P&L'!B7 -> -0.0039458564 | D4: =('Consolidated P&L'!D7-'Consolidated P&L'!C7)/'Consolidated P&L'!C7 -> 0.12856749 | E4: =('Consolidated P&L'!E7-'Consolidated P&L'!D7)/'Consolidated P&L'!D7 -> 0.24376225 | F4: =('Consolidated P&L'!F7-'Consolidated P&L'!E7)/'Consolidated P&L'!E7 -> 0.025064864 | H4: =AVERAGE(C4:F4) -> 0.098362188 | I4: =MEDIAN(C4:F4) -> 0.076816177
A5: EBITDA Growth | C5: =(('Consolidated P&L'!C7-'Consolidated P&L'!C12-'Consolidated P&L'!C13-'Consolidated P&L'!C16)-('Consolidated P&L'!B7-'Consolidated P&L'!B12-'Consolidated P&L'!B13-'Consolidated P&L'!B16))/('Consolidated P&L'!B7-'Consolidated P&L'!B12-'Consolidated P&L'!B13-'Consolidated P&L'!B16) -> -0.0095721238 | D5: =(('Consolidated P&L'!D7-'Consolidated P&L'!D12-'Consolidated P&L'!D13-'Consolidated P&L'!D16)-('Consolidated P&L'!C7-'Consolidated P&L'!C12-'Consolidated P&L'!C13-'Consolidated P&L'!C16))/('Consolidated P&L'!C7-'Consolidated P&L'!C12-'Consolidated P&L'!C13-'Consolidated P&L'!C16) -> 0.23044476 | E5: =(('Consolidated P&L'!E7-'Consolidated P&L'!E12-'Consolidated P&L'!E13-'Consolidated P&L'!E16)-('Consolidated P&L'!D7-'Consolidated P&L'!D12-'Consolidated P&L'!D13-'Consolidated P&L'!D16))/('Consolidated P&L'!D7-'Consolidated P&L'!D12-'Consolidated P&L'!D13-'Consolidated P&L'!D16) -> -0.0070446412 | F5: =(('Consolidated P&L'!F7-'Consolidated P&L'!F12-'Consolidated P&L'!F13-'Consolidated P&L'!F16)-('Consolidated P&L'!E7-'Consolidated P&L'!E12-'Consolidated P&L'!E13-'Consolidated P&L'!E16))/('Consolidated P&L'!E7-'Consolidated P&L'!E12-'Consolidated P&L'!E13-'Consolidated P&L'!E16) -> 1.9862518 | H5: =AVERAGE(C5:F5) -> 0.55001995 | I5: =MEDIAN(C5:F5) -> 0.11170006
A6: EBIT Growth | C6: =(('Consolidated P&L'!C7-'Consolidated P&L'!C12-'Consolidated P&L'!C13-'Consolidated P&L'!C16-'Consolidated P&L'!C15)-('Consolidated P&L'!B7-'Consolidated P&L'!B12-'Consolidated P&L'!B13-'Consolidated P&L'!B16-'Consolidated P&L'!B15))/('Consolidated P&L'!B7-'Consolidated P&L'!B12-'Consolidated P&L'!B13-'Consolidated P&L'!B16-'Consolidated P&L'!B15) -> -0.0099615848 | D6: =(('Consolidated P&L'!D7-'Consolidated P&L'!D12-'Consolidated P&L'!D13-'Consolidated P&L'!D16-'Consolidated P&L'!D15)-('Consolidated P&L'!C7-'Consolidated P&L'!C12-'Consolidated P&L'!C13-'Consolidated P&L'!C16-'Consolidated P&L'!C15))/('Consolidated P&L'!C7-'Consolidated P&L'!C12-'Consolidated P&L'!C13-'Consolidated P&L'!C16-'Consolidated P&L'!C15) -> 0.25259154 | E6: =(('Consolidated P&L'!E7-'Consolidated P&L'!E12-'Consolidated P&L'!E13-'Consolidated P&L'!E16-'Consolidated P&L'!E15)-('Consolidated P&L'!D7-'Consolidated P&L'!D12-'Consolidated P&L'!D13-'Consolidated P&L'!D16-'Consolidated P&L'!D15))/('Consolidated P&L'!D7-'Consolidated P&L'!D12-'Consolidated P&L'!D13-'Consolidated P&L'!D16-'Consolidated P&L'!D15) -> -0.0089438919 | F6: =(('Consolidated P&L'!F7-'Consolidated P&L'!F12-'Consolidated P&L'!F13-'Consolidated P&L'!F16-'Consolidated P&L'!F15)-('Consolidated P&L'!E7-'Consolidated P&L'!E12-'Consolidated P&L'!E13-'Consolidated P&L'!E16-'Consolidated P&L'!E15))/('Consolidated P&L'!E7-'Consolidated P&L'!E12-'Consolidated P&L'!E13-'Consolidated P&L'!E16-'Consolidated P&L'!E15) -> 2.1433007 | H6: =AVERAGE(C6:F6) -> 0.5942467 | I6: =MEDIAN(C6:F6) -> 0.12182382
A7: Net Profit Growth | C7: =('Consolidated P&L'!C31-'Consolidated P&L'!B31)/'Consolidated P&L'!B31 -> 0.35645134 | D7: =('Consolidated P&L'!D31-'Consolidated P&L'!C31)/'Consolidated P&L'!C31 -> 0.33955684 | E7: =('Consolidated P&L'!E31-'Consolidated P&L'!D31)/'Consolidated P&L'!D31 -> 0.60155623 | F7: =('Consolidated P&L'!F31-'Consolidated P&L'!E31)/'Consolidated P&L'!E31 -> 0.010774747 | H7: =AVERAGE(C7:F7) -> 0.32708479 | I7: =MEDIAN(C7:F7) -> 0.34800409
A8: Dividend Growth | C8: =('Consolidated P&L'!C36-'Consolidated P&L'!B36)/'Consolidated P&L'!B36 -> 0.5 | D8: =('Consolidated P&L'!D36-'Consolidated P&L'!C36)/'Consolidated P&L'!C36 -> 0.33333333 | E8: =('Consolidated P&L'!E36-'Consolidated P&L'!D36)/'Consolidated P&L'!D36 -> 0.2500101 | H8: =AVERAGE(C8:E8) -> 0.36111448 | I8: =MEDIAN(C8:E8) -> 0.33333333
A10: Gross Margin | B10: =('Consolidated P&L'!B7-'Consolidated P&L'!B12-'Consolidated P&L'!B13)/'Consolidated P&L'!B7 -> 0.4579782 | C10: =('Consolidated P&L'!C7-'Consolidated P&L'!C12-'Consolidated P&L'!C13)/'Consolidated P&L'!C7 -> 0.47639526 | D10: =('Consolidated P&L'!D7-'Consolidated P&L'!D12-'Consolidated P&L'!D13)/'Consolidated P&L'!D7 -> 0.48036253 | E10: =('Consolidated P&L'!E7-'Consolidated P&L'!E12-'Consolidated P&L'!E13)/'Consolidated P&L'!E7 -> 0.4090892 | F10: =('Consolidated P&L'!F7-'Consolidated P&L'!F12-'Consolidated P&L'!F13)/'Consolidated P&L'!F7 -> 0.92185765 | H10: =AVERAGE(B10:F10) -> 0.54913657 | I10: =MEDIAN(B10:F10) -> 0.47639526
A11: EBITDA Margin | B11: =('Consolidated P&L'!B7-'Consolidated P&L'!B12-'Consolidated P&L'!B13-'Consolidated P&L'!B16)/'Consolidated P&L'!B7 -> 0.30478243 | C11: =('Consolidated P&L'!C7-'Consolidated P&L'!C12-'Consolidated P&L'!C13-'Consolidated P&L'!C16)/'Consolidated P&L'!C7 -> 0.30306085 | D11: =('Consolidated P&L'!D7-'Consolidated P&L'!D12-'Consolidated P&L'!D13-'Consolidated P&L'!D16)/'Consolidated P&L'!D7 -> 0.33041855 | E11: =('Consolidated P&L'!E7-'Consolidated P&L'!E12-'Consolidated P&L'!E13-'Consolidated P&L'!E16)/'Consolidated P&L'!E7 -> 0.26378905 | F11: =('Consolidated P&L'!F7-'Consolidated P&L'!F12-'Consolidated P&L'!F13-'Consolidated P&L'!F16)/'Consolidated P&L'!F7 -> 0.76847872 | H11: =AVERAGE(B11:F11) -> 0.39410592 | I11: =MEDIAN(B11:F11) -> 0.30478243
A12: EBIT Margin | B12: =('Consolidated P&L'!B7-'Consolidated P&L'!B12-'Consolidated P&L'!B13-'Consolidated P&L'!B16-'Consolidated P&L'!B15)/'Consolidated P&L'!B7 -> 0.27864463 | C12: =('Consolidated P&L'!C7-'Consolidated P&L'!C12-'Consolidated P&L'!C13-'Consolidated P&L'!C16-'Consolidated P&L'!C15)/'Consolidated P&L'!C7 -> 0.27696174 | D12: =('Consolidated P&L'!D7-'Consolidated P&L'!D12-'Consolidated P&L'!D13-'Consolidated P&L'!D16-'Consolidated P&L'!D15)/'Consolidated P&L'!D7 -> 0.30739848 | E12: =('Consolidated P&L'!E7-'Consolidated P&L'!E12-'Consolidated P&L'!E13-'Consolidated P&L'!E16-'Consolidated P&L'!E15)/'Consolidated P&L'!E7 -> 0.24494162 | F12: =('Consolidated P&L'!F7-'Consolidated P&L'!F12-'Consolidated P&L'!F13-'Consolidated P&L'!F16-'Consolidated P&L'!F15)/'Consolidated P&L'!F7 -> 0.75109897 | H12: =AVERAGE(B12:F12) -> 0.37180909 | I12: =MEDIAN(B12:F12) -> 0.27864463
A13: EBT Margin | B13: ='Consolidated P&L'!B20/'Consolidated P&L'!B7 -> 0.20369259 | C13: ='Consolidated P&L'!C20/'Consolidated P&L'!C7 -> 0.26382175 | D13: ='Consolidated P&L'!D20/'Consolidated P&L'!D7 -> 0.33461179 | E13: ='Consolidated P&L'!E20/'Consolidated P&L'!E7 -> 0.28280162 | F13: ='Consolidated P&L'!F20/'Consolidated P&L'!F7 -> 0.35779996 | H13: =AVERAGE(B13:F13) -> 0.28854554 | I13: =MEDIAN(B13:F13) -> 0.28280162
A14: Net Profit Margin | B14: ='Consolidated P&L'!B31/'Consolidated P&L'!B7 -> 0.26250614 | C14: ='Consolidated P&L'!C31/'Consolidated P&L'!C7 -> 0.35748741 | D14: ='Consolidated P&L'!D31/'Consolidated P&L'!D7 -> 0.42432083 | E14: ='Consolidated P&L'!E31/'Consolidated P&L'!E7 -> 0.54638551 | F14: ='Consolidated P&L'!F31/'Consolidated P&L'!F7 -> 0.53876852 | H14: =AVERAGE(B14:F14) -> 0.42589368 | I14: =MEDIAN(B14:F14) -> 0.42432083
A16: Sales Expenses%Sales | B16: ='Consolidated P&L'!B17/'Consolidated P&L'!B7 -> 0.83059228 | C16: ='Consolidated P&L'!C17/'Consolidated P&L'!C7 -> 0.79189721 | D16: ='Consolidated P&L'!D17/'Consolidated P&L'!D7 -> 0.74806286 | E16: ='Consolidated P&L'!E17/'Consolidated P&L'!E7 -> 0.80474776 | F16: ='Consolidated P&L'!F17/'Consolidated P&L'!F7 -> 0.86491612 | H16: =AVERAGE(B16:F16) -> 0.80804325 | I16: =MEDIAN(B16:F16) -> 0.80474776
A17: Depriciation%Sales | B17: ='Consolidated P&L'!B15/'Consolidated P&L'!B7 -> 0.026137801 | C17: ='Consolidated P&L'!C15/'Consolidated P&L'!C7 -> 0.026099111 | D17: ='Consolidated P&L'!D15/'Consolidated P&L'!D7 -> 0.023020072 | E17: ='Consolidated P&L'!E15/'Consolidated P&L'!E7 -> 0.018847437 | F17: ='Consolidated P&L'!F15/'Consolidated P&L'!F7 -> 0.017379748 | H17: =AVERAGE(B17:F17) -> 0.022296833 | I17: =MEDIAN(B17:F17) -> 0.023020072
A18: Operating Income%Sales | B18: =('Consolidated P&L'!B7-'Consolidated P&L'!B12-'Consolidated P&L'!B13-'Consolidated P&L'!B16-'Consolidated P&L'!B15)/'Consolidated P&L'!B7 -> 0.27864463 | C18: =('Consolidated P&L'!C7-'Consolidated P&L'!C12-'Consolidated P&L'!C13-'Consolidated P&L'!C16-'Consolidated P&L'!C15)/'Consolidated P&L'!C7 -> 0.27696174 | D18: =('Consolidated P&L'!D7-'Consolidated P&L'!D12-'Consolidated P&L'!D13-'Consolidated P&L'!D16-'Consolidated P&L'!D15)/'Consolidated P&L'!D7 -> 0.30739848 | E18: =('Consolidated P&L'!E7-'Consolidated P&L'!E12-'Consolidated P&L'!E13-'Consolidated P&L'!E16-'Consolidated P&L'!E15)/'Consolidated P&L'!E7 -> 0.24494162 | F18: =('Consolidated P&L'!F7-'Consolidated P&L'!F12-'Consolidated P&L'!F13-'Consolidated P&L'!F16-'Consolidated P&L'!F15)/'Consolidated P&L'!F7 -> 0.75109897 | H18: =AVERAGE(B18:F18) -> 0.37180909 | I18: =MEDIAN(B18:F18) -> 0.27864463
A20: Return on Capital Employed | B20: =('Consolidated P&L'!B7-'Consolidated P&L'!B12-'Consolidated P&L'!B13-'Consolidated P&L'!B16-'Consolidated P&L'!B15)/('Consolidated Balance Sheet'!B9+'Consolidated Balance Sheet'!B12+'Consolidated Balance Sheet'!B18) -> 0.039509671 | C20: =('Consolidated P&L'!C7-'Consolidated P&L'!C12-'Consolidated P&L'!C13-'Consolidated P&L'!C16-'Consolidated P&L'!C15)/('Consolidated Balance Sheet'!C9+'Consolidated Balance Sheet'!C12+'Consolidated Balance Sheet'!C18) -> 0.038666978 | D20: =('Consolidated P&L'!D7-'Consolidated P&L'!D12-'Consolidated P&L'!D13-'Consolidated P&L'!D16-'Consolidated P&L'!D15)/('Consolidated Balance Sheet'!D9+'Consolidated Balance Sheet'!D12+'Consolidated Balance Sheet'!D18) -> 0.044871022 | E20: =('Consolidated P&L'!E7-'Consolidated P&L'!E12-'Consolidated P&L'!E13-'Consolidated P&L'!E16-'Consolidated P&L'!E15)/('Consolidated Balance Sheet'!E9+'Consolidated Balance Sheet'!E12+'Consolidated Balance Sheet'!E18) -> 0.04219398 | F20: =('Consolidated P&L'!F7-'Consolidated P&L'!F12-'Consolidated P&L'!F13-'Consolidated P&L'!F16-'Consolidated P&L'!F15)/('Consolidated Balance Sheet'!F9+'Consolidated Balance Sheet'!F12+'Consolidated Balance Sheet'!F18) -> 0.13520974 | H20: =AVERAGE(B20:F20) -> 0.060090277 | I20: =MEDIAN(B20:F20) -> 0.04219398
A21: Retained Earning % | B21: =('Consolidated P&L'!B31-'Consolidated P&L'!B36)/'Consolidated P&L'!B31 -> 0.67014692 | C21: =('Consolidated P&L'!C31-'Consolidated P&L'!C36)/'Consolidated P&L'!C31 -> 0.63523968 | D21: =('Consolidated P&L'!D31-'Consolidated P&L'!D36)/'Consolidated P&L'!D31 -> 0.63693434 | E21: =('Consolidated P&L'!E31-'Consolidated P&L'!E36)/'Consolidated P&L'!E31 -> 0.71662828 | F21: =('Consolidated P&L'!F31-'Consolidated P&L'!F36)/'Consolidated P&L'!F31 -> 1 | H21: =AVERAGE(B21:F21) -> 0.73178984 | I21: =MEDIAN(B21:F21) -> 0.67014692
A22: Return on Equity % | B22: ='Consolidated P&L'!B31/'Consolidated Balance Sheet'!B9 -> 0.041274915 | C22: ='Consolidated P&L'!C31/'Consolidated Balance Sheet'!C9 -> 0.054018663 | D22: ='Consolidated P&L'!D31/'Consolidated Balance Sheet'!D9 -> 0.069161907 | E22: ='Consolidated P&L'!E31/'Consolidated Balance Sheet'!E9 -> 0.10264624 | F22: ='Consolidated P&L'!F31/'Consolidated Balance Sheet'!F9 -> 0.097082754 | H22: =AVERAGE(B22:F22) -> 0.072836895 | I22: =MEDIAN(B22:F22) -> 0.069161907
A23: Self Sustained Growth Rate | B23: =B22*B21 -> 0.027660257 | C23: =C22*C21 -> 0.034314799 | D23: =D22*D21 -> 0.044051593 | E23: =E22*E21 -> 0.073559197 | F23: =F22*F21 -> 0.097082754 | H23: =AVERAGE(B23:F23) -> 0.05533372 | I23: =MEDIAN(B23:F23) -> 0.044051593
A24: Interest Coverage Ratio | B24: =('Consolidated P&L'!B7-'Consolidated P&L'!B12-'Consolidated P&L'!B13-'Consolidated P&L'!B16-'Consolidated P&L'!B15)/'Consolidated P&L'!B14 -> 2.5508286 | C24: =('Consolidated P&L'!C7-'Consolidated P&L'!C12-'Consolidated P&L'!C13-'Consolidated P&L'!C16-'Consolidated P&L'!C15)/'Consolidated P&L'!C14 -> 4.0221605 | D24: =('Consolidated P&L'!D7-'Consolidated P&L'!D12-'Consolidated P&L'!D13-'Consolidated P&L'!D16-'Consolidated P&L'!D15)/'Consolidated P&L'!D14 -> 5.5425726 | E24: =('Consolidated P&L'!E7-'Consolidated P&L'!E12-'Consolidated P&L'!E13-'Consolidated P&L'!E16-'Consolidated P&L'!E15)/'Consolidated P&L'!E14 -> 4.9294562 | F24: =('Consolidated P&L'!F7-'Consolidated P&L'!F12-'Consolidated P&L'!F13-'Consolidated P&L'!F16-'Consolidated P&L'!F15)/'Consolidated P&L'!F14 -> 30.916361 | H24: =AVERAGE(B24:F24) -> 9.5922758 | I24: =MEDIAN(B24:F24) -> 4.9294562
A26: Debtor Turnover Ratio | B26: ='Consolidated P&L'!B7/'Consolidated Balance Sheet'!B39 -> 10.144411 | C26: ='Consolidated P&L'!C7/'Consolidated Balance Sheet'!C39 -> 10.368753 | D26: ='Consolidated P&L'!D7/'Consolidated Balance Sheet'!D39 -> 11.944543 | E26: ='Consolidated P&L'!E7/'Consolidated Balance Sheet'!E39 -> 9.9645479 | F26: ='Consolidated P&L'!F7/'Consolidated Balance Sheet'!F39 -> 9.6698294 | H26: =AVERAGE(B26:F26) -> 10.418417 | I26: =MEDIAN(B26:F26) -> 10.144411
A27: Creditor Turnover Ratio | B27: ='Consolidated P&L'!B7/'Consolidated Balance Sheet'!B19 -> 3.7399606 | C27: ='Consolidated P&L'!C7/'Consolidated Balance Sheet'!C19 -> 3.4646407 | D27: ='Consolidated P&L'!D7/'Consolidated Balance Sheet'!D19 -> 3.5948809 | E27: ='Consolidated P&L'!E7/'Consolidated Balance Sheet'!E19 -> 3.5354064 | F27: ='Consolidated P&L'!F7/'Consolidated Balance Sheet'!F19 -> 4.765101 | H27: =AVERAGE(B27:F27) -> 3.8199979 | I27: =MEDIAN(B27:F27) -> 3.5948809
A28: Inventory Turnover | B28: ='Consolidated P&L'!B7/'Consolidated Balance Sheet'!B38 -> 0.28434838 | C28: ='Consolidated P&L'!C7/'Consolidated Balance Sheet'!C38 -> 0.29413575 | D28: ='Consolidated P&L'!D7/'Consolidated Balance Sheet'!D38 -> 0.30381774 | E28: ='Consolidated P&L'!E7/'Consolidated Balance Sheet'!E38 -> 0.32466204 | F28: ='Consolidated P&L'!F7/'Consolidated Balance Sheet'!F38 -> 0.3315071 | H28: =AVERAGE(B28:F28) -> 0.3076942 | I28: =MEDIAN(B28:F28) -> 0.30381774
A29: Fixed Asset Turnover | B29: ='Consolidated P&L'!B7/'Consolidated Balance Sheet'!B30 -> 1.429637 | C29: ='Consolidated P&L'!C7/'Consolidated Balance Sheet'!C30 -> 1.4593709 | D29: ='Consolidated P&L'!D7/'Consolidated Balance Sheet'!D30 -> 2.1377301 | E29: ='Consolidated P&L'!E7/'Consolidated Balance Sheet'!E30 -> 3.0236295 | F29: ='Consolidated P&L'!F7/'Consolidated Balance Sheet'!F30 -> 2.4597138 | H29: =AVERAGE(B29:F29) -> 2.1020163 | I29: =MEDIAN(B29:F29) -> 2.1377301
A30: Capital Turnover Ratio | B30: ='Consolidated P&L'!B7/('Consolidated Balance Sheet'!B9+'Consolidated Balance Sheet'!B12+'Consolidated Balance Sheet'!B18) -> 0.14179233 | C30: ='Consolidated P&L'!C7/('Consolidated Balance Sheet'!C9+'Consolidated Balance Sheet'!C12+'Consolidated Balance Sheet'!C18) -> 0.13961126 | D30: ='Consolidated P&L'!D7/('Consolidated Balance Sheet'!D9+'Consolidated Balance Sheet'!D12+'Consolidated Balance Sheet'!D18) -> 0.14597022 | E30: ='Consolidated P&L'!E7/('Consolidated Balance Sheet'!E9+'Consolidated Balance Sheet'!E12+'Consolidated Balance Sheet'!E18) -> 0.17226138 | F30: ='Consolidated P&L'!F7/('Consolidated Balance Sheet'!F9+'Consolidated Balance Sheet'!F12+'Consolidated Balance Sheet'!F18) -> 0.18001587 | H30: =AVERAGE(B30:F30) -> 0.15593021 | I30: =MEDIAN(B30:F30) -> 0.14597022
A32: (In days)
A33: Debtors Day | B33: ='Consolidated Balance Sheet'!B39/'Consolidated P&L'!B7*365 -> 35.980404 | C33: ='Consolidated Balance Sheet'!C39/'Consolidated P&L'!C7*365 -> 35.20192 | D33: ='Consolidated Balance Sheet'!D39/'Consolidated P&L'!D7*365 -> 30.557889 | E33: ='Consolidated Balance Sheet'!E39/'Consolidated P&L'!E7*365 -> 36.62986 | F33: ='Consolidated Balance Sheet'!F39/'Consolidated P&L'!F7*365 -> 37.746271 | H33: =AVERAGE(B33:F33) -> 35.223269 | I33: =MEDIAN(B33:F33) -> 35.980404
A34: Payable Days | B34: ='Consolidated Balance Sheet'!B19/'Consolidated P&L'!B7*365 -> 97.59461 | C34: ='Consolidated Balance Sheet'!C19/'Consolidated P&L'!C7*365 -> 105.35003 | D34: ='Consolidated Balance Sheet'!D19/'Consolidated P&L'!D7*365 -> 101.53327 | E34: ='Consolidated Balance Sheet'!E19/'Consolidated P&L'!E7*365 -> 103.24131 | F34: ='Consolidated Balance Sheet'!F19/'Consolidated P&L'!F7*365 -> 76.598587 | H34: =AVERAGE(B34:F34) -> 96.863561 | I34: =MEDIAN(B34:F34) -> 101.53327
A35: Inventory Days | B35: ='Consolidated Balance Sheet'!B38/'Consolidated P&L'!B7*365 -> 1283.6367 | C35: ='Consolidated Balance Sheet'!C38/'Consolidated P&L'!C7*365 -> 1240.9236 | D35: ='Consolidated Balance Sheet'!D38/'Consolidated P&L'!D7*365 -> 1201.3782 | E35: ='Consolidated Balance Sheet'!E38/'Consolidated P&L'!E7*365 -> 1124.246 | F35: ='Consolidated Balance Sheet'!F38/'Consolidated P&L'!F7*365 -> 1101.0322 | H35: =AVERAGE(B35:F35) -> 1190.2433 | I35: =MEDIAN(B35:F35) -> 1201.3782
A36: Cash Conversion Cycle | B36: =B33+B35-B34 -> 1222.0224 | C36: =C33+C35-C34 -> 1170.7755 | D36: =D33+D35-D34 -> 1130.4028 | E36: =E33+E35-E34 -> 1057.6345 | F36: =F33+F35-F34 -> 1062.1799 | H36: =AVERAGE(B36:F36) -> 1128.603 | I36: =MEDIAN(B36:F36) -> 1130.4028
A38: CFO/Sales | B38: ='Cash flow Statement'!B4/'Consolidated P&L'!B7 -> 0.49529943 | C38: ='Cash flow Statement'!C4/'Consolidated P&L'!C7 -> 0.41709059 | D38: ='Cash flow Statement'!D4/'Consolidated P&L'!D7 -> 0.39502256 | E38: ='Cash flow Statement'!E4/'Consolidated P&L'!E7 -> 0.65492153 | F38: ='Cash flow Statement'!F4/'Consolidated P&L'!F7 -> 0.77463443 | H38: =AVERAGE(B38:F38) -> 0.54739371 | I38: =MEDIAN(B38:F38) -> 0.49529943
A39: CFO/Total Assets | B39: ='Cash flow Statement'!B4/'Consolidated Balance Sheet'!B44 -> 0.053935936 | C39: ='Cash flow Statement'!C4/'Consolidated Balance Sheet'!C44 -> 0.044045031 | D39: ='Cash flow Statement'!D4/'Consolidated Balance Sheet'!D44 -> 0.042129255 | E39: ='Cash flow Statement'!E4/'Consolidated Balance Sheet'!E44 -> 0.075353611 | F39: ='Cash flow Statement'!F4/'Consolidated Balance Sheet'!F44 -> 0.084773149 | H39: =AVERAGE(B39:F39) -> 0.060047396 | I39: =MEDIAN(B39:F39) -> 0.053935936
A40: CFO/Total Debt | B40: ='Cash flow Statement'!B4/('Consolidated Balance Sheet'!B12+'Consolidated Balance Sheet'!B18) -> 0.71510606 | C40: ='Cash flow Statement'!C4/('Consolidated Balance Sheet'!C12+'Consolidated Balance Sheet'!C18) -> 0.76544992 | D40: ='Cash flow Statement'!D4/('Consolidated Balance Sheet'!D12+'Consolidated Balance Sheet'!D18) -> 0.55206884 | E40: ='Cash flow Statement'!E4/('Consolidated Balance Sheet'!E12+'Consolidated Balance Sheet'!E18) -> 1.3583755 | F40: ='Cash flow Statement'!F4/('Consolidated Balance Sheet'!F12+'Consolidated Balance Sheet'!F18) -> 141.20957 | H40: =AVERAGE(B40:F40) -> 28.920113 | I40: =MEDIAN(B40:F40) -> 0.76544992

Sheet FCFF
A1: Particular | B1: 44621 | C1: 44986 | D1: 45352 | E1: 45717 | F1: 46082
A2: EBIT | B2: ='Consolidated P&L'!B7-'Consolidated P&L'!B12-'Consolidated P&L'!B13-'Consolidated P&L'!B16-'Consolidated P&L'!B15 -> 1593.12 | C2: ='Consolidated P&L'!C7-'Consolidated P&L'!C12-'Consolidated P&L'!C13-'Consolidated P&L'!C16-'Consolidated P&L'!C15 -> 1577.25 | D2: ='Consolidated P&L'!D7-'Consolidated P&L'!D12-'Consolidated P&L'!D13-'Consolidated P&L'!D16-'Consolidated P&L'!D15 -> 1975.65 | E2: ='Consolidated P&L'!E7-'Consolidated P&L'!E12-'Consolidated P&L'!E13-'Consolidated P&L'!E16-'Consolidated P&L'!E15 -> 1957.98 | F2: ='Consolidated P&L'!F7-'Consolidated P&L'!F12-'Consolidated P&L'!F13-'Consolidated P&L'!F16-'Consolidated P&L'!F15 -> 6154.52
A3: Less: Tax on EBIT | B3: =B2*$J$5 -> 218.08834 | C3: =C2*$J$5 -> 215.91584 | D3: =D2*$J$5 -> 270.45435 | E3: =E2*$J$5 -> 268.03544 | F3: =F2*$J$5 -> 842.51599
A4: EBIT * (1- Tax) NOPAT | B4: =B2-B3 -> 1375.0317 | C4: =C2-C3 -> 1361.3342 | D4: =D2-D3 -> 1705.1956 | E4: =E2-E3 -> 1689.9446 | F4: =F2-F3 -> 5312.004
A5: Less: Net Capital expenditure | C5: ='Fixed Asset Scheduled'!C8 -> -96.94 | D5: ='Fixed Asset Scheduled'!D8 -> -895.79 | E5: ='Fixed Asset Scheduled'!E8 -> -362.73 | F5: ='Fixed Asset Scheduled'!F8 -> 687.56 | I5: Avg of effective tax rate | J5: =Assumptions!I32 -> 0.13689386
A6: Less: Net Change in working Capital | C6: ='Change in working capital'!C6 -> -875.1 | D6: ='Change in working capital'!D6 -> 1637.62 | E6: ='Change in working capital'!E6 -> 3258.28 | F6: ='Change in working capital'!F6 -> 682.61
A7: Reinvestment | C7: =C5+C6 -> -972.04 | D7: =D5+D6 -> 741.83 | E7: =E5+E6 -> 2895.55 | F7: =F5+F6 -> 1370.17
A8: Free Cash Flow | C8: =C4-C7 -> 2333.3742 | D8: =D4-D7 -> 963.36565 | E8: =E4-E7 -> -1205.6054 | F8: =F4-F7 -> 3941.834
I9: Marginal tax rate | J9: =Assumptions!I33 -> 0.25
A10: Reinvestment Rate | C10: =C7/C4 -> -0.71403482 | D10: =D7/D4 -> 0.43504099 | E10: =E7/E4 -> 1.7133994 | F10: =F7/F4 -> 0.25793843
A12: Median Reinvestment rate /Sales percentage | B12: =MEDIAN(C10:F10) -> 0.34648971
A13: Average Reinvestment rate /Sales percentage | B13: =AVERAGE(C10:F10) -> 0.423086

Sheet Change in working capital
A1: Particular | B1: 44621 | C1: 44986 | D1: 45352 | E1: 45717 | F1: 46082
A2: Inventory | B2: ='Consolidated Balance Sheet'!B38 -> 20106.99 | C2: ='Consolidated Balance Sheet'!C38 -> 19361.23 | D2: ='Consolidated Balance Sheet'!D38 -> 21154.13 | E2: ='Consolidated Balance Sheet'!E38 -> 24621.48 | F2: ='Consolidated Balance Sheet'!F38 -> 24717.48
A3: Trade Receivables | B3: ='Consolidated Balance Sheet'!B39 -> 563.6 | C3: ='Consolidated Balance Sheet'!C39 -> 549.23 | D3: ='Consolidated Balance Sheet'!D39 -> 538.07 | E3: ='Consolidated Balance Sheet'!E39 -> 802.21 | F3: ='Consolidated Balance Sheet'!F39 -> 847.38
A4: Trade Payable | B4: ='Consolidated Balance Sheet'!B19 -> 1528.73 | C4: ='Consolidated Balance Sheet'!C19 -> 1643.7 | D4: ='Consolidated Balance Sheet'!D19 -> 1787.82 | E4: ='Consolidated Balance Sheet'!E19 -> 2261.03 | F4: ='Consolidated Balance Sheet'!F19 -> 1719.59
A5: Non Cash working Capital | B5: =B2+B3-B4 -> 19141.86 | C5: =C2+C3-C4 -> 18266.76 | D5: =D2+D3-D4 -> 19904.38 | E5: =E2+E3-E4 -> 23162.66 | F5: =F2+F3-F4 -> 23845.27
A6: Change in Working Capital | C6: =C5-B5 -> -875.1 | D6: =D5-C5 -> 1637.62 | E6: =E5-D5 -> 3258.28 | F6: =F5-E5 -> 682.61
A7: change in working Capital /percentage of sales | C7: =C6/'Consolidated P&L'!C7 -> -0.15366569 | D7: =D6/'Consolidated P&L'!D7 -> 0.25480317 | E7: =E6/'Consolidated P&L'!E7 -> 0.40760803 | F7: =F6/'Consolidated P&L'!F7 -> 0.083305874
A9: Median Non Cash working Capital /Sales percentage | C9: =MEDIAN(C7:F7) -> 0.16905452
A10: Average Non Cash working Capital /Sales percentage | C10: =AVERAGE(C7:F7) -> 0.14801285

Sheet Fixed Asset Scheduled
A1: Particular | B1: 44621 | C1: 44986 | D1: 45352 | E1: 45717 | F1: 46082
A2: Beginning balance | C2: =B6 -> 3999.19 | D2: =C6 -> 3902.25 | E2: =D6 -> 3006.46 | F2: =E6 -> 2643.73
A3: Add: Net Purchases | C3: =C6-C2+C5 -> 51.69 | D3: =D6-D2+D5 -> -747.84 | E3: =E6-E2+E5 -> -212.07 | F3: =F6-F2+F5 -> 829.97
A4: Total Fixed Assets | B4: =B5+B6 -> 4148.63 | C4: =C5+C6 -> 4050.88 | D4: =D5+D6 -> 3154.41 | E4: =E5+E6 -> 2794.39 | F4: =F5+F6 -> 3473.7
A5: Less: Depreciation | B5: ='Consolidated P&L'!B15 -> 149.44 | C5: ='Consolidated P&L'!C15 -> 148.63 | D5: ='Consolidated P&L'!D15 -> 147.95 | E5: ='Consolidated P&L'!E15 -> 150.66 | F5: ='Consolidated P&L'!F15 -> 142.41
A6: Closing Balance(Fixed Asests ) | B6: ='Consolidated Balance Sheet'!B30 -> 3999.19 | C6: ='Consolidated Balance Sheet'!C30 -> 3902.25 | D6: ='Consolidated Balance Sheet'!D30 -> 3006.46 | E6: ='Consolidated Balance Sheet'!E30 -> 2643.73 | F6: ='Consolidated Balance Sheet'!F30 -> 3331.29
A8: Net Capital expenditure | C8: =C3-C5 -> -96.94 | D8: =D3-D5 -> -895.79 | E8: =E3-E5 -> -362.73 | F8: =F3-F5 -> 687.56
A9: Net Capital expenditure / Sales percentage | C9: =C8/'Consolidated P&L'!C7 -> -0.017022457 | D9: =D8/'Consolidated P&L'!D7 -> -0.13937918 | E9: =E8/'Consolidated P&L'!E7 -> -0.045377211 | F9: =F8/'Consolidated P&L'!F7 -> 0.083909973
A11: Median Capital expenditure /Sales percentage | C11: =MEDIAN(C9:F9) -> -0.031199834
A12: Average Capital expenditure /Sales percentage | C12: =AVERAGE(C9:F9) -> -0.029467219

Sheet Forecasting 
D3: Sales Forecasting | I3: EBITDA Forecasting | N3: Earning per share Forecasting
D4: Year Weight | E4: Year | F4: Sales | G4: Sales Growth | I4: Year Weight | J4: Year | K4: EBITDA | L4: EBITDA Growth | N4: Year Weight | O4: Year | P4: EPS | Q4: EPS Growth
D5: 1 | E5: ='Ratio Analysis'!B2 -> 44621 | F5: =Assumptions!B3 -> 5717.39 | I5: 1 | J5: ='Ratio Analysis'!B2 -> 44621 | K5: =Assumptions!B9 -> 1742.56 | N5: 1 | O5: ='Ratio Analysis'!B2 -> 44621 | P5: ='Consolidated P&L'!B33 -> 6
D6: =D5+1 -> 2 | E6: =E5+365 -> 44986 | F6: =Assumptions!C3 -> 5694.83 | G6: =(F6-F5)/F5 -> -0.0039458564 | I6: =I5+1 -> 2 | J6: =J5+365 -> 44986 | K6: =Assumptions!C9 -> 1725.88 | L6: =(K6-K5)/K5 -> -0.0095721238 | N6: =N5+1 -> 2 | O6: =O5+365 -> 44986 | P6: ='Consolidated P&L'!C33 -> 8 | Q6: =(P6-P5)/P5 -> 0.33333333
D7: =D6+1 -> 3 | E7: =E6+365 -> 45351 | F7: =Assumptions!D3 -> 6427 | G7: =(F7-F6)/F6 -> 0.12856749 | I7: =I6+1 -> 3 | J7: =J6+365 -> 45351 | K7: =Assumptions!D9 -> 2123.6 | L7: =(K7-K6)/K6 -> 0.23044476 | N7: =N6+1 -> 3 | O7: =O6+365 -> 45351 | P7: ='Consolidated P&L'!D33 -> 11 | Q7: =(P7-P6)/P6 -> 0.375
D8: =D7+1 -> 4 | E8: =E7+365 -> 45716 | F8: =Assumptions!E3 -> 7993.66 | G8: =(F8-F7)/F7 -> 0.24376225 | I8: =I7+1 -> 4 | J8: =J7+365 -> 45716 | K8: =Assumptions!E9 -> 2108.64 | L8: =(K8-K7)/K7 -> -0.0070446412 | N8: =N7+1 -> 4 | O8: =O7+365 -> 45716 | P8: ='Consolidated P&L'!E33 -> 18 | Q8: =(P8-P7)/P7 -> 0.63636364
D9: =D8+1 -> 5 | E9: =E8+365 -> 46081 | F9: =Assumptions!F3 -> 8194.02 | G9: =(F9-F8)/F8 -> 0.025064864 | I9: =I8+1 -> 5 | J9: =J8+365 -> 46081 | K9: =Assumptions!F9 -> 1448.36 | L9: =(K9-K8)/K8 -> -0.31313074 | N9: =N8+1 -> 5 | O9: =O8+365 -> 46081 | P9: ='Consolidated P&L'!F33 -> 18 | Q9: =(P9-P8)/P8 -> 0
D10: =D9+1 -> 6 | E10: =E9+365 -> 46446 | F10: =FORECAST(E10,$F$5:$F$9,$E$5:$E$9) -> 8981.007 | G10: =(F10-F9)/F9 -> 0.096044066 | I10: =I9+1 -> 6 | J10: =J9+365 -> 46446 | K10: =FORECAST(J10,$K$5:$K$9,$J$5:$J$9) -> 1768.116 | L10: =(K10-K9)/K9 -> 0.22077108 | N10: =N9+1 -> 6 | O10: =O9+365 -> 46446 | P10: =FORECAST(O10,$P$5:$P$9,$O$5:$O$9) -> 22.4 | Q10: =(P10-P9)/P9 -> 0.24444444
D11: =D10+1 -> 7 | E11: =E10+365 -> 46811 | F11: =FORECAST(E11,$F$5:$F$9,$E$5:$E$9) -> 9706.216 | G11: =(F11-F10)/F10 -> 0.080749185 | I11: =I10+1 -> 7 | J11: =J10+365 -> 46811 | K11: =FORECAST(J11,$K$5:$K$9,$J$5:$J$9) -> 1747.552 | L11: =(K11-K10)/K10 -> -0.011630459 | N11: =N10+1 -> 7 | O11: =O10+365 -> 46811 | P11: =FORECAST(O11,$P$5:$P$9,$O$5:$O$9) -> 25.8 | Q11: =(P11-P10)/P10 -> 0.15178571
D12: =D11+1 -> 8 | E12: =E11+365 -> 47176 | F12: =FORECAST(E12,$F$5:$F$9,$E$5:$E$9) -> 10431.425 | G12: =(F12-F11)/F11 -> 0.074715935 | I12: =I11+1 -> 8 | J12: =J11+365 -> 47176 | K12: =FORECAST(J12,$K$5:$K$9,$J$5:$J$9) -> 1726.988 | L12: =(K12-K11)/K11 -> -0.011767318 | N12: =N11+1 -> 8 | O12: =O11+365 -> 47176 | P12: =FORECAST(O12,$P$5:$P$9,$O$5:$O$9) -> 29.2 | Q12: =(P12-P11)/P11 -> 0.13178295
D13: =D12+1 -> 9 | E13: =E12+365 -> 47541 | F13: =FORECAST(E13,$F$5:$F$9,$E$5:$E$9) -> 11156.634 | G13: =(F13-F12)/F12 -> 0.069521566 | I13: =I12+1 -> 9 | J13: =J12+365 -> 47541 | K13: =FORECAST(J13,$K$5:$K$9,$J$5:$J$9) -> 1706.424 | L13: =(K13-K12)/K12 -> -0.011907437 | N13: =N12+1 -> 9 | O13: =O12+365 -> 47541 | P13: =FORECAST(O13,$P$5:$P$9,$O$5:$O$9) -> 32.6 | Q13: =(P13-P12)/P12 -> 0.11643836
D14: =D13+1 -> 10 | E14: =E13+365 -> 47906 | F14: =FORECAST(E14,$F$5:$F$9,$E$5:$E$9) -> 11881.843 | G14: =(F14-F13)/F13 -> 0.065002491 | I14: =I13+1 -> 10 | J14: =J13+365 -> 47906 | K14: =FORECAST(J14,$K$5:$K$9,$J$5:$J$9) -> 1685.86 | L14: =(K14-K13)/K13 -> -0.012050932 | N14: =N13+1 -> 10 | O14: =O13+365 -> 47906 | P14: =FORECAST(O14,$P$5:$P$9,$O$5:$O$9) -> 36 | Q14: =(P14-P13)/P13 -> 0.10429448

Sheet Growth Scenario
A1: Scenario 1: High Growth
A2: INR Cr. | B2: LTM | C2: Y1E | D2: Y2E | E2: Y3E | F2: Y4W | G2: Y5E | H2: Y6E | I2: Y7E | J2: Y8E | K2: Y9E | L2: Y10E
A3: Sales | B3: =Assumptions!F3 -> 8194.02 | C3: =B3*(1+C4) -> 8805.5576 | D3: =C3*(1+D4) -> 9450.8654 | E3: =D3*(1+E4) -> 10130.724 | F3: =E3*(1+F4) -> 10845.833 | G3: =F3*(1+G4) -> 11596.799 | H3: =G3*(1+H4) -> 12384.13 | I3: =H3*(1+I4) -> 13208.221 | J3: =I3*(1+J4) -> 14069.344 | ... L3: =K3*(1+L4) -> 15903.122 | M3: =Assumptions!B23 -> 0.074632177 | P3: Risk free rate
A4: Sales Growth % | C4: =M3 -> 0.074632177 | D4: =C4-$O$4 -> 0.073284158 | E4: =D4-$O$4 -> 0.071936138 | F4: =E4-$O$4 -> 0.070588118 | G4: =F4-$O$4 -> 0.069240099 | H4: =G4-$O$4 -> 0.067892079 | I4: =H4-$O$4 -> 0.066544059 | J4: =I4-$O$4 -> 0.065196039 | K4: =J4-$O$4 -> 0.06384802 | L4: =K4-$O$4 -> 0.0625 | M4: =P4 -> 0.0625 | N4: =M3-M4 -> 0.012132177 | O4: =N4/9 -> 0.0013480197 | P4: =Wacc!B10 -> 0.0625
A6: Scenario 2: Average Growth
A7: INR Cr. | B7: LTM | C7: Y1E | D7: Y2E | E7: Y3E | F7: Y4W | G7: Y5E | H7: Y6E | I7: Y7E | J7: Y8E | K7: Y9E | L7: Y10E | N7: =Assumptions!B22 -> 0.098362188
A8: Sales | B8: =B3 -> 8194.02 | C8: =B8*(1+C9) -> 9000.0017 | D8: =C8*(1+D9) -> 9849.3994 | E8: =D8*(1+E9) -> 10739.714 | F8: =E8*(1+F9) -> 11667.713 | G8: =F8*(1+G9) -> 12629.406 | H8: =G8*(1+H9) -> 13620.041 | I8: =H8*(1+I9) -> 14634.108 | J8: =I8*(1+J9) -> 15665.365 | ... L8: =K8*(1+L9) -> 17751.051 | N8: =M4 -> 0.0625 | O8: =N7-N8 -> 0.035862188 | P8: =O8/9 -> 0.0039846875
A9: Sales Growth % | C9: =N7 -> 0.098362188 | D9: =C9-$P$8 -> 0.0943775 | E9: =D9-$P$8 -> 0.090392813 | F9: =E9-$P$8 -> 0.086408125 | G9: =F9-$P$8 -> 0.082423438 | H9: =G9-$P$8 -> 0.07843875 | I9: =H9-$P$8 -> 0.074454063 | J9: =I9-$P$8 -> 0.070469375 | K9: =J9-$P$8 -> 0.066484688 | L9: =K9-$P$8 -> 0.0625
A11: Scenario 3: EBIT Growth
A12: INR Cr. | B12: LTM | C12: Y1E | D12: Y2E | E12: Y3E | F12: Y4W | G12: Y5E | H12: Y6E | I12: Y7E | J12: Y8E | K12: Y9E | L12: Y10E | N12: =FCFF!B12*Assumptions!F43 -> 0.0063714534
A13: Sales | B13: =B8 -> 8194.02 | C13: =B13*(1+C14) -> 8246.2278 | D13: =C13*(1+D14) -> 8350.1959 | E13: =D13*(1+E14) -> 8507.5509 | F13: =E13*(1+F14) -> 8720.9285 | G13: =F13*(1+G14) -> 8994.0459 | H13: =G13*(1+H14) -> 9331.8082 | I13: =H13*(1+I14) -> 9740.4526 | J13: =I13*(1+J14) -> 10227.738 | ... L13: =K13*(1+L14) -> 11478.386 | N13: =N8 -> 0.0625 | O13: =N12-N13 -> -0.056128547 | P13: =O13/9 -> -0.0062365052
A14: Sales Growth % | C14: =N12 -> 0.0063714534 | D14: =C14-($P$13) -> 0.012607959 | E14: =D14-($P$13) -> 0.018844464 | F14: =E14-($P$13) -> 0.025080969 | G14: =F14-($P$13) -> 0.031317474 | H14: =G14-($P$13) -> 0.037553979 | I14: =H14-($P$13) -> 0.043790484 | J14: =I14-($P$13) -> 0.05002699 | K14: =J14-($P$13) -> 0.056263495 | L14: =K14-($P$13) -> 0.0625
A16: Live Scenario | B16: 3
A17: INR Cr. | B17: LTM | C17: Y1E | D17: Y2E | E17: Y3E | F17: Y4W | G17: Y5E | H17: Y6E | I17: Y7E | J17: Y8E | K17: Y9E | L17: Y10E
A18: Sales | B18: =B13 -> 8194.02 | C18: =B18*(1+C19) -> 8246.2278 | D18: =C18*(1+D19) -> 8350.1959 | E18: =D18*(1+E19) -> 8507.5509 | F18: =E18*(1+F19) -> 8720.9285 | G18: =F18*(1+G19) -> 8994.0459 | H18: =G18*(1+H19) -> 9331.8082 | I18: =H18*(1+I19) -> 9740.4526 | J18: =I18*(1+J19) -> 10227.738 | ... L18: =K18*(1+L19) -> 11478.386
A19: Sales Growth % | C19: =CHOOSE($B$16,C4,C9,C14) -> 0.0063714534 | D19: =CHOOSE($B$16,D4,D9,D14) -> 0.012607959 | E19: =CHOOSE($B$16,E4,E9,E14) -> 0.018844464 | F19: =CHOOSE($B$16,F4,F9,F14) -> 0.025080969 | G19: =CHOOSE($B$16,G4,G9,G14) -> 0.031317474 | H19: =CHOOSE($B$16,H4,H9,H14) -> 0.037553979 | I19: =CHOOSE($B$16,I4,I9,I14) -> 0.043790484 | J19: =CHOOSE($B$16,J4,J9,J14) -> 0.05002699 | ... L19: =CHOOSE($B$16,L4,L9,L14) -> 0.0625

Sheet DCF Valuation
C1: 1 | D1: 2 | E1: 3 | F1: 4 | G1: 5 | H1: 6 | I1: 7 | J1: 8 | K1: 9 | L1: 10
A2: INR Cr | B2: LTM | C2: Y1E | D2: Y2E | E2: Y3E | F2: Y4E | G2: Y5E | H2: Y6E | I2: Y7E | J2: Y8E | K2: Y9E | L2: Y10E | N2: Terminal Year | P2: Terminal growth rate % | Q2: =S22 -> 0.041640939
A3: Sales | B3: ='Growth Scenario'!B18 -> 8194.02 | C3: ='Growth Scenario'!C18 -> 8246.2278 | D3: ='Growth Scenario'!D18 -> 8350.1959 | E3: ='Growth Scenario'!E18 -> 8507.5509 | F3: ='Growth Scenario'!F18 -> 8720.9285 | G3: ='Growth Scenario'!G18 -> 8994.0459 | H3: ='Growth Scenario'!H18 -> 9331.8082 | I3: ='Growth Scenario'!I18 -> 9740.4526 | ... L3: ='Growth Scenario'!L18 -> 11478.386 | N3: =L3*(1+$Q$2) -> 11956.356 | P3: Cost of Capital % | Q3: =Wacc!D26 -> 0.16246627
A4: Sales Growth | C4: ='Growth Scenario'!C19 -> 0.0063714534 | D4: ='Growth Scenario'!D19 -> 0.012607959 | E4: ='Growth Scenario'!E19 -> 0.018844464 | F4: ='Growth Scenario'!F19 -> 0.025080969 | G4: ='Growth Scenario'!G19 -> 0.031317474 | H4: ='Growth Scenario'!H19 -> 0.037553979 | I4: ='Growth Scenario'!I19 -> 0.043790484 | J4: ='Growth Scenario'!J19 -> 0.05002699 | ... L4: ='Growth Scenario'!L19 -> 0.0625 | N4: =$Q$2 -> 0.041640939 | P4: Terminal reinvestment rate % | Q4: =Q2*Q3 -> 0.0067652479
A5: EBIT | C5: =C3*C6 -> 2090.1299 | D5: =D3*D6 -> 2116.4822 | E5: =E3*E6 -> 2156.3662 | F5: =F3*F6 -> 2210.4499 | G5: =G3*G6 -> 2279.6756 | H5: =H3*H6 -> 2365.2865 | I5: =I3*I6 -> 2468.8636 | J5: =J3*J6 -> 2592.3734 | ... L5: =L3*L6 -> 2909.3687 | N5: =N6*N3 -> 3030.5175
A6: EBIT Margin % | C6: =AVERAGE(Assumptions!B27:F27) -> 0.25346498 | D6: =C6 -> 0.25346498 | E6: =D6 -> 0.25346498 | F6: =E6 -> 0.25346498 | G6: =F6 -> 0.25346498 | H6: =G6 -> 0.25346498 | I6: =H6 -> 0.25346498 | J6: =I6 -> 0.25346498 | K6: =J6 -> 0.25346498 | L6: =K6 -> 0.25346498 | N6: =L6 -> 0.25346498 | P6: Enterprise value = Equity Value + Minority interest
A7: Less: Tax on EBIT | C7: =Assumptions!$B$33*'DCF Valuation'!C5 -> 522.53248 | D7: =Assumptions!$B$33*'DCF Valuation'!D5 -> 529.12055 | E7: =Assumptions!$B$33*'DCF Valuation'!E5 -> 539.09154 | F7: =Assumptions!$B$33*'DCF Valuation'!F5 -> 552.61248 | G7: =Assumptions!$B$33*'DCF Valuation'!G5 -> 569.91891 | H7: =Assumptions!$B$33*'DCF Valuation'!H5 -> 591.32163 | I7: =Assumptions!$B$33*'DCF Valuation'!I5 -> 617.21589 | J7: =Assumptions!$B$33*'DCF Valuation'!J5 -> 648.09335 | ... L7: =Assumptions!$B$33*'DCF Valuation'!L5 -> 727.34218 | N7: =Assumptions!$B$33*N5 -> 757.62939
A8: EBIT(1-T) | C8: =C5-C7 -> 1567.5974 | D8: =D5-D7 -> 1587.3617 | E8: =E5-E7 -> 1617.2746 | F8: =F5-F7 -> 1657.8374 | G8: =G5-G7 -> 1709.7567 | H8: =H5-H7 -> 1773.9649 | I8: =I5-I7 -> 1851.6477 | J8: =J5-J7 -> 1944.28 | ... L8: =L5-L7 -> 2182.0265 | N8: =N5-N7 -> 2272.8882
A9: Less: Net Capital Expenditure | C9: =C3*'Fixed Asset Scheduled'!$C$11 -> -257.28094 | D9: =D3*'Fixed Asset Scheduled'!$C$11 -> -260.52473 | E9: =E3*'Fixed Asset Scheduled'!$C$11 -> -265.43418 | F9: =F3*'Fixed Asset Scheduled'!$C$11 -> -272.09152 | G9: =G3*'Fixed Asset Scheduled'!$C$11 -> -280.61274 | H9: =H3*'Fixed Asset Scheduled'!$C$11 -> -291.15087 | I9: =I3*'Fixed Asset Scheduled'!$C$11 -> -303.90051 | J9: =J3*'Fixed Asset Scheduled'!$C$11 -> -319.10373 | ... L9: =L3*'Fixed Asset Scheduled'!$C$11 -> -358.12373
A10: Non Cash Working Capital | B10: ='Change in working capital'!F5 -> 23845.27 | C10: =('Change in working capital'!$F$5/'Consolidated P&L'!$F$7)*C3 -> 23997.199 | D10: =('Change in working capital'!$F$5/'Consolidated P&L'!$F$7)*D3 -> 24299.755 | E10: =('Change in working capital'!$F$5/'Consolidated P&L'!$F$7)*E3 -> 24757.671 | F10: =('Change in working capital'!$F$5/'Consolidated P&L'!$F$7)*F3 -> 25378.617 | G10: =('Change in working capital'!$F$5/'Consolidated P&L'!$F$7)*G3 -> 26173.411 | H10: =('Change in working capital'!$F$5/'Consolidated P&L'!$F$7)*H3 -> 27156.327 | I10: =('Change in working capital'!$F$5/'Consolidated P&L'!$F$7)*I3 -> 28345.516 | J10: =('Change in working capital'!$F$5/'Consolidated P&L'!$F$7)*J3 -> 29763.556 | ... L10: =('Change in working capital'!$F$5/'Consolidated P&L'!$F$7)*L3 -> 33403.043
A11: Less: Change in Working Capital | C11: =C10-B10 -> 151.92903 | D11: =D10-C10 -> 302.55569 | E11: =E10-D10 -> 457.91585 | F11: =F10-E10 -> 620.94637 | G11: =G10-F10 -> 794.79418 | H11: =H10-G10 -> 982.91574 | I11: =I10-H10 -> 1189.1887 | J11: =J10-I10 -> 1418.0408 | ... L11: =L10-K10 -> 1964.8849 | P11: GROWTH RATE | Q11: Roe *Retention Ratio
A12: Reinvestment | C12: =C9+C11 -> -105.35192 | D12: =D9+D11 -> 42.030961 | E12: =E9+E11 -> 192.48167 | F12: =F9+F11 -> 348.85484 | G12: =G9+G11 -> 514.18143 | H12: =H9+H11 -> 691.76487 | I12: =I9+I11 -> 885.2882 | J12: =J9+J11 -> 1098.9371 | ... L12: =L9+L11 -> 1606.7612 | N12: =N8*N14 -> 15.376652 | P12: roe | Q12: net income/equity share holder
A13: Free Cash Flow To Firm (FCFF) | C13: =C8-(C12) -> 1672.9494 | D13: =D8-(D12) -> 1545.3307 | E13: =E8-(E12) -> 1424.793 | F13: =F8-(F12) -> 1308.9826 | G13: =G8-(G12) -> 1195.5753 | H13: =H8-(H12) -> 1082.2 | I13: =I8-(I12) -> 966.35948 | J13: =J8-(J12) -> 845.34296 | ... L13: =L8-(L12) -> 575.26538 | N13: =N8-N12 -> 2257.5115 | Q13: ='Consolidated P&L'!F26/'Consolidated Balance Sheet'!F9 -> 0.057656822
A14: Implied Reinvestment rate % | C14: =C13/C8 -> 1.067206 | D14: =D13/D8 -> 0.9735215 | E14: =E13/E8 -> 0.88098393 | F14: =F13/F8 -> 0.78957235 | G14: =G13/G8 -> 0.69926632 | H14: =H13/H8 -> 0.61004591 | I14: =I13/I8 -> 0.52189166 | J14: =J13/J8 -> 0.43478457 | ... L14: =L13/L8 -> 0.26363812 | N14: =$Q$4 -> 0.0067652479 | P14: retention ratio | Q14: 1- payback
P15: share outstanding | Q15: mkt capital / share price
A16: Terminal Value | L16: =L13/(Q3-Q2) -> 4761.1323 | Q16: 152355/615.50
Q17: =152355/615.5 -> 247.53046
A18: Present Value Interest Factor(PVIF) | C18: =1/(1+$Q$3)^C1 -> 0.86024002 | D18: =1/(1+$Q$3)^D1 -> 0.74001288 | E18: =1/(1+$Q$3)^E1 -> 0.6365887 | F18: =1/(1+$Q$3)^F1 -> 0.54761907 | G18: =1/(1+$Q$3)^G1 -> 0.47108384 | H18: =1/(1+$Q$3)^H1 -> 0.40524517 | I18: =1/(1+$Q$3)^I1 -> 0.34860811 | J18: =1/(1+$Q$3)^J1 -> 0.29988665 | ... L18: =1/(1+$Q$3)^L1 -> 0.22191998 | Q18: ='Consolidated P&L'!E36/'DCF Valuation'!Q17 -> 5.000031 | R18: dps
R19: payback | S19: =Q18/'Consolidated P&L'!E33 -> 0.2777795
A20: Present value of FCFF | C20: =SUMPRODUCT(C18:L18,C13:L13) -> 6111.0995 | R20: retention | S20: =1-S19 -> 0.7222205
A21: Present value of Terminal value | C21: =L16*L18 -> 1056.5904
H22: Calculation of Sensitivity Analysis | Q22: growth rate | S22: =Q13*S20 -> 0.041640939
A23: Value of operating assets | C23: =C20+C21 -> 7167.6899 | H23: Terminal Growth ↓ / WACC → | I23: =K23-0.02 -> 0.14246627 | J23: =K23-0.01 -> 0.15246627 | K23: =$Q$3 -> 0.16246627 | L23: =K23+0.01 -> 0.17246627 | M23: =K23+0.02 -> 0.18246627
A24: Add: Cash | C24: =Assumptions!F39 -> 7746.4 | H24: =C30 -> 60.070052
A25: Less: Debt | C25: =Assumptions!F38 -> 44.95 | H25: =H26-0.01 -> 0.021640939 | I25: 62.5 | J25: 60.89 | K25: 59.46 | L25: 58.19 | M25: 57.05
A26: Less: Minority Interest | C26: ='Consolidated Balance Sheet'!F10 -> 0 | H26: =H27-0.01 -> 0.031640939 | I26: 62.96 | J26: 61.24 | K26: 59.74 | L26: 58.42 | M26: 57.23
A27: Equity Value | C27: =C23+C24-C25-C26 -> 14869.14 | H27: =$Q$2 -> 0.041640939 | I27: 63.51 | J27: 61.66 | K27: 60.07 | L27: 58.67 | M27: 57.43
H28: =H27+0.01 -> 0.051640939 | I28: 64.18 | J28: 62.17 | K28: 60.46 | L28: 58.97 | M28: 57.67
A29: No. of Shares outstanding (Cr) | C29: ='Consolidated Balance Sheet'!F6/2 -> 247.53 | H29: =H28+0.01 -> 0.061640939 | I29: 65.01 | J29: 62.78 | K29: 60.92 | L29: 59.33 | M29: 57.94
A30: intrinsic value per share | C30: =C27/C29 -> 60.070052

Sheet Relative Valuation
A1: RELATIVE VALUATION – DLF (FY2025 | INR Crores)
A3: Company | B3: Market Data | F3: Financial Data | J3: Valuation Ratios
B4: Price (₹) | C4: Shares (Cr.) | D4: Mkt Cap (Cr.) | E4: EV (Cr.) | F4: Revenue (Cr.) | G4: EBITDA (Cr.) | H4: EBIT (Cr.) | I4: EPS (₹) | J4: P/E | K4: EV/Sales | L4: EV/EBITDA | M4: EV/EBIT
A5: DLF | B5: 613.05 | C5: ='Consolidated Balance Sheet'!E6/2 -> 247.53 | D5: =B5*C5 -> 151748.27 | E5: =D5+'Consolidated Balance Sheet'!E12+'Consolidated Balance Sheet'!E18-'Consolidated Balance Sheet'!E40 -> 151264.22 | F5: =Assumptions!E3 -> 7993.66 | G5: =Assumptions!E9 -> 2108.64 | H5: =Assumptions!E11 -> 1957.98 | I5: ='Consolidated P&L'!E33 -> 18 | J5: =B5/I5 -> 34.058333 | K5: =E5/F5 -> 18.923024 | L5: =E5/G5 -> 71.735439 | M5: =E5/H5 -> 77.255241
A6: Lodha Developers | B6: 921.85 | C6: =999/10 -> 99.9 | D6: 92092.97 | E6: 98403 | F6: 16676 | G6: 4921 | H6: =4371+657 -> 5028 | I6: 34.32 | J6: =B6/I6 -> 26.860431 | K6: =E6/F6 -> 5.9008755 | L6: =E6/G6 -> 19.996545 | M6: =E6/H6 -> 19.571002
A7: Phoenix Mills | B7: 1848.7 | C7: =72/2 -> 36 | D7: 66116.99 | E7: 70587 | F7: 4423 | G7: 2637 | H7: =2032+387 -> 2419 | I7: 34.22 | J7: =B7/I7 -> 54.023963 | K7: =E7/F7 -> 15.959078 | L7: =E7/G7 -> 26.767918 | M7: =E7/H7 -> 29.18024
A8: Prestige Estates | B8: 1469.85 | C8: =431/10 -> 43.1 | D8: 63310.9 | E8: 78636 | F8: 12685 | G8: 3692 | H8: =1714+1582 -> 3296 | I8: 27.76 | J8: =B8/I8 -> 52.948487 | K8: =E8/F8 -> 6.1991328 | L8: =E8/G8 -> 21.299025 | M8: =E8/H8 -> 23.85801
A9: Oberoi Realty | B9: 1668 | C9: =364/10 -> 36.4 | D9: 60648.8 | E9: 61772 | F9: 6009 | G9: 3359 | H9: =3276+241 -> 3517 | I9: 68.96 | J9: =B9/I9 -> 24.187935 | K9: =E9/F9 -> 10.279913 | L9: =E9/G9 -> 18.389997 | M9: =E9/H9 -> 17.563833
A10: Godrej Propert. | B10: 1769.75 | C10: =151/5 -> 30.2 | D10: 53309.44 | E10: 63539 | F10: 5131 | G10: -453 | H10: =2551+137 -> 2688 | I10: 61.43 | J10: =B10/I10 -> 28.809214 | K10: =E10/F10 -> 12.383356 | L10: =E10/G10 -> -140.26269 | M10: =E10/H10 -> 23.638021
A11: Peer Average | B11: =AVERAGE(B6:B10) -> 1535.63 | C11: =AVERAGE(C6:C10) -> 49.12 | D11: =AVERAGE(D6:D10) -> 67095.82 | E11: =AVERAGE(E6:E10) -> 74587.4 | F11: =AVERAGE(F6:F10) -> 8984.8 | G11: =AVERAGE(G6:G10) -> 2831.2 | H11: =AVERAGE(H6:H10) -> 3389.6 | I11: =AVERAGE(I6:I10) -> 45.338 | ... M11: =AVERAGE(M6:M10) -> 22.762221
A12: Peer Median | B12: =MEDIAN(B6:B10) -> 1668 | C12: =MEDIAN(C6:C10) -> 36.4 | D12: =MEDIAN(D6:D10) -> 63310.9 | E12: =MEDIAN(E6:E10) -> 70587 | F12: =MEDIAN(F6:F10) -> 6009 | G12: =MEDIAN(G6:G10) -> 3359 | H12: =MEDIAN(H6:H10) -> 3296 | I12: =MEDIAN(I6:I10) -> 34.32 | ... M12: =MEDIAN(M6:M10) -> 23.638021
A14: NMDC — IMPLIED SHARE PRICE FROM PEER MULTIPLES
A15: Valuation Basis | B15: Peer Avg Multiple | C15: Peer Median Multiple | D15: NMDC Actual | E15: Implied EV (Avg) | F15: Implied EV (Median) | G15: Implied Equity (Avg) | H15: Implied Equity (Median) | I15: Implied Price (Avg) ₹ | J15: Implied Price (Med) ₹ | K15: CMP ₹ | L15: Premium/Disc (vs Avg) | M15: Premium/Disc (vs Med)
A16: EV / Sales | B16: =K11 -> 10.144471 | C16: =K12 -> 10.279913 | D16: =K5 -> 18.923024 | E16: =B16*F5 -> 81091.453 | F16: =C16*F5 -> 82174.133 | G16: =E16-(E5-D5) -> 81575.503 | H16: =F16-(E5-D5) -> 82658.183 | I16: =G16/C5 -> 329.55804 | J16: =H16/C5 -> 333.93198 | K16: =B5 -> 613.05 | L16: =(B5-I16)/I16 -> 0.86021859 | M16: =(B5-J16)/J16 -> 0.83585292
A17: EV / EBITDA | B17: =L11 -> -10.761842 | C17: =L12 -> 19.996545 | D17: =L5 -> 71.735439 | E17: =B17*G5 -> -22692.85 | F17: =C17*G5 -> 42165.516 | G17: =E17-(E5-D5) -> -22208.8 | H17: =F17-(E5-D5) -> 42649.566 | I17: =G17/C5 -> -89.721648 | J17: =H17/C5 -> 172.30059 | K17: =K16 -> 613.05 | L17: =(B5-I17)/I17 -> -7.8327991 | M17: =(B5-J17)/J17 -> 2.5580261
A18: P / E | B18: =J11 -> 37.366006 | C18: =J12 -> 28.809214 | D18: =J5 -> 34.058333 | E18: =B18*I5 -> 672.58811 | F18: =C18*I5 -> 518.56585 | G18: =E18*C5 -> 166485.73 | H18: =F18*C5 -> 128360.6 | I18: =E18 -> 672.58811 | J18: =F18 -> 518.56585 | K18: =K17 -> 613.05 | L18: =(B5-I18)/I18 -> -0.088520903 | M18: =(B5-J18)/J18 -> 0.18220281
O20: EV/Revenue | P20: EV/EBITDA | Q20: P/E Ratio
A21: Max | O21: =MAX(K6:K10) -> 15.959078 | P21: =MAX(L6:L10) -> 26.767918 | Q21: =MAX(J6:J10) -> 54.023963
A22: 75th Percentile | O22: =QUARTILE(K6:K10,3) -> 12.383356 | P22: =QUARTILE(L6:L10,3) -> 21.299025 | Q22: =QUARTILE(J6:J10,3) -> 52.948487
A23: Average | O23: =AVERAGE(K6:K10) -> 10.144471 | P23: =AVERAGE(L6:L10) -> -10.761842 | Q23: =AVERAGE(J6:J10) -> 37.366006
A24: median | O24: =MEDIAN(K6:K10) -> 10.279913 | P24: =MEDIAN(L6:L10) -> 19.996545 | Q24: =MEDIAN(J6:J10) -> 28.809214
A25: 25th Percentile | O25: =QUARTILE(K6:K10,1) -> 6.1991328 | P25: =QUARTILE(L6:L10,1) -> 18.389997 | Q25: =QUARTILE(J6:J10,1) -> 26.860431
A26: Min. | O26: =MIN(K6:K10) -> 5.9008755 | P26: =MIN(L6:L10) -> -140.26269 | Q26: =MIN(J6:J10) -> 24.187935
A28: Industry Comparable comps | O28: EV/Revenue | P28: EV/EBITDA | Q28: P/E Ratio
A30: Implied Enterprise Value | O30: =O23*F5 -> 81091.453 | P30: =P23*G5 -> -22692.85 | Q30: =Q23*I5*C5 -> 166485.73
A31: Net Debt | O31: =E5-D5 -> -484.05 | P31: =E5-D5 -> -484.05 | Q31: =E5-D5 -> -484.05
A32: Implied Market Value | O32: =O30-O31 -> 81575.503 | P32: =P30-P31 -> -22208.8 | Q32: =Q30-Q31 -> 166969.78
A33: Share Outstanding | O33: =C5 -> 247.53 | P33: =C5 -> 247.53 | Q33: =C5 -> 247.53
A35: Implied Value per Share | O35: =O32/O33 -> 329.55804 | P35: =P32/P33 -> -89.721648 | Q35: =Q23*I5 -> 672.58811

Sheet Gordon growth model
A1: Gordon Growth Model (Dividend Discount Model) — DLF
A2: Intrinsic Value = D1 / (Ke - g) where D1 = next year dividend, Ke = cost of equity, g = sustainable growth rate
A4: STEP 1: Historical Dividend Per Share
A5: Year | B5: FY22 | C5: FY23 | D5: FY24 | E5: FY25
A6: Total Equity Dividend Paid (Rs Cr) | B6: ='Consolidated P&L'!B36 -> 495.06 | C6: ='Consolidated P&L'!C36 -> 742.59 | D6: ='Consolidated P&L'!D36 -> 990.12 | E6: ='Consolidated P&L'!E36 -> 1237.66
A7: Shares Outstanding (Cr) | B7: ='Consolidated Balance Sheet'!B6/2 -> 247.53 | C7: ='Consolidated Balance Sheet'!C6/2 -> 247.53 | D7: ='Consolidated Balance Sheet'!D6/2 -> 247.53 | E7: ='Consolidated Balance Sheet'!E6/2 -> 247.53
A8: Dividend Per Share - DPS (Rs) | B8: =B6/B7 -> 2 | C8: =C6/C7 -> 3 | D8: =D6/D7 -> 4 | E8: =E6/E7 -> 5.0000404
A10: STEP 2: Dividend Growth Rate (g)
A11: YoY DPS Growth | C11: =(C8-B8)/B8 -> 0.5 | D11: =(D8-C8)/C8 -> 0.33333333 | E11: =(E8-D8)/D8 -> 0.2500101
A12: Average Historical DPS Growth | B12: =AVERAGE(C11:E11) -> 0.36111448 | C12: (FY23 to FY25 average)
A13: CAGR of DPS (FY22 to FY25) | B13: =(E8/B8)^(1/3)-1 -> 0.35721246 | C13: (3 year CAGR)
A14: Revenue CAGR (from Assumptions sheet) | B14: =Assumptions!B23 -> 0.074632177 | C14: (used as proxy for sustainable growth)
A16: Dividend Growth Rate Used (g) | B16: =B14 -> 0.074632177 | C16: Revenue CAGR used as g (DPS CAGR FY22-25 unreliable due to low base - see B13)
A18: STEP 3: Cost of Equity (Ke) — from CAPM
A19: Risk Free Rate (Rf) | B19: =Wacc!B10 -> 0.0625 | C19: RBI 10Y Gsec yield
A20: Beta (β) | B20: =Wacc!B11 -> 1.5661234 | C20: Regression beta from Nifty50 vs DLF
A21: Market Risk Premium (Rm - Rf) | B21: =Wacc!B12 -> 0.065 | C21: India ERP (Damodaran)
A22: Cost of Equity Ke = Rf + β × (Rm - Rf) | B22: =Wacc!B13 -> 0.16429802
A24: STEP 4: Validity Check — Ke must be > g
A25: Cost of Equity (Ke) | B25: =B22 -> 0.16429802
A26: Growth Rate (g) | B26: =B16 -> 0.074632177
A27: Ke - g (spread) | B27: =B25-B26 -> 0.089665843 | C27: =IF(B27>0,"Valid — model can proceed","INVALID — g cannot exceed Ke") -> Valid — model can proceed
A29: STEP 5: D1 — Expected Dividend Next Year
A30: D0 — Latest DPS (FY25) | B30: =E8 -> 5.0000404 | C30: FY25 actual dividend per share
A31: D1 = D0 × (1 + g) | B31: =B30*(1+B16) -> 5.3732043 | C31: Expected dividend in next year (D1)
A33: STEP 6: Intrinsic Value per Share
A34: Gordon Growth Model Formula: P = D1 / (Ke - g)
A35: Intrinsic Value (P) | B35: =B31/(B25-B26) -> 59.924762
A36: Current Market Price (CMP) | B36: =Beta!C1532 -> 587.04999 | C36: DLF CMP from Beta sheet (latest close)
A37: Premium / (Discount) to Intrinsic Value | B37: =(B36-B35)/B35 -> 8.7964509 | C37: =IF(B36>B35,"Stock is OVERVALUED vs GGM","Stock is UNDERVALUED vs GGM") -> Stock is OVERVALUED vs GGM
A39: STEP 7: Sensitivity Analysis — Intrinsic Value at different g and Ke
A40: g ↓ / Ke → | B40: =B22-0.02 -> 0.14429802 | C40: =B22-0.01 -> 0.15429802 | D40: =B22 -> 0.16429802 | E40: =B22+0.01 -> 0.17429802 | F40: =B22+0.02 -> 0.18429802
A41: =B16-0.01 -> 0.064632177 | B41: =B31/(B22+-0.02-(B16+-0.01)) -> 67.446776 | C41: =B31/(B22+-0.01-(B16+-0.01)) -> 59.924762 | D41: =B31/(B22-(B16+-0.01)) -> 53.912194 | E41: =B31/(B22+0.01-(B16+-0.01)) -> 48.996152 | F41: =B31/(B22+0.02-(B16+-0.01)) -> 44.901738
A42: =B16 -> 0.074632177 | B42: =B31/(B22+-0.02-(B16)) -> 77.128246 | C42: =B31/(B22+-0.01-(B16)) -> 67.446776 | D42: =B31/(B22-(B16)) -> 59.924762 | E42: =B31/(B22+0.01-(B16)) -> 53.912194 | F42: =B31/(B22+0.02-(B16)) -> 48.996152
A43: =B16+0.01 -> 0.084632177 | B43: =B31/(B22+-0.02-(B16+0.01)) -> 90.054946 | C43: =B31/(B22+-0.01-(B16+0.01)) -> 77.128246 | D43: =B31/(B22-(B16+0.01)) -> 67.446776 | E43: =B31/(B22+0.01-(B16+0.01)) -> 59.924762 | F43: =B31/(B22+0.02-(B16+0.01)) -> 53.912194
A44: =B16+0.02 -> 0.094632177 | B44: =B31/(B22+-0.02-(B16+0.02)) -> 108.18711 | C44: =B31/(B22+-0.01-(B16+0.02)) -> 90.054946 | D44: =B31/(B22-(B16+0.02)) -> 77.128246 | E44: =B31/(B22+0.01-(B16+0.02)) -> 67.446776 | F44: =B31/(B22+0.02-(B16+0.02)) -> 59.924762
A45: =B16+0.03 -> 0.10463218 | B45: =B31/(B22+-0.02-(B16+0.03)) -> 135.46174 | C45: =B31/(B22+-0.01-(B16+0.03)) -> 108.18711 | D45: =B31/(B22-(B16+0.03)) -> 90.054946 | E45: =B31/(B22+0.01-(B16+0.03)) -> 77.128246 | F45: =B31/(B22+0.02-(B16+0.03)) -> 67.446776

Sheet Stock Analysis
D1: Metric | E1: Value | G1: Financial Year | H1: Revenue (₹ Crore) | I1: Profit After Tax (PAT) (₹ Crore) | J1: Revenue Change (%) | K1: PAT Change (%) | L1: Nifty 50 Prices | M1: Nifty 50 Change (%)
D2: Market Cap | E2: 154261 | G2: FY 2025-26 | H2: 8194 | I2: 4415 | J2: =(H2-H3)/H3 -> 0.025018764 | K2: =(I2-I3)/I3 -> 0.010991527 | L2: 23853.9 | M2: =(L2-L3)/L3 -> -0.087092799
D3: Current Price | E3: 623 | G3: FY 2024-25 | H3: 7994 | I3: 4367 | J3: =(H3-H4)/H4 -> 0.24381515 | K3: =(I3-I4)/I4 -> 0.60315712 | L3: 26129.6 | M3: =(L3-L4)/L4 -> 0.10400541
D4: High / Low | E4: 882 / 489 | G4: FY 2023-24 | H4: 6427 | I4: 2724 | J4: =(H4-H5)/H5 -> 0.1285338 | K4: =(I4-I5)/I5 -> 0.33923304 | L4: 23668 | M4: =(L4-L5)/L5 -> 0.089365933
D5: Stock P/E | E5: ='Relative Valuation'!J5 -> 34.058333 | G5: FY 2022-23 | H5: 5695 | I5: 2034 | J5: =(H5-H6)/H6 -> -0.0038481721 | K5: =(I5-I6)/I6 -> 0.356 | L5: 21726.4 | M5: =(L5-L6)/L6 -> 0.20000221
D6: Book Value | E6: 184 | G6: FY 2021-22 | H6: 5717 | I6: 1500 | L6: 18105.3
D7: Dividend Yield | E7: 0.0098
D8: ROCE | E8: 0.0634
D9: ROE | E9: 0.0962
D10: Face Value | E10: 2
D12: DLF LIMITED — EQUITY RESEARCH NOTE
D13: Initiating Coverage | Real Estate — Premium Residential & Annuity | Recommendation: HOLD | CMP: ₹623 | 12-Month Target: ₹710
D15: 1. INVESTMENT THESIS
D16: DLF Limited is India's pre-eminent premium and luxury real estate developer with an unrivalled 60+ year track record. The company operates a uniquely positioned dual-engine business model: (i) a high-margin Residential Development business driven by super-luxury launches such as The Dahlias and Privana, and (ii) a stable, contractually annuity-like Rental business held through DCCDL (66.66% owned JV with GIC, Singapore) spanning 45 msf of Grade-A offices, retail malls and hospitality assets. This combination delivers a rare mix of cyclical earnings upside through residential bookings and defensive cash flow stability through long-lease rental income — making DLF one of the most resilient real estate franchises in the country. The FY2024-25 consolidated revenue of ₹7,994 Cr (+24.4% YoY) and PAT of ₹4,368 Cr (+60.3% YoY) confirm that the residential upcycle is firmly intact. Record pre-sales on new launches and strong rental EBITDA from DCCDL are the twin growth engines. Consolidated Cash & Cash Equivalents stand at ₹4,338 Cr as of Mar 2025, providing ample runway for land acquisition and capital deployment without balance sheet stress. Promoter holding remains high at 74.08%, signalling alignment with long-term value creation.
D18: 2. KEY FINANCIAL METRICS AT A GLANCE
D19: Metric | E19: FY22 | F19: FY23 | G19: FY24 | H19: FY25 | I19: FY26E
D20: Revenue (₹ Cr) | E20: 5717 | F20: 5695 | G20: 6427 | H20: 7994 | I20: 8194
D21: YoY Growth (%) | E21: – | F21: -0.4% | G21: +12.9% | H21: +24.4% | I21: +2.5%
D22: PAT — Consol. (₹ Cr) | E22: 1501 | F22: 2036 | G22: 2727 | H22: 4368 | I22: 4415
D23: PAT Growth (%) | E23: – | F23: +35.6% | G23: +34.0% | H23: +60.2% | I23: +1.1%
D24: EPS — Basic (₹) | E24: 6 | F24: 8 | G24: 11 | H24: 18 | I24: 18
D25: EBITDA Margin (%)* | E25: 0.31 | F25: 0.33 | G25: 0.38 | H25: 0.37 | I25: 38%E
D26: ROCE (%) | E26: – | F26: – | G26: – | H26: 6.3% | I26: –
D27: ROE (%) | E27: – | F27: – | G27: – | H27: 9.6% | I27: –
D28: Dividend (₹ Cr) | E28: 495 | F28: 743 | G28: 990 | H28: 1238 | I28: –
D29: Net Debt / Equity | E29: Low | F29: Low | G29: Moderate | H29: Low | I29: Low
D32: 3. SHAREHOLDING STRUCTURE & INSTITUTIONAL INTEREST
D33: Category | E33: Shareholders | F33: Shares Held | G33: Stake (%) | H33: Voting Rights (%) | M33: Key Insight
D34: Promoter & Promoter Group | E34: 13 | F34: 1,833,636,385 | G34: 74.08% | H34: 74.08% | M34: Rajdhani Inv. & Agencies Pvt. Ltd holds 61.53% — cornerstone family control
D35: Domestic Institutions (MFs, Insurance, PF) | E35: 77 | F35: 171,773,695 | G35: 6.94% | H35: 6.94% | M35: SBI Equity Hybrid & ICICI Pru Large Cap among top holders — quality DII base
D36: Foreign Portfolio Investors (FPI) | E36: 726 | F36: 335,171,497 | G36: 13.54% | H36: 13.54% | M36: Invesco Global Fund (1.30%) — meaningful FII conviction; Cat I dominates
D37: Retail & Non-Institutions | E37: 505,753+ | F37: 134,727,246 | G37: 5.44% | H37: 5.44% | M37: 487K+ retail holders; robust shareholder breadth
D38: TOTAL | E38: 506,572 | F38: 2,475,311,706 | G38: 100.00% | H38: 100.00%
D41: 4. VALUATION, RISKS & INVESTMENT RECOMMENDATION
D42: Valuation Summary | H42: Key Risks
D43: CMP (₹) | G43: ₹623 | H43: ▪ Real estate cycle risk: residential presales can slow sharply in a rate-tightening or demand-slowdown environment.
D44: Market Cap (₹ Cr) | G44: ₹1,54,261 Cr | H44: ▪ Execution risk: large pipeline of 205 msf requires sustained capital deployment and delivery capability.
D45: Stock P/E (TTM) | G45: 34.1x | H45: ▪ Concentration risk: DCCDL rental income (~40% of revenue mix) depends on Grade-A office absorption trends.
D46: Book Value / Share (₹) | G46: ₹184 | H46: ▪ Regulatory risk: GST, RERA, and approval delays can compress margins and stretch working capital cycles.
D47: Price-to-Book (P/B) | G47: ~3.4x | H47: ▪ Valuation premium: at 34x P/E, stock already prices in near-term earnings optimism; limited margin of safety.
D48: Dividend Yield | G48: 0.98% | H48: ▪ Promoter holding at 74.08% limits free float — large block sales could trigger sharp price corrections.
D49: Beta (vs Nifty 50) | G49: 1.57 (high sensitivity)
D50: 52-Week High / Low | G50: ₹882 / ₹489
D51: DCF-Based Fair Value* | G51: ₹640–₹720 range
D52: 12-Month Price Target | G52: ₹710 (upside ~14%)
D54: ANALYST RECOMMENDATION — HOLD | CMP: ₹623 | TARGET: ₹710 | UPSIDE: 14%
D55: HOLD — DLF is a quality franchise trading at a fair, though not cheap, valuation. We initiate with a HOLD recommendation at the current market price of ₹623, with a 12-month price target of ₹710 implying ~14% upside. This target is derived from a blended DCF-based intrinsic value estimate (WACC-based FCFF model) and a relative valuation cross-check using sector P/E and EV/EBITDA multiples. BULL CASE (Target: ₹820+): Sustained luxury residential bookings above ₹15,000 Cr annually, DCCDL office occupancy trending above 92%, accelerated land acquisition in NCR/MMR, and a broader re-rating of Indian real estate multiples could push the stock toward its 52-week high and beyond. BASE CASE (Target: ₹710): Revenue growth of 8–12% over FY26–27E on steady presales momentum, DCCDL rental EBITDA growing ~10% YoY driven by new office and mall completions, and manageable balance sheet with net debt/equity below 0.3x. Beta of 1.57 means this stock amplifies market moves — time entry carefully. BEAR CASE (Target: ₹490–520): A sharp slowdown in luxury housing demand (interest rate spike, wealth effect reversal), rising unsold inventory in Gurugram, and a correction in commercial office absorption due to GCC hiring freeze could compress multiples and drag the stock toward its 52-week low. Dividend yield of ~1% provides limited downside cushion. SINGLE METRIC TO WATCH: Residential pre-sales bookings for FY26 (company guidance: ₹17,000+ Cr). If this number is delivered, the stock will re-rate higher. Miss it, and the 34x P/E becomes a significant headwind. Disclosure: This note is for academic/educational purposes only and does not constitute SEBI-registered investment advice.
D56: 5. MARKET SENSITIVITY (BETA ANALYSIS)
D57: DLF's Beta (β) against Nifty 50 stands at approximately 1.57 (OLS regression, daily returns, 6-year window as per the Beta sheet). This is materially above 1.0, indicating DLF is a high-beta, market-sensitive stock. What this means for investors: ▪ In a Nifty bull run of +10%, DLF is expected to gain approximately +15.7% on average — meaningful amplification. ▪ In a Nifty correction of -10%, DLF tends to fall approximately -15.7% — significantly higher downside than the index. ▪ R-squared of ~0.44 implies ~44% of DLF's price variance is explained by market movement; the remaining ~56% is driven by company-specific factors (pre-sales data, rental updates, management guidance, real estate cycle news). ▪ Implication: DLF is best held by investors with a medium-to-long investment horizon who can absorb inter-quarter volatility. Short-term traders must size positions conservatively given the elevated beta. Portfolio managers with strict VaR constraints should note that DLF adds meaningful systematic risk to a portfolio.
