Workbook

Sheet About the Company
C1: About the Company
C3: Info Edge (India) Limited is one of India's most prominent consumer internet companies, founded in 1995 by Sanjeev Bikhchandani and listed on NSE & BSE since 2006. With a market capitalisation of over ₹920 Billion (as of March 31, 2025), the Company operates four leading digital platforms — Recruitment (Naukri), Real Estate (99acres), Matchmaking (Jeevansathi), and Education (Shiksha) — enabling millions of Indians to make critical life decisions. Products & Services — Naukri: India's #1 job portal & talent solutions platform (iimjobs, Hirist, AmbitionBox, JobHai, DoSelect, Naukri Campus, NaukriGulf). 99acres: India's leading real estate classifieds. Jeevansathi & Aisle: Online matchmaking platforms. Shiksha: Education classifieds (domestic & study abroad). Investment Portfolio: 110+ investments across balance sheet and AIF (Eternal/Zomato, PB Fintech, and others). Vision — To create world-class platforms that transform lives. Mission — To continuously delight customers in current and new businesses by delivering superior value through enhanced offerings on the Internet and other platforms, preserving entrepreneurial spirit and leveraging financial strength in building brands, communities, products and technology. FY25 Key Highlights — Standalone Billings: ₹28,817 Mn | Standalone Revenue (Net): ₹26,536 Mn | Recruitment Op. PBT Margin: 56.3% | Non-Recruitment businesses turned cash-positive for the first time. EPS (pre-exceptional, post split): ₹15.42 | Dividend: ₹6/share | Active Investments: 110+ | Value of Listed Investments: ₹333 Bn | AI Team: 130+ professionals.
C5: Business Verticals & Platforms
C6: Vertical | D6: Key Platform(s) | E6: Description | F6: FY25 Billings
C7: Recruitment | D7: Naukri, iimjobs, Hirist, AmbitionBox, JobHai, DoSelect, NaukriGulf | E7: India's leading job portal; full-stack talent solutions across sourcing, assessment, branding & automation | F7: ₹21,577 Mn (FY25)
C8: Real Estate | D8: 99acres | E8: India's #1 online real estate classifieds for buying, selling and renting residential & commercial property | F8: ₹4,507 Mn (FY25)
C9: Matchmaking | D9: Jeevansathi, Aisle, Zwayam | E9: Online matrimonial and social networking platform; also includes enterprise HR tech (Zwayam) | F9: ₹1,400 Mn (FY25 est.)
C10: Education | D10: Shiksha | E10: Education classifieds for domestic admissions and study-abroad; growing rapidly in new private universities | F10: ₹1,624 Mn (FY25)
C12: Subsidiaries, Associates & Key Investments
C13: S.No | D13: Entity Name | E13: Type | F13: Stake / Details
C14: 1 | D14: Info Edge (India) Limited | E14: Listed Parent (NSE: NAUKRI) | F14: Holding & Operating Co.
C15: 2 | D15: Allcheckdeals India Pvt. Ltd. | E15: Wholly Owned Subsidiary | F15: 99acres – Real Estate
C16: 3 | D16: Jeevansathi Internet Services Pvt. Ltd. | E16: Wholly Owned Subsidiary | F16: Matchmaking
C17: 4 | D17: Naukri Internet Services Pvt. Ltd. | E17: Wholly Owned Subsidiary | F17: Recruitment
C18: 5 | D18: Info Edge Ventures Fund I & II (AIF) | E18: AIF – Venture Capital | F18: Early-stage startups
C19: 6 | D19: Eternal Ltd. (formerly Zomato) | E19: Listed Associate / Investment | F19: Food-tech; value ₹333 Bn+ combined
C20: 7 | D20: PB Fintech Ltd. (PolicyBazaar) | E20: Listed Investment | F20: Fintech – insurance aggregator
C21: 8 | D21: Strategic Portfolio Entities | E21: Strategic Investments (7 entities) | F21: ₹3,971 Mn invested
C22: 9 | D22: Financial Portfolio Companies | E22: Financial Investments (110+ entities) | F22: ₹17,553 Mn invested in startups
C24: Registered Office & Corporate Details
C25: Ground Floor, GF-12A, 94 Meghdoot, Nehru Place, New Delhi – 110019
C26: CIN: L74899DL1995PLC068827
C27: BSE Scrip Code: 532777 | NSE Symbol: NAUKRI | ISIN: INE663F01024
C28: Website: www.infoedge.in | Investor Email: investorrelations@infoedge.in
C29: Statutory Auditor: S.R. Batliboi & Associates LLP (ICAI Reg. 101049W/E300004)
C30: FY End: March 31 | Incorporated: 1995 | Listed: 2006
C32: Operational Footprint & Key Metrics (FY25)
C33: Metric | D33: Platform / Unit | E33: Value | F33: Notes
C34: Total Employees (FY25) | D34: Consolidated | E34: ~6,548 | F34: Permanent + contract; 4,179 permanent
C35: Naukri Resumes (Active DB) | D35: Naukri | E35: ~100 Mn+ | F35: Largest resume database in India
C36: Job Listings | D36: Naukri | E36: Millions per annum | F36: B2B; 56,000+ active recruiters
C37: Properties Listed | D37: 99acres | E37: Millions per annum | F37: Buy/sell/rent listings
C38: Shiksha Colleges Listed | D38: Shiksha | E38: 50,000+ | F38: Domestic + international
C39: Countries of Operation | D39: Info Edge | E39: 2 (India, Gulf) | F39: NaukriGulf covers MENA region
C40: Stock Exchanges Listed | D40: Info Edge | E40: 2 (BSE & NSE) | F40: Part of Nifty 500 index
C41: AI/ML Models Deployed | D41: Tech Platform | E41: 500+ | F41: Across all verticals; 130+ AI team
C43: Board of Directors (As on March 31, 2025)
C44: Name | D44: Designation / Category
C45: Mr. Kapil Kapoor | D45: Non-Executive Chairman
C46: Mr. Sanjeev Bikhchandani | D46: Founder & Executive Vice-Chairman
C47: Mr. Hitesh Oberoi | D47: Co-Promoter, Managing Director & CEO
C48: Mr. Chintan Thakkar | D48: Whole-time Director & CFO
C49: Mr. Pawan Goyal | D49: Whole-time Director & Chief Business Officer – Naukri
C50: Mr. Ashish Gupta | D50: Independent Director
C51: Ms. Geeta Mathur | D51: Independent Director
C52: Ms. Aruna Sundararajan | D52: Independent Director
C53: Mr. Arindam Kumar Bhattacharya | D53: Independent Director
C54: Mr. Sanjiv Sachar | D54: Independent Director
C56: Key Managerial Personnel (KMP)
C57: Name | D57: Designation
C58: Mr. Hitesh Oberoi | D58: Managing Director & Chief Executive Officer
C59: Mr. Chintan Thakkar | D59: Whole-time Director & Chief Financial Officer
C60: Ms. Jaya Bhatia | D60: Company Secretary
C62: Source: Info Edge Annual Report FY2024-25 | Data as of March 31, 2025 | All figures in INR unless stated

Sheet Promoter
A1: INFO EDGE (INDIA) LIMITED — PROMOTER SHAREHOLDING PATTERN | As on March 31, 2025
A2: Category of shareholder | B2: Entity Type | C2: Nos. of shareholders | D2: No. of fully paid up equity shares held | E2: Total nos. shares held | F2: Shareholding as a % of total no. of shares (calculated as per SCRR, 1957)As a % of (A+B+C2) | G2: Number of Voting Rights held in each class of securities | I2: Total No. Of shares on fully diluted basis (including warrants, ESOP, Convertible Securities etc.) | J2: Shareholding , as a % assuming full conversion of convertible securities ( as a percentage of diluted share capital)As a % of (A+B+C2) | K2: Number of equity shares held in dematerialized form
G3: Class eg: X | H3: Total
A5: A9) Indian | C5: - | D5: - | E5: - | F5: 0 | G5: - | H5: 0 | I5: - | J5: 0 | K5: -
A6: Individuals/Hindu undivided Family | C6: 4 | D6: 202814070 | E6: 202814070 | F6: 31.28 | G6: 202814070 | H6: 31.28 | I6: 202814070 | J6: 31.28 | K6: 202814070
A7: Sanjeev Bikhchandani | B7: Promoter | C7: 1 | D7: 155995490 | E7: 155995490 | F7: 24.06 | G7: 155995490 | H7: 24.06 | I7: 155995490 | J7: 24.06 | K7: 155995490
A8: Hitesh Oberoi | B8: Promoter | C8: 1 | D8: 32007350 | E8: 32007350 | F8: 4.94 | G8: 32007350 | H8: 4.94 | I8: 32007350 | J8: 4.94 | K8: 32007350
A9: Surabhi Motihar Bikhchandani | B9: Promoter Group | C9: 1 | D9: 7470160 | E9: 7470160 | F9: 1.15 | G9: 7470160 | H9: 1.15 | I9: 7470160 | J9: 1.15 | K9: 7470160
A10: Dayawanti Bikhchandani | B10: Promoter Group | C10: 1 | D10: 7341070 | E10: 7341070 | F10: 1.13 | G10: 7341070 | H10: 1.13 | I10: 7341070 | J10: 1.13 | K10: 7341070
A11: Rimy Oberoi | B11: Promoter Group | C11: - | D11: - | E11: - | F11: 0 | G11: - | H11: 0 | I11: - | J11: 0 | K11: -
A12: Suresh Kumar Oberai | B12: Promoter Group | C12: - | D12: - | E12: - | F12: 0 | G12: - | H12: 0 | I12: - | J12: 0 | K12: -
A13: Meera Oberai | B13: Promoter Group | C13: - | D13: - | E13: - | F13: 0 | G13: - | H13: 0 | I13: - | J13: 0 | K13: -
A14: Misha Oberoi | B14: Promoter Group | C14: - | D14: - | E14: - | F14: 0 | G14: - | H14: 0 | I14: - | J14: 0 | K14: -
A15: Megha Oberoi | B15: Promoter Group | C15: - | D15: - | E15: - | F15: 0 | G15: - | H15: 0 | I15: - | J15: 0 | K15: -
A16: Divya Batra | B16: Promoter Group | C16: - | D16: - | E16: - | F16: 0 | G16: - | H16: 0 | I16: - | J16: 0 | K16: -
A17: Raghav Bikhchandani | B17: Promoter Group | C17: - | D17: - | E17: - | F17: 0 | G17: - | H17: 0 | I17: - | J17: 0 | K17: -
A18: Tanvi Bikhchandani | B18: Promoter Group | C18: - | D18: - | E18: - | F18: 0 | G18: - | H18: 0 | I18: - | J18: 0 | K18: -
A19: Sushil Bikhchandani | B19: Promoter Group | C19: - | D19: - | E19: - | F19: 0 | G19: - | H19: 0 | I19: - | J19: 0 | K19: -
A20: Sunita Gehani | B20: Promoter Group | C20: - | D20: - | E20: - | F20: 0 | G20: - | H20: 0 | I20: - | J20: 0 | K20: -
A21: Ratan Ramchand Motihar | B21: Promoter Group | C21: - | D21: - | E21: - | F21: 0 | G21: - | H21: 0 | I21: - | J21: 0 | K21: -
A22: Pushpa Motihar | B22: Promoter Group | C22: - | D22: - | E22: - | F22: 0 | G22: - | H22: 0 | I22: - | J22: 0 | K22: -
... A27: Rejoy Manjuran | B27: Promoter Group | C27: - | D27: - | E27: - | F27: 0 | G27: - | H27: 0 | I27: - | J27: 0 | K27: -
A28: Any Other (specify) | C28: 1 | D28: 40312605 | E28: 40312605 | F28: 6.22 | G28: 40312605 | H28: 6.22 | I28: 40312605 | J28: 6.22 | K28: 40312605
A29: Sanjeev Bikhchandani & Hitesh Oberoi (Endeavour Holding Trust) | B29: Promoter Group | C29: 1 | D29: 40312605 | E29: 40312605 | F29: 6.22 | G29: 40312605 | H29: 6.22 | I29: 40312605 | J29: 6.22 | K29: 40312605
A30: Calangute Advisory Services Pvt. Ltd. | B30: Promoter Group | C30: - | D30: - | E30: - | F30: 0 | G30: - | H30: 0 | I30: - | J30: 0 | K30: -
A31: Roomal Craft Private Limited | B31: Promoter Group | C31: - | D31: - | E31: - | F31: 0 | G31: - | H31: 0 | I31: - | J31: 0 | K31: -
A32: Minik Enterprises | B32: Promoter Group | C32: - | D32: - | E32: - | F32: 0 | G32: - | H32: 0 | I32: - | J32: 0 | K32: -
A33: Sub Total A1 | C33: 5 | D33: 243126675 | E33: 243126675 | F33: 37.5 | G33: 243126675 | H33: 37.5 | I33: 243126675 | J33: 37.5 | K33: 243126675
A34: A10) Foreign | C34: - | D34: - | E34: - | F34: 0 | G34: - | H34: 0 | I34: - | J34: 0 | K34: -
A35: A=A1+A2 | C35: 5 | D35: 243126675 | E35: 243126675 | F35: 37.5 | G35: 243126675 | H35: 37.5 | I35: 243126675 | J35: 37.5 | K35: 243126675

Sheet Public
A1: INFO EDGE (INDIA) LIMITED — PUBLIC SHAREHOLDING PATTERN | As on March 31, 2025
A2: Category & Name of the Shareholders | B2: No. of shareholder | C2: No. of fully paid up equity shares held | D2: Total no. shares held | E2: Shareholding % calculated as per SCRR, 1957 As a % of (A+B+C2) | F2: No. of Voting Rights | G2: Total as a % of Total Voting right | H2: Total No. Of shares on fully diluted basis (including warrants, ESOP, Convertible Securities etc.) | I2: Shareholding , as a % assuming full conversion of convertible securities ( as a percentage of diluted share capital)As a % of (A+B+C2) | J2: No. of equity shares held in dematerialized form(Not Applicable) | K2: Sub-categorization of shares (XV)
K3: Shareholding (No. of shares) under
K4: SubCategory_I | L4: SubCategory_II | M4: SubCategory_III
A5: Institutions | B5: 0 | C5: 0 | D5: - | E5: 0 | F5: - | G5: 0 | H5: - | I5: 0 | J5: - | K5: - | L5: - | M5: -
A6: B2) Institutions (Domestic) | B6: 0 | C6: 0 | D6: - | E6: 0 | F6: - | G6: 0 | H6: - | I6: 0 | J6: - | K6: - | L6: - | M6: -
A7: Mutual Funds/ | B7: 33 | C7: 101047661 | D7: 101047661 | E7: 15.58 | F7: 101047661 | G7: 15.58 | H7: 101047661 | I7: 15.58 | J7: 101047661 | K7: - | L7: - | M7: -
A8: Nippon Life India Trustee Ltd- A/C Nippon India Growth Mid Cap Fund | B8: 1 | C8: 11217402 | D8: 11217402 | E8: 1.73 | F8: 11217402 | G8: 1.73 | H8: 11217402 | I8: 1.73 | J8: 11217402 | K8: - | L8: - | M8: -
A9: Uti-Flexi Cap Fund | B9: 1 | C9: 15085692 | D9: 15085692 | E9: 2.33 | F9: 15085692 | G9: 2.33 | H9: 15085692 | I9: 2.33 | J9: 15085692 | K9: - | L9: - | M9: -
A10: Icici Prudential Large & Mid Cap Fund | B10: 1 | C10: 40392595 | D10: 40392595 | E10: 6.23 | F10: 40392595 | G10: 6.23 | H10: 40392595 | I10: 6.23 | J10: 40392595 | K10: - | L10: - | M10: -
A11: Alternate Investment Funds | B11: 18 | C11: 2156178 | D11: 2156178 | E11: 0.33 | F11: 2156178 | G11: 0.33 | H11: 2156178 | I11: 0.33 | J11: 2156178 | K11: - | L11: - | M11: -
A12: Insurance Companies | B12: 16 | C12: 39209464 | D12: 39209464 | E12: 6.05 | F12: 39209464 | G12: 6.05 | H12: 39209464 | I12: 6.05 | J12: 39209464 | K12: - | L12: - | M12: -
A13: Life Insurance Corporation Of India - P & Gs Fund | B13: 1 | C13: 24285548 | D13: 24285548 | E13: 3.75 | F13: 24285548 | G13: 3.75 | H13: 24285548 | I13: 3.75 | J13: 24285548 | K13: - | L13: - | M13: -
A14: Provident Funds/ Pension Funds | B14: 1 | C14: 9500403 | D14: 9500403 | E14: 1.47 | F14: 9500403 | G14: 1.47 | H14: 9500403 | I14: 1.47 | J14: 9500403 | K14: - | L14: - | M14: -
A15: Nps Trust A/C Uti Pension Fund Limited-Scheme State Govt | B15: 1 | C15: 9500403 | D15: 9500403 | E15: 1.47 | F15: 9500403 | G15: 1.47 | H15: 9500403 | I15: 1.47 | J15: 9500403 | K15: - | L15: - | M15: -
A16: Sovereign Wealth Funds | B16: 2 | C16: 4257235 | D16: 4257235 | E16: 0.66 | F16: 4257235 | G16: 0.66 | H16: 4257235 | I16: 0.66 | J16: 4257235 | K16: - | L16: - | M16: -
A17: NBFCs registered with RBI | B17: 1 | C17: 39 | D17: 39 | E17: 0 | F17: 39 | G17: 0 | H17: 39 | I17: 0 | J17: 39 | K17: - | L17: - | M17: -
A18: Sub Total B1 | B18: 71 | C18: 156170980 | D18: 156170980 | E18: 24.08 | F18: 156170980 | G18: 24.08 | H18: 156170980 | I18: 24.08 | J18: 156170980 | K18: - | L18: - | M18: -
A19: B15) Institutions (Foreign) | B19: 0 | C19: 0 | D19: - | E19: 0 | F19: - | G19: 0 | H19: - | I19: 0 | J19: - | K19: - | L19: - | M19: -
A20: Foreign Portfolio Investors Category I | B20: 663 | C20: 174076658 | D20: 174076658 | E20: 26.85 | F20: 174076658 | G20: 26.85 | H20: 174076658 | I20: 26.85 | J20: 174076658 | K20: - | L20: - | M20: -
A21: Government Pension Fund Global | B21: 1 | C21: 12411886 | D21: 12411886 | E21: 1.91 | F21: 12411886 | G21: 1.91 | H21: 12411886 | I21: 1.91 | J21: 12411886 | K21: - | L21: - | M21: -
A22: Government Of Singapore | B22: 1 | C22: 17912369 | D22: 17912369 | E22: 2.76 | F22: 17912369 | G22: 2.76 | H22: 17912369 | I22: 2.76 | J22: 17912369 | K22: - | L22: - | M22: -
A23: Nalanda India Equity Fund Limited | B23: 1 | C23: 18318465 | D23: 18318465 | E23: 2.83 | F23: 18318465 | G23: 2.83 | H23: 18318465 | I23: 2.83 | J23: 18318465 | K23: - | L23: - | M23: -
A24: Foreign Portfolio Investors Category II | B24: 30 | C24: 7271994 | D24: 7271994 | E24: 1.12 | F24: 7271994 | G24: 1.12 | H24: 7271994 | I24: 1.12 | J24: 7271994 | K24: - | L24: - | M24: -
A25: Sub Total B2 | B25: 693 | C25: 181348652 | D25: 181348652 | E25: 27.97 | F25: 181348652 | G25: 27.97 | H25: 181348652 | I25: 27.97 | J25: 181348652 | K25: - | L25: - | M25: -
A26: B22) Central Government/ State Government(s)/ President of India | B26: 0 | C26: 0 | D26: - | E26: 0 | F26: - | G26: 0 | H26: - | I26: 0 | J26: - | K26: - | L26: - | M26: -
A27: Central Government / President of India | B27: 1 | C27: 26949 | D27: 26949 | E27: 0 | F27: 26949 | G27: 0 | H27: 26949 | I27: 0 | J27: 26949 | K27: - | L27: - | M27: -
A28: Sub Total B3 | B28: 1 | C28: 26949 | D28: 26949 | E28: 0 | F28: 26949 | G28: 0 | H28: 26949 | I28: 0 | J28: 26949 | K28: - | L28: - | M28: -
A29: B25) Non-Institutions | B29: 0 | C29: 0 | D29: - | E29: 0 | F29: - | G29: 0 | H29: - | I29: 0 | J29: - | K29: - | L29: - | M29: -
A30: Directors and their relatives (excluding independent directors and nominee directors) | B30: 2 | C30: 11641497 | D30: 11641497 | E30: 1.8 | F30: 11641497 | G30: 1.8 | H30: 11641497 | I30: 1.8 | J30: 11641497 | K30: - | L30: - | M30: -
A31: Kapil Kapoor | B31: 1 | C31: 11555795 | D31: 11555795 | E31: 1.78 | F31: 11555795 | G31: 1.78 | H31: 11555795 | I31: 1.78 | J31: 11555795 | K31: - | L31: - | M31: -
A32: Key Managerial Personnel | B32: 1 | C32: 6815145 | D32: 6815145 | E32: 1.05 | F32: 6815145 | G32: 1.05 | H32: 6815145 | I32: 1.05 | J32: 6815145 | K32: - | L32: - | M32: -
A33: Ambarish Raghuvanshi | B33: 1 | C33: 6815145 | D33: 6815145 | E33: 1.05 | F33: 6815145 | G33: 1.05 | H33: 6815145 | I33: 1.05 | J33: 6815145 | K33: - | L33: - | M33: -
A34: Investor Education and Protection Fund (IEPF) | B34: 1 | C34: 53070 | D34: 53070 | E34: 0.01 | F34: 53070 | G34: 0.01 | H34: 53070 | I34: 0.01 | J34: 53070 | K34: - | L34: - | M34: -
A35: Resident Individuals holding nominal share capital up to Rs. 2 lakhs | B35: 223109 | C35: 21427661 | D35: 21427661 | E35: 3.3 | F35: 21427661 | G35: 3.3 | H35: 21427661 | I35: 3.3 | J35: 21421006 | K35: - | L35: - | M35: -
A36: Resident Individuals holding nominal share capital in excess of Rs. 2 lakhs | B36: 20 | C36: 19257629 | D36: 19257629 | E36: 2.97 | F36: 19257629 | G36: 2.97 | H36: 19257629 | I36: 2.97 | J36: 19257629 | K36: - | L36: - | M36: -
A37: Anil Lall | B37: 1 | C37: 15667375 | D37: 15667375 | E37: 2.42 | F37: 15667375 | G37: 2.42 | H37: 15667375 | I37: 2.42 | J37: 15667375 | K37: - | L37: - | M37: -
A38: Non Resident Indians (NRIs) | B38: 5987 | C38: 4238493 | D38: 4238493 | E38: 0.65 | F38: 4238493 | G38: 0.65 | H38: 4238493 | I38: 0.65 | J38: 4238493 | K38: - | L38: - | M38: -
A39: Bodies Corporate | B39: 1027 | C39: 1438787 | D39: 1438787 | E39: 0.22 | F39: 1438787 | G39: 0.22 | H39: 1438787 | I39: 0.22 | J39: 1438787 | K39: - | L39: - | M39: -
A40: Any Other (specify) | B40: 6043 | C40: 2191900 | D40: 2191900 | E40: 0.34 | F40: 2191900 | G40: 0.34 | H40: 2191900 | I40: 0.34 | J40: 2191900 | K40: - | L40: - | M40: -
A41: Any Other (specify) | B41: 27 | C41: 900079 | D41: 900079 | E41: 0.14 | F41: 900079 | G41: 0.14 | H41: 900079 | I41: 0.14 | J41: 900079 | K41: - | L41: - | M41: -
... A47: B=B1+B2+B3+B4 | B47: 236955 | C47: 404610763 | D47: 404610763 | E47: 62.4 | F47: 404610763 | G47: 62.4 | H47: 404610763 | I47: 62.4 | J47: 404604108 | K47: - | L47: - | M47: -

Sheet consolidated balance sheet
A1: INFO EDGE INDIA — CONSOLIDATED BALANCE SHEET
A2: (Rs. Cr.)
A3: PARTICULARS | B3: Mar 22 | C3: Mar 23 | D3: Mar 24 | E3: Mar 25 | F3: Mar 26
A4: EQUITIES AND LIABILITIES
A5: SHAREHOLDER'S FUNDS
A6: Equity Share Capital | B6: 128.71 | C6: 129.01 | D6: 129.13 | E6: 129.43 | F6: 129.55
A7: Total Share Capital | B7: 128.71 | C7: 129.01 | D7: 129.13 | E7: 129.43 | F7: 129.55
A8: Reserves and Surplus | B8: 17112.66 | C8: 13104.8 | D8: 29945.43 | E8: 34773.63 | F8: 37783.59
A9: Total Reserves and Surplus | B9: 17112.66 | C9: 13104.8 | D9: 29945.43 | E9: 34773.63 | F9: 37783.59
A10: Employees Stock Options | B10: 0 | C10: 164.21 | D10: 187.73 | E10: 0 | F10: 0
A11: Total Shareholders Funds | B11: 17241.36 | C11: 13398.02 | D11: 30262.29 | E11: 34903.06 | F11: 37913.13
A12: Minority Interest | B12: 809.32 | C12: 1027.85 | D12: 1366.2 | E12: 1913.31 | F12: 2456.31
A13: NON-CURRENT LIABILITIES
A14: Long Term Borrowings | B14: 0.65 | C14: 1.4 | D14: 1.27 | E14: 0.43 | F14: 0.09
A15: Deferred Tax Liabilities [Net] | B15: 1245.12 | C15: 800.43 | D15: 2746.21 | E15: 3987.72 | F15: 4988.04
A16: Other Long Term Liabilities | B16: 45.49 | C16: 82.05 | D16: 217.93 | E16: 234.79 | F16: 218.43
A17: Long Term Provisions | B17: 0.55 | C17: 1.61 | D17: 1.27 | E17: 1.01 | F17: 1.36
A18: Total Non-Current Liabilities | B18: 1291.81 | C18: 885.49 | D18: 2966.69 | E18: 4223.95 | F18: 5207.92
A19: CURRENT LIABILITIES
A20: Short Term Borrowings | B20: 0 | C20: 1.02 | D20: 1.31 | E20: 0.84 | F20: 0.34
A21: Trade Payables | B21: 120.77 | C21: 94.59 | D21: 88.9 | E21: 75.39 | F21: 116.74
A22: Other Current Liabilities | B22: 930.94 | C22: 1156.11 | D22: 1281.3 | E22: 1516.05 | F22: 1684.69
A23: Short Term Provisions | B23: 88.69 | C23: 97.22 | D23: 124.13 | E23: 138.75 | F23: 180.34
A24: Total Current Liabilities | B24: 1140.4 | C24: 1348.94 | D24: 1495.64 | E24: 1731.03 | F24: 1982.12
A25: Total Capital And Liabilities | B25: 20482.89 | C25: 16660.3 | D25: 36090.82 | E25: 42771.35 | F25: 47559.48
A26: ASSETS
A27: NON-CURRENT ASSETS
A28: Tangible Assets | B28: 131.03 | C28: 202.75 | D28: 350.02 | E28: 398.67 | F28: 390.97
A29: Intangible Assets | B29: 61.12 | C29: 120.03 | D29: 89.61 | E29: 63.67 | F29: 36.71
A30: Capital Work-In-Progress | B30: 0 | C30: 4.2 | D30: 0 | E30: 2.63 | F30: 17.53
A31: Intangible Assets Under Dev. | B31: 0 | C31: 0 | D31: 0 | E31: 0.22 | F31: 0
A32: Fixed Assets | B32: 192.15 | C32: 326.98 | D32: 439.64 | E32: 465.19 | F32: 445.21
A33: Non-Current Investments | B33: 15173.26 | C33: 11648.67 | D33: 30475.88 | E33: 36512.61 | F33: 41039.51
A34: Deferred Tax Assets [Net] | B34: 0.01 | C34: 1.9 | D34: 1.41 | E34: 0.66 | F34: 0.72
A35: Other Non-Current Assets | B35: 805.29 | C35: 514.14 | D35: 467.73 | E35: 1023.38 | F35: 859.66
A36: Total Non-Current Assets | B36: 17011.1 | C36: 12969.67 | D36: 31754.64 | E36: 38324.29 | F36: 42667.59
A37: CURRENT ASSETS
A38: Current Investments | B38: 440.93 | C38: 754.68 | D38: 726.74 | E38: 1148.37 | F38: 1259.81
A39: Trade Receivables | B39: 30.02 | C39: 12.62 | D39: 10.65 | E39: 13.19 | F39: 11.02
A40: Cash And Cash Equivalents | B40: 368.29 | C40: 571.46 | D40: 1192.98 | E40: 267.13 | F40: 375.91
A41: Short Term Loans And Advances | B41: 8.37 | C41: 0 | D41: 1 | E41: 1 | F41: 1.5
A42: Other Current Assets | B42: 2624.19 | C42: 2351.88 | D42: 2404.82 | E42: 3017.37 | F42: 3243.65
A43: Total Current Assets | B43: 3471.79 | C43: 3690.63 | D43: 4336.18 | E43: 4447.06 | F43: 4891.89
A44: Total Assets | B44: 20482.89 | C44: 16660.3 | D44: 36090.82 | E44: 42771.35 | F44: 47559.48
A46: OTHER ADDITIONAL INFORMATION
A47: Contingent Liabilities | C47: 15.06 | D47: 3.78
A48: Bonus Equity Share Capital | B48: 103.59 | C48: 103.59 | D48: 103.59 | E48: 103.59
A49: Non-Current Investments Quoted Market Value | C49: 7872.53 | D49: 24939.16
A50: Non-Current Investments Unquoted Book Value | B50: 12745.77 | C50: 1703.39 | D50: 2370.77
A51: Current Investments Unquoted Book Value | C51: 754.68 | D51: 726.74 | E51: 1148.37

Sheet consolidated P&l 
A1: INFO EDGE INDIA — CONSOLIDATED PROFIT & LOSS ACCOUNT
A2: (Rs. Cr.)
A3: PARTICULARS | B3: Mar 22 | C3: Mar 23 | D3: Mar 24 | E3: Mar 25 | F3: Mar 26
A4: INCOME
A5: Revenue From Operations [Gross] | B5: 1589.03 | C5: 2345.69 | D5: 2536.34 | E5: 2849.55 | F5: 3284.73
A6: Revenue From Operations [Net] | B6: 1589.03 | C6: 2345.69 | D6: 2536.34 | E6: 2849.55 | F6: 3284.73
A7: Total Operating Revenues | B7: 1589.03 | C7: 2345.69 | D7: 2536.34 | E7: 2849.55 | F7: 3284.73
A8: Other Income | B8: 440.36 | C8: 392.85 | D8: 413.74 | E8: 1073.25 | F8: 1058.55
A9: Total Revenue | B9: 2029.39 | C9: 2738.54 | D9: 2950.08 | E9: 3922.8 | F9: 4343.29
A10: EXPENSES
A11: Operating And Direct Expenses | B11: 34.02 | C11: 63.37 | D11: 74.71 | E11: 78.3 | F11: 0
A12: Employee Benefit Expenses | B12: 746.31 | C12: 1097.31 | D12: 1128.24 | E12: 1235.34 | F12: 1341.5
A13: Finance Costs | B13: 4.65 | C13: 7.34 | D13: 22.26 | E13: 24.24 | F13: 27.43
A14: Depreciation And Amortisation Expenses | B14: 44.91 | C14: 73.02 | D14: 101.13 | E14: 113.09 | F14: 122.58
A15: Other Expenses | B15: 369.47 | C15: 616.64 | D15: 504.15 | E15: 551.2 | F15: 771.02
A16: Total Expenses | B16: 1199.35 | C16: 1857.67 | D16: 1830.48 | E16: 2002.16 | F16: 2262.52
A17: Profit/Loss Before Exceptional Items And Tax | B17: 830.04 | C17: 880.88 | D17: 1119.59 | E17: 1920.64 | F17: 2080.77
A18: Exceptional Items | B18: 11174.71 | C18: -509.25 | D18: -110.58 | E18: 146.98 | F18: 38.81
A19: Profit/Loss Before Tax | B19: 12004.75 | C19: 371.63 | D19: 1009.02 | E19: 2067.61 | F19: 2119.57
A20: TAX EXPENSES — CONTINUED OPERATIONS
A21: Current Tax | B21: 153.02 | C21: 227.94 | D21: 289.64 | E21: 286.85 | F21: 358.55
A22: Deferred Tax | B22: 1164.87 | C22: -16.87 | D22: -6.16 | E22: 347.87 | F22: 0
A23: Total Tax Expenses | B23: 1317.88 | C23: 211.07 | D23: 283.48 | E23: 634.72 | F23: 358.55
A24: Profit/Loss After Tax And Before Extraordinary Items | B24: 10686.87 | C24: 160.56 | D24: 725.54 | E24: 1432.89 | F24: 1761.02
A25: Profit/Loss From Continuing Operations | B25: 10686.87 | C25: 160.56 | D25: 725.54 | E25: 1432.89 | F25: 1761.02
A26: Profit/Loss For The Period | B26: 10686.87 | C26: 160.56 | D26: 725.54 | E26: 1432.89 | F26: 1761.02
A27: Minority Interest | B27: -122.66 | C27: -36.95 | D27: -19.35 | E27: -347.76 | F27: -313.03
A28: Share Of Profit/Loss Of Associates | B28: 2195.36 | C28: -231.01 | D28: -130.98 | E28: -122.99 | F28: 1.82
A29: Consolidated Profit/Loss After MI And Associates | B29: 12759.57 | C29: -107.41 | D29: 575.21 | E29: 962.14 | F29: 1449.81
A31: OTHER ADDITIONAL INFORMATION
A32: Basic EPS (Rs.) | B32: 991 | C32: -8 | D32: 45 | E32: 15 | F32: 22
A33: Diluted EPS (Rs.) | B33: 986 | C33: -8 | D33: 44 | E33: 18 | F33: 22
A34: Equity Share Dividend | B34: 205.78 | C34: 193.16 | D34: 245.21 | E34: 310.21 | F34: 0

Sheet Consolidated Quarterly Results
D1: Consolidated Quarterly Results (Rs. Crores)
E2: Quarter ended | H2: Years | J2: % CHANGE
D3: Particulars | E3: 46082 | F3: 45992 | G3: 45901 | H3: 46082 | I3: 45717 | J3: QTQ | K3: YOY
D4: I. REVENUE
D5: Net Sales/Income from Operations | E5: 869 | F5: 819 | G5: 805 | H5: 3284 | I5: 2849 | J5: =IF(F5=0,"",((E5-F5)/F5)) -> 0.061050061 | K5: =IF(I5=0,"",((H5-I5)/I5)) -> 0.15268515
D6: Other Operating Income
D7: Total Income From Operations | E7: 869 | F7: 819 | G7: 805 | H7: 3284 | I7: 2849 | J7: =IF(F7=0,"",((E7-F7)/F7)) -> 0.061050061 | K7: =IF(I7=0,"",((H7-I7)/I7)) -> 0.15268515
D9: II. EXPENDITURE
D10: Consumption of Raw Materials
D11: Purchase of Traded Goods
D12: Increase/Decrease in Stocks
D13: Power & Fuel
D14: Employees Cost | E14: 331 | F14: 342 | G14: 340 | H14: 1341 | I14: 1235 | J14: =IF(F14=0,"",((E14-F14)/F14)) -> -0.032163743 | K14: =IF(I14=0,"",((H14-I14)/I14)) -> 0.08582996
D15: Depreciation | E15: 30 | F15: 30 | G15: 30 | H15: 122 | I15: 113 | J15: =IF(F15=0,"",((E15-F15)/F15)) -> 0 | K15: =IF(I15=0,"",((H15-I15)/I15)) -> 0.079646018
D16: Excise Duty
D17: Admin. And Selling Expenses
D18: R & D Expenses
D19: Provisions And Contingencies
D20: Exp. Capitalised
D21: Other Expenses | E21: 203 | F21: 182 | G21: 185 | H21: 771 | I21: 551 | J21: =IF(F21=0,"",((E21-F21)/F21)) -> 0.11538462 | K21: =IF(I21=0,"",((H21-I21)/I21)) -> 0.39927405
D22: Total Expenses
D24: III. PROFIT & LOSS
D25: P/L Before Other Inc., Int., Excpt. Items & Tax | E25: 303 | F25: 263 | G25: 248 | H25: 1049 | I25: 871 | J25: =IF(F25=0,"",((E25-F25)/F25)) -> 0.15209125 | K25: =IF(I25=0,"",((H25-I25)/I25)) -> 0.2043628
D26: Other Income | E26: 496 | F26: 187 | G26: 161 | H26: 1058 | I26: 1073 | J26: =IF(F26=0,"",((E26-F26)/F26)) -> 1.6524064 | K26: =IF(I26=0,"",((H26-I26)/I26)) -> -0.013979497
D27: P/L Before Int., Excpt. Items & Tax | E27: 799 | F27: 451 | G27: 410 | H27: 2108 | I27: 1944 | J27: =IF(F27=0,"",((E27-F27)/F27)) -> 0.77161863 | K27: =IF(I27=0,"",((H27-I27)/I27)) -> 0.08436214
D28: Interest | E28: 7 | F28: 6 | G28: 6 | H28: 27 | I28: 24 | J28: =IF(F28=0,"",((E28-F28)/F28)) -> 0.16666667 | K28: =IF(I28=0,"",((H28-I28)/I28)) -> 0.125
D29: P/L Before Exceptional Items & Tax | E29: 792 | F29: 444 | G29: 403 | H29: 2080 | I29: 1920 | J29: =IF(F29=0,"",((E29-F29)/F29)) -> 0.78378378 | K29: =IF(I29=0,"",((H29-I29)/I29)) -> 0.083333333
D30: Exceptional Items | E30: 70 | F30: -51 | G30: 25 | H30: 38 | I30: 146 | J30: =IF(F30=0,"",((E30-F30)/F30)) -> -2.372549 | K30: =IF(I30=0,"",((H30-I30)/I30)) -> -0.73972603
D31: P/L Before Tax | E31: 862 | F31: 392 | G31: 428 | H31: 2119 | I31: 2067 | J31: =IF(F31=0,"",((E31-F31)/F31)) -> 1.1989796 | K31: =IF(I31=0,"",((H31-I31)/I31)) -> 0.025157233
D32: Tax | E32: 112 | F32: 76 | G32: 81 | H32: 358 | I32: 634 | J32: =IF(F32=0,"",((E32-F32)/F32)) -> 0.47368421 | K32: =IF(I32=0,"",((H32-I32)/I32)) -> -0.43533123
D33: P/L After Tax from Ordinary Activities | E33: 749 | F33: 316 | G33: 347 | H33: 1761 | I33: 1432 | J33: =IF(F33=0,"",((E33-F33)/F33)) -> 1.3702532 | K33: =IF(I33=0,"",((H33-I33)/I33)) -> 0.2297486
D34: Prior Year Adjustments
D35: Extra Ordinary Items
D36: Net Profit/(Loss) For the Period | E36: 749 | F36: 316 | G36: 347 | H36: 1761 | I36: 1432 | J36: =IF(F36=0,"",((E36-F36)/F36)) -> 1.3702532 | K36: =IF(I36=0,"",((H36-I36)/I36)) -> 0.2297486
D38: Minority Interest | E38: -189 | F38: -45 | G38: -31 | H38: -313 | I38: -347 | J38: =IF(F38=0,"",((E38-F38)/F38)) -> 3.2 | K38: =IF(I38=0,"",((H38-I38)/I38)) -> -0.097982709
D39: Share Of P/L Of Associates | E39: 6 | F39: 0 | G39: 0 | H39: 1 | I39: -122 | K39: =IF(I39=0,"",((H39-I39)/I39)) -> -1.0081967
D40: Net P/L After M.I & Associates | E40: 565 | F40: 271 | G40: 316 | H40: 1449 | I40: 962 | J40: =IF(F40=0,"",((E40-F40)/F40)) -> 1.0848708 | K40: =IF(I40=0,"",((H40-I40)/I40)) -> 0.50623701
D42: Equity Share Capital | E42: 129 | F42: 129 | G42: 129 | H42: 129 | I42: 129 | J42: =IF(F42=0,"",((E42-F42)/F42)) -> 0 | K42: =IF(I42=0,"",((H42-I42)/I42)) -> 0
D43: Reserves Excluding Revaluation Reserves
D44: Equity Dividend Rate (%)
D46: IV. EARNINGS PER SHARE (Rs.)
D47: EPS Before Extra Ordinary - Basic | E47: 8.73 | F47: 4.8 | G47: 4.5 | H47: 22.39 | I47: 14.88 | J47: =IF(F47=0,"",((E47-F47)/F47)) -> 0.81875 | K47: =IF(I47=0,"",((H47-I47)/I47)) -> 0.5047043
D48: EPS Before Extra Ordinary - Diluted | E48: 8.72 | F48: 4.78 | G48: 4.49 | H48: 22.36 | I48: 17.82 | J48: =IF(F48=0,"",((E48-F48)/F48)) -> 0.82426778 | K48: =IF(I48=0,"",((H48-I48)/I48)) -> 0.25476992
D50: EPS After Extra Ordinary - Basic | E50: 8.73 | F50: 4.2 | G50: 4.89 | H50: 22.39 | I50: 14.88 | J50: =IF(F50=0,"",((E50-F50)/F50)) -> 1.0785714 | K50: =IF(I50=0,"",((H50-I50)/I50)) -> 0.5047043
D51: EPS After Extra Ordinary - Diluted | E51: 8.72 | F51: 4.19 | G51: 4.88 | H51: 22.36 | I51: 17.82 | J51: =IF(F51=0,"",((E51-F51)/F51)) -> 1.0811456 | K51: =IF(I51=0,"",((H51-I51)/I51)) -> 0.25476992

Sheet cash flow statement 
A1: INFO EDGE INDIA — CONSOLIDATED CASH FLOW STATEMENT
A2: (Rs. Cr.)
A3: PARTICULARS | B3: Mar 22 | C3: Mar 23 | D3: Mar 24 | E3: Mar 25 | F3: Mar 26
A4: Net Profit Before Tax | B4: 3025.4 | C4: 649.86 | D4: 988.61 | E4: 1797.64 | F4: 2119.57
A5: Net Cash From Operating Activities | B5: 706.75 | C5: 520.79 | D5: 702.3 | E5: 875.84 | F5: 1076.43
A6: Net Cash (used in)/from Investing Activities | B6: -1176.53 | C6: -366.62 | D6: -851.7 | E6: -817.77 | F6: -610.71
A7: Net Cash (used in)/from Financing Activities | B7: 34.64 | C7: 1.97 | D7: 120 | E7: -126.99 | F7: -363.28
A8: Net (decrease)/increase In Cash and Cash Equivalents | B8: -435.15 | C8: 156.14 | D8: -29.4 | E8: -68.92 | F8: 102.44
A9: Opening Cash & Cash Equivalents | B9: 640.3 | C9: 205.15 | D9: 361.3 | E9: 331.9 | F9: 262.98
A10: Closing Cash & Cash Equivalents | B10: 205.15 | C10: 361.3 | D10: 331.9 | E10: 262.98 | F10: 365.42

Sheet Ratio Analysis
A1: Ratio Analysis- Info Edge
A2: Years | B2: 44621 | C2: 44986 | D2: 45352 | E2: 45717 | F2: 46082 | G2: Trends | H2: Mean | I2: Median
A4: Sales Growth | C4: =('consolidated P&l '!C6-'consolidated P&l '!B6)/'consolidated P&l '!B6 -> 0.47617729 | D4: =('consolidated P&l '!D6-'consolidated P&l '!C6)/'consolidated P&l '!C6 -> 0.081276725 | E4: =('consolidated P&l '!E6-'consolidated P&l '!D6)/'consolidated P&l '!D6 -> 0.12348896 | F4: =('consolidated P&l '!F6-'consolidated P&l '!E6)/'consolidated P&l '!E6 -> 0.15271885 | H4: =AVERAGE(C4:F4) -> 0.20841546 | I4: =MEDIAN(C4:F4) -> 0.13810391
A5: EBITDA Growth | C5: =(('consolidated P&l '!C17+'consolidated P&l '!C14)-('consolidated P&l '!B17+'consolidated P&l '!B14))/('consolidated P&l '!B17+'consolidated P&l '!B14) -> 0.090233728 | D5: =(('consolidated P&l '!D17+'consolidated P&l '!D14)-('consolidated P&l '!C17+'consolidated P&l '!C14))/('consolidated P&l '!C17+'consolidated P&l '!C14) -> 0.27971485 | E5: =(('consolidated P&l '!E17+'consolidated P&l '!E14)-('consolidated P&l '!D17+'consolidated P&l '!D14))/('consolidated P&l '!D17+'consolidated P&l '!D14) -> 0.66600859 | F5: =(('consolidated P&l '!F17+'consolidated P&l '!F14)-('consolidated P&l '!E17+'consolidated P&l '!E14))/('consolidated P&l '!E17+'consolidated P&l '!E14) -> 0.083403402 | H5: =AVERAGE(C5:F5) -> 0.27984014 | I5: =MEDIAN(C5:F5) -> 0.18497429
A6: EBIT Growth | C6: =('consolidated P&l '!C17-'consolidated P&l '!B17)/'consolidated P&l '!B17 -> 0.06125006 | D6: =('consolidated P&l '!D17-'consolidated P&l '!C17)/'consolidated P&l '!C17 -> 0.27099037 | E6: =('consolidated P&l '!E17-'consolidated P&l '!D17)/'consolidated P&l '!D17 -> 0.71548513 | F6: =('consolidated P&l '!F17-'consolidated P&l '!E17)/'consolidated P&l '!E17 -> 0.083373251 | H6: =AVERAGE(C6:F6) -> 0.2827747 | I6: =MEDIAN(C6:F6) -> 0.17718181
A7: Net Profit Growth | C7: =('consolidated P&l '!C29-'consolidated P&l '!B29)/'consolidated P&l '!B29 -> -1.008418 | D7: =('consolidated P&l '!D29-'consolidated P&l '!C29)/'consolidated P&l '!C29 -> -6.3552742 | E7: =('consolidated P&l '!E29-'consolidated P&l '!D29)/'consolidated P&l '!D29 -> 0.67267607 | F7: =('consolidated P&l '!F29-'consolidated P&l '!E29)/'consolidated P&l '!E29 -> 0.50685971 | H7: =AVERAGE(C7:F7) -> -1.5460391 | I7: =MEDIAN(C7:F7) -> -0.25077914
A8: Dividend Growth | C8: =IF('consolidated P&l '!B34=0,"",('consolidated P&l '!C34-'consolidated P&l '!B34)/'consolidated P&l '!B34) -> -0.061327631 | D8: =IF('consolidated P&l '!C34=0,"",('consolidated P&l '!D34-'consolidated P&l '!C34)/'consolidated P&l '!C34) -> 0.26946573 | E8: =IF('consolidated P&l '!D34=0,"",('consolidated P&l '!E34-'consolidated P&l '!D34)/'consolidated P&l '!D34) -> 0.26507891 | F8: =IF('consolidated P&l '!E34=0,"",('consolidated P&l '!F34-'consolidated P&l '!E34)/'consolidated P&l '!E34) -> -1 | H8: =IFERROR(AVERAGE(C8:F8),"") -> -0.13169575 | I8: =IFERROR(MEDIAN(C8:F8),"") -> 0.10187564
A10: Gross Margin | B10: =('consolidated P&l '!B6-'consolidated P&l '!B11)/'consolidated P&l '!B6 -> 0.97859071 | C10: =('consolidated P&l '!C6-'consolidated P&l '!C11)/'consolidated P&l '!C6 -> 0.97298449 | D10: =('consolidated P&l '!D6-'consolidated P&l '!D11)/'consolidated P&l '!D6 -> 0.97054417 | E10: =('consolidated P&l '!E6-'consolidated P&l '!E11)/'consolidated P&l '!E6 -> 0.97252198 | F10: =('consolidated P&l '!F6-'consolidated P&l '!F11)/'consolidated P&l '!F6 -> 1 | H10: =AVERAGE(B10:F10) -> 0.97892827 | I10: =MEDIAN(B10:F10) -> 0.97298449
A11: EBITDA Margin | B11: =('consolidated P&l '!B17+'consolidated P&l '!B14)/'consolidated P&l '!B6 -> 0.55061893 | C11: =('consolidated P&l '!C17+'consolidated P&l '!C14)/'consolidated P&l '!C6 -> 0.40666073 | D11: =('consolidated P&l '!D17+'consolidated P&l '!D14)/'consolidated P&l '!D6 -> 0.48129194 | E11: =('consolidated P&l '!E17+'consolidated P&l '!E14)/'consolidated P&l '!E6 -> 0.71370216 | F11: =('consolidated P&l '!F17+'consolidated P&l '!F14)/'consolidated P&l '!F6 -> 0.67078573 | H11: =AVERAGE(B11:F11) -> 0.5646119 | I11: =MEDIAN(B11:F11) -> 0.55061893
A12: EBIT Margin | B12: ='consolidated P&l '!B17/'consolidated P&l '!B6 -> 0.52235641 | C12: ='consolidated P&l '!C17/'consolidated P&l '!C6 -> 0.37553129 | D12: ='consolidated P&l '!D17/'consolidated P&l '!D6 -> 0.44141953 | E12: ='consolidated P&l '!E17/'consolidated P&l '!E6 -> 0.6740152 | F12: ='consolidated P&l '!F17/'consolidated P&l '!F6 -> 0.63346759 | H12: =AVERAGE(B12:F12) -> 0.529358 | I12: =MEDIAN(B12:F12) -> 0.52235641
A13: EBT Margin | B13: ='consolidated P&l '!B19/'consolidated P&l '!B6 -> 7.5547661 | C13: ='consolidated P&l '!C19/'consolidated P&l '!C6 -> 0.15843099 | D13: ='consolidated P&l '!D19/'consolidated P&l '!D6 -> 0.39782521 | E13: ='consolidated P&l '!E19/'consolidated P&l '!E6 -> 0.72559176 | F13: ='consolidated P&l '!F19/'consolidated P&l '!F6 -> 0.64527983 | H13: =AVERAGE(B13:F13) -> 1.8963788 | I13: =MEDIAN(B13:F13) -> 0.64527983
A14: Net Profit Margin | B14: ='consolidated P&l '!B29/'consolidated P&l '!B6 -> 8.0297855 | C14: ='consolidated P&l '!C29/'consolidated P&l '!C6 -> -0.045790364 | D14: ='consolidated P&l '!D29/'consolidated P&l '!D6 -> 0.22678742 | E14: ='consolidated P&l '!E29/'consolidated P&l '!E6 -> 0.3376463 | F14: ='consolidated P&l '!F29/'consolidated P&l '!F6 -> 0.44137874 | H14: =AVERAGE(B14:F14) -> 1.7979615 | I14: =MEDIAN(B14:F14) -> 0.3376463
A16: Sales Expenses%Sales | B16: ='consolidated P&l '!B16/'consolidated P&l '!B6 -> 0.75476863 | C16: ='consolidated P&l '!C16/'consolidated P&l '!C6 -> 0.79195034 | D16: ='consolidated P&l '!D16/'consolidated P&l '!D6 -> 0.72170135 | E16: ='consolidated P&l '!E16/'consolidated P&l '!E6 -> 0.70262322 | F16: ='consolidated P&l '!F16/'consolidated P&l '!F6 -> 0.68879938 | H16: =AVERAGE(B16:F16) -> 0.73196859 | I16: =MEDIAN(B16:F16) -> 0.72170135
A17: Depriciation%Sales | B17: ='consolidated P&l '!B14/'consolidated P&l '!B6 -> 0.028262525 | C17: ='consolidated P&l '!C14/'consolidated P&l '!C6 -> 0.031129433 | D17: ='consolidated P&l '!D14/'consolidated P&l '!D6 -> 0.039872415 | E17: ='consolidated P&l '!E14/'consolidated P&l '!E6 -> 0.039686968 | F17: ='consolidated P&l '!F14/'consolidated P&l '!F6 -> 0.037318136 | H17: =AVERAGE(B17:F17) -> 0.035253895 | I17: =MEDIAN(B17:F17) -> 0.037318136
A18: Operating Income%Sales | B18: ='consolidated P&l '!B17/'consolidated P&l '!B6 -> 0.52235641 | C18: ='consolidated P&l '!C17/'consolidated P&l '!C6 -> 0.37553129 | D18: ='consolidated P&l '!D17/'consolidated P&l '!D6 -> 0.44141953 | E18: ='consolidated P&l '!E17/'consolidated P&l '!E6 -> 0.6740152 | F18: ='consolidated P&l '!F17/'consolidated P&l '!F6 -> 0.63346759 | H18: =AVERAGE(B18:F18) -> 0.529358 | I18: =MEDIAN(B18:F18) -> 0.52235641
A20: Return on Capital Employed | B20: ='consolidated P&l '!B17/('consolidated balance sheet'!B11+'consolidated balance sheet'!B14+'consolidated balance sheet'!B20) -> 0.048140559 | C20: ='consolidated P&l '!C17/('consolidated balance sheet'!C11+'consolidated balance sheet'!C14+'consolidated balance sheet'!C20) -> 0.065735155 | D20: ='consolidated P&l '!D17/('consolidated balance sheet'!D11+'consolidated balance sheet'!D14+'consolidated balance sheet'!D20) -> 0.036993055 | E20: ='consolidated P&l '!E17/('consolidated balance sheet'!E11+'consolidated balance sheet'!E14+'consolidated balance sheet'!E20) -> 0.055025838 | F20: ='consolidated P&l '!F17/('consolidated balance sheet'!F11+'consolidated balance sheet'!F14+'consolidated balance sheet'!F20) -> 0.054881947 | H20: =AVERAGE(B20:F20) -> 0.052155311 | I20: =MEDIAN(B20:F20) -> 0.054881947
A21: Retained Earning % | B21: =IF('consolidated P&l '!B29=0,"",('consolidated P&l '!B29-'consolidated P&l '!B34)/'consolidated P&l '!B29) -> 0.9838725 | C21: =IF('consolidated P&l '!C29=0,"",('consolidated P&l '!C29-'consolidated P&l '!C34)/'consolidated P&l '!C29) -> 2.7983428 | D21: =IF('consolidated P&l '!D29=0,"",('consolidated P&l '!D29-'consolidated P&l '!D34)/'consolidated P&l '!D29) -> 0.57370352 | E21: =IF('consolidated P&l '!E29=0,"",('consolidated P&l '!E29-'consolidated P&l '!E34)/'consolidated P&l '!E29) -> 0.6775833 | F21: =IF('consolidated P&l '!F29=0,"",('consolidated P&l '!F29-'consolidated P&l '!F34)/'consolidated P&l '!F29) -> 1 | H21: =IFERROR(AVERAGE(B21:F21),"") -> 1.2067004 | I21: =IFERROR(MEDIAN(B21:F21),"") -> 0.9838725
A22: Return on Equity % | B22: ='consolidated P&l '!B29/'consolidated balance sheet'!B11 -> 0.74005589 | C22: ='consolidated P&l '!C29/'consolidated balance sheet'!C11 -> -0.0080168562 | D22: ='consolidated P&l '!D29/'consolidated balance sheet'!D11 -> 0.019007484 | E22: ='consolidated P&l '!E29/'consolidated balance sheet'!E11 -> 0.027566064 | F22: ='consolidated P&l '!F29/'consolidated balance sheet'!F11 -> 0.038240314 | H22: =AVERAGE(B22:F22) -> 0.16337058 | I22: =MEDIAN(B22:F22) -> 0.027566064
A23: Self Sustained Growth Rate | B23: =B22*B21 -> 0.72812064 | C23: =C22*C21 -> -0.022433912 | D23: =D22*D21 -> 0.010904661 | E23: =E22*E21 -> 0.018678305 | F23: =F22*F21 -> 0.038240314 | H23: =IFERROR(AVERAGE(B23:F23),"") -> 0.154702 | I23: =IFERROR(MEDIAN(B23:F23),"") -> 0.018678305
A24: Interest Coverage Ratio | B24: =IF('consolidated P&l '!B13=0,"",'consolidated P&l '!B17/'consolidated P&l '!B13) -> 178.50323 | C24: =IF('consolidated P&l '!C13=0,"",'consolidated P&l '!C17/'consolidated P&l '!C13) -> 120.0109 | D24: =IF('consolidated P&l '!D13=0,"",'consolidated P&l '!D17/'consolidated P&l '!D13) -> 50.296047 | E24: =IF('consolidated P&l '!E13=0,"",'consolidated P&l '!E17/'consolidated P&l '!E13) -> 79.234323 | F24: =IF('consolidated P&l '!F13=0,"",'consolidated P&l '!F17/'consolidated P&l '!F13) -> 75.857455 | H24: =IFERROR(AVERAGE(B24:F24),"") -> 100.78039 | I24: =IFERROR(MEDIAN(B24:F24),"") -> 79.234323
A26: Debtor Turnover Ratio | B26: ='consolidated P&l '!B6/'consolidated balance sheet'!B39 -> 52.932378 | C26: ='consolidated P&l '!C6/'consolidated balance sheet'!C39 -> 185.87084 | D26: ='consolidated P&l '!D6/'consolidated balance sheet'!D39 -> 238.15399 | E26: ='consolidated P&l '!E6/'consolidated balance sheet'!E39 -> 216.03867 | F26: ='consolidated P&l '!F6/'consolidated balance sheet'!F39 -> 298.06987 | H26: =AVERAGE(B26:F26) -> 198.21315 | I26: =MEDIAN(B26:F26) -> 216.03867
A27: Creditor Turnover Ratio | B27: ='consolidated P&l '!B16/'consolidated balance sheet'!B21 -> 9.9308603 | C27: ='consolidated P&l '!C16/'consolidated balance sheet'!C21 -> 19.63918 | D27: ='consolidated P&l '!D16/'consolidated balance sheet'!D21 -> 20.590326 | E27: ='consolidated P&l '!E16/'consolidated balance sheet'!E21 -> 26.557368 | F27: ='consolidated P&l '!F16/'consolidated balance sheet'!F21 -> 19.380846 | H27: =AVERAGE(B27:F27) -> 19.219716 | I27: =MEDIAN(B27:F27) -> 19.63918
A28: Inventory Turnover
A29: Fixed Asset Turnover | B29: ='consolidated P&l '!B6/'consolidated balance sheet'!B32 -> 8.2697372 | C29: ='consolidated P&l '!C6/'consolidated balance sheet'!C32 -> 7.1738027 | D29: ='consolidated P&l '!D6/'consolidated balance sheet'!D32 -> 5.7691293 | E29: ='consolidated P&l '!E6/'consolidated balance sheet'!E32 -> 6.1255616 | F29: ='consolidated P&l '!F6/'consolidated balance sheet'!F32 -> 7.377934 | H29: =AVERAGE(B29:F29) -> 6.943233 | I29: =MEDIAN(B29:F29) -> 7.1738027
A30: Capital Turnover Ratio | B30: ='consolidated P&l '!B6/('consolidated balance sheet'!B11+'consolidated balance sheet'!B14+'consolidated balance sheet'!B20) -> 0.092160369 | C30: ='consolidated P&l '!C6/('consolidated balance sheet'!C11+'consolidated balance sheet'!C14+'consolidated balance sheet'!C20) -> 0.17504574 | D30: ='consolidated P&l '!D6/('consolidated balance sheet'!D11+'consolidated balance sheet'!D14+'consolidated balance sheet'!D20) -> 0.083804754 | E30: ='consolidated P&l '!E6/('consolidated balance sheet'!E11+'consolidated balance sheet'!E14+'consolidated balance sheet'!E20) -> 0.081638868 | F30: ='consolidated P&l '!F6/('consolidated balance sheet'!F11+'consolidated balance sheet'!F14+'consolidated balance sheet'!F20) -> 0.08663734 | H30: =AVERAGE(B30:F30) -> 0.10385742 | I30: =MEDIAN(B30:F30) -> 0.08663734
A32: (In days)
A33: Debtors Day | B33: =365/B26 -> 6.8955904 | C33: =365/C26 -> 1.9637292 | D33: =365/D26 -> 1.5326218 | E33: =365/E26 -> 1.6895124 | F33: =365/F26 -> 1.2245451 | H33: =AVERAGE(B33:F33) -> 2.6611998 | I33: =MEDIAN(B33:F33) -> 1.6895124
A34: Payable Days | B34: =365/B27 -> 36.754117 | C34: =365/C27 -> 18.585298 | D34: =365/D27 -> 17.726771 | E34: =365/E27 -> 13.743832 | F34: =365/F27 -> 18.833027 | H34: =AVERAGE(B34:F34) -> 21.128609 | I34: =MEDIAN(B34:F34) -> 18.585298
A35: Inventory Days
A36: Cash Conversion Cycle | B36: =B33-B34 -> -29.858526 | C36: =C33-C34 -> -16.621568 | D36: =D33-D34 -> -16.194149 | E36: =E33-E34 -> -12.054319 | F36: =F33-F34 -> -17.608482 | H36: =AVERAGE(B36:F36) -> -18.467409 | I36: =MEDIAN(B36:F36) -> -16.621568
A38: CFO/Sales | B38: ='cash flow statement '!B5/'consolidated P&l '!B6 -> 0.44476819 | C38: ='cash flow statement '!C5/'consolidated P&l '!C6 -> 0.22201996 | D38: ='cash flow statement '!D5/'consolidated P&l '!D6 -> 0.27689505 | E38: ='cash flow statement '!E5/'consolidated P&l '!E6 -> 0.30736081 | F38: ='cash flow statement '!F5/'consolidated P&l '!F6 -> 0.3277073 | H38: =AVERAGE(B38:F38) -> 0.31575026 | I38: =MEDIAN(B38:F38) -> 0.30736081
A39: CFO/Total Assets | B39: ='cash flow statement '!B5/'consolidated balance sheet'!B44 -> 0.034504408 | C39: ='cash flow statement '!C5/'consolidated balance sheet'!C44 -> 0.031259341 | D39: ='cash flow statement '!D5/'consolidated balance sheet'!D44 -> 0.019459242 | E39: ='cash flow statement '!E5/'consolidated balance sheet'!E44 -> 0.020477259 | F39: ='cash flow statement '!F5/'consolidated balance sheet'!F44 -> 0.022633343 | H39: =AVERAGE(B39:F39) -> 0.025666719 | I39: =MEDIAN(B39:F39) -> 0.022633343
A40: CFO/Total Debt | B40: =IF(('consolidated balance sheet'!B14+'consolidated balance sheet'!B20)=0,"",'cash flow statement '!B5/('consolidated balance sheet'!B14+'consolidated balance sheet'!B20)) -> 1087.3077 | C40: =IF(('consolidated balance sheet'!C14+'consolidated balance sheet'!C20)=0,"",'cash flow statement '!C5/('consolidated balance sheet'!C14+'consolidated balance sheet'!C20)) -> 215.20248 | D40: =IF(('consolidated balance sheet'!D14+'consolidated balance sheet'!D20)=0,"",'cash flow statement '!D5/('consolidated balance sheet'!D14+'consolidated balance sheet'!D20)) -> 272.2093 | E40: =IF(('consolidated balance sheet'!E14+'consolidated balance sheet'!E20)=0,"",'cash flow statement '!E5/('consolidated balance sheet'!E14+'consolidated balance sheet'!E20)) -> 689.6378 | F40: =IF(('consolidated balance sheet'!F14+'consolidated balance sheet'!F20)=0,"",'cash flow statement '!F5/('consolidated balance sheet'!F14+'consolidated balance sheet'!F20)) -> 2503.3256 | H40: =IFERROR(AVERAGE(B40:F40),"") -> 953.53657 | I40: =IFERROR(MEDIAN(B40:F40),"") -> 689.6378

Sheet FCFF
A1: Particular | B1: 44621 | C1: 44986 | D1: 45352 | E1: 45717 | F1: 46082
A2: EBIT | B2: ='consolidated P&l '!B17 -> 830.04 | C2: ='consolidated P&l '!C17 -> 880.88 | D2: ='consolidated P&l '!D17 -> 1119.59 | E2: ='consolidated P&l '!E17 -> 1920.64 | F2: ='consolidated P&l '!F17 -> 2080.77
A3: Less: Tax on EBIT | B3: =IF('consolidated P&l '!B19=0,"",B2*(ABS('consolidated P&l '!B23)/ABS('consolidated P&l '!B19))) -> 91.121691 | C3: =IF('consolidated P&l '!C19=0,"",C2*(ABS('consolidated P&l '!C23)/ABS('consolidated P&l '!C19))) -> 500.30229 | D3: =IF('consolidated P&l '!D19=0,"",D2*(ABS('consolidated P&l '!D23)/ABS('consolidated P&l '!D19))) -> 314.54418 | E3: =IF('consolidated P&l '!E19=0,"",E2*(ABS('consolidated P&l '!E23)/ABS('consolidated P&l '!E19))) -> 589.60279 | F3: =IF('consolidated P&l '!F19=0,"",F2*(ABS('consolidated P&l '!F23)/ABS('consolidated P&l '!F19))) -> 351.98653
A4: EBIT * (1- Tax) NOPAT | B4: =B2-B3 -> 738.91831 | C4: =C2-C3 -> 380.57771 | D4: =D2-D3 -> 805.04582 | E4: =E2-E3 -> 1331.0372 | F4: =F2-F3 -> 1728.7835
A5: Less: Net Capital expenditure | C5: ='Fixed Asset scheduled'!C8 -> 134.83 | D5: ='Fixed Asset scheduled'!D8 -> 112.66 | E5: ='Fixed Asset scheduled'!E8 -> 25.55 | F5: ='Fixed Asset scheduled'!F8 -> -19.98
A6: Less: Net Change in working Capital | C6: ='Change in working capital'!C6 -> 8.78 | D6: ='Change in working capital'!D6 -> 3.72 | E6: ='Change in working capital'!E6 -> 16.05 | F6: ='Change in working capital'!F6 -> -43.52
A7: Reinvestment | C7: =C5+C6 -> 143.61 | D7: =D5+D6 -> 116.38 | E7: =E5+E6 -> 41.6 | F7: =F5+F6 -> -63.5
A8: Free Cash Flow | C8: =C4-C7 -> 236.96771 | D8: =D4-D7 -> 688.66582 | E8: =E4-E7 -> 1289.4372 | F8: =F4-F7 -> 1792.2835
A10: Reinvestment Rate | C10: =IF(C4=0,"",C7/C4) -> 0.37734738 | D10: =IF(D4=0,"",D7/D4) -> 0.1445632 | E10: =IF(E4=0,"",E7/E4) -> 0.031253822 | F10: =IF(F4=0,"",F7/F4) -> -0.036731031
A12: Median Reinvestment rate /Sales percentage | C12: =MEDIAN(C10:F10) -> 0.087908511
A13: Average Reinvestment rate /Sales percentage | C13: =AVERAGE(C10:F10) -> 0.12910834

Sheet Fixed Asset scheduled
A1: Particular | B1: 44621 | C1: 44986 | D1: 45352 | E1: 45717 | F1: 46082
A2: Beginning balance | C2: =B6 -> 192.15 | D2: =C6 -> 326.98 | E2: =D6 -> 439.64 | F2: =E6 -> 465.19
A3: Add: Net Purchases | C3: =C6+C5-C2 -> 207.85 | D3: =D6+D5-D2 -> 213.79 | E3: =E6+E5-E2 -> 138.64 | F3: =F6+F5-F2 -> 102.6
A4: Total Fixed Assets | B4: ='consolidated balance sheet'!B32 -> 192.15 | C4: =C2+C3 -> 400 | D4: =D2+D3 -> 540.77 | E4: =E2+E3 -> 578.28 | F4: =F2+F3 -> 567.79
A5: Less: Depreciation | B5: ='consolidated P&l '!B14 -> 44.91 | C5: ='consolidated P&l '!C14 -> 73.02 | D5: ='consolidated P&l '!D14 -> 101.13 | E5: ='consolidated P&l '!E14 -> 113.09 | F5: ='consolidated P&l '!F14 -> 122.58
A6: Closing Balance(Fixed Asests ) | B6: ='consolidated balance sheet'!B32 -> 192.15 | C6: ='consolidated balance sheet'!C32 -> 326.98 | D6: ='consolidated balance sheet'!D32 -> 439.64 | E6: ='consolidated balance sheet'!E32 -> 465.19 | F6: ='consolidated balance sheet'!F32 -> 445.21
A8: Net Capital expenditure | C8: =C3-C5 -> 134.83 | D8: =D3-D5 -> 112.66 | E8: =E3-E5 -> 25.55 | F8: =F3-F5 -> -19.98
A9: Net Capital expenditure / Sales percentage | C9: =C8/'consolidated P&l '!C6 -> 0.057479889 | D9: =D8/'consolidated P&l '!D6 -> 0.044418335 | E9: =E8/'consolidated P&l '!E6 -> 0.008966328 | F9: =F8/'consolidated P&l '!F6 -> -0.0060826917
A11: Median Capital expenditure /Sales percentage | C11: =MEDIAN(C9:F9) -> 0.026692332
A12: Average Capital expenditure /Sales percentage | C12: =AVERAGE(C9:F9) -> 0.026195465

Sheet Change in working capital
A1: Particular | B1: 44621 | C1: 44986 | D1: 45352 | E1: 45717 | F1: 46082
A2: Inventory | B2: 0 | C2: 0 | D2: 0 | E2: 0 | F2: 0
A3: Trade Receivables | B3: ='consolidated balance sheet'!B39 -> 30.02 | C3: ='consolidated balance sheet'!C39 -> 12.62 | D3: ='consolidated balance sheet'!D39 -> 10.65 | E3: ='consolidated balance sheet'!E39 -> 13.19 | F3: ='consolidated balance sheet'!F39 -> 11.02
A4: Trade Payable | B4: ='consolidated balance sheet'!B21 -> 120.77 | C4: ='consolidated balance sheet'!C21 -> 94.59 | D4: ='consolidated balance sheet'!D21 -> 88.9 | E4: ='consolidated balance sheet'!E21 -> 75.39 | F4: ='consolidated balance sheet'!F21 -> 116.74
A5: Non Cash working Capital | B5: =B2+B3-B4 -> -90.75 | C5: =C2+C3-C4 -> -81.97 | D5: =D2+D3-D4 -> -78.25 | E5: =E2+E3-E4 -> -62.2 | F5: =F2+F3-F4 -> -105.72
A6: Change in Working Capital | C6: =C5-B5 -> 8.78 | D6: =D5-C5 -> 3.72 | E6: =E5-D5 -> 16.05 | F6: =F5-E5 -> -43.52
A7: change in working Capital /percentage of sales | C7: =C6/'consolidated P&l '!C6 -> 0.0037430351 | D7: =D6/'consolidated P&l '!D6 -> 0.0014666803 | E7: =E6/'consolidated P&l '!E6 -> 0.0056324683 | F7: =F6/'consolidated P&l '!F6 -> -0.013249186
A9: Median Non Cash working Capital /Sales percentage | C9: =MEDIAN(C5:F5)/MEDIAN('consolidated P&l '!C6:F6) -> -0.029748101
A10: Average Non Cash working Capital /Sales percentage | C10: =AVERAGE(C5:F5)/AVERAGE('consolidated P&l '!C6:F6) -> -0.029786743

Sheet Assumptions
A1: INFO EDGE
A2: Particulars (in RS Cr.) | B2: Mar 22 | C2: Mar 23 | D2: Mar 24 | E2: Mar 25 | F2: 46082
A3: Revenue from operations | B3: ='consolidated P&l '!B6 -> 1589.03 | C3: ='consolidated P&l '!C6 -> 2345.69 | D3: ='consolidated P&l '!D6 -> 2536.34 | E3: ='consolidated P&l '!E6 -> 2849.55 | F3: ='consolidated P&l '!F6 -> 3284.73
A4: Revenue growth in % | C4: =(C3-B3)/B3 -> 0.47617729 | D4: =(D3-C3)/C3 -> 0.081276725 | E4: =(E3-D3)/D3 -> 0.12348896 | F4: =(F3-E3)/E3 -> 0.15271885
A5: Less: Material cost | B5: ='consolidated P&l '!B11 -> 34.02 | C5: ='consolidated P&l '!C11 -> 63.37 | D5: ='consolidated P&l '!D11 -> 74.71 | E5: ='consolidated P&l '!E11 -> 78.3 | F5: ='consolidated P&l '!F11 -> 0
A6: Less: Employee costs | B6: ='consolidated P&l '!B12 -> 746.31 | C6: ='consolidated P&l '!C12 -> 1097.31 | D6: ='consolidated P&l '!D12 -> 1128.24 | E6: ='consolidated P&l '!E12 -> 1235.34 | F6: ='consolidated P&l '!F12 -> 1341.5
A7: Less: Other Expenses | B7: ='consolidated P&l '!B15 -> 369.47 | C7: ='consolidated P&l '!C15 -> 616.64 | D7: ='consolidated P&l '!D15 -> 504.15 | E7: ='consolidated P&l '!E15 -> 551.2 | F7: ='consolidated P&l '!F15 -> 771.02
A8: Total Expenses | B8: =B5+B6+B7 -> 1149.8 | C8: =C5+C6+C7 -> 1777.32 | D8: =D5+D6+D7 -> 1707.1 | E8: =E5+E6+E7 -> 1864.84 | F8: =F5+F6+F7 -> 2112.52
A9: EBITDA | B9: =B3-B8 -> 439.23 | C9: =C3-C8 -> 568.37 | D9: =D3-D8 -> 829.24 | E9: =E3-E8 -> 984.71 | F9: =F3-F8 -> 1172.21
A10: Less: Depreciation And Amortization | B10: ='consolidated P&l '!B14 -> 44.91 | C10: ='consolidated P&l '!C14 -> 73.02 | D10: ='consolidated P&l '!D14 -> 101.13 | E10: ='consolidated P&l '!E14 -> 113.09 | F10: ='consolidated P&l '!F14 -> 122.58
A11: EBIT | B11: =B9-B10 -> 394.32 | C11: =C9-C10 -> 495.35 | D11: =D9-D10 -> 728.11 | E11: =E9-E10 -> 871.62 | F11: =F9-F10 -> 1049.63
A12: ADD: Non operating income/ Other Income | B12: ='consolidated P&l '!B8 -> 440.36 | C12: ='consolidated P&l '!C8 -> 392.85 | D12: ='consolidated P&l '!D8 -> 413.74 | E12: ='consolidated P&l '!E8 -> 1073.25 | F12: ='consolidated P&l '!F8 -> 1058.55
A13: Less: Interest Expenses | B13: ='consolidated P&l '!B13 -> 4.65 | C13: ='consolidated P&l '!C13 -> 7.34 | D13: ='consolidated P&l '!D13 -> 22.26 | E13: ='consolidated P&l '!E13 -> 24.24 | F13: ='consolidated P&l '!F13 -> 27.43
A14: EBT | B14: =B11+B12-B13 -> 830.03 | C14: =C11+C12-C13 -> 880.86 | D14: =D11+D12-D13 -> 1119.59 | E14: =E11+E12-E13 -> 1920.63 | F14: =F11+F12-F13 -> 2080.75
A15: Less: TAX | B15: ='consolidated P&l '!B23 -> 1317.88 | C15: ='consolidated P&l '!C23 -> 211.07 | D15: ='consolidated P&l '!D23 -> 283.48 | E15: ='consolidated P&l '!E23 -> 634.72 | F15: ='consolidated P&l '!F23 -> 358.55
A16: Less:Non Controlling Interest/Minority Interest | B16: =ABS('consolidated P&l '!B27) -> 122.66 | C16: =ABS('consolidated P&l '!C27) -> 36.95 | D16: =ABS('consolidated P&l '!D27) -> 19.35 | E16: =ABS('consolidated P&l '!E27) -> 347.76 | F16: =ABS('consolidated P&l '!F27) -> 313.03
A17: Net Profit- Pat | B17: =B14-B15-B16 -> -610.51 | C17: =C14-C15-C16 -> 632.84 | D17: =D14-D15-D16 -> 816.76 | E17: =E14-E15-E16 -> 938.15 | F17: =F14-F15-F16 -> 1409.17
A23: Historical Growth
A24: Average Growth | B24: =AVERAGE(C4:F4) -> 0.20841546
A25: CAGR | B25: =(F3/B3)^(1/5)-1 -> 0.15630796 | C25: =_xlfn.RRI(5,B3,F3) -> 0.15630796 | D25: RRI
A27: Margins
A28: EBITDA | B28: =B9/B3 -> 0.27641391 | C28: =C9/C3 -> 0.24230397 | D28: =D9/D3 -> 0.32694355 | E28: =E9/E3 -> 0.34556684 | F28: =F9/F3 -> 0.35686647
A29: EBIT | B29: =B11/B3 -> 0.24815139 | C29: =C11/C3 -> 0.21117454 | D29: =D11/D3 -> 0.28707113 | E29: =E11/E3 -> 0.30587988 | F29: =F11/F3 -> 0.31954833
A30: EBT | B30: =B14/B3 -> 0.52235011 | C30: =C14/C3 -> 0.37552277 | D30: =D14/D3 -> 0.44141953 | E30: =E14/E3 -> 0.67401169 | F30: =F14/F3 -> 0.6334615
A31: Net Proftt | B31: =B17/B3 -> -0.38420294 | C31: =C17/C3 -> 0.26978842 | D31: =D17/D3 -> 0.32202307 | E31: =E17/E3 -> 0.32922742 | F31: =F17/F3 -> 0.42900634
A33: Tax Rate
A34: Effective tax rate | B34: =B15/B14 -> 1.5877498 | C34: =C15/C14 -> 0.2396181 | D34: =D15/D14 -> 0.25319983 | E34: =E15/E14 -> 0.3304749 | F34: =F15/F14 -> 0.17231767 | G34: =AVERAGE(B34:F34) -> 0.51667207
A35: Marginal Tax rate | B35: 0.3 | C35: =B35 -> 0.3 | D35: =C35 -> 0.3 | E35: =D35 -> 0.3 | F35: =E35 -> 0.3
A37: Return On Capital
A38: EBIT*(1-T) | B38: =B11*(1-B35) -> 276.024 | C38: =C11*(1-C35) -> 346.745 | D38: =D11*(1-D35) -> 509.677 | E38: =E11*(1-E35) -> 610.134 | F38: =F11*(1-F35) -> 734.741
A39: Book Equity | B39: ='consolidated balance sheet'!B11 -> 17241.36 | C39: ='consolidated balance sheet'!C11 -> 13398.02 | D39: ='consolidated balance sheet'!D11 -> 30262.29 | E39: ='consolidated balance sheet'!E11 -> 34903.06 | F39: ='consolidated balance sheet'!F11 -> 37913.13
A40: Book Debt | B40: ='consolidated balance sheet'!B14+'consolidated balance sheet'!B20 -> 0.65 | C40: ='consolidated balance sheet'!C14+'consolidated balance sheet'!C20 -> 2.42 | D40: ='consolidated balance sheet'!D14+'consolidated balance sheet'!D20 -> 2.58 | E40: ='consolidated balance sheet'!E14+'consolidated balance sheet'!E20 -> 1.27 | F40: ='consolidated balance sheet'!F14+'consolidated balance sheet'!F20 -> 0.43
A41: Cash and Cash equivalents | B41: ='consolidated balance sheet'!B40 -> 368.29 | C41: ='consolidated balance sheet'!C40 -> 571.46 | D41: ='consolidated balance sheet'!D40 -> 1192.98 | E41: ='consolidated balance sheet'!E40 -> 267.13 | F41: ='consolidated balance sheet'!F40 -> 375.91
A42: Capital Employed | B42: =B39+B40-B41 -> 16873.72 | C42: =C39+C40-C41 -> 12828.98 | D42: =D39+D40-D41 -> 29071.89 | E42: =E39+E40-E41 -> 34637.2 | F42: =F39+F40-F41 -> 37537.65
A44: Pre-Tax Return on capital | B44: =B11/B42 -> 0.023368884 | C44: =C11/C42 -> 0.038611799 | D44: =D11/D42 -> 0.025045155 | E44: =E11/E42 -> 0.025164274 | F44: =F11/F42 -> 0.027962059
A45: Post Tax return On capital | B45: =B38/B42 -> 0.016358219 | C45: =C38/C42 -> 0.027028259 | D45: =D38/D42 -> 0.017531609 | E45: =E38/E42 -> 0.017614992 | F45: =F38/F42 -> 0.019573442
A47: Growth In EBIT | B47: =FCFF!C12*F45 -> 0.0017206721

Sheet Wacc
A1: Capital Structure
A2: Total Debt | B2: ='consolidated balance sheet'!E14+'consolidated balance sheet'!E20 -> 1.27
A3: Total Equity | B3: ='consolidated balance sheet'!E11 -> 34903.06
A4: Total Mix (Debt + Equity) | B4: =B2+B3 -> 34904.33
A5: % of Debt | B5: =B2/B4 -> 3.6385171e-05
A6: % of Equity | B6: =B3/B4 -> 0.99996361
A7: Debt to Equity | B7: =B2/B3 -> 3.6386494e-05
A9: Cost of Equity (CAPM)
A10: Risk-free Rate (Rf) | B10: 0.0707 | D10: Source: RBI 10-year Government Securities yield (FY2025)
A11: Beta (β) | B11: =Beta!I25 -> 1.1473589
A12: Market Risk Premium (Rm - Rf) | B12: 0.0685 | D12: Source: India Equity Risk Premium (Damodaran estimate)
A13: Cost of Equity [Ke = Rf + β×(Rm-Rf)] | B13: =B10+B11*(B12) -> 0.14929409
A15: Cost of Debt
A16: Finance Cost (FY2025) | B16: ='consolidated P&l '!E13 -> 24.24
A17: Total Debt (FY2025) | B17: =B2 -> 1.27
A18: Pre-tax Cost of Debt [Kd = FC/Debt] | B18: =B16/B17 -> 19.086614 | E18: Note: Pre-tax Kd is distorted; Info Edge is near-zero debt company (Total Debt = ₹1.27 Cr). Finance Costs include lease & other items. WACC effectively = Ke.
A19: Tax Rate | B19: =Assumptions!E35 -> 0.3 | D19: Source: Marginal Tax Rate (Assumptions sheet)
A20: Post-tax Cost of Debt [Kd*(1-T)] | B20: =B18*(1-B19) -> 13.36063
A22: WACC
A23: Source | B23: Weight | C23: Cost | D23: Weighted Cost
A24: Debt | B24: =B5 -> 3.6385171e-05 | C24: =B20 -> 13.36063 | D24: =B24*C24 -> 0.0004861288
A25: Equity | B25: =B6 -> 0.99996361 | C25: =B13 -> 0.14929409 | D25: =B25*C25 -> 0.14928865
A26: WACC | B26: =SUM(B24:B25) -> 1 | C26: (Check: weights = 100%) | D26: =D24+D25 -> 0.14977478 | F26: wacc = we*ke+wd*kd

Sheet Beta
A1: Trading_Date | B1: NIFTY50_Close | C1: INFOEDGE_Close | D1: Rm Nifty | E1: Rm Info edge | F1: slope | G1: covariance
A2: 2020-04-01 | B2: 8253.7998 | C2: 402.79001
A3: 2020-04-03 | B3: 8083.7998 | C3: 401.32999 | D3: =(B3-B2)/B2 -> -0.020596574 | E3: =(C3-C2)/C2 -> -0.0036247721 | F3: =SLOPE(E3:E1524,D3:D1524) -> 1.1473467 | G3: =_xlfn.COVARIANCE.S(E3:E1524,D3:D1524)/_xlfn.VAR.S(D3:D1524) -> 1.1473467 | H3: SUMMARY OUTPUT
A4: 2020-04-07 | B4: 8792.2002 | C4: 471.62 | D4: =(B4-B3)/B3 -> 0.087632105 | E4: =(C4-C3)/C3 -> 0.17514268
A5: 2020-04-08 | B5: 8748.75 | C5: 450.76999 | D5: =(B5-B4)/B4 -> -0.0049419024 | E5: =(C5-C4)/C4 -> -0.044209334 | H5: Regression Statistics
A6: 2020-04-09 | B6: 9111.9004 | C6: 448.39001 | D6: =(B6-B5)/B5 -> 0.041508832 | E6: =(C6-C5)/C5 -> -0.0052797977 | H6: Multiple R | I6: 0.48608648
A7: 2020-04-13 | B7: 8993.8496 | C7: 432.26001 | D7: =(B7-B6)/B6 -> -0.012955671 | E7: =(C7-C6)/C6 -> -0.035973158 | H7: R Square | I7: 0.23628006
A8: 2020-04-15 | B8: 8925.2998 | C8: 472.39001 | D8: =(B8-B7)/B7 -> -0.0076218536 | E8: =(C8-C7)/C7 -> 0.092837653 | H8: Adjusted R Square | I8: 0.23577762
A9: 2020-04-16 | B9: 8992.7998 | C9: 469.69 | D9: =(B9-B8)/B8 -> 0.0075627712 | E9: =(C9-C8)/C8 -> -0.005715642 | H9: Standard Error | I9: 0.020246729
A10: 2020-04-17 | B10: 9266.75 | C10: 497.31 | D10: =(B10-B9)/B9 -> 0.030463282 | E10: =(C10-C9)/C9 -> 0.058804733 | H10: Observations | I10: 1522
A11: 2020-04-20 | B11: 9261.8496 | C11: 488.97 | D11: =(B11-B10)/B10 -> -0.00052881438 | E11: =(C11-C10)/C10 -> -0.016770217
A12: 2020-04-21 | B12: 8981.4502 | C12: 477.42999 | D12: =(B12-B11)/B11 -> -0.030274667 | E12: =(C12-C11)/C11 -> -0.023600647 | H12: ANOVA
A13: 2020-04-22 | B13: 9187.2998 | C13: 499.32999 | D13: =(B13-B12)/B12 -> 0.022919418 | E13: =(C13-C12)/C12 -> 0.045870587 | I13: df | J13: SS | K13: MS | L13: F | M13: Significance F
A14: 2020-04-23 | B14: 9313.9004 | C14: 492.57001 | D14: =(B14-B13)/B13 -> 0.013779956 | E14: =(C14-C13)/C13 -> -0.0135381 | H14: Regression | I14: 1 | J14: 0.19277302 | K14: 0.19277302 | L14: 470.25837 | M14: 4.5004222e-91
A15: 2020-04-24 | B15: 9154.4004 | C15: 465.42001 | D15: =(B15-B14)/B14 -> -0.017124942 | E15: =(C15-C14)/C14 -> -0.055119056 | H15: Residual | I15: 1520 | J15: 0.62309363 | K15: 0.00040993002
A16: 2020-04-27 | B16: 9282.2998 | C16: 464.54999 | D16: =(B16-B15)/B15 -> 0.013971359 | E16: =(C16-C15)/C15 -> -0.0018693344 | H16: Total | I16: 1521 | J16: 0.81586665
A17: 2020-04-28 | B17: 9380.9004 | C17: 478.45001 | D17: =(B17-B16)/B16 -> 0.010622431 | E17: =(C17-C16)/C16 -> 0.029921483
A18: 2020-04-29 | B18: 9553.3496 | C18: 486.95001 | D18: =(B18-B17)/B17 -> 0.018383014 | E18: =(C18-C17)/C17 -> 0.017765701 | I18: Coefficients | J18: Standard Error | K18: t Stat | L18: P-value | M18: Lower 95% | N18: Upper 95% | O18: Lower 95.0% | P18: Upper 95.0%
A19: 2020-04-30 | B19: 9859.9004 | C19: 509.51999 | D19: =(B19-B18)/B18 -> 0.032088303 | E19: =(C19-C18)/C18 -> 0.046349679 | H19: Intercept | I19: 2.9906338e-05 | J19: 0.00052043249 | K19: 0.057464393 | L19: 0.95418282 | M19: -0.00099093548 | N19: 0.0010507482 | O19: -0.00099093548 | P19: 0.0010507482
A20: 2020-05-04 | B20: 9293.5 | C20: 500.14999 | D20: =(B20-B19)/B19 -> -0.057444839 | E20: =(C20-C19)/C19 -> -0.018389848 | H20: X Variable 1 | I20: 1.1473467 | J20: 0.052908616 | K20: 21.685442 | L20: 4.5004222e-91 | M20: 1.0435651 | N20: 1.2511283 | O20: 1.0435651 | P20: 1.2511283
A21: 2020-05-05 | B21: 9205.5996 | C21: 518.31 | D21: =(B21-B20)/B20 -> -0.0094582655 | E21: =(C21-C20)/C20 -> 0.036309115
A22: 2020-05-06 | B22: 9270.9004 | C22: 529.37 | D22: =(B22-B21)/B21 -> 0.0070935935 | E22: =(C22-C21)/C21 -> 0.021338577 | H22: unlevered betA | I22: Bl/1+(1-t)*D/E
A23: 2020-05-07 | B23: 9199.0498 | C23: 518.65997 | D23: =(B23-B22)/B22 -> -0.0077501195 | E23: =(C23-C22)/C22 -> -0.020231638 | H23: LEVERED BETA | I23: BU(1+(1-T)*D/E
A24: 2020-05-08 | B24: 9251.5 | C24: 539.59003 | D24: =(B24-B23)/B23 -> 0.0057016971 | E24: =(C24-C23)/C23 -> 0.040354095 | H24: UL | I24: =F3/1+(1-25%)*('consolidated balance sheet'!F14+'consolidated balance sheet'!F20)/130327.3 -> 1.1473492
A25: 2020-05-11 | B25: 9239.2002 | C25: 514.19 | D25: =(B25-B24)/B24 -> -0.001329493 | E25: =(C25-C24)/C24 -> -0.04707282 | I25: =I24*(1+(1-25%)*('consolidated balance sheet'!F14+'consolidated balance sheet'!F20)/'consolidated balance sheet'!F11) -> 1.1473589
A26: 2020-05-12 | B26: 9196.5498 | C26: 505.09 | D26: =(B26-B25)/B25 -> -0.0046162427 | E26: =(C26-C25)/C25 -> -0.01769775
A27: 2020-05-13 | B27: 9383.5498 | C27: 523.22998 | D27: =(B27-B26)/B26 -> 0.020333713 | E27: =(C27-C26)/C26 -> 0.03591436
A28: 2020-05-14 | B28: 9142.75 | C28: 539.15997 | D28: =(B28-B27)/B27 -> -0.025661909 | E28: =(C28-C27)/C27 -> 0.030445489
A29: 2020-05-15 | B29: 9136.8496 | C29: 518.33002 | D29: =(B29-B28)/B28 -> -0.00064536279 | E29: =(C29-C28)/C28 -> -0.038634092
A30: 2020-05-18 | B30: 8823.25 | C30: 480.78 | D30: =(B30-B29)/B29 -> -0.03432251 | E30: =(C30-C29)/C29 -> -0.072444229
A31: 2020-05-19 | B31: 8879.0996 | C31: 492.51999 | D31: =(B31-B30)/B30 -> 0.0063298228 | E31: =(C31-C30)/C30 -> 0.024418633
A32: 2020-05-20 | B32: 9066.5498 | C32: 479.41 | D32: =(B32-B31)/B31 -> 0.021111397 | E32: =(C32-C31)/C31 -> -0.026618179
A33: 2020-05-21 | B33: 9106.25 | C33: 491.20999 | D33: =(B33-B32)/B32 -> 0.0043787545 | E33: =(C33-C32)/C32 -> 0.024613562
A34: 2020-05-22 | B34: 9039.25 | C34: 484.66 | D34: =(B34-B33)/B33 -> -0.0073575841 | E34: =(C34-C33)/C33 -> -0.013334394
A35: 2020-05-26 | B35: 9029.0498 | C35: 479.01999 | D35: =(B35-B34)/B34 -> -0.0011284338 | E35: =(C35-C34)/C34 -> -0.011637054
A36: 2020-05-27 | B36: 9314.9502 | C36: 486.38 | D36: =(B36-B35)/B35 -> 0.031664505 | E36: =(C36-C35)/C35 -> 0.015364736
A37: 2020-05-28 | B37: 9490.0996 | C37: 514.17999 | D37: =(B37-B36)/B36 -> 0.018803044 | E37: =(C37-C36)/C36 -> 0.05715693
... A1524: 2026-06-02 | B1524: 23483.551 | C1524: 1015.7 | D1524: =(B1524-B1523)/B1523 -> 0.0043173631 | E1524: =(C1524-C1523)/C1523 -> 0.011603032

Sheet FORECASTING
D3: Sales Forecasting | I3: EBITDA Forecasting | N3: Earning per share Forecasting
D4: Year Weight | E4: Year | F4: Sales | G4: Sales Growth | I4: Year Weight | J4: Year | K4: EBITDA | L4: EBITDA Growth | N4: Year Weight | O4: Year | P4: EPS | Q4: EPS Growth
D5: 1 | E5: ='Ratio Analysis'!B2 -> 44621 | F5: =Assumptions!B3 -> 1589.03 | I5: 1 | J5: ='Ratio Analysis'!B2 -> 44621 | K5: =Assumptions!B9 -> 439.23 | N5: 1 | O5: ='Ratio Analysis'!B2 -> 44621 | P5: ='consolidated P&l '!B32 -> 991
D6: =D5+1 -> 2 | E6: =E5+365 -> 44986 | F6: =Assumptions!C3 -> 2345.69 | G6: =(F6-F5)/F5 -> 0.47617729 | I6: =I5+1 -> 2 | J6: =J5+365 -> 44986 | K6: =Assumptions!C9 -> 568.37 | L6: =(K6-K5)/K5 -> 0.29401453 | N6: =N5+1 -> 2 | O6: =O5+365 -> 44986 | P6: ='consolidated P&l '!C32 -> -8 | Q6: =(P6-P5)/P5 -> -1.0080727
D7: =D6+1 -> 3 | E7: =E6+365 -> 45351 | F7: =Assumptions!D3 -> 2536.34 | G7: =(F7-F6)/F6 -> 0.081276725 | I7: =I6+1 -> 3 | J7: =J6+365 -> 45351 | K7: =Assumptions!D9 -> 829.24 | L7: =(K7-K6)/K6 -> 0.45897919 | N7: =N6+1 -> 3 | O7: =O6+365 -> 45351 | P7: ='consolidated P&l '!D32 -> 45 | Q7: =(P7-P6)/P6 -> -6.625
D8: =D7+1 -> 4 | E8: =E7+365 -> 45716 | F8: =Assumptions!E3 -> 2849.55 | G8: =(F8-F7)/F7 -> 0.12348896 | I8: =I7+1 -> 4 | J8: =J7+365 -> 45716 | K8: =Assumptions!E9 -> 984.71 | L8: =(K8-K7)/K7 -> 0.18748493 | N8: =N7+1 -> 4 | O8: =O7+365 -> 45716 | P8: ='consolidated P&l '!E32 -> 15 | Q8: =(P8-P7)/P7 -> -0.66666667
D9: =D8+1 -> 5 | E9: =E8+365 -> 46081 | F9: =Assumptions!F3 -> 3284.73 | G9: =(F9-F8)/F8 -> 0.15271885 | I9: =I8+1 -> 5 | J9: =J8+365 -> 46081 | K9: =Assumptions!F9 -> 1172.21 | L9: =(K9-K8)/K8 -> 0.19041139 | N9: =N8+1 -> 5 | O9: =O8+365 -> 46081 | P9: ='consolidated P&l '!F32 -> 22 | Q9: =(P9-P8)/P8 -> 0.46666667
D10: =D9+1 -> 6 | E10: =E9+365 -> 46446 | F10: =FORECAST(D10,$F$5:$F$9,$D$5:$D$9) -> 3689.646 | G10: =(F10-F9)/F9 -> 0.12327223 | I10: =I9+1 -> 6 | J10: =J9+365 -> 46446 | K10: =FORECAST(I10,$K$5:$K$9,$I$5:$I$9) -> 1363.442 | L10: =(K10-K9)/K9 -> 0.163138 | N10: =N9+1 -> 6 | O10: =O9+365 -> 46446 | P10: =FORECAST(N10,$P$5:$P$9,$N$5:$N$9) -> -361.5 | Q10: =(P10-P9)/P9 -> -17.431818
D11: =D10+1 -> 7 | E11: =E10+365 -> 46811 | F11: =FORECAST(D11,$F$5:$F$9,$D$5:$D$9) -> 4079.172 | G11: =(F11-F10)/F10 -> 0.10557273 | I11: =I10+1 -> 7 | J11: =J10+365 -> 46811 | K11: =FORECAST(I11,$K$5:$K$9,$I$5:$I$9) -> 1551.672 | L11: =(K11-K10)/K10 -> 0.13805501 | N11: =N10+1 -> 7 | O11: =O10+365 -> 46811 | P11: =FORECAST(N11,$P$5:$P$9,$N$5:$N$9) -> -553 | Q11: =(P11-P10)/P10 -> 0.52973721
D12: =D11+1 -> 8 | E12: =E11+365 -> 47176 | F12: =FORECAST(D12,$F$5:$F$9,$D$5:$D$9) -> 4468.698 | G12: =(F12-F11)/F11 -> 0.095491438 | I12: =I11+1 -> 8 | J12: =J11+365 -> 47176 | K12: =FORECAST(I12,$K$5:$K$9,$I$5:$I$9) -> 1739.902 | L12: =(K12-K11)/K11 -> 0.12130785 | N12: =N11+1 -> 8 | O12: =O11+365 -> 47176 | P12: =FORECAST(N12,$P$5:$P$9,$N$5:$N$9) -> -744.5 | Q12: =(P12-P11)/P11 -> 0.34629295
D13: =D12+1 -> 9 | E13: =E12+365 -> 47541 | F13: =FORECAST(D13,$F$5:$F$9,$D$5:$D$9) -> 4858.224 | G13: =(F13-F12)/F12 -> 0.087167672 | I13: =I12+1 -> 9 | J13: =J12+365 -> 47541 | K13: =FORECAST(I13,$K$5:$K$9,$I$5:$I$9) -> 1928.132 | L13: =(K13-K12)/K12 -> 0.10818425 | N13: =N12+1 -> 9 | O13: =O12+365 -> 47541 | P13: =FORECAST(N13,$P$5:$P$9,$N$5:$N$9) -> -936 | Q13: =(P13-P12)/P12 -> 0.25721961
D14: =D13+1 -> 10 | E14: =E13+365 -> 47906 | F14: =FORECAST(D14,$F$5:$F$9,$D$5:$D$9) -> 5247.75 | G14: =(F14-F13)/F13 -> 0.080178683 | I14: =I13+1 -> 10 | J14: =J13+365 -> 47906 | K14: =FORECAST(I14,$K$5:$K$9,$I$5:$I$9) -> 2116.362 | L14: =(K14-K13)/K13 -> 0.097622984 | N14: =N13+1 -> 10 | O14: =O13+365 -> 47906 | P14: =FORECAST(N14,$P$5:$P$9,$N$5:$N$9) -> -1127.5 | Q14: =(P14-P13)/P13 -> 0.20459402

Sheet Relative valuation
A1: RELATIVE VALUATION – Info Edge | INR Crores)
A3: Company | B3: Market Data | F3: Financial Data | J3: Valuation Ratios
B4: Price (₹) | C4: Shares (Cr.) | D4: Mkt Cap (Cr.) | E4: EV (Cr.) | F4: Revenue (Cr.) | G4: EBITDA (Cr.) | H4: EBIT (Cr.) | I4: EPS (₹) | J4: P/E | K4: EV/Sales | L4: EV/EBITDA | M4: EV/EBIT
A5: Info Edge | B5: 988 | C5: ='consolidated balance sheet'!F6/2 -> 64.775 | D5: =B5*C5 -> 63997.7 | E5: =D5+'consolidated balance sheet'!F14+'consolidated balance sheet'!F20-'consolidated balance sheet'!F40-'consolidated balance sheet'!F38 -> 62362.41 | F5: ='consolidated P&l '!F5 -> 3284.73 | G5: =Assumptions!F9 -> 1172.21 | H5: =Assumptions!F11 -> 1049.63 | I5: ='consolidated P&l '!F32 -> 22 | J5: =B5/I5 -> 44.909091 | K5: =E5/F5 -> 18.985551 | L5: =E5/G5 -> 53.200715 | M5: =E5/H5 -> 59.413708
A6: Indiamart Inter. | B6: 2000 | C6: =60/10 -> 6 | D6: 12031.04 | E6: 11963 | F6: 1569 | G6: 475 | H6: =648+3 -> 651 | I6: 79 | J6: =B6/I6 -> 25.316456 | K6: =E6/F6 -> 7.6246017 | L6: =E6/G6 -> 25.185263 | M6: =E6/H6 -> 18.376344
A7: Just Dial | B7: 523.6 | C7: =85/10 -> 8.5 | D7: 4453.17 | E7: 4329 | F7: 1214 | G7: 358 | H7: =616+9 -> 625 | I7: 58.44 | J7: =B7/I7 -> 8.9596167 | K7: =E7/F7 -> 3.5658979 | L7: =E7/G7 -> 12.092179 | M7: =E7/H7 -> 6.9264
A8: Crizac | B8: 214.38 | C8: =35/2 -> 17.5 | D8: 3751.27 | E8: 3588 | F8: 1042 | G8: 286 | H8: 287 | I8: 12.52 | J8: =B8/I8 -> 17.123003 | K8: =E8/F8 -> 3.4433781 | L8: =E8/G8 -> 12.545455 | M8: =E8/H8 -> 12.501742
A9: TCC Concept | B9: 361.85 | C9: =48/10 -> 4.8 | D9: 1719.8 | E9: 1931 | F9: 179 | G9: 97 | H9: =54+22 -> 76 | I9: 13.25 | J9: =B9/I9 -> 27.309434 | K9: =E9/F9 -> 10.787709 | L9: =E9/G9 -> 19.907216 | M9: =E9/H9 -> 25.407895
A10: Peer Average | B10: =AVERAGE(B6:B9) -> 774.9575 | C10: =AVERAGE(C6:C9) -> 9.2 | D10: =AVERAGE(D6:D9) -> 5488.82 | E10: =AVERAGE(E6:E9) -> 5452.75 | F10: =AVERAGE(F6:F9) -> 1001 | G10: =AVERAGE(G6:G9) -> 304 | H10: =AVERAGE(H6:H9) -> 409.75 | I10: =AVERAGE(I6:I9) -> 40.8025 | ... M10: =AVERAGE(M6:M9) -> 15.803095
A11: Peer Median | B11: =MEDIAN(B6:B9) -> 442.725 | C11: =MEDIAN(C6:C9) -> 7.25 | D11: =MEDIAN(D6:D9) -> 4102.22 | E11: =MEDIAN(E6:E9) -> 3958.5 | F11: =MEDIAN(F6:F9) -> 1128 | G11: =MEDIAN(G6:G9) -> 322 | H11: =MEDIAN(H6:H9) -> 456 | I11: =MEDIAN(I6:I9) -> 35.845 | ... M11: =MEDIAN(M6:M9) -> 15.439043
A13: INFO EDGE — IMPLIED SHARE PRICE FROM PEER MULTIPLES
A14: Valuation Basis | B14: Peer Avg Multiple | C14: Peer Median Multiple | D14: NMDC Actual | E14: Implied EV (Avg) | F14: Implied EV (Median) | G14: Implied Equity (Avg) | H14: Implied Equity (Median) | I14: Implied Price (Avg) ₹ | J14: Implied Price (Med) ₹ | K14: CMP ₹ | L14: Premium/Disc (vs Avg) | M14: Premium/Disc (vs Med)
A15: EV / Sales | B15: =K10 -> 6.3553968 | C15: =K11 -> 5.5952498 | D15: =K5 -> 18.985551 | E15: =B15*F5 -> 20875.762 | F15: =C15*F5 -> 18378.885 | G15: =E15-(E5-D5) -> 22511.052 | H15: =F15-(E5-D5) -> 20014.175 | I15: =G15/C5 -> 347.52686 | J15: =H15/C5 -> 308.97993 | K15: =B5 -> 988 | L15: =(B5-I15)/I15 -> 1.8429457 | M15: =(B5-J15)/J15 -> 2.1976187
A16: EV / EBITDA | B16: =L10 -> 17.432528 | C16: =L11 -> 16.226336 | D16: =L5 -> 53.200715 | E16: =B16*G5 -> 20434.584 | F16: =C16*G5 -> 19020.673 | G16: =E16-(E5-D5) -> 22069.874 | H16: =F16-(E5-D5) -> 20655.963 | I16: =G16/C5 -> 340.71592 | J16: =H16/C5 -> 318.88789 | K16: =K15 -> 988 | L16: =(B5-I16)/I16 -> 1.8997764 | M16: =(B5-J16)/J16 -> 2.0982676
A17: P / E | B17: =J10 -> 19.677127 | C17: =J11 -> 21.219729 | D17: =J5 -> 44.909091 | E17: =B17*I5 -> 432.8968 | F17: =C17*I5 -> 466.83405 | G17: =E17*C5 -> 28040.89 | H17: =F17*C5 -> 30239.175 | I17: =E17 -> 432.8968 | J17: =F17 -> 466.83405 | K17: =K16 -> 988 | L17: =(B5-I17)/I17 -> 1.2822991 | M17: =(B5-J17)/J17 -> 1.1163838
O19: EV/Revenue | P19: EV/EBITDA | Q19: P/E Ratio
A20: Max | O20: =MAX(K6:K9) -> 10.787709 | P20: =MAX(L6:L9) -> 25.185263 | Q20: =MAX(J6:J9) -> 27.309434
A21: 75th Percentile | O21: =QUARTILE(K6:K9,3) -> 8.4153786 | P21: =QUARTILE(L6:L9,3) -> 21.226728 | Q21: =QUARTILE(J6:J9,3) -> 25.8147
A22: Average | O22: =AVERAGE(K6:K9) -> 6.3553968 | P22: =AVERAGE(L6:L9) -> 17.432528 | Q22: =AVERAGE(J6:J9) -> 19.677127
A23: median | O23: =MEDIAN(K6:K9) -> 5.5952498 | P23: =MEDIAN(L6:L9) -> 16.226336 | Q23: =MEDIAN(J6:J9) -> 21.219729
A24: 25th Percentile | O24: =QUARTILE(K6:K9,1) -> 3.5352679 | P24: =QUARTILE(L6:L9,1) -> 12.432136 | Q24: =QUARTILE(J6:J9,1) -> 15.082157
A25: Min. | O25: =MIN(K6:K9) -> 3.4433781 | P25: =MIN(L6:L9) -> 12.092179 | Q25: =MIN(J6:J9) -> 8.9596167
A27: M&M Industry Comparable comps | O27: EV/Revenue | P27: EV/EBITDA | Q27: P/E Ratio
A29: Implied Enterprise Value | O29: =O22*F5 -> 20875.762 | P29: =P22*G5 -> 20434.584 | Q29: =Q22*I5*C5 -> 28040.89
A30: Net Debt | O30: =E5-D5 -> -1635.29 | P30: =E5-D5 -> -1635.29 | Q30: =E5-D5 -> -1635.29
A31: Implied Market Value | O31: =O29-O30 -> 22511.052 | P31: =P29-P30 -> 22069.874 | Q31: =Q29-Q30 -> 29676.18
A32: Share Outstanding | O32: =C5 -> 64.775 | P32: =C5 -> 64.775 | Q32: =C5 -> 64.775
A34: Implied Value per Share | O34: =O31/O32 -> 347.52686 | P34: =P31/P32 -> 340.71592 | Q34: =Q22*I5 -> 432.8968

Sheet Growth scenario
A1: Scenario 1: High Growth
A2: INR Cr. | B2: LTM | C2: Y1E | D2: Y2E | E2: Y3E | F2: Y4W | G2: Y5E | H2: Y6E | I2: Y7E | J2: Y8E | K2: Y9E | L2: Y10E
A3: Sales | B3: =Assumptions!F3 -> 3284.73 | C3: =B3*(1+C4) -> 3798.1595 | D3: =C3*(1+D4) -> 4356.98 | E3: =D3*(1+E4) -> 4958.0282 | F3: =E3*(1+F4) -> 5596.4832 | G3: =F3*(1+G4) -> 6265.7852 | H3: =G3*(1+H4) -> 6957.6197 | I3: =H3*(1+I4) -> 7661.9812 | J3: =I3*(1+J4) -> 8367.3227 | ... L3: =K3*(1+L4) -> 9728.5758 | M3: =Assumptions!B25 -> 0.15630796 | P3: Risk free rate
A4: Sales Growth % | C4: =M3 -> 0.15630796 | D4: =C4-$O$4 -> 0.1471293 | E4: =D4-$O$4 -> 0.13795064 | F4: =E4-$O$4 -> 0.12877197 | G4: =F4-$O$4 -> 0.11959331 | H4: =G4-$O$4 -> 0.11041465 | I4: =H4-$O$4 -> 0.10123599 | J4: =I4-$O$4 -> 0.092057325 | K4: =J4-$O$4 -> 0.082878662 | L4: =K4-$O$4 -> 0.0737 | M4: 0.0737 | N4: =M3-M4 -> 0.082607962 | O4: =N4/9 -> 0.0091786624 | P4: =M4 -> 0.0737
A6: Scenario 2: Average Growth
A7: INR Cr. | B7: LTM | C7: Y1E | D7: Y2E | E7: Y3E | F7: Y4W | G7: Y5E | H7: Y6E | I7: Y7E | J7: Y8E | K7: Y9E | L7: Y10E | N7: =Assumptions!B24 -> 0.20841546
A8: Sales | B8: =B3 -> 3284.73 | C8: =B8*(1+C9) -> 3969.3185 | D8: =C8*(1+D9) -> 4737.1716 | E8: =D8*(1+E9) -> 5582.6557 | F8: =E8*(1+F9) -> 6495.4775 | G8: =F8*(1+G9) -> 7460.3282 | H8: =G8*(1+H9) -> 8456.8306 | I8: =H8*(1+I9) -> 9459.8543 | J8: =I8*(1+J9) -> 10440.243 | ... L8: =K8*(1+L9) -> 12203.634 | N8: =M4 -> 0.0737 | O8: =N7-N8 -> 0.13471546 | P8: =O8/9 -> 0.014968384
A9: Sales Growth % | C9: =N7 -> 0.20841546 | D9: =C9-$P$8 -> 0.19344707 | E9: =D9-$P$8 -> 0.17847869 | F9: =E9-$P$8 -> 0.1635103 | G9: =F9-$P$8 -> 0.14854192 | H9: =G9-$P$8 -> 0.13357354 | I9: =H9-$P$8 -> 0.11860515 | J9: =I9-$P$8 -> 0.10363677 | K9: =J9-$P$8 -> 0.088668384 | L9: =K9-$P$8 -> 0.0737
A11: Scenario 3: EBIT Growth
A12: INR Cr. | B12: LTM | C12: Y1E | D12: Y2E | E12: Y3E | F12: Y4W | G12: Y5E | H12: Y6E | I12: Y7E | J12: Y8E | K12: Y9E | L12: Y10E | N12: =FCFF!C12*Assumptions!F45 -> 0.0017206721
A13: Sales | B13: =B8 -> 3284.73 | C13: =B13*(1+C14) -> 3290.3819 | D13: =C13*(1+D14) -> 3322.3591 | E13: =D13*(1+E14) -> 3381.2183 | F13: =E13*(1+F14) -> 3468.1622 | G13: =F13*(1+G14) -> 3585.0791 | H13: =G13*(1+H14) -> 3734.6098 | I13: =H13*(1+I14) -> 3920.2457 | J13: =I13*(1+J14) -> 4146.4619 | ... L13: =K13*(1+L14) -> 4744.5664 | N13: =N8 -> 0.0737 | O13: =N12-N13 -> -0.071979328 | P13: =O13/9 -> -0.0079977031
A14: Sales Growth % | C14: =N12 -> 0.0017206721 | D14: =C14-($P$13) -> 0.0097183752 | E14: =D14-($P$13) -> 0.017716078 | F14: =E14-($P$13) -> 0.025713781 | G14: =F14-($P$13) -> 0.033711485 | H14: =G14-($P$13) -> 0.041709188 | I14: =H14-($P$13) -> 0.049706891 | J14: =I14-($P$13) -> 0.057704594 | K14: =J14-($P$13) -> 0.065702297 | L14: =K14-($P$13) -> 0.0737
A16: Live Scenario | B16: 3
A17: INR Cr. | B17: LTM | C17: Y1E | D17: Y2E | E17: Y3E | F17: Y4W | G17: Y5E | H17: Y6E | I17: Y7E | J17: Y8E | K17: Y9E | L17: Y10E
A18: Sales | B18: =B13 -> 3284.73 | C18: =B18*(1+C19) -> 3290.3819 | D18: =C18*(1+D19) -> 3322.3591 | E18: =D18*(1+E19) -> 3381.2183 | F18: =E18*(1+F19) -> 3468.1622 | G18: =F18*(1+G19) -> 3585.0791 | H18: =G18*(1+H19) -> 3734.6098 | I18: =H18*(1+I19) -> 3920.2457 | J18: =I18*(1+J19) -> 4146.4619 | ... L18: =K18*(1+L19) -> 4744.5664
A19: Sales Growth % | C19: =CHOOSE($B$16,C4,C9,C14) -> 0.0017206721 | D19: =CHOOSE($B$16,D4,D9,D14) -> 0.0097183752 | E19: =CHOOSE($B$16,E4,E9,E14) -> 0.017716078 | F19: =CHOOSE($B$16,F4,F9,F14) -> 0.025713781 | G19: =CHOOSE($B$16,G4,G9,G14) -> 0.033711485 | H19: =CHOOSE($B$16,H4,H9,H14) -> 0.041709188 | I19: =CHOOSE($B$16,I4,I9,I14) -> 0.049706891 | J19: =CHOOSE($B$16,J4,J9,J14) -> 0.057704594 | ... L19: =CHOOSE($B$16,L4,L9,L14) -> 0.0737

Sheet DCF Valuation
C1: 1 | D1: 2 | E1: 3 | F1: 4 | G1: 5 | H1: 6 | I1: 7 | J1: 8 | K1: 9 | L1: 10
A2: INR Cr | B2: LTM | C2: Y1E | D2: Y2E | E2: Y3E | F2: Y4E | G2: Y5E | H2: Y6E | I2: Y7E | J2: Y8E | K2: Y9E | L2: Y10E | N2: Terminal Year | P2: Terminal growth rate % | Q2: 0.04
A3: Sales | B3: ='Growth scenario'!B18 -> 3284.73 | C3: ='Growth scenario'!C18 -> 3290.3819 | D3: ='Growth scenario'!D18 -> 3322.3591 | E3: ='Growth scenario'!E18 -> 3381.2183 | F3: ='Growth scenario'!F18 -> 3468.1622 | G3: ='Growth scenario'!G18 -> 3585.0791 | H3: ='Growth scenario'!H18 -> 3734.6098 | I3: ='Growth scenario'!I18 -> 3920.2457 | ... L3: ='Growth scenario'!L18 -> 4744.5664 | N3: =L3*(1+$Q$2) -> 4934.3491 | P3: Cost of Capital % | Q3: =Wacc!D26 -> 0.14977478
A4: Sales Growth | C4: ='Growth scenario'!C19 -> 0.0017206721 | D4: ='Growth scenario'!D19 -> 0.0097183752 | E4: ='Growth scenario'!E19 -> 0.017716078 | F4: ='Growth scenario'!F19 -> 0.025713781 | G4: ='Growth scenario'!G19 -> 0.033711485 | H4: ='Growth scenario'!H19 -> 0.041709188 | I4: ='Growth scenario'!I19 -> 0.049706891 | J4: ='Growth scenario'!J19 -> 0.057704594 | ... L4: ='Growth scenario'!L19 -> 0.0737 | N4: =$Q$2 -> 0.04 | P4: Terminal reinvestment rate % | Q4: =$Q$2/$Q$3 -> 0.26706765
A5: EBIT | C5: =C3*C6 -> 902.76582 | D5: =D3*D6 -> 911.53924 | E5: =E3*E6 -> 927.68814 | F5: =F3*F6 -> 951.54251 | G5: =G3*G6 -> 983.62042 | H5: =H3*H6 -> 1024.6464 | I5: =I3*I6 -> 1075.5784 | J5: =J3*J6 -> 1137.6442 | ... L5: =L3*L6 -> 1301.7432 | N5: =N6*N3 -> 1353.8129
A6: EBIT Margin % | C6: =AVERAGE(Assumptions!B29:F29) -> 0.27436505 | D6: =C6 -> 0.27436505 | E6: =D6 -> 0.27436505 | F6: =E6 -> 0.27436505 | G6: =F6 -> 0.27436505 | H6: =G6 -> 0.27436505 | I6: =H6 -> 0.27436505 | J6: =I6 -> 0.27436505 | K6: =J6 -> 0.27436505 | L6: =K6 -> 0.27436505 | N6: =L6 -> 0.27436505 | P6: Enterprise value = Equity Value + Minority interest
A7: Less: Tax on EBIT | C7: =Assumptions!$B$35*'DCF Valuation'!C5 -> 270.82975 | D7: =Assumptions!$B$35*'DCF Valuation'!D5 -> 273.46177 | E7: =Assumptions!$B$35*'DCF Valuation'!E5 -> 278.30644 | F7: =Assumptions!$B$35*'DCF Valuation'!F5 -> 285.46275 | G7: =Assumptions!$B$35*'DCF Valuation'!G5 -> 295.08613 | H7: =Assumptions!$B$35*'DCF Valuation'!H5 -> 307.39393 | I7: =Assumptions!$B$35*'DCF Valuation'!I5 -> 322.67352 | J7: =Assumptions!$B$35*'DCF Valuation'!J5 -> 341.29327 | ... L7: =Assumptions!$B$35*'DCF Valuation'!L5 -> 390.52296 | N7: =Assumptions!$B$35*N5 -> 406.14388
A8: EBIT(1-T) | C8: =C5-C7 -> 631.93607 | D8: =D5-D7 -> 638.07747 | E8: =E5-E7 -> 649.3817 | F8: =F5-F7 -> 666.07975 | G8: =G5-G7 -> 688.53429 | H8: =H5-H7 -> 717.2525 | I8: =I5-I7 -> 752.90489 | J8: =J5-J7 -> 796.35096 | ... L8: =L5-L7 -> 911.22025 | N8: =N5-N7 -> 947.66906
A9: Less: Net Capital Expenditure | C9: =C3*'Fixed Asset scheduled'!$C$11 -> 87.827966 | D9: =D3*'Fixed Asset scheduled'!$C$11 -> 88.681511 | E9: =E3*'Fixed Asset scheduled'!$C$11 -> 90.252599 | F9: =F3*'Fixed Asset scheduled'!$C$11 -> 92.573335 | G9: =G3*'Fixed Asset scheduled'!$C$11 -> 95.69412 | H9: =H3*'Fixed Asset scheduled'!$C$11 -> 99.685444 | I9: =I3*'Fixed Asset scheduled'!$C$11 -> 104.6405 | J9: =J3*'Fixed Asset scheduled'!$C$11 -> 110.67873 | ... L9: =L3*'Fixed Asset scheduled'!$C$11 -> 126.64354
A10: Non Cash Working Capital | B10: ='Change in working capital'!E5 -> -62.2 | C10: ='Change in working capital'!$C$9*'DCF Valuation'!C3 -> -97.882615 | D10: ='Change in working capital'!$C$9*'DCF Valuation'!D3 -> -98.833875 | E10: ='Change in working capital'!$C$9*'DCF Valuation'!E3 -> -100.58482 | F10: ='Change in working capital'!$C$9*'DCF Valuation'!F3 -> -103.17124 | G10: ='Change in working capital'!$C$9*'DCF Valuation'!G3 -> -106.64929 | H10: ='Change in working capital'!$C$9*'DCF Valuation'!H3 -> -111.09755 | I10: ='Change in working capital'!$C$9*'DCF Valuation'!I3 -> -116.61986 | J10: ='Change in working capital'!$C$9*'DCF Valuation'!J3 -> -123.34937 | ... L10: ='Change in working capital'!$C$9*'DCF Valuation'!L3 -> -141.14184
A11: Less: Change in Working Capital | C11: =C10-B10 -> -35.682615 | D11: =D10-C10 -> -0.95125998 | E11: =E10-D10 -> -1.7509487 | F11: =F10-E10 -> -2.5864162 | G11: =G10-F10 -> -3.4780556 | H11: =H10-G10 -> -4.4482555 | I11: =I10-H10 -> -5.5223138 | J11: =J10-I10 -> -6.7295019 | ... L11: =L10-K10 -> -9.6881379
A12: Reinvestment | C12: =C9+C11 -> 52.145351 | D12: =D9+D11 -> 87.730251 | E12: =E9+E11 -> 88.501651 | F12: =F9+F11 -> 89.986919 | G12: =G9+G11 -> 92.216064 | H12: =H9+H11 -> 95.237188 | I12: =I9+I11 -> 99.118183 | J12: =J9+J11 -> 103.94923 | ... L12: =L9+L11 -> 116.9554 | N12: =N8*N14 -> 253.09175
A13: Free Cash Flow To Firm (FCFF) | C13: =C8-C12 -> 579.79072 | D13: =D8-(D12) -> 550.34721 | E13: =E8-(E12) -> 560.88004 | F13: =F8-(F12) -> 576.09284 | G13: =G8-(G12) -> 596.31823 | H13: =H8-(H12) -> 622.01531 | I13: =I8-(I12) -> 653.78671 | J13: =J8-(J12) -> 692.40173 | K13: =K8-(K12) -> 738.8268 | L13: =L8-(L12) -> 794.26485 | N13: =N8-N12 -> 694.57731
A14: Implied Reinvestment rate % | C14: =C12/C8 -> 0.082516814 | D14: =D12/D8 -> 0.13749154 | E14: =E12/E8 -> 0.13628603 | F14: =F12/F8 -> 0.13509932 | G14: =G12/G8 -> 0.13393097 | H14: =H12/H8 -> 0.13278056 | I14: =I12/I8 -> 0.13164768 | J14: =J12/J8 -> 0.13053194 | ... L14: =L12/L8 -> 0.12835031 | N14: =$Q$4 -> 0.26706765
A16: Terminal Value | L16: =N13/(Q3-Q2) -> 6327.2938
A18: Present Value Interest Factor(PVIF) | C18: =1/(1+$Q$3)^C1 -> 0.86973555 | D18: =1/(1+$Q$3)^D1 -> 0.75643992 | E18: =1/(1+$Q$3)^E1 -> 0.65790269 | F18: =1/(1+$Q$3)^F1 -> 0.57220136 | G18: =1/(1+$Q$3)^G1 -> 0.49766386 | H18: =1/(1+$Q$3)^H1 -> 0.43283595 | I18: =1/(1+$Q$3)^I1 -> 0.37645281 | J18: =1/(1+$Q$3)^J1 -> 0.32741439 | ... L18: =1/(1+$Q$3)^L1 -> 0.24766932
A20: Present value of FCFF | C20: =SUMPRODUCT(C18:L18,C13:L13) -> 3065.1398
A21: Present value of Terminal value | C21: =L16*L18 -> 1567.0765
H22: Calculation of Sensitivity Analysis
A23: Value of operating assets | C23: =C20+C21 -> 4632.2163 | H23: Terminal Growth ↓ / WACC →
A24: Add: Cash | C24: ='consolidated balance sheet'!E40 -> 267.13 | H24: =C30 -> 46.078986 | I24: =J24-1% -> 0.12977478 | J24: =K24-1% -> 0.13977478 | K24: =$Q$3 -> 0.14977478 | L24: =K24+1% -> 0.15977478 | M24: =L24+1% -> 0.16977478
A25: Less: Debt | C25: ='consolidated balance sheet'!E14+'consolidated balance sheet'!E20 -> 1.27 | H25: =H26-1% -> 0.02
A26: Less: Minority Interest | C26: ='consolidated balance sheet'!E12 -> 1913.31 | H26: =H27-1% -> 0.03
A27: Equity Value | C27: =C23+C24-C25-C26 -> 2984.7663 | H27: =$Q$2 -> 0.04
H28: =H27+1% -> 0.05
A29: No. of Shares outstanding (Cr) | C29: ='Relative valuation'!C5 -> 64.775 | H29: =H28+1% -> 0.06
A30: intrinsic value per share | C30: =C27/C29 -> 46.078986

Sheet Gordon Growth Model
A1: Gordon Growth Model (Dividend Discount Model) — Info Edge India
A2: Intrinsic Value = D1 / (Ke - g) where D1 = next year dividend, Ke = cost of equity, g = sustainable growth rate
A4: STEP 1: Historical Dividend Per Share
A5: Year | B5: FY22 | C5: FY23 | D5: FY24 | E5: FY25
A6: Total Equity Dividend Paid (Rs Cr) | B6: ='consolidated P&l '!B34 -> 205.78 | C6: ='consolidated P&l '!C34 -> 193.16 | D6: ='consolidated P&l '!D34 -> 245.21 | E6: ='consolidated P&l '!E34 -> 310.21
A7: Shares Outstanding (Cr) | B7: ='consolidated balance sheet'!B6/2 -> 64.355 | C7: ='consolidated balance sheet'!C6/2 -> 64.505 | D7: ='consolidated balance sheet'!D6/2 -> 64.565 | E7: ='consolidated balance sheet'!E6/2 -> 64.715
A8: Dividend Per Share - DPS (Rs) | B8: =B6/B7 -> 3.1975759 | C8: =C6/C7 -> 2.9944966 | D8: =D6/D7 -> 3.7978781 | E8: =E6/E7 -> 4.7934791
A10: STEP 2: Dividend Growth Rate (g)
A11: YoY DPS Growth | C11: =(C8-B8)/B8 -> -0.063510421 | D11: =(D8-C8)/C8 -> 0.26828602 | E11: =(E8-D8)/D8 -> 0.26214664
A12: Average Historical DPS Growth | B12: =AVERAGE(C11:E11) -> 0.15564075 | C12: (FY23 to FY25 average)
A13: CAGR of DPS (FY22 to FY25) | B13: =(E8/B8)^(1/3)-1 -> 0.1444847 | C13: (3 year CAGR)
A14: Revenue CAGR (from Assumptions sheet) | B14: =Assumptions!B25 -> 0.15630796 | C14: (used as proxy for sustainable growth)
A16: Dividend Growth Rate Used (g) | B16: =B13 -> 0.1444847 | C16: DPS CAGR FY22-FY25 (conservative, based on actual dividend history)
A18: STEP 3: Cost of Equity (Ke) — from CAPM
A19: Risk Free Rate (Rf) | B19: =Wacc!B10 -> 0.0707 | C19: RBI 10Y Gsec yield
A20: Beta (β) | B20: =Wacc!B11 -> 1.1473589 | C20: Regression beta from Nifty50 vs Info Edge
A21: Market Risk Premium (Rm - Rf) | B21: =Wacc!B12 -> 0.0685 | C21: India ERP (Damodaran)
A22: Cost of Equity Ke = Rf + β × (Rm - Rf) | B22: =Wacc!B13 -> 0.14929409
A24: STEP 4: Validity Check — Ke must be > g
A25: Cost of Equity (Ke) | B25: =B22 -> 0.14929409
A26: Growth Rate (g) | B26: =B16 -> 0.1444847
A27: Ke - g (spread) | B27: =B25-B26 -> 0.0048093895 | C27: =IF(B27>0,"Valid — model can proceed","INVALID — g cannot exceed Ke") -> Valid — model can proceed
A29: STEP 5: D1 — Expected Dividend Next Year
A30: D0 — Latest DPS (FY25) | B30: =E8 -> 4.7934791 | C30: FY25 actual dividend per share
A31: D1 = D0 × (1 + g) | B31: =B30*(1+B16) -> 5.4860635 | C31: Expected dividend in next year (D1)
A33: STEP 6: Intrinsic Value per Share
A34: Gordon Growth Model Formula: P = D1 / (Ke - g)
A35: Intrinsic Value (P) | B35: =B31/(B25-B26) -> 1140.6985
A36: Current Market Price (CMP) | B36: ='Relative valuation'!B5 -> 988 | C36: Info Edge CMP from Relative Valuation sheet
A37: Premium / (Discount) to Intrinsic Value | B37: =(B36-B35)/B35 -> -0.13386404 | C37: =IF(B36>B35,"Stock is OVERVALUED vs GGM","Stock is UNDERVALUED vs GGM") -> Stock is UNDERVALUED vs GGM
A39: STEP 7: Sensitivity Analysis — Intrinsic Value at different g and Ke
A40: g ↓ / Ke → | B40: =B22-0.02 -> 0.12929409 | C40: =B22-0.01 -> 0.13929409 | D40: =B22 -> 0.14929409 | E40: =B22+0.01 -> 0.15929409 | F40: =B22+0.02 -> 0.16929409
A41: =B16-0.01 -> 0.1344847 | B41: =B31/(B22+-0.02-(B16+-0.01)) -> -1056.9207 | C41: =B31/(B22+-0.01-(B16+-0.01)) -> 1140.6985 | D41: =B31/(B22-(B16+-0.01)) -> 370.44494 | E41: =B31/(B22+0.01-(B16+-0.01)) -> 221.12852 | F41: =B31/(B22+0.02-(B16+-0.01)) -> 157.60298
A42: =B16 -> 0.1444847 | B42: =B31/(B22+-0.02-(B16)) -> -361.14832 | C42: =B31/(B22+-0.01-(B16)) -> -1056.9207 | D42: =B31/(B22-(B16)) -> 1140.6985 | E42: =B31/(B22+0.01-(B16)) -> 370.44494 | F42: =B31/(B22+0.02-(B16)) -> 221.12852
A43: =B16+0.01 -> 0.1544847 | B43: =B31/(B22+-0.02-(B16+0.01)) -> -217.78208 | C43: =B31/(B22+-0.01-(B16+0.01)) -> -361.14832 | D43: =B31/(B22-(B16+0.01)) -> -1056.9207 | E43: =B31/(B22+0.01-(B16+0.01)) -> 1140.6985 | F43: =B31/(B22+0.02-(B16+0.01)) -> 370.44494
A44: =B16+0.02 -> 0.1644847 | B44: =B31/(B22+-0.02-(B16+0.02)) -> -155.89566 | C44: =B31/(B22+-0.01-(B16+0.02)) -> -217.78208 | D44: =B31/(B22-(B16+0.02)) -> -361.14832 | E44: =B31/(B22+0.01-(B16+0.02)) -> -1056.9207 | F44: =B31/(B22+0.02-(B16+0.02)) -> 1140.6985
A45: =B16+0.03 -> 0.1744847 | B45: =B31/(B22+-0.02-(B16+0.03)) -> -121.3983 | C45: =B31/(B22+-0.01-(B16+0.03)) -> -155.89566 | D45: =B31/(B22-(B16+0.03)) -> -217.78208 | E45: =B31/(B22+0.01-(B16+0.03)) -> -361.14832 | F45: =B31/(B22+0.02-(B16+0.03)) -> -1056.9207
