Workbook

Sheet About the company 
A1: About the Company Larsen & Toubro Limited
A3: Who We Are — Larsen & Toubro Limited (L&T) is an Indian multinational conglomerate founded in 1938, with operations spanning Engineering, Procurement & Construction (EPC), Hi-Tech Manufacturing, IT & Technology Services, and Financial Services. Headquartered in Mumbai, L&T is listed on BSE (500510) and NSE (LT) with a CIN: L99999MH1946PLC004768. The Company operates across 50+ countries and held its 81st Annual General Meeting on June 5, 2026 through Video Conferencing. Business Model — L&T's diversified portfolio is organised into six broad segments: Infrastructure Projects, Energy Projects (Hydrocarbon Onshore, Offshore & Offshore Wind), Hi-Tech Manufacturing (Heavy Engineering, Precision Engineering, Rubber & Construction Equipment, Valves, Special Steels), IT & Technology Services (LTM/LTIMindtree, L&T Technology Services), Financial Services (L&T Finance – NBFC), and Development Projects (Hyderabad Metro, Nabha Power – both classified as Assets Held for Sale as of FY26). Digital & emerging businesses include Larsen & Toubro Vyoma (data centres), L&T Semiconductor Technologies, L&T EduTech, and L&T-SuFin (B2B e-commerce). FY26 Key Highlights (Consolidated) — Order Inflows: ₹4,35,590 Cr (+22.1% YoY, highest ever) | Order Book: ₹7,40,327 Cr (+27.8% YoY, all-time record) | Revenue from Operations: ₹2,85,874 Cr (+11.8% YoY) | PBDIT: ₹29,151 Cr (+10.3% YoY); EBITDA Margin: 10.2% | PAT (Consolidated): ₹16,084 Cr (+7.0% YoY) | Recurring PAT: ₹17,238 Cr (+18% YoY) | Basic EPS: ₹116.93 | Dividend: ₹38 per share | Net Debt:Equity: 0.35:1 | Gross Debt:Equity: 0.95:1 | RONW: 15.5% | Employees (Standalone): 59,403 | Group entities: 90 subsidiaries, 5 associates, 9 JVs, 35 jointly held operations. Strategic Plan — Lakshya 2026 concluded in March 2026. The next five-year strategic plan, Lakshya 2031 (FY27–FY31), is being formulated with a focus on EPC & Manufacturing profitability improvement, green energy transition (51% green portfolio share in FY26), technology & AI leadership, and shareholder value creation through asset divestments (Nabha Power sold to Torrent Power for ₹6,889 Cr enterprise value; Hyderabad Metro stake sale agreement signed). Vision & Mission — L&T aspires to be a builder of nations through engineering, technology and innovation, with trust, integrity and excellence at its core, partnering with customers and empowering employees to reach their fullest potential.
A18: Key Subsidiaries / Group Entities
A19: S.No | B19: Company Name | C19: Type | D19: FY26 Revenue / Status
A20: 1 | B20: LTM Limited (formerly LTIMindtree) | C20: Listed Subsidiary (NSE/BSE) | D20: Revenue ₹53,947 Cr; rebranded as AI-centric "Business Creativity Partner"
A21: 2 | B21: L&T Technology Services Limited (LTTS) | C21: Listed Subsidiary | D21: Revenue segment contribution in IT & Tech; LTTS formed strategic alliance with SiMa.ai for Physical AI solutions
A22: 3 | B22: L&T Finance Limited (LTF) | C22: Listed Subsidiary (NBFC) | D22: Revenue ₹17,283 Cr; acquired gold loan business of Paul Merchants Finance Pvt Ltd during FY26
A23: 4 | B23: Larsen & Toubro Vyoma Limited | C23: Wholly Owned Subsidiary | D23: Data centre capacity 26 MW (Chennai & Panvel); 36 MW AI-ready green data centre under development at Mahape, Navi Mumbai; sovereign cloud platform launched
A24: 5 | B24: L&T Semiconductor Technologies Ltd (LTSCT) | C24: Wholly Owned Subsidiary | D24: Acquired power module design assets from Fujitsu General Electronics, Japan; partnership with Hon Young Semiconductor (Foxconn) for SiC semiconductors
A25: 6 | B25: SuFin Limited | C25: Wholly Owned Subsidiary | D25: B2B digital marketplace; L&T-SuFin business transferred from parent w.e.f. April 1, 2026
A26: 7 | B26: L&T Realty Properties Limited | C26: Wholly Owned Subsidiary | D26: Realty business being transferred via Scheme of Arrangement (slump sale); 71 mn sq.ft. development portfolio
A27: 8 | B27: L&T Energy GreenTech Limited | C27: Wholly Owned Subsidiary | D27: JDA with ITOCHU Corporation (Japan) to develop 300 KTPA green ammonia facility at Kandla, Gujarat
A28: 9 | B28: L&T Metro Rail (Hyderabad) Limited | C28: Subsidiary (Asset Held for Sale) | D28: Share Purchase Agreement signed with Hyderabad Metro Rail Ltd (Govt. of Telangana) for full stake divestment; transaction expected by June 30, 2026
A29: 10 | B29: Nabha Power Limited | C29: Subsidiary (Asset Held for Sale) | D29: Securities purchase agreement signed to sell 100% equity to Torrent Power Limited for enterprise value of ₹6,889 Cr
A30: Total Group Entities (as on March 31, 2026) | C30: 90 Subsidiaries, 5 Associates, 9 JVs, 35 Jointly Held Operations
A32: Registered Office
A33: L&T House, Ballard Estate, Narottam Morarjee Marg, Mumbai – 400 001, India
A34: CIN: L99999MH1946PLC004768
A35: Website: www.larsentoubro.com | Email: igrc@larsentoubro.com
A37: Operational Footprint
A38: Entity | B38: Metric | C38: Value | D38: Details
A39: L&T Group | B39: Order Book | C39: ₹7,40,327 Cr | D39: All-time record as at March 31, 2026; +27.8% YoY; Infrastructure 57%, Energy 35%, Others 8%
A40: L&T Group | B40: Order Inflows (FY26) | C40: ₹4,35,590 Cr | D40: Highest ever; +22.1% YoY; International 58%, Domestic 42%
A41: L&T Group | B41: Revenue from Operations | C41: ₹2,85,874 Cr | D41: +11.8% YoY; International revenue 54% of total in FY26
A42: L&T Group | B42: EBITDA Margin | C42: 10.2% | D42: PBDIT: ₹29,151 Cr (+10.3% YoY)
A43: L&T Group | B43: Consolidated PAT | C43: ₹16,084 Cr | D43: +7.0% YoY; Recurring PAT ₹17,238 Cr (+18% YoY)
A44: L&T Group | B44: Net Debt : Equity | C44: 0.35 : 1 | D44: Improved from 0.60:1 in FY25; Gross Debt:Equity at 0.95:1
A45: L&T Group | B45: Employees (Standalone) | C45: 59,403 | D45: As of March 31, 2026
A46: L&T Group | B46: Countries of Operation | C46: 50+ | D46: Global footprint across Americas, Europe, Middle East, Africa, Asia-Pacific
A47: L&T Group | B47: Green Portfolio Share | C47: 51% | D47: Green business ₹787 bn as % of standalone revenues in FY26
A48: L&T Group | B48: Dividend (FY26) | C48: ₹38 per share | D48: Face value ₹2 per share; paid on or before June 10, 2026
A49: L&T Group | B49: Stock Exchanges | C49: BSE & NSE | D49: BSE Code: 500510 | NSE Symbol: LT
A50: L&T Group | B50: Statutory Auditors | C50: M/s. M S K A & Associates LLP | D50: Registrar & Transfer Agent: KFin Technologies Limited
A53: Board of Directors
A54: Name | C54: Designation
A55: Mr. S. N. Subrahmanyan | C55: Chairman & Managing Director
A56: Mr. Subramanian Sarma | C56: Deputy Managing Director & President
A57: Mr. R. Shankar Raman | C57: President, Whole-time Director & CFO
A58: Mr. S. V. Desai | C58: Whole-time Director & Sr. EVP – Civil Infrastructure
A59: Mr. T. Madhava Das | C59: Whole-time Director & Sr. EVP – Utilities
A60: Mr. Anil V. Parab | C60: Whole-time Director & Sr. EVP – Heavy Engineering & Manufacturing
A61: Mr. Sanjeev Aga | C61: Independent Director
A62: Mr. Narayanan Kumar | C62: Independent Director
A63: Mrs. Preetha Reddy | C63: Independent Director
A64: Mr. Pramit Jhaveri | C64: Independent Director
A65: Mr. Rajnish Kumar | C65: Independent Director
... A72: Mr. Subramanian Narayan | C72: Company Secretary & Compliance Officer (ACS 16354)

Sheet Promoter
A1: LARSEN & TOUBRO LIMITED (L&T)
A2: Shareholding Pattern – Promoter & Promoter Group | As at March 31, 2026
A3: KEY NOTE — PROFESSIONALLY MANAGED COMPANY | PROMOTER SHAREHOLDING: NIL Larsen & Toubro Limited has NO identifiable Promoter or Promoter Group. The Company's Promoter shareholding stands at NIL as at March 31, 2026 (Previous Year: NIL). L&T is a professionally managed public limited company incorporated in 1938, with a broad-based institutional and public ownership structure. This is formally confirmed in the Company's Standalone and Consolidated Financial Statements (Note to Share Capital) for FY 2025-26.
A6: (A) PROMOTER & PROMOTER GROUP SHAREHOLDING
A7: Sr. No. | B7: Name of Shareholder / Category | C7: Category | D7: No. of Shareholders | E7: No. of Shares Held | F7: % of Total Share Capital
A8: (A1) Indian Promoters
A9: - | B9: Nil — No Indian Promoter identified | D9: - | E9: - | F9: -
A10: Sub-Total (A1) – Indian Promoters | D10: - | E10: - | F10: -
A11: (A2) Foreign Promoters
A12: - | B12: Nil — No Foreign Promoter identified | D12: - | E12: - | F12: -
A13: TOTAL PROMOTER & PROMOTER GROUP SHAREHOLDING (A) | D13: NIL | E13: NIL | F13: NIL
A15: CONTEXT: Significant Shareholders (Holding >= 1% as at March 31, 2026)
A16: Sr. No. | B16: Name of Shareholder | C16: Category | D16: No. of Shares Held | E16: % of Total Capital | F16: Change vs FY25
A17: 1 | B17: L&T Employees Trust | C17: Non-Institution / Trust | D17: 19,86,79,507 | E17: 14.44% | F17: +0.27 pp
A18: 2 | B18: Life Insurance Corporation of India (LIC) | C18: Financial Institution (Domestic) | D18: 17,03,27,420 | E18: 12.38% | F18: -0.72 pp
A19: 3 | B19: SBI Mutual Fund | C19: Mutual Fund (Domestic) | D19: 6,17,78,496 | E19: 4.49% | F19: N/A
A20: 4 | B20: ICICI Prudential Mutual Fund | C20: Mutual Fund (Domestic) | D20: 5,32,51,701 | E20: 3.87% | F20: N/A
A21: 5 | B21: NPS Trust A/C – SBI Pension Fund (UPS-CG) | C21: Provident / Pension Fund | D21: 4,48,28,833 | E21: 3.26% | F21: N/A
A22: 6 | B22: HDFC Mutual Fund | C22: Mutual Fund (Domestic) | D22: 2,79,55,760 | E22: 2.03% | F22: N/A
A23: 7 | B23: Government of Singapore | C23: FPI – Category I (Foreign) | D23: 2,15,92,388 | E23: 1.57% | F23: N/A
A24: 8 | B24: Nippon Life India Trustee Ltd | C24: Mutual Fund (Domestic) | D24: 2,27,69,781 | E24: 1.66% | F24: N/A
A25: 9 | B25: UTI Mutual Fund | C25: Mutual Fund (Domestic) | D25: 2,11,47,408 | E25: 1.54% | F25: N/A
A26: CATEGORY-WISE SHAREHOLDING SUMMARY (FY26 vs FY25)
A27: Category | B27: No. of Shares (FY26) | C27: % (FY26) | D27: No. of Shares (FY25) | E27: % (FY25) | F27: Change (pp)
A28: Promoter & Promoter Group | B28: NIL | C28: NIL | D28: NIL | E28: NIL | F28: -
A29: Financial Institutions (Domestic) | B29: 19,88,97,611 | C29: 14.46% | D29: 21,24,90,650 | E29: 15.45% | F29: -0.99
A30: Foreign Portfolio Investors (FPI) | B30: 25,56,55,493 | C30: 18.58% | D30: 26,91,74,120 | E30: 19.57% | F30: -0.99
A31: Shares underlying GDRs | B31: 1,44,89,280 | C31: 1.05% | D31: 1,56,44,404 | E31: 1.14% | F31: -0.09
A32: Mutual Funds (Domestic) | B32: 27,90,56,228 | C32: 20.29% | D32: 27,11,21,158 | E32: 19.72% | F32: +0.57
A33: Bodies Corporate & QIBs | B33: 7,06,67,920 | C33: 5.14% | D33: 9,85,23,938 | E33: 7.16% | F33: -2.02
A34: Directors & Relatives | B34: 11,34,111 | C34: 0.08% | D34: 10,89,114 | E34: 0.08% | F34: Flat
A35: L&T Employees Trust | B35: 19,86,79,507 | C35: 14.44% | D35: 19,48,87,516 | E35: 14.17% | F35: +0.27
A36: Others (Retail, NRI, HUF, etc.) | B36: 35,70,52,040 | C36: 25.96% | D36: 31,22,61,265 | E36: 22.71% | F36: +3.25
A37: TOTAL (A+B) | B37: 1,37,56,32,190 | C37: 100.00% | D37: 1,37,51,92,165 | E37: 100.00% | F37: -
A39: Notes
A40: 1. The Company's Promoter shareholding is NIL as at March 31, 2026 (Previous Year: NIL). L&T is a professionally managed company with no identifiable promoter group. Source: Note to Share Capital, L&T Integrated Annual Report FY 2025-26.
A41: 2. Significant shareholders (holding >5%) as disclosed in Note to Share Capital: (i) L&T Employees Trust – 19,86,79,507 shares (14.44%) and (ii) Life Insurance Corporation of India – 17,03,27,420 shares (12.38%).
A42: 3. Total paid-up equity share capital as at March 31, 2026: 1,37,56,32,190 shares of face value ₹2 each. During FY26, 4,40,025 shares were allotted upon exercise of employee stock options.
A43: 4. Demat status as at March 31, 2026: NSDL – 1,28,03,97,625 shares (93.07%); CDSL – 8,66,29,700 shares (6.30%); Physical – 86,04,865 shares (0.63%).
A44: 5. GDR shares (1,44,89,280 shares) are backed by underlying equity shares forming part of the existing paid-up capital.
A45: 6. Source: L&T Integrated Annual Report 2025-26 — Corporate Governance Report (Categories of Shareholders section) and Standalone Financial Statements (Note to Share Capital).

Sheet Public
A1: LARSEN & TOUBRO LIMITED (L&T)
A2: Shareholding Pattern – Public Shareholders | As at March 31, 2026
A4: Sr. No. | B4: Name of Shareholder / Category | C4: Category | D4: No. of Shareholders | E4: No. of Shares Held | F4: % of Total Share Capital
A5: DOMESTIC INSTITUTIONS
A6: 1 | B6: Mutual Funds | C6: Mutual Fund | D6: 60 | E6: 279,056,228 | F6: 20.50%
A7: 2 | B7: SBI Mutual Fund | C7: Mutual Fund | D7: 1 | E7: 61,778,496 | F7: 4.54%
A8: 3 | B8: UTI Mutual Fund | C8: Mutual Fund | D8: 1 | E8: 21,147,408 | F8: 1.55%
A9: 4 | B9: Nippon Life India Trustee Ltd | C9: Mutual Fund | D9: 1 | E9: 22,769,781 | F9: 1.67%
A10: 5 | B10: HDFC Mutual Fund | C10: Mutual Fund | D10: 1 | E10: 27,955,760 | F10: 2.05%
A11: 6 | B11: ICICI Prudential Mutual Fund | C11: Mutual Fund | D11: 1 | E11: 53,251,701 | F11: 3.91%
A12: 7 | B12: Alternate Investment Funds | C12: AIF | D12: 93 | E12: 9,646,399 | F12: 0.71%
A13: 8 | B13: Banks | C13: Banks | D13: 20 | E13: 981,714 | F13: 0.07%
A14: 9 | B14: Insurance Companies | C14: Insurance | D14: 41 | E14: 255,262,445 | F14: 18.75%
A15: 10 | B15: SBI Life Insurance Co. Ltd | C15: Insurance | D15: 1 | E15: 15,246,344 | F15: 1.12%
A16: 11 | B16: Life Insurance Corporation of India | C16: Insurance | D16: 1 | E16: 170,327,420 | F16: 12.51%
A17: 12 | B17: ICICI Prudential Life Insurance Co. Ltd | C17: Insurance | D17: 1 | E17: 14,561,355 | F17: 1.07%
... A21: 16 | B21: NBFCs Registered with RBI | C21: NBFC | D21: 25 | E21: 66,188 | F21: -
B22: Sub-Total (B1) – Domestic Institutions | D22: 240 | E22: 589,841,807 | F22: 43.33%
A23: FOREIGN INSTITUTIONS
A24: 17 | B24: Foreign Portfolio Investors – Category I | C24: FPI – Cat I | D24: 807 | E24: 243,914,010 | F24: 17.92%
A25: 18 | B25: Government of Singapore | C25: FPI – Cat I | D25: 1 | E25: 21,592,388 | F25: 1.59%
A26: 19 | B26: Foreign Portfolio Investors – Category II | C26: FPI – Cat II | D26: 83 | E26: 11,318,792 | F26: 0.83%
A27: 20 | B27: Any Other – Foreign Institutional Investors | C27: FII | D27: 50 | E27: 422,691 | F27: 0.03%
B28: Sub-Total (B2) – Foreign Institutions | D28: 940 | E28: 255,655,493 | F28: 18.78%
A29: GOVERNMENT HOLDING
A30: 21 | B30: Central Government / President of India | C30: Central Govt | D30: 2 | E30: 3,347,457 | F30: 0.25%
B31: Sub-Total (B3) – Government Holding | D31: 2 | E31: 3,347,457 | F31: 0.25%
A32: NON-INSTITUTIONS
A33: 22 | B33: Directors and their Relatives (excl. Independent & Nominee Directors) | C33: Directors / Relatives | D33: 12 | E33: 1,106,642 | F33: 0.08%
A34: 23 | B34: Investor Education and Protection Fund (IEPF) | C34: IEPF | D34: 1 | E34: 5,417,024 | F34: 0.40%
A35: 24 | B35: Resident Individuals – Nominal Share Capital up to ₹2 Lakhs | C35: Retail Individual | D35: 1,705,682 | E35: 257,491,210 | F35: 18.92%
A36: 25 | B36: Resident Individuals – Nominal Share Capital in excess of ₹2 Lakhs | C36: HNI / Individual | D36: 37 | E36: 9,751,493 | F36: 0.72%
A37: 26 | B37: Non-Resident Indians (NRIs) | C37: NRI | D37: 57,165 | E37: 17,268,786 | F37: 1.27%
A38: 27 | B38: Foreign Nationals | C38: Foreign National | D38: 11 | E38: 568,878 | F38: 0.04%
A39: 28 | B39: Foreign Companies | C39: Foreign Company | D39: 4 | E39: 38,771 | F39: -
A40: 29 | B40: Bodies Corporate | C40: Corporate Body | D40: 7,874 | E40: 14,303,086 | F40: 1.05%
A41: 30 | B41: Any Other (specify) – Total | C41: Others | D41: 29,285 | E41: 206,352,263 | F41: 15.16%
A42: 31 | B42: Nationalised Banks | C42: Banks (Nationalised) | D42: 38 | E42: 1,521,868 | F42: 0.11%
A43: 32 | B43: Hindu Undivided Families (HUF) | C43: HUF | D43: 29,091 | E43: 5,461,783 | F43: 0.40%
A44: 33 | B44: Clearing Members | C44: Clearing Member | D44: 14 | E44: 20,805 | F44: -
... A47: 36 | B47: ESOP / ESOS / ESPS | C47: Employee Stock Options | D47: 0 | E47: 0 | F47: -
B48: Sub-Total (B4) – Non-Institutions | D48: 1,800,071 | E48: 512,298,153 | F48: 37.64%
B49: TOTAL PUBLIC SHAREHOLDING (B = B1 + B2 + B3 + B4) | D49: 1,801,253 | E49: 1,361,142,910 | F49: 100.00%

Sheet Consolidated P&L
A1: LARSEN & TOUBRO LIMITED — Consolidated Profit & Loss Account
A2: (₹ in Crores)
A3: Particulars | B3: Mar 22 12 mths | C3: Mar 23 12 mths | D3: Mar 24 12 mths | E3: Mar 25 12 mths | F3: Mar 26 12 mths
A4: INCOME
A5: Revenue From Operations [Gross] | B5: 155672.46 | C5: 181661.42 | D5: 221112.91 | E5: 254208.65 | F5: 284225.19
A6: Revenue From Operations [Net] | B6: 155672.46 | C6: 181661.42 | D6: 221112.91 | E6: 254208.65 | F6: 284225.19
A7: Other Operating Revenues | B7: 848.77 | C7: 1679.28 | D7: 0 | E7: 1525.8 | F7: 1649.17
A8: Total Operating Revenues | B8: 156521.23 | C8: 183340.7 | D8: 221112.91 | E8: 255734.45 | F8: 285874.36
A9: Other Income | B9: 2267.08 | C9: 2929.17 | D9: 4158.03 | E9: 4124.82 | F9: 5760.68
A10: Total Revenue | B10: 158788.31 | C10: 186269.87 | D10: 225270.94 | E10: 259859.27 | F10: 291635.04
A11: EXPENSES
A12: Cost Of Materials Consumed | B12: 17100.84 | C12: 18995.11 | D12: 19442.25 | E12: 27655.02 | F12: 33031.76
A13: Purchase Of Stock-In Trade | B13: 1069.5 | C13: 1052.86 | D13: 1063.77 | E13: 1402.14 | F13: 1262.3
A14: Operating And Direct Expenses | B14: 83644.77 | C14: 99723.94 | D14: 124501.73 | E14: 142326.53 | F14: 153510.27
A15: Changes In Inventories Of FG, WIP And Stock-In Trade | B15: -2076.6 | C15: -3156.64 | D15: 1021.07 | E15: -410.79 | F15: -1963.12
A16: Employee Benefit Expenses | B16: 29733.53 | C16: 37214.11 | D16: 41171.02 | E16: 46768.68 | F16: 52187.22
A17: Finance Costs | B17: 3125.7 | C17: 3207.16 | D17: 3545.85 | E17: 3334.37 | F17: 9844.16
A18: Depreciation And Amortisation Expenses | B18: 2947.95 | C18: 3502.25 | D18: 3682.33 | E18: 4121.18 | F18: 4364.75
A19: Other Expenses | B19: 8831.89 | C19: 8758.04 | D19: 10419.42 | E19: 11558.13 | F19: 11699.45
A20: Total Expenses | B20: 144377.58 | C20: 169296.83 | D20: 204847.44 | E20: 236755.26 | F20: 263936.79
A21: PROFIT / LOSS
A22: Profit/Loss Before Exceptional, ExtraOrdinary Items And Tax | B22: 14410.73 | C22: 16973.04 | D22: 20423.5 | E22: 23104.01 | F22: 27698.25
A23: Exceptional Items | B23: 96.93 | C23: 135.99 | D23: 93.61 | E23: 474.78 | F23: -1722.44
A24: Profit/Loss Before Tax | B24: 14507.66 | C24: 17109.03 | D24: 20517.11 | E24: 23578.79 | F24: 25975.81
A25: TAX EXPENSES — CONTINUED OPERATIONS
A26: Current Tax | B26: 4512.09 | C26: 5055.17 | D26: 5127.7 | E26: 6100.82 | F26: 6752.96
A27: Deferred Tax | B27: -295.48 | C27: -571.01 | D27: -180.31 | E27: -209.42 | F27: 63.45
A28: Total Tax Expenses | B28: 4216.61 | C28: 4484.16 | D28: 4947.39 | E28: 5891.4 | F28: 6816.41
A29: Profit/Loss After Tax And Before ExtraOrdinary Items | B29: 10291.05 | C29: 12624.87 | D29: 15569.72 | E29: 17687.39 | F29: 19159.4
A30: Profit/Loss From Continuing Operations | B30: 10291.05 | C30: 12624.87 | D30: 15569.72 | E30: 17687.39 | F30: 19159.4
A31: Profit/Loss For The Period | B31: 10291.05 | C31: 12624.87 | D31: 15569.72 | E31: 17687.39 | F31: 19159.4
A32: Minority Interest | B32: -1749.91 | C32: -2059.9 | D32: -2487.99 | E32: -2636.22 | F32: -2869.89
A33: Share Of Profit/Loss Of Associates | B33: 128.19 | C33: -94.25 | D33: -22.62 | E33: -14.06 | F33: -205.52
A34: Consolidated Profit/Loss After MI And Associates | B34: 8669.33 | C34: 10470.72 | D34: 13059.11 | E34: 15037.11 | F34: 16083.99
A35: EARNINGS PER SHARE
A36: Basic EPS (₹) | B36: 62 | C36: 75 | D36: 94 | E36: 109 | F36: 117
A37: Diluted EPS (₹) | B37: 62 | C37: 74 | D37: 94 | E37: 109 | F37: 117
A38: DIVIDEND
A39: Equity Share Dividend (₹ Cr.) | B39: 2528.46 | C39: 3091.42 | D39: 4216.95 | E39: 3849.57 | F39: 0

Sheet Consolidated Balance sheet
A1: LARSEN & TOUBRO LIMITED — Consolidated Balance Sheet
A2: (₹ in Crores)
A3: Particulars | B3: Mar 22 12 mths | C3: Mar 23 12 mths | D3: Mar 24 12 mths | E3: Mar 25 12 mths | F3: Mar 26 12 mths
A4: EQUITIES AND LIABILITIES | I4: SHARE OUTSTANDING
A5: SHAREHOLDER'S FUNDS | I5: EQUITY SHARE CAPITAL/FACE VALUE
A6: Equity Share Capital | B6: 281.01 | C6: 281.1 | D6: 274.93 | E6: 275.04 | F6: 275.13 | I6: =E6/2 -> 137.52
A7: Preference Share Capital | B7: 215.65 | C7: 0 | D7: 0 | E7: 0 | F7: 0 | I7: MKT CAPITALIZATION/CURRENT MKT PRICE
A8: Total Share Capital | B8: 496.66 | C8: 281.1 | D8: 274.93 | E8: 275.04 | F8: 275.13 | I8: =578632/4206 -> 137.57299
A9: Reserves and Surplus | B9: 81755 | C9: 88577.76 | D9: 85533.77 | E9: 97380.56 | F9: 109014.67 | I9: DPS
A10: Total Reserves and Surplus | B10: 81755 | C10: 88577.76 | D10: 85533.77 | E10: 97380.56 | F10: 109014.67 | I10: ='Consolidated P&L'!E39/'Consolidated Balance sheet'!I8 -> 27.982019
A11: Employees Stock Options | B11: 371.65 | C11: 467.09 | D11: 550.54 | E11: 0 | F11: 0
A12: Total Shareholders Funds | B12: 82623.31 | C12: 89325.95 | D12: 86359.24 | E12: 97655.6 | F12: 109289.8
A13: Minority Interest | B13: 12966.07 | C13: 14241.27 | D13: 16190.42 | E13: 17748.08 | F13: 19240.66
A14: NON-CURRENT LIABILITIES
A15: Long Term Borrowings | B15: 61402.66 | C15: 61217.68 | D15: 56506.97 | E15: 57503.34 | F15: 63738.59
A16: Deferred Tax Liabilities [Net] | B16: 1039.33 | C16: 630.43 | D16: 533.63 | E16: 410.01 | F16: 167.11
A17: Other Long Term Liabilities | B17: 1766.25 | C17: 2001 | D17: 2448.87 | E17: 3112.16 | F17: 4783.73
A18: Long Term Provisions | B18: 817.77 | C18: 869.99 | D18: 987.38 | E18: 1124.01 | F18: 832.48
A19: Total Non-Current Liabilities | B19: 65026.01 | C19: 64719.1 | D19: 60476.85 | E19: 62149.52 | F19: 69521.91
A20: CURRENT LIABILITIES
A21: Short Term Borrowings | B21: 61849.92 | C21: 57295.7 | D21: 57532.8 | E21: 72056 | F21: 57944.43
A22: Trade Payables | B22: 51144.24 | C22: 49784.12 | D22: 53292.88 | E22: 52459.34 | F22: 69455.63
A23: Other Current Liabilities | B23: 43083.51 | C23: 51492.7 | D23: 62317.54 | E23: 72763.89 | F23: 122088.42
A24: Short Term Provisions | B24: 3355.86 | C24: 3493.47 | D24: 3457.51 | E24: 4691.67 | F24: 5009.03
A25: Total Current Liabilities | B25: 159433.53 | C25: 162065.99 | D25: 176600.73 | E25: 201970.9 | F25: 254497.51
A26: Total Capital And Liabilities | B26: 320048.92 | C26: 330352.31 | D26: 339627.24 | E26: 379524.1 | F26: 452549.88
A27: ASSETS
A28: NON-CURRENT ASSETS
A29: Tangible Assets | B29: 16530.47 | C29: 16834.37 | D29: 17778.42 | E29: 18656.21 | F29: 20557.16
A30: Intangible Assets | B30: 18729.37 | C30: 18007.98 | D30: 17384.52 | E30: 17050.76 | F30: 1828.21
A31: Capital Work-In-Progress | B31: 1170.32 | C31: 2949.09 | D31: 2897.04 | E31: 2390.86 | F31: 3036.25
A32: Intangible Assets Under Development | B32: 79.23 | C32: 116.48 | D32: 147.97 | E32: 197.82 | F32: 274.7
A33: Fixed Assets | B33: 36509.39 | C33: 37907.92 | D33: 38207.95 | E33: 38295.65 | F33: 25696.32
A34: Non-Current Investments | B34: 9810.86 | C34: 9224.89 | D34: 10690.19 | E34: 11444.65 | F34: 8851.93
A35: Deferred Tax Assets [Net] | B35: 2840.1 | C35: 3984.79 | D35: 3863.72 | E35: 3792.88 | F35: 4252.76
A36: Long Term Loans And Advances | B36: 46989.83 | C36: 41276.92 | D36: 52630.22 | E36: 63196.31 | F36: 75582.53
A37: Other Non-Current Assets | B37: 8240.59 | C37: 7954.82 | D37: 8354.41 | E37: 9104.42 | F37: 11373.48
A38: Total Non-Current Assets | B38: 111867.75 | C38: 108147.99 | D38: 121547.37 | E38: 134182.39 | F38: 134238.56
A39: CURRENT ASSETS
A40: Current Investments | B40: 29792.51 | C40: 35573.42 | D40: 34957.63 | E40: 43360.62 | F40: 59524.86
A41: Inventories | B41: 5943.32 | C41: 6828.78 | D41: 6620.19 | E41: 7670.55 | F41: 9530.93
A42: Trade Receivables | B42: 46138.92 | C42: 44731.53 | D42: 48770.95 | E42: 53713.68 | F42: 60461.26
A43: Cash And Cash Equivalents | B43: 18953.17 | C43: 22519.6 | D43: 15358.39 | E43: 22965.34 | F43: 20847.67
A44: Short Term Loans And Advances | B44: 42549.54 | C44: 40711.7 | D44: 34921.13 | E44: 36494.36 | F44: 43459.94
A45: Other Current Assets | B45: 64803.71 | C45: 71839.29 | D45: 77451.58 | E45: 81137.16 | F45: 124486.66
A46: Total Current Assets | B46: 208181.17 | C46: 222204.32 | D46: 218079.87 | E46: 245341.71 | F46: 318311.32
A47: Total Assets | B47: 320048.92 | C47: 330352.31 | D47: 339627.24 | E47: 379524.1 | F47: 452549.88
A48: OTHER ADDITIONAL INFORMATION
A49: CONTINGENT LIABILITIES & COMMITMENTS
A50: Contingent Liabilities | B50: 23020.82 | C50: 19620.76 | D50: 21246.24 | E50: 28086.58 | F50: 33600.73
A51: BONUS DETAILS
A52: Bonus Equity Share Capital | B52: 244.94 | C52: 244.94 | D52: 244.94 | E52: 244.94 | F52: 244.94
A53: NON-CURRENT INVESTMENTS
A54: Non-Current Investments Unquoted Book Value | B54: 7081.51 | C54: 0 | D54: 0 | E54: 0 | F54: 0
A55: CURRENT INVESTMENTS
A56: Current Investments Unquoted Book Value | B56: 29792.51 | C56: 0 | D56: 0 | E56: 0 | F56: 0

Sheet Consolidated Cash flow 
A1: LARSEN & TOUBRO LIMITED — Consolidated Cash Flow Statement
A2: (₹ in Crores)
A3: Particulars | B3: Mar 22 12 mths | C3: Mar 23 12 mths | D3: Mar 24 12 mths | E3: Mar 25 12 mths | F3: Mar 26 12 mths
A4: CASH FLOW STATEMENT
A5: Net Profit Before Tax | B5: 14410.73 | C5: 16973.04 | D5: 20423.5 | E5: 23104.01 | F5: 27698.25
A6: Net Cash From Operating Activities | B6: 19163.58 | C6: 22776.96 | D6: 18266.28 | E6: 9160.71 | F6: 16740.97
A7: Net Cash (used in)/from Investing Activities | B7: -3667.68 | C7: -8311.7 | D7: 2163.04 | E7: -15517.51 | F7: -11738.84
A8: Net Cash (used in)/from Financing Activities | B8: -15181.48 | C8: -11572.49 | D8: -25413.36 | E8: 6556.62 | F8: -2156.43
A9: Net (decrease)/increase In Cash and Cash Equivalents | B9: 396.72 | C9: 3156.45 | D9: -4968.19 | E9: 228.5 | F9: 3204.24
A10: Opening Cash & Cash Equivalents | B10: 13373.52 | C10: 13770.24 | D10: 16926.69 | E10: 11958.5 | F10: 12187
A11: Closing Cash & Cash Equivalents | B11: 13770.24 | C11: 16926.69 | D11: 11958.5 | E11: 12187 | F11: 15391.24

Sheet Consolidated Quarterly Result
A1: Consolidated Quarterly Results (Rs. Crores) | K1: Date Begin | L1: 46023 | N1: Date Begin | O1: 45931 | Q1: Date Begin | R1: 45839 | U1: Date Begin | V1: 45748 | X1: Date Begin | Y1: 45383
B2: Quarter ended | E2: Years | G2: % CHANGE | K2: Date End | L2: 46112 | N2: Date End | O2: 46022 | Q2: Date End | R2: 45930 | U2: Date End | V2: 46112 | X2: Date End | Y2: 45747
A3: Particulars | B3: 46082 | C3: 45992 | D3: 45901 | E3: 46082 | F3: 45717 | G3: QTQ | H3: YOY | K3: Description | L3: Amount (Rs. million) | N3: Description | O3: Amount (Rs. million) | Q3: Description | R3: Amount (Rs. million) | U3: Description | V3: Amount (Rs. million) | X3: Description | Y3: Amount (Rs. million)
A4: =K4 -> Net Sales | B4: =L4 -> 827621.6 | C4: =O4 -> 714497 | D4: =R4 -> 679835.3 | E4: =V4 -> 2858743.6 | F4: =Y4 -> 2557344.5 | G4: =IF(AND(ISNUMBER(B4),ISNUMBER(C4),C4<>0),(B4-C4)/ABS(C4),"-") -> 0.15832761 | H4: =IF(AND(ISNUMBER(B4),ISNUMBER(F4),F4<>0),(B4-F4)/ABS(F4),"-") -> -0.67637461 | K4: Net Sales | L4: 827621.6 | N4: Net Sales | O4: 714497 | Q4: Net Sales | R4: 679835.3 | U4: Net Sales | V4: 2858743.6 | X4: Net Sales | Y4: 2557344.5
A5: =K5 -> Other Income | B5: =L5 -> 15785.9 | C5: =O5 -> 14410.4 | D5: =R5 -> 13842.8 | E5: =V5 -> 57606.8 | F5: =Y5 -> 41248.2 | G5: =IF(AND(ISNUMBER(B5),ISNUMBER(C5),C5<>0),(B5-C5)/ABS(C5),"-") -> 0.095451896 | H5: =IF(AND(ISNUMBER(B5),ISNUMBER(F5),F5<>0),(B5-F5)/ABS(F5),"-") -> -0.61729482 | K5: Other Income | L5: 15785.9 | N5: Other Income | O5: 14410.4 | Q5: Other Income | R5: 13842.8 | U5: Other Income | V5: 57606.8 | X5: Other Income | Y5: 41248.2
A6: =K6 -> Total Income | B6: =L6 -> 843407.5 | C6: =O6 -> 728907.4 | D6: =R6 -> 693678.1 | E6: =V6 -> 2916350.4 | F6: =Y6 -> 2598592.7 | G6: =IF(AND(ISNUMBER(B6),ISNUMBER(C6),C6<>0),(B6-C6)/ABS(C6),"-") -> 0.15708456 | H6: =IF(AND(ISNUMBER(B6),ISNUMBER(F6),F6<>0),(B6-F6)/ABS(F6),"-") -> -0.67543682 | K6: Total Income | L6: 843407.5 | N6: Total Income | O6: 728907.4 | Q6: Total Income | R6: 693678.1 | U6: Total Income | V6: 2916350.4 | X6: Total Income | Y6: 2598592.7
A7: =K7 -> Expenditure | B7: =L7 -> -759991.2 | C7: =O7 -> -657297.6 | D7: =R7 -> -630317 | E7: =V7 -> -2639367.9 | F7: =Y7 -> -2367552.6 | G7: =IF(AND(ISNUMBER(B7),ISNUMBER(C7),C7<>0),(B7-C7)/ABS(C7),"-") -> -0.15623608 | H7: =IF(AND(ISNUMBER(B7),ISNUMBER(F7),F7<>0),(B7-F7)/ABS(F7),"-") -> 0.67899712 | K7: Expenditure | L7: -759991.2 | N7: Expenditure | O7: -657297.6 | Q7: Expenditure | R7: -630317 | U7: Expenditure | V7: -2639367.9 | X7: Expenditure | Y7: -2367552.6
A8: =K8 -> Cost of Materials Consumed | B8: =L8 -> -299388.4 | C8: =O8 -> 53698.9 | D8: =R8 -> -245925.7 | E8: =V8 -> 259758.1 | F8: =Y8 -> -955748.5 | G8: =IF(AND(ISNUMBER(B8),ISNUMBER(C8),C8<>0),(B8-C8)/ABS(C8),"-") -> -6.5753172 | H8: =IF(AND(ISNUMBER(B8),ISNUMBER(F8),F8<>0),(B8-F8)/ABS(F8),"-") -> 0.68674981 | K8: Cost of Materials Consumed | L8: -299388.4 | N8: Profit (+)/ Loss (-) from Ordinary Activities before Tax | O8: 53698.9 | Q8: Cost of Materials Consumed | R8: -245925.7 | U8: Profit (+)/ Loss (-) from Ordinary Activities before Tax | V8: 259758.1 | X8: Cost of Materials Consumed | Y8: -955748.5
A9: =K9 -> Finance Costs | B9: =L9 -> -6792.7 | C9: =O9 -> -15406.6 | D9: =R9 -> -7628.1 | E9: =V9 -> -68164.1 | F9: =Y9 -> -33343.7 | G9: =IF(AND(ISNUMBER(B9),ISNUMBER(C9),C9<>0),(B9-C9)/ABS(C9),"-") -> 0.55910454 | H9: =IF(AND(ISNUMBER(B9),ISNUMBER(F9),F9<>0),(B9-F9)/ABS(F9),"-") -> 0.79628236 | K9: Finance Costs | L9: -6792.7 | N9: Tax | O9: -15406.6 | Q9: Finance Costs | R9: -7628.1 | U9: Tax | V9: -68164.1 | X9: Finance Costs | Y9: -33343.7
A10: =K10 -> Other Expenses | B10: =L10 -> -312905.7 | C10: =O10 -> 38292.3 | D10: =R10 -> -234651.7 | E10: =V10 -> 191594 | F10: =Y10 -> -859648.3 | G10: =IF(AND(ISNUMBER(B10),ISNUMBER(C10),C10<>0),(B10-C10)/ABS(C10),"-") -> -9.1715045 | H10: =IF(AND(ISNUMBER(B10),ISNUMBER(F10),F10<>0),(B10-F10)/ABS(F10),"-") -> 0.63600731 | K10: Other Expenses | L10: -312905.7 | N10: Net Profit (+)/ Loss (-) from Ordinary Activities after Tax | O10: 38292.3 | Q10: Other Expenses | R10: -234651.7 | U10: Net Profit (+)/ Loss (-) from Ordinary Activities after Tax | V10: 191594 | X10: Other Expenses | Y10: -859648.3
A11: =K11 -> Purchases of stock-in-trade | B11: =L11 -> -4495.7 | C11: =O11 -> 38246.5 | D11: =R11 -> -129859.8 | E11: =V11 -> 189538.8 | F11: =Y11 -> -14021.4 | G11: =IF(AND(ISNUMBER(B11),ISNUMBER(C11),C11<>0),(B11-C11)/ABS(C11),"-") -> -1.1175454 | H11: =IF(AND(ISNUMBER(B11),ISNUMBER(F11),F11<>0),(B11-F11)/ABS(F11),"-") -> 0.67936868 | K11: Purchases of stock-in-trade | L11: -4495.7 | N11: Net Profit | O11: 38246.5 | Q11: Employee benefit expense | R11: -129859.8 | U11: Net Profit | V11: 189538.8 | X11: Purchases of stock-in-trade | Y11: -14021.4
A12: =K12 -> Changes in inventories of finished goods, work-in-progress and stock-in-trade | B12: =L12 -> 12900 | C12: =O12 -> 0 | D12: =R12 -> -3020.8 | E12: =V12 -> 0 | F12: =Y12 -> -41211.8 | G12: =IF(AND(ISNUMBER(B12),ISNUMBER(C12),C12<>0),(B12-C12)/ABS(C12),"-") -> - | H12: =IF(AND(ISNUMBER(B12),ISNUMBER(F12),F12<>0),(B12-F12)/ABS(F12),"-") -> 1.3130171 | K12: Changes in inventories of finished goods, work-in-progress and stock-in-trade | L12: 12900 | N12: Minority Interest | O12: 0 | Q12: Purchases of stock-in-trade | R12: -3020.8 | U12: Minority Interest | V12: 0 | X12: Depreciation and amortisation expense | Y12: -41211.8
A13: =K13 -> Employee benefit expense | B13: =L13 -> -137629.2 | C13: =O13 -> 0 | D13: =R13 -> 1686.8 | E13: =V13 -> 0 | F13: =Y13 -> -467686.8 | G13: =IF(AND(ISNUMBER(B13),ISNUMBER(C13),C13<>0),(B13-C13)/ABS(C13),"-") -> - | H13: =IF(AND(ISNUMBER(B13),ISNUMBER(F13),F13<>0),(B13-F13)/ABS(F13),"-") -> 0.70572357 | K13: Employee benefit expense | L13: -137629.2 | N13: Share of Profit & Loss of Asso | O13: 0 | Q13: Changes in inventories of finished goods, work-in-progress and stock-in-trade | R13: 1686.8 | U13: Share of Profit & Loss of Asso | V13: 0 | X13: Employee benefit expense | Y13: -467686.8
A14: =K14 -> Depreciation and amortisation expense | B14: =L14 -> -11679.5 | C14: =O14 -> 38246.5 | D14: =R14 -> -10917.7 | E14: =V14 -> 189538.8 | F14: =Y14 -> 4107.9 | G14: =IF(AND(ISNUMBER(B14),ISNUMBER(C14),C14<>0),(B14-C14)/ABS(C14),"-") -> -1.3053743 | H14: =IF(AND(ISNUMBER(B14),ISNUMBER(F14),F14<>0),(B14-F14)/ABS(F14),"-") -> -3.8431802 | K14: Depreciation and amortisation expense | L14: -11679.5 | N14: Net Profit after Mino Inter & Share of P & L | O14: 38246.5 | Q14: Depreciation and amortisation expense | R14: -10917.7 | U14: Net Profit after Mino Inter & Share of P & L | V14: 189538.8 | X14: Changes in inventories of finished goods, work-in-progress and stock-in-trade | Y14: 4107.9
A15: =K15 -> Profit (+)/ Loss (-) from Ordinary Activities before Tax | B15: =L15 -> 84102.8 | C15: =O15 -> 0 | D15: =R15 -> 63361.1 | E15: =V15 -> 0 | F15: =Y15 -> 235787.9 | G15: =IF(AND(ISNUMBER(B15),ISNUMBER(C15),C15<>0),(B15-C15)/ABS(C15),"-") -> - | H15: =IF(AND(ISNUMBER(B15),ISNUMBER(F15),F15<>0),(B15-F15)/ABS(F15),"-") -> -0.64331164 | K15: Profit (+)/ Loss (-) from Ordinary Activities before Tax | L15: 84102.8 | N15: Any Other | O15: 0 | Q15: Profit (+)/ Loss (-) from Ordinary Activities before Tax | R15: 63361.1 | U15: Any Other | V15: 0 | X15: Profit (+)/ Loss (-) from Ordinary Activities before Tax | Y15: 235787.9
A16: =K16 -> Tax | B16: =L16 -> -20927.5 | C16: =O16 -> 38246.5 | D16: =R16 -> -16490.2 | E16: =V16 -> 189538.8 | F16: =Y16 -> -58914 | G16: =IF(AND(ISNUMBER(B16),ISNUMBER(C16),C16<>0),(B16-C16)/ABS(C16),"-") -> -1.5471743 | H16: =IF(AND(ISNUMBER(B16),ISNUMBER(F16),F16<>0),(B16-F16)/ABS(F16),"-") -> 0.64477883 | K16: Tax | L16: -20927.5 | N16: Income Attributable to Consolidated Group | O16: 38246.5 | Q16: Tax | R16: -16490.2 | U16: Income Attributable to Consolidated Group | V16: 189538.8 | X16: Tax | Y16: -58914
A17: =K17 -> Net Profit (+)/ Loss (-) from Ordinary Activities after Tax | B17: =L17 -> 63175.3 | C17: =O17 -> - | D17: =R17 -> 46870.9 | E17: =V17 -> - | F17: =Y17 -> 176873.9 | G17: =IF(AND(ISNUMBER(B17),ISNUMBER(C17),C17<>0),(B17-C17)/ABS(C17),"-") -> - | H17: =IF(AND(ISNUMBER(B17),ISNUMBER(F17),F17<>0),(B17-F17)/ABS(F17),"-") -> -0.64282294 | K17: Net Profit (+)/ Loss (-) from Ordinary Activities after Tax | L17: 63175.3 | N17: EPS after Extraordinary items (in Rs) | O17: - | Q17: Net Profit (+)/ Loss (-) from Ordinary Activities after Tax | R17: 46870.9 | U17: EPS after Extraordinary items (in Rs) | V17: - | X17: Net Profit (+)/ Loss (-) from Ordinary Activities after Tax | Y17: 176873.9
A18: =K18 -> Net Profit | B18: =L18 -> 61330.6 | C18: =O18 -> -17910.9 | D18: =R18 -> 46780.1 | E18: =V18 -> -17224.4 | F18: =Y18 -> 0 | G18: =IF(AND(ISNUMBER(B18),ISNUMBER(C18),C18<>0),(B18-C18)/ABS(C18),"-") -> 4.4242054 | H18: =IF(AND(ISNUMBER(B18),ISNUMBER(F18),F18<>0),(B18-F18)/ABS(F18),"-") -> - | K18: Net Profit | L18: 61330.6 | N18: Exceptional Item | O18: -17910.9 | Q18: Net Profit | R18: 46780.1 | U18: Exceptional Item | V18: -17224.4 | X18: Extraordinary Items | Y18: 0
A19: =K19 -> Current tax | B19: =L19 -> -22154.5 | C19: =O19 -> 71609.8 | D19: =R19 -> -15769.7 | E19: =V19 -> 276982.5 | F19: =Y19 -> 176873.9 | G19: =IF(AND(ISNUMBER(B19),ISNUMBER(C19),C19<>0),(B19-C19)/ABS(C19),"-") -> -1.309378 | H19: =IF(AND(ISNUMBER(B19),ISNUMBER(F19),F19<>0),(B19-F19)/ABS(F19),"-") -> -1.1252559 | K19: Current tax | L19: -22154.5 | N19: Profit after Interest but before Exceptional Items | O19: 71609.8 | Q19: Current tax | R19: -15769.7 | U19: Profit after Interest but before Exceptional Items | V19: 276982.5 | X19: Net Profit | Y19: 176873.9
A20: =K20 -> Deferred tax | B20: =L20 -> 1227 | C20: =O20 -> 38292.3 | D20: =R20 -> -720.5 | E20: =V20 -> 191594 | F20: =Y20 -> -26362.2 | G20: =IF(AND(ISNUMBER(B20),ISNUMBER(C20),C20<>0),(B20-C20)/ABS(C20),"-") -> -0.967957 | H20: =IF(AND(ISNUMBER(B20),ISNUMBER(F20),F20<>0),(B20-F20)/ABS(F20),"-") -> 1.0465439 | K20: Deferred tax | L20: 1227 | N20: Net Profit Loss for the period from continuing operations | O20: 38292.3 | Q20: Deferred tax | R20: -720.5 | U20: Net Profit Loss for the period from continuing operations | V20: 191594 | X20: Minority Interest | Y20: -26362.2
A21: =K21 -> Minority Interest | B21: =L21 -> 0 | C21: =O21 -> 0 | D21: =R21 -> 0 | E21: =V21 -> 0 | F21: =Y21 -> -61008.2 | G21: =IF(AND(ISNUMBER(B21),ISNUMBER(C21),C21<>0),(B21-C21)/ABS(C21),"-") -> - | H21: =IF(AND(ISNUMBER(B21),ISNUMBER(F21),F21<>0),(B21-F21)/ABS(F21),"-") -> 1 | K21: Minority Interest | L21: 0 | N21: Profit (loss) from discontinuing operations before tax | O21: 0 | Q21: Minority Interest | R21: 0 | U21: Profit (loss) from discontinuing operations before tax | V21: 0 | X21: Current tax | Y21: -61008.2
A22: =K22 -> Share of Profit & Loss of Asso | B22: =L22 -> 0 | C22: =O22 -> 0 | D22: =R22 -> 0 | E22: =V22 -> 0 | F22: =Y22 -> 2094.2 | G22: =IF(AND(ISNUMBER(B22),ISNUMBER(C22),C22<>0),(B22-C22)/ABS(C22),"-") -> - | H22: =IF(AND(ISNUMBER(B22),ISNUMBER(F22),F22<>0),(B22-F22)/ABS(F22),"-") -> -1 | K22: Share of Profit & Loss of Asso | L22: 0 | N22: Tax expense of discontinuing operations | O22: 0 | Q22: Share of Profit & Loss of Asso | R22: 0 | U22: Tax expense of discontinuing operations | V22: 0 | X22: Deferred Tax | Y22: 2094.2
A23: =K23 -> Net Profit after Mino Inter & Share of P & L | B23: =L23 -> 61330.6 | C23: =O23 -> 0 | D23: =R23 -> 46780.1 | E23: =V23 -> 0 | F23: =Y23 -> -140.6 | G23: =IF(AND(ISNUMBER(B23),ISNUMBER(C23),C23<>0),(B23-C23)/ABS(C23),"-") -> - | H23: =IF(AND(ISNUMBER(B23),ISNUMBER(F23),F23<>0),(B23-F23)/ABS(F23),"-") -> 437.20626 | K23: Net Profit after Mino Inter & Share of P & L | L23: 61330.6 | N23: Net profit (loss) from discontinuing operation after tax | O23: 0 | Q23: Net Profit after Mino Inter & Share of P & L | R23: 46780.1 | U23: Net profit (loss) from discontinuing operation after tax | V23: 0 | X23: Share of Profit & Loss of Asso | Y23: -140.6
A24: =K24 -> Any Other | B24: =L24 -> 0 | C24: =O24 -> 6475.5 | D24: =R24 -> 0 | E24: =V24 -> -4065 | F24: =Y24 -> 176873.9 | G24: =IF(AND(ISNUMBER(B24),ISNUMBER(C24),C24<>0),(B24-C24)/ABS(C24),"-") -> -1 | H24: =IF(AND(ISNUMBER(B24),ISNUMBER(F24),F24<>0),(B24-F24)/ABS(F24),"-") -> -1 | K24: Any Other | L24: 0 | N24: Other Comprehensive Income Net of Taxes | O24: 6475.5 | Q24: Any Other | R24: 0 | U24: Other Comprehensive Income Net of Taxes | V24: -4065 | X24: Net Profit after Mino Inter & Share of P & L | Y24: 176873.9
A25: =K25 -> Income Attributable to Consolidated Group | B25: =L25 -> 61330.6 | C25: =O25 -> 0 | D25: =R25 -> 46780.1 | E25: =V25 -> 0 | F25: =Y25 -> 0 | G25: =IF(AND(ISNUMBER(B25),ISNUMBER(C25),C25<>0),(B25-C25)/ABS(C25),"-") -> - | H25: =IF(AND(ISNUMBER(B25),ISNUMBER(F25),F25<>0),(B25-F25)/ABS(F25),"-") -> - | K25: Income Attributable to Consolidated Group | L25: 61330.6 | N25: Any Other Comprehensive Item | O25: 0 | Q25: Income Attributable to Consolidated Group | R25: 46780.1 | U25: Any Other Comprehensive Item | V25: 0 | X25: Any Other | Y25: 0
A26: =K26 -> EPS after Extraordinary items (in Rs) | B26: =L26 -> - | C26: =O26 -> 44722 | D26: =R26 -> - | E26: =V26 -> 185473.8 | F26: =Y26 -> 176873.9 | G26: =IF(AND(ISNUMBER(B26),ISNUMBER(C26),C26<>0),(B26-C26)/ABS(C26),"-") -> - | H26: =IF(AND(ISNUMBER(B26),ISNUMBER(F26),F26<>0),(B26-F26)/ABS(F26),"-") -> - | K26: EPS after Extraordinary items (in Rs) | L26: - | N26: Total Comprehensive Income for the Period | O26: 44722 | Q26: EPS after Extraordinary items (in Rs) | R26: - | U26: Total Comprehensive Income for the Period | V26: 185473.8 | X26: Income Attributable to Consolidated Group | Y26: 176873.9
A27: =K27 -> Exceptional Item | B27: =L27 -> 686.5 | C27: =O27 -> 0 | D27: =R27 -> 0 | E27: =V27 -> 0 | F27: =Y27 -> - | G27: =IF(AND(ISNUMBER(B27),ISNUMBER(C27),C27<>0),(B27-C27)/ABS(C27),"-") -> - | H27: =IF(AND(ISNUMBER(B27),ISNUMBER(F27),F27<>0),(B27-F27)/ABS(F27),"-") -> - | K27: Exceptional Item | L27: 686.5 | N27: Total Amount of items that will not be reclassified to profit and loss | O27: 0 | Q27: Exceptional Item | R27: 0 | U27: Total Amount of items that will not be reclassified to profit and loss | V27: 0 | X27: EPS after Extraordinary items (in Rs) | Y27: -
A28: =K28 -> Profit after Interest but before Exceptional Items | B28: =L28 -> 83416.3 | C28: =O28 -> 0 | D28: =R28 -> 63361.1 | E28: =V28 -> 0 | F28: =Y28 -> 4747.8 | G28: =IF(AND(ISNUMBER(B28),ISNUMBER(C28),C28<>0),(B28-C28)/ABS(C28),"-") -> - | H28: =IF(AND(ISNUMBER(B28),ISNUMBER(F28),F28<>0),(B28-F28)/ABS(F28),"-") -> 16.569464 | K28: Profit after Interest but before Exceptional Items | L28: 83416.3 | N28: Income tax relating to items that will not be reclassified to profit or loss | O28: 0 | Q28: Profit after Interest but before Exceptional Items | R28: 63361.1 | U28: Income tax relating to items that will not be reclassified to profit or loss | V28: 0 | X28: Exceptional Item | Y28: 4747.8
A29: =K29 -> Net Profit Loss for the period from continuing operations | B29: =L29 -> 63175.3 | C29: =O29 -> 0 | D29: =R29 -> 46870.9 | E29: =V29 -> 0 | F29: =Y29 -> 231040.1 | G29: =IF(AND(ISNUMBER(B29),ISNUMBER(C29),C29<>0),(B29-C29)/ABS(C29),"-") -> - | H29: =IF(AND(ISNUMBER(B29),ISNUMBER(F29),F29<>0),(B29-F29)/ABS(F29),"-") -> -0.72656132 | K29: Net Profit Loss for the period from continuing operations | L29: 63175.3 | N29: Total Amount of items that will be reclassified to profit and loss | O29: 0 | Q29: Net Profit Loss for the period from continuing operations | R29: 46870.9 | U29: Total Amount of items that will be reclassified to profit and loss | V29: 0 | X29: Profit after Interest but before Exceptional Items | Y29: 231040.1
A30: =K30 -> Profit (loss) from discontinuing operations before tax | B30: =L30 -> 0 | C30: =O30 -> 0 | D30: =R30 -> 0 | E30: =V30 -> 0 | F30: =Y30 -> - | G30: =IF(AND(ISNUMBER(B30),ISNUMBER(C30),C30<>0),(B30-C30)/ABS(C30),"-") -> - | H30: =IF(AND(ISNUMBER(B30),ISNUMBER(F30),F30<>0),(B30-F30)/ABS(F30),"-") -> - | K30: Profit (loss) from discontinuing operations before tax | L30: 0 | N30: Income tax relating to items that will be reclassified to profit or loss | O30: 0 | Q30: Profit (loss) from discontinuing operations before tax | R30: 0 | U30: Income tax relating to items that will be reclassified to profit or loss | V30: 0 | X30: Net Profit Loss for the period from continuing operations | Y30: -
A31: =K31 -> Tax expense of discontinuing operations | B31: =L31 -> 0 | C31: =O31 -> 0 | D31: =R31 -> 0 | E31: =V31 -> 0 | F31: =Y31 -> 0 | G31: =IF(AND(ISNUMBER(B31),ISNUMBER(C31),C31<>0),(B31-C31)/ABS(C31),"-") -> - | H31: =IF(AND(ISNUMBER(B31),ISNUMBER(F31),F31<>0),(B31-F31)/ABS(F31),"-") -> - | K31: Tax expense of discontinuing operations | L31: 0 | N31: Net movement in regulatory deferral account balances | O31: 0 | Q31: Tax expense of discontinuing operations | R31: 0 | U31: Net movement in regulatory deferral account balances | V31: 0 | X31: Profit (loss) from discontinuing operations before tax | Y31: 0
A32: =K32 -> Net profit (loss) from discontinuing operation after tax | B32: =L32 -> 0 | C32: =O32 -> -45.8 | D32: =R32 -> 0 | E32: =V32 -> -2055.2 | F32: =Y32 -> 0 | G32: =IF(AND(ISNUMBER(B32),ISNUMBER(C32),C32<>0),(B32-C32)/ABS(C32),"-") -> 1 | H32: =IF(AND(ISNUMBER(B32),ISNUMBER(F32),F32<>0),(B32-F32)/ABS(F32),"-") -> - | K32: Net profit (loss) from discontinuing operation after tax | L32: 0 | N32: Share of profit(loss) of associates and joint ventures | O32: -45.8 | Q32: Net profit (loss) from discontinuing operation after tax | R32: 0 | U32: Share of profit(loss) of associates and joint ventures | V32: -2055.2 | X32: Tax expense of discontinuing operations | Y32: 0
A33: =K33 -> Other Comprehensive Income Net of Taxes | B33: =L33 -> -17234.2 | C33: =O33 -> 0 | D33: =R33 -> -4895.4 | E33: =V33 -> 0 | F33: =Y33 -> 0 | G33: =IF(AND(ISNUMBER(B33),ISNUMBER(C33),C33<>0),(B33-C33)/ABS(C33),"-") -> - | H33: =IF(AND(ISNUMBER(B33),ISNUMBER(F33),F33<>0),(B33-F33)/ABS(F33),"-") -> - | K33: Other Comprehensive Income Net of Taxes | L33: -17234.2 | Q33: Other Comprehensive Income Net of Taxes | R33: -4895.4 | X33: Net profit (loss) from discontinuing operation after tax | Y33: 0
A34: =K34 -> Any Other Comprehensive Item | B34: =L34 -> 0 | C34: =O34 -> 0 | D34: =R34 -> 0 | E34: =V34 -> 0 | F34: =Y34 -> 235787.9 | G34: =IF(AND(ISNUMBER(B34),ISNUMBER(C34),C34<>0),(B34-C34)/ABS(C34),"-") -> - | H34: =IF(AND(ISNUMBER(B34),ISNUMBER(F34),F34<>0),(B34-F34)/ABS(F34),"-") -> -1 | K34: Any Other Comprehensive Item | L34: 0 | Q34: Any Other Comprehensive Item | R34: 0 | X34: Profit before extraordinary items and Tax | Y34: 235787.9
A35: =K35 -> Total Comprehensive Income for the Period | B35: =L35 -> 44096.4 | C35: =O35 -> 0 | D35: =R35 -> 41884.7 | E35: =V35 -> 0 | F35: =Y35 -> 109.36 | G35: =IF(AND(ISNUMBER(B35),ISNUMBER(C35),C35<>0),(B35-C35)/ABS(C35),"-") -> - | H35: =IF(AND(ISNUMBER(B35),ISNUMBER(F35),F35<>0),(B35-F35)/ABS(F35),"-") -> 402.22238 | K35: Total Comprehensive Income for the Period | L35: 44096.4 | Q35: Total Comprehensive Income for the Period | R35: 41884.7 | X35: Basic for discontinued & continuing operation | Y35: 109.36
A36: =K36 -> Total Amount of items that will not be reclassified to profit and loss | B36: =L36 -> 0 | C36: =O36 -> 0 | D36: =R36 -> 0 | E36: =V36 -> 0 | F36: =Y36 -> 109.28 | G36: =IF(AND(ISNUMBER(B36),ISNUMBER(C36),C36<>0),(B36-C36)/ABS(C36),"-") -> - | H36: =IF(AND(ISNUMBER(B36),ISNUMBER(F36),F36<>0),(B36-F36)/ABS(F36),"-") -> -1 | K36: Total Amount of items that will not be reclassified to profit and loss | L36: 0 | Q36: Total Amount of items that will not be reclassified to profit and loss | R36: 0 | X36: Diluted for discontinued & continuing operation | Y36: 109.28
A37: =K37 -> Income tax relating to items that will not be reclassified to profit or loss | B37: =L37 -> 0 | C37: =O37 -> 0 | D37: =R37 -> 0 | E37: =V37 -> 0 | F37: =Y37 -> 0 | G37: =IF(AND(ISNUMBER(B37),ISNUMBER(C37),C37<>0),(B37-C37)/ABS(C37),"-") -> - | H37: =IF(AND(ISNUMBER(B37),ISNUMBER(F37),F37<>0),(B37-F37)/ABS(F37),"-") -> - | K37: Income tax relating to items that will not be reclassified to profit or loss | L37: 0 | Q37: Income tax relating to items that will not be reclassified to profit or loss | R37: 0
A38: =K38 -> Total Amount of items that will be reclassified to profit and loss | B38: =L38 -> 0 | C38: =O38 -> 0 | D38: =R38 -> 0 | E38: =V38 -> 0 | F38: =Y38 -> 0 | G38: =IF(AND(ISNUMBER(B38),ISNUMBER(C38),C38<>0),(B38-C38)/ABS(C38),"-") -> - | H38: =IF(AND(ISNUMBER(B38),ISNUMBER(F38),F38<>0),(B38-F38)/ABS(F38),"-") -> - | K38: Total Amount of items that will be reclassified to profit and loss | L38: 0 | Q38: Total Amount of items that will be reclassified to profit and loss | R38: 0
A39: =K39 -> Income tax relating to items that will be reclassified to profit or loss | B39: =L39 -> 0 | C39: =O39 -> 0 | D39: =R39 -> 0 | E39: =V39 -> 0 | F39: =Y39 -> 0 | G39: =IF(AND(ISNUMBER(B39),ISNUMBER(C39),C39<>0),(B39-C39)/ABS(C39),"-") -> - | H39: =IF(AND(ISNUMBER(B39),ISNUMBER(F39),F39<>0),(B39-F39)/ABS(F39),"-") -> - | K39: Income tax relating to items that will be reclassified to profit or loss | L39: 0 | Q39: Income tax relating to items that will be reclassified to profit or loss | R39: 0
A40: =K40 -> Net movement in regulatory deferral account balances | B40: =L40 -> 0 | C40: =O40 -> 0 | D40: =R40 -> 0 | E40: =V40 -> 0 | F40: =Y40 -> 0 | G40: =IF(AND(ISNUMBER(B40),ISNUMBER(C40),C40<>0),(B40-C40)/ABS(C40),"-") -> - | H40: =IF(AND(ISNUMBER(B40),ISNUMBER(F40),F40<>0),(B40-F40)/ABS(F40),"-") -> - | K40: Net movement in regulatory deferral account balances | L40: 0 | Q40: Net movement in regulatory deferral account balances | R40: 0
A41: =K41 -> Share of profit(loss) of associates and joint ventures | B41: =L41 -> -1844.7 | C41: =O41 -> 0 | D41: =R41 -> -90.8 | E41: =V41 -> 0 | F41: =Y41 -> 0 | G41: =IF(AND(ISNUMBER(B41),ISNUMBER(C41),C41<>0),(B41-C41)/ABS(C41),"-") -> - | H41: =IF(AND(ISNUMBER(B41),ISNUMBER(F41),F41<>0),(B41-F41)/ABS(F41),"-") -> - | K41: Share of profit(loss) of associates and joint ventures | L41: -1844.7 | Q41: Share of profit(loss) of associates and joint ventures | R41: -90.8
A42: =K42 -> Basic EPS for continuing operation | B42: =L42 -> 38.71 | C42: =O42 -> 0 | D42: =R42 -> 28.54 | E42: =V42 -> 0 | F42: =Y42 -> 0 | G42: =IF(AND(ISNUMBER(B42),ISNUMBER(C42),C42<>0),(B42-C42)/ABS(C42),"-") -> - | H42: =IF(AND(ISNUMBER(B42),ISNUMBER(F42),F42<>0),(B42-F42)/ABS(F42),"-") -> - | K42: Basic EPS for continuing operation | L42: 38.71 | Q42: Basic EPS for continuing operation | R42: 28.54
A43: =K43 -> Diluted EPS for continuing operation | B43: =L43 -> 38.7 | C43: =O43 -> 0 | D43: =R43 -> 28.53 | E43: =V43 -> 0 | F43: =Y43 -> 0 | G43: =IF(AND(ISNUMBER(B43),ISNUMBER(C43),C43<>0),(B43-C43)/ABS(C43),"-") -> - | H43: =IF(AND(ISNUMBER(B43),ISNUMBER(F43),F43<>0),(B43-F43)/ABS(F43),"-") -> - | K43: Diluted EPS for continuing operation | L43: 38.7 | Q43: Diluted EPS for continuing operation | R43: 28.53
A44: =K44 -> Basic for discontinued & continuing operation | B44: =L44 -> 0 | C44: =O44 -> 0 | D44: =R44 -> 0 | E44: =V44 -> 0 | F44: =Y44 -> 0 | G44: =IF(AND(ISNUMBER(B44),ISNUMBER(C44),C44<>0),(B44-C44)/ABS(C44),"-") -> - | H44: =IF(AND(ISNUMBER(B44),ISNUMBER(F44),F44<>0),(B44-F44)/ABS(F44),"-") -> - | K44: Basic for discontinued & continuing operation | L44: 0 | Q44: Basic for discontinued & continuing operation | R44: 0
A45: =K45 -> Diluted for discontinued & continuing operation | B45: =L45 -> 0 | C45: =O45 -> 0 | D45: =R45 -> 0 | E45: =V45 -> 0 | F45: =Y45 -> 0 | G45: =IF(AND(ISNUMBER(B45),ISNUMBER(C45),C45<>0),(B45-C45)/ABS(C45),"-") -> - | H45: =IF(AND(ISNUMBER(B45),ISNUMBER(F45),F45<>0),(B45-F45)/ABS(F45),"-") -> - | K45: Diluted for discontinued & continuing operation | L45: 0 | Q45: Diluted for discontinued & continuing operation | R45: 0

Sheet Beta
A1: Date | B1: LT_Close | C1: Nifty50_Close | D1: Market return nifty 50 | E1: Rm LT_Close | F1: SLOPE | G1: COVARIANCE
A2: 43922 | B2: 774.34998 | C2: 8253.7998
A3: 43924 | B3: 774.65002 | C3: 8083.7998 | D3: =(C3-C2)/C2 -> -0.020596574 | E3: =(B3-B2)/B2 -> 0.00038748478 | F3: =SLOPE(E3:E1534,D3:D1534) -> 1.0792935 | G3: =_xlfn.COVARIANCE.S(E3:E1534,D3:D1534)/_xlfn.VAR.S(D3:D1534) -> 1.0792935 | H3: SUMMARY OUTPUT
A4: 43928 | B4: 801.65002 | C4: 8792.2002 | D4: =(C4-C3)/C3 -> 0.087632105 | E4: =(B4-B3)/B3 -> 0.034854449
A5: 43929 | B5: 807.09998 | C5: 8748.75 | D5: =(C5-C4)/C4 -> -0.0049419024 | E5: =(B5-B4)/B4 -> 0.006798417 | H5: Regression Statistics
A6: 43930 | B6: 812.79999 | C6: 9111.9004 | D6: =(C6-C5)/C5 -> 0.041508832 | E6: =(B6-B5)/B5 -> 0.0070623372 | H6: Multiple R | I6: 0.64267828
A7: 43934 | B7: 865.45001 | C7: 8993.8496 | D7: =(C7-C6)/C6 -> -0.012955671 | E7: =(B7-B6)/B6 -> 0.064776114 | H7: R Square | I7: 0.41303537
A8: 43936 | B8: 880.15002 | C8: 8925.2998 | D8: =(C8-C7)/C7 -> -0.0076218536 | E8: =(B8-B7)/B7 -> 0.016985397 | H8: Adjusted R Square | I8: 0.41265173
A9: 43937 | B9: 911.65002 | C9: 8992.7998 | D9: =(C9-C8)/C8 -> 0.0075627712 | E9: =(B9-B8)/B8 -> 0.035789353 | H9: Standard Error | I9: 0.012615505
A10: 43938 | B10: 932.90002 | C10: 9266.75 | D10: =(C10-C9)/C9 -> 0.030463282 | E10: =(B10-B9)/B9 -> 0.023309383 | H10: Observations | I10: 1532
A11: 43941 | B11: 915.59998 | C11: 9261.8496 | D11: =(C11-C10)/C10 -> -0.00052881438 | E11: =(B11-B10)/B10 -> -0.018544376
A12: 43942 | B12: 870.34998 | C12: 8981.4502 | D12: =(C12-C11)/C11 -> -0.030274667 | E12: =(B12-B11)/B11 -> -0.049421146 | H12: ANOVA
A13: 43943 | B13: 852.59998 | C13: 9187.2998 | D13: =(C13-C12)/C12 -> 0.022919418 | E13: =(B13-B12)/B12 -> -0.020394095 | I13: df | J13: SS | K13: MS | L13: F | M13: Significance F
A14: 43944 | B14: 840.59998 | C14: 9313.9004 | D14: =(C14-C13)/C13 -> 0.013779956 | E14: =(B14-B13)/B13 -> -0.014074596 | H14: Regression | I14: 1 | J14: 0.17134681 | K14: 0.17134681 | L14: 1076.6307 | M14: 3.0850009e-179
A15: 43945 | B15: 851.20001 | C15: 9154.4004 | D15: =(C15-C14)/C14 -> -0.017124942 | E15: =(B15-B14)/B14 -> 0.012610084 | H15: Residual | I15: 1530 | J15: 0.24350098 | K15: 0.00015915096
A16: 43948 | B16: 855.25 | C16: 9282.2998 | D16: =(C16-C15)/C15 -> 0.013971359 | E16: =(B16-B15)/B15 -> 0.0047579743 | H16: Total | I16: 1531 | J16: 0.41484778
A17: 43949 | B17: 857.15002 | C17: 9380.9004 | D17: =(C17-C16)/C16 -> 0.010622431 | E17: =(B17-B16)/B16 -> 0.0022216012
A18: 43950 | B18: 875.34998 | C18: 9553.3496 | D18: =(C18-C17)/C17 -> 0.018383014 | E18: =(B18-B17)/B17 -> 0.021233099 | I18: Coefficients | J18: Standard Error | K18: t Stat | L18: P-value | M18: Lower 95% | N18: Upper 95% | O18: Lower 95.0% | P18: Upper 95.0%
A19: 43951 | B19: 897.54999 | C19: 9859.9004 | D19: =(C19-C18)/C18 -> 0.032088303 | E19: =(B19-B18)/B18 -> 0.025361299 | H19: Intercept | I19: 0.0004338008 | J19: 0.00032324044 | K19: 1.3420375 | L19: 0.17978294 | M19: -0.00020024039 | N19: 0.001067842 | O19: -0.00020024039 | P19: 0.001067842
A20: 43955 | B20: 850.65002 | C20: 9293.5 | D20: =(C20-C19)/C19 -> -0.057444839 | E20: =(B20-B19)/B19 -> -0.052253316 | H20: X Variable 1 | I20: 1.0792935 | J20: 0.032893204 | K20: 32.812051 | L20: 3.0850009e-179 | M20: 1.0147729 | N20: 1.143814 | O20: 1.0147729 | P20: 1.143814
A21: 43956 | B21: 836.90002 | C21: 9205.5996 | D21: =(C21-C20)/C20 -> -0.0094582655 | E21: =(B21-B20)/B20 -> -0.016164109
A22: 43957 | B22: 837.29999 | C22: 9270.9004 | D22: =(C22-C21)/C21 -> 0.0070935935 | E22: =(B22-B21)/B21 -> 0.00047791058
A23: 43958 | B23: 822.84998 | C23: 9199.0498 | D23: =(C23-C22)/C22 -> -0.0077501195 | E23: =(B23-B22)/B22 -> -0.017257867
A24: 43959 | B24: 815.95001 | C24: 9251.5 | D24: =(C24-C23)/C23 -> 0.0057016971 | E24: =(B24-B23)/B23 -> -0.0083854452
A25: 43962 | B25: 821.59998 | C25: 9239.2002 | D25: =(C25-C24)/C24 -> -0.001329493 | E25: =(B25-B24)/B24 -> 0.0069243989
A26: 43963 | B26: 814.79999 | C26: 9196.5498 | D26: =(C26-C25)/C25 -> -0.0046162427 | E26: =(B26-B25)/B25 -> -0.008276519
A27: 43964 | B27: 862.90002 | C27: 9383.5498 | D27: =(C27-C26)/C26 -> 0.020333713 | E27: =(B27-B26)/B26 -> 0.059032937
A28: 43965 | B28: 871.65002 | C28: 9142.75 | D28: =(C28-C27)/C27 -> -0.025661909 | E28: =(B28-B27)/B27 -> 0.010140225
A29: 43966 | B29: 864.40002 | C29: 9136.8496 | D29: =(C29-C28)/C28 -> -0.00064536279 | E29: =(B29-B28)/B28 -> -0.0083175584
A30: 43969 | B30: 813.34998 | C30: 8823.25 | D30: =(C30-C29)/C29 -> -0.03432251 | E30: =(B30-B29)/B29 -> -0.059058361
A31: 43970 | B31: 796.34998 | C31: 8879.0996 | D31: =(C31-C30)/C30 -> 0.0063298228 | E31: =(B31-B30)/B30 -> -0.020901212
A32: 43971 | B32: 835 | C32: 9066.5498 | D32: =(C32-C31)/C31 -> 0.021111397 | E32: =(B32-B31)/B31 -> 0.048533968
... A1534: 46189 | B1534: 4186.3999 | C1534: 23989.15 | D1534: =(C1534-C1533)/C1533 -> 0.0056699323 | E1534: =(B1534-B1533)/B1533 -> 0.0039810299

Sheet Wacc
A1: Capital Structure
A2: Total Debt | B2: ='Consolidated Balance sheet'!E15+'Consolidated Balance sheet'!E21 -> 129559.34
A3: Total Equity | B3: ='Consolidated Balance sheet'!E6/2*E3 -> 481320 | D3: CMP (₹) — Current Market Price (Input) | E3: 3500
A4: Total Mix (Debt + Equity) | B4: =B2+B3 -> 610879.34
A5: % of Debt | B5: =B2/B4 -> 0.21208663
A6: % of Equity | B6: =B3/B4 -> 0.78791337
A7: Debt to Equity | B7: =B2/B3 -> 0.26917506
A9: Cost of Equity (CAPM)
A10: Risk-free Rate (Rf) | B10: 0.0625 | D10: Source: RBI 10-year Government Securities yield (FY2025)
A11: Beta (β) | B11: =Beta!I20 -> 1.0792935
A12: Market Risk Premium (Rm - Rf) | B12: 0.0605 | D12: Source: India Equity Risk Premium (Damodaran estimate)
A13: Cost of Equity [Ke = Rf + β×(Rm-Rf)] | B13: =B10+B11*B12 -> 0.12779725
A15: Cost of Debt
A16: Finance Cost (FY2025) | B16: ='Consolidated P&L'!E17 -> 3334.37
A17: Total Debt (FY2025) | B17: =B2 -> 129559.34
A18: Pre-tax Cost of Debt [Kd = FC/Debt] | B18: =IF(B17=0,0,B16/B17) -> 0.025736238
A19: Tax Rate | B19: =Assumptions!G34 -> 0.26002506
A20: Post-tax Cost of Debt [Kd*(1-T)] | B20: =B18*(1-B19) -> 0.019044171
A22: WACC
A23: Source | B23: Weight | C23: Cost | D23: Weighted Cost
A24: Debt | B24: =B5 -> 0.21208663 | C24: =B20 -> 0.019044171 | D24: =C24*B24 -> 0.0040390141
A25: Equity | B25: =B6 -> 0.78791337 | C25: =B13 -> 0.12779725 | D25: =C25*B25 -> 0.10069317
A26: WACC | B26: =B24+B25 -> 1 | D26: =D24+D25 -> 0.10473218 | F26: wacc = we*ke+wd*kd

Sheet Ratio Analysis
A1: Ratio Analysis- Larsen & Toubro
A2: Years | B2: 44621 | C2: 44986 | D2: 45352 | E2: 45717 | F2: 46082 | G2: Trends | H2: Mean | I2: Median
A4: Sales Growth | C4: =(Assumptions!C3-Assumptions!B3)/Assumptions!B3 -> 0.17134717 | D4: =(Assumptions!D3-Assumptions!C3)/Assumptions!C3 -> 0.20602196 | E4: =(Assumptions!E3-Assumptions!D3)/Assumptions!D3 -> 0.15657856 | F4: =(Assumptions!F3-Assumptions!E3)/Assumptions!E3 -> 0.11785628 | H4: =AVERAGE(C4:F4) -> 0.16295099 | I4: =MEDIAN(B4:F4) -> 0.16396286
A5: EBITDA Growth | C5: =(Assumptions!C9-Assumptions!B9)/Assumptions!B9 -> 0.13920724 | D5: =(Assumptions!D9-Assumptions!C9)/Assumptions!C9 -> 0.13204515 | E5: =(Assumptions!E9-Assumptions!D9)/Assumptions!D9 -> 0.12518659 | F5: =(Assumptions!F9-Assumptions!E9)/Assumptions!E9 -> 0.36738549 | H5: =AVERAGE(B5:F5) -> 0.19095612 | I5: =MEDIAN(B5:F5) -> 0.13562619
A6: EBIT Growth | C6: =(Assumptions!C11-Assumptions!B11)/Assumptions!B11 -> 0.12978156 | D6: =(Assumptions!D11-Assumptions!C11)/Assumptions!C11 -> 0.14841375 | E6: =(Assumptions!E11-Assumptions!D11)/Assumptions!D11 -> 0.12630355 | F6: =(Assumptions!F11-Assumptions!E11)/Assumptions!E11 -> 0.4243236 | H6: =AVERAGE(B6:F6) -> 0.20720561 | I6: =MEDIAN(B6:F6) -> 0.13909765
A7: Net Profit Growth | C7: =(Assumptions!C17-Assumptions!B17)/Assumptions!B17 -> 0.23504508 | D7: =(Assumptions!D17-Assumptions!C17)/Assumptions!C17 -> 0.24538737 | E7: =(Assumptions!E17-Assumptions!D17)/Assumptions!D17 -> 0.12228637 | F7: =(Assumptions!F17-Assumptions!E17)/Assumptions!E17 -> 0.23569347 | H7: =AVERAGE(B7:F7) -> 0.20960307 | I7: =MEDIAN(B7:F7) -> 0.23536928
A8: Dividend Growth
A10: Gross Margin | B10: =(Assumptions!B3-Assumptions!B8)/Assumptions!B3 -> 0.11638868 | C10: =(Assumptions!C3-Assumptions!C8)/Assumptions!C3 -> 0.11319516 | D10: =(Assumptions!D3-Assumptions!D8)/Assumptions!D3 -> 0.10625182 | E10: =(Assumptions!E3-Assumptions!E8)/Assumptions!E3 -> 0.10336793 | F10: =(Assumptions!F3-Assumptions!F8)/Assumptions!F3 -> 0.12644184 | H10: =AVERAGE(B10:F10) -> 0.11312909 | I10: =MEDIAN(B10:F10) -> 0.11319516
A11: EBITDA Margin | B11: =Assumptions!B28 -> 0.11638868 | C11: =Assumptions!C28 -> 0.11319516 | D11: =Assumptions!D28 -> 0.10625182 | E11: =Assumptions!E28 -> 0.10336793 | F11: =Assumptions!F28 -> 0.12644184 | H11: =AVERAGE(B11:F11) -> 0.11312909 | I11: =MEDIAN(B11:F11) -> 0.11319516
A12: EBIT Margin | B12: =Assumptions!B29 -> 0.097554498 | C12: =Assumptions!C29 -> 0.094092746 | D12: =Assumptions!D29 -> 0.089598206 | E12: =Assumptions!E29 -> 0.087252852 | F12: =Assumptions!F29 -> 0.11117377 | H12: =AVERAGE(B12:F12) -> 0.095934414 | I12: =MEDIAN(B12:F12) -> 0.094092746
A13: EBT Margin | B13: =Assumptions!B30 -> 0.092068852 | C13: =Assumptions!C30 -> 0.092576498 | D13: =Assumptions!D30 -> 0.092366836 | E13: =Assumptions!E30 -> 0.090343753 | F13: =Assumptions!F30 -> 0.096889592 | H13: =AVERAGE(B13:F13) -> 0.092849106 | I13: =MEDIAN(B13:F13) -> 0.092366836
A14: Net Profit Margin | B14: =Assumptions!B31 -> 0.053949295 | C14: =Assumptions!C31 -> 0.05688306 | D14: =Assumptions!D31 -> 0.058739763 | E14: =Assumptions!E31 -> 0.056998148 | F14: =Assumptions!F31 -> 0.063006525 | H14: =AVERAGE(B14:F14) -> 0.057915358 | I14: =MEDIAN(B14:F14) -> 0.056998148
A16: Sales Expenses%Sales | B16: =Assumptions!B8/Assumptions!B3 -> 0.88361132 | C16: =Assumptions!C8/Assumptions!C3 -> 0.88680484 | D16: =Assumptions!D8/Assumptions!D3 -> 0.89374818 | E16: =Assumptions!E8/Assumptions!E3 -> 0.89663207 | F16: =Assumptions!F8/Assumptions!F3 -> 0.87355816 | H16: =AVERAGE(B16:F16) -> 0.88687091 | I16: =MEDIAN(B16:F16) -> 0.88680484
A17: Depriciation%Sales | B17: =Assumptions!B10/Assumptions!B3 -> 0.018834186 | C17: =Assumptions!C10/Assumptions!C3 -> 0.019102414 | D17: =Assumptions!D10/Assumptions!D3 -> 0.016653618 | E17: =Assumptions!E10/Assumptions!E3 -> 0.016115076 | F17: =Assumptions!F10/Assumptions!F3 -> 0.015268071 | H17: =AVERAGE(B17:F17) -> 0.017194673 | I17: =MEDIAN(B17:F17) -> 0.016653618
A18: Operating Income%Sales | B18: =Assumptions!B9/Assumptions!B3 -> 0.11638868 | C18: =Assumptions!C9/Assumptions!C3 -> 0.11319516 | D18: =Assumptions!D9/Assumptions!D3 -> 0.10625182 | E18: =Assumptions!E9/Assumptions!E3 -> 0.10336793 | F18: =Assumptions!F9/Assumptions!F3 -> 0.12644184 | H18: =AVERAGE(B18:F18) -> 0.11312909 | I18: =MEDIAN(B18:F18) -> 0.11319516
A20: Return on Capital Employed | B20: =Assumptions!B44 -> 0.081688037 | C20: =Assumptions!C44 -> 0.09308793 | D20: =Assumptions!D44 -> 0.10706471 | E20: =Assumptions!E44 -> 0.10924653 | F20: =Assumptions!F44 -> 0.15125143 | H20: =AVERAGE(B20:F20) -> 0.10846773 | I20: =MEDIAN(B20:F20) -> 0.10706471
A21: Retained Earning % | B21: =Assumptions!B17/Assumptions!B3 -> 0.053949295 | C21: =Assumptions!C17/Assumptions!C3 -> 0.05688306 | D21: =Assumptions!D17/Assumptions!D3 -> 0.058739763 | E21: =Assumptions!E17/Assumptions!E3 -> 0.056998148 | F21: =Assumptions!F17/Assumptions!F3 -> 0.063006525 | H21: =AVERAGE(B21:F21) -> 0.057915358 | I21: =MEDIAN(B21:F21) -> 0.056998148
A22: Return on Equity % | B22: =Assumptions!B17/Assumptions!B39 -> 0.1022013 | C22: =Assumptions!C17/Assumptions!C39 -> 0.11675196 | D22: =Assumptions!D17/Assumptions!D39 -> 0.15039641 | E22: =Assumptions!E17/Assumptions!E39 -> 0.14926323 | F22: =Assumptions!F17/Assumptions!F39 -> 0.16480907 | H22: =AVERAGE(B22:F22) -> 0.13668439 | I22: =MEDIAN(B22:F22) -> 0.14926323
A23: Self Sustained Growth Rate | B23: =B22*B21 -> 0.0055136883 | C23: =C22*C21 -> 0.0066412089 | D23: =D22*D21 -> 0.0088342498 | E23: =E22*E21 -> 0.0085077275 | F23: =F22*F21 -> 0.010384047 | H23: =AVERAGE(B23:F23) -> 0.0079761842 | I23: =MEDIAN(B23:F23) -> 0.0085077275
A24: Interest Coverage Ratio | B24: =IF(Assumptions!B13=0,"",Assumptions!B11/Assumptions!B13) -> 4.8850977 | C24: =IF(Assumptions!C13=0,"",Assumptions!C11/Assumptions!C13) -> 5.3789116 | D24: =IF(Assumptions!D13=0,"",Assumptions!D11/Assumptions!D13) -> 5.587185 | E24: =IF(Assumptions!E13=0,"",Assumptions!E11/Assumptions!E13) -> 6.6919868 | F24: =IF(Assumptions!F13=0,"",Assumptions!F11/Assumptions!F13) -> 3.2284857 | H24: =AVERAGE(B24:F24) -> 5.1543334 | I24: =MEDIAN(B24:F24) -> 5.3789116
A26: Debtor Turnover Ratio | B26: =Assumptions!B3/'Consolidated Balance sheet'!B42 -> 3.3923904 | C26: =Assumptions!C3/'Consolidated Balance sheet'!C42 -> 4.0986906 | D26: =Assumptions!D3/'Consolidated Balance sheet'!D42 -> 4.5337011 | E26: =Assumptions!E3/'Consolidated Balance sheet'!E42 -> 4.7610674 | F26: =Assumptions!F3/'Consolidated Balance sheet'!F42 -> 4.7282237 | H26: =AVERAGE(B26:F26) -> 4.3028146 | I26: =MEDIAN(B26:F26) -> 4.5337011
A27: Creditor Turnover Ratio | B27: =Assumptions!B8/'Consolidated Balance sheet'!B22 -> 2.7041937 | C27: =Assumptions!C8/'Consolidated Balance sheet'!C22 -> 3.265849 | D27: =Assumptions!D8/'Consolidated Balance sheet'!D22 -> 3.7081738 | E27: =Assumptions!E8/'Consolidated Balance sheet'!E22 -> 4.3709988 | F27: =Assumptions!F8/'Consolidated Balance sheet'!F22 -> 3.5955023 | H27: =AVERAGE(B27:F27) -> 3.5289435 | I27: =MEDIAN(B27:F27) -> 3.5955023
A28: Inventory Turnover | B28: =Assumptions!B8/'Consolidated Balance sheet'!B41 -> 23.270484 | C28: =Assumptions!C8/'Consolidated Balance sheet'!C41 -> 23.809146 | D28: =Assumptions!D8/'Consolidated Balance sheet'!D41 -> 29.850995 | E28: =Assumptions!E8/'Consolidated Balance sheet'!E41 -> 29.893516 | F28: =Assumptions!F8/'Consolidated Balance sheet'!F41 -> 26.201838 | H28: =AVERAGE(B28:F28) -> 26.605196 | I28: =MEDIAN(B28:F28) -> 26.201838
A29: Fixed Asset Turnover | B29: =Assumptions!B3/'Consolidated Balance sheet'!B33 -> 4.28715 | C29: =Assumptions!C3/'Consolidated Balance sheet'!C33 -> 4.8364748 | D29: =Assumptions!D3/'Consolidated Balance sheet'!D33 -> 5.7870917 | E29: =Assumptions!E3/'Consolidated Balance sheet'!E33 -> 6.6778981 | F29: =Assumptions!F3/'Consolidated Balance sheet'!F33 -> 11.125109 | H29: =AVERAGE(B29:F29) -> 6.5427447 | I29: =MEDIAN(B29:F29) -> 5.7870917
A30: Capital Turnover Ratio | B30: =Assumptions!B3/Assumptions!B42 -> 0.83735797 | C30: =Assumptions!C3/Assumptions!C42 -> 0.989321 | D30: =Assumptions!D3/Assumptions!D42 -> 1.1949425 | E30: =Assumptions!E3/Assumptions!E42 -> 1.2520683 | F30: =Assumptions!F3/Assumptions!F42 -> 1.3604957 | H30: =AVERAGE(B30:F30) -> 1.1268371 | I30: =MEDIAN(B30:F30) -> 1.1949425
A32: (In days)
A33: Debtors Day | B33: =365/B26 -> 107.59375 | C33: =365/C26 -> 89.052831 | D33: =365/D26 -> 80.508175 | E33: =365/E26 -> 76.663481 | F33: =365/F26 -> 77.19601 | H33: =AVERAGE(B33:F33) -> 86.202849 | I33: =MEDIAN(B33:F33) -> 80.508175
A34: Payable Days | B34: =365/B27 -> 134.97554 | C34: =365/C27 -> 111.76267 | D34: =365/D27 -> 98.431201 | E34: =365/E27 -> 83.504943 | F34: =365/F27 -> 101.51572 | H34: =AVERAGE(B34:F34) -> 106.03801 | I34: =MEDIAN(B34:F34) -> 101.51572
A35: Inventory Days | B35: =365/B28 -> 15.685106 | C35: =365/C28 -> 15.330243 | D35: =365/D28 -> 12.227398 | E35: =365/E28 -> 12.210006 | F35: =365/F28 -> 13.930321 | H35: =AVERAGE(B35:F35) -> 13.876615 | I35: =MEDIAN(B35:F35) -> 13.930321
A36: Cash Conversion Cycle | B36: =B33+B35-B34 -> -11.696686 | C36: =C33+C35-C34 -> -7.3795931 | D36: =D33+D35-D34 -> -5.6956289 | E36: =E33+E35-E34 -> 5.3685443 | F36: =F33+F35-F34 -> -10.389387 | H36: =AVERAGE(B36:F36) -> -5.9585501 | I36: =MEDIAN(B36:F36) -> -7.3795931
A38: CFO/Sales | B38: =(Assumptions!B17+Assumptions!B10)/Assumptions!B3 -> 0.072783481 | C38: =(Assumptions!C17+Assumptions!C10)/Assumptions!C3 -> 0.075985474 | D38: =(Assumptions!D17+Assumptions!D10)/Assumptions!D3 -> 0.075393382 | E38: =(Assumptions!E17+Assumptions!E10)/Assumptions!E3 -> 0.073113224 | F38: =(Assumptions!F17+Assumptions!F10)/Assumptions!F3 -> 0.078274596 | H38: =AVERAGE(B38:F38) -> 0.075110031 | I38: =MEDIAN(B38:F38) -> 0.075393382
A39: CFO/Total Assets | B39: =(Assumptions!B17+Assumptions!B10)/'Consolidated Balance sheet'!B47 -> 0.035595058 | C39: =(Assumptions!C17+Assumptions!C10)/'Consolidated Balance sheet'!C47 -> 0.042170827 | D39: =(Assumptions!D17+Assumptions!D10)/'Consolidated Balance sheet'!D47 -> 0.049084549 | E39: =(Assumptions!E17+Assumptions!E10)/'Consolidated Balance sheet'!E47 -> 0.049265831 | F39: =(Assumptions!F17+Assumptions!F10)/'Consolidated Balance sheet'!F47 -> 0.04944582 | H39: =AVERAGE(B39:F39) -> 0.045112417 | I39: =MEDIAN(B39:F39) -> 0.049084549
A40: CFO/Total Debt | B40: =IF(Assumptions!B40=0,"",(Assumptions!B17+Assumptions!B10)/Assumptions!B40) -> 0.092429384 | C40: =IF(Assumptions!C40=0,"",(Assumptions!C17+Assumptions!C10)/Assumptions!C40) -> 0.11754985 | D40: =IF(Assumptions!D40=0,"",(Assumptions!D17+Assumptions!D10)/Assumptions!D40) -> 0.14618102 | E40: =IF(Assumptions!E40=0,"",(Assumptions!E17+Assumptions!E10)/Assumptions!E40) -> 0.14431665 | F40: =IF(Assumptions!F40=0,"",(Assumptions!F17+Assumptions!F10)/Assumptions!F40) -> 0.18389336 | H40: =AVERAGE(B40:F40) -> 0.13687405 | I40: =MEDIAN(B40:F40) -> 0.14431665

Sheet FCFF
A1: Particular | B1: 44621 | C1: 44986 | D1: 45352 | E1: 45717 | F1: 46082
A2: EBIT | B2: =Assumptions!B11 -> 15269.35 | C2: =Assumptions!C11 -> 17251.03 | D2: =Assumptions!D11 -> 19811.32 | E2: =Assumptions!E11 -> 22313.56 | F2: =Assumptions!F11 -> 31781.73
A3: Less: Tax on EBIT | B3: =B2*$J$5 -> 3970.4136 | C3: =C2*$J$5 -> 4485.7001 | D3: =D2*$J$5 -> 5151.4397 | E3: =E2*$J$5 -> 5802.0848 | F3: =F2*$J$5 -> 8264.0462
A4: EBIT * (1- Tax) NOPAT | B4: =B2-B3 -> 11298.936 | C4: =C2-C3 -> 12765.33 | D4: =D2-D3 -> 14659.88 | E4: =E2-E3 -> 16511.475 | F4: =F2-F3 -> 23517.684
A5: Less: Net Capital expenditure | C5: ='Fixed Assets scheduled'!C8 -> 1398.53 | D5: ='Fixed Assets scheduled'!D8 -> 300.03 | E5: ='Fixed Assets scheduled'!E8 -> 87.7 | F5: ='Fixed Assets scheduled'!F8 -> -12599.33 | I5: Avg of effective tax rate | J5: =AVERAGE(Assumptions!B34:F34) -> 0.26002506
A6: Less: Net Change in working Capital | C6: ='Change in working capital'!C6 -> 838.19 | D6: ='Change in working capital'!D6 -> 322.07 | E6: ='Change in working capital'!E6 -> 6826.63 | F6: ='Change in working capital'!F6 -> -8388.33
A7: Reinvestment | C7: =C5+C6 -> 2236.72 | D7: =D5+D6 -> 622.1 | E7: =E5+E6 -> 6914.33 | F7: =F5+F6 -> -20987.66
A8: Free Cash Flow | C8: =C4-C7 -> 10528.61 | D8: =D4-D7 -> 14037.78 | E8: =E4-E7 -> 9597.1452 | F8: =F4-F7 -> 44505.344
I9: Marginal tax rate | J9: =Assumptions!B35 -> 0.3
A10: Reinvestment Rate | C10: =C7/C4 -> 0.17521835 | D10: =D7/D4 -> 0.042435544 | E10: =E7/E4 -> 0.41875907 | F10: =F7/F4 -> -0.89242037
A12: Median Reinvestment rate /Sales percentage | B12: =MEDIAN(C10:F10) -> 0.10882695
A13: Average Reinvestment rate /Sales percentage | B13: =AVERAGE(C10:F10) -> -0.064001852

Sheet Change in working capital
A1: Particular | B1: 44621 | C1: 44986 | D1: 45352 | E1: 45717 | F1: 46082
A2: Inventory | B2: ='Consolidated Balance sheet'!B41 -> 5943.32 | C2: ='Consolidated Balance sheet'!C41 -> 6828.78 | D2: ='Consolidated Balance sheet'!D41 -> 6620.19 | E2: ='Consolidated Balance sheet'!E41 -> 7670.55 | F2: ='Consolidated Balance sheet'!F41 -> 9530.93
A3: Trade Receivables | B3: ='Consolidated Balance sheet'!B42 -> 46138.92 | C3: ='Consolidated Balance sheet'!C42 -> 44731.53 | D3: ='Consolidated Balance sheet'!D42 -> 48770.95 | E3: ='Consolidated Balance sheet'!E42 -> 53713.68 | F3: ='Consolidated Balance sheet'!F42 -> 60461.26
A4: Trade Payable | B4: ='Consolidated Balance sheet'!B22 -> 51144.24 | C4: ='Consolidated Balance sheet'!C22 -> 49784.12 | D4: ='Consolidated Balance sheet'!D22 -> 53292.88 | E4: ='Consolidated Balance sheet'!E22 -> 52459.34 | F4: ='Consolidated Balance sheet'!F22 -> 69455.63
A5: Non Cash working Capital | B5: =B2+B3-B4 -> 938 | C5: =C2+C3-C4 -> 1776.19 | D5: =D2+D3-D4 -> 2098.26 | E5: =E2+E3-E4 -> 8924.89 | F5: =F2+F3-F4 -> 536.56
A6: Change in Working Capital | C6: =C5-B5 -> 838.19 | D6: =D5-C5 -> 322.07 | E6: =E5-D5 -> 6826.63 | F6: =F5-E5 -> -8388.33
A7: change in working Capital /percentage of sales | C7: =C6/'Consolidated P&L'!B8 -> 0.0053551202 | D7: =D6/'Consolidated P&L'!C8 -> 0.0017566749 | E7: =E6/'Consolidated P&L'!D8 -> 0.030873955 | F7: =F6/'Consolidated P&L'!E8 -> -0.032800939
A9: Median Non Cash working Capital /Sales percentage | C9: =MEDIAN(C7:F7) -> 0.0035558975
A10: Average Non Cash working Capital /Sales percentage | C10: =AVERAGE(C7:F7) -> 0.0012962028

Sheet Fixed Assets scheduled
A1: Particular | B1: 44621 | C1: 44986 | D1: 45352 | E1: 45717 | F1: 46082
A2: Beginning balance | C2: =B6 -> 36509.39 | D2: =C6 -> 37907.92 | E2: =D6 -> 38207.95 | F2: =E6 -> 38295.65
A3: Add: Net Purchases | C3: =C6-C2+C5 -> 4900.78 | D3: =D6-D2+D5 -> 3982.36 | E3: =E6-E2+E5 -> 4208.88 | F3: =F6-F2+F5 -> -8234.58
A4: Total Fixed Assets | B4: =B5+B6 -> 39457.34 | C4: =C5+C6 -> 41410.17 | D4: =D5+D6 -> 41890.28 | E4: =E5+E6 -> 42416.83 | F4: =F5+F6 -> 30061.07
A5: Less: Depreciation | B5: ='Consolidated P&L'!B18 -> 2947.95 | C5: ='Consolidated P&L'!C18 -> 3502.25 | D5: ='Consolidated P&L'!D18 -> 3682.33 | E5: ='Consolidated P&L'!E18 -> 4121.18 | F5: ='Consolidated P&L'!F18 -> 4364.75
A6: Closing Balance(Fixed Asests ) | B6: ='Consolidated Balance sheet'!B33 -> 36509.39 | C6: ='Consolidated Balance sheet'!C33 -> 37907.92 | D6: ='Consolidated Balance sheet'!D33 -> 38207.95 | E6: ='Consolidated Balance sheet'!E33 -> 38295.65 | F6: ='Consolidated Balance sheet'!F33 -> 25696.32
A8: Net Capital expenditure | C8: =C3-C5 -> 1398.53 | D8: =D3-D5 -> 300.03 | E8: =E3-E5 -> 87.7 | F8: =F3-F5 -> -12599.33
A9: Net Capital expenditure / Sales percentage | C9: =C8/'Consolidated P&L'!B8 -> 0.0089350818 | D9: =D8/'Consolidated P&L'!C8 -> 0.0016364615 | E9: =E8/'Consolidated P&L'!D8 -> 0.00039662994 | F9: =F8/'Consolidated P&L'!E8 -> -0.049267238
A11: Median Capital expenditure /Sales percentage | C11: =MEDIAN(C9:F9) -> 0.0010165457
A12: Average Capital expenditure /Sales percentage | C12: =AVERAGE(C9:F9) -> -0.0095747662

Sheet Assumptions
A1: L&T
A2: Particulars (in RS Cr.) | B2: Mar 22 | C2: Mar 23 | D2: Mar 24 | E2: 45717 | F2: 46082
A3: Revenue from operations | B3: ='Consolidated P&L'!B8 -> 156521.23 | C3: ='Consolidated P&L'!C8 -> 183340.7 | D3: ='Consolidated P&L'!D8 -> 221112.91 | E3: ='Consolidated P&L'!E8 -> 255734.45 | F3: ='Consolidated P&L'!F8 -> 285874.36
A4: Revenue growth in % | C4: =(C3-B3)/B3 -> 0.17134717 | D4: =(D3-C3)/C3 -> 0.20602196 | E4: =(E3-D3)/D3 -> 0.15657856 | F4: =(F3-E3)/E3 -> 0.11785628
A5: Less: Material cost | B5: ='Consolidated P&L'!B12+'Consolidated P&L'!B13+'Consolidated P&L'!B14+'Consolidated P&L'!B15 -> 99738.51 | C5: ='Consolidated P&L'!C12+'Consolidated P&L'!C13+'Consolidated P&L'!C14+'Consolidated P&L'!C15 -> 116615.27 | D5: ='Consolidated P&L'!D12+'Consolidated P&L'!D13+'Consolidated P&L'!D14+'Consolidated P&L'!D15 -> 146028.82 | E5: ='Consolidated P&L'!E12+'Consolidated P&L'!E13+'Consolidated P&L'!E14+'Consolidated P&L'!E15 -> 170972.9 | F5: ='Consolidated P&L'!F12+'Consolidated P&L'!F13+'Consolidated P&L'!F14+'Consolidated P&L'!F15 -> 185841.21
A6: Less: Employee costs | B6: ='Consolidated P&L'!B16 -> 29733.53 | C6: ='Consolidated P&L'!C16 -> 37214.11 | D6: ='Consolidated P&L'!D16 -> 41171.02 | E6: ='Consolidated P&L'!E16 -> 46768.68 | F6: ='Consolidated P&L'!F16 -> 52187.22
A7: Less: Other Expenses | B7: ='Consolidated P&L'!B19 -> 8831.89 | C7: ='Consolidated P&L'!C19 -> 8758.04 | D7: ='Consolidated P&L'!D19 -> 10419.42 | E7: ='Consolidated P&L'!E19 -> 11558.13 | F7: ='Consolidated P&L'!F19 -> 11699.45
A8: Total Expenses | B8: =B5+B6+B7 -> 138303.93 | C8: =C5+C6+C7 -> 162587.42 | D8: =D5+D6+D7 -> 197619.26 | E8: =E5+E6+E7 -> 229299.71 | F8: =F5+F6+F7 -> 249727.88
A9: EBITDA | B9: =B3-B8 -> 18217.3 | C9: =C3-C8 -> 20753.28 | D9: =D3-D8 -> 23493.65 | E9: =E3-E8 -> 26434.74 | F9: =F3-F8 -> 36146.48
A10: Less: Depreciation And Amortization | B10: ='Consolidated P&L'!B18 -> 2947.95 | C10: ='Consolidated P&L'!C18 -> 3502.25 | D10: ='Consolidated P&L'!D18 -> 3682.33 | E10: ='Consolidated P&L'!E18 -> 4121.18 | F10: ='Consolidated P&L'!F18 -> 4364.75
A11: EBIT | B11: =B9-B10 -> 15269.35 | C11: =C9-C10 -> 17251.03 | D11: =D9-D10 -> 19811.32 | E11: =E9-E10 -> 22313.56 | F11: =F9-F10 -> 31781.73
A12: ADD: Non operating income/ Other Income | B12: ='Consolidated P&L'!B9 -> 2267.08 | C12: ='Consolidated P&L'!C9 -> 2929.17 | D12: ='Consolidated P&L'!D9 -> 4158.03 | E12: ='Consolidated P&L'!E9 -> 4124.82 | F12: ='Consolidated P&L'!F9 -> 5760.68
A13: Less: Interest Expenses | B13: ='Consolidated P&L'!B17 -> 3125.7 | C13: ='Consolidated P&L'!C17 -> 3207.16 | D13: ='Consolidated P&L'!D17 -> 3545.85 | E13: ='Consolidated P&L'!E17 -> 3334.37 | F13: ='Consolidated P&L'!F17 -> 9844.16
A14: EBT | B14: =B11+B12-B13 -> 14410.73 | C14: =C11+C12-C13 -> 16973.04 | D14: =D11+D12-D13 -> 20423.5 | E14: =E11+E12-E13 -> 23104.01 | F14: =F11+F12-F13 -> 27698.25
A15: Less: TAX | B15: ='Consolidated P&L'!B28 -> 4216.61 | C15: ='Consolidated P&L'!C28 -> 4484.16 | D15: ='Consolidated P&L'!D28 -> 4947.39 | E15: ='Consolidated P&L'!E28 -> 5891.4 | F15: ='Consolidated P&L'!F28 -> 6816.41
A16: Less:Non Controlling Interest/Minority Interest | B16: =ABS('Consolidated P&L'!B32) -> 1749.91 | C16: =ABS('Consolidated P&L'!C32) -> 2059.9 | D16: =ABS('Consolidated P&L'!D32) -> 2487.99 | E16: =ABS('Consolidated P&L'!E32) -> 2636.22 | F16: =ABS('Consolidated P&L'!F32) -> 2869.89
A17: Net Profit- Pat | B17: =B14-B15-B16 -> 8444.21 | C17: =C14-C15-C16 -> 10428.98 | D17: =D14-D15-D16 -> 12988.12 | E17: =E14-E15-E16 -> 14576.39 | F17: =F14-F15-F16 -> 18011.95
A23: Historical Growth
A24: Average Growth | B24: =AVERAGE(C4:F4) -> 0.16295099
A25: CAGR | B25: =(F3/B3)^(1/5)-1 -> 0.12802933 | C25: =(F3/B3)^(1/5)-1 -> 0.12802933 | D25: RRI
A27: Margins
A28: EBITDA | B28: =B9/B3 -> 0.11638868 | C28: =C9/C3 -> 0.11319516 | D28: =D9/D3 -> 0.10625182 | E28: =E9/E3 -> 0.10336793 | F28: =F9/F3 -> 0.12644184
A29: EBIT | B29: =B11/B3 -> 0.097554498 | C29: =C11/C3 -> 0.094092746 | D29: =D11/D3 -> 0.089598206 | E29: =E11/E3 -> 0.087252852 | F29: =F11/F3 -> 0.11117377
A30: EBT | B30: =B14/B3 -> 0.092068852 | C30: =C14/C3 -> 0.092576498 | D30: =D14/D3 -> 0.092366836 | E30: =E14/E3 -> 0.090343753 | F30: =F14/F3 -> 0.096889592
A31: Net Proftt | B31: =B17/B3 -> 0.053949295 | C31: =C17/C3 -> 0.05688306 | D31: =D17/D3 -> 0.058739763 | E31: =E17/E3 -> 0.056998148 | F31: =F17/F3 -> 0.063006525
A33: Tax Rate
A34: Effective tax rate | B34: =B15/B14 -> 0.29260211 | C34: =C15/C14 -> 0.2641931 | D34: =D15/D14 -> 0.24224007 | E34: =E15/E14 -> 0.2549947 | F34: =F15/F14 -> 0.24609533 | G34: =AVERAGE(B34:F34) -> 0.26002506 | H34: Effective tax rate
A35: Marginal Tax rate | B35: 0.3 | C35: =B35 -> 0.3 | D35: =C35 -> 0.3 | E35: =D35 -> 0.3 | F35: =E35 -> 0.3
A37: Return On Capital
A38: EBIT*(1-T) | B38: =B11*(1-B35) -> 10688.545 | C38: =C11*(1-C35) -> 12075.721 | D38: =D11*(1-D35) -> 13867.924 | E38: =E11*(1-E35) -> 15619.492 | F38: =F11*(1-F35) -> 22247.211
A39: Book Equity | B39: ='Consolidated Balance sheet'!B12 -> 82623.31 | C39: ='Consolidated Balance sheet'!C12 -> 89325.95 | D39: ='Consolidated Balance sheet'!D12 -> 86359.24 | E39: ='Consolidated Balance sheet'!E12 -> 97655.6 | F39: ='Consolidated Balance sheet'!F12 -> 109289.8
A40: Book Debt | B40: ='Consolidated Balance sheet'!B15+'Consolidated Balance sheet'!B21 -> 123252.58 | C40: ='Consolidated Balance sheet'!C15+'Consolidated Balance sheet'!C21 -> 118513.38 | D40: ='Consolidated Balance sheet'!D15+'Consolidated Balance sheet'!D21 -> 114039.77 | E40: ='Consolidated Balance sheet'!E15+'Consolidated Balance sheet'!E21 -> 129559.34 | F40: ='Consolidated Balance sheet'!F15+'Consolidated Balance sheet'!F21 -> 121683.02
A41: Cash and Cash equivalents | B41: ='Consolidated Balance sheet'!B43 -> 18953.17 | C41: ='Consolidated Balance sheet'!C43 -> 22519.6 | D41: ='Consolidated Balance sheet'!D43 -> 15358.39 | E41: ='Consolidated Balance sheet'!E43 -> 22965.34 | F41: ='Consolidated Balance sheet'!F43 -> 20847.67
A42: Capital Employed | B42: =B39+B40-B41 -> 186922.72 | C42: =C39+C40-C41 -> 185319.73 | D42: =D39+D40-D41 -> 185040.62 | E42: =E39+E40-E41 -> 204249.6 | F42: =F39+F40-F41 -> 210125.15
A44: Pre-Tax Return on capital | B44: =B11/B42 -> 0.081688037 | C44: =C11/C42 -> 0.09308793 | D44: =D11/D42 -> 0.10706471 | E44: =E11/E42 -> 0.10924653 | F44: =F11/F42 -> 0.15125143
A45: Post Tax return On capital | B45: =B38/B42 -> 0.057181626 | C45: =C38/C42 -> 0.065161551 | D45: =D38/D42 -> 0.074945296 | E45: =E38/E42 -> 0.076472571 | F45: =F38/F42 -> 0.105876
A47: Growth In EBIT | B47: =FCFF!B12*F45 -> 0.011522162

Sheet Forecasting
E2: Sales Forecasting | J2: EBITDA Forecasting | O2: Earning per share Forecasting
E3: Year Weight | F3: Year | G3: Sales | H3: Sales Growth | J3: Year Weight | K3: Year | L3: EBITDA | M3: EBITDA Growth | O3: Year Weight | P3: Year | Q3: EPS | R3: EPS Growth
E4: 1 | F4: 44621 | G4: ='Consolidated P&L'!B8 -> 156521.23 | J4: 1 | K4: 44621 | L4: ='Consolidated P&L'!B22+'Consolidated P&L'!B17+'Consolidated P&L'!B18 -> 20484.38 | O4: 1 | P4: 44621 | Q4: ='Consolidated P&L'!B36 -> 62
E5: 2 | F5: 44986 | G5: ='Consolidated P&L'!C8 -> 183340.7 | H5: =(G5-G4)/G4 -> 0.17134717 | J5: 2 | K5: 44986 | L5: ='Consolidated P&L'!C22+'Consolidated P&L'!C17+'Consolidated P&L'!C18 -> 23682.45 | M5: =(L5-L4)/L4 -> 0.15612237 | O5: 2 | P5: 44986 | Q5: ='Consolidated P&L'!C36 -> 75 | R5: =(Q5-Q4)/Q4 -> 0.20967742
E6: 3 | F6: 45352 | G6: ='Consolidated P&L'!D8 -> 221112.91 | H6: =(G6-G5)/G5 -> 0.20602196 | J6: 3 | K6: 45352 | L6: ='Consolidated P&L'!D22+'Consolidated P&L'!D17+'Consolidated P&L'!D18 -> 27651.68 | M6: =(L6-L5)/L5 -> 0.16760217 | O6: 3 | P6: 45352 | Q6: ='Consolidated P&L'!D36 -> 94 | R6: =(Q6-Q5)/Q5 -> 0.25333333
E7: 4 | F7: 45717 | G7: ='Consolidated P&L'!E8 -> 255734.45 | H7: =(G7-G6)/G6 -> 0.15657856 | J7: 4 | K7: 45717 | L7: ='Consolidated P&L'!E22+'Consolidated P&L'!E17+'Consolidated P&L'!E18 -> 30559.56 | M7: =(L7-L6)/L6 -> 0.10516106 | O7: 4 | P7: 45717 | Q7: ='Consolidated P&L'!E36 -> 109 | R7: =(Q7-Q6)/Q6 -> 0.15957447
E8: 5 | F8: 46082 | G8: ='Consolidated P&L'!F8 -> 285874.36 | H8: =(G8-G7)/G7 -> 0.11785628 | J8: 5 | K8: 46082 | L8: ='Consolidated P&L'!F22+'Consolidated P&L'!F17+'Consolidated P&L'!F18 -> 41907.16 | M8: =(L8-L7)/L7 -> 0.37132734 | O8: 5 | P8: 46082 | Q8: ='Consolidated P&L'!F36 -> 117 | R8: =(Q8-Q7)/Q7 -> 0.073394495
E9: 6 | F9: 46447 | G9: =FORECAST(E9,$G$4:$G$8,$E$4:$E$8) -> 319846.73 | H9: =(G9-G8)/G8 -> 0.11883673 | J9: 6 | K9: 46447 | L9: =FORECAST(J9,$L$4:$L$8,$J$4:$J$8) -> 43773.847 | M9: =(L9-L8)/L8 -> 0.044543391 | O9: 6 | P9: 46447 | Q9: =FORECAST(O9,$Q$4:$Q$8,$O$4:$O$8) -> 134.6 | R9: =(Q9-Q8)/Q8 -> 0.15042735
E10: 7 | F10: 46813 | G10: =FORECAST(E10,$G$4:$G$8,$E$4:$E$8) -> 352956.73 | H10: =(G10-G9)/G9 -> 0.10351833 | J10: 7 | K10: 46813 | L10: =FORECAST(J10,$L$4:$L$8,$J$4:$J$8) -> 48746.114 | M10: =(L10-L9)/L9 -> 0.1135899 | O10: 7 | P10: 46813 | Q10: =FORECAST(O10,$Q$4:$Q$8,$O$4:$O$8) -> 149 | R10: =(Q10-Q9)/Q9 -> 0.10698366
E11: 8 | F11: 47178 | G11: =FORECAST(E11,$G$4:$G$8,$E$4:$E$8) -> 386066.73 | H11: =(G11-G10)/G10 -> 0.093807534 | J11: 8 | K11: 47178 | L11: =FORECAST(J11,$L$4:$L$8,$J$4:$J$8) -> 53718.381 | M11: =(L11-L10)/L10 -> 0.10200335 | O11: 8 | P11: 47178 | Q11: =FORECAST(O11,$Q$4:$Q$8,$O$4:$O$8) -> 163.4 | R11: =(Q11-Q10)/Q10 -> 0.096644295
E12: 9 | F12: 47543 | G12: =FORECAST(E12,$G$4:$G$8,$E$4:$E$8) -> 419176.74 | H12: =(G12-G11)/G11 -> 0.085762377 | J12: 9 | K12: 47543 | L12: =FORECAST(J12,$L$4:$L$8,$J$4:$J$8) -> 58690.648 | M12: =(L12-L11)/L11 -> 0.092561743 | O12: 9 | P12: 47543 | Q12: =FORECAST(O12,$Q$4:$Q$8,$O$4:$O$8) -> 177.8 | R12: =(Q12-Q11)/Q11 -> 0.088127295
E13: 10 | F13: 47908 | G13: =FORECAST(E13,$G$4:$G$8,$E$4:$E$8) -> 452286.74 | H13: =(G13-G12)/G12 -> 0.078988165 | J13: 10 | K13: 47908 | L13: =FORECAST(J13,$L$4:$L$8,$J$4:$J$8) -> 63662.915 | M13: =(L13-L12)/L12 -> 0.08471992 | O13: 10 | P13: 47908 | Q13: =FORECAST(O13,$Q$4:$Q$8,$O$4:$O$8) -> 192.2 | R13: =(Q13-Q12)/Q12 -> 0.080989876
E15: Historical Avg Growth | G15: =AVERAGE(H5:H8) -> 0.16295099 | J15: Historical Avg Growth | L15: =AVERAGE(M5:M8) -> 0.20005323 | O15: Historical Avg Growth | Q15: =AVERAGE(R5:R8) -> 0.17399493
E16: Forecast Avg Growth | G16: =AVERAGE(H9:H13) -> 0.096182627 | J16: Forecast Avg Growth | L16: =AVERAGE(M9:M13) -> 0.087483662 | O16: Forecast Avg Growth | Q16: =AVERAGE(R9:R13) -> 0.10463449

Sheet Growth Scenario
A1: Scenario 1: High Growth
A2: INR Cr. | B2: LTM | C2: Y1E | D2: Y2E | E2: Y3E | F2: Y4W | G2: Y5E | H2: Y6E | I2: Y7E | J2: Y8E | K2: Y9E | L2: Y10E
A3: Sales | B3: =Assumptions!F3 -> 285874.36 | C3: =B3*(1+C4) -> 322474.66 | D3: =C3*(1+D4) -> 361412.93 | E3: =D3*(1+E4) -> 402421.46 | F3: =E3*(1+F4) -> 445153.07 | G3: =F3*(1+G4) -> 489181.02 | H3: =G3*(1+H4) -> 534001.81 | I3: =H3*(1+I4) -> 579041.18 | J3: =I3*(1+J4) -> 623663.29 | ... L3: =K3*(1+L4) -> 708882.11 | M3: CAGR | N3: =Assumptions!B25 -> 0.12802933 | P3: Risk free rate
A4: Sales Growth % | C4: =N3 -> 0.12802933 | D4: =C4-$O$4 -> 0.12074829 | E4: =D4-$O$4 -> 0.11346725 | F4: =E4-$O$4 -> 0.10618622 | G4: =F4-$O$4 -> 0.098905181 | H4: =G4-$O$4 -> 0.091624145 | I4: =H4-$O$4 -> 0.084343109 | J4: =I4-$O$4 -> 0.077062073 | K4: =J4-$O$4 -> 0.069781036 | L4: =K4-$O$4 -> 0.0625 | M4: =P4 -> 0.0625 | N4: =N3-M4 -> 0.065529327 | O4: =N4/9 -> 0.0072810363 | P4: =Wacc!B10 -> 0.0625
A6: Scenario 2: Average Growth
A7: INR Cr. | B7: LTM | C7: Y1E | D7: Y2E | E7: Y3E | F7: Y4W | G7: Y5E | H7: Y6E | I7: Y7E | J7: Y8E | K7: Y9E | L7: Y10E | M7: Average rate | N7: =Assumptions!B24 -> 0.16295099
A8: Sales | B8: =B3 -> 285874.36 | C8: =B8*(1+C9) -> 332457.87 | D8: =C8*(1+D9) -> 382921.57 | E8: =D8*(1+E9) -> 436771.28 | F8: =E8*(1+F9) -> 493318.89 | G8: =F8*(1+G9) -> 551681.52 | H8: =G8*(1+H9) -> 610791.38 | I8: =H8*(1+I9) -> 669417.37 | J8: =I8*(1+J9) -> 726198.99 | ... L8: =K8*(1+L9) -> 828422.42 | N8: =M4 -> 0.0625 | O8: =N7-N8 -> 0.10045099 | P8: =O8/9 -> 0.011161221
A9: Sales Growth % | C9: =N7 -> 0.16295099 | D9: =C9-$P$8 -> 0.15178977 | E9: =D9-$P$8 -> 0.14062855 | F9: =E9-$P$8 -> 0.12946733 | G9: =F9-$P$8 -> 0.11830611 | H9: =G9-$P$8 -> 0.10714488 | I9: =H9-$P$8 -> 0.095983663 | J9: =I9-$P$8 -> 0.084822442 | K9: =J9-$P$8 -> 0.073661221 | L9: =K9-$P$8 -> 0.0625
A11: Scenario 3: EBIT Growth
A12: INR Cr. | B12: LTM | C12: Y1E | D12: Y2E | E12: Y3E | F12: Y4W | G12: Y5E | H12: Y6E | I12: Y7E | J12: Y8E | K12: Y9E | L12: Y10E | N12: =Assumptions!B47 -> 0.011522162
A13: Sales | B13: =B8 -> 285874.36 | C13: =B13*(1+C14) -> 289168.25 | D13: =C13*(1+D14) -> 294138 | E13: =D13*(1+E14) -> 300859.22 | F13: =E13*(1+F14) -> 309438.16 | G13: =F13*(1+G14) -> 320014.44 | H13: =G13*(1+H14) -> 332764.83 | I13: =H13*(1+I14) -> 347908.09 | J13: =I13*(1+J14) -> 365711.1 | ... L13: =K13*(1+L14) -> 410652.62 | N13: =N8 -> 0.0625 | O13: =N12-N13 -> -0.050977838 | P13: =O13/9 -> -0.0056642042
A14: Sales Growth % | C14: =N12 -> 0.011522162 | D14: =(C14)-($P$13) -> 0.017186366 | E14: =(D14)-($P$13) -> 0.02285057 | F14: =(E14)-($P$13) -> 0.028514775 | G14: =(F14)-($P$13) -> 0.034178979 | H14: =(G14)-($P$13) -> 0.039843183 | I14: =(H14)-($P$13) -> 0.045507387 | J14: =(I14)-($P$13) -> 0.051171592 | K14: =(J14)-($P$13) -> 0.056835796 | L14: =(K14)-($P$13) -> 0.0625
A16: Live Scenario | B16: 3
A17: INR Cr. | C17: Y1E | D17: Y2E | E17: Y3E | F17: Y4W | G17: Y5E | H17: Y6E | I17: Y7E | J17: Y8E | K17: Y9E | L17: Y10E
A18: Sales | B18: =B13 -> 285874.36 | C18: =B18*(1+C19) -> 289168.25 | D18: =C18*(1+D19) -> 294138 | E18: =D18*(1+E19) -> 300859.22 | F18: =E18*(1+F19) -> 309438.16 | G18: =F18*(1+G19) -> 320014.44 | H18: =G18*(1+H19) -> 332764.83 | I18: =H18*(1+I19) -> 347908.09 | J18: =I18*(1+J19) -> 365711.1 | ... L18: =K18*(1+L19) -> 410652.62
A19: Sales Growth % | C19: =CHOOSE($B$16,C4,C9,C14) -> 0.011522162 | D19: =CHOOSE($B$16,D4,D9,D14) -> 0.017186366 | E19: =CHOOSE($B$16,E4,E9,E14) -> 0.02285057 | F19: =CHOOSE($B$16,F4,F9,F14) -> 0.028514775 | G19: =CHOOSE($B$16,G4,G9,G14) -> 0.034178979 | H19: =CHOOSE($B$16,H4,H9,H14) -> 0.039843183 | I19: =CHOOSE($B$16,I4,I9,I14) -> 0.045507387 | J19: =CHOOSE($B$16,J4,J9,J14) -> 0.051171592 | ... L19: =CHOOSE($B$16,L4,L9,L14) -> 0.0625
A21: Growth Rate (g = ROE x Retention Ratio)
A22: Dividend Per Share (Rs.) | B22: ='Consolidated P&L'!E39*'Consolidated P&L'!E36/'Consolidated P&L'!E34 -> 27.904506
A23: EPS (Rs.) | B23: ='Consolidated P&L'!E36 -> 109
A24: ROE | B24: =Assumptions!F17/SUM('Consolidated Balance sheet'!F6,'Consolidated Balance sheet'!F9) -> 0.16480907
A25: Payout Ratio (DPR) | B25: =B22/B23 -> 0.25600464 | C25: DPS/EPS
A26: Retention Ratio (b = 1 - DPR) | B26: =1-B25 -> 0.74399536
A28: Growth Rate (g) | B28: =B26*B24 -> 0.12261718

Sheet DCF Valuation
C1: 1 | D1: 2 | E1: 3 | F1: 4 | G1: 5 | H1: 6 | I1: 7 | J1: 8 | K1: 9 | L1: 10
A2: INR Cr | B2: LTM | C2: Y1E | D2: Y2E | E2: Y3E | F2: Y4E | G2: Y5E | H2: Y6E | I2: Y7E | J2: Y8E | K2: Y9E | L2: Y10E | N2: Terminal Year | P2: Terminal growth rate % | Q2: 0.04
A3: Sales | B3: ='Growth Scenario'!B18 -> 285874.36 | C3: ='Growth Scenario'!C18 -> 289168.25 | D3: ='Growth Scenario'!D18 -> 294138 | E3: ='Growth Scenario'!E18 -> 300859.22 | F3: ='Growth Scenario'!F18 -> 309438.16 | G3: ='Growth Scenario'!G18 -> 320014.44 | H3: ='Growth Scenario'!H18 -> 332764.83 | I3: ='Growth Scenario'!I18 -> 347908.09 | ... L3: ='Growth Scenario'!L18 -> 410652.62 | N3: =L3*(1+$Q$2) -> 427078.72 | P3: Cost of Capital % | Q3: =Wacc!D26 -> 0.10473218
A4: Sales Growth | C4: ='Growth Scenario'!C19 -> 0.011522162 | D4: ='Growth Scenario'!D19 -> 0.017186366 | E4: ='Growth Scenario'!E19 -> 0.02285057 | F4: ='Growth Scenario'!F19 -> 0.028514775 | G4: ='Growth Scenario'!G19 -> 0.034178979 | H4: ='Growth Scenario'!H19 -> 0.039843183 | I4: ='Growth Scenario'!I19 -> 0.045507387 | J4: ='Growth Scenario'!J19 -> 0.051171592 | ... L4: ='Growth Scenario'!L19 -> 0.0625 | N4: =$Q$2 -> 0.04 | P4: Terminal reinvestment rate % | Q4: =Q2*Q3 -> 0.0041892872
A5: EBIT | C5: =C3*C6 -> 27741.187 | D5: =D3*D6 -> 28217.957 | E5: =E3*E6 -> 28862.753 | F5: =F3*F6 -> 29685.768 | G5: =G3*G6 -> 30700.397 | H5: =H3*H6 -> 31923.599 | I5: =I3*I6 -> 33376.359 | J5: =J3*J6 -> 35084.28 | ... L5: =L3*L6 -> 39395.718 | N5: =N6*N3 -> 40971.547
A6: EBIT Margin % | C6: =AVERAGE(Assumptions!B29:F29) -> 0.095934414 | D6: =C6 -> 0.095934414 | E6: =D6 -> 0.095934414 | F6: =E6 -> 0.095934414 | G6: =F6 -> 0.095934414 | H6: =G6 -> 0.095934414 | I6: =H6 -> 0.095934414 | J6: =I6 -> 0.095934414 | K6: =J6 -> 0.095934414 | L6: =K6 -> 0.095934414 | N6: =L6 -> 0.095934414 | P6: Enterprise value = Equity Value + Minority interest
A7: Less: Tax on EBIT | C7: =Assumptions!$B$35*C5 -> 8322.356 | D7: =Assumptions!$B$35*D5 -> 8465.3871 | E7: =Assumptions!$B$35*E5 -> 8658.826 | F7: =Assumptions!$B$35*F5 -> 8905.7305 | G7: =Assumptions!$B$35*G5 -> 9210.1192 | H7: =Assumptions!$B$35*H5 -> 9577.0797 | I7: =Assumptions!$B$35*I5 -> 10012.908 | J7: =Assumptions!$B$35*J5 -> 10525.284 | ... L7: =Assumptions!$B$35*L5 -> 11818.715 | N7: =Assumptions!$B$35*N5 -> 12291.464
A8: EBIT(1-T) | C8: =C5-C7 -> 19418.831 | D8: =D5-D7 -> 19752.57 | E8: =E5-E7 -> 20203.927 | F8: =F5-F7 -> 20780.038 | G8: =G5-G7 -> 21490.278 | H8: =H5-H7 -> 22346.519 | I8: =I5-I7 -> 23363.451 | J8: =J5-J7 -> 24558.996 | ... L8: =L5-L7 -> 27577.003 | N8: =N5-N7 -> 28680.083
A9: Less: Net Capital Expenditure | C9: =C3*'Fixed Assets scheduled'!$C$11 -> 293.95275 | D9: =D3*'Fixed Assets scheduled'!$C$11 -> 299.00473 | E9: =E3*'Fixed Assets scheduled'!$C$11 -> 305.83716 | F9: =F3*'Fixed Assets scheduled'!$C$11 -> 314.55804 | G9: =G3*'Fixed Assets scheduled'!$C$11 -> 325.30931 | H9: =H3*'Fixed Assets scheduled'!$C$11 -> 338.27067 | I9: =I3*'Fixed Assets scheduled'!$C$11 -> 353.66448 | J9: =J3*'Fixed Assets scheduled'!$C$11 -> 371.76206 | ... L9: =L3*'Fixed Assets scheduled'!$C$11 -> 417.44716
A10: Non Cash Working Capital | B10: ='Change in working capital'!F5 -> 536.56 | C10: ='Change in working capital'!$C$9*C3 -> 1028.2527 | D10: ='Change in working capital'!$C$9*D3 -> 1045.9246 | E10: ='Change in working capital'!$C$9*E3 -> 1069.8246 | F10: ='Change in working capital'!$C$9*F3 -> 1100.3304 | G10: ='Change in working capital'!$C$9*G3 -> 1137.9385 | H10: ='Change in working capital'!$C$9*H3 -> 1183.2776 | I10: ='Change in working capital'!$C$9*I3 -> 1237.1255 | J10: ='Change in working capital'!$C$9*J3 -> 1300.4312 | ... L10: ='Change in working capital'!$C$9*L3 -> 1460.2386
A11: Less: Change in Working Capital | C11: =C10-B10 -> 491.69267 | D11: =D10-C10 -> 17.671927 | E11: =E10-D10 -> 23.899974 | F11: =F10-E10 -> 30.505807 | G11: =G10-F10 -> 37.608169 | H11: =H10-G10 -> 45.339094 | I11: =I10-H10 -> 53.847874 | J11: =J10-I10 -> 63.305681 | ... L11: =L10-K10 -> 85.89639
A12: Reinvestment | C12: =C9+C11 -> 785.64542 | D12: =D9+D11 -> 316.67666 | E12: =E9+E11 -> 329.73713 | F12: =F9+F11 -> 345.06384 | G12: =G9+G11 -> 362.91748 | H12: =H9+H11 -> 383.60976 | I12: =I9+I11 -> 407.51235 | J12: =J9+J11 -> 435.06774 | ... L12: =L9+L11 -> 503.34355 | N12: =N8*N14 -> 120.1491
A13: Free Cash Flow To Firm (FCFF) | C13: =C8-C12 -> 18633.185 | D13: =D8-D12 -> 19435.893 | E13: =E8-E12 -> 19874.19 | F13: =F8-F12 -> 20434.974 | G13: =G8-G12 -> 21127.361 | H13: =H8-H12 -> 21962.91 | I13: =I8-I12 -> 22955.939 | J13: =J8-J12 -> 24123.928 | ... L13: =L8-L12 -> 27073.659 | N13: =N8-N12 -> 28559.934
A14: Implied Reinvestment rate % | C14: =C13/C8 -> 0.95954208 | D14: =D13/D8 -> 0.98396782 | E14: =E13/E8 -> 0.98367955 | F14: =F13/F8 -> 0.98339446 | G14: =G13/G8 -> 0.98311248 | H14: =H13/H8 -> 0.98283358 | I14: =I13/I8 -> 0.9825577 | J14: =J13/J8 -> 0.98228479 | ... L14: =L13/L8 -> 0.98174771 | N14: =$Q$4 -> 0.0041892872
A16: Terminal Value | L16: =L13/(Q3-Q2) -> 418241.12
A18: Present Value Interest Factor(PVIF) | C18: =1/(1+$Q$3)^C1 -> 0.90519677 | D18: =1/(1+$Q$3)^D1 -> 0.81938119 | E18: =1/(1+$Q$3)^E1 -> 0.74170121 | F18: =1/(1+$Q$3)^F1 -> 0.67138554 | G18: =1/(1+$Q$3)^G1 -> 0.60773602 | H18: =1/(1+$Q$3)^H1 -> 0.55012068 | I18: =1/(1+$Q$3)^I1 -> 0.49796746 | J18: =1/(1+$Q$3)^J1 -> 0.45075854 | ... L18: =1/(1+$Q$3)^L1 -> 0.36934307
A20: Present value of FCFF | C20: =SUMPRODUCT(C18:L18,C13:L13) -> 128879.27
A21: Present value of Terminal value | C21: =L16*L18 -> 154474.46
H22: Calculation of Sensitivity Analysis
A23: Value of operating assets | C23: =C20+C21 -> 283353.73 | H23: Terminal Growth ↓ / WACC →
A24: Add: Cash | C24: =Assumptions!F41 -> 20847.67 | H24: =C30 -> 1187.7334 | I24: =J24-1% -> 0.08473218 | J24: =K24-1% -> 0.09473218 | K24: =$Q$3 -> 0.10473218 | L24: =K24+1% -> 0.11473218 | M24: =L24+1% -> 0.12473218
A25: Less: Debt | C25: =Assumptions!F40 -> 121683.02 | H25: =H26-1% -> 0.02 | I25: 1504.17 | J25: 1174.02 | K25: 922.5 | L25: 724.66 | M25: 565.09
A26: Less: Minority Interest | C26: ='Consolidated Balance sheet'!F13 -> 19240.66 | H26: =H27-1% -> 0.03 | I26: 1750.63 | J26: 1338.69 | K26: 1037.37 | L26: 807.47 | M26: 626.37
A27: Equity Value | C27: =C23+C24-C25-C26 -> 163277.72 | H27: =$Q$2 -> 0.04 | I27: 2107.29 | J27: 1563.55 | K27: 1187.73 | L27: 912.45 | M27: 702.1
H28: =H27+1% -> 0.05 | I28: 2669.32 | J28: 1888.93 | K28: 1393.04 | L28: 1049.85 | M28: 798.11
A29: No. of Shares outstanding (Cr) | C29: ='Consolidated P&L'!F34/'Consolidated P&L'!F36 -> 137.47 | H29: =H28+1% -> 0.06 | I29: 3685.85 | J29: 2401.68 | K29: 1690.14 | L29: 1237.47 | M29: 923.77
A30: intrinsic value per share | C30: =C27/C29 -> 1187.7334

Sheet Relative Valuation
A1: RELATIVE VALUATION – L&T (FY2025 | INR Crores)
A3: Company | B3: Market Data | F3: Financial Data | J3: Valuation Ratios
B4: Price (₹) | C4: Shares (Cr.) | D4: Mkt Cap (Cr.) | E4: EV (Cr.) | F4: Revenue (Cr.) | G4: EBITDA (Cr.) | H4: EBIT (Cr.) | I4: EPS (₹) | J4: P/E | K4: EV/Sales | L4: EV/EBITDA | M4: EV/EBIT
A5: Larsen & Toubro | B5: 4207.7 | C5: ='Consolidated Balance sheet'!I6 -> 137.52 | D5: =B5*C5 -> 578642.9 | E5: =D5+'Consolidated Balance sheet'!E15+'Consolidated Balance sheet'!E21-'Consolidated Balance sheet'!E43-'Consolidated Balance sheet'!E40 -> 641876.28 | F5: =Assumptions!E3 -> 255734.45 | G5: =Assumptions!E9 -> 26434.74 | H5: =Assumptions!E11 -> 22313.56 | I5: ='Consolidated P&L'!E36 -> 109 | J5: =B5/I5 -> 38.602752 | K5: =E5/F5 -> 2.5099328 | L5: =E5/G5 -> 24.281543 | M5: =E5/H5 -> 28.766198
A6: Rail Vikas | B6: 245.14 | C6: =D6/B6 -> 208.45011 | D6: 51099.46 | E6: 54950 | F6: 20412 | G6: 767 | H6: =1181+419 -> 1600 | I6: 4.2 | J6: =B6/I6 -> 58.366667 | K6: =E6/F6 -> 2.6920439 | L6: =E6/G6 -> 71.642764 | M6: =E6/H6 -> 34.34375
A7: NBCC | B7: 112.83 | C7: =D7/B7 -> 269.97527 | D7: 30461.31 | E7: 23946 | F7: 12889 | G7: 617 | H7: =991 -> 991 | I7: 2.67 | J7: =B7/I7 -> 42.258427 | K7: =E7/F7 -> 1.8578633 | L7: =E7/G7 -> 38.810373 | M7: =E7/H7 -> 24.163471
A8: IRB Infra.Devl. | B8: 21.34 | C8: =D8/B8 -> 1207.7999 | D8: 25774.45 | E8: 43891 | F8: 7648 | G8: 3982 | H8: =1248+1755 -> 3003 | I8: 0.7 | J8: =B8/I8 -> 30.485714 | K8: =E8/F8 -> 5.738886 | L8: =E8/G8 -> 11.022351 | M8: =E8/H8 -> 14.615718
A9: Kalpataru Proj. | B9: 1369.3 | C9: =D9/B9 -> 17.073505 | D9: 23378.75 | E9: 25079 | F9: 27143 | G9: 2240 | H9: =1371+501 -> 1872 | I9: 60.9 | J9: =B9/I9 -> 22.484401 | K9: =E9/F9 -> 0.92395829 | L9: =E9/G9 -> 11.195982 | M9: =E9/H9 -> 13.396902
A10: Peer Average | B10: =AVERAGE(B6:B9) -> 437.1525 | C10: =AVERAGE(C6:C9) -> 425.8247 | D10: =AVERAGE(D6:D9) -> 32678.493 | E10: =AVERAGE(E6:E9) -> 36966.5 | F10: =AVERAGE(F6:F9) -> 17023 | G10: =AVERAGE(G6:G9) -> 1901.5 | H10: =AVERAGE(H6:H9) -> 1866.5 | I10: =AVERAGE(I6:I9) -> 17.1175 | ... M10: =AVERAGE(M6:M9) -> 21.62996
A11: Peer Median | B11: =MEDIAN(B6:B9) -> 178.985 | C11: =MEDIAN(C6:C9) -> 239.21269 | D11: =MEDIAN(D6:D9) -> 28117.88 | E11: =MEDIAN(E6:E9) -> 34485 | F11: =MEDIAN(F6:F9) -> 16650.5 | G11: =MEDIAN(G6:G9) -> 1503.5 | H11: =MEDIAN(H6:H9) -> 1736 | I11: =MEDIAN(I6:I9) -> 3.435 | ... M11: =MEDIAN(M6:M9) -> 19.389594
A13: NMDC — IMPLIED SHARE PRICE FROM PEER MULTIPLES
A14: Valuation Basis | B14: Peer Avg Multiple | C14: Peer Median Multiple | D14: NMDC Actual | E14: Implied EV (Avg) | F14: Implied EV (Median) | G14: Implied Equity (Avg) | H14: Implied Equity (Median) | I14: Implied Price (Avg) ₹ | J14: Implied Price (Med) ₹ | K14: CMP ₹ | L14: Premium/Disc (vs Avg) | M14: Premium/Disc (vs Med)
A15: EV / Sales | B15: =K10 -> 2.8031879 | C15: =K11 -> 2.2749536 | D15: =K5 -> 2.5099328 | E15: =B15*F5 -> 716871.71 | F15: =C15*F5 -> 581784.01 | G15: =E15-(E5-D5) -> 653638.33 | H15: =F15-(E5-D5) -> 518550.63 | I15: =G15/C5 -> 4753.0419 | J15: =H15/C5 -> 3770.7288 | K15: =B5 -> 4207.7 | L15: =(B5-I15)/I15 -> -0.11473535 | M15: =(B5-J15)/J15 -> 0.11588507
A16: EV / EBITDA | B16: =L10 -> 33.167867 | C16: =L11 -> 25.003177 | D16: =L5 -> 24.281543 | E16: =B16*G5 -> 876783.95 | F16: =C16*G5 -> 660952.5 | G16: =E16-(E5-D5) -> 813550.57 | H16: =F16-(E5-D5) -> 597719.12 | I16: =G16/C5 -> 5915.8709 | J16: =H16/C5 -> 4346.4159 | K16: =K15 -> 4207.7 | L16: =(B5-I16)/I16 -> -0.28874378 | M16: =(B5-J16)/J16 -> -0.03191501
A17: P / E | B17: =J10 -> 38.398802 | C17: =J11 -> 36.372071 | D17: =J5 -> 38.602752 | E17: =B17*I5 -> 4185.4694 | F17: =C17*I5 -> 3964.5557 | G17: =E17*C5 -> 575585.76 | H17: =F17*C5 -> 545205.7 | I17: =E17 -> 4185.4694 | J17: =F17 -> 3964.5557 | K17: =K16 -> 4207.7 | L17: =(B5-I17)/I17 -> 0.0053113675 | M17: =(B5-J17)/J17 -> 0.061329521
O19: EV/Revenue | P19: EV/EBITDA | Q19: P/E Ratio
A20: Max | O20: =MAX(K6:K9) -> 5.738886 | P20: =MAX(L6:L9) -> 71.642764 | Q20: =MAX(J6:J9) -> 58.366667
A21: 75th Percentile | O21: =QUARTILE(K6:K9,3) -> 3.4537544 | P21: =QUARTILE(L6:L9,3) -> 47.018471 | Q21: =QUARTILE(J6:J9,3) -> 46.285487
A22: Average | O22: =AVERAGE(K6:K9) -> 2.8031879 | P22: =AVERAGE(L6:L9) -> 33.167867 | Q22: =AVERAGE(J6:J9) -> 38.398802
A23: median | O23: =MEDIAN(K6:K9) -> 2.2749536 | P23: =MEDIAN(L6:L9) -> 25.003177 | Q23: =MEDIAN(J6:J9) -> 36.372071
A24: 25th Percentile | O24: =QUARTILE(K6:K9,1) -> 1.624387 | P24: =QUARTILE(L6:L9,1) -> 11.152574 | Q24: =QUARTILE(J6:J9,1) -> 28.485386
A25: Min. | O25: =MIN(K6:K9) -> 0.92395829 | P25: =MIN(L6:L9) -> 11.022351 | Q25: =MIN(J6:J9) -> 22.484401
A27: Industry Comparable comps | O27: EV/Revenue | P27: EV/EBITDA | Q27: P/E Ratio
A29: Implied Enterprise Value | O29: =O22*F5 -> 716871.71 | P29: =P22*G5 -> 876783.95 | Q29: =Q22*I5*C5 -> 575585.76
A30: Net Debt | O30: =E5-D5 -> 63233.38 | P30: =E5-D5 -> 63233.38 | Q30: =E5-D5 -> 63233.38
A31: Implied Market Value | O31: =O29-O30 -> 653638.33 | P31: =P29-P30 -> 813550.57 | Q31: =Q29-Q30 -> 512352.38
A32: Share Outstanding | O32: =C5 -> 137.52 | P32: =C5 -> 137.52 | Q32: =C5 -> 137.52
A34: Implied Value per Share | O34: =O31/O32 -> 4753.0419 | P34: =P31/P32 -> 5915.8709 | Q34: =Q22*I5 -> 4185.4694

Sheet Stock Analysis
A1: Metric | B1: Value | D1: Financial Year | E1: Revenue (₹ Crore) | F1: Profit After Tax (PAT) (₹ Crore) | G1: Revenue Change (%) | H1: PAT Change (%) | I1: Nifty 50 Change (%) | J1: Nifty 50 Prices
A2: Market Cap | B2: ₹ 5,74,683 | D2: FY 2025-26 | E2: 285874 | F2: 18954 | G2: =(E2-E3)/E3 -> 0.11785684 | H2: =(G2-G3)/G3 -> -0.24728695 | I2: =(J2-J3)/J3 -> -0.01001941 | J2: 23283.7
A3: Current Price | B3: ₹ 4,177 | D3: FY 2024-25 | E3: 255734 | F3: 17673 | G3: =(E3-E4)/E4 -> 0.15657605 | H3: =(G3-G4)/G4 -> -0.23999763 | I3: =(J3-J4)/J4 -> 0.053408668 | J3: 23519.35
A4: High / Low | B4: ₹ 4,440 / 3,288 | D4: FY 2023-24 | E4: 221113 | F4: 15547 | G4: =(E4-E5)/E5 -> 0.20602048 | H4: =(G4-G5)/G5 -> 0.2023315 | I4: =(J4-J5)/J5 -> 0.28613027 | J4: 22326.9
A5: Stock P/E | B5: ='Relative Valuation'!J5 -> 38.602752 | D5: FY 2022-23 | E5: 183341 | F5: 12531 | G5: =(E5-E6)/E6 -> 0.17135081 | H5: =(F5-F6)/F6 -> 0.20270659 | I5: =(J5-J6)/J6 -> -0.0060121101 | J5: 17359.75
A6: Book Value | B6: ₹ 794 | D6: FY 2021-22 | E6: 156521 | F6: 10419 | J6: 17464.75
A7: Dividend Yield | B7: 0.89 %
A8: ROCE | B8: 14.6 %
A9: ROE | B9: 15.9 %
A10: Face Value | B10: ₹ 2.00
A12: INVESTMENT VIEW & RECOMMENDATION
A14: Investment Thesis — Why It Works
A15: • Record order book of ₹7,40,327 Cr (+27.8% YoY) and all-time-high order inflows of ₹4,35,590 Cr (+22.1% YoY) provide multi-year revenue visibility, with international orders contributing 58% of FY26 inflows.
A16: • Revenue grew 11.8% YoY to ₹2,85,874 Cr — the fastest pace in three years — while EBITDA margin expanded to 10.2%, an early sign of operating leverage coming through in the Infrastructure & Energy segments.
A17: • Balance sheet is de-risking: Net Debt:Equity improved to 0.35:1 from 0.60:1 in FY25, aided by monetising non-core, capital-heavy assets (Nabha Power sale to Torrent Power; Hyderabad Metro stake divestment).
A18: • New-age bets — L&T Semiconductor Technologies, L&T Vyoma data centres, and a 51% green portfolio — add optional, longer-duration growth levers beyond the core EPC cycle as the Lakshya 2031 plan is finalised.
A21: Key Risks & Watch-Points
A22: • Stock trades at ~38.6x trailing P/E and ~5.3x Book Value — in line with peer average P/E (38.4x) but leaving little room for de-rating if order-to-revenue conversion slips or execution timelines stretch.
A23: • Under the model's conservative ‘EBIT Growth’ live scenario, DCF intrinsic value works out to just ~₹1,188/share — a reminder that a large part of the current price already bakes in continued high growth.
A24: • Dividend yield is low (0.89%), so returns depend almost entirely on earnings growth and re-rating playing out as expected — this is a growth bet, not an income one.
A27: Valuation Snapshot (linked to DCF & Relative Valuation sheets)
A28: Valuation Basis | E28: Implied Value / Share (₹) | Premium / (Discount) to CMP
A29: Current Market Price (CMP) | E29: ='Relative Valuation'!B5 -> 4207.7 | H29: —
A30: P/E — Peer Average (~38x) | E30: ='Relative Valuation'!I17 -> 4185.4694 | H30: =(E30-E29)/E29 -> -0.0052833059
A31: EV/Sales — Peer Average | E31: ='Relative Valuation'!I15 -> 4753.0419 | H31: =(E31-E29)/E29 -> 0.12960571
A32: EV/EBITDA — Peer Average | E32: ='Relative Valuation'!I16 -> 5915.8709 | H32: =(E32-E29)/E29 -> 0.4059631
A33: DCF Intrinsic Value (conservative growth scenario) | E33: ='DCF Valuation'!C30 -> 1187.7334 | H33: =(E33-E29)/E29 -> -0.71772383
A36: RECOMMENDATION: BUY — ACCUMULATE ON DIPS | LONG-TERM (3+ YEAR HORIZON)
A38: L&T's FY26 operating performance — record order book, accelerating revenue, expanding margins and a de-leveraging balance sheet — supports a constructive long-term view. The Relative Valuation read-through (EV/Sales and EV/EBITDA implying ₹4,750–5,900/share) suggests the market is not over-paying for this growth, even though the stock isn't cheap at ~38x earnings on an absolute basis. A staggered, SIP-style entry is the more sensible way to build a position rather than a one-time lump-sum buy.
A39: Analyst note: The DCF intrinsic value (₹1,188) uses the most conservative of the three modelled Growth Scenarios (Sales CAGR ~1–6% vs. the order book's actual +27.8% YoY growth) and is best read as a downside stress-test, not the base-case fair value.
