Workbook

Sheet About the Company
E13: About the Company
E15: Message from the chairman -“Our strategic pivot to an AI-first approach has been instrumental in reimagining our operations and client relationships. By embedding AI in every aspect of our services, we have harnessed its power to enhance decisionmaking, optimize processes, and elevate customer experiences.” Who we are - As one of the world’s leading technology consulting and digital solutions enterprise, LTIMindtree enables businesses across diverse sectors to harness the power of digital technology to deal with complex business challenges, innovate at scale, and drive tangible business outcomes Services offering - Consulting, Enterprise Automation, Digital Engineering, Platform Operations, Low Code Integration, Enterprise Cloud Applications, Oracle, Data and Analytics, Cloud and Digital Infrastructure, Cybersecurity, Salesforce, Interactive, SAP, Quality Engineering Services, Enterprise AI, iNXT Industires Served - 1. Core / Strong Presence BFSI (Banking, Financial Services, Insurance) Technology sector 2. Expansion / Growth Industries Manufacturing, Resources (Energy & Utilities),Healthcare,Life Sciences,Media & Communications Consumer Business which include: Retail, Consumer Goods,Travel, Transport, Hospitality
E31: Subsidiaries
E32: S.No | F32: Company Name,Type,Country/Region
E33: 1 | F33: Larsen & Toubro Limited,Parent Company,India
E34: 2 | F34: L&T Infotech LLC,Subsidiary,USA
E35: 3 | F35: L&T Infotech GmbH,Subsidiary,Germany
E36: 4 | F36: L&T Infotech S.A.,Subsidiary,France
E37: 5 | F37: L&T Infotech (Canada) Limited,Subsidiary,Canada
E38: 6 | F38: L&T Infotech (UK) Limited,Subsidiary,UK
E39: 7 | F39: L&T Infotech (Singapore) Pte. Ltd.,Subsidiary,Singapore
E40: 8 | F40: L&T Infotech (Australia) Pty Ltd,Subsidiary,Australia
E41: 9 | F41: L&T Infotech (South Africa) (Pty) Ltd,Subsidiary,South Africa
E42: 10 | F42: Mindtree LLC,Subsidiary,USA
E43: 11 | F43: Mindtree Software Solutions (UK) Ltd,Subsidiary,UK
E44: 12 | F44: Mindtree Consulting Pte Ltd,Subsidiary,Singapore
... E46: 14 | F46: Mindtree GmbH,Subsidiary,Germany
E48: Registered Office
E49: L&T House, Ballard Estate, Mumbai – 400001, Maharashtra
E50: Technology Tower I, Powai, Mumbai – 400072
E51: Global Village, Mysore Road, Bengaluru – 560059
E54: Units
E55: Company | F55: Units Type | G55: Number | H55: Details
E56: LTIMindtree | F56: Offices | G56: 117 | H56: Across 41 countries
E57: LTIMindtree | F57: Countries | G57: 41 | H57: Global presence

Sheet Promoter
A1: Category & Name of Shareholder | B1: Entity Type | C1: No. of Shareholders | D1: No. of Fully Paid-Up Equity Shares held | E1: Partly paid up equity shares held | F1: No. of shares underlying Depository Receipts | G1: Total No. Shares held | H1: Shareholding Calculated as per SCRR , 1957 As a % of (A+B+C2) | I1: Number of Voting Rights held in each class of securities | M1: No. of Shares Underlying Outstanding convertible securities | N1: No. Of Shares Underlying Outstanding Warrants | O1: No. Of Outstanding ESOP Granted | P1: Total No. Of shares on fully diluted basis (including warrants, ESOP, Convertible Securities etc.) | Q1: Total Shareholding, as a% assuming full conversion of convertible securities ( as a percentage of diluted share capital) As a % of (A+B+C) | R1: No. of equity shares held in dematerialized form
I2: No. of Voting Rights | L2: Total as a % of Total Voting Rights
I3: Class X | J3: Class Y | K3: Total
A4: Promoter and Promoter Group | C4: 0 | H4: 0 | L4: 0 | Q4: 0
A5: A1) Indian | C5: 0 | H5: 0 | L5: 0 | Q5: 0
A6: Bodies Corporate | C6: 1 | D6: 203169279 | G6: 203169279 | H6: 68.53 | I6: 203169279 | K6: 203169279 | L6: 68.53 | P6: 203169279 | Q6: 68.46 | R6: 203169279
A7: Larsen And Toubro Limited | B7: 0 | C7: 0 | D7: 203169279 | G7: 203169279 | H7: 68.53 | I7: 203169279 | K7: 203169279 | L7: 0 | P7: 203169279 | Q7: 68.46 | R7: 203169279
A8: Sub-Total(A)(1) | C8: 1 | D8: 203169279 | G8: 203169279 | H8: 68.53 | I8: 203169279 | K8: 203169279 | L8: 68.53 | P8: 203169279 | Q8: 68.46 | R8: 203169279
A9: A2) Foreign | C9: 0 | H9: 0 | L9: 0 | Q9: 0
A10: Sub-Total(A)(2) | C10: 0 | H10: 0 | L10: 0 | Q10: 0
A11: Promoter and Promoter Group (A=A1+A2) | C11: 1 | D11: 203169279 | G11: 203169279 | H11: 68.53 | I11: 203169279 | K11: 203169279 | L11: 68.53 | P11: 203169279 | Q11: 68.46 | R11: 203169279
A12: Public | C12: 0 | H12: 0 | L12: 0 | Q12: 0
A13: B1) Institutions (Domestic) | C13: 0 | H13: 0 | L13: 0 | Q13: 0
A14: Mutual Funds | C14: 36 | D14: 13675751 | G14: 13675751 | H14: 4.61 | I14: 13675751 | K14: 13675751 | L14: 4.61 | P14: 13675751 | Q14: 4.61 | R14: 13675751
A15: Alternate Investment Funds | C15: 23 | D15: 447487 | G15: 447487 | H15: 0.15 | I15: 447487 | K15: 447487 | L15: 0.15 | P15: 447487 | Q15: 0.15 | R15: 447487
A16: Banks | C16: 5 | D16: 904 | G16: 904 | H16: 0 | I16: 904 | K16: 904 | L16: 0 | P16: 904 | Q16: 0 | R16: 904
A17: Insurance Companies | C17: 31 | D17: 32877824 | G17: 32877824 | H17: 11.09 | I17: 32877824 | K17: 32877824 | L17: 11.09 | P17: 32877824 | Q17: 11.08 | R17: 32877824
A18: LICI INDEX PLUS FLEXI GROWTH FUND | B18: 0 | C18: 0 | D18: 28388052 | G18: 28388052 | H18: 9.58 | I18: 28388052 | K18: 28388052 | L18: 0 | P18: 28388052 | Q18: 9.57 | R18: 28388052
A19: Provident Funds/ Pension Funds | C19: 1 | D19: 2819735 | G19: 2819735 | H19: 0.95 | I19: 2819735 | K19: 2819735 | L19: 0.95 | P19: 2819735 | Q19: 0.95 | R19: 2819735
A20: NBFCs registered with RBI | C20: 6 | D20: 8763 | G20: 8763 | H20: 0 | I20: 8763 | K20: 8763 | L20: 0 | P20: 8763 | Q20: 0 | R20: 8763
A21: Bodies Corporate | C21: 2 | D21: 294725 | G21: 294725 | H21: 0.1 | I21: 294725 | K21: 294725 | L21: 0.1 | P21: 294725 | Q21: 0.1 | R21: 294725
A22: Trust | C22: 9 | D22: 89214 | G22: 89214 | H22: 0.03 | I22: 89214 | K22: 89214 | L22: 0.03 | P22: 89214 | Q22: 0.03 | R22: 89214
A23: Sub-Total(B)(1) | C23: 113 | D23: 50214403 | G23: 50214403 | H23: 16.93 | I23: 50214403 | K23: 50214403 | L23: 16.93 | P23: 50214403 | Q23: 16.92 | R23: 50214403
A24: B2) Institutions (Foreign) | C24: 0 | H24: 0 | L24: 0 | Q24: 0
A25: Foreign Portfolio Investors Category I | C25: 455 | D25: 18667693 | G25: 18667693 | H25: 6.3 | I25: 18667693 | K25: 18667693 | L25: 6.3 | P25: 18667693 | Q25: 6.29 | R25: 18667693
A26: Foreign Portfolio Investors Category II | C26: 27 | D26: 620614 | G26: 620614 | H26: 0.21 | I26: 620614 | K26: 620614 | L26: 0.21 | P26: 620614 | Q26: 0.21 | R26: 620614
A27: Sub-Total(B)(2) | C27: 482 | D27: 19288307 | G27: 19288307 | H27: 6.51 | I27: 19288307 | K27: 19288307 | L27: 6.51 | P27: 19288307 | Q27: 6.5 | R27: 19288307
A28: B3) Central Government/ State Government(s)/ President of India | C28: 0 | H28: 0 | L28: 0 | Q28: 0
A29: Sub-Total(B)(3) | C29: 0 | H29: 0 | K29: - | L29: 0 | O29: - | P29: - | Q29: 0
A30: B4) Non-Institutions | C30: 0 | H30: 0 | L30: 0 | Q30: 0
A31: Investor Education and Protection Fund (IEPF) | C31: 1 | D31: 93849 | G31: 93849 | H31: 0.03 | I31: 93849 | K31: 93849 | L31: 0.03 | P31: 93849 | Q31: 0.03 | R31: 93849
A32: Resident Individuals holding nominal share capital up to Rs. 2 lakhs | C32: 360593 | D32: 15515724 | G32: 15515724 | H32: 5.23 | I32: 15515724 | K32: 15515724 | L32: 5.23 | P32: 15515724 | Q32: 5.23 | R32: 15510847
A33: Resident Individuals holding nominal share capital in excess of Rs. 2 lakhs | C33: 3 | D33: 1668088 | G33: 1668088 | H33: 0.56 | I33: 1668088 | K33: 1668088 | L33: 0.56 | P33: 1668088 | Q33: 0.56 | R33: 1668088
A34: Non Resident Indians (NRIs) | C34: 10595 | D34: 5434602 | G34: 5434602 | H34: 1.83 | I34: 5434602 | K34: 5434602 | L34: 1.83 | P34: 5434602 | Q34: 1.83 | R34: 5434152
A35: Foreign Nationals | C35: 17 | D35: 167612 | G35: 167612 | H35: 0.06 | I35: 167612 | K35: 167612 | L35: 0.06 | P35: 167612 | Q35: 0.06 | R35: 167612
A36: Bodies Corporate | C36: 1087 | D36: 410209 | G36: 410209 | H36: 0.14 | I36: 410209 | K36: 410209 | L36: 0.14 | N36: 291467 | O36: 291467 | P36: 701676 | Q36: 0.24 | R36: 410209
A37: Clearing Members | C37: 53 | D37: 27408 | G37: 27408 | H37: 0.01 | I37: 27408 | K37: 27408 | L37: 0.01 | P37: 27408 | Q37: 0.01 | R37: 27408
A38: Foreign Nationals | C38: 5 | D38: 20525 | G38: 20525 | H38: 0.01 | I38: 20525 | K38: 20525 | L38: 0.01 | P38: 20525 | Q38: 0.01
A39: HUF | C39: 7028 | D39: 323451 | G39: 323451 | H39: 0.11 | I39: 323451 | K39: 323451 | L39: 0.11 | P39: 323451 | Q39: 0.11 | R39: 323451
A40: LLP | C40: 131 | D40: 23674 | G40: 23674 | H40: 0.01 | I40: 23674 | K40: 23674 | L40: 0.01 | P40: 23674 | Q40: 0.01 | R40: 23674
A41: Non-Resident Indian (NRI) | C41: 20 | D41: 82427 | G41: 82427 | H41: 0.03 | I41: 82427 | K41: 82427 | L41: 0.03 | P41: 82427 | Q41: 0.03
A42: Trusts | C42: 8 | D42: 49687 | G42: 49687 | H42: 0.02 | I42: 49687 | K42: 49687 | L42: 0.02 | P42: 49687 | Q42: 0.02 | R42: 49687
A43: Sub-Total(B)(4) | C43: 379541 | D43: 23817256 | G43: 23817256 | H43: 8.04 | I43: 23817256 | K43: 23817256 | L43: 8.04 | N43: 291467 | O43: 291467 | P43: 24108723 | Q43: 8.14 | R43: 23708977
A44: Public (B=B1+B2+B3+B4) | C44: 380136 | D44: 93319966 | G44: 93319966 | H44: 31.48 | I44: 93319966 | K44: 93319966 | L44: 31.48 | N44: 291467 | O44: 291467 | P44: 93611433 | Q44: 31.56 | R44: 93211687
A45: (C) Non Promoter-Non Public | C45: 0 | H45: 0 | L45: 0 | Q45: 0
A46: C1) Custodian/DR Holder | C46: 0 | H46: 0 | L46: 0 | Q46: 0
A47: Sub-Total(C)(1) | C47: 0 | H47: 0 | K47: - | L47: 0 | Q47: 0
A48: C2) Employee Benefit Trust | C48: 0 | H48: 0 | L48: 0 | Q48: 0
A49: Sub-Total(C)(2) | C49: 0 | H49: 0 | K49: - | L49: 0 | Q49: 0
A50: Non Promoter-Non Public (C= C1+C2) | C50: 0 | H50: 0 | K50: - | L50: 0 | Q50: 0
A51: GRAND TOTAL | C51: 380137 | D51: 296489245 | G51: 296489245 | H51: 100.01 | I51: 296489245 | K51: 296489245 | L51: 100.01 | N51: 291467 | O51: 291467 | P51: 296780712 | Q51: 100.02 | R51: 296380966

Sheet Public
A1: Category & Name of the Shareholders | B1: No. of shareholder | C1: No. of fully paid up equity shares held | D1: Total no. shares held | E1: Shareholding % calculated as per SCRR, 1957 As a % of (A+B+C2) | F1: No. of Voting Rights | G1: Total as a % of Total Voting right | H1: No. Of Outstanding ESOP Granted | I1: Total No. Of shares on fully diluted basis (including warrants, ESOP, Convertible Securities etc.) | J1: Shareholding , as a % assuming full conversion of convertible securities ( as a percentage of diluted share capital)As a % of (A+B+C2) | K1: No. of equity shares held in dematerialized form(Not Applicable)
A5: Institutions | B5: 0 | C5: 0 | E5: 0 | G5: 0 | J5: 0
A6: B1) Institutions (Domestic) | B6: 0 | C6: 0 | E6: 0 | G6: 0 | J6: 0
A7: Mutual Funds/ | B7: 35 | C7: 12833231 | D7: 12833231 | E7: 4.33 | F7: 12833231 | G7: 4.33 | I7: 12833231 | J7: 4.32 | K7: 12833231
A8: Venture Capital Funds | B8: 0 | C8: 0 | E8: 0 | G8: 0 | J8: 0
A9: Alternate Investment Funds | B9: 13 | C9: 338888 | D9: 338888 | E9: 0.11 | F9: 338888 | G9: 0.11 | I9: 338888 | J9: 0.11 | K9: 338888
A10: Banks | B10: 4 | C10: 104 | D10: 104 | E10: 0 | F10: 104 | G10: 0 | I10: 104 | J10: 0 | K10: 104
A11: Insurance Companies | B11: 28 | C11: 33752317 | D11: 33752317 | E11: 11.38 | F11: 33752317 | G11: 11.38 | I11: 33752317 | J11: 11.37 | K11: 33752317
A12: Life Insurance Corporation Of India | B12: 1 | C12: 29061981 | D12: 29061981 | E12: 9.8 | F12: 29061981 | G12: 9.8 | I12: 29061981 | J12: 9.79 | K12: 29061981
A13: Provident Funds/ Pension Funds | B13: 1 | C13: 3197187 | D13: 3197187 | E13: 1.08 | F13: 3197187 | G13: 1.08 | I13: 3197187 | J13: 1.08 | K13: 3197187
A14: Nps Trust A/C Uti Pension Fund Limited-Scheme State Govt | B14: 1 | C14: 3197187 | D14: 3197187 | E14: 1.08 | F14: 3197187 | G14: 1.08 | I14: 3197187 | J14: 1.08 | K14: 3197187
A15: Asset reconstruction companies | B15: 0 | C15: 0 | E15: 0 | G15: 0 | J15: 0
A16: Sovereign Wealth Funds | B16: 2 | C16: 294725 | D16: 294725 | E16: 0.1 | F16: 294725 | G16: 0.1 | I16: 294725 | J16: 0.1 | K16: 294725
A17: NBFCs registered with RBI | B17: 4 | C17: 8338 | D17: 8338 | E17: 0 | F17: 8338 | G17: 0 | I17: 8338 | J17: 0 | K17: 8338
A18: Other Financial Institutions | B18: 0 | C18: 0 | E18: 0 | G18: 0 | J18: 0
A19: Any Other(Institutions (Domestic)) | B19: 0 | C19: 0 | E19: 0 | G19: 0 | J19: 0
A20: Sub Total B1 | B20: 87 | C20: 50424790 | D20: 50424790 | E20: 17.01 | F20: 50424790 | G20: 17.01 | I20: 50424790 | J20: 16.99 | K20: 50424790
A21: B2) Institutions (Foreign) | B21: 0 | C21: 0 | E21: 0 | G21: 0 | J21: 0
A22: Foreign Direct Investment | B22: 0 | C22: 0 | E22: 0 | G22: 0 | J22: 0
A23: Foreign Venture Capital Investors | B23: 0 | C23: 0 | E23: 0 | G23: 0 | J23: 0
A24: Sovereign Wealth Funds | B24: 0 | C24: 0 | E24: 0 | G24: 0 | J24: 0
A25: Foreign Portfolio Investors Category I | B25: 450 | C25: 18904782 | D25: 18904782 | E25: 6.38 | F25: 18904782 | G25: 6.38 | I25: 18904782 | J25: 6.37 | K25: 18904782
A26: Foreign Portfolio Investors Category II | B26: 24 | C26: 755300 | D26: 755300 | E26: 0.25 | F26: 755300 | G26: 0.25 | I26: 755300 | J26: 0.25 | K26: 755300
A27: Overseas Depositories (holding DRs) (balancing figure) | B27: 0 | C27: 0 | E27: 0 | G27: 0 | J27: 0
A28: Any Other(Institutions (Foreign)) | B28: 0 | C28: 0 | E28: 0 | G28: 0 | J28: 0
A29: Sub Total B2 | B29: 474 | C29: 19660082 | D29: 19660082 | E29: 6.63 | F29: 19660082 | G29: 6.63 | I29: 19660082 | J29: 6.62 | K29: 19660082
A30: B3) Central Government/ State Government(s)/ President of India | B30: 0 | C30: 0 | E30: 0 | G30: 0 | J30: 0
A31: Central Government / President of India | B31: 1 | C31: 2256 | D31: 2256 | E31: 0 | F31: 2256 | G31: 0 | I31: 2256 | J31: 0 | K31: 2256
A32: State Government / Governor | B32: 0 | C32: 0 | E32: 0 | G32: 0 | J32: 0
A33: Shareholding by Companies or Bodies Corporate where Central / State Government is a promoter | B33: 0 | C33: 0 | E33: 0 | G33: 0 | J33: 0
A34: Sub Total B3 | B34: 1 | C34: 2256 | D34: 2256 | E34: 0 | F34: 2256 | G34: 0 | I34: 2256 | J34: 0 | K34: 2256
A35: B4) Non-Institutions | B35: 0 | C35: 0 | E35: 0 | G35: 0 | J35: 0
A36: Associate companies / Subsidiaries | B36: 0 | C36: 0 | E36: 0 | G36: 0 | J36: 0
A37: Directors and their relatives (excluding independent directors and nominee directors) | B37: 4 | C37: 318644 | D37: 318644 | E37: 0.11 | F37: 318644 | G37: 0.11 | H37: 30000 | I37: 348644 | J37: 0.12 | K37: 318644
A38: Key Managerial Personnel | B38: 1 | C38: 4885 | D38: 4885 | E38: 0 | F38: 4885 | G38: 0 | I38: 4885 | J38: 0 | K38: 4885
A39: Relatives of promoters (other than 'immediate relatives' of promoters disclosed under 'Promoter and Promoter Group' category) | B39: 0 | C39: 0 | E39: 0 | G39: 0 | J39: 0
A40: Trusts where any person belonging to 'Promoter and Promoter Group' category is 'trustee', 'beneficiary', or 'author of the trust' | B40: 0 | C40: 0 | E40: 0 | G40: 0 | J40: 0
A41: Investor Education and Protection Fund (IEPF) | B41: 1 | C41: 97191 | D41: 97191 | E41: 0.03 | F41: 97191 | G41: 0.03 | I41: 97191 | J41: 0.03 | K41: 97191
A42: Resident Individuals holding nominal share capital up to Rs. 2 lakhs | B42: 356089 | C42: 14777058 | D42: 14777058 | E42: 4.98 | F42: 14777058 | G42: 4.98 | I42: 14777058 | J42: 4.98 | K42: 14772253
A43: Resident Individuals holding nominal share capital in excess of Rs. 2 lakhs | B43: 3 | C43: 1667588 | D43: 1667588 | E43: 0.56 | F43: 1667588 | G43: 0.56 | I43: 1667588 | J43: 0.56 | K43: 1667588
A44: Non Resident Indians (NRIs) | B44: 10641 | C44: 5301282 | D44: 5301282 | E44: 1.79 | F44: 5301282 | G44: 1.79 | I44: 5301282 | J44: 1.79 | K44: 5214030
A45: Foreign Nationals | B45: 21 | C45: 177106 | D45: 177106 | E45: 0.06 | F45: 177106 | G45: 0.06 | I45: 177106 | J45: 0.06 | K45: 160956
A46: Foreign Companies | B46: 0 | C46: 0 | E46: 0 | G46: 0 | J46: 0
A47: Bodies Corporate | B47: 1023 | C47: 456812 | D47: 456812 | E47: 0.15 | F47: 456812 | G47: 0.15 | I47: 456812 | J47: 0.15 | K47: 456812
A48: Any Other (specify) | B48: 7004 | C48: 404244 | D48: 404244 | E48: 0.14 | F48: 404244 | G48: 0.14 | H48: 282506 | I48: 686750 | J48: 0.23 | K48: 404244
A49: Trusts | B49: 17 | C49: 38469 | D49: 38469 | E49: 0.01 | F49: 38469 | G49: 0.01 | I49: 38469 | J49: 0.01 | K49: 38469
A50: LLP | B50: 116 | C50: 25239 | D50: 25239 | E50: 0.01 | F50: 25239 | G50: 0.01 | I50: 25239 | J50: 0.01 | K50: 25239
A51: HUF | B51: 6822 | C51: 280192 | D51: 280192 | E51: 0.09 | F51: 280192 | G51: 0.09 | I51: 280192 | J51: 0.09 | K51: 280192
A52: Clearing Members | B52: 49 | C52: 60344 | D52: 60344 | E52: 0.02 | F52: 60344 | G52: 0.02 | I52: 60344 | J52: 0.02 | K52: 60344
A53: ESOP or ESOS or ESPS | B53: 0 | C53: 0 | E53: 0 | G53: 0 | H53: 282506 | I53: 282506 | J53: 0.1
A54: Sub Total B4 | B54: 374787 | C54: 23204810 | D54: 23204810 | E54: 7.83 | F54: 23204810 | G54: 7.83 | H54: 312506 | I54: 23517316 | J54: 7.92 | K54: 23096603
A55: B=B1+B2+B3+B4 | B55: 375349 | C55: 93291938 | D55: 93291938 | E55: 31.47 | F55: 93291938 | G55: 31.47 | H55: 312506 | I55: 93604444 | J55: 31.54 | K55: 93183731

Sheet Standalone Quarterly Results
C1: Standalone Quarterly Results (Rs. Crores) | J1: % CHANGE
D2: Quarter ended | F2: Half Year ended | H2: Years | J2: QTQ | K2: HY YOY | L2: YOY
C3: Particulars | D3: 45992 | E3: 45901 | F3: 45992 | G3: 45627 | H3: 45717 | I3: 45352
C4: I. REVENUE
C5: Revenue from Operations | D5: 10312 | E5: 9966 | F5: =D5+E5 -> 20278 | G5: 9286 | H5: 34921 | I5: 33992 | J5: =D5/E5-1 -> 0.034718041 | K5: =F5/G5-1 -> 1.1837174 | L5: =H5/I5-1 -> 0.02732996
C6: Other Income | D6: 234 | E6: 288 | F6: =D6+E6 -> 522 | G6: 518 | H6: 810 | I6: 653 | J6: =D6/E6-1 -> -0.1875 | K6: =F6/G6-1 -> 0.0077220077 | L6: =H6/I6-1 -> 0.24042879
C7: Total Income | D7: =D5+D6 -> 10546 | E7: =E5+E6 -> 10254 | F7: =D7+E7 -> 20800 | G7: =G5+G6 -> 9804 | H7: =H5+H6 -> 35731 | I7: =I5+I6 -> 34645 | J7: =D7/E7-1 -> 0.028476692 | K7: =F7/G7-1 -> 1.121583 | L7: =H7/I7-1 -> 0.031346515
C8: II. EXPENSES
C9: Employee Benefits Expense | D9: 5942 | E9: 5863 | F9: =D9+E9 -> 11805 | G9: 11204 | H9: 21370 | I9: 20892 | J9: =D9/E9-1 -> 0.013474331 | K9: =F9/G9-1 -> 0.053641557 | L9: =H9/I9-1 -> 0.022879571
C10: Other Expenses | D10: 2449 | E10: 2222 | F10: =D10+E10 -> 4671 | G10: 4073 | H10: 7251 | I10: 7259 | J10: =D10/E10-1 -> 0.10216022 | K10: =F10/G10-1 -> 0.14682053 | L10: =H10/I10-1 -> -0.0011020802
C11: Depreciation & Amortisation | D11: 249 | E11: 249 | F11: =D11+E11 -> 498 | G11: 461 | H11: 797 | I11: 721 | J11: =D11/E11-1 -> 0 | K11: =F11/G11-1 -> 0.080260304 | L11: =H11/I11-1 -> 0.10540915
C12: Finance Costs | D12: 66 | E12: 65 | F12: =D12+E12 -> 131 | G12: 134 | H12: 224 | I12: 197 | J12: =D12/E12-1 -> 0.015384615 | K12: =F12/G12-1 -> -0.02238806 | L12: =H12/I12-1 -> 0.13705584
C13: Total Expenses | D13: =D9+D10+D11+D12 -> 8706 | E13: =E9+E10+E11+E12 -> 8399 | F13: =D13+E13 -> 17105 | G13: =G9+G10+G11+G12 -> 15872 | H13: =H9+H10+H11+H12 -> 29642 | I13: =I9+I10+I11+I12 -> 29069 | J13: =D13/E13-1 -> 0.03655197 | K13: =F13/G13-1 -> 0.077683972 | L13: =H13/I13-1 -> 0.01971172
C14: III. PROFIT & LOSS
C15: EBITDA | D15: =D7-D9-D10 -> 2155 | E15: =E7-E9-E10 -> 2169 | F15: =D15+E15 -> 4324 | G15: =G7-G9-G10 -> -5473 | H15: =H7-H9-H10 -> 7110 | I15: =I7-I9-I10 -> 6494 | J15: =D15/E15-1 -> -0.0064545874 | K15: =F15/G15-1 -> -1.7900603 | L15: =H15/I15-1 -> 0.094856791
C16: EBIT | D16: =D15-D11 -> 1906 | E16: =E15-E11 -> 1920 | F16: =D16+E16 -> 3826 | G16: =G15-G11 -> -5934 | H16: =H15-H11 -> 6313 | I16: =I15-I11 -> 5773 | J16: =D16/E16-1 -> -0.0072916667 | K16: =F16/G16-1 -> -1.644759 | L16: =H16/I16-1 -> 0.093538888
C17: Profit before Exceptional Items & Tax | D17: =D16-D12 -> 1840 | E17: =E16-E12 -> 1855 | F17: =D17+E17 -> 3695 | G17: =G16-G12 -> -6068 | H17: =H16-H12 -> 6089 | I17: =I16-I12 -> 5576 | J17: =D17/E17-1 -> -0.0080862534 | K17: =F17/G17-1 -> -1.6089321 | L17: =H17/I17-1 -> 0.092001435
C18: Exceptional Items | D18: -590 | E18: 0 | F18: =D18+E18 -> -590 | G18: 0 | H18: 0 | I18: 0
C19: Profit Before Tax | D19: =D17+D18 -> 1250 | E19: =E17+E18 -> 1855 | F19: =D19+E19 -> 3105 | G19: =G17+G18 -> -6068 | H19: =H17+H18 -> 6089 | I19: =I17+I18 -> 5576 | J19: =D19/E19-1 -> -0.32614555 | K19: =F19/G19-1 -> -1.5117007 | L19: =H19/I19-1 -> 0.092001435
C20: Tax Expense | D20: 320 | E20: 468 | F20: =D20+E20 -> 788 | G20: 772 | H20: 1503 | I20: 1288 | J20: =D20/E20-1 -> -0.31623932 | K20: =F20/G20-1 -> 0.020725389 | L20: =H20/I20-1 -> 0.16692547
C21: Profit After Tax (PAT) | D21: =D19-D20 -> 930 | E21: =E19-E20 -> 1387 | F21: =D21+E21 -> 2317 | G21: =G19-G20 -> -6840 | H21: =H19-H20 -> 4586 | I21: =I19-I20 -> 4288 | J21: =D21/E21-1 -> -0.3294881 | K21: =F21/G21-1 -> -1.3387427 | L21: =H21/I21-1 -> 0.069496269
C22: IV. EARNINGS PER SHARE (Rs.)
C23: Basic EPS | D23: 31.33 | E23: 46.77 | F23: =D23+E23 -> 78.1 | G23: 76.38 | H23: 90.56 | I23: 78.58 | J23: =D23/E23-1 -> -0.33012615 | K23: =F23/G23-1 -> 0.022518984 | L23: =H23/I23-1 -> 0.1524561
C24: Diluted EPS | D24: 31.3 | E24: 46.72 | F24: =D24+E24 -> 78.02 | G24: 76.28 | H24: 90.45 | I24: 78.43 | J24: =D24/E24-1 -> -0.33005137 | K24: =F24/G24-1 -> 0.022810697 | L24: =H24/I24-1 -> 0.15325768
C25: V. SUPPLEMENTARY
C26: Paid-up Equity Share Capital (Rs. Cr) | D26: 29 | E26: 29 | F26: =D26 -> 29 | G26: 29 | H26: 29 | I26: 29 | J26: =D26/E26-1 -> 0 | K26: =F26/G26-1 -> 0 | L26: =H26/I26-1 -> 0
C27: Reserves excl. Revaluation (Rs. Cr) | F27: =D27+E27 -> 0 | H27: 19268

Sheet Consolidated Quarterly Results
E1: Consolidated Quarterly Results (Rs. Crores) | L1: % CHANGE
F2: Quarter ended | I2: Years | L2: QTQ | M2: QOQ YOY | N2: YOY
E3: Particulars | F3: 45992 | G3: 45901 | H3: 45627 | I3: 45717 | J3: 45352
E4: I. REVENUE
E5: Revenue from Operations | F5: 10781 | G5: 10394 | H5: 9660 | I5: 38008 | J5: 35517 | L5: =F5/G5-1 -> 0.037233019 | M5: =F5/H5-1 -> 0.11604555 | N5: =I5/J5-1 -> 0.070135428
E6: Other Income | F6: 227 | G6: 300 | H6: 212 | I6: 990 | J6: 702 | L6: =F6/G6-1 -> -0.24333333 | M6: =F6/H6-1 -> 0.070754717 | N6: =I6/J6-1 -> 0.41025641
E7: Total Income | F7: =F5+F6 -> 11008 | G7: =G5+G6 -> 10694 | H7: =H5+H6 -> 9872 | I7: =I5+I6 -> 38998 | J7: =J5+J6 -> 36219 | L7: =F7/G7-1 -> 0.029362259 | M7: =F7/H7-1 -> 0.11507293 | N7: =I7/J7-1 -> 0.076727684
E8: II. EXPENSES
E9: Employee Benefits Expense | F9: 6549 | G9: 6467 | H9: 6254 | I9: 23180 | J9: 22504 | L9: =F9/G9-1 -> 0.012679759 | M9: =F9/H9-1 -> 0.047169811 | N9: =I9/J9-1 -> 0.030039104
E10: Other Expenses | F10: 2229 | G10: 1996 | H10: 1812 | I10: 6430 | J10: 6615 | L10: =F10/G10-1 -> 0.11673347 | M10: =F10/H10-1 -> 0.23013245 | N10: =I10/J10-1 -> -0.027966742
E11: Depreciation & Amortisation | F11: 265 | G11: 282 | H11: 264 | I11: 868 | J11: 786 | L11: =F11/G11-1 -> -0.060283688 | M11: =F11/H11-1 -> 0.0037878788 | N11: =I11/J11-1 -> 0.1043257
E12: Finance Costs | F12: 69 | G12: 69 | H12: 68 | I12: 235 | J12: 209 | L12: =F12/G12-1 -> 0 | M12: =F12/H12-1 -> 0.014705882 | N12: =I12/J12-1 -> 0.12440191
E13: Total Expenses | F13: =F9+F10+F11+F12 -> 9112 | G13: =G9+G10+G11+G12 -> 8814 | H13: =H9+H10+H11+H12 -> 8398 | I13: =I9+I10+I11+I12 -> 30713 | J13: =J9+J10+J11+J12 -> 30114 | L13: =F13/G13-1 -> 0.033809848 | M13: =F13/H13-1 -> 0.085020243 | N13: =I13/J13-1 -> 0.019891081
E14: III. PROFIT & LOSS
E15: EBITDA | F15: =F7-F9-F10 -> 2230 | G15: =G7-G9-G10 -> 2231 | H15: =H7-H9-H10 -> 1806 | I15: =I7-I9-I10 -> 9388 | J15: =J7-J9-J10 -> 7100 | L15: =F15/G15-1 -> -0.00044822949 | M15: =F15/H15-1 -> 0.23477298 | N15: =I15/J15-1 -> 0.32225352
E16: EBIT | F16: =F15-F11 -> 1965 | G16: =G15-G11 -> 1949 | H16: =H15-H11 -> 1542 | I16: =I15-I11 -> 8520 | J16: =J15-J11 -> 6314 | L16: =F16/G16-1 -> 0.0082093381 | M16: =F16/H16-1 -> 0.27431907 | N16: =I16/J16-1 -> 0.34938232
E17: Profit before Exceptional Items & Tax | F17: =F16-F12 -> 1896 | G17: =G16-G12 -> 1880 | H17: =H16-H12 -> 1474 | I17: =I16-I12 -> 8285 | J17: =J16-J12 -> 6105 | L17: =F17/G17-1 -> 0.0085106383 | M17: =F17/H17-1 -> 0.28629579 | N17: =I17/J17-1 -> 0.35708436
E18: Exceptional Items | F18: -590 | G18: 0 | H18: 0 | I18: 0 | J18: 0
E19: Profit Before Tax | F19: =F17+F18 -> 1306 | G19: =G17+G18 -> 1880 | H19: =H17+H18 -> 1474 | I19: =I17+I18 -> 8285 | J19: =J17+J18 -> 6105 | L19: =F19/G19-1 -> -0.30531915 | M19: =F19/H19-1 -> -0.11397558 | N19: =I19/J19-1 -> 0.35708436
E20: Tax Expense | F20: 345 | G20: 498 | H20: 385 | I20: 1612 | J20: 1464 | L20: =F20/G20-1 -> -0.30722892 | M20: =F20/H20-1 -> -0.1038961 | N20: =I20/J20-1 -> 0.1010929
E21: Profit After Tax (PAT) | F21: =F19-F20 -> 961 | G21: =G19-G20 -> 1382 | H21: =H19-H20 -> 1089 | I21: =I19-I20 -> 6673 | J21: =J19-J20 -> 4641 | L21: =F21/G21-1 -> -0.30463097 | M21: =F21/H21-1 -> -0.11753903 | N21: =I21/J21-1 -> 0.43783667
E22: Minority Interest | F22: 11 | G22: 19 | H22: -1 | I22: 19 | J22: -1 | L22: =F22/G22-1 -> -0.42105263 | M22: =F22/H22-1 -> -12 | N22: =I22/J22-1 -> -20
E23: Net Profit after Minority Interest | F23: =F21+F22 -> 972 | G23: =G21+G22 -> 1401 | H23: =H21+H22 -> 1088 | I23: =I21+I22 -> 6692 | J23: =J21+J22 -> 4640 | L23: =F23/G23-1 -> -0.30620985 | M23: =F23/H23-1 -> -0.10661765 | N23: =I23/J23-1 -> 0.44224138
E24: Total Comprehensive Income | F24: 918 | G24: 692 | H24: 782 | I24: 4547 | L24: =F24/G24-1 -> 0.3265896 | M24: =F24/H24-1 -> 0.17391304
E25: IV. EARNINGS PER SHARE (Rs.)
E26: Basic EPS | F26: 32.75 | G26: 47.28 | H26: 36.65 | I26: 155.22 | J26: 154.55 | L26: =F26/G26-1 -> -0.3073181 | M26: =F26/H26-1 -> -0.10641201 | N26: =I26/J26-1 -> 0.0043351666
E27: Diluted EPS | F27: 32.71 | G27: 47.23 | H27: 36.59 | I27: 155.22 | J27: 154.55 | L27: =F27/G27-1 -> -0.30743172 | M27: =F27/H27-1 -> -0.1060399 | N27: =I27/J27-1 -> 0.0043351666
E28: V. SUPPLEMENTARY
E29: Paid-up Equity Share Capital (Rs. Cr) | F29: 29 | G29: 29 | H29: 29 | I29: 29 | J29: 29 | L29: =F29/G29-1 -> 0 | M29: =F29/H29-1 -> 0 | N29: =I29/J29-1 -> 0
E30: Reserves excl. Revaluation (Rs. Cr) | I30: 19996

Sheet Standalone Balance sheet
E1: Standalone Balance Sheet
E2: Particulars (Rs. Cr.) | F2: Mar 25 | G2: Mar 24 | H2: % Change
E3: 12 Months Ended | F3: 12 mths | G3: 12 mths
E4: EQUITIES AND LIABILITIES
E5: SHAREHOLDER'S FUNDS
E6: Equity Share Capital | F6: 29.6 | G6: 29.6 | H6: =F6/G6-1 -> 0
E7: Total Share Capital | F7: =F6 -> 29.6 | G7: =G6 -> 29.6 | H7: =F7/G7-1 -> 0
E8: Reserves and Surplus | F8: 21570.7 | G8: 18925.5 | H8: =F8/G8-1 -> 0.13976909
E9: Total Reserves and Surplus | F9: =F8 -> 21570.7 | G9: =G8 -> 18925.5 | H9: =F9/G9-1 -> 0.13976909
E10: Employees Stock Options | F10: 233.7 | G10: 343.3 | H10: =F10/G10-1 -> -0.3192543
E11: Total Shareholders Funds | F11: =F7+F9+F10 -> 21834 | G11: =G7+G9+G10 -> 19298.4 | H11: =F11/G11-1 -> 0.13138913
E12: Equity Share Application Money | F12: 0.1 | G12: 0.1 | H12: =F12/G12-1 -> 0
E13: NON-CURRENT LIABILITIES
E14: Other Long Term Liabilities | F14: 1825.4 | G14: 1674.3 | H14: =F14/G14-1 -> 0.09024667
E15: Long Term Provisions | F15: 19.7 | G15: 15.7 | H15: =F15/G15-1 -> 0.25477707
E16: Total Non-Current Liabilities | F16: =F14+F15 -> 1845.1 | G16: =G14+G15 -> 1690 | H16: =F16/G16-1 -> 0.091775148
E17: CURRENT LIABILITIES
E18: Trade Payables | F18: 1515.3 | G18: 1504.5 | H18: =F18/G18-1 -> 0.0071784646
E19: Other Current Liabilities | F19: 3115.6 | G19: 3169.3 | H19: =F19/G19-1 -> -0.016943805
E20: Short Term Provisions | F20: 906.6 | G20: 795.4 | H20: =F20/G20-1 -> 0.13980387
E21: Total Current Liabilities | F21: =F18+F19+F20 -> 5537.5 | G21: =G18+G19+G20 -> 5469.2 | H21: =F21/G21-1 -> 0.012488115
E22: Total Capital And Liabilities | F22: =F11+F12+F16+F21 -> 29216.7 | G22: =G11+G12+G16+G21 -> 26457.7 | H22: =F22/G22-1 -> 0.10427966
E23: ASSETS
E24: NON-CURRENT ASSETS
E25: Tangible Assets | F25: 3845.6 | G25: 3444.7 | H25: =F25/G25-1 -> 0.11638169
E26: Intangible Assets | F26: 715.2 | G26: 774.9 | H26: =F26/G26-1 -> -0.077042199
E27: Capital Work-In-Progress | F27: 563.2 | G27: 464.2 | H27: =F27/G27-1 -> 0.21327014
E28: Intangible Assets Under Development | F28: 0 | G28: 12.7 | H28: =F28/G28-1 -> -1
E29: Fixed Assets | F29: =F25+F26+F27+F28 -> 5124 | G29: =G25+G26+G27+G28 -> 4696.5 | H29: =F29/G29-1 -> 0.091025232
E30: Non-Current Investments | F30: 2982.7 | G30: 2449.9 | H30: =F30/G30-1 -> 0.21747826
E31: Deferred Tax Assets [Net] | F31: 201.8 | G31: 201.4 | H31: =F31/G31-1 -> 0.0019860973
E32: Long Term Loans And Advances | F32: 0 | G32: 0
E33: Other Non-Current Assets | F33: 986.9 | G33: 928.3 | H33: =F33/G33-1 -> 0.063126145
E34: Total Non-Current Assets | F34: =F29+F30+F31+F32+F33 -> 9295.4 | G34: =G29+G30+G31+G32+G33 -> 8276.1 | H34: =F34/G34-1 -> 0.12316188
E35: CURRENT ASSETS
E36: Current Investments | F36: 7374 | G36: 6753.4 | H36: =F36/G36-1 -> 0.091894453
E37: Inventories | F37: 2.8 | G37: 3 | H37: =F37/G37-1 -> -0.066666667
E38: Trade Receivables | F38: 5671.8 | G38: 5372.1 | H38: =F38/G38-1 -> 0.055788239
E39: Cash And Cash Equivalents | F39: 2964.7 | G39: 2590.7 | H39: =F39/G39-1 -> 0.14436253
E40: Short Term Loans And Advances | F40: 35.1 | G40: 45.6 | H40: =F40/G40-1 -> -0.23026316
E41: OtherCurrentAssets | F41: 3872.9 | G41: 3416.8 | H41: =F41/G41-1 -> 0.13348747
E42: Total Current Assets | F42: =F36+F37+F38+F39+F40+F41 -> 19921.3 | G42: =G36+G37+G38+G39+G40+G41 -> 18181.6 | H42: =F42/G42-1 -> 0.095684648
E43: Total Assets | F43: =F34+F42 -> 29216.7 | G43: =G34+G42 -> 26457.7 | H43: =F43/G43-1 -> 0.10427966
E45: OTHER ADDITIONAL INFORMATION
E46: CONTINGENT LIABILITIES, COMMITMENTS
E47: Contingent Liabilities | F47: 2737.1 | G47: 1211.4 | H47: =F47/G47-1 -> 1.2594519
E48: CIF VALUE OF IMPORTS
E49: EXPENDITURE IN FOREIGN EXCHANGE
E50: Expenditure In Foreign Currency | F50: 15195.8 | G50: 13899.1 | H50: =F50/G50-1 -> 0.09329381
E51: REMITTANCES IN FOREIGN CURRENCIES FOR DIVIDENDS
E52: Dividend Remittance In Foreign Currency | F52: - | G52: -
E53: EARNINGS IN FOREIGN EXCHANGE
E54: FOB Value Of Goods | F54: - | G54: -
E55: Other Earnings | F55: 35075 | G55: 32540.2 | H55: =F55/G55-1 -> 0.077897493
E56: BONUS DETAILS
E57: Bonus Equity Share Capital | F57: - | G57: -
E58: NON-CURRENT INVESTMENTS
E59: Non-Current Investments Quoted Market Value | F59: 2193.8 | G59: 1801.2 | H59: =F59/G59-1 -> 0.2179658
E60: Non-Current Investments Unquoted Book Value | F60: 861.2 | G60: 688.3 | H60: =F60/G60-1 -> 0.25119861
E61: CURRENT INVESTMENTS
E62: Current Investments Quoted Market Value | F62: 6815.1 | G62: 6295.1 | H62: =F62/G62-1 -> 0.08260393
E63: Current Investments Unquoted Book Value | F63: 516.7 | G63: 421 | H63: =F63/G63-1 -> 0.22731591

Sheet Standalone P&L
E1: Standalone Profit & Loss account
E2: Particulars (Rs. Cr.) | F2: Mar 25 | G2: Mar 24 | H2: % Change
E3: 12 Months Ended | F3: 12 mths | G3: 12 mths
E4: INCOME
E5: Revenue From Operations [Gross] | F5: 36682.5 | G5: 34253.4 | H5: =F5/G5-1 -> 0.070915588
E6: Revenue From Operations [Net] | F6: =F5 -> 36682.5 | G6: =G5 -> 34253.4 | H6: =F6/G6-1 -> 0.070915588
E7: Total Operating Revenues | F7: =F6 -> 36682.5 | G7: =G6 -> 34253.4 | H7: =F7/G7-1 -> 0.070915588
E8: Other Income | F8: 973.8 | G8: 709.9 | H8: =F8/G8-1 -> 0.3717425
E9: Total Revenue | F9: =F7+F8 -> 37656.3 | G9: =G7+G8 -> 34963.3 | H9: =F9/G9-1 -> 0.077023622
E10: EXPENSES
E11: Operating And Direct Expenses | F11: 3627.1 | G11: 4813.5 | H11: =F11/G11-1 -> -0.24647346
E12: Employee Benefit Expenses | F12: 22596.1 | G12: 21049 | H12: =F12/G12-1 -> 0.073499929
E13: Finance Costs | F13: 270.7 | G13: 207.1 | H13: =F13/G13-1 -> 0.30709802
E14: Depreciation And Amortisation Expenses | F14: 904.3 | G14: 760.4 | H14: =F14/G14-1 -> 0.1892425
E15: Other Expenses | F15: 4289.4 | G15: 2253.9 | H15: =F15/G15-1 -> 0.90310129
E16: Total Expenses | F16: =F11+F12+F13+F14+F15 -> 31687.6 | G16: =G11+G12+G13+G14+G15 -> 29083.9 | H16: =F16/G16-1 -> 0.089523757
F17: 45717 | G17: 45352
F19: 12 mths | G19: 12 mths
E21: Profit/Loss Before Exceptional, ExtraOrdinary Items And Tax | F21: =F9-F16 -> 5968.7 | G21: =G9-G16 -> 5879.4 | H21: =F21/G21-1 -> 0.015188625
E22: Profit/Loss Before Tax | F22: =F21 -> 5968.7 | G22: =G21 -> 5879.4 | H22: =F22/G22-1 -> 0.015188625
E23: Tax Expenses-Continued Operations
E24: Current Tax | F24: 1505.7 | G24: 1391.7 | H24: =F24/G24-1 -> 0.081914206
E25: Deferred Tax | F25: 16.5 | G25: 1.8 | H25: =F25/G25-1 -> 8.1666667
E26: Total Tax Expenses | F26: =F24+F25 -> 1522.2 | G26: =G24+G25 -> 1393.5 | H26: =F26/G26-1 -> 0.092357374
E27: Profit/Loss After Tax And Before ExtraOrdinary Items | F27: =F22-F26 -> 4446.5 | G27: =G22-G26 -> 4485.9 | H27: =F27/G27-1 -> -0.0087830759
E28: Profit/Loss From Continuing Operations | F28: =F27 -> 4446.5 | G28: =G27 -> 4485.9 | H28: =F28/G28-1 -> -0.0087830759
E29: Profit/Loss For The Period | F29: =F28 -> 4446.5 | G29: =G28 -> 4485.9 | H29: =F29/G29-1 -> -0.0087830759
F30: 45717 | G30: 45352
F32: 12 mths | G32: 12 mths
E34: OTHER ADDITIONAL INFORMATION
E35: EARNINGS PER SHARE
E36: Basic EPS (Rs.) | F36: 150.15 | G36: 151.6 | H36: =F36/G36-1 -> -0.0095646438
E37: Diluted EPS (Rs.) | F37: 149.87 | G37: 151.24 | H37: =F37/G37-1 -> -0.0090584501
E38: VALUE OF IMPORTED AND INDIGENIOUS RAW MATERIALS
E39: STORES, SPARES AND LOOSE TOOLS
E40: DIVIDEND AND DIVIDEND PERCENTAGE
E41: Equity Share Dividend | F41: 1924.6 | G41: 1775.3 | H41: =F41/G41-1 -> 0.084098462
E42: Equity Dividend Rate (%) | F42: 6500 | G42: 6500 | H42: =F42/G42-1 -> 0

Sheet Consolidated P&L
E1: Consolidated Profit & Loss account | L1: % Change
E2: Particulars (Rs. Cr.) | F2: Mar 22 | G2: Mar 23 | H2: Mar 24 | I2: Mar 25 | J2: Mar 26 | L2: Mar 22 | M2: Mar 23 | N2: Mar 24 | O2: Mar 25 | P2: Mar 26
E3: 12 Months Ended | F3: 12 mths | G3: 12 mths | H3: 12 mths | I3: 12 mths | J3: 12 mths
E4: INCOME
E5: Revenue From Operations [Gross] | F5: 15668.7 | G5: 33183 | H5: 35517 | I5: 38008.1 | J5: 42307.6 | M5: =(G5-F5)/F5 -> 1.117789 | N5: =(H5-G5)/G5 -> 0.070337221 | O5: =(I5-H5)/H5 -> 0.070138244 | P5: =(J5-I5)/I5 -> 0.11312062
E6: Revenue From Operations [Net] | F6: =F5 -> 15668.7 | G6: =G5 -> 33183 | H6: =H5 -> 35517 | I6: =I5 -> 38008.1 | J6: =J5 -> 42307.6 | M6: =(G6-F6)/F6 -> 1.117789 | N6: =(H6-G6)/G6 -> 0.070337221 | O6: =(I6-H6)/H6 -> 0.070138244 | P6: =(J6-I6)/I6 -> 0.11312062
E7: Total Operating Revenues | F7: =F6 -> 15668.7 | G7: =G6 -> 33183 | H7: =H6 -> 35517 | I7: =I6 -> 38008.1 | J7: =J6 -> 42307.6 | M7: =(G7-F7)/F7 -> 1.117789 | N7: =(H7-G7)/G7 -> 0.070337221 | O7: =(I7-H7)/H7 -> 0.070138244 | P7: =(J7-I7)/I7 -> 0.11312062
E8: Other Income | F8: 466.7 | G8: 556.9 | H8: 701.9 | I8: 989.7 | J8: 1094.4 | M8: =(G8-F8)/F8 -> 0.19327191 | N8: =(H8-G8)/G8 -> 0.2603699 | O8: =(I8-H8)/H8 -> 0.41002992 | P8: =(J8-I8)/I8 -> 0.10578963
E9: Total Revenue | F9: =F7+F8 -> 16135.4 | G9: =G7+G8 -> 33739.9 | H9: =H7+H8 -> 36218.9 | I9: =I7+I8 -> 38997.8 | J9: =J7+J8 -> 43402 | M9: =(G9-F9)/F9 -> 1.0910483 | N9: =(H9-G9)/G9 -> 0.07347384 | O9: =(I9-H9)/H9 -> 0.076725135 | P9: =(J9-I9)/I9 -> 0.11293458
E10: EXPENSES
E11: Operating And Direct Expenses | F11: 2656.5 | G11: 3967.9 | H11: 4179.5 | I11: 2631.2 | J11: 0 | M11: =(G11-F11)/F11 -> 0.49365707 | N11: =(H11-G11)/G11 -> 0.053327957 | O11: =(I11-H11)/H11 -> -0.37045101 | P11: =(J11-I11)/I11 -> -1
E12: Employee Benefit Expenses | F12: 9700.7 | G12: 20879.9 | H12: 22732.3 | I12: 24622.6 | J12: 26286.9 | M12: =(G12-F12)/F12 -> 1.1524117 | N12: =(H12-G12)/G12 -> 0.0887169 | O12: =(I12-H12)/H12 -> 0.083154806 | P12: =(J12-I12)/I12 -> 0.067592374
E13: Finance Costs | F13: 72.8 | G13: 150.4 | H13: 221.7 | I13: 278.9 | J13: 276.3 | M13: =(G13-F13)/F13 -> 1.0659341 | N13: =(H13-G13)/G13 -> 0.47406915 | O13: =(I13-H13)/H13 -> 0.25800631 | P13: =(J13-I13)/I13 -> -0.0093223378
E14: Depreciation And Amortisation Expenses | F14: 354.9 | G14: 722.7 | H14: 818.9 | I14: 991.5 | J14: 1054.1 | M14: =(G14-F14)/F14 -> 1.0363483 | N14: =(H14-G14)/G14 -> 0.13311194 | O14: =(I14-H14)/H14 -> 0.21077055 | P14: =(J14-I14)/I14 -> 0.063136662
E15: Other Expenses | F15: 253.1 | G15: 2227.5 | H15: 2217.8 | I15: 4259.4 | J15: 8465.5 | M15: =(G15-F15)/F15 -> 7.8008692 | N15: =(H15-G15)/G15 -> -0.0043546577 | O15: =(I15-H15)/H15 -> 0.9205519 | P15: =(J15-I15)/I15 -> 0.9874865
E16: Total Expenses | F16: =F11+F12+F13+F14+F15 -> 13038 | G16: =G11+G12+G13+G14+G15 -> 27948.4 | H16: =H11+H12+H13+H14+H15 -> 30170.2 | I16: =I11+I12+I13+I14+I15 -> 32783.6 | J16: =J11+J12+J13+J14+J15 -> 36082.8 | M16: =(G16-F16)/F16 -> 1.143611 | N16: =(H16-G16)/G16 -> 0.079496501 | O16: =(I16-H16)/H16 -> 0.086621898 | P16: =(J16-I16)/I16 -> 0.10063568
E17: Profit/Loss Before Exceptional, ExtraOrdinary Items And Tax | F17: =F9-F16 -> 3097.4 | G17: =G9-G16 -> 5791.5 | H17: =H9-H16 -> 6048.7 | I17: =I9-I16 -> 6214.2 | J17: =J9-J16 -> 7319.2 | M17: =(G17-F17)/F17 -> 0.86979402 | N17: =(H17-G17)/G17 -> 0.044409911 | O17: =(I17-H17)/H17 -> 0.027361251 | P17: =(J17-I17)/I17 -> 0.17781854
E18: Exceptional Items | F18: 0 | G18: 0 | H18: 0 | I18: 0 | J18: -528.1
E19: Profit/Loss Before Tax | F19: =F17+F18 -> 3097.4 | G19: =G17+G18 -> 5791.5 | H19: =H17+H18 -> 6048.7 | I19: =I17+I18 -> 6214.2 | J19: =J17+J18 -> 6791.1 | M19: =(G19-F19)/F19 -> 0.86979402 | N19: =(H19-G19)/G19 -> 0.044409911 | O19: =(I19-H19)/H19 -> 0.027361251 | P19: =(J19-I19)/I19 -> 0.092835763
E20: Tax Expenses-Continued Operations
E21: Current Tax | F21: 818.1 | G21: 1439.1 | H21: 1460 | I21: 1578.4 | J21: 1808.4 | M21: =(G21-F21)/F21 -> 0.75907591 | N21: =(H21-G21)/G21 -> 0.014522966 | O21: =(I21-H21)/H21 -> 0.08109589 | P21: =(J21-I21)/I21 -> 0.14571718
E22: Deferred Tax | F22: -19.2 | G22: -57.9 | H22: 4.1 | I22: 33.8 | J22: 0 | M22: =(G22-F22)/F22 -> 2.015625 | N22: =(H22-G22)/G22 -> -1.0708117 | O22: =(I22-H22)/H22 -> 7.2439024 | P22: =(J22-I22)/I22 -> -1
E23: Total Tax Expenses | F23: =F21+F22 -> 798.9 | G23: =G21+G22 -> 1381.2 | H23: =H21+H22 -> 1464.1 | I23: =I21+I22 -> 1612.2 | J23: =J21+J22 -> 1808.4 | M23: =(G23-F23)/F23 -> 0.72887721 | N23: =(H23-G23)/G23 -> 0.060020272 | O23: =(I23-H23)/H23 -> 0.10115429 | P23: =(J23-I23)/I23 -> 0.12169706
E24: Profit/Loss After Tax And Before ExtraOrdinary Items | F24: =F19-F23 -> 2298.5 | G24: =G19-G23 -> 4410.3 | H24: =H19-H23 -> 4584.6 | I24: =I19-I23 -> 4602 | J24: =J19-J23 -> 4982.7 | M24: =(G24-F24)/F24 -> 0.91877311 | N24: =(H24-G24)/G24 -> 0.039521121 | O24: =(I24-H24)/H24 -> 0.0037953147 | P24: =(J24-I24)/I24 -> 0.082724902
E25: Profit/Loss From Continuing Operations | F25: =F24 -> 2298.5 | G25: =G24 -> 4410.3 | H25: =H24 -> 4584.6 | I25: =I24 -> 4602 | J25: =J24 -> 4982.7 | M25: =(G25-F25)/F25 -> 0.91877311 | N25: =(H25-G25)/G25 -> 0.039521121 | O25: =(I25-H25)/H25 -> 0.0037953147 | P25: =(J25-I25)/I25 -> 0.082724902
E26: Profit/Loss For The Period | F26: =F25 -> 2298.5 | G26: =G25 -> 4410.3 | H26: =H25 -> 4584.6 | I26: =I25 -> 4602 | J26: =J25 -> 4982.7 | M26: =(G26-F26)/F26 -> 0.91877311 | N26: =(H26-G26)/G26 -> 0.039521121 | O26: =(I26-H26)/H26 -> 0.0037953147 | P26: =(J26-I26)/I26 -> 0.082724902
E27: Minority Interest | F27: -1.7 | G27: -2 | H27: -2.5 | I27: -3.3 | J27: 35.4 | M27: =(G27-F27)/F27 -> 0.17647059 | N27: =(H27-G27)/G27 -> 0.25 | O27: =(I27-H27)/H27 -> 0.32 | P27: =(J27-I27)/I27 -> -11.727273
E28: Consolidated Profit/Loss After MI And Associates | F28: =F26+F27 -> 2296.8 | G28: =G26+G27 -> 4408.3 | H28: =H26+H27 -> 4582.1 | I28: =I26+I27 -> 4598.7 | J28: =J26+J27 -> 5018.1 | M28: =(G28-F28)/F28 -> 0.91932254 | N28: =(H28-G28)/G28 -> 0.039425629 | O28: =(I28-H28)/H28 -> 0.003622793 | P28: =(J28-I28)/I28 -> 0.091199687
E29: OTHER ADDITIONAL INFORMATION
E30: EARNINGS PER SHARE
E31: Basic EPS (Rs.) | F31: 131 | G31: 149 | H31: 155 | I31: 155 | J31: 169 | M31: =(G31-F31)/F31 -> 0.13740458 | N31: =(H31-G31)/G31 -> 0.040268456 | O31: =(I31-H31)/H31 -> 0 | P31: =(J31-I31)/I31 -> 0.090322581
E32: Diluted EPS (Rs.) | F32: 131 | G32: 149 | H32: 155 | I32: 155 | M32: =(G32-F32)/F32 -> 0.13740458 | N32: =(H32-G32)/G32 -> 0.040268456 | O32: =(I32-H32)/H32 -> 0 | P32: =(J32-I32)/I32 -> -1
E33: DIVIDEND AND DIVIDEND PERCENTAGE
E34: Equity Share Dividend | F34: 874.9 | G34: 1562.7 | H34: 1775.3 | I34: 1924.6 | J34: 0 | M34: =(G34-F34)/F34 -> 0.78614699 | N34: =(H34-G34)/G34 -> 0.13604659 | O34: =(I34-H34)/H34 -> 0.084098462 | P34: =(J34-I34)/I34 -> -1

Sheet Consolidated Balance sheet
D1: Consolidated Balance Sheet | L1: % Change
D2: Particulars (Rs. Cr.) | E2: Mar 22 | F2: Mar 23 | G2: Mar 24 | H2: Mar 25 | I2: Mar 26 | L2: Mar 22 | M2: Mar 23 | N2: Mar 24 | O2: Mar 25 | P2: Mar 26
D3: 12 Months Ended | E3: 12 mths | F3: 12 mths | G3: 12 mths | H3: 12 mths | I3: 12 mths
D4: EQUITIES AND LIABILITIES
D5: SHAREHOLDER'S FUNDS
D6: Equity Share Capital | E6: 17.5 | F6: 29.6 | G6: 29.6 | H6: 29.6 | I6: 29.6 | M6: =(F6-E6)/E6 -> 0.69142857 | N6: =(G6-F6)/F6 -> 0 | O6: =(H6-G6)/G6 -> 0 | P6: =(I6-H6)/H6 -> 0
D7: Total Share Capital | E7: =E6 -> 17.5 | F7: =F6 -> 29.6 | G7: =G6 -> 29.6 | H7: =H6 -> 29.6 | I7: =I6 -> 29.6
D8: Reserves and Surplus | E8: 8797.1 | F8: 16078.6 | G8: 19503.6 | H8: 22434.9 | I8: 23995.4 | M8: =(F8-E8)/E8 -> 0.82771595 | N8: =(G8-F8)/F8 -> 0.21301606 | O8: =(H8-G8)/G8 -> 0.15029533 | P8: =(I8-H8)/H8 -> 0.069556807
D9: Total Reserves and Surplus | E9: =E8 -> 8797.1 | F9: =F8 -> 16078.6 | G9: =G8 -> 19503.6 | H9: =H8 -> 22434.9 | I9: =I8 -> 23995.4 | M9: =(F9-E9)/E9 -> 0.82771595 | N9: =(G9-F9)/F9 -> 0.21301606 | O9: =(H9-G9)/G9 -> 0.15029533 | P9: =(I9-H9)/H9 -> 0.069556807
D10: Employees Stock Options | E10: 0 | F10: 483.9 | G10: 483.9 | H10: 233.7 | I10: 0 | N10: =(G10-F10)/F10 -> 0 | O10: =(H10-G10)/G10 -> -0.51704898 | P10: =(I10-H10)/H10 -> -1
D11: Total Shareholders Funds | E11: =E7+E9+E10 -> 8814.6 | F11: =F7+F9+F10 -> 16592.1 | G11: =G7+G9+G10 -> 20017.1 | H11: =H7+H9+H10 -> 22698.2 | I11: =I7+I9+I10 -> 24025 | M11: =(F11-E11)/E11 -> 0.88234293 | N11: =(G11-F11)/F11 -> 0.20642354 | O11: =(H11-G11)/G11 -> 0.13394048 | P11: =(I11-H11)/H11 -> 0.058453974
D12: Equity Share Application Money | E12: 0 | F12: 0 | G12: 0.1 | H12: 0.1 | I12: 0 | P12: =(I12-H12)/H12 -> -1
D13: Minority Interest | E13: 5.7 | F13: 7.1 | G13: 9.2 | H13: 13.2 | I13: 82.7 | M13: =(F13-E13)/E13 -> 0.24561404 | N13: =(G13-F13)/F13 -> 0.29577465 | O13: =(H13-G13)/G13 -> 0.43478261 | P13: =(I13-H13)/H13 -> 5.2651515
D14: NON-CURRENT LIABILITIES
D15: Long Term Borrowings | E15: 667.5 | F15: 0 | G15: 0 | H15: 0 | I15: 0
D16: Deferred Tax Liabilities [Net] | E16: 10.5 | F16: 14.7 | G16: 18.7 | H16: 31.9 | I16: 47.5 | M16: =(F16-E16)/E16 -> 0.4 | N16: =(G16-F16)/F16 -> 0.27210884 | O16: =(H16-G16)/G16 -> 0.70588235 | P16: =(I16-H16)/H16 -> 0.48902821
D17: Other Long Term Liabilities | E17: 52.7 | F17: 1364.6 | G17: 1759 | H17: 1901 | I17: 3235.6 | M17: =(F17-E17)/E17 -> 24.893738 | N17: =(G17-F17)/F17 -> 0.28902242 | O17: =(H17-G17)/G17 -> 0.080727686 | P17: =(I17-H17)/H17 -> 0.70205155
D18: Long Term Provisions | E18: 0 | F18: 35 | G18: 15.7 | H18: 19.7 | I18: 21.5 | N18: =(G18-F18)/F18 -> -0.55142857 | O18: =(H18-G18)/G18 -> 0.25477707 | P18: =(I18-H18)/H18 -> 0.091370558
D19: Total Non-Current Liabilities | E19: =E15+E16+E17+E18 -> 730.7 | F19: =F15+F16+F17+F18 -> 1414.3 | G19: =G15+G16+G17+G18 -> 1793.4 | H19: =H15+H16+H17+H18 -> 1952.6 | I19: =I15+I16+I17+I18 -> 3304.6 | M19: =(F19-E19)/E19 -> 0.93554126 | N19: =(G19-F19)/F19 -> 0.2680478 | O19: =(H19-G19)/G19 -> 0.088769934 | P19: =(I19-H19)/H19 -> 0.69241012
D20: CURRENT LIABILITIES
D21: Short Term Borrowings | E21: 168 | F21: 125.3 | G21: 40.7 | H21: 2.3 | I21: 0 | M21: =(F21-E21)/E21 -> -0.25416667 | N21: =(G21-F21)/F21 -> -0.67517957 | O21: =(H21-G21)/G21 -> -0.94348894 | P21: =(I21-H21)/H21 -> -1
D22: Trade Payables | E22: 802.8 | F22: 1293.8 | G22: 1493.9 | H22: 1549.9 | I22: 2061 | M22: =(F22-E22)/E22 -> 0.61160937 | N22: =(G22-F22)/F22 -> 0.15466069 | O22: =(H22-G22)/G22 -> 0.037485775 | P22: =(I22-H22)/H22 -> 0.32976321
D23: Other Current Liabilities | E23: 1560.1 | F23: 3250.1 | G23: 3360 | H23: 3444.6 | I23: 6548.6 | M23: =(F23-E23)/E23 -> 1.0832639 | N23: =(G23-F23)/F23 -> 0.033814344 | O23: =(H23-G23)/G23 -> 0.025178571 | P23: =(I23-H23)/H23 -> 0.90112059
D24: Short Term Provisions | E24: 387.4 | F24: 813.4 | G24: 848.6 | H24: 969.1 | I24: 1174.1 | M24: =(F24-E24)/E24 -> 1.0996386 | N24: =(G24-F24)/F24 -> 0.043275141 | O24: =(H24-G24)/G24 -> 0.14199859 | P24: =(I24-H24)/H24 -> 0.21153648
D25: Total Current Liabilities | E25: =E21+E22+E23+E24 -> 2918.3 | F25: =F21+F22+F23+F24 -> 5482.6 | G25: =G21+G22+G23+G24 -> 5743.2 | H25: =H21+H22+H23+H24 -> 5965.9 | I25: =I21+I22+I23+I24 -> 9783.7 | M25: =(F25-E25)/E25 -> 0.8786965 | N25: =(G25-F25)/F25 -> 0.047532193 | O25: =(H25-G25)/G25 -> 0.038776292 | P25: =(I25-H25)/H25 -> 0.63993698
D26: Total Capital And Liabilities | E26: =E11+E12+E13+E19+E25 -> 12469.3 | F26: =F11+F12+F13+F19+F25 -> 23496.1 | G26: =G11+G12+G13+G19+G25 -> 27563 | H26: =H11+H12+H13+H19+H25 -> 30630 | I26: =I11+I12+I13+I19+I25 -> 37196 | M26: =(F26-E26)/E26 -> 0.88431588 | N26: =(G26-F26)/F26 -> 0.1730883 | O26: =(H26-G26)/G26 -> 0.11127236 | P26: =(I26-H26)/H26 -> 0.214365
D27: ASSETS
D28: NON-CURRENT ASSETS
D29: Tangible Assets | E29: 1135.9 | F29: 2223.6 | G29: 3556.8 | H29: 3963.1 | I29: 4175.6 | M29: =(F29-E29)/E29 -> 0.95756669 | N29: =(G29-F29)/F29 -> 0.59956827 | O29: =(H29-G29)/G29 -> 0.11423189 | P29: =(I29-H29)/H29 -> 0.053619641
D30: Intangible Assets | E30: 271.8 | F30: 266.3 | G30: 231.3 | H30: 118 | I30: 162.9 | M30: =(F30-E30)/E30 -> -0.020235467 | N30: =(G30-F30)/F30 -> -0.13143072 | O30: =(H30-G30)/G30 -> -0.48984003 | P30: =(I30-H30)/H30 -> 0.38050847
D31: Capital Work-In-Progress | E31: 437.4 | F31: 812.6 | G31: 466.9 | H31: 581.8 | I31: 917.1 | M31: =(F31-E31)/E31 -> 0.85779607 | N31: =(G31-F31)/F31 -> -0.42542456 | O31: =(H31-G31)/G31 -> 0.24609124 | P31: =(I31-H31)/H31 -> 0.57631488
D32: Intangible Assets Under Development | E32: 43.9 | F32: 89.7 | G32: 83.8 | H32: 99.6 | I32: 0 | M32: =(F32-E32)/E32 -> 1.0432802 | N32: =(G32-F32)/F32 -> -0.065774805 | O32: =(H32-G32)/G32 -> 0.18854415 | P32: =(I32-H32)/H32 -> -1
D33: Fixed Assets | E33: =E29+E30+E31+E32 -> 1889 | F33: =F29+F30+F31+F32 -> 3392.2 | G33: =G29+G30+G31+G32 -> 4338.8 | H33: =H29+H30+H31+H32 -> 4762.5 | I33: =I29+I30+I31+I32 -> 5255.6 | M33: =(F33-E33)/E33 -> 0.79576496 | N33: =(G33-F33)/F33 -> 0.27905194 | O33: =(H33-G33)/G33 -> 0.097653729 | P33: =(I33-H33)/H33 -> 0.10353806
D34: Non-Current Investments | E34: 345.4 | F34: 716.5 | G34: 1990.2 | H34: 2470.6 | I34: 532.2 | M34: =(F34-E34)/E34 -> 1.0744065 | N34: =(G34-F34)/F34 -> 1.7776692 | O34: =(H34-G34)/G34 -> 0.24138278 | P34: =(I34-H34)/H34 -> -0.78458674
D35: Deferred Tax Assets [Net] | E35: 54.9 | F35: 380.9 | G35: 225 | H35: 222 | I35: 951.8 | M35: =(F35-E35)/E35 -> 5.9380692 | N35: =(G35-F35)/F35 -> -0.40929378 | O35: =(H35-G35)/G35 -> -0.013333333 | P35: =(I35-H35)/H35 -> 3.2873874
D36: Long Term Loans And Advances | E36: 0 | F36: 0 | G36: 0 | H36: 0 | I36: 0
D37: Other Non-Current Assets | E37: 624.4 | F37: 631.5 | G37: 969.9 | H37: 1033.4 | I37: 1466.9 | M37: =(F37-E37)/E37 -> 0.011370916 | N37: =(G37-F37)/F37 -> 0.53586698 | O37: =(H37-G37)/G37 -> 0.065470667 | P37: =(I37-H37)/H37 -> 0.41948907
D38: Total Non-Current Assets | E38: 3603.7 | F38: 6310.3 | G38: 8716.6 | H38: 9692.1 | I38: 9498.8 | M38: =(F38-E38)/E38 -> 0.75106141 | N38: =(G38-F38)/F38 -> 0.38132894 | O38: =(H38-G38)/G38 -> 0.1119129 | P38: =(I38-H38)/H38 -> -0.019944078
D39: CURRENT ASSETS
D40: Current Investments | E40: 3136.6 | F40: 4741.8 | G40: 6753.4 | H40: 7374 | I40: 12035.5 | M40: =(F40-E40)/E40 -> 0.51176433 | N40: =(G40-F40)/F40 -> 0.42422709 | O40: =(H40-G40)/G40 -> 0.091894453 | P40: =(I40-H40)/H40 -> 0.63215351
D41: Inventories | E41: 0 | F41: 3.3 | G41: 3 | H41: 2.8 | I41: 3.3 | N41: =(G41-F41)/F41 -> -0.090909091 | O41: =(H41-G41)/G41 -> -0.066666667 | P41: =(I41-H41)/H41 -> 0.17857143
D42: Trade Receivables | E42: 2833.5 | F42: 5623.4 | G42: 5706 | H42: 5867.6 | I42: 7424.8 | M42: =(F42-E42)/E42 -> 0.98461267 | N42: =(G42-F42)/F42 -> 0.014688623 | O42: =(H42-G42)/G42 -> 0.028321066 | P42: =(I42-H42)/H42 -> 0.2653896
D43: Cash And Cash Equivalents | E43: 777.3 | F43: 2932 | G43: 2816 | H43: 3588.2 | I43: 2812.4 | M43: =(F43-E43)/E43 -> 2.7720314 | N43: =(G43-F43)/F43 -> -0.039563438 | O43: =(H43-G43)/G43 -> 0.27421875 | P43: =(I43-H43)/H43 -> -0.21620868
D44: Short Term Loans And Advances | E44: 0 | F44: 0 | G44: 0 | H44: 0 | I44: 0
D45: OtherCurrentAssets | E45: 2118.2 | F45: 3885.3 | G45: 3568 | H45: 4105.3 | I45: 5421.2 | M45: =(F45-E45)/E45 -> 0.83424606 | N45: =(G45-F45)/F45 -> -0.081666795 | O45: =(H45-G45)/G45 -> 0.15058857 | P45: =(I45-H45)/H45 -> 0.32053687
D46: Total Current Assets | E46: =E40+E41+E42+E43+E44+E45 -> 8865.6 | F46: =F40+F41+F42+F43+F44+F45 -> 17185.8 | G46: =G40+G41+G42+G43+G44+G45 -> 18846.4 | H46: =H40+H41+H42+H43+H44+H45 -> 20937.9 | I46: =I40+I41+I42+I43+I44+I45 -> 27697.2 | M46: =(F46-E46)/E46 -> 0.93848132 | N46: =(G46-F46)/F46 -> 0.096626284 | O46: =(H46-G46)/G46 -> 0.1109761 | P46: =(I46-H46)/H46 -> 0.32282607
D47: Total Assets | E47: =E38+E46 -> 12469.3 | F47: =F38+F46 -> 23496.1 | G47: =G38+G46 -> 27563 | H47: =H38+H46 -> 30630 | I47: =I38+I46 -> 37196 | M47: =(F47-E47)/E47 -> 0.88431588 | N47: =(G47-F47)/F47 -> 0.1730883 | O47: =(H47-G47)/G47 -> 0.11127236 | P47: =(I47-H47)/H47 -> 0.214365
D48: OTHER ADDITIONAL INFORMATION
D49: CONTINGENT LIABILITIES, COMMITMENTS
D50: Contingent Liabilities | E50: 708.7 | F50: 517.9 | G50: 1218.4 | H50: 2746.4 | I50: 0 | M50: =(F50-E50)/E50 -> -0.26922534 | N50: =(G50-F50)/F50 -> 1.3525777 | O50: =(H50-G50)/G50 -> 1.2541037 | P50: =(I50-H50)/H50 -> -1
D51: BONUS DETAILS
D52: NON-CURRENT INVESTMENTS
D53: Non-Current Investments Quoted Market Value | E53: 0 | F53: 574.1 | G53: 1801.2 | H53: 2193.8 | I53: 0 | N53: =(G53-F53)/F53 -> 2.1374325 | O53: =(H53-G53)/G53 -> 0.2179658 | P53: =(I53-H53)/H53 -> -1
D54: Non-Current Investments Unquoted Book Value | E54: 142.3 | F54: 132.5 | G54: 228.6 | H54: 348.5 | I54: 0 | M54: =(F54-E54)/E54 -> -0.068868587 | N54: =(G54-F54)/F54 -> 0.72528302 | O54: =(H54-G54)/G54 -> 0.52449694 | P54: =(I54-H54)/H54 -> -1
D55: CURRENT INVESTMENTS
D56: Current Investments Quoted Market Value | E56: 2856.6 | F56: 3858.2 | G56: 6295.1 | H56: 6815.1 | I56: 0 | M56: =(F56-E56)/E56 -> 0.35062662 | N56: =(G56-F56)/F56 -> 0.63161578 | O56: =(H56-G56)/G56 -> 0.08260393 | P56: =(I56-H56)/H56 -> -1
D57: Current Investments Unquoted Book Value | E57: 280 | F57: 884.6 | G57: 421 | H57: 516.7 | I57: 0 | M57: =(F57-E57)/E57 -> 2.1592857 | N57: =(G57-F57)/F57 -> -0.52407868 | O57: =(H57-G57)/G57 -> 0.22731591 | P57: =(I57-H57)/H57 -> -1

Sheet Fixed assets scheduled
A1: Particular | B1: 44621 | C1: 44986 | D1: 45352 | E1: 45717 | F1: 46082
A2: Beginning balance | C2: =B6 -> 1889 | D2: =C6 -> 3392.2 | E2: =D6 -> 4338.8 | F2: =E6 -> 4762.5
A3: Add: Net Purchases | C3: =C6-C2+C5 -> 2225.9 | D3: =D6-D2+D5 -> 1765.5 | E3: =E6-E2+E5 -> 1415.2 | F3: =F6-F2+F5 -> 1547.2
A4: Total Fixed Assets | B4: =B5+B6 -> 2243.9 | C4: =C5+C6 -> 4114.9 | D4: =D5+D6 -> 5157.7 | E4: =E5+E6 -> 5754 | F4: =F5+F6 -> 6309.7
A5: Less: Depreciation | B5: ='Consolidated P&L'!F14 -> 354.9 | C5: ='Consolidated P&L'!G14 -> 722.7 | D5: ='Consolidated P&L'!H14 -> 818.9 | E5: ='Consolidated P&L'!I14 -> 991.5 | F5: ='Consolidated P&L'!J14 -> 1054.1
A6: Closing Balance(Fixed Asests ) | B6: ='Consolidated Balance sheet'!E33 -> 1889 | C6: ='Consolidated Balance sheet'!F33 -> 3392.2 | D6: ='Consolidated Balance sheet'!G33 -> 4338.8 | E6: ='Consolidated Balance sheet'!H33 -> 4762.5 | F6: ='Consolidated Balance sheet'!I33 -> 5255.6
A8: Net Capital expenditure | C8: =C3-C5 -> 1503.2 | D8: =D3-D5 -> 946.6 | E8: =E3-E5 -> 423.7 | F8: =F3-F5 -> 493.1
A9: Net Capital expenditure / Sales percentage | C9: =C8/'Consolidated P&L'!G7 -> 0.045300304 | D9: =D8/'Consolidated P&L'!H7 -> 0.026652026 | E9: =E8/'Consolidated P&L'!I7 -> 0.011147624 | F9: =F8/'Consolidated P&L'!J7 -> 0.011655116
A11: Median Capital expenditure /Sales percentage | C11: =MEDIAN(C9:F9) -> 0.019153571
A12: Average Capital expenditure /Sales percentage | C12: =AVERAGE(C9:F9) -> 0.023688768

Sheet Change in working capital
A1: Particular | B1: 44621 | C1: 44986 | D1: 45352 | E1: 45717 | F1: 46082
A2: Inventory | B2: ='Merge data sheet'!B41 -> 0 | C2: ='Merge data sheet'!C41 -> 3.3 | D2: ='Merge data sheet'!D41 -> 3 | E2: ='Merge data sheet'!E41 -> 2.8 | F2: ='Merge data sheet'!F41 -> 3.3
A3: Trade Receivables | B3: ='Merge data sheet'!B42 -> 2833.5 | C3: ='Merge data sheet'!C42 -> 5623.4 | D3: ='Merge data sheet'!D42 -> 5706 | E3: ='Merge data sheet'!E42 -> 5867.6 | F3: ='Merge data sheet'!F42 -> 7424.8
A4: Trade Payable | B4: ='Merge data sheet'!B22 -> 802.8 | C4: ='Merge data sheet'!C22 -> 1293.8 | D4: ='Merge data sheet'!D22 -> 1493.9 | E4: ='Merge data sheet'!E22 -> 1549.9 | F4: ='Merge data sheet'!F22 -> 2061
A5: Non Cash working Capital | B5: =B2+B3-B4 -> 2030.7 | C5: =C2+C3-C4 -> 4332.9 | D5: =D2+D3-D4 -> 4215.1 | E5: =E2+E3-E4 -> 4320.5 | F5: =F2+F3-F4 -> 5367.1
A6: Change in Working Capital | C6: =C5-B5 -> 2302.2 | D6: =D5-C5 -> -117.8 | E6: =E5-D5 -> 105.4 | F6: =F5-E5 -> 1046.6
A7: change in working Capital /percentage of sales | C7: =C6/'Merge data sheet'!B64 -> 0.14692987 | D7: =D6/'Merge data sheet'!C64 -> -0.0035500105 | E7: =E6/'Merge data sheet'!D64 -> 0.002967593 | F7: =F6/'Merge data sheet'!E64 -> 0.027536236
A9: Median Non Cash working Capital /Sales percentage | C9: =MEDIAN(C7:F7) -> 0.015251914
A10: Average Non Cash working Capital /Sales percentage | C10: =AVERAGE(C7:F7) -> 0.043470921

Sheet Peers
D3: LTIM | E3: LTIMindtree is a global technology consulting and digital solutions company that enables enterprises across industries to reimagine business models, accelerate innovation, and maximize growth by harnessing digital technologies. As a digital transformation partner to more than 700 clients, LTIMindtree brings extensive domain and technology expertise to help drive superior competitive differentiation, customer experiences, and business outcomes in a converging world. Powered by 83,000+ talented and entrepreneurial professionals across more than 40 countries, LTIMindtree - a Larsen & Toubro Group company - solves the most complex business challenges and delivers transformation at scale. LTP: ₹5,124.50 | Revenue (FY25): ₹38,008 Cr | PAT: ₹4,602 Cr | OPM: 17.08% | NPM: 12.09% | EPS: ₹155.22 | CEPS: ₹184.49 | ROCE: 28.60%
D7: TCS | E7: Tata Consultancy Services is an IT solution provider.TCS offers a consulting-led, integrated portfolio of IT and IT-enabled services delivered through its unique Global Network Delivery Model, recognized as the benchmark of excellence in software development..The company also engagged in the business of Telecom, Retail and Distribution, Banking, Financial Services and Insurance. LTP: ₹2,583.60 | Revenue (FY25): ₹2,55,324 Cr | PAT: ₹48,553 Cr | OPM: 26.40% | NPM: 19.01% | EPS: ₹134.13 | CEPS: ₹159.25 | ROCE: 69.78%
D11: Infosys | E11: Infosys Limited (Infosys), formerly Infosys Technologies Limited, provides business consulting, technology, engineering and outsourcing services. Its end-to-end business solutions include consulting and systems integration comprising consulting, enterprise solutions, systems integration and advanced technologies; business information technology (IT) services consisting application development and maintenance, independent validation services, infrastructure management, engineering services comprising product engineering and life cycle solutions and business process management; products, business platforms and solutions, including Finacle, its banking product, which offers solutions to address core banking, mobile banking and e-banking needs of retail, corporate and universal banks globally, and areas, such as cloud computing, enterprise mobility and sustainability. On January 4, 2012, Infosys BPO Limited acquired Portland Group Pty Ltd. In October 2012, it acquired Lodestone Holding AG..The company also in the business segment of Financial Services, Energy & utilities, Life Sciences and Healthcare, Consumer packaged goods and Logistics. LTP: ₹1,323.30 | Revenue (FY25): ₹1,60,879 Cr | PAT: ₹26,248 Cr | OPM: 23.70% | NPM: 16.38% | EPS: ₹63.02 | CEPS: ₹72.88 | ROCE: 39.68%
D15: HCL Tech | E15: HCL Technologies Ltd is a leading global IT services company. It has portfolio of services including software-led IT solutions, remote infrastructure management, engineering and R&D services and BPO..The company also in the business activities of IT services, Infrastructure Services, Business Process Outsourcing Services. LTP: ₹1,458.00 | Revenue (FY25): ₹1,16,647 Cr | PAT: ₹17,327 Cr | OPM: 21.78% | NPM: 14.85% | EPS: ₹63.94 | CEPS: ₹79.00 | ROCE: 33.22%
E20: Attribute | F20: LTP (₹) | G20: Change (%) | H20: Sales (₹ crore) | I20: PAT (₹ crore) | J20: Equity (₹ crore) | K20: Operating Profit Margin (OPM%) | L20: Net Profit Margin (NPM%) | M20: Earnings Per Share (EPS) | N20: Cash Earnings Per Share (CEPS)
E21: LTIM | F21: 5124.5 | H21: 38008 | I21: 4602 | J21: 29 | K21: 0.1708 | L21: 0.1209 | M21: 155.22 | N21: 184.49
E22: TCS | F22: 2583.6 | G22: -21.32 | H22: 255324 | I22: 48553 | J22: 362 | K22: 0.264 | L22: 0.1901 | M22: 134.13 | N22: 159.25
E23: INFOSYS | F23: 1323.3 | G23: -9.54 | H23: 160879 | I23: 26248 | J23: 2090 | K23: 0.237 | L23: 0.1638 | M23: 63.02 | N23: 72.88
E24: HCL TECH | F24: 1458 | H24: 116647 | I24: 17327 | J24: 542 | K24: 0.2178 | L24: 0.1485 | M24: 63.94 | N24: 79
E27: LTIM | L27: TCS
E28: Metric | F28: 44986 | G28: 45352 | H28: 45717 | L28: Metric | M28: 44986 | N28: 45352 | O28: 45717
E29: Debtor Days | F29: 46.5 | G29: 58.2 | H29: 55.6 | L29: Debtor Days | M29: 68 | N29: 78.5 | O29: 80.6
E30: Inventory Days | F30: 0 | G30: 0 | H30: 0 | L30: Inventory Days | M30: 0 | N30: 0 | O30: 0
E31: Days Payable | F31: 26.7 | G31: 47.4 | H31: 40.5 | L31: Days Payable | M31: 50.4 | N31: 58.5 | O31: 63.9
E32: Cash Conversion Cycle | F32: 19.8 | G32: 10.8 | H32: 15.1 | L32: Cash Conversion Cycle | M32: 17.6 | N32: 20 | O32: 16.7
E33: Working Capital Days | F33: 19.78 | G33: 10.77 | H33: 15.11 | L33: Working Capital Days | M33: 17.56 | N33: 20.04 | O33: 16.68
E34: ROCE % | F34: 0.366 | G34: 0.3203 | H34: 0.286 | L34: ROCE % | M34: 0.6379 | N34: 0.7043 | O34: 0.6978
E37: INFOSYS | L37: HCL TECH
E38: Metric | F38: 44986 | G38: 45352 | H38: 45717 | L38: Metric | M38: 44986 | N38: 45352 | O38: 45717
E39: Debtor Days | F39: 59.8 | G39: 66 | H39: 68.7 | L39: Debtor Days | M39: 83.1 | N39: 84.7 | O39: 80
E40: Inventory Days | F40: 0 | G40: 0 | H40: 0 | L40: Inventory Days | M40: 0 | N40: 0 | O40: 0
E41: Days Payable | F41: 86.8 | G41: 71.4 | H41: 57.8 | L41: Days Payable | M41: 20.3 | N41: 23.2 | O41: 27.4
E42: Cash Conversion Cycle | F42: -27 | G42: -5.4 | H42: 10.9 | L42: Cash Conversion Cycle | M42: 62.8 | N42: 61.5 | O42: 52.6
E43: Working Capital Days | F43: -27.05 | G43: -5.44 | H43: 10.95 | L43: Working Capital Days | M43: 62.78 | N43: 61.5 | O43: 52.56
E44: ROCE % | F44: 0.4509 | G44: 0.4137 | H44: 0.3968 | L44: ROCE % | M44: 0.2932 | N44: 0.3048 | O44: 0.3322

Sheet Stock Analysis
C22: Metric | D22: Value | F22: Financial Year | G22: Revenue (₹ Crore) | H22: Profit After Tax (PAT) (₹ Crore) | I22: Revenue Change (%) | J22: PAT Change (%) | K22: Nifty 50 Change (%) | L22: Nifty 50 Prices
C23: Market Cap | D23: 138154 | F23: FY 2024-25 | G23: 38008.1 | H23: 4602 | I23: =((G23-G24)/G24) -> 0.070138244 | J23: =(H23-H24)/H24 -> 0.0037953147 | K23: =(L23-L24)/L24 -> 0.076503494 | L23: 24334.2
C24: Current Price | D24: 4662.3 | F24: FY 2023-24 | G24: 35517 | H24: 4584.6 | I24: =((G24-G25)/G25) -> 0.070337221 | J24: =(H24-H25)/H25 -> 0.039521121 | K24: =(L24-L25)/L25 -> 0.25130639 | L24: 22604.85
C25: High / Low | D25: 4703.80/4630.10 | F25: FY 2022-23 | G25: 33183 | H25: 4410.3 | I25: =((G25-G26)/G26) -> 1.117789 | J25: =(H25-H26)/H26 -> 0.91877311 | K25: =(L25-L26)/L26 -> 0.056275234 | L25: 18065
C26: Stock P/E | D26: 29.04 | F26: FY 2021-22 | G26: 15668.7 | H26: 2298.5 | I26: =((G26-G27)/G27) -> 0.26668984 | J26: =(H26-H27)/H27 -> 0.18589413 | K26: =(L26-L27)/L27 -> 0.16891758 | L26: 17102.55
C27: Book Value | D27: 821.7 | F27: FY 2020-21 | G27: 12369.8 | H27: 1938.2 | L27: 14631.1
C28: Dividend Yield | D28: 1.4
C29: ROCE | D29: 0.2634
C30: ROE | D30: 0.2036 | F30: LTIM is a genuinely strong company - zero debt, ₹10,962 Cr cash, L&T backing, and solid revenue growth. But the stock got hammered 38% from its peak because margins are terrible vs peers (17% vs TCS's 26%), EPS didn't grow at all in FY25, and a ₹590 Cr one-time restructuring charge destroyed Q3 FY26 numbers. The market overreacted. The beaten-down price at ₹4,200-4,500 is where you should accumulate in tranches. If Q4 results come clean and margins start recovering toward 18%+ the stock can realistically re-rate to ₹5,200-5,800 in 12–18 months. The one thing you keep watching: margin expansion - that's the entire thesis.
C31: Face Value | D31: 1
F39: Accumulate & Hold. Don't panic sell. BUY in Tranches The stock is down 26% from its peak - mostly because of a one-time restructuring charge, not because the business is broken. Fundamentals are intact, balance sheet is rock solid, and Q4 results are out today. This is a beaten-down quality stock, not a failing one.

Sheet BETA
A1: Date | B1: Close (Nifty) | C1: Date | D1: Close(Ltim) | G1: Rm Nifty | H1: Rm LTIM | I1: Beta | J1: Covariance
A2: 43922 | B2: 8253.8 | C2: 43922 | D2: 1295.58
A3: 43924 | B3: 8083.8 | C3: 43924 | D3: 1260.13 | G3: =(B3-B2)/B2 -> -0.020596574 | H3: =(D3-D2)/D2 -> -0.027362262 | I3: =SLOPE(H3:H1482,G3:G1482) -> 0.83831404 | J3: =_xlfn.COVARIANCE.S(H3:H1482,G3:G1482)/_xlfn.VAR.S(G3:G1482) -> 0.83831404
A4: 43928 | B4: 8792.2 | C4: 43928 | D4: 1272.22 | G4: =(B4-B3)/B3 -> 0.087632054 | H4: =(D4-D3)/D3 -> 0.0095942482
A5: 43929 | B5: 8748.75 | C5: 43929 | D5: 1261.38 | G5: =(B5-B4)/B4 -> -0.0049418803 | H5: =(D5-D4)/D4 -> -0.0085205389
A6: 43930 | B6: 9111.9 | C6: 43930 | D6: 1301.54 | G6: =(B6-B5)/B5 -> 0.041508787 | H6: =(D6-D5)/D5 -> 0.031838146
A7: 43934 | B7: 8993.85 | C7: 43934 | D7: 1302.09 | G7: =(B7-B6)/B6 -> -0.012955586 | H7: =(D7-D6)/D6 -> 0.00042257633
A8: 43936 | B8: 8925.3 | C8: 43936 | D8: 1368.4 | G8: =(B8-B7)/B7 -> -0.0076218749 | H8: =(D8-D7)/D7 -> 0.050925819
A9: 43937 | B9: 8992.8 | C9: 43937 | D9: 1365.93 | G9: =(B9-B8)/B8 -> 0.007562771 | H9: =(D9-D8)/D8 -> -0.0018050278
A10: 43938 | B10: 9266.75 | C10: 43938 | D10: 1344.39 | G10: =(B10-B9)/B9 -> 0.030463259 | H10: =(D10-D9)/D9 -> -0.015769476
A11: 43941 | B11: 9261.85 | C11: 43941 | D11: 1388.5 | G11: =(B11-B10)/B10 -> -0.00052877222 | H11: =(D11-D10)/D10 -> 0.03281042
A12: 43942 | B12: 8981.45 | C12: 43942 | D12: 1349.23 | G12: =(B12-B11)/B11 -> -0.030274729 | H12: =(D12-D11)/D11 -> -0.028282319
A13: 43943 | B13: 9187.3 | C13: 43943 | D13: 1319.96 | G13: =(B13-B12)/B12 -> 0.022919462 | H13: =(D13-D12)/D12 -> -0.021693855
A14: 43944 | B14: 9313.9 | C14: 43944 | D14: 1357.84 | G14: =(B14-B13)/B13 -> 0.013779892 | H14: =(D14-D13)/D13 -> 0.028697839
A15: 43945 | B15: 9154.4 | C15: 43945 | D15: 1334.25 | G15: =(B15-B14)/B14 -> -0.017124942 | H15: =(D15-D14)/D14 -> -0.017373181
A16: 43948 | B16: 9282.3 | C16: 43948 | D16: 1349.93 | G16: =(B16-B15)/B15 -> 0.013971424 | H16: =(D16-D15)/D15 -> 0.011751921 | L16: SUMMARY OUTPUT
A17: 43949 | B17: 9380.9 | C17: 43949 | D17: 1364.07 | G17: =(B17-B16)/B16 -> 0.010622367 | H17: =(D17-D16)/D16 -> 0.010474617
A18: 43950 | B18: 9553.35 | C18: 43950 | D18: 1363.33 | G18: =(B18-B17)/B17 -> 0.018383098 | H18: =(D18-D17)/D17 -> -0.00054249415 | L18: Regression Statistics
A19: 43951 | B19: 9859.9 | C19: 43951 | D19: 1482.35 | G19: =(B19-B18)/B18 -> 0.03208822 | H19: =(D19-D18)/D18 -> 0.087300947 | L19: Multiple R | M19: 0.39971074
A20: 43955 | B20: 9293.5 | C20: 43955 | D20: 1438.05 | G20: =(B20-B19)/B19 -> -0.057444802 | H20: =(D20-D19)/D19 -> -0.02988498 | L20: R Square | M20: 0.15976867
A21: 43956 | B21: 9205.6 | C21: 43956 | D21: 1428.79 | G21: =(B21-B20)/B20 -> -0.0094582235 | H21: =(D21-D20)/D20 -> -0.0064392754 | L21: Adjusted R Square | M21: 0.15920018
A22: 43957 | B22: 9270.9 | C22: 43957 | D22: 1429.44 | G22: =(B22-B21)/B21 -> 0.0070935083 | H22: =(D22-D21)/D21 -> 0.0004549304 | L22: Standard Error | M22: 0.018849085
A23: 43958 | B23: 9199.05 | C23: 43958 | D23: 1482.62 | G23: =(B23-B22)/B22 -> -0.0077500566 | H23: =(D23-D22)/D22 -> 0.03720338 | L23: Observations | M23: 1480
A24: 43959 | B24: 9251.5 | C24: 43959 | D24: 1474.62 | G24: =(B24-B23)/B23 -> 0.0057016757 | H24: =(D24-D23)/D23 -> -0.0053958533
A25: 43962 | B25: 9239.2 | C25: 43962 | D25: 1502.12 | G25: =(B25-B24)/B24 -> -0.0013295141 | H25: =(D25-D24)/D24 -> 0.018648872 | L25: ANOVA
A26: 43963 | B26: 9196.55 | C26: 43963 | D26: 1533.9 | G26: =(B26-B25)/B25 -> -0.0046162005 | H26: =(D26-D25)/D25 -> 0.021156765 | M26: df | N26: SS | O26: MS | P26: F | Q26: Significance F
A27: 43964 | B27: 9383.55 | C27: 43964 | D27: 1541.44 | G27: =(B27-B26)/B26 -> 0.020333712 | H27: =(D27-D26)/D26 -> 0.0049155747 | L27: Regression | M27: 1 | N27: 0.099849927 | O27: 0.099849927 | P27: 281.03939 | Q27: 6.9906567e-58
A28: 43965 | B28: 9142.75 | C28: 43965 | D28: 1533.81 | G28: =(B28-B27)/B27 -> -0.02566193 | H28: =(D28-D27)/D27 -> -0.004949917 | L28: Residual | M28: 1478 | N28: 0.52511568 | O28: 0.00035528801
A29: 43966 | B29: 9136.85 | C29: 43966 | D29: 1531.53 | G29: =(B29-B28)/B28 -> -0.00064532006 | H29: =(D29-D28)/D28 -> -0.0014864944 | L29: Total | M29: 1479 | N29: 0.62496561
A30: 43969 | B30: 8823.25 | C30: 43969 | D30: 1531.39 | G30: =(B30-B29)/B29 -> -0.034322551 | H30: =(D30-D29)/D29 -> -9.1411856e-05
A31: 43970 | B31: 8879.1 | C31: 43970 | D31: 1554.19 | G31: =(B31-B30)/B30 -> 0.0063298671 | H31: =(D31-D30)/D30 -> 0.014888435 | M31: Coefficients | N31: Standard Error | O31: t Stat | P31: P-value | Q31: Lower 95% | R31: Upper 95% | S31: Lower 95.0% | T31: Upper 95.0%
A32: 43971 | B32: 9066.55 | C32: 43971 | D32: 1660.13 | G32: =(B32-B31)/B31 -> 0.021111374 | H32: =(D32-D31)/D31 -> 0.068164124 | L32: Intercept | M32: 0.00037025714 | N32: 0.00049128236 | O32: 0.75365444 | P32: 0.45117678 | Q32: -0.00059342777 | R32: 0.001333942 | S32: -0.00059342777 | T32: 0.001333942
A33: 43972 | B33: 9106.25 | C33: 43972 | D33: 1660.97 | G33: =(B33-B32)/B32 -> 0.0043787328 | H33: =(D33-D32)/D32 -> 0.00050598447 | L33: X Variable 1 | M33: 0.83831404 | N33: 0.050006118 | O33: 16.76423 | P33: 6.9906567e-58 | Q33: 0.74022352 | R33: 0.93640456 | S33: 0.74022352 | T33: 0.93640456
A34: 43973 | B34: 9039.25 | C34: 43973 | D34: 1662.6 | G34: =(B34-B33)/B33 -> -0.0073575841 | H34: =(D34-D33)/D33 -> 0.00098135427
A35: 43977 | B35: 9029.05 | C35: 43977 | D35: 1663.15 | G35: =(B35-B34)/B34 -> -0.0011284122 | H35: =(D35-D34)/D34 -> 0.00033080717
A36: 43978 | B36: 9314.95 | C36: 43978 | D36: 1669.62 | G36: =(B36-B35)/B35 -> 0.031664461 | H36: =(D36-D35)/D35 -> 0.0038902083
A37: 43979 | B37: 9490.1 | C37: 43979 | D37: 1668.88 | G37: =(B37-B36)/B36 -> 0.018803107 | H37: =(D37-D36)/D36 -> -0.00044321462
A38: 43980 | B38: 9580.3 | C38: 43980 | D38: 1673.95 | G38: =(B38-B37)/B37 -> 0.0095046417 | H38: =(D38-D37)/D37 -> 0.0030379656
A39: 43983 | B39: 9826.15 | C39: 43983 | D39: 1714.99 | G39: =(B39-B38)/B38 -> 0.025662036 | H39: =(D39-D38)/D38 -> 0.024516861
A40: 43984 | B40: 9979.1 | C40: 43984 | D40: 1729.5 | G40: =(B40-B39)/B39 -> 0.015565608 | H40: =(D40-D39)/D39 -> 0.0084606907
A41: 43985 | B41: 10061.55 | C41: 43985 | D41: 1720.01 | G41: =(B41-B40)/B40 -> 0.0082622681 | H41: =(D41-D40)/D40 -> -0.005487135
A42: 43986 | B42: 10029.1 | C42: 43986 | D42: 1732.02 | G42: =(B42-B41)/B41 -> -0.0032251492 | H42: =(D42-D41)/D41 -> 0.0069825175
A43: 43987 | B43: 10142.15 | C43: 43987 | D43: 1728.29 | G43: =(B43-B42)/B42 -> 0.011272198 | H43: =(D43-D42)/D42 -> -0.0021535548
A44: 43990 | B44: 10167.45 | C44: 43990 | D44: 1740.16 | G44: =(B44-B43)/B43 -> 0.0024945401 | H44: =(D44-D43)/D43 -> 0.0068680603
A45: 43991 | B45: 10046.65 | C45: 43991 | D45: 1754.49 | G45: =(B45-B44)/B44 -> -0.011881052 | H45: =(D45-D44)/D44 -> 0.008234875
... A1482: 46111 | B1482: 22331.4 | C1482: 46111 | D1482: 4013.8 | G1482: =(B1482-B1481)/B1481 -> -0.021393889 | H1482: =(D1482-D1481)/D1481 -> -0.044492585

Sheet Ratio Analysis
A1: Ratio Analysis- LTIM
A2: Years | B2: 44621 | C2: 44986 | D2: 45352 | E2: 45717 | F2: 46082 | G2: Trends | H2: Mean | I2: Median
A4: Sales Growth | C4: =('Consolidated P&L'!G5-'Consolidated P&L'!F5)/'Consolidated P&L'!F5 -> 1.117789 | D4: =('Consolidated P&L'!H5-'Consolidated P&L'!G5)/'Consolidated P&L'!G5 -> 0.070337221 | E4: =('Consolidated P&L'!I5-'Consolidated P&L'!H5)/'Consolidated P&L'!H5 -> 0.070138244 | F4: =('Consolidated P&L'!J5-'Consolidated P&L'!I5)/'Consolidated P&L'!I5 -> 0.11312062 | H4: =AVERAGE(C4:F4) -> 0.34284626 | I4: =MEDIAN(C4:F4) -> 0.091728923
A5: EBITDA Growth | C5: =('Assumptions (Historical FS)'!C9-'Assumptions (Historical FS)'!B9)/'Assumptions (Historical FS)'!B9 -> 0.99702459 | D5: =('Assumptions (Historical FS)'!D9-'Assumptions (Historical FS)'!C9)/'Assumptions (Historical FS)'!C9 -> 0.045794653 | E5: =('Assumptions (Historical FS)'!E9-'Assumptions (Historical FS)'!D9)/'Assumptions (Historical FS)'!D9 -> 0.016830009 | F5: =('Assumptions (Historical FS)'!F9-'Assumptions (Historical FS)'!E9)/'Assumptions (Historical FS)'!E9 -> 0.16325117 | H5: =AVERAGE(C5:F5) -> 0.3057251 | I5: =MEDIAN(C5:F5) -> 0.10452291
A6: EBIT Growth | C6: =('Assumptions (Historical FS)'!C11-'Assumptions (Historical FS)'!B11)/'Assumptions (Historical FS)'!B11 -> 0.9918624 | D6: =('Assumptions (Historical FS)'!D11-'Assumptions (Historical FS)'!C11)/'Assumptions (Historical FS)'!C11 -> 0.034076137 | E6: =('Assumptions (Historical FS)'!E11-'Assumptions (Historical FS)'!D11)/'Assumptions (Historical FS)'!D11 -> -0.011690761 | F6: =('Assumptions (Historical FS)'!F11-'Assumptions (Historical FS)'!E11)/'Assumptions (Historical FS)'!E11 -> 0.18128793 | H6: =AVERAGE(C6:F6) -> 0.29888393 | I6: =MEDIAN(C6:F6) -> 0.10768203
A7: Net Profit Growth | C7: =('Assumptions (Historical FS)'!C18-'Assumptions (Historical FS)'!B18)/'Assumptions (Historical FS)'!B18 -> 0.9182245 | D7: =('Assumptions (Historical FS)'!D18-'Assumptions (Historical FS)'!C18)/'Assumptions (Historical FS)'!C18 -> 0.039616527 | E7: =('Assumptions (Historical FS)'!E18-'Assumptions (Historical FS)'!D18)/'Assumptions (Historical FS)'!D18 -> 0.0039676484 | F7: =('Assumptions (Historical FS)'!F18-'Assumptions (Historical FS)'!E18)/'Assumptions (Historical FS)'!E18 -> 0.18893449 | H7: =AVERAGE(C7:F7) -> 0.28768579 | I7: =MEDIAN(C7:F7) -> 0.11427551
A8: Dividend Growth | C8: =('Merge data sheet'!C91-'Merge data sheet'!B91)/'Merge data sheet'!B91 -> 0.78614699 | D8: =('Merge data sheet'!D91-'Merge data sheet'!C91)/'Merge data sheet'!C91 -> 0.13604659 | E8: =('Merge data sheet'!E91-'Merge data sheet'!D91)/'Merge data sheet'!D91 -> 0.084098462 | H8: =AVERAGE(C8:E8) -> 0.33543068 | I8: =MEDIAN(C8:E8) -> 0.13604659
A10: Gross Margin | B10: =('Consolidated P&L'!F5-'Merge data sheet'!B68-'Merge data sheet'!B69)/'Consolidated P&L'!F5 -> 0.21134491 | C10: =('Consolidated P&L'!G5-'Merge data sheet'!C68-'Merge data sheet'!C69)/'Consolidated P&L'!G5 -> 0.25118886 | D10: =('Consolidated P&L'!H5-'Merge data sheet'!D68-'Merge data sheet'!D69)/'Consolidated P&L'!H5 -> 0.24228398 | E10: =('Consolidated P&L'!I5-'Merge data sheet'!E68-'Merge data sheet'!E69)/'Consolidated P&L'!I5 -> 0.28294758 | F10: =('Consolidated P&L'!J5-'Merge data sheet'!F68-'Merge data sheet'!F69)/'Consolidated P&L'!J5 -> 0.37867192 | H10: =AVERAGE(B10:F10) -> 0.27328745 | I10: =MEDIAN(B10:F10) -> 0.25118886
A11: EBITDA Margin | B11: ='Assumptions (Historical FS)'!B9/'Assumptions (Historical FS)'!B3 -> 0.19519169 | C11: ='Assumptions (Historical FS)'!C9/'Assumptions (Historical FS)'!C3 -> 0.18406112 | D11: ='Assumptions (Historical FS)'!D9/'Assumptions (Historical FS)'!D3 -> 0.17984064 | E11: ='Assumptions (Historical FS)'!E9/'Assumptions (Historical FS)'!E3 -> 0.170882 | F11: ='Assumptions (Historical FS)'!F9/'Assumptions (Historical FS)'!F3 -> 0.17857784 | H11: =AVERAGE(B11:F11) -> 0.18171066 | I11: =MEDIAN(B11:F11) -> 0.17984064
A12: EBIT Margin | B12: ='Assumptions (Historical FS)'!B11/'Assumptions (Historical FS)'!B3 -> 0.17254144 | C12: ='Assumptions (Historical FS)'!C11/'Assumptions (Historical FS)'!C3 -> 0.16228189 | D12: ='Assumptions (Historical FS)'!D11/'Assumptions (Historical FS)'!D3 -> 0.15678408 | E12: ='Assumptions (Historical FS)'!E11/'Assumptions (Historical FS)'!E3 -> 0.14479545 | F12: ='Assumptions (Historical FS)'!F11/'Assumptions (Historical FS)'!F3 -> 0.1536627 | H12: =AVERAGE(B12:F12) -> 0.15801311 | I12: =MEDIAN(B12:F12) -> 0.15678408
A13: EBT Margin | B13: ='Assumptions (Historical FS)'!B14/'Assumptions (Historical FS)'!B3 -> 0.19768073 | C13: ='Assumptions (Historical FS)'!C14/'Assumptions (Historical FS)'!C3 -> 0.17453214 | D13: ='Assumptions (Historical FS)'!D14/'Assumptions (Historical FS)'!D3 -> 0.17030436 | E13: ='Assumptions (Historical FS)'!E14/'Assumptions (Historical FS)'!E3 -> 0.16349673 | F13: ='Assumptions (Historical FS)'!F14/'Assumptions (Historical FS)'!F3 -> 0.17299965 | H13: =AVERAGE(B13:F13) -> 0.17580272 | I13: =MEDIAN(B13:F13) -> 0.17299965
A14: Net Profit Margin | B14: ='Assumptions (Historical FS)'!B18/'Assumptions (Historical FS)'!B3 -> 0.14680222 | C14: ='Assumptions (Historical FS)'!C18/'Assumptions (Historical FS)'!C3 -> 0.13296869 | D14: ='Assumptions (Historical FS)'!D18/'Assumptions (Historical FS)'!D3 -> 0.12915224 | E14: ='Assumptions (Historical FS)'!E18/'Assumptions (Historical FS)'!E3 -> 0.12116628 | F14: ='Assumptions (Historical FS)'!F18/'Assumptions (Historical FS)'!F3 -> 0.12941883 | H14: =AVERAGE(B14:F14) -> 0.13190165 | I14: =MEDIAN(B14:F14) -> 0.12941883
A16: Sales Expenses%Sales | B16: ='Consolidated P&L'!F16/'Consolidated P&L'!F5 -> 0.83210477 | C16: ='Consolidated P&L'!G16/'Consolidated P&L'!G5 -> 0.84225055 | D16: ='Consolidated P&L'!H16/'Consolidated P&L'!H5 -> 0.84945801 | E16: ='Consolidated P&L'!I16/'Consolidated P&L'!I5 -> 0.86254246 | F16: ='Consolidated P&L'!J16/'Consolidated P&L'!J5 -> 0.85286804 | H16: =AVERAGE(B16:F16) -> 0.84784477 | I16: =MEDIAN(B16:F16) -> 0.84945801
A17: Depriciation%Sales | B17: ='Merge data sheet'!B71/'Consolidated P&L'!F5 -> 0.022650252 | C17: ='Merge data sheet'!C71/'Consolidated P&L'!G5 -> 0.021779224 | D17: ='Merge data sheet'!D71/'Consolidated P&L'!H5 -> 0.023056564 | E17: ='Merge data sheet'!E71/'Consolidated P&L'!I5 -> 0.026086545 | F17: ='Merge data sheet'!F71/'Consolidated P&L'!J5 -> 0.024915145 | H17: =AVERAGE(B17:F17) -> 0.023697546 | I17: =MEDIAN(B17:F17) -> 0.023056564
A18: Operating Income%Sales | B18: ='Assumptions (Historical FS)'!B11/'Consolidated P&L'!F5 -> 0.17254144 | C18: ='Assumptions (Historical FS)'!C11/'Consolidated P&L'!G5 -> 0.16228189 | D18: ='Assumptions (Historical FS)'!D11/'Consolidated P&L'!H5 -> 0.15678408 | E18: ='Assumptions (Historical FS)'!E11/'Consolidated P&L'!I5 -> 0.14479545 | F18: ='Assumptions (Historical FS)'!F11/'Consolidated P&L'!J5 -> 0.1536627 | H18: =AVERAGE(B18:F18) -> 0.15801311 | I18: =MEDIAN(B18:F18) -> 0.15678408
A20: Return on Capital Employed | B20: ='Assumptions (Historical FS)'!B11/('Merge data sheet'!B47-'Merge data sheet'!B25) -> 0.28305937 | C20: ='Assumptions (Historical FS)'!C11/('Merge data sheet'!C47-'Merge data sheet'!C25) -> 0.29894246 | D20: ='Assumptions (Historical FS)'!D11/('Merge data sheet'!D47-'Merge data sheet'!D25) -> 0.25520399 | E20: ='Assumptions (Historical FS)'!E11/('Merge data sheet'!E47-'Merge data sheet'!E25) -> 0.22313403 | F20: ='Assumptions (Historical FS)'!F11/('Merge data sheet'!F47-'Merge data sheet'!F25) -> 0.23715996 | H20: =AVERAGE(B20:F20) -> 0.25949996 | I20: =MEDIAN(B20:F20) -> 0.25520399
A21: Retained Earning % | B21: =('Assumptions (Historical FS)'!B18-'Merge data sheet'!B91)/'Assumptions (Historical FS)'!B18 -> 0.61964177 | C21: =('Assumptions (Historical FS)'!C18-'Merge data sheet'!C91)/'Assumptions (Historical FS)'!C18 -> 0.64583097 | D21: =('Assumptions (Historical FS)'!D18-'Merge data sheet'!D91)/'Assumptions (Historical FS)'!D18 -> 0.61297988 | E21: =('Assumptions (Historical FS)'!E18-'Merge data sheet'!E91)/'Assumptions (Historical FS)'!E18 -> 0.5820902 | F21: =('Assumptions (Historical FS)'!F18-'Merge data sheet'!F91)/'Assumptions (Historical FS)'!F18 -> 1 | H21: =AVERAGE(B21:E21) -> 0.61513571 | I21: =MEDIAN(B21:E21) -> 0.61631082
A22: Return on Equity % | B22: ='Assumptions (Historical FS)'!B18/'Merge data sheet'!B11 -> 0.26095342 | C22: ='Assumptions (Historical FS)'!C18/'Merge data sheet'!C11 -> 0.26592776 | D22: ='Assumptions (Historical FS)'!D18/'Merge data sheet'!D11 -> 0.22915907 | E22: ='Assumptions (Historical FS)'!E18/'Merge data sheet'!E11 -> 0.20289274 | F22: ='Assumptions (Historical FS)'!F18/'Merge data sheet'!F11 -> 0.22790427 | H22: =AVERAGE(B22:F22) -> 0.23736745 | I22: =MEDIAN(B22:F22) -> 0.22915907
A23: Self Sustained Growth Rate | B23: =B22*B21 -> 0.16169764 | C23: =C22*C21 -> 0.17174438 | D23: =D22*D21 -> 0.1404699 | E23: =E22*E21 -> 0.11810188 | F23: =F22*F21 -> 0.22790427 | H23: =AVERAGE(B23:F23) -> 0.16398361 | I23: =MEDIAN(B23:F23) -> 0.16169764
A24: Interest Coverage Ratio | B24: ='Assumptions (Historical FS)'!B11/'Merge data sheet'!B70 -> 37.135989 | C24: ='Assumptions (Historical FS)'!C11/'Merge data sheet'!C70 -> 35.804521 | D24: ='Assumptions (Historical FS)'!D11/'Merge data sheet'!D70 -> 25.117276 | E24: ='Assumptions (Historical FS)'!E11/'Merge data sheet'!E70 -> 19.732521 | F24: ='Assumptions (Historical FS)'!F11/'Merge data sheet'!F70 -> 23.529135 | H24: =AVERAGE(B24:F24) -> 28.263888 | I24: =MEDIAN(B24:F24) -> 25.117276
A26: Debtor Turnover Ratio | B26: ='Consolidated P&L'!F5/'Merge data sheet'!B42 -> 5.5298041 | C26: ='Consolidated P&L'!G5/'Merge data sheet'!C42 -> 5.9008785 | D26: ='Consolidated P&L'!H5/'Merge data sheet'!D42 -> 6.2245005 | E26: ='Consolidated P&L'!I5/'Merge data sheet'!E42 -> 6.4776229 | F26: ='Consolidated P&L'!J5/'Merge data sheet'!F42 -> 5.6981468 | H26: =AVERAGE(B26:F26) -> 5.9661906 | I26: =MEDIAN(B26:F26) -> 5.9008785
A27: Creditor Turnover Ratio | B27: ='Consolidated P&L'!F5/'Merge data sheet'!B22 -> 19.517564 | C27: ='Consolidated P&L'!G5/'Merge data sheet'!C22 -> 25.647704 | D27: ='Consolidated P&L'!H5/'Merge data sheet'!D22 -> 23.774684 | E27: ='Consolidated P&L'!I5/'Merge data sheet'!E22 -> 24.522937 | F27: ='Consolidated P&L'!J5/'Merge data sheet'!F22 -> 20.527705 | H27: =AVERAGE(B27:F27) -> 22.798119 | I27: =MEDIAN(B27:F27) -> 23.774684
A28: Inventory Turnover | B28: =IF('Merge data sheet'!B41=0,"",'Consolidated P&L'!F5/'Merge data sheet'!B41) | C28: =IF('Merge data sheet'!C41=0,"",'Consolidated P&L'!G5/'Merge data sheet'!C41) -> 10055.455 | D28: =IF('Merge data sheet'!D41=0,"",'Consolidated P&L'!H5/'Merge data sheet'!D41) -> 11839 | E28: =IF('Merge data sheet'!E41=0,"",'Consolidated P&L'!I5/'Merge data sheet'!E41) -> 13574.321 | F28: =IF('Merge data sheet'!F41=0,"",'Consolidated P&L'!J5/'Merge data sheet'!F41) -> 12820.485 | H28: =IFERROR(AVERAGE(B28:F28),"") -> 12072.315 | I28: =IFERROR(MEDIAN(B28:F28),"") -> 12329.742
A29: Fixed Asset Turnover | B29: ='Consolidated P&L'!F5/'Merge data sheet'!B33 -> 8.2947062 | C29: ='Consolidated P&L'!G5/'Merge data sheet'!C33 -> 9.7821473 | D29: ='Consolidated P&L'!H5/'Merge data sheet'!D33 -> 8.1859039 | E29: ='Consolidated P&L'!I5/'Merge data sheet'!E33 -> 7.9807034 | F29: ='Consolidated P&L'!J5/'Merge data sheet'!F33 -> 8.0500038 | H29: =AVERAGE(B29:F29) -> 8.4586929 | I29: =MEDIAN(B29:F29) -> 8.1859039
A30: Capital Turnover Ratio | B30: ='Consolidated P&L'!F5/('Merge data sheet'!B11+'Merge data sheet'!B15+'Merge data sheet'!B21) -> 1.6236827 | C30: ='Consolidated P&L'!G5/('Merge data sheet'!C11+'Merge data sheet'!C15+'Merge data sheet'!C21) -> 1.9849378 | D30: ='Consolidated P&L'!H5/('Merge data sheet'!D11+'Merge data sheet'!D15+'Merge data sheet'!D21) -> 1.7707326 | E30: ='Consolidated P&L'!I5/('Merge data sheet'!E11+'Merge data sheet'!E15+'Merge data sheet'!E21) -> 1.6743288 | F30: ='Consolidated P&L'!J5/('Merge data sheet'!F11+'Merge data sheet'!F15+'Merge data sheet'!F21) -> 1.7609823 | H30: =AVERAGE(B30:F30) -> 1.7629328 | I30: =MEDIAN(B30:F30) -> 1.7609823
A32: (In days)
A33: Debtors Day | B33: ='Merge data sheet'!B42/'Consolidated P&L'!F5*365 -> 66.005955 | C33: ='Merge data sheet'!C42/'Consolidated P&L'!G5*365 -> 61.855197 | D33: ='Merge data sheet'!D42/'Consolidated P&L'!H5*365 -> 58.639243 | E33: ='Merge data sheet'!E42/'Consolidated P&L'!I5*365 -> 56.347831 | F33: ='Merge data sheet'!F42/'Consolidated P&L'!J5*365 -> 64.055914 | H33: =AVERAGE(B33:F33) -> 61.380828 | I33: =MEDIAN(B33:F33) -> 61.855197
A34: Payable Days | B34: ='Merge data sheet'!B22/'Consolidated P&L'!F5*365 -> 18.701105 | C34: ='Merge data sheet'!C22/'Consolidated P&L'!G5*365 -> 14.231293 | D34: ='Merge data sheet'!D22/'Consolidated P&L'!H5*365 -> 15.352465 | E34: ='Merge data sheet'!E22/'Consolidated P&L'!I5*365 -> 14.884025 | F34: ='Merge data sheet'!F22/'Consolidated P&L'!J5*365 -> 17.780848 | H34: =AVERAGE(B34:F34) -> 16.189947 | I34: =MEDIAN(B34:F34) -> 15.352465
A35: Inventory Days | B35: =IF('Merge data sheet'!B41=0,0,'Merge data sheet'!B41/'Consolidated P&L'!F5*365) -> 0 | C35: =IF('Merge data sheet'!C41=0,0,'Merge data sheet'!C41/'Consolidated P&L'!G5*365) -> 0.036298707 | D35: =IF('Merge data sheet'!D41=0,0,'Merge data sheet'!D41/'Consolidated P&L'!H5*365) -> 0.030830307 | E35: =IF('Merge data sheet'!E41=0,0,'Merge data sheet'!E41/'Consolidated P&L'!I5*365) -> 0.026889005 | F35: =IF('Merge data sheet'!F41=0,0,'Merge data sheet'!F41/'Consolidated P&L'!J5*365) -> 0.028470062 | H35: =AVERAGE(B35:F35) -> 0.024497616 | I35: =MEDIAN(B35:F35) -> 0.028470062
A36: Cash Conversion Cycle | B36: =B33+B35-B34 -> 47.30485 | C36: =C33+C35-C34 -> 47.660203 | D36: =D33+D35-D34 -> 43.317608 | E36: =E33+E35-E34 -> 41.490695 | F36: =F33+F35-F34 -> 46.303536 | H36: =AVERAGE(B36:F36) -> 45.215379 | I36: =MEDIAN(B36:F36) -> 46.303536
A38: CFO/Sales | B38: ='Merge data sheet'!B97/'Consolidated P&L'!F5 -> 0.10543312 | C38: ='Merge data sheet'!C97/'Consolidated P&L'!G5 -> 0.093258596 | D38: ='Merge data sheet'!D97/'Consolidated P&L'!H5 -> 0.15962778 | E38: ='Merge data sheet'!E97/'Consolidated P&L'!I5 -> 0.11960082 | F38: ='Merge data sheet'!F97/'Consolidated P&L'!J5 -> 0.11342643 | H38: =AVERAGE(B38:F38) -> 0.11826935 | I38: =MEDIAN(B38:F38) -> 0.11342643
A39: CFO/Total Assets | B39: ='Merge data sheet'!B97/'Merge data sheet'!B47 -> 0.13248538 | C39: ='Merge data sheet'!C97/'Merge data sheet'!C47 -> 0.13170696 | D39: ='Merge data sheet'!D97/'Merge data sheet'!D47 -> 0.20569241 | E39: ='Merge data sheet'!E97/'Merge data sheet'!E47 -> 0.14841006 | F39: ='Merge data sheet'!F97/'Merge data sheet'!F47 -> 0.12901387 | H39: =AVERAGE(B39:F39) -> 0.14946174 | I39: =MEDIAN(B39:F39) -> 0.13248538
A40: CFO/Total Debt | B40: =IF('Merge data sheet'!B15+'Merge data sheet'!B21=0,"",'Merge data sheet'!B97/('Merge data sheet'!B15+'Merge data sheet'!B21)) -> 1.9772591 | C40: =IF('Merge data sheet'!C15+'Merge data sheet'!C21=0,"",'Merge data sheet'!C97/('Merge data sheet'!C15+'Merge data sheet'!C21)) -> 24.697526 | D40: =IF('Merge data sheet'!D15+'Merge data sheet'!D21=0,"",'Merge data sheet'!D97/('Merge data sheet'!D15+'Merge data sheet'!D21)) -> 139.29975 | E40: =IF('Merge data sheet'!E15+'Merge data sheet'!E21=0,"",'Merge data sheet'!E97/('Merge data sheet'!E15+'Merge data sheet'!E21)) -> 1976.4348 | F40: =IF('Merge data sheet'!F15+'Merge data sheet'!F21=0,"",'Merge data sheet'!F97/('Merge data sheet'!F15+'Merge data sheet'!F21)) | H40: =IFERROR(AVERAGE(B40:F40),"") -> 535.60233 | I40: =IFERROR(MEDIAN(B40:F40),"") -> 81.99864

Sheet FCFF
A1: Particular | B1: 44621 | C1: 44986 | D1: 45352 | E1: 45717 | F1: 46082
A2: EBIT | B2: ='Merge data sheet'!B66-'Merge data sheet'!B68-'Merge data sheet'!B69-'Merge data sheet'!B71-'Merge data sheet'!B72 -> 3170.2 | C2: ='Merge data sheet'!C66-'Merge data sheet'!C68-'Merge data sheet'!C69-'Merge data sheet'!C71-'Merge data sheet'!C72 -> 5941.9 | D2: ='Merge data sheet'!D66-'Merge data sheet'!D68-'Merge data sheet'!D69-'Merge data sheet'!D71-'Merge data sheet'!D72 -> 6270.4 | E2: ='Merge data sheet'!E66-'Merge data sheet'!E68-'Merge data sheet'!E69-'Merge data sheet'!E71-'Merge data sheet'!E72 -> 6493.1 | F2: ='Merge data sheet'!F66-'Merge data sheet'!F68-'Merge data sheet'!F69-'Merge data sheet'!F71-'Merge data sheet'!F72 -> 7595.5
A3: Less: Tax on EBIT | B3: =B2*$J$5 -> 789.36693 | C3: =C2*$J$5 -> 1479.509 | D3: =D2*$J$5 -> 1561.3041 | E3: =E2*$J$5 -> 1616.7555 | F3: =F2*$J$5 -> 1891.2487
A4: EBIT * (1- Tax) NOPAT | B4: =B2-B3 -> 2380.8331 | C4: =C2-C3 -> 4462.391 | D4: =D2-D3 -> 4709.0959 | E4: =E2-E3 -> 4876.3445 | F4: =F2-F3 -> 5704.2513
A5: Less: Net Capital expenditure | C5: ='Fixed assets scheduled'!C8 -> 1503.2 | D5: ='Fixed assets scheduled'!D8 -> 946.6 | E5: ='Fixed assets scheduled'!E8 -> 423.7 | F5: ='Fixed assets scheduled'!F8 -> 493.1 | I5: Avg of effective tax rate | J5: =AVERAGE('Assumptions (Historical FS)'!B16:F16) -> 0.24899594
A6: Less: Net Change in working Capital | C6: ='Change in working capital'!C6 -> 2302.2 | D6: ='Change in working capital'!D6 -> -117.8 | E6: ='Change in working capital'!E6 -> 105.4 | F6: ='Change in working capital'!F6 -> 1046.6
A7: Reinvestment | C7: =C5+C6 -> 3805.4 | D7: =D5+D6 -> 828.8 | E7: =E5+E6 -> 529.1 | F7: =F5+F6 -> 1539.7
A8: Free Cash Flow | C8: =C4-C7 -> 656.99103 | D8: =D4-D7 -> 3880.2959 | E8: =E4-E7 -> 4347.2445 | F8: =F4-F7 -> 4164.5513
I9: Marginal tax rate | J9: 0.25
A10: Reinvestment Rate | C10: =C7/C4 -> 0.85277152 | D10: =D7/D4 -> 0.17599981 | E10: =E7/E4 -> 0.10850341 | F10: =F7/F4 -> 0.26992149
A12: Median Reinvestment rate /Sales percentage | B12: =MEDIAN(C10:F10) -> 0.22296065
A13: Average Reinvestment rate /Sales percentage | B13: =AVERAGE(C10:F10) -> 0.35179906

Sheet Assumptions (Historical FS)
A1: LTIM
A2: Particulars (in RS Cr.) | B2: 44621 | C2: 44986 | D2: 45352 | E2: 45717 | F2: 46082
A3: Revenue from operations | B3: ='Merge data sheet'!B63 -> 15668.7 | C3: ='Merge data sheet'!C63 -> 33183 | D3: ='Merge data sheet'!D63 -> 35517 | E3: ='Merge data sheet'!E63 -> 38008.1 | F3: ='Merge data sheet'!F63 -> 42307.6 | H3: Median of revenue growth
A4: Revenue growth in % | C4: ='Consolidated P&L'!M5 -> 1.117789 | D4: ='Consolidated P&L'!N5 -> 0.070337221 | E4: ='Consolidated P&L'!O5 -> 0.070138244 | F4: ='Consolidated P&L'!P5 -> 0.11312062 | G4: =AVERAGE(C4:F4) -> 0.34284626 | H4: =MEDIAN(C4:F4) -> 0.091728923
A5: Less: Material cost | B5: ='Merge data sheet'!B68 -> 2656.5 | C5: ='Merge data sheet'!C68 -> 3967.9 | D5: ='Merge data sheet'!D68 -> 4179.5 | E5: ='Merge data sheet'!E68 -> 2631.2 | F5: ='Merge data sheet'!F68 -> 0
A6: Less: Employee costs | B6: ='Merge data sheet'!B69 -> 9700.7 | C6: ='Merge data sheet'!C69 -> 20879.9 | D6: ='Merge data sheet'!D69 -> 22732.3 | E6: ='Merge data sheet'!E69 -> 24622.6 | F6: ='Merge data sheet'!F69 -> 26286.9
A7: Less: Other Expenses | B7: ='Merge data sheet'!B72 -> 253.1 | C7: ='Merge data sheet'!C72 -> 2227.5 | D7: ='Merge data sheet'!D72 -> 2217.8 | E7: ='Merge data sheet'!E72 -> 4259.4 | F7: ='Merge data sheet'!F72 -> 8465.5
A8: Total Expenses | B8: =B7+B6+B5 -> 12610.3 | C8: =C7+C6+C5 -> 27075.3 | D8: =D7+D6+D5 -> 29129.6 | E8: =E7+E6+E5 -> 31513.2 | F8: =F7+F6+F5 -> 34752.4
A9: EBITDA | B9: =B3-B8 -> 3058.4 | C9: =C3-C8 -> 6107.7 | D9: =D3-D8 -> 6387.4 | E9: =E3-E8 -> 6494.9 | F9: =F3-F8 -> 7555.2
A10: Less: Depreciation And Amortization | B10: ='Merge data sheet'!B71 -> 354.9 | C10: ='Merge data sheet'!C71 -> 722.7 | D10: ='Merge data sheet'!D71 -> 818.9 | E10: ='Merge data sheet'!E71 -> 991.5 | F10: ='Merge data sheet'!F71 -> 1054.1
A11: EBIT | B11: =B9-B10 -> 2703.5 | C11: =C9-C10 -> 5385 | D11: =D9-D10 -> 5568.5 | E11: =E9-E10 -> 5503.4 | F11: =F9-F10 -> 6501.1
A12: ADD: Non operating income/ Other Income | B12: ='Merge data sheet'!B65 -> 466.7 | C12: ='Merge data sheet'!C65 -> 556.9 | D12: ='Merge data sheet'!D65 -> 701.9 | E12: ='Merge data sheet'!E65 -> 989.7 | F12: ='Merge data sheet'!F65 -> 1094.4
A13: Less: Interest Expenses | B13: ='Merge data sheet'!B70 -> 72.8 | C13: ='Merge data sheet'!C70 -> 150.4 | D13: ='Merge data sheet'!D70 -> 221.7 | E13: ='Merge data sheet'!E70 -> 278.9 | F13: ='Merge data sheet'!F70 -> 276.3
A14: EBT | B14: =B11+B12-B13 -> 3097.4 | C14: =C11+C12-C13 -> 5791.5 | D14: =D11+D12-D13 -> 6048.7 | E14: =E11+E12-E13 -> 6214.2 | F14: =F11+F12-F13 -> 7319.2
A15: Less: TAX | B15: ='Merge data sheet'!B80 -> 798.9 | C15: ='Merge data sheet'!C80 -> 1381.2 | D15: ='Merge data sheet'!D80 -> 1464.1 | E15: ='Merge data sheet'!E80 -> 1612.2 | F15: ='Merge data sheet'!F80 -> 1808.4
A16: Tax Rate | B16: =B15/B14 -> 0.257926 | C16: =C15/C14 -> 0.23848744 | D16: =D15/D14 -> 0.24205201 | E16: =E15/E14 -> 0.25943806 | F16: =F15/F14 -> 0.24707618
A17: Less:Non Controlling Interest/Minority Interest | B17: ='Merge data sheet'!B84 -> -1.7 | C17: ='Merge data sheet'!C84 -> -2 | D17: ='Merge data sheet'!D84 -> -2.5 | E17: ='Merge data sheet'!E84 -> -3.3 | F17: ='Merge data sheet'!F84 -> 35.4
A18: Net Profit- Pat | B18: =B14-B15-B17 -> 2300.2 | C18: =C14-C15-C17 -> 4412.3 | D18: =D14-D15-D17 -> 4587.1 | E18: =E14-E15-E17 -> 4605.3 | F18: =F14-F15-F17 -> 5475.4
A20: Historical Growth
A21: Average Growth | B21: =AVERAGE(C4:F4) -> 0.34284626
A22: CAGR | B22: =(F3/B3)^(1/5)-1 -> 0.21976758 | C22: =_xlfn.RRI(5,B3,F3) -> 0.21976758 | D22: RRI
A24: Margins
A25: EBITDA | B25: =B9/B3 -> 0.19519169 | C25: =C9/C3 -> 0.18406112 | D25: =D9/D3 -> 0.17984064 | E25: =E9/E3 -> 0.170882 | F25: =F9/F3 -> 0.17857784
A26: EBIT | B26: =B11/B3 -> 0.17254144 | C26: =C11/C3 -> 0.16228189 | D26: =D11/D3 -> 0.15678408 | E26: =E11/E3 -> 0.14479545 | F26: =F11/F3 -> 0.1536627
A27: EBT | B27: =B14/B3 -> 0.19768073 | C27: =C14/C3 -> 0.17453214 | D27: =D14/D3 -> 0.17030436 | E27: =E14/E3 -> 0.16349673 | F27: =F14/F3 -> 0.17299965
A28: Net Proftt | B28: =B18/B3 -> 0.14680222 | C28: =C18/C3 -> 0.13296869 | D28: =D18/D3 -> 0.12915224 | E28: =E18/E3 -> 0.12116628 | F28: =F18/F3 -> 0.12941883
A30: Tax Rate
A31: Effective tax rate | B31: =B15/B14 -> 0.257926 | C31: =C15/C14 -> 0.23848744 | D31: =D15/D14 -> 0.24205201 | E31: =E15/E14 -> 0.25943806 | F31: =F15/F14 -> 0.24707618
A32: Marginal Tax rate | B32: 0.25 | C32: 0.25 | D32: 0.25 | E32: 0.25 | F32: 0.25
A34: Return On Capital
A35: EBIT*(1-T) | B35: =B11*(1-B32) -> 2027.625 | C35: =C11*(1-C32) -> 4038.75 | D35: =D11*(1-D32) -> 4176.375 | E35: =E11*(1-E32) -> 4127.55 | F35: =F11*(1-F32) -> 4875.825
A36: Book Equity | B36: ='Merge data sheet'!B11 -> 8814.6 | C36: ='Merge data sheet'!C11 -> 16592.1 | D36: ='Merge data sheet'!D11 -> 20017.1 | E36: ='Merge data sheet'!E11 -> 22698.2 | F36: ='Merge data sheet'!F11 -> 24025
A37: Book Debt | B37: ='Merge data sheet'!B21+'Merge data sheet'!B15 -> 835.5 | C37: ='Merge data sheet'!C21+'Merge data sheet'!C15 -> 125.3 | D37: ='Merge data sheet'!D21+'Merge data sheet'!D15 -> 40.7 | E37: ='Merge data sheet'!E21+'Merge data sheet'!E15 -> 2.3 | F37: ='Merge data sheet'!F21+'Merge data sheet'!F15 -> 0
A38: Cash and Cash equivalents | B38: ='Merge data sheet'!B43 -> 777.3 | C38: ='Merge data sheet'!C43 -> 2932 | D38: ='Merge data sheet'!D43 -> 2816 | E38: ='Merge data sheet'!E43 -> 3588.2 | F38: ='Merge data sheet'!F43 -> 2812.4
A39: Capital Employed | B39: =B36+B37+B38 -> 10427.4 | C39: =C36+C37+C38 -> 19649.4 | D39: =D36+D37+D38 -> 22873.8 | E39: =E36+E37+E38 -> 26288.7 | F39: =F36+F37+F38 -> 26837.4
A41: Pre-Tax Return on capital | B41: =B11/B39 -> 0.25926885 | C41: =C11/C39 -> 0.27405417 | D41: =D11/D39 -> 0.24344446 | E41: =E11/E39 -> 0.2093447 | F41: =F11/F39 -> 0.24224031
A42: Post Tax return On capital | B42: =B35/B39 -> 0.19445164 | C42: =C35/C39 -> 0.20554063 | D42: =D35/D39 -> 0.18258335 | E42: =E35/E39 -> 0.15700852 | F42: =F35/F39 -> 0.18168023
A43: Growth Summary
A46: Growth In EBIT | C46: =FCFF!B12*'Assumptions (Historical FS)'!F42 -> 0.040507542

Sheet Merge data sheet
A1: Consolidated Balance Sheet
A2: Particulars (Rs. Cr.) | B2: 44621 | C2: Mar 23 | D2: Mar 24 | E2: Mar 25 | F2: Mar 26
A3: 12 Months Ended | B3: 12 mths | C3: 12 mths | D3: 12 mths | E3: 12 mths | F3: 12 mths
A4: EQUITIES AND LIABILITIES
A5: SHAREHOLDER'S FUNDS
A6: Equity Share Capital | B6: ='Consolidated Balance sheet'!E6 -> 17.5 | C6: ='Consolidated Balance sheet'!F6 -> 29.6 | D6: ='Consolidated Balance sheet'!G6 -> 29.6 | E6: ='Consolidated Balance sheet'!H6 -> 29.6 | F6: ='Consolidated Balance sheet'!I6 -> 29.6
A7: Total Share Capital | B7: ='Consolidated Balance sheet'!E7 -> 17.5 | C7: ='Consolidated Balance sheet'!F7 -> 29.6 | D7: ='Consolidated Balance sheet'!G7 -> 29.6 | E7: ='Consolidated Balance sheet'!H7 -> 29.6 | F7: ='Consolidated Balance sheet'!I7 -> 29.6
A8: Reserves and Surplus | B8: ='Consolidated Balance sheet'!E8 -> 8797.1 | C8: ='Consolidated Balance sheet'!F8 -> 16078.6 | D8: ='Consolidated Balance sheet'!G8 -> 19503.6 | E8: ='Consolidated Balance sheet'!H8 -> 22434.9 | F8: ='Consolidated Balance sheet'!I8 -> 23995.4
A9: Total Reserves and Surplus | B9: ='Consolidated Balance sheet'!E9 -> 8797.1 | C9: ='Consolidated Balance sheet'!F9 -> 16078.6 | D9: ='Consolidated Balance sheet'!G9 -> 19503.6 | E9: ='Consolidated Balance sheet'!H9 -> 22434.9 | F9: ='Consolidated Balance sheet'!I9 -> 23995.4
A10: Employees Stock Options | B10: ='Consolidated Balance sheet'!E10 -> 0 | C10: ='Consolidated Balance sheet'!F10 -> 483.9 | D10: ='Consolidated Balance sheet'!G10 -> 483.9 | E10: ='Consolidated Balance sheet'!H10 -> 233.7 | F10: ='Consolidated Balance sheet'!I10 -> 0
A11: Total Shareholders Funds | B11: ='Consolidated Balance sheet'!E11 -> 8814.6 | C11: ='Consolidated Balance sheet'!F11 -> 16592.1 | D11: ='Consolidated Balance sheet'!G11 -> 20017.1 | E11: ='Consolidated Balance sheet'!H11 -> 22698.2 | F11: ='Consolidated Balance sheet'!I11 -> 24025
A12: Equity Share Application Money | B12: ='Consolidated Balance sheet'!E12 -> 0 | C12: ='Consolidated Balance sheet'!F12 -> 0 | D12: ='Consolidated Balance sheet'!G12 -> 0.1 | E12: ='Consolidated Balance sheet'!H12 -> 0.1 | F12: ='Consolidated Balance sheet'!I12 -> 0
A13: Minority Interest | B13: ='Consolidated Balance sheet'!E13 -> 5.7 | C13: ='Consolidated Balance sheet'!F13 -> 7.1 | D13: ='Consolidated Balance sheet'!G13 -> 9.2 | E13: ='Consolidated Balance sheet'!H13 -> 13.2 | F13: ='Consolidated Balance sheet'!I13 -> 82.7 | J13: In debt mostly interest bearing obligations will count
A14: NON-CURRENT LIABILITIES | B14: ='Consolidated Balance sheet'!E14 -> 0 | C14: ='Consolidated Balance sheet'!F14 -> 0 | D14: ='Consolidated Balance sheet'!G14 -> 0 | E14: ='Consolidated Balance sheet'!H14 -> 0 | F14: ='Consolidated Balance sheet'!I14 -> 0
A15: Long Term Borrowings | B15: ='Consolidated Balance sheet'!E15 -> 667.5 | C15: ='Consolidated Balance sheet'!F15 -> 0 | D15: ='Consolidated Balance sheet'!G15 -> 0 | E15: ='Consolidated Balance sheet'!H15 -> 0 | F15: ='Consolidated Balance sheet'!I15 -> 0
A16: Deferred Tax Liabilities [Net] | B16: ='Consolidated Balance sheet'!E16 -> 10.5 | C16: ='Consolidated Balance sheet'!F16 -> 14.7 | D16: ='Consolidated Balance sheet'!G16 -> 18.7 | E16: ='Consolidated Balance sheet'!H16 -> 31.9 | F16: ='Consolidated Balance sheet'!I16 -> 47.5
A17: Other Long Term Liabilities | B17: ='Consolidated Balance sheet'!E17 -> 52.7 | C17: ='Consolidated Balance sheet'!F17 -> 1364.6 | D17: ='Consolidated Balance sheet'!G17 -> 1759 | E17: ='Consolidated Balance sheet'!H17 -> 1901 | F17: ='Consolidated Balance sheet'!I17 -> 3235.6
A18: Long Term Provisions | B18: ='Consolidated Balance sheet'!E18 -> 0 | C18: ='Consolidated Balance sheet'!F18 -> 35 | D18: ='Consolidated Balance sheet'!G18 -> 15.7 | E18: ='Consolidated Balance sheet'!H18 -> 19.7 | F18: ='Consolidated Balance sheet'!I18 -> 21.5
A19: Total Non-Current Liabilities | B19: ='Consolidated Balance sheet'!E19 -> 730.7 | C19: ='Consolidated Balance sheet'!F19 -> 1414.3 | D19: ='Consolidated Balance sheet'!G19 -> 1793.4 | E19: ='Consolidated Balance sheet'!H19 -> 1952.6 | F19: ='Consolidated Balance sheet'!I19 -> 3304.6
A20: CURRENT LIABILITIES | B20: ='Consolidated Balance sheet'!E20 -> 0 | C20: ='Consolidated Balance sheet'!F20 -> 0 | D20: ='Consolidated Balance sheet'!G20 -> 0 | E20: ='Consolidated Balance sheet'!H20 -> 0 | F20: ='Consolidated Balance sheet'!I20 -> 0
A21: Short Term Borrowings | B21: ='Consolidated Balance sheet'!E21 -> 168 | C21: ='Consolidated Balance sheet'!F21 -> 125.3 | D21: ='Consolidated Balance sheet'!G21 -> 40.7 | E21: ='Consolidated Balance sheet'!H21 -> 2.3 | F21: ='Consolidated Balance sheet'!I21 -> 0
A22: Trade Payables | B22: ='Consolidated Balance sheet'!E22 -> 802.8 | C22: ='Consolidated Balance sheet'!F22 -> 1293.8 | D22: ='Consolidated Balance sheet'!G22 -> 1493.9 | E22: ='Consolidated Balance sheet'!H22 -> 1549.9 | F22: ='Consolidated Balance sheet'!I22 -> 2061
A23: Other Current Liabilities | B23: ='Consolidated Balance sheet'!E23 -> 1560.1 | C23: ='Consolidated Balance sheet'!F23 -> 3250.1 | D23: ='Consolidated Balance sheet'!G23 -> 3360 | E23: ='Consolidated Balance sheet'!H23 -> 3444.6 | F23: ='Consolidated Balance sheet'!I23 -> 6548.6
A24: Short Term Provisions | B24: ='Consolidated Balance sheet'!E24 -> 387.4 | C24: ='Consolidated Balance sheet'!F24 -> 813.4 | D24: ='Consolidated Balance sheet'!G24 -> 848.6 | E24: ='Consolidated Balance sheet'!H24 -> 969.1 | F24: ='Consolidated Balance sheet'!I24 -> 1174.1
A25: Total Current Liabilities | B25: ='Consolidated Balance sheet'!E25 -> 2918.3 | C25: ='Consolidated Balance sheet'!F25 -> 5482.6 | D25: ='Consolidated Balance sheet'!G25 -> 5743.2 | E25: ='Consolidated Balance sheet'!H25 -> 5965.9 | F25: ='Consolidated Balance sheet'!I25 -> 9783.7
... A57: Current Investments Unquoted Book Value | B57: ='Consolidated Balance sheet'!E57 -> 280 | C57: ='Consolidated Balance sheet'!F57 -> 884.6 | D57: ='Consolidated Balance sheet'!G57 -> 421 | E57: ='Consolidated Balance sheet'!H57 -> 516.7 | F57: ='Consolidated Balance sheet'!I57 -> 0
A58: Consolidated Profit & Loss account
A59: Particulars (Rs. Cr.) | B59: Mar 22 | C59: Mar 23 | D59: Mar 24 | E59: Mar 25 | F59: Mar 26
A60: 12 Months Ended | B60: 12 mths | C60: 12 mths | D60: 12 mths | E60: 12 mths | F60: 12 mths
A61: INCOME
A62: Revenue From Operations [Gross] | B62: ='Consolidated P&L'!F5 -> 15668.7 | C62: ='Consolidated P&L'!G5 -> 33183 | D62: ='Consolidated P&L'!H5 -> 35517 | E62: ='Consolidated P&L'!I5 -> 38008.1 | F62: ='Consolidated P&L'!J5 -> 42307.6
A63: Revenue From Operations [Net] | B63: ='Consolidated P&L'!F6 -> 15668.7 | C63: ='Consolidated P&L'!G6 -> 33183 | D63: ='Consolidated P&L'!H6 -> 35517 | E63: ='Consolidated P&L'!I6 -> 38008.1 | F63: ='Consolidated P&L'!J6 -> 42307.6
A64: Total Operating Revenues | B64: ='Consolidated P&L'!F7 -> 15668.7 | C64: ='Consolidated P&L'!G7 -> 33183 | D64: ='Consolidated P&L'!H7 -> 35517 | E64: ='Consolidated P&L'!I7 -> 38008.1 | F64: ='Consolidated P&L'!J7 -> 42307.6
A65: Other Income | B65: ='Consolidated P&L'!F8 -> 466.7 | C65: ='Consolidated P&L'!G8 -> 556.9 | D65: ='Consolidated P&L'!H8 -> 701.9 | E65: ='Consolidated P&L'!I8 -> 989.7 | F65: ='Consolidated P&L'!J8 -> 1094.4
A66: Total Revenue | B66: ='Consolidated P&L'!F9 -> 16135.4 | C66: ='Consolidated P&L'!G9 -> 33739.9 | D66: ='Consolidated P&L'!H9 -> 36218.9 | E66: ='Consolidated P&L'!I9 -> 38997.8 | F66: ='Consolidated P&L'!J9 -> 43402
A67: EXPENSES | B67: ='Consolidated P&L'!F10 -> 0 | C67: ='Consolidated P&L'!G10 -> 0 | D67: ='Consolidated P&L'!H10 -> 0 | E67: ='Consolidated P&L'!I10 -> 0 | F67: ='Consolidated P&L'!J10 -> 0
A68: Operating And Direct Expenses | B68: ='Consolidated P&L'!F11 -> 2656.5 | C68: ='Consolidated P&L'!G11 -> 3967.9 | D68: ='Consolidated P&L'!H11 -> 4179.5 | E68: ='Consolidated P&L'!I11 -> 2631.2 | F68: ='Consolidated P&L'!J11 -> 0
A69: Employee Benefit Expenses | B69: ='Consolidated P&L'!F12 -> 9700.7 | C69: ='Consolidated P&L'!G12 -> 20879.9 | D69: ='Consolidated P&L'!H12 -> 22732.3 | E69: ='Consolidated P&L'!I12 -> 24622.6 | F69: ='Consolidated P&L'!J12 -> 26286.9
A70: Finance Costs | B70: ='Consolidated P&L'!F13 -> 72.8 | C70: ='Consolidated P&L'!G13 -> 150.4 | D70: ='Consolidated P&L'!H13 -> 221.7 | E70: ='Consolidated P&L'!I13 -> 278.9 | F70: ='Consolidated P&L'!J13 -> 276.3
A71: Depreciation And Amortisation Expenses | B71: ='Consolidated P&L'!F14 -> 354.9 | C71: ='Consolidated P&L'!G14 -> 722.7 | D71: ='Consolidated P&L'!H14 -> 818.9 | E71: ='Consolidated P&L'!I14 -> 991.5 | F71: ='Consolidated P&L'!J14 -> 1054.1
A72: Other Expenses | B72: ='Consolidated P&L'!F15 -> 253.1 | C72: ='Consolidated P&L'!G15 -> 2227.5 | D72: ='Consolidated P&L'!H15 -> 2217.8 | E72: ='Consolidated P&L'!I15 -> 4259.4 | F72: ='Consolidated P&L'!J15 -> 8465.5
A73: Total Expenses | B73: ='Consolidated P&L'!F16 -> 13038 | C73: ='Consolidated P&L'!G16 -> 27948.4 | D73: ='Consolidated P&L'!H16 -> 30170.2 | E73: ='Consolidated P&L'!I16 -> 32783.6 | F73: ='Consolidated P&L'!J16 -> 36082.8
... A91: Equity Share Dividend | B91: ='Consolidated P&L'!F34 -> 874.9 | C91: ='Consolidated P&L'!G34 -> 1562.7 | D91: ='Consolidated P&L'!H34 -> 1775.3 | E91: ='Consolidated P&L'!I34 -> 1924.6 | F91: ='Consolidated P&L'!J34 -> 0
A93: Consolidated Cash Flow
A94: Particulars (Rs. Cr.) | B94: Mar 22 | C94: Mar 23 | D94: Mar 24 | E94: Mar 25 | F94: Mar 26
B95: 12 mths | C95: 12 mths | D95: 12 mths | E95: 12 mths | F95: 12 mths
A96: Net Profit Before Tax | B96: 2298.5 | C96: 4410.3 | D96: 4584.6 | E96: 4602 | F96: 6791.1
A97: Net Cash From Operating Activities | B97: 1652 | C97: 3094.6 | D97: 5669.5 | E97: 4545.8 | F97: 4798.8
A98: Net Cash (used in)/from Investing Activities | B98: -959.4 | C98: -330.9 | D98: -3912.1 | E98: -1738.2 | F98: -1767.9
A99: Net Cash (used in)/from Financing Activities | B99: -1045.8 | C99: -1931.7 | D99: -2268.8 | E99: -2574.4 | F99: -2926.4
A100: Net (decrease)/increase In Cash and Cash Equivalents | B100: -364.5 | C100: 891.5 | D100: -517.7 | E100: 242.3 | F100: 268.8
A101: Opening Cash & Cash Equivalents | B101: 759.4 | C101: 1446.2 | D101: 2337.7 | E101: 1820 | F101: 2062.3
A102: Closing Cash & Cash Equivalents | B102: 394.9 | C102: 2337.7 | D102: 1820 | E102: 2062.3 | F102: 2331.1

Sheet Relative valuation
A1: RELATIVE VALUATION – LTIM (FY2025 | INR Crores)
A3: Company | B3: Market Data | F3: Financial Data | J3: Valuation Ratios
B4: Price (₹) | C4: Shares (Cr.) | D4: Mkt Cap (Cr.) | E4: EV (Cr.) | F4: Revenue (Cr.) | G4: EBITDA (Cr.) | H4: EBIT (Cr.) | I4: EPS (₹) | J4: P/E | K4: EV/Sales | L4: EV/EBITDA | M4: EV/EBIT
A5: LTIM | B5: 4167.8 | C5: ='Merge data sheet'!F6 -> 29.6 | D5: 124006 | E5: =D5+'Merge data sheet'!F21+'Merge data sheet'!F15-('Merge data sheet'!F43) -> 121193.6 | F5: ='Assumptions (Historical FS)'!F3 -> 42307.6 | G5: ='Assumptions (Historical FS)'!F9 -> 7555.2 | H5: ='Assumptions (Historical FS)'!F11 -> 6501.1 | I5: ='Consolidated P&L'!J31 -> 169 | J5: =B5/I5 -> 24.661538 | K5: =E5/F5 -> 2.8645822 | L5: =E5/G5 -> 16.041084 | M5: =E5/H5 -> 18.642014
A6: TCS | B6: 2298 | C6: 362 | D6: 830496 | E6: 842432.1 | F6: 267021 | G6: 72274 | H6: =1227+65487 -> 66714 | I6: 136.61 | J6: =B6/I6 -> 16.821609 | K6: =E6/F6 -> 3.1549283 | L6: =E6/G6 -> 11.656088 | M6: =E6/H6 -> 12.627516
A7: INFOSYS | B7: 1132.4 | C7: 2024 | D7: 458127 | E7: 498708.64 | F7: 166590 | G7: 42836 | H7: =37608+416 -> 38024 | I7: 64.52 | J7: =B7/I7 -> 17.551147 | K7: =E7/F7 -> 2.9936289 | L7: =E7/G7 -> 11.642278 | M7: =E7/H7 -> 13.115628
A8: HCL TECH | B8: 1147.6 | C8: 543 | D8: 311393 | E8: 340709.19 | F8: 130824 | G8: 27326 | H8: =22102+869 -> 22971 | I8: 61.33 | J8: =B8/I8 -> 18.711887 | K8: =E8/F8 -> 2.6043325 | L8: =E8/G8 -> 12.468316 | M8: =E8/H8 -> 14.832144
A9: WIPRO | B9: 190.8 | C9: 2097.7 | D9: 200054 | E9: 200184.02 | F9: 92624 | G9: 21684.9 | H9: 18774.2 | I9: 13 | J9: =B9/I9 -> 14.676923 | K9: =E9/F9 -> 2.1612543 | L9: =E9/G9 -> 9.2314938 | M9: =E9/H9 -> 10.662719
A10: TECH MAHINDRA | B10: 1406.1 | C10: 442.8 | D10: 137615 | E10: 134008.27 | F10: 56815.4 | G10: 8793.6 | H10: 6912 | I10: 54.28 | J10: =B10/I10 -> 25.904569 | K10: =E10/F10 -> 2.358661 | L10: =E10/G10 -> 15.239296 | M10: =E10/H10 -> 19.387771
A11: Peer Average | B11: =AVERAGE(B6:B10) -> 1234.98 | C11: =AVERAGE(C6:C10) -> 1093.9 | D11: =AVERAGE(D6:D10) -> 387537 | E11: =AVERAGE(E6:E10) -> 403208.44 | F11: =AVERAGE(F6:F10) -> 142774.88 | G11: =AVERAGE(G6:G10) -> 34582.9 | H11: =AVERAGE(H6:H10) -> 30679.04 | I11: =AVERAGE(I6:I10) -> 65.948 | ... M11: =AVERAGE(M6:M10) -> 14.125156
A12: Peer Median | B12: =MEDIAN(B6:B10) -> 1147.6 | C12: =MEDIAN(C6:C10) -> 543 | D12: =MEDIAN(D6:D10) -> 311393 | E12: =MEDIAN(E6:E10) -> 340709.19 | F12: =MEDIAN(F6:F10) -> 130824 | G12: =MEDIAN(G6:G10) -> 27326 | H12: =MEDIAN(H6:H10) -> 22971 | I12: =MEDIAN(I6:I10) -> 61.33 | ... M12: =MEDIAN(M6:M10) -> 13.115628
A14: Ltim — IMPLIED SHARE PRICE FROM PEER MULTIPLES
A15: Valuation Basis | B15: Peer Avg Multiple | C15: Peer Median Multiple | D15: LTIM Actual | E15: Implied EV (Avg) | F15: Implied EV (Median) | G15: Implied Equity (Avg) | H15: Implied Equity (Median) | I15: Implied Price (Avg) ₹ | J15: Implied Price (Med) ₹ | K15: CMP ₹ | L15: Premium/Disc (vs Avg) | M15: Premium/Disc (vs Med)
A16: EV / Sales | B16: =K11 -> 2.654561 | C16: =K12 -> 2.6043325 | D16: =K5 -> 2.8645822 | E16: =B16*F5 -> 112308.1 | F16: =C16*F5 -> 110183.06 | G16: =E16-(E5-D5) -> 115120.5 | H16: =F16-(E5-D5) -> 112995.46 | I16: =G16/C5 -> 3889.2062 | J16: =H16/C5 -> 3817.4141 | K16: =B5 -> 4167.8 | L16: =(B5-I16)/I16 -> 0.071632549 | M16: =(B5-J16)/J16 -> 0.091786204
A17: EV / EBITDA | B17: =L11 -> 12.047494 | C17: =L12 -> 11.656088 | D17: =L5 -> 16.041084 | E17: =B17*G5 -> 91021.229 | F17: =C17*G5 -> 88064.076 | G17: =E17-(E5-D5) -> 93833.629 | H17: =F17-(E5-D5) -> 90876.476 | I17: =G17/C5 -> 3170.055 | J17: =H17/C5 -> 3070.1512 | K17: =K16 -> 4167.8 | L17: =(B5-I17)/I17 -> 0.31474059 | M17: =(B5-J17)/J17 -> 0.35752272
A18: P / E | B18: =J11 -> 18.733227 | C18: =J12 -> 17.551147 | D18: =J5 -> 24.661538 | E18: =B18*I5 -> 3165.9153 | F18: =C18*I5 -> 2966.1438 | G18: =E18*C5 -> 93711.094 | H18: =F18*C5 -> 87797.857 | I18: =E18 -> 3165.9153 | J18: =F18 -> 2966.1438 | K18: =K17 -> 4167.8 | L18: =(B5-I18)/I18 -> 0.31645971 | M18: =(B5-J18)/J18 -> 0.40512404
O20: EV/Revenue | P20: EV/EBITDA | Q20: P/E Ratio
A21: Max | O21: =MAX(K6:K10) -> 3.1549283 | P21: =MAX(L6:L10) -> 15.239296 | Q21: =MAX(J6:J10) -> 25.904569
A22: 75th Percentile | O22: =QUARTILE(K6:K10,3) -> 2.9936289 | P22: =QUARTILE(L6:L10,3) -> 12.468316 | Q22: =QUARTILE(J6:J10,3) -> 18.711887
A23: Average | O23: =AVERAGE(K6:K10) -> 2.654561 | P23: =AVERAGE(L6:L10) -> 12.047494 | Q23: =AVERAGE(J6:J10) -> 18.733227
A24: median | O24: =MEDIAN(K6:K10) -> 2.6043325 | P24: =MEDIAN(L6:L10) -> 11.656088 | Q24: =MEDIAN(J6:J10) -> 17.551147
A25: 25th Percentile | O25: =QUARTILE(K6:K10,1) -> 2.358661 | P25: =QUARTILE(L6:L10,1) -> 11.642278 | Q25: =QUARTILE(J6:J10,1) -> 16.821609
A26: Min. | O26: =MIN(K6:K10) -> 2.1612543 | P26: =MIN(L6:L10) -> 9.2314938 | Q26: =MIN(J6:J10) -> 14.676923
A28: M&M Industry Comparable comps | O28: EV/Revenue | P28: EV/EBITDA | Q28: P/E Ratio
A30: Implied Enterprise Value | O30: =O23*F5 -> 112308.1 | P30: =P23*G5 -> 91021.229 | Q30: =Q23*I5*C5 -> 93711.094
A31: Net Debt | O31: =E5-D5 -> -2812.4 | P31: =E5-D5 -> -2812.4 | Q31: =E5-D5 -> -2812.4
A32: Implied Market Value | O32: =O30-O31 -> 115120.5 | P32: =P30-P31 -> 93833.629 | Q32: =Q30-Q31 -> 96523.494
A33: Share Outstanding | O33: =C5 -> 29.6 | P33: =C5 -> 29.6 | Q33: =C5 -> 29.6
A35: Implied Value per Share | O35: =O32/O33 -> 3889.2062 | P35: =P32/P33 -> 3170.055 | Q35: =Q23*I5 -> 3165.9153

Sheet Growth Scenario
A1: Scenario 1: High Growth
A2: INR Cr. | B2: LTM | C2: Y1E | D2: Y2E | E2: Y3E | F2: Y4W | G2: Y5E | H2: Y6E | I2: Y7E | J2: Y8E | K2: Y9E | L2: Y10E
A3: Sales | B3: ='Assumptions (Historical FS)'!F3 -> 42307.6 | C3: =B3*(1+C4) -> 51605.439 | D3: =C3*(1+D4) -> 62109.099 | E3: =D3*(1+E4) -> 73742.637 | F3: =E3*(1+F4) -> 86358.408 | G3: =F3*(1+G4) -> 99730.891 | H3: =G3*(1+H4) -> 113555.48 | I3: =H3*(1+I4) -> 127453.44 | J3: =I3*(1+J4) -> 140983.83 | ... L3: =K3*(1+L4) -> 164987.39 | M3: ='Assumptions (Historical FS)'!B22 -> 0.21976758 | P3: Risk free rate
A4: Sales Growth % | C4: =M3 -> 0.21976758 | D4: =C4-$O$4 -> 0.20353785 | E4: =D4-$O$4 -> 0.18730811 | F4: =E4-$O$4 -> 0.17107838 | G4: =F4-$O$4 -> 0.15484865 | H4: =G4-$O$4 -> 0.13861892 | I4: =H4-$O$4 -> 0.12238919 | J4: =I4-$O$4 -> 0.10615946 | K4: =J4-$O$4 -> 0.089929731 | L4: =K4-$O$4 -> 0.0737 | M4: 0.0737 | N4: =M3-M4 -> 0.14606758 | O4: =N4/9 -> 0.016229731 | P4: =M4 -> 0.0737
A6: Scenario 2: Average Growth
A7: INR Cr. | B7: LTM | C7: Y1E | D7: Y2E | E7: Y3E | F7: Y4W | G7: Y5E | H7: Y6E | I7: Y7E | J7: Y8E | K7: Y9E | L7: Y10E | M7: Average rate | N7: ='Assumptions (Historical FS)'!B21 -> 0.34284626
A8: Sales | B8: =B3 -> 42307.6 | C8: =B8*(1+C9) -> 56812.603 | D8: =C8*(1+D9) -> 74591.602 | E8: =D8*(1+E9) -> 95703.71 | F8: =E8*(1+F9) -> 119929.27 | G8: =F8*(1+G9) -> 146700.57 | H8: =G8*(1+H9) -> 175060.8 | I8: =H8*(1+I9) -> 203668.44 | J8: =I8*(1+J9) -> 230860.27 | ... L8: =K8*(1+L9) -> 273555.76 | N8: =M4 -> 0.0737 | O8: =N7-N8 -> 0.26914626 | P8: =O8/9 -> 0.02990514
A9: Sales Growth % | C9: =N7 -> 0.34284626 | D9: =C9-$P$8 -> 0.31294112 | E9: =D9-$P$8 -> 0.28303598 | F9: =E9-$P$8 -> 0.25313084 | G9: =F9-$P$8 -> 0.2232257 | H9: =G9-$P$8 -> 0.19332056 | I9: =H9-$P$8 -> 0.16341542 | J9: =I9-$P$8 -> 0.13351028 | K9: =J9-$P$8 -> 0.10360514 | L9: =K9-$P$8 -> 0.0737
A11: Scenario 3: EBIT Growth
A12: INR Cr. | B12: LTM | C12: Y1E | D12: Y2E | E12: Y3E | F12: Y4W | G12: Y5E | H12: Y6E | I12: Y7E | J12: Y8E | K12: Y9E | L12: Y10E | N12: ='Assumptions (Historical FS)'!C46 -> 0.040507542
A13: Sales | B13: =B8 -> 42307.6 | C13: =B13*(1+C14) -> 44021.377 | D13: =C13*(1+D14) -> 45966.928 | E13: =D13*(1+E14) -> 48167.992 | F13: =E13*(1+F14) -> 50652.097 | G13: =F13*(1+G14) -> 53451.119 | H13: =G13*(1+H14) -> 56601.944 | I13: =H13*(1+I14) -> 60147.255 | J13: =I13*(1+J14) -> 64136.456 | ... L13: =K13*(1+L14) -> 73684.567 | N13: =N8 -> 0.0737 | O13: =N12-N13 -> -0.033192458 | P13: =O13/9 -> -0.0036880509
A14: Sales Growth % | C14: =N12 -> 0.040507542 | D14: =C14-($P$13) -> 0.044195593 | E14: =D14-($P$13) -> 0.047883644 | F14: =E14-($P$13) -> 0.051571695 | G14: =F14-($P$13) -> 0.055259746 | H14: =G14-($P$13) -> 0.058947797 | I14: =H14-($P$13) -> 0.062635847 | J14: =I14-($P$13) -> 0.066323898 | K14: =J14-($P$13) -> 0.070011949 | L14: =K14-($P$13) -> 0.0737 | P14: 0.00294
A16: Live Scenario | B16: 3
A17: INR Cr. | C17: Y1E | D17: Y2E | E17: Y3E | F17: Y4W | G17: Y5E | H17: Y6E | I17: Y7E | J17: Y8E | K17: Y9E | L17: Y10E
A18: Sales | B18: =B13 -> 42307.6 | C18: =B18*(1+C19) -> 44021.377 | D18: =C18*(1+D19) -> 45966.928 | E18: =D18*(1+E19) -> 48167.992 | F18: =E18*(1+F19) -> 50652.097 | G18: =F18*(1+G19) -> 53451.119 | H18: =G18*(1+H19) -> 56601.944 | I18: =H18*(1+I19) -> 60147.255 | J18: =I18*(1+J19) -> 64136.456 | ... L18: =K18*(1+L19) -> 73684.567
A19: Sales Growth % | C19: =CHOOSE($B$16,C4,C9,C14) -> 0.040507542 | D19: =CHOOSE($B$16,D4,D9,D14) -> 0.044195593 | E19: =CHOOSE($B$16,E4,E9,E14) -> 0.047883644 | F19: =CHOOSE($B$16,F4,F9,F14) -> 0.051571695 | G19: =CHOOSE($B$16,G4,G9,G14) -> 0.055259746 | H19: =CHOOSE($B$16,H4,H9,H14) -> 0.058947797 | I19: =CHOOSE($B$16,I4,I9,I14) -> 0.062635847 | J19: =CHOOSE($B$16,J4,J9,J14) -> 0.066323898 | ... L19: =CHOOSE($B$16,L4,L9,L14) -> 0.0737

Sheet Forecasting
C3: Sales Forecasting | H3: EBITDA Forecasting | M3: Earning per share Forecasting
C4: Year Weight | D4: Year | E4: Sales | F4: Sales Growth | H4: Year Weight | I4: Year | J4: EBITDA | K4: EBITDA Growth | M4: Year Weight | N4: Year | O4: EPS | P4: EPS Growth
C5: 1 | D5: ='Merge data sheet'!B2 -> 44621 | E5: {=TRANSPOSE('Merge data sheet'!B63:F63)} -> 15668.7 | H5: 1 | I5: ='Merge data sheet'!B2 -> 44621 | J5: {=TRANSPOSE('Assumptions (Historical FS)'!B9:F9)} -> 3058.4 | M5: 1 | N5: ='Merge data sheet'!B2 -> 44621 | O5: {=TRANSPOSE('Merge data sheet'!B88:F88)} -> 131
C6: =C5+1 -> 2 | D6: =D5+365 -> 44986 | E6: 33183 | F6: =(E6-E5)/E5 -> 1.117789 | H6: =H5+1 -> 2 | I6: =I5+365 -> 44986 | J6: 6107.7 | K6: =(J6-J5)/J5 -> 0.99702459 | M6: =M5+1 -> 2 | N6: =N5+365 -> 44986 | O6: 149 | P6: =(O6-O5)/O5 -> 0.13740458
C7: =C6+1 -> 3 | D7: =D6+365 -> 45351 | E7: 35517 | F7: =(E7-E6)/E6 -> 0.070337221 | H7: =H6+1 -> 3 | I7: =I6+365 -> 45351 | J7: 6387.4 | K7: =(J7-J6)/J6 -> 0.045794653 | M7: =M6+1 -> 3 | N7: =N6+365 -> 45351 | O7: 155 | P7: =(O7-O6)/O6 -> 0.040268456
C8: =C7+1 -> 4 | D8: =D7+365 -> 45716 | E8: 38008.1 | F8: =(E8-E7)/E7 -> 0.070138244 | H8: =H7+1 -> 4 | I8: =I7+365 -> 45716 | J8: 6494.9 | K8: =(J8-J7)/J7 -> 0.016830009 | M8: =M7+1 -> 4 | N8: =N7+365 -> 45716 | O8: 155 | P8: =(O8-O7)/O7 -> 0
C9: =C8+1 -> 5 | D9: =D8+365 -> 46081 | E9: 42307.6 | F9: =(E9-E8)/E8 -> 0.11312062 | H9: =H8+1 -> 5 | I9: =I8+365 -> 46081 | J9: 7555.2 | K9: =(J9-J8)/J8 -> 0.16325117 | M9: =M8+1 -> 5 | N9: =N8+365 -> 46081 | O9: 169 | P9: =(O9-O8)/O8 -> 0.090322581
C10: =C9+1 -> 6 | D10: =D9+365 -> 46446 | E10: =FORECAST(C10,$E$5:$E$9,$C$5:$C$9) -> 50367.75 | F10: =(E10-E9)/E9 -> 0.19051305 | H10: =H9+1 -> 6 | I10: =I9+365 -> 46446 | J10: =FORECAST(H10,$J$5:$J$9,$H$5:$H$9) -> 8734.96 | K10: =(J10-J9)/J9 -> 0.15615205 | M10: =M9+1 -> 6 | N10: =N9+365 -> 46446 | O10: =FORECAST(M10,$O$5:$O$9,$M$5:$M$9) -> 176.4 | P10: =(O10-O9)/O9 -> 0.043786982
C11: =C10+1 -> 7 | D11: =D10+365 -> 46811 | E11: =FORECAST(C11,$E$5:$E$9,$C$5:$C$9) -> 56178.04 | F11: =(E11-E10)/E10 -> 0.11535735 | H11: =H10+1 -> 7 | I11: =I10+365 -> 46811 | J11: =FORECAST(H11,$J$5:$J$9,$H$5:$H$9) -> 9673.04 | K11: =(J11-J10)/J10 -> 0.10739374 | M11: =M10+1 -> 7 | N11: =N10+365 -> 46811 | O11: =FORECAST(M11,$O$5:$O$9,$M$5:$M$9) -> 184.6 | P11: =(O11-O10)/O10 -> 0.046485261
C12: =C11+1 -> 8 | D12: =D11+365 -> 47176 | E12: =FORECAST(C12,$E$5:$E$9,$C$5:$C$9) -> 61988.33 | F12: =(E12-E11)/E11 -> 0.10342636 | H12: =H11+1 -> 8 | I12: =I11+365 -> 47176 | J12: =FORECAST(H12,$J$5:$J$9,$H$5:$H$9) -> 10611.12 | K12: =(J12-J11)/J11 -> 0.096978819 | M12: =M11+1 -> 8 | N12: =N11+365 -> 47176 | O12: =FORECAST(M12,$O$5:$O$9,$M$5:$M$9) -> 192.8 | P12: =(O12-O11)/O11 -> 0.044420368
C13: =C12+1 -> 9 | D13: =D12+365 -> 47541 | E13: =FORECAST(C13,$E$5:$E$9,$C$5:$C$9) -> 67798.62 | F13: =(E13-E12)/E12 -> 0.093731998 | H13: =H12+1 -> 9 | I13: =I12+365 -> 47541 | J13: =FORECAST(H13,$J$5:$J$9,$H$5:$H$9) -> 11549.2 | K13: =(J13-J12)/J12 -> 0.088405371 | M13: =M12+1 -> 9 | N13: =N12+365 -> 47541 | O13: =FORECAST(M13,$O$5:$O$9,$M$5:$M$9) -> 201 | P13: =(O13-O12)/O12 -> 0.04253112
C14: =C13+1 -> 10 | D14: =D13+365 -> 47906 | E14: =FORECAST(C14,$E$5:$E$9,$C$5:$C$9) -> 73608.91 | F14: =(E14-E13)/E13 -> 0.085699237 | H14: =H13+1 -> 10 | I14: =I13+365 -> 47906 | J14: =FORECAST(H14,$J$5:$J$9,$H$5:$H$9) -> 12487.28 | K14: =(J14-J13)/J13 -> 0.081224674 | M14: =M13+1 -> 10 | N14: =N13+365 -> 47906 | O14: =FORECAST(M14,$O$5:$O$9,$M$5:$M$9) -> 209.2 | P14: =(O14-O13)/O13 -> 0.04079602

Sheet WACC
B2: Capital Structure
B3: Total Debt | C3: ='Merge data sheet'!F15+'Merge data sheet'!F21 -> 0
B4: Total Equity | C4: ='Merge data sheet'!F7*'Stock Analysis'!D24 -> 138004.08
B5: Total Mix (Debt + Equity) | C5: =C4+C3 -> 138004.08
B6: % of Debt | C6: =C3/C5 -> 0
B7: % of Equity | C7: =C4/C5 -> 1
B8: Debt to Equity | C8: =C3/C4 -> 0
B10: Cost of Equity (CAPM)
B11: Risk-free Rate (Rf) | C11: 0.0737 | E11: Source: RBI 10-year Government Securities yield (FY2025)
B12: Beta (β) | C12: =BETA!I3 -> 0.83831404
B13: Market Risk Premium (Rm - Rf) | C13: 0.0685 | E13: Source: India Equity Risk Premium (Damodaran estimate)
B14: Cost of Equity [Ke = Rf + β×(Rm-Rf)] | C14: =C11+C12*C13 -> 0.13112451
B16: Cost of Debt
B17: Finance Cost (FY2025) | C17: ='Merge data sheet'!F70 -> 276.3
B18: Total Debt (FY2025) | C18: =C3 -> 0
B19: Pre-tax Cost of Debt [Kd = FC/Debt] | C19: =IFERROR(C17/C18,0) -> 0
B20: Tax Rate | C20: ='Assumptions (Historical FS)'!F16 -> 0.24707618
B21: Post-tax Cost of Debt [Kd*(1-T)] | C21: =C19*(1-C20) -> 0
B23: WACC
B24: Source | C24: Weight | D24: Cost | E24: Weighted Cost
B25: Debt | C25: =C6 -> 0 | D25: =C21 -> 0 | E25: =D25*C25 -> 0
B26: Equity | C26: =C7 -> 1 | D26: =C14 -> 0.13112451 | E26: =C26*D26 -> 0.13112451
B27: WACC | C27: =SUM(C25:C26) -> 1 | D27: (Check: weights = 100%) | E27: =E25+E26 -> 0.13112451 | G27: wacc = we*ke+wd*kd
