Workbook

Sheet About the Company
C3: About the Company (NMDC LTD)
C5: Message from CMD - "Iron ore is the lifeblood of India's infrastructure and industrial economy. Every tonne we mine contributes directly to the nation's roads, railways, ports, factories, and homes. We are committed to Responsible Mining to ensure progress is rooted in responsibility." - Shri Amitava Mukherjee, Chairman & Managing Director, NMDC Limited Who We Are - NMDC Limited is India's largest iron ore producer and a Navratna Public Sector Enterprise under the Ministry of Steel, Government of India. With over six decades of operational excellence, NMDC specialises in mechanised, cost-efficient and sustainable mining, serving markets both within India and internationally. Our operations include some of India's most advanced iron ore mines in Chhattisgarh and Karnataka, as well as South-East Asia's only mechanised diamond mine in Panna, Madhya Pradesh. Our mines have earned 5-Star ratings from the Indian Bureau of Mines. Our R&D Centre in Hyderabad is recognised as a Centre of Excellence by UNIDO. Products & Services - Iron Ore Products: Baila ROM (Fe 65.5%), DRCLO (Fe 67%), Baila Lump (Fe 65.5%), 10-20mm Baila (Fe 65.5%), Baila Fine (Fe 64%), Kumaraswamy Lump (Fe 64.5%), Kumaraswamy Fine (Fe 65%), Doni Lump (Fe 61%), Doni Fines (Fe 60%), Iron Ore Pellets (BF Grade). Also produces Rough Diamonds from Panna Mines. Industries Served - Steel manufacturing (primary), infrastructure, power, construction. Key customers include major steel producers across India. Current production ~44.07 MnT iron ore per annum; target 100 MTPA by FY30. Vision - To emerge as a global environment friendly mining organisation and also as a quality steel producer with a positive thrust on social development. Mission - To maintain its leadership as the largest iron ore producer in India, while establishing itself as a quality steel producer and expanding business by acquiring and operating iron ore, coal and other mineral assets in India and abroad, rendering optimum satisfaction to all stakeholders. FY25 Key Highlights - Revenue from Operations: Rs.23,668 Cr | PAT: Rs.6,693 Cr | PBT: Rs.9,296 Cr | Net Worth: Rs.29,579 Cr | Dividend: Rs.2,901 Cr (330%) | EPS: Rs.7.61 | ROCE: 32% | Iron Ore Production: 44.07 MnT | Iron Ore Sales: 44.40 MnT | Pellet Production: 1,70,605 T | Diamond Production: 4,602.03 Carats
C19: Subsidiaries & Joint Ventures
C20: S.No | D20: Company Name | E20: Type | F20: Country / Stake
C21: 1 | D21: Karnataka Vijaynagar Steel Ltd. | E21: Wholly Owned Subsidiary | F21: India - 100%
C22: 2 | D22: NMDC CSR Foundation | E22: Wholly Owned Subsidiary | F22: India - 100%
C23: 3 | D23: J&KMDC Ltd. | E23: Subsidiary | F23: India - 95.86%
C24: 4 | D24: Legacy Iron Ore Ltd. | E24: Subsidiary | F24: Australia - 92.84%
C25: 5 | D25: Jharkhand NMDC Ltd. | E25: Joint Venture | F25: India - 60%
C26: 6 | D26: Bastar Railway Private Ltd. | E26: Joint Venture | F26: India - 52%
C27: 7 | D27: NMDC-CMDC Ltd. | E27: Joint Venture | F27: India - 51%
C29: Total Investments in Subsidiaries, JVs & Associates | D29: Rs.1,115.34 Crore
C32: Registered Office
C33: Khanij Bhavan, 10-3-311/A, Castle Hills, Masab Tank, Hyderabad - 500028, Telangana
C34: CIN: L13100AP1958GOI001674
C35: Website: www.nmdc.co.in | Email: investors@nmdc.co.in
C38: Units & Operational Footprint
C39: Company | D39: Unit Type | E39: Number | F39: Details
C40: NMDC Limited | D40: Iron Ore Mines | E40: 3 | F40: Bailadila Complex (CG), Donimalai & Kumaraswamy (KA)
C41: NMDC Limited | D41: Diamond Mine | E41: 1 | F41: Panna Diamond Mine, Madhya Pradesh
C42: NMDC Limited | D42: Pellet Plant | E42: 1 | F42: Donimalai Pellet Plant, Karnataka
C43: NMDC Limited | D43: R&D Centre | E43: 1 | F43: Hyderabad - UNIDO Centre of Excellence
C44: NMDC Limited | D44: Iron Ore Production Capacity | E44: 44 MnT | F44: Current; target 100 MTPA by FY30
C45: NMDC Limited | D45: Total Workforce | E45: 5677 | F45: As of FY2024-25
C46: NMDC Limited | D46: Countries of Operation | E46: 3 | F46: India, Australia, Mozambique
C47: NMDC Limited | D47: Stock Exchanges | E47: 2 | F47: BSE & NSE (Nifty 50 Index)
C50: Board of Directors
C51: Name | D51: Designation
C52: Shri Amitava Mukherjee | D52: Chairman & Managing Director
C53: Shri Vishwanath Suresh | D53: Director (Commercial)
C54: Shri Joydeep Dasgupta | D54: Director (Production)
C55: Shri Vinay Kumar | D55: Director (Technical)
C56: Smt. Priyadarshini Gaddam | D56: Director (Personnel) & Director (Finance) - Addl. Charge
C57: Shri Ashish Chatterjee IAS | D57: Addl. Secretary & Financial Advisor, Ministry of Steel (Govt. Nominee)
C58: Shri Abhijit Narendra IRTS | D58: Joint Secretary, Ministry of Steel (Govt. Nominee)
C59: Shri Sanjay Tandon | D59: Independent Director
C60: Shri Mahendra Singh Rao | D60: Independent Director
C61: Shri Bharat Baburao Patil | D61: Independent Director
C62: Shri Achal Kumar Sinha | D62: Independent Director
... C65: Shri B. Vishwanath IRSS | D65: Chief Vigilance Officer

Sheet Promoter
B2: NMDC Limited — Shareholding Pattern (As of Q4 FY2024-25)
B4: PROMOTER (GoI) | D4: INSTITUTIONAL (DII + FII) | F4: RETAIL & OTHERS
B5: 60.79% | D5: 27.36% | F5: 11.85%
B6: 5,34,49,00,713 shares | D6: DII: 13.76% | FII: 13.60% | F6: Retail + NRI + Bodies Corp.
B8: (A) Promoter & Promoter Group
B9: Category | C9: No. of Shareholders | D9: Shares Held | E9: Stake % | F9: Voting Rights % | G9: Demat Shares
B10: Central Govt. / State Govt. (Indian) | C10: 1 | D10: 5,34,49,00,713 | E10: 60.79% | F10: 60.79% | G10: 5,34,49,00,713
B11: PRESIDENT OF INDIA | C11: 1 | D11: 5,34,49,00,713 | E11: 60.79% | F11: 60.79% | G11: 5,34,49,00,713
B12: Sub-Total A1 (Indian) | C12: 1 | D12: 5,34,49,00,713 | E12: 60.79% | F12: 60.79% | G12: 5,34,49,00,713
B13: A2 — Foreign | C13: - | D13: - | E13: 0.00% | F13: 0.00% | G13: -
B14: TOTAL PROMOTER (A = A1 + A2) | C14: 1 | D14: 5,34,49,00,713 | E14: 60.79% | F14: 60.79% | G14: 5,34,49,00,713
B16: (B1) Domestic Institutional Investors (DII)
B17: Investor Category | C17: No. of Shareholders | D17: Shares Held | E17: Stake % | F17: Voting Rights % | G17: Demat Shares
B18: Mutual Funds | C18: 41 | D18: 58,95,25,071 | E18: 6.71% | F18: 6.71% | G18: 58,95,25,071
B19: SBI Arbitrage Opp. Fund ★ | C19: 1 | D19: 12,02,18,423 | E19: 1.37% | F19: 1.37% | G19: —
B20: Insurance Companies | C20: 27 | D20: 60,67,99,104 | E20: 6.90% | F20: 6.90% | G20: 60,67,99,104
B21: LIC of India ★ | C21: 1 | D21: 43,02,17,392 | E21: 4.89% | F21: 4.89% | G21: —
B22: Alternate Investment Funds | C22: 17 | D22: 84,47,230 | E22: 0.10% | F22: 0.10% | G22: 84,47,230
B23: Banks | C23: 3 | D23: 82,469 | E23: 0.00% | F23: 0.00% | G23: 82,469
B24: Other Financial Institutions | C24: 1 | D24: 46,93,620 | E24: 0.05% | F24: 0.05% | G24: 46,93,620
B25: NBFCs (RBI Registered) | C25: 10 | D25: 2,61,021 | E25: 0.00% | F25: 0.00% | G25: 2,61,021
B26: Sub-Total B1 — DII | C26: 99 | D26: 1,20,98,08,515 | E26: 13.76% | F26: 13.76% | G26: 1,20,98,08,515
B28: (B2) Foreign Institutional Investors (FII)
B29: Investor Category | C29: No. of Shareholders | D29: Shares Held | E29: Stake % | F29: Voting Rights % | G29: Demat Shares
B30: Foreign Portfolio Investors — Cat I | C30: 583 | D30: 1,13,53,68,005 | E30: 12.91% | F30: 12.91% | G30: 1,13,53,68,005
B31: Foreign Portfolio Investors — Cat II | C31: 31 | D31: 6,04,21,353 | E31: 0.69% | F31: 0.69% | G31: 6,04,21,353
B32: Foreign Direct Investment | C32: 0 | D32: — | E32: 0.00% | F32: 0.00% | G32: —
B33: Sovereign Wealth Funds | C33: 0 | D33: — | E33: 0.00% | F33: 0.00% | G33: —
B34: Sub-Total B2 — FII | C34: 614 | D34: 1,19,57,89,358 | E34: 13.60% | F34: 13.60% | G34: 1,19,57,89,358
B36: (B4) Non-Institutions (Retail & Others)
B37: Category | C37: No. of Shareholders | D37: Shares Held | E37: Stake % | F37: Voting Rights % | G37: Demat Shares
B38: Resident Individuals (≤ ₹2L capital) | C38: 1112355 | D38: 75,48,95,145 | E38: 8.59% | F38: 8.59% | G38: 75,48,37,682
B39: Resident Individuals (> ₹2L capital) | C39: 160 | D39: 13,24,54,755 | E39: 1.51% | F39: 1.51% | G39: 13,24,54,755
B40: Bodies Corporate | C40: 2536 | D40: 10,93,14,096 | E40: 1.24% | F40: 1.24% | G40: 10,93,12,096
B41: Non-Resident Indians (NRIs) | C41: 14956 | D41: 3,96,00,637 | E41: 0.45% | F41: 0.45% | G41: 3,96,00,637
B42: Trusts | C42: 60 | D42: 42,20,003 | E42: 0.05% | F42: 0.05% | G42: 42,20,003
B43: Employees | C43: 114 | D43: 2,08,479 | E43: 0.00% | F43: 0.00% | G43: 2,00,989
B44: IEPF | C44: 1 | D44: 2,23,561 | E44: 0.00% | F44: 0.00% | G44: 2,23,561
B45: Others (FPI Cat III, Clearing, etc.) | C45: 10 | D45: 3,94,088 | E45: 0.00% | F45: 0.00% | G45: 3,94,088
B46: Foreign Nationals | C46: 3 | D46: 3,802 | E46: 0.00% | F46: 0.00% | G46: 3,802
B47: Sub-Total B4 — Non-Institutions | C47: 11,30,198 | D47: 1,04,13,14,746 | E47: 11.84% | F47: 11.84% | G47: 1,04,12,47,793
B49: GRAND TOTAL (A + B) | C49: 1,131,914 | D49: 8,79,18,17,550 | E49: 100.00% | F49: 100.00% | G49: 8,79,11,50,597
B51: ★ = Top holder within category shown for reference | Source: NMDC BSE/NSE Filing, Q4 FY2024-25 | All share counts in absolute numbers

Sheet Public
B2: NMDC Limited — Public Shareholding Detail (Q4 FY2024-25)
B4: DOMESTIC INSTITUTIONS (DII) | D4: FOREIGN INSTITUTIONS (FII) | F4: RETAIL & OTHERS
B5: 13.76% | D5: 13.60% | F5: 11.84%
B6: 99 shareholders | 1,20,98,08,515 shares | D6: 614 shareholders | 1,19,57,89,358 shares | F6: 11,30,198 shareholders | 1,04,13,14,746 shares
B9: (B1) Domestic Institutional Investors (DII)
B10: Category & Name of Shareholders | C10: No. of Shareholders | D10: Shares Held | E10: Stake % (A+B+C2) | F10: Voting Rights % | G10: Diluted Stake % | H10: Demat Shares
B11: Institutions | C11: 0 | D11: 0 | E11: - | F11: - | G11: - | H11: -
B12: B2) Institutions (Domestic) | C12: 0 | D12: 0 | E12: - | F12: - | G12: - | H12: -
B13: Mutual Funds | C13: 41 | D13: 58,95,25,071 | E13: 6.71% | F13: 6.71% | G13: 6.71% | H13: 58,95,25,071
B14: SBI Arbitrage Opportunities Fund ★ | C14: 1 | D14: 12,02,18,423 | E14: 1.37% | F14: 1.37% | G14: 1.37% | H14: —
B15: Venture Capital Funds | C15: 0 | D15: 0 | E15: — | F15: — | G15: — | H15: —
B16: Alternate Investment Funds | C16: 17 | D16: 84,47,230 | E16: 0.10% | F16: 0.10% | G16: 0.10% | H16: 84,47,230
B17: Banks | C17: 3 | D17: 82,469 | E17: 0.00% | F17: 0.00% | G17: 0.00% | H17: 82,469
B18: Insurance Companies | C18: 27 | D18: 60,67,99,104 | E18: 6.90% | F18: 6.90% | G18: 6.90% | H18: 60,67,99,104
B19: Life Insurance Corporation of India ★ | C19: 1 | D19: 43,02,17,392 | E19: 4.89% | F19: 4.89% | G19: 4.89% | H19: —
B20: Provident Funds / Pension Funds | C20: 0 | D20: 0 | E20: — | F20: — | G20: — | H20: —
B21: Asset Reconstruction Companies | C21: 0 | D21: 0 | E21: — | F21: — | G21: — | H21: —
B22: Sovereign Wealth Funds | C22: 0 | D22: 0 | E22: — | F22: — | G22: — | H22: —
B23: NBFCs Registered with RBI | C23: 10 | D23: 2,61,021 | E23: 0.00% | F23: 0.00% | G23: 0.00% | H23: 2,61,021
B24: Other Financial Institutions | C24: 1 | D24: 46,93,620 | E24: 0.05% | F24: 0.05% | G24: 0.05% | H24: 46,93,620
B25: Any Other — Institutions (Domestic) | C25: 0 | D25: 0 | E25: — | F25: — | G25: — | H25: —
B26: Sub-Total B1 — DII | C26: 99 | D26: 1,20,98,08,515 | E26: 13.76% | F26: 13.76% | G26: 13.76% | H26: 1,20,98,08,515
B28: (B2) Foreign Institutional Investors (FII)
B29: Category & Name of Shareholders | C29: No. of Shareholders | D29: Shares Held | E29: Stake % (A+B+C2) | F29: Voting Rights % | G29: Diluted Stake % | H29: Demat Shares
B30: B17) Institutions (Foreign) | C30: 0 | D30: 0 | E30: - | F30: - | G30: - | H30: -
B31: Foreign Direct Investment | C31: 0 | D31: 0 | E31: — | F31: — | G31: — | H31: —
B32: Foreign Venture Capital Investors | C32: 0 | D32: 0 | E32: — | F32: — | G32: — | H32: —
B33: Sovereign Wealth Funds | C33: 0 | D33: 0 | E33: — | F33: — | G33: — | H33: —
B34: Foreign Portfolio Investors — Category I | C34: 583 | D34: 1,13,53,68,005 | E34: 12.91% | F34: 12.91% | G34: 12.91% | H34: 1,13,53,68,005
B35: Foreign Portfolio Investors — Category II | C35: 31 | D35: 6,04,21,353 | E35: 0.69% | F35: 0.69% | G35: 0.69% | H35: 6,04,21,353
B36: Overseas Depositories (DRs) — balancing | C36: 0 | D36: 0 | E36: — | F36: — | G36: — | H36: —
B37: Any Other — Institutions (Foreign) | C37: 0 | D37: 0 | E37: — | F37: — | G37: — | H37: —
B38: Sub-Total B2 — FII | C38: 614 | D38: 1,19,57,89,358 | E38: 13.60% | F38: 13.60% | G38: 13.60% | H38: 1,19,57,89,358
B40: (B3) Central / State Government (in Public Category)
B41: Category & Name of Shareholders | C41: No. of Shareholders | D41: Shares Held | E41: Stake % (A+B+C2) | F41: Voting Rights % | G41: Diluted Stake % | H41: Demat Shares
B42: B26) Central Govt./ State Govt./ President of India | C42: 0 | D42: 0 | E42: - | F42: - | G42: - | H42: -
B43: Central Government / President of India | C43: 0 | D43: 0 | E43: — | F43: — | G43: — | H43: —
B44: State Government / Governor | C44: 0 | D44: 0 | E44: — | F44: — | G44: — | H44: —
B45: Bodies Corporate (Central/State Govt. promoter) | C45: 2 | D45: 4,218 | E45: 0.00% | F45: 0.00% | G45: 0.00% | H45: 4,218
B46: Sub-Total B3 | C46: 2 | D46: 4,218 | E46: 0.00% | F46: 0.00% | G46: 0.00% | H46: 4,218
B48: (B4) Non-Institutions (Retail & Others)
B49: Category & Name of Shareholders | C49: No. of Shareholders | D49: Shares Held | E49: Stake % (A+B+C2) | F49: Voting Rights % | G49: Diluted Stake % | H49: Demat Shares
B50: B31) Non-Institutions | C50: 0 | D50: 0 | E50: - | F50: - | G50: - | H50: -
B51: Associate Companies / Subsidiaries | C51: 0 | D51: 0 | E51: — | F51: — | G51: — | H51: —
B52: Directors & Relatives (excl. Indep. / Nominee) | C52: 1 | D52: 180 | E52: 0.00% | F52: 0.00% | G52: 0.00% | H52: 180
B53: Key Managerial Personnel | C53: 0 | D53: 0 | E53: — | F53: — | G53: — | H53: —
B54: Relatives of Promoters (non-immediate) | C54: 0 | D54: 0 | E54: — | F54: — | G54: — | H54: —
B55: Trusts (Promoter group as trustee/beneficiary) | C55: 0 | D55: 0 | E55: — | F55: — | G55: — | H55: —
B56: Investor Education & Protection Fund (IEPF) | C56: 1 | D56: 2,23,561 | E56: 0.00% | F56: 0.00% | G56: 0.00% | H56: 2,23,561
B57: Resident Individuals — upto ₹2L share capital | C57: 1112355 | D57: 75,48,95,145 | E57: 8.59% | F57: 8.59% | G57: 8.59% | H57: 75,48,37,682
B58: Resident Individuals — above ₹2L share capital | C58: 160 | D58: 13,24,54,755 | E58: 1.51% | F58: 1.51% | G58: 1.51% | H58: 13,24,54,755
B59: Non-Resident Indians (NRIs) | C59: 14956 | D59: 3,96,00,637 | E59: 0.45% | F59: 0.45% | G59: 0.45% | H59: 3,96,00,637
B60: Foreign Nationals | C60: 3 | D60: 3,802 | E60: 0.00% | F60: 0.00% | G60: 0.00% | H60: 3,802
B61: Foreign Companies | C61: 0 | D61: 0 | E61: — | F61: — | G61: — | H61: —
B62: Bodies Corporate | C62: 2536 | D62: 10,93,14,096 | E62: 1.24% | F62: 1.24% | G62: 1.24% | H62: 10,93,12,096
B63: Any Other — FPI Category III | C63: 1 | D63: 66,000 | E63: 0.00% | F63: 0.00% | G63: 0.00% | H63: 66,000
B64: Any Other — Employees | C64: 114 | D64: 2,08,479 | E64: 0.00% | F64: 0.00% | G64: 0.00% | H64: 2,00,989
B65: Any Other — Trusts | C65: 60 | D65: 42,20,003 | E65: 0.05% | F65: 0.05% | G65: 0.05% | H65: 42,20,003
B66: Any Other — Clearing Members | C66: 10 | D66: 1,70,712 | E66: 0.00% | F66: 0.00% | G66: 0.00% | H66: 1,70,712
B67: Any Other — Unclaimed / Suspense / Escrow | C67: 0 | D67: 0 | E67: — | F67: — | G67: — | H67: —
B68: Any Other — Unclaimed Suspense Account | C68: 1 | D68: 1,57,376 | E68: 0.00% | F68: 0.00% | G68: 0.00% | H68: 1,57,376
B69: Sub-Total B4 — Retail & Others | C69: 11,30,198 | D69: 1,04,13,14,746 | E69: 11.84% | F69: 11.84% | G69: 11.84% | H69: 1,04,12,47,793
B71: TOTAL PUBLIC (B = B1+B2+B3+B4) | C71: 11,30,913 | D71: 3,44,69,16,837 | E71: 39.21% | F71: 39.21% | G71: 39.21% | H71: 3,44,68,49,884
B73: ★ = Top holder shown within category for reference | '—' = Nil / Not Applicable | Source: NMDC BSE/NSE Filing, Q4 FY2024-25 | Share counts in absolute numbers

Sheet Standalone Quarterly Results
D2: Standalone Quarterly Results (Rs. Crores) | K2: % CHANGE
E3: Quarter ended | G3: Half Year ended | I3: Years | K3: QTQ | L3: HY YOY | M3: YOY
D4: Particulars | E4: 45992 | F4: 45901 | G4: 45992 | H4: 45627 | I4: 45717 | J4: 45352
D5: I. REVENUE
D6: Net Sales/Income from Operations | E6: 7485 | F6: 6260 | G6: 13745 | H6: 11336 | I6: 23668.32 | J6: 21293.81 | K6: =(E6-F6)/F6 -> 0.1956869 | L6: =(G6-H6)/H6 -> 0.21250882 | M6: =(I6-J6)/J6 -> 0.11151175
D7: Other Operating Income
D8: Total Income From Operations | E8: 7485 | F8: 6260 | G8: 13745 | H8: 11336 | I8: 23668.32 | J8: 21293.81 | K8: =(E8-F8)/F8 -> 0.1956869 | L8: =(G8-H8)/H8 -> 0.21250882 | M8: =(I8-J8)/J8 -> 0.11151175
D9: II. EXPENSES
D10: Consumption of Raw Materials | E10: 0 | F10: 1 | G10: 1 | H10: 278 | I10: 12.42 | J10: 20.97 | K10: =IF(F10<>0,(E10-F10)/ABS(F10),"") -> -1 | L10: =IF(H10<>0,(G10-H10)/ABS(H10),"") -> -0.99640288 | M10: =(I10-J10)/J10 -> -0.40772532
D11: Purchase of Traded Goods | E11: 582 | F11: 430 | G11: 1012 | H11: 113 | I11: 197.09 | K11: =IF(F11<>0,(E11-F11)/ABS(F11),"") -> 0.35348837 | L11: =IF(H11<>0,(G11-H11)/ABS(H11),"") -> 7.9557522
D12: Increase / Decrease in Stocks | E12: -53 | F12: 100 | G12: 47 | H12: 140 | I12: 81.97 | J12: -66.08 | K12: =IF(F12<>0,(E12-F12)/ABS(F12),"") -> -1.53 | L12: =IF(H12<>0,(G12-H12)/ABS(H12),"") -> -0.66428571 | M12: =(I12-J12)/J12 -> -2.2404661
D13: Power & Fuel
D14: Employee Benefits Expense | E14: 442 | F14: 401 | G14: 843 | H14: 847 | I14: 1781.44 | J14: 1619.44 | K14: =(E10-F10)/F10 -> -1 | L14: =(G10-H10)/H10 -> -0.99640288 | M14: =(I14-J14)/J14 -> 0.10003458
D15: Depreciation & Amortisation | E15: 103 | F15: 106 | G15: 209 | H15: 176 | I15: 372.78 | J15: 337.05 | K15: =IF(F15<>0,(E15-F15)/ABS(F15),"") -> -0.028301887 | L15: =IF(H15<>0,(G15-H15)/ABS(H15),"") -> 0.1875 | M15: =(I15-J15)/J15 -> 0.10600801
D16: Excise Duty
D17: Admin. And Selling Expenses | E17: 0 | F17: 0 | G17: 0 | H17: 0 | J17: 329.52 | K17: =IF(F17<>0,(E17-F17)/ABS(F17),"") | L17: =IF(H17<>0,(G17-H17)/ABS(H17),"") | M17: =(I17-J17)/J17 -> -1
D18: R & D Expenses
D19: Provisions And Contingencies
D20: Exp. Capitalised
D21: Other Expenses | E21: 4365 | F21: 3322 | G21: 7687 | H21: 6106 | I21: 13337.54 | J21: 12034.76 | K21: =IF(F21<>0,(E21-F21)/ABS(F21),"") -> 0.31396749 | L21: =IF(H21<>0,(G21-H21)/ABS(H21),"") -> 0.25892565 | M21: =(I21-J21)/J21 -> 0.10825143
D22: Finance Costs | E22: 34 | F22: 7 | G22: 41 | H22: 89 | I22: 177.65 | J22: 78.24 | K22: =IF(F22<>0,(E22-F22)/ABS(F22),"") -> 3.8571429 | L22: =IF(H22<>0,(G22-H22)/ABS(H22),"") -> -0.53932584 | M22: =(I22-J22)/J22 -> 1.2705777
D23: Total Expenses | E23: 4944 | F23: 3836 | G23: 8780 | H23: 7218 | I23: 15960.89 | J23: 14353.88 | K23: =IF(F23<>0,(E23-F23)/ABS(F23),"") -> 0.28884254 | L23: =IF(H23<>0,(G23-H23)/ABS(H23),"") -> 0.21640344 | M23: =(I23-J23)/J23 -> 0.11195649
D24: III. PROFIT & LOSS
D25: EBITDA | E25: 2503 | F25: 2384 | G25: 4887 | H25: 4583 | I25: 8257.86 | J25: 7355.2 | K25: =IF(AND(F25<>0,ISNUMBER(F25)),(E25-F25)/ABS(F25),"") -> 0.049916107 | L25: =IF(AND(H25<>0,ISNUMBER(H25)),(G25-H25)/ABS(H25),"") -> 0.066332097 | M25: =(I25-J25)/J25 -> 0.12272406
D26: P/L Before Other Inc., Int., Excpt. Items & Tax | E26: 2044 | F26: 1897 | G26: 3941 | H26: 3672 | I26: 7885.08 | J26: 7018.15 | K26: =IF(F26<>0,(E26-F26)/ABS(F26),"") -> 0.077490775 | L26: =IF(H26<>0,(G26-H26)/ABS(H26),"") -> 0.073257081 | M26: =(I26-J26)/J26 -> 0.12352686
D27: Other Income | E27: 356 | F27: 381 | G27: 737 | H27: 734 | I27: 1590.24 | J27: 1355.54 | K27: =IF(F27<>0,(E27-F27)/ABS(F27),"") -> -0.065616798 | L27: =IF(H27<>0,(G27-H27)/ABS(H27),"") -> 0.0040871935 | M27: =(I27-J27)/J27 -> 0.17314133
D28: P/L Before Int., Excpt. Items & Tax (EBIT) | E28: 2400 | F28: 2278 | G28: 4678 | H28: 4407 | I28: 9475.32 | J28: 8373.69 | K28: =IF(F28<>0,(E28-F28)/ABS(F28),"") -> 0.053555751 | L28: =IF(H28<>0,(G28-H28)/ABS(H28),"") -> 0.061493079 | M28: =(I28-J28)/J28 -> 0.13155849
D29: Finance Costs (Interest) | E29: 34 | F29: 7 | G29: 41 | H29: 89 | I29: 177.65 | J29: 78.24 | K29: =IF(F29<>0,(E29-F29)/ABS(F29),"") -> 3.8571429 | L29: =IF(H29<>0,(G29-H29)/ABS(H29),"") -> -0.53932584 | M29: =(I29-J29)/J29 -> 1.2705777
D30: Profit before Exceptional Items & Tax | E30: 2365 | F30: 2270 | G30: 4635 | H30: 4317 | I30: 9297.67 | J30: 8295.45 | K30: =IF(F30<>0,(E30-F30)/ABS(F30),"") -> 0.04185022 | L30: =IF(H30<>0,(G30-H30)/ABS(H30),"") -> 0.073662265 | M30: =(I30-J30)/J30 -> 0.12081563
D31: Exceptional Items | E31: 0 | F31: 0 | G31: 0 | H31: 0 | J31: -282.15 | K31: =IF(F31<>0,(E31-F31)/ABS(F31),"") | L31: =IF(H31<>0,(G31-H31)/ABS(H31),"") | M31: =(I31-J31)/J31 -> -1
D32: Profit Before Tax | E32: 2365 | F32: 2270 | G32: 4635 | H32: 4317 | I32: 9297.67 | J32: 8013.3 | K32: =IF(F32<>0,(E32-F32)/ABS(F32),"") -> 0.04185022 | L32: =IF(H32<>0,(G32-H32)/ABS(H32),"") -> 0.073662265 | M32: =(I32-J32)/J32 -> 0.16027978
D33: Tax Expense | E33: 627 | F33: 576 | G33: 1203 | H33: 1104 | I33: 2604.14 | J33: 2380.42 | K33: =IF(F33<>0,(E33-F33)/ABS(F33),"") -> 0.088541667 | L33: =IF(H33<>0,(G33-H33)/ABS(H33),"") -> 0.089673913 | M33: =(I33-J33)/J33 -> 0.093983415
D34: P/L After Tax from Ordinary Activities | E34: 1738 | F34: 1694 | G34: 3432 | H34: 3212 | I34: 6693.53 | J34: 5632.88 | K34: =IF(F34<>0,(E34-F34)/ABS(F34),"") -> 0.025974026 | L34: =IF(H34<>0,(G34-H34)/ABS(H34),"") -> 0.068493151 | M34: =(I34-J34)/J34 -> 0.18829622
D35: Prior Year Adjustments
D36: Extra Ordinary Items | E36: 0 | F36: 0 | G36: 0 | H36: 0 | I36: -0.93 | J36: -0.99 | M36: =(I36-J36)/J36 -> -0.060606061
D37: Net Profit/(Loss) For the Period | E37: 1738 | F37: 1694 | G37: 3432 | H37: 3212 | I37: 6692.6 | J37: 5631.89 | K37: =IF(F37<>0,(E37-F37)/ABS(F37),"") -> 0.025974026 | L37: =IF(H37<>0,(G37-H37)/ABS(H37),"") -> 0.068493151 | M37: =(I37-J37)/J37 -> 0.18833997
D38: IV. EARNINGS PER SHARE (Rs.)
D39: EPS Before Extra Ordinary - Basic | E39: 1.98 | F39: 1.93 | G39: 3.9 | H39: 3.65 | I39: 7.61 | J39: 19.22 | K39: =IF(AND(F39<>0,ISNUMBER(F39)),(E39-F39)/ABS(F39),"") -> 0.025906736 | L39: =IF(AND(H39<>0,ISNUMBER(H39)),(G39-H39)/ABS(H39),"") -> 0.068493151 | M39: =(I39-J39)/J39 -> -0.60405827
D40: EPS Before Extra Ordinary - Diluted | E40: 1.98 | F40: 1.93 | G40: 3.9 | H40: 3.65 | I40: 7.61 | J40: 19.22 | K40: =IF(F40<>0,(E40-F40)/ABS(F40),"") -> 0.025906736 | L40: =IF(H40<>0,(G40-H40)/ABS(H40),"") -> 0.068493151 | M40: =(I40-J40)/J40 -> -0.60405827
D41: EPS After Extra Ordinary - Basic | E41: 1.98 | F41: 1.93 | G41: 3.9 | H41: 3.65 | I41: 7.61 | J41: 19.22 | K41: =IF(F41<>0,(E41-F41)/ABS(F41),"") -> 0.025906736 | L41: =IF(H41<>0,(G41-H41)/ABS(H41),"") -> 0.068493151 | M41: =(I41-J41)/J41 -> -0.60405827
D42: EPS After Extra Ordinary - Diluted | E42: 1.98 | F42: 1.93 | G42: 3.9 | H42: 3.65 | I42: 7.61 | J42: 19.22 | K42: =IF(F42<>0,(E42-F42)/ABS(F42),"") -> 0.025906736 | L42: =IF(H42<>0,(G42-H42)/ABS(H42),"") -> 0.068493151 | M42: =(I42-J42)/J42 -> -0.60405827
D43: V. SUPPLEMENTARY | K43: =IF(F41<>0,(E41-F41)/ABS(F41),"") -> 0.025906736 | L43: =IF(H41<>0,(G41-H41)/ABS(H41),"") -> 0.068493151
D44: Paid-up Equity Share Capital (Rs. Cr) | E44: 879 | F44: 879 | G44: 879 | H44: 879 | I44: 879.18 | J44: 293.07 | K44: =(E27-F27)/F27 -> -0.065616798 | L44: =(G27-H27)/H27 -> 0.0040871935 | M44: =(I44-J44)/J44 -> 1.9998976
D45: Reserves excl. Revaluation (Rs. Cr) | I45: 28700 | J45: 25112.71 | M45: =(I45-J45)/J45 -> 0.14284759
D46: Equity Dividend Rate (%) | I46: 330 | J46: 725 | M46: =(I46-J46)/J46 -> -0.54482759

Sheet Consolidated Quarterly Results
D2: Consolidated Quarterly Results (Rs. Crores) | K2: % CHANGE
E3: Quarter ended | H3: Years | K3: QTQ | L3: QOQ YOY | M3: YOY
D4: Particulars | E4: 45992 | F4: 45901 | G4: 45627 | H4: 45717 | I4: 45352
D5: I. REVENUE
D6: Net Sales/Income from Operations | E6: 7610 | F6: 6378 | G6: 6567 | H6: 23905.52 | I6: 21307.85 | K6: =(E6-F6)/F6 -> 0.193164 | L6: =IF(G6<>0,(E6-G6)/ABS(G6),"") -> 0.15882443 | M6: =(H6-I6)/I6 -> 0.12191141
D7: Other Operating Income
D8: Total Income From Operations | E8: 7610 | F8: 6378 | G8: 6567 | H8: 23905.52 | I8: 21307.85 | K8: =(E8-F8)/F8 -> 0.193164 | L8: =IF(G8<>0,(E8-G8)/ABS(G8),"") -> 0.15882443 | M8: =(H8-I8)/I8 -> 0.12191141
D9: II. EXPENSES
D10: Consumption of Raw Materials | E10: 0 | F10: 1 | G10: 192 | H10: 12.42 | I10: 20.97 | K10: =(E10-F10)/F10 -> -1 | L10: =IF(G10<>0,(E10-G10)/ABS(G10),"") -> -1 | M10: =(H10-I10)/I10 -> -0.40772532
D11: Purchase of Traded Goods | E11: 582 | F11: 430 | G11: 113 | H11: 197.09 | K11: =(E11-F11)/F11 -> 0.35348837 | L11: =IF(G11<>0,(E11-G11)/ABS(G11),"") -> 4.1504425
D12: Increase / Decrease in Stocks | E12: -52 | F12: 107 | G12: -340 | H12: 99.31 | I12: -93.36 | K12: =(E12-F12)/F12 -> -1.4859813 | L12: =IF(G12<>0,(E12-G12)/ABS(G12),"") -> 0.84705882 | M12: =(H12-I12)/I12 -> -2.0637318
D13: Power & Fuel
D14: Employee Benefits Expense | E14: 445 | F14: 402 | G14: 439 | H14: 1795.04 | I14: 1625.54 | K14: =(E14-F14)/F14 -> 0.10696517 | L14: =IF(G10<>0,(E10-G10)/ABS(G10),"") -> -1 | M14: =(H14-I14)/I14 -> 0.10427304
D15: Depreciation & Amortisation | E15: 106 | F15: 110 | G15: 102 | H15: 420.42 | I15: 350.66 | K15: =(E15-F15)/F15 -> -0.036363636 | L15: =IF(G15<>0,(E15-G15)/ABS(G15),"") -> 0.039215686 | M15: =(H15-I15)/I15 -> 0.19893914
D16: Excise Duty
D17: Admin. And Selling Expenses | E17: 0 | F17: 0 | G17: 0 | H17: 538.94 | I17: 338.47 | L17: =IF(G17<>0,(E17-G17)/ABS(G17),"") | M17: =(H17-I17)/I17 -> 0.59228292
D18: R & D Expenses
D19: Provisions And Contingencies
D20: Exp. Capitalised
D21: Other Expenses | E21: 4492 | F21: 3442 | G21: 3790 | H21: 13114.05 | I21: 12123.4 | K21: =(E21-F21)/F21 -> 0.3050552 | L21: =IF(G21<>0,(E21-G21)/ABS(G21),"") -> 0.18522427 | M21: =(H21-I21)/I21 -> 0.081713876
D22: Finance Costs | E22: 34 | F22: 7 | G22: 60 | H22: 177.68 | I22: 78.24 | K22: =(E22-F22)/F22 -> 3.8571429 | L22: =IF(G22<>0,(E22-G22)/ABS(G22),"") -> -0.43333333 | M22: =(H22-I22)/I22 -> 1.2709611
D23: Total Expenses | E23: 5077 | F23: 3961 | G23: 4391 | H23: 16354.95 | I23: 14443.92 | K23: =(E23-F23)/F23 -> 0.28174703 | L23: =IF(G23<>0,(E23-G23)/ABS(G23),"") -> 0.15622865 | M23: =(H23-I23)/I23 -> 0.13230688
D24: III. PROFIT & LOSS
D25: EBITDA | E25: 2514 | F25: 2375 | G25: 2745 | H25: 8148.67 | I25: 7292.83 | K25: =(E25-F25)/F25 -> 0.058526316 | L25: =IF(G16<>0,(E16-G16)/ABS(G16),"") | M25: =(H25-I25)/I25 -> 0.11735362
D26: P/L Before Other Inc., Int., Excpt. Items & Tax | E26: 2037 | F26: 1883 | G26: 2269 | H26: 7728.25 | I26: 6942.17 | K26: =(E26-F26)/F26 -> 0.081784387 | L26: =IF(G26<>0,(E26-G26)/ABS(G26),"") -> -0.10224769 | M26: =(H26-I26)/I26 -> 0.11323261
D27: Other Income | E27: 372 | F27: 383 | G27: 375 | H27: 1593.32 | I27: 1370.88 | K27: =(E27-F27)/F27 -> -0.028720627 | L27: =IF(G27<>0,(E27-G27)/ABS(G27),"") -> -0.008 | M27: =(H27-I27)/I27 -> 0.16226074
D28: P/L Before Int., Excpt. Items & Tax (EBIT) | E28: 2408 | F28: 2265 | G28: 2643 | H28: 9321.57 | I28: 8313.05 | K28: =(E28-F28)/F28 -> 0.063134658 | L28: =IF(G28<>0,(E28-G28)/ABS(G28),"") -> -0.088914113 | M28: =(H28-I28)/I28 -> 0.12131769
D29: Finance Costs (Interest) | E29: 34 | F29: 7 | G29: 60 | H29: 177.68 | I29: 78.24 | K29: =(E29-F29)/F29 -> 3.8571429 | L29: =IF(G29<>0,(E29-G29)/ABS(G29),"") -> -0.43333333 | M29: =(H29-I29)/I29 -> 1.2709611
D30: Profit before Exceptional Items & Tax | E30: 2374 | F30: 2258 | G30: 2583 | H30: 9143.89 | I30: 8234.81 | K30: =(E30-F30)/F30 -> 0.051372896 | L30: =IF(G30<>0,(E30-G30)/ABS(G30),"") -> -0.080913666 | M30: =(H30-I30)/I30 -> 0.11039478
D31: Exceptional Items | E31: 0 | F31: 0 | G31: 0 | I31: -282.15 | L31: =IF(G31<>0,(E31-G31)/ABS(G31),"") | M31: =(H31-I31)/I31 -> -1
D32: Profit Before Tax | E32: 2374 | F32: 2258 | G32: 2583 | H32: 9143.89 | I32: 7952.66 | K32: =(E32-F32)/F32 -> 0.051372896 | L32: =IF(G32<>0,(E32-G32)/ABS(G32),"") -> -0.080913666 | M32: =(H32-I32)/I32 -> 0.14979013
D33: Tax Expense | E33: 627 | F33: 576 | G33: 686 | H33: 2604.14 | I33: 2380.42 | K33: =(E33-F33)/F33 -> 0.088541667 | L33: =IF(G33<>0,(E33-G33)/ABS(G33),"") -> -0.086005831 | M33: =(H33-I33)/I33 -> 0.093983415
D34: P/L After Tax from Ordinary Activities | E34: 1747 | F34: 1682 | G34: 1896 | H34: 6539.75 | I34: 5572.24 | K34: =(E34-F34)/F34 -> 0.038644471 | L34: =IF(G34<>0,(E34-G34)/ABS(G34),"") -> -0.078586498 | M34: =(H34-I34)/I34 -> 0.17363035
D35: Share Of P/L Of Associates | E35: 10 | F35: 15 | G35: 1 | H35: 10.95 | I35: -0.38 | K35: =(E35-F35)/F35 -> -0.33333333 | L35: =IF(G35<>0,(E35-G35)/ABS(G35),"") -> 9 | M35: =(H35-I35)/I35 -> -29.815789
D36: Minority Interest | E36: 0 | F36: 0 | G36: -16 | H36: -7.79 | I36: 4.19 | L36: =IF(G36<>0,(E36-G36)/ABS(G36),"") -> 1 | M36: =(H36-I36)/I36 -> -2.8591885
D37: Net P/L After Minority Interest & Associates | E37: 1756 | F37: 1698 | G37: 1881 | H37: 6541.98 | I37: 5575.06 | K37: =(E37-F37)/F37 -> 0.034157833 | L37: =IF(G37<>0,(E37-G37)/ABS(G37),"") -> -0.066454014 | M37: =(H37-I37)/I37 -> 0.1734367
D38: Total Comprehensive Income | E38: 1756 | F38: 1698 | G38: 1881 | H38: 6541.98 | I38: 5575.06 | K38: =(E38-F38)/F38 -> 0.034157833 | L38: =IF(G25<>0,(E25-G25)/ABS(G25),"") -> -0.084153005 | M38: =(H38-I38)/I38 -> 0.1734367
D39: Prior Year Adjustments
D40: Extra Ordinary Items | E40: 0 | F40: 0 | G40: 0 | H40: -0.93 | I40: -0.99 | M40: =(H40-I40)/I40 -> -0.060606061
D41: Net Profit/(Loss) For the Period | E41: 1756 | F41: 1698 | G41: 1881 | H41: 6538.82 | I41: 5571.25 | K41: =(E41-F41)/F41 -> 0.034157833 | L41: =IF(G41<>0,(E41-G41)/ABS(G41),"") -> -0.066454014 | M41: =(H41-I41)/I41 -> 0.17367198
D42: IV. EARNINGS PER SHARE (Rs.)
D43: EPS Before Extra Ordinary - Basic | E43: 2 | F43: 1.93 | G43: 2.14 | H43: 7.44 | I43: 19.02 | K43: =(E43-F43)/F43 -> 0.03626943 | L43: =IF(G43<>0,(E43-G43)/ABS(G43),"") -> -0.065420561 | M43: =(H43-I43)/I43 -> -0.60883281
D44: EPS Before Extra Ordinary - Diluted | E44: 2 | F44: 1.93 | G44: 2.14 | H44: 7.44 | I44: 19.02 | K44: =(E44-F44)/F44 -> 0.03626943 | L44: =IF(G44<>0,(E44-G44)/ABS(G44),"") -> -0.065420561 | M44: =(H44-I44)/I44 -> -0.60883281
D45: EPS After Extra Ordinary - Basic | E45: 2 | F45: 1.93 | G45: 2.14 | H45: 7.44 | I45: 19.02 | K45: =(E45-F45)/F45 -> 0.03626943 | L45: =IF(G45<>0,(E45-G45)/ABS(G45),"") -> -0.065420561 | M45: =(H45-I45)/I45 -> -0.60883281
D46: EPS After Extra Ordinary - Diluted | E46: 2 | F46: 1.93 | G46: 2.14 | H46: 7.44 | I46: 19.02 | K46: =(E46-F46)/F46 -> 0.03626943 | L46: =IF(G46<>0,(E46-G46)/ABS(G46),"") -> -0.065420561 | M46: =(H46-I46)/I46 -> -0.60883281
D47: V. SUPPLEMENTARY
D48: Paid-up Equity Share Capital (Rs. Cr) | E48: 879 | F48: 879 | G48: 879 | H48: 879.18 | I48: 293.07 | K48: =(E48-F48)/F48 -> 0 | L48: =IF(G30<>0,(E30-G30)/ABS(G30),"") -> -0.080913666 | M48: =(H48-I48)/I48 -> 1.9998976
D49: Reserves excl. Revaluation (Rs. Cr) | H49: 28816.59 | I49: 25362.83

Sheet Standalone balance sheet
A1: NMDC - Standalone Balance Sheet (Rs. Cr.)
A2: Particulars (Rs. Cr.) | B2: Mar 25 | C2: Mar 24 | D2: Mar 23 | E2: Mar 22 | F2: Mar 21 | G2: % Chg Mar 25/Mar 24 | H2: % Chg Mar 24/Mar 23 | I2: % Chg Mar 23/Mar 22 | J2: % Chg Mar 22/Mar 21
A3: 12 Months Ended | B3: 12 mths | C3: 12 mths | D3: 12 mths | E3: 12 mths | F3: 12 mths
A4: EQUITIES AND LIABILITIES
A5: SHAREHOLDER'S FUNDS
A6: Equity Share Capital | B6: 879.18 | C6: 293.07 | D6: 293.07 | E6: 293.07 | F6: 293.07 | G6: =(B6-C6)/C6 -> 1.9998976 | H6: =(C6-D6)/D6 -> 0 | I6: =(D6-E6)/E6 -> 0 | J6: =(E6-F6)/F6 -> 0
A7: Total Share Capital | B7: 879.18 | C7: 293.07 | D7: 293.07 | E7: 293.07 | F7: 293.07 | G7: =(B7-C7)/C7 -> 1.9998976 | H7: =(C7-D7)/D7 -> 0 | I7: =(D7-E7)/E7 -> 0 | J7: =(E7-F7)/F7 -> 0
A8: Reserves and Surplus | B8: 28700 | C8: 25112.71 | D8: 22039.24 | E8: 34550.9 | F8: 29463.07 | G8: =(B8-C8)/C8 -> 0.14284759 | H8: =(C8-D8)/D8 -> 0.13945445 | I8: =(D8-E8)/E8 -> -0.36212255 | J8: =(E8-F8)/F8 -> 0.17268499
A9: Total Reserves and Surplus | B9: 28700 | C9: 25112.71 | D9: 22039.24 | E9: 34550.9 | F9: 29463.07 | G9: =(B9-C9)/C9 -> 0.14284759 | H9: =(C9-D9)/D9 -> 0.13945445 | I9: =(D9-E9)/E9 -> -0.36212255 | J9: =(E9-F9)/F9 -> 0.17268499
A10: Total Shareholders Funds | B10: 29579.18 | C10: 25405.78 | D10: 22332.31 | E10: 34843.97 | F10: 29756.14 | G10: =(B10-C10)/C10 -> 0.16426971 | H10: =(C10-D10)/D10 -> 0.13762437 | I10: =(D10-E10)/E10 -> -0.35907676 | J10: =(E10-F10)/F10 -> 0.17098421
A11: NON-CURRENT LIABILITIES
A12: Long Term Borrowings | B12: 0 | C12: 0 | D12: 0 | E12: 1668.22 | F12: 546.43 | H12: =IF(D12<>0,C12/D12-1,"") | I12: =(D12-E12)/E12 -> -1 | J12: =(E12-F12)/F12 -> 2.0529437
A13: Other Long Term Liabilities | B13: 152.25 | C13: 151.95 | D13: 155.02 | E13: 156.13 | F13: 4.57 | G13: =(B13-C13)/C13 -> 0.0019743337 | H13: =(C13-D13)/D13 -> -0.019803896 | I13: =(D13-E13)/E13 -> -0.0071094601 | J13: =(E13-F13)/F13 -> 33.164114
A14: Long Term Provisions | B14: 1453.81 | C14: 1430.75 | D14: 1255.56 | E14: 1092 | F14: 945.16 | G14: =(B14-C14)/C14 -> 0.016117421 | H14: =(C14-D14)/D14 -> 0.13953136 | I14: =(D14-E14)/E14 -> 0.14978022 | J14: =(E14-F14)/F14 -> 0.15535994
A15: Total Non-Current Liabilities | B15: 1606.06 | C15: 1582.7 | D15: 1410.58 | E15: 2916.35 | F15: 1496.16 | G15: =(B15-C15)/C15 -> 0.014759588 | H15: =(C15-D15)/D15 -> 0.12202073 | I15: =(D15-E15)/E15 -> -0.51632006 | J15: =(E15-F15)/F15 -> 0.94922335
A16: CURRENT LIABILITIES
A17: Short Term Borrowings | B17: 3770.45 | C17: 3356.54 | D17: 415.98 | E17: 1815.13 | F17: 1448.04 | G17: =(B17-C17)/C17 -> 0.12331448 | H17: =(C17-D17)/D17 -> 7.0689937 | I17: =(D17-E17)/E17 -> -0.77082633 | J17: =(E17-F17)/F17 -> 0.25350819
A18: Trade Payables | B18: 298.49 | C18: 372.52 | D18: 425.76 | E18: 967.22 | F18: 360.26 | G18: =(B18-C18)/C18 -> -0.19872759 | H18: =(C18-D18)/D18 -> -0.12504697 | I18: =(D18-E18)/E18 -> -0.55981059 | J18: =(E18-F18)/F18 -> 1.6847832
A19: Other Current Liabilities | B19: 5190.94 | C19: 4377.14 | D19: 3233.84 | E19: 4134.88 | F19: 3626.3 | G19: =(B19-C19)/C19 -> 0.18592049 | H19: =(C19-D19)/D19 -> 0.35354254 | I19: =(D19-E19)/E19 -> -0.21791201 | J19: =(E19-F19)/F19 -> 0.14024764
A20: Short Term Provisions | B20: 382.61 | C20: 254.41 | D20: 123.23 | E20: 14.39 | F20: 98 | G20: =(B20-C20)/C20 -> 0.50391101 | H20: =(C20-D20)/D20 -> 1.0645135 | I20: =(D20-E20)/E20 -> 7.5635858 | J20: =(E20-F20)/F20 -> -0.85316327
A21: Total Current Liabilities | B21: 9642.49 | C21: 8360.61 | D21: 4198.81 | E21: 6931.62 | F21: 5532.6 | G21: =(B21-C21)/C21 -> 0.15332374 | H21: =(C21-D21)/D21 -> 0.9911856 | I21: =(D21-E21)/E21 -> -0.39425271 | J21: =(E21-F21)/F21 -> 0.25286845
A22: Total Capital And Liabilities | B22: 40827.73 | C22: 35349.09 | D22: 27941.7 | E22: 44691.94 | F22: 36784.9 | G22: =(B22-C22)/C22 -> 0.15498673 | H22: =(C22-D22)/D22 -> 0.26510162 | I22: =(D22-E22)/E22 -> -0.37479331 | J22: =(E22-F22)/F22 -> 0.21495342
A23: ASSETS
A24: NON-CURRENT ASSETS
A25: Tangible Assets | B25: 4156.54 | C25: 2499.06 | D25: 2385.54 | E25: 3522.13 | F25: 2677.28 | G25: =(B25-C25)/C25 -> 0.66324138 | H25: =(C25-D25)/D25 -> 0.04758671 | I25: =(D25-E25)/E25 -> -0.32269962 | J25: =(E25-F25)/F25 -> 0.31556281
A26: Intangible Assets | B26: 645.61 | C26: 663.59 | D26: 628.33 | E26: 443.9 | F26: 441.17 | G26: =(B26-C26)/C26 -> -0.027095044 | H26: =(C26-D26)/D26 -> 0.056117009 | I26: =(D26-E26)/E26 -> 0.41547646 | J26: =(E26-F26)/F26 -> 0.0061880908
A27: Capital Work-In-Progress | B27: 4737.48 | C27: 3230.51 | D27: 1961.72 | E27: 18294.69 | F27: 17076.68 | G27: =(B27-C27)/C27 -> 0.46648052 | H27: =(C27-D27)/D27 -> 0.64677426 | I27: =(D27-E27)/E27 -> -0.89277107 | J27: =(E27-F27)/F27 -> 0.071325925
A28: Intangible Assets Under Development | B28: 0 | C28: 4.14 | D28: 6.49 | E28: 5 | F28: 51.42 | G28: =(B28-C28)/C28 -> -1 | H28: =(C28-D28)/D28 -> -0.36209553 | I28: =(D28-E28)/E28 -> 0.298 | J28: =(E28-F28)/F28 -> -0.90276157
A29: Fixed Assets | B29: 9539.63 | C29: 6397.3 | D29: 4982.08 | E29: 22265.72 | F29: 20246.55 | G29: =(B29-C29)/C29 -> 0.49119629 | H29: =(C29-D29)/D29 -> 0.28406208 | I29: =(D29-E29)/E29 -> -0.77624438 | J29: =(E29-F29)/F29 -> 0.09972909
A30: Non-Current Investments | B30: 1115.34 | C30: 991.65 | D30: 886.72 | E30: 987.43 | F30: 984.88 | G30: =(B30-C30)/C30 -> 0.12473151 | H30: =(C30-D30)/D30 -> 0.11833499 | I30: =(D30-E30)/E30 -> -0.10199204 | J30: =(E30-F30)/F30 -> 0.0025891479
A31: Deferred Tax Assets [Net] | B31: 296.25 | C31: 265.89 | D31: 297.5 | E31: 530.95 | F31: 408.28 | G31: =(B31-C31)/C31 -> 0.11418256 | H31: =(C31-D31)/D31 -> -0.1062521 | I31: =(D31-E31)/E31 -> -0.43968359 | J31: =(E31-F31)/F31 -> 0.30045557
A32: Long Term Loans And Advances | B32: 769.64 | C32: 724.43 | D32: 705.06 | E32: 682.99 | F32: 901.16 | G32: =(B32-C32)/C32 -> 0.062407686 | H32: =(C32-D32)/D32 -> 0.027472839 | I32: =(D32-E32)/E32 -> 0.032313797 | J32: =(E32-F32)/F32 -> -0.24209907
A33: Other Non-Current Assets | B33: 5816.66 | C33: 5562.82 | D33: 5309.48 | E33: 4449.79 | F33: 3695.91 | G33: =(B33-C33)/C33 -> 0.045631532 | H33: =(C33-D33)/D33 -> 0.047714654 | I33: =(D33-E33)/E33 -> 0.19319788 | J33: =(E33-F33)/F33 -> 0.20397683
A34: Total Non-Current Assets | B34: 17537.52 | C34: 13942.09 | D34: 12180.84 | E34: 28916.88 | F34: 26236.78 | G34: =(B34-C34)/C34 -> 0.25788314 | H34: =(C34-D34)/D34 -> 0.14459183 | I34: =(D34-E34)/E34 -> -0.57876368 | J34: =(E34-F34)/F34 -> 0.10215049
A35: CURRENT ASSETS
A36: Inventories | B36: 2626.89 | C36: 2738.92 | D36: 2660.58 | E36: 2164.9 | F36: 921.72 | G36: =(B36-C36)/C36 -> -0.040902984 | H36: =(C36-D36)/D36 -> 0.029444708 | I36: =(D36-E36)/E36 -> 0.22896208 | J36: =(E36-F36)/F36 -> 1.348761
A37: Trade Receivables | B37: 7734.19 | C37: 3499.21 | D37: 2656.02 | E37: 2954.3 | F37: 2139.89 | G37: =(B37-C37)/C37 -> 1.2102675 | H37: =(C37-D37)/D37 -> 0.31746372 | I37: =(D37-E37)/E37 -> -0.1009647 | J37: =(E37-F37)/F37 -> 0.38058498
A38: Cash And Cash Equivalents | B38: 10030.75 | C38: 12272.95 | D38: 7048.04 | E38: 7940.17 | F38: 5806.01 | G38: =(B38-C38)/C38 -> -0.18269446 | H38: =(C38-D38)/D38 -> 0.74132809 | I38: =(D38-E38)/E38 -> -0.11235654 | J38: =(E38-F38)/F38 -> 0.36757773
A39: Short Term Loans And Advances | B39: 51.68 | C39: 0 | D39: 0 | E39: 0 | F39: 0
A40: OtherCurrentAssets | B40: 2846.7 | C40: 2895.92 | D40: 3396.22 | E40: 2715.69 | F40: 1680.5 | G40: =(B40-C40)/C40 -> -0.016996326 | H40: =(C40-D40)/D40 -> -0.14731083 | I40: =(D40-E40)/E40 -> 0.25059193 | J40: =(E40-F40)/F40 -> 0.61600119
A41: Total Current Assets | B41: 23290.21 | C41: 21407 | D41: 15760.86 | E41: 15775.06 | F41: 10548.12 | G41: =(B41-C41)/C41 -> 0.087971692 | H41: =(C41-D41)/D41 -> 0.35823807 | I41: =(D41-E41)/E41 -> -0.00090015505 | J41: =(E41-F41)/F41 -> 0.49553285
A42: Total Assets | B42: 40827.73 | C42: 35349.09 | D42: 27941.7 | E42: 44691.94 | F42: 36784.9 | G42: =(B42-C42)/C42 -> 0.15498673 | H42: =(C42-D42)/D42 -> 0.26510162 | I42: =(D42-E42)/E42 -> -0.37479331 | J42: =(E42-F42)/F42 -> 0.21495342
A44: OTHER ADDITIONAL INFORMATION
A45: CONTINGENT LIABILITIES, COMMITMENTS
A46: Contingent Liabilities | B46: 25533.63 | C46: 7742.6 | D46: 8951.59 | E46: 11783.56 | F46: 9795.84 | G46: =IF(C46<>0,B46/C46-1,"") -> 2.2978108 | H46: =IF(D46<>0,C46/D46-1,"") -> -0.13505869 | I46: =IF(E46<>0,D46/E46-1,"") -> -0.24033229 | J46: =IF(F46<>0,E46/F46-1,"") -> 0.20291471
A47: Other Earnings | B47: 448.19 | C47: 0 | D47: 0 | E47: 0 | F47: 0 | G47: =IF(C47<>0,B47/C47-1,"") | H47: =IF(D47<>0,C47/D47-1,"") | I47: =IF(E47<>0,D47/E47-1,"") | J47: =IF(F47<>0,E47/F47-1,"")
A48: BONUS DETAILS
A49: Bonus Equity Share Capital | B49: 841.9 | C49: 255.79 | D49: 255.79 | E49: 255.79 | F49: 255.79 | G49: =IF(C49<>0,B49/C49-1,"") -> 2.2913718 | H49: =IF(D49<>0,C49/D49-1,"") -> 0 | I49: =IF(E49<>0,D49/E49-1,"") -> 0 | J49: =IF(F49<>0,E49/F49-1,"") -> 0
A50: NON-CURRENT INVESTMENTS
A51: Non-Current Investments Quoted Market Value | B51: 536.44 | C51: 648.43 | D51: 476.01 | E51: 622.09 | F51: 321.25 | G51: =IF(C51<>0,B51/C51-1,"") -> -0.17270947 | H51: =IF(D51<>0,C51/D51-1,"") -> 0.36221928 | I51: =IF(E51<>0,D51/E51-1,"") -> -0.23482133 | J51: =IF(F51<>0,E51/F51-1,"") -> 0.93646693
A52: Non-Current Investments Unquoted Book Value | B52: 707.84 | C52: 707.84 | D52: 707.84 | E52: 809.26 | F52: 806.74 | G52: =IF(C52<>0,B52/C52-1,"") -> 0 | H52: =IF(D52<>0,C52/D52-1,"") -> 0 | I52: =IF(E52<>0,D52/E52-1,"") -> -0.12532437 | J52: =IF(F52<>0,E52/F52-1,"") -> 0.003123683
A53: CURRENT INVESTMENTS
A54: Current Investments Quoted Market Value | G54: =IF(C54<>0,B54/C54-1,"") | H54: =IF(D54<>0,C54/D54-1,"") | I54: =IF(E54<>0,D54/E54-1,"") | J54: =IF(F54<>0,E54/F54-1,"")
A55: Current Investments Unquoted Book Value | G55: =IF(C55<>0,B55/C55-1,"") | H55: =IF(D55<>0,C55/D55-1,"") | I55: =IF(E55<>0,D55/E55-1,"") | J55: =IF(F55<>0,E55/F55-1,"")

Sheet Standalone P&L 
A1: NMDC - Standalone Profit & Loss (Rs. Cr.)
A2: Particulars (Rs. Cr.) | B2: Mar 25 | C2: Mar 24 | D2: Mar 23 | E2: Mar 22 | F2: Mar 21 | G2: % Chg Mar 25/Mar 24 | H2: % Chg Mar 24/Mar 23 | I2: % Chg Mar 23/Mar 22 | J2: % Chg Mar 22/Mar 21
A3: 12 Months Ended | B3: 12 mths | C3: 12 mths | D3: 12 mths | E3: 12 mths | F3: 12 mths
A4: INCOME
A5: Revenue From Operations [Gross] | B5: 23663.58 | C5: 21289.96 | D5: 17661.1 | E5: 25881.73 | F5: 15370.05 | G5: =IF(C5=0,"",(B5-C5)/C5) -> 0.11149011 | H5: =IF(D5=0,"",(C5-D5)/D5) -> 0.20547191 | I5: =IF(E5=0,"",(D5-E5)/E5) -> -0.31762289 | J5: =IF(F5=0,"",(E5-F5)/F5) -> 0.68390669
A6: Revenue From Operations [Net] | B6: 23663.58 | C6: 21289.96 | D6: 17661.1 | E6: 25881.73 | F6: 15370.05 | G6: =IF(C6=0,"",(B6-C6)/C6) -> 0.11149011 | H6: =IF(D6=0,"",(C6-D6)/D6) -> 0.20547191 | I6: =IF(E6=0,"",(D6-E6)/E6) -> -0.31762289 | J6: =IF(F6=0,"",(E6-F6)/F6) -> 0.68390669
A7: Other Operating Revenues | B7: 4.74 | C7: 3.85 | D7: 5.78 | E7: 0 | F7: 0.01 | G7: =IF(C7=0,"",(B7-C7)/C7) -> 0.23116883 | H7: =IF(D7=0,"",(C7-D7)/D7) -> -0.33391003 | I7: =IF(E7=0,"",(D7-E7)/E7) | J7: =IF(F7=0,"",(E7-F7)/F7) -> -1
A8: Total Operating Revenues | B8: 23668.32 | C8: 21293.81 | D8: 17666.88 | E8: 25881.73 | F8: 15370.06 | G8: =IF(C8=0,"",(B8-C8)/C8) -> 0.11151175 | H8: =IF(D8=0,"",(C8-D8)/D8) -> 0.20529545 | I8: =IF(E8=0,"",(D8-E8)/E8) -> -0.31739957 | J8: =IF(F8=0,"",(E8-F8)/F8) -> 0.68390559
A9: Other Income | B9: 1590.24 | C9: 1355.54 | D9: 747.85 | E9: 718.33 | F9: 349.88 | G9: =IF(C9=0,"",(B9-C9)/C9) -> 0.17314133 | H9: =IF(D9=0,"",(C9-D9)/D9) -> 0.81258274 | I9: =IF(E9=0,"",(D9-E9)/E9) -> 0.041095318 | J9: =IF(F9=0,"",(E9-F9)/F9) -> 1.0530753
A10: Total Revenue | B10: 25258.56 | C10: 22649.35 | D10: 18414.73 | E10: 26600.06 | F10: 15719.94 | G10: =IF(C10=0,"",(B10-C10)/C10) -> 0.11520022 | H10: =IF(D10=0,"",(C10-D10)/D10) -> 0.2299583 | I10: =IF(E10=0,"",(D10-E10)/E10) -> -0.30771848 | J10: =IF(F10=0,"",(E10-F10)/F10) -> 0.69212223
A11: EXPENSES
A12: Cost Of Materials Consumed | B12: 772.11 | C12: 777.39 | D12: 771 | E12: 625.99 | F12: 410.21 | G12: =IF(C12=0,"",(B12-C12)/C12) -> -0.0067919577 | H12: =IF(D12=0,"",(C12-D12)/D12) -> 0.0082879377 | I12: =IF(E12=0,"",(D12-E12)/E12) -> 0.23164907 | J12: =IF(F12=0,"",(E12-F12)/F12) -> 0.52602326
A13: Purchase Of Stock-In Trade | B13: 197.09 | C13: 0 | D13: 0 | E13: 0 | F13: 0 | G13: =IF(C13=0,"",(B13-C13)/C13) | H13: =IF(D13=0,"",(C13-D13)/D13) | I13: =IF(E13=0,"",(D13-E13)/E13) | J13: =IF(F13=0,"",(E13-F13)/F13)
A14: Operating And Direct Expenses | B14: 10327.27 | C14: 9460.28 | D14: 7934.97 | E14: 9986.76 | F14: 2969.38 | G14: =IF(C14=0,"",(B14-C14)/C14) -> 0.091645279 | H14: =IF(D14=0,"",(C14-D14)/D14) -> 0.19222631 | I14: =IF(E14=0,"",(D14-E14)/E14) -> -0.20545102 | J14: =IF(F14=0,"",(E14-F14)/F14) -> 2.3632475
A15: Changes In Inventories Of FG,WIP And Stock-In Trade | B15: 81.97 | C15: -66.08 | D15: -496.6 | E15: -1200.5 | F15: -161.81 | G15: =IF(C15=0,"",(B15-C15)/C15) -> -2.2404661 | H15: =IF(D15=0,"",(C15-D15)/D15) -> -0.86693516 | I15: =IF(E15=0,"",(D15-E15)/E15) -> -0.58633903 | J15: =IF(F15=0,"",(E15-F15)/F15) -> 6.4191954
A16: Employee Benefit Expenses | B16: 1781.44 | C16: 1619.44 | D16: 1526.5 | E16: 1333.68 | F16: 1081.81 | G16: =IF(C16=0,"",(B16-C16)/C16) -> 0.10003458 | H16: =IF(D16=0,"",(C16-D16)/D16) -> 0.060884376 | I16: =IF(E16=0,"",(D16-E16)/E16) -> 0.14457741 | J16: =IF(F16=0,"",(E16-F16)/F16) -> 0.23282277
A17: Finance Costs | B17: 177.65 | C17: 78.24 | D17: 75.23 | E17: 39.06 | F17: 16.81 | G17: =IF(C17=0,"",(B17-C17)/C17) -> 1.2705777 | H17: =IF(D17=0,"",(C17-D17)/D17) -> 0.040010634 | I17: =IF(E17=0,"",(D17-E17)/E17) -> 0.92601126 | J17: =IF(F17=0,"",(E17-F17)/F17) -> 1.3236169
A18: Depreciation And Amortisation Expenses | B18: 372.78 | C18: 337.05 | D18: 335.41 | E18: 286.85 | F18: 227.83 | G18: =IF(C18=0,"",(B18-C18)/C18) -> 0.10600801 | H18: =IF(D18=0,"",(C18-D18)/D18) -> 0.0048895382 | I18: =IF(E18=0,"",(D18-E18)/E18) -> 0.16928708 | J18: =IF(F18=0,"",(E18-F18)/F18) -> 0.2590528
A19: Other Expenses | B19: 2250.58 | C19: 2147.56 | D19: 1867.97 | E19: 2546.81 | F19: 2274.61 | G19: =IF(C19=0,"",(B19-C19)/C19) -> 0.04797072 | H19: =IF(D19=0,"",(C19-D19)/D19) -> 0.14967585 | I19: =IF(E19=0,"",(D19-E19)/E19) -> -0.26654521 | J19: =IF(F19=0,"",(E19-F19)/F19) -> 0.11966887
A20: Total Expenses | B20: 15960.89 | C20: 14353.88 | D20: 12014.48 | E20: 13618.65 | F20: 6818.84 | G20: =IF(C20=0,"",(B20-C20)/C20) -> 0.11195649 | H20: =IF(D20=0,"",(C20-D20)/D20) -> 0.19471504 | I20: =IF(E20=0,"",(D20-E20)/E20) -> -0.11779215 | J20: =IF(F20=0,"",(E20-F20)/F20) -> 0.9972092
A21: Profit/Loss Before Exceptional, ExtraOrdinary Items And Tax | B21: 9297.67 | C21: 8295.47 | D21: 6400.25 | E21: 12981.41 | F21: 8901.1 | G21: =IF(C21=0,"",(B21-C21)/C21) -> 0.12081293 | H21: =IF(D21=0,"",(C21-D21)/D21) -> 0.29611656 | I21: =IF(E21=0,"",(D21-E21)/E21) -> -0.50696804 | J21: =IF(F21=0,"",(E21-F21)/F21) -> 0.45840514
A22: Exceptional Items | B22: 0 | C22: -282.15 | D22: 1237.27 | E22: 0 | F22: 0 | G22: =IF(C22=0,"",(B22-C22)/C22) -> -1 | H22: =IF(D22=0,"",(C22-D22)/D22) -> -1.2280424 | I22: =IF(E22=0,"",(D22-E22)/E22) | J22: =IF(F22=0,"",(E22-F22)/F22)
A23: Profit/Loss Before Tax | B23: 9297.67 | C23: 8013.32 | D23: 7637.52 | E23: 12981.41 | F23: 8901.1 | G23: =IF(C23=0,"",(B23-C23)/C23) -> 0.16027689 | H23: =IF(D23=0,"",(C23-D23)/D23) -> 0.049204454 | I23: =IF(E23=0,"",(D23-E23)/E23) -> -0.41165713 | J23: =IF(F23=0,"",(E23-F23)/F23) -> 0.45840514
A24: Tax Expenses-Continued Operations
A25: Current Tax | B25: 2410.81 | C25: 2117.62 | D25: 1664.65 | E25: 3444.39 | F25: 2316.46 | G25: =IF(C25=0,"",(B25-C25)/C25) -> 0.1384526 | H25: =IF(D25=0,"",(C25-D25)/D25) -> 0.27211125 | I25: =IF(E25=0,"",(D25-E25)/E25) -> -0.51670688 | J25: =IF(F25=0,"",(E25-F25)/F25) -> 0.4869197
A26: Deferred Tax | B26: -30.36 | C26: 31.62 | D26: 271.43 | E26: -122.67 | F26: -11.21 | G26: =IF(C26=0,"",(B26-C26)/C26) -> -1.9601518 | H26: =IF(D26=0,"",(C26-D26)/D26) -> -0.88350588 | I26: =IF(E26=0,"",(D26-E26)/E26) -> -3.2126844 | J26: =IF(F26=0,"",(E26-F26)/F26) -> 9.9429081
A27: Tax For Earlier Years | B27: 223.69 | C27: 231.18 | D27: 172.13 | E27: 260.53 | F27: 343.2 | G27: =IF(C27=0,"",(B27-C27)/C27) -> -0.032398996 | H27: =IF(D27=0,"",(C27-D27)/D27) -> 0.34305467 | I27: =IF(E27=0,"",(D27-E27)/E27) -> -0.33930833 | J27: =IF(F27=0,"",(E27-F27)/F27) -> -0.24087995
A28: Total Tax Expenses | B28: 2604.14 | C28: 2380.42 | D28: 2108.21 | E28: 3582.25 | F28: 2648.45 | G28: =IF(C28=0,"",(B28-C28)/C28) -> 0.093983415 | H28: =IF(D28=0,"",(C28-D28)/D28) -> 0.12911902 | I28: =IF(E28=0,"",(D28-E28)/E28) -> -0.4114844 | J28: =IF(F28=0,"",(E28-F28)/F28) -> 0.35258359
A29: Profit/Loss After Tax And Before ExtraOrdinary Items | B29: 6693.53 | C29: 5632.9 | D29: 5529.31 | E29: 9399.16 | F29: 6252.65 | G29: =IF(C29=0,"",(B29-C29)/C29) -> 0.188292 | H29: =IF(D29=0,"",(C29-D29)/D29) -> 0.018734707 | I29: =IF(E29=0,"",(D29-E29)/E29) -> -0.41172296 | J29: =IF(F29=0,"",(E29-F29)/F29) -> 0.50322823
A30: Profit/Loss From Continuing Operations | B30: 6693.53 | C30: 5632.9 | D30: 5529.31 | E30: 9399.16 | F30: 6252.65 | G30: =IF(C30=0,"",(B30-C30)/C30) -> 0.188292 | H30: =IF(D30=0,"",(C30-D30)/D30) -> 0.018734707 | I30: =IF(E30=0,"",(D30-E30)/E30) -> -0.41172296 | J30: =IF(F30=0,"",(E30-F30)/F30) -> 0.50322823
A31: Profit Loss From Discontinuing Operations | B31: -1.24 | C31: -1.32 | D31: -0.91 | E31: -0.91 | F31: 0.53 | G31: =IF(C31=0,"",(B31-C31)/C31) -> -0.060606061 | H31: =IF(D31=0,"",(C31-D31)/D31) -> 0.45054945 | I31: =IF(E31=0,"",(D31-E31)/E31) -> 0 | J31: =IF(F31=0,"",(E31-F31)/F31) -> -2.7169811
A32: Total Tax Expenses Discontinuing Operations | B32: -0.31 | C32: -0.33 | D32: -0.23 | E32: -0.23 | F32: 0.13 | G32: =IF(C32=0,"",(B32-C32)/C32) -> -0.060606061 | H32: =IF(D32=0,"",(C32-D32)/D32) -> 0.43478261 | I32: =IF(E32=0,"",(D32-E32)/E32) -> 0 | J32: =IF(F32=0,"",(E32-F32)/F32) -> -2.7692308
A33: Net Profit Loss From Discontinuing Operations | B33: -0.93 | C33: -0.99 | D33: -0.68 | E33: -0.68 | F33: 0.4 | G33: =IF(C33=0,"",(B33-C33)/C33) -> -0.060606061 | H33: =IF(D33=0,"",(C33-D33)/D33) -> 0.45588235 | I33: =IF(E33=0,"",(D33-E33)/E33) -> 0 | J33: =IF(F33=0,"",(E33-F33)/F33) -> -2.7
A34: Profit/Loss For The Period | B34: 6692.6 | C34: 5631.91 | D34: 5528.63 | E34: 9398.48 | F34: 6253.05 | G34: =IF(C34=0,"",(B34-C34)/C34) -> 0.18833575 | H34: =IF(D34=0,"",(C34-D34)/D34) -> 0.018680939 | I34: =IF(E34=0,"",(D34-E34)/E34) -> -0.41175275 | J34: =IF(F34=0,"",(E34-F34)/F34) -> 0.50302332
A36: OTHER ADDITIONAL INFORMATION
A37: EARNINGS PER SHARE
A38: Basic EPS (Rs.) | B38: 7.61 | C38: 19.22 | D38: 18.86 | E38: 32.07 | F38: 20.62 | G38: =IF(C38=0,"",(B38-C38)/C38) -> -0.60405827 | H38: =IF(D38=0,"",(C38-D38)/D38) -> 0.019088017 | I38: =IF(E38=0,"",(D38-E38)/E38) -> -0.41191144 | J38: =IF(F38=0,"",(E38-F38)/F38) -> 0.55528613
A39: Diluted EPS (Rs.) | B39: 7.61 | C39: 19.22 | D39: 18.86 | E39: 32.07 | F39: 20.62 | G39: =IF(C39=0,"",(B39-C39)/C39) -> -0.60405827 | H39: =IF(D39=0,"",(C39-D39)/D39) -> 0.019088017 | I39: =IF(E39=0,"",(D39-E39)/E39) -> -0.41191144 | J39: =IF(F39=0,"",(E39-F39)/F39) -> 0.55528613
A40: Indigenous Raw Materials | B40: 12.42 | C40: 20.97 | D40: 70.59 | E40: 106.95 | F40: 42.01 | G40: =IF(C40=0,"",(B40-C40)/C40) -> -0.40772532 | H40: =IF(D40=0,"",(C40-D40)/D40) -> -0.70293243 | I40: =IF(E40=0,"",(D40-E40)/E40) -> -0.33997195 | J40: =IF(F40=0,"",(E40-F40)/F40) -> 1.5458224
A41: Imported Stores And Spares | B41: 1.12 | C41: 1.85 | D41: 1.69 | E41: 2.07 | F41: 6.01 | G41: =IF(C41=0,"",(B41-C41)/C41) -> -0.39459459 | H41: =IF(D41=0,"",(C41-D41)/D41) -> 0.094674556 | I41: =IF(E41=0,"",(D41-E41)/E41) -> -0.18357488 | J41: =IF(F41=0,"",(E41-F41)/F41) -> -0.65557404
A42: Indigenous Stores And Spares | B42: 595.47 | C42: 586.49 | D42: 554.65 | E42: 394.46 | F42: 251.4 | G42: =IF(C42=0,"",(B42-C42)/C42) -> 0.015311429 | H42: =IF(D42=0,"",(C42-D42)/D42) -> 0.057405571 | I42: =IF(E42=0,"",(D42-E42)/E42) -> 0.40609948 | J42: =IF(F42=0,"",(E42-F42)/F42) -> 0.5690533
A43: DIVIDEND AND DIVIDEND PERCENTAGE
A44: Equity Share Dividend | B44: 2461.71 | C44: 2520.34 | D44: 1098.98 | E44: 4319.72 | F44: 2274.15 | G44: =IF(C44=0,"",(B44-C44)/C44) -> -0.023262734 | H44: =IF(D44=0,"",(C44-D44)/D44) -> 1.2933447 | I44: =IF(E44=0,"",(D44-E44)/E44) -> -0.74558999 | J44: =IF(F44=0,"",(E44-F44)/F44) -> 0.89948772
A45: Equity Dividend Rate (%) | B45: 330 | C45: 725 | D45: 660 | E45: 1474 | F45: 776 | G45: =IF(C45=0,"",(B45-C45)/C45) -> -0.54482759 | H45: =IF(D45=0,"",(C45-D45)/D45) -> 0.098484848 | I45: =IF(E45=0,"",(D45-E45)/E45) -> -0.55223881 | J45: =IF(F45=0,"",(E45-F45)/F45) -> 0.89948454

Sheet Consolidated Balance sheet
A1: NMDC - Consolidated Balance Sheet (Rs. Cr.)
A2: Particulars (Rs. Cr.) | B2: Mar 21 | C2: Mar 22 | D2: Mar 23 | E2: Mar 24 | F2: Mar 25 | G2: % Chg Mar 22/Mar 21 | H2: % Chg Mar 23/Mar 22 | I2: % Chg Mar 24/Mar 23 | J2: % Chg Mar 25/Mar 24 | K2: % Chg Mar 25/Mar 25
A3: 12 Months Ended | B3: 12 mths | C3: 12 mths | D3: 12 mths | E3: 12 mths | F3: 12 mths
A4: EQUITIES AND LIABILITIES
A5: SHAREHOLDER'S FUNDS
A6: Equity Share Capital | B6: 293.07 | C6: 293.07 | D6: 293.07 | E6: 293.07 | F6: 879.18 | H6: =(C6-B6)/B6 -> 0 | I6: =(D6-C6)/C6 -> 0 | J6: =(E6-D6)/D6 -> 0 | K6: =(F6-E6)/E6 -> 1.9998976
A7: Total Share Capital | B7: 293.07 | C7: 293.07 | D7: 293.07 | E7: 293.07 | F7: 879.18 | H7: =(C7-B7)/B7 -> 0 | I7: =(D7-C7)/C7 -> 0 | J7: =(E7-D7)/D7 -> 0 | K7: =(F7-E7)/E7 -> 1.9998976
A8: Reserves and Surplus | B8: 29590.98 | C8: 34693.83 | D8: 22327.76 | E8: 25362.83 | F8: 28816.59 | H8: =(C8-B8)/B8 -> 0.17244613 | I8: =(D8-C8)/C8 -> -0.35643427 | J8: =(E8-D8)/D8 -> 0.13593258 | K8: =(F8-E8)/E8 -> 0.13617408
A9: Total Reserves and Surplus | B9: 29590.98 | C9: 34693.83 | D9: 22327.76 | E9: 25362.83 | F9: 28816.59 | H9: =(C9-B9)/B9 -> 0.17244613 | I9: =(D9-C9)/C9 -> -0.35643427 | J9: =(E9-D9)/D9 -> 0.13593258 | K9: =(F9-E9)/E9 -> 0.13617408
A10: Minority Interest | B10: 13.54 | C10: 13.45 | D10: 14.23 | E10: 17.01 | F10: 11.41 | H10: =(C10-B10)/B10 -> -0.0066469719 | I10: =(D10-C10)/C10 -> 0.057992565 | J10: =(E10-D10)/D10 -> 0.19536191 | K10: =(F10-E10)/E10 -> -0.32921811
A11: Total Shareholders Funds | B11: 29884.05 | C11: 34986.9 | D11: 22620.83 | E11: 25655.9 | F11: 29695.77 | H11: =(C11-B11)/B11 -> 0.17075497 | I11: =(D11-C11)/C11 -> -0.35344858 | J11: =(E11-D11)/D11 -> 0.13417147 | K11: =(F11-E11)/E11 -> 0.15746359
A12: NON-CURRENT LIABILITIES
A13: Long Term Borrowings | B13: 546.43 | C13: 1668.22 | D13: 0 | E13: 0 | F13: 0 | H13: =(C13-B13)/B13 -> 2.0529437 | I13: =(D13-C13)/C13 -> -1
A14: Other Long Term Liabilities | B14: 4.7 | C14: 156.13 | D14: 155.3 | E14: 152.04 | F14: 152.25 | H14: =(C14-B14)/B14 -> 32.219149 | I14: =(D14-C14)/C14 -> -0.0053160828 | J14: =(E14-D14)/D14 -> -0.020991629 | K14: =(F14-E14)/E14 -> 0.0013812155
A15: Long Term Provisions | B15: 945.41 | C15: 1092.46 | D15: 1255.99 | E15: 1431.26 | F15: 1479.09 | H15: =(C15-B15)/B15 -> 0.15554098 | I15: =(D15-C15)/C15 -> 0.14968969 | J15: =(E15-D15)/D15 -> 0.13954729 | K15: =(F15-E15)/E15 -> 0.033418107
A16: Total Non-Current Liabilities | B16: 1496.54 | C16: 2916.81 | D16: 1411.29 | E16: 1583.3 | F16: 1631.34 | H16: =(C16-B16)/B16 -> 0.94903578 | I16: =(D16-C16)/C16 -> -0.51615292 | J16: =(E16-D16)/D16 -> 0.1218814 | K16: =(F16-E16)/E16 -> 0.030341691
A17: CURRENT LIABILITIES
A18: Short Term Borrowings | B18: 1448.04 | C18: 1815.13 | D18: 415.98 | E18: 3356.54 | F18: 3770.45 | H18: =(C18-B18)/B18 -> 0.25350819 | I18: =(D18-C18)/C18 -> -0.77082633 | J18: =(E18-D18)/D18 -> 7.0689937 | K18: =(F18-E18)/E18 -> 0.12331448
A19: Trade Payables | B19: 360.78 | C19: 967.53 | D19: 425.91 | E19: 412.55 | F19: 321.46 | H19: =(C19-B19)/B19 -> 1.6817728 | I19: =(D19-C19)/C19 -> -0.5597966 | J19: =(E19-D19)/D19 -> -0.031368129 | K19: =(F19-E19)/E19 -> -0.22079748
A20: Other Current Liabilities | B20: 3628.29 | C20: 4136.62 | D20: 3235.61 | E20: 4380.44 | F20: 5192.7 | H20: =(C20-B20)/B20 -> 0.14010181 | I20: =(D20-C20)/C20 -> -0.21781309 | J20: =(E20-D20)/D20 -> 0.353822 | K20: =(F20-E20)/E20 -> 0.18542886
A21: Short Term Provisions | B21: 98.56 | C21: 15.13 | D21: 123.86 | E21: 255.29 | F21: 383.75 | H21: =(C21-B21)/B21 -> -0.84648945 | I21: =(D21-C21)/C21 -> 7.1863847 | J21: =(E21-D21)/D21 -> 1.0611174 | K21: =(F21-E21)/E21 -> 0.50319245
A22: Total Current Liabilities | B22: 5535.67 | C22: 6934.41 | D22: 4201.36 | E22: 8404.82 | F22: 9668.36 | H22: =(C22-B22)/B22 -> 0.25267763 | I22: =(D22-C22)/C22 -> -0.3941287 | J22: =(E22-D22)/D22 -> 1.0004998 | K22: =(F22-E22)/E22 -> 0.15033516
A23: Total Capital And Liabilities | B23: 36929.8 | C23: 44851.57 | D23: 28247.71 | E23: 35661.03 | F23: 41006.88 | H23: =(C23-B23)/B23 -> 0.21450888 | I23: =(D23-C23)/C23 -> -0.37019574 | J23: =(E23-D23)/D23 -> 0.26243968 | K23: =(F23-E23)/E23 -> 0.14990734
A24: ASSETS
A25: NON-CURRENT ASSETS
A26: Tangible Assets | B26: 3320.95 | C26: 4165.13 | D26: 2388.75 | E26: 2520.49 | F26: 4177.3 | H26: =(C26-B26)/B26 -> 0.25419835 | I26: =(D26-C26)/C26 -> -0.42648849 | J26: =(E26-D26)/D26 -> 0.055150183 | K26: =(F26-E26)/E26 -> 0.65733647
A27: Intangible Assets | B27: 518.57 | C27: 535.73 | D27: 715.93 | E27: 762.24 | F27: 767.27 | H27: =(C27-B27)/B27 -> 0.033091 | I27: =(D27-C27)/C27 -> 0.33636347 | J27: =(E27-D27)/D27 -> 0.064685095 | K27: =(F27-E27)/E27 -> 0.0065989715
A28: Capital Work-In-Progress | B28: 17106.51 | C28: 18324.52 | D28: 1991.55 | E28: 3230.51 | F28: 4737.48 | H28: =(C28-B28)/B28 -> 0.071201548 | I28: =(D28-C28)/C28 -> -0.89131775 | J28: =(E28-D28)/D28 -> 0.62210841 | K28: =(F28-E28)/E28 -> 0.46648052
A29: Intangible Assets Under Development | B29: 51.42 | C29: 5 | D29: 6.49 | E29: 4.14 | F29: 0 | H29: =(C29-B29)/B29 -> -0.90276157 | I29: =(D29-C29)/C29 -> 0.298 | J29: =(E29-D29)/D29 -> -0.36209553 | K29: =(F29-E29)/E29 -> -1
A30: Fixed Assets | B30: 20997.45 | C30: 23030.38 | D30: 5102.72 | E30: 6517.38 | F30: 9682.05 | H30: =(C30-B30)/B30 -> 0.096817947 | I30: =(D30-C30)/C30 -> -0.77843527 | J30: =(E30-D30)/D30 -> 0.27723645 | K30: =(F30-E30)/E30 -> 0.48557396
A31: Non-Current Investments | B31: 874.9 | C31: 894.95 | D31: 934.68 | E31: 951.17 | F31: 974.53 | H31: =(C31-B31)/B31 -> 0.022916905 | I31: =(D31-C31)/C31 -> 0.044393542 | J31: =(E31-D31)/D31 -> 0.017642402 | K31: =(F31-E31)/E31 -> 0.024559227
A32: Deferred Tax Assets [Net] | B32: 408.28 | C32: 530.95 | D32: 297.5 | E32: 265.89 | F32: 296.25 | H32: =(C32-B32)/B32 -> 0.30045557 | I32: =(D32-C32)/C32 -> -0.43968359 | J32: =(E32-D32)/D32 -> -0.1062521 | K32: =(F32-E32)/E32 -> 0.11418256
A33: Long Term Loans And Advances | B33: 259.17 | C33: 40.77 | D33: 62.62 | E33: 81.74 | F33: 126.72 | H33: =(C33-B33)/B33 -> -0.84269013 | I33: =(D33-C33)/C33 -> 0.53593328 | J33: =(E33-D33)/D33 -> 0.30533376 | K33: =(F33-E33)/E33 -> 0.55028138
A34: Other Non-Current Assets | B34: 3695.91 | C34: 4449.8 | D34: 5949.09 | E34: 6202.43 | F34: 6456.76 | H34: =(C34-B34)/B34 -> 0.20397953 | I34: =(D34-C34)/C34 -> 0.33693424 | J34: =(E34-D34)/D34 -> 0.042584664 | K34: =(F34-E34)/E34 -> 0.041004896
A35: Total Non-Current Assets | B35: 26329.6 | C35: 29040.74 | D35: 12440.5 | E35: 14112.5 | F35: 17630.2 | H35: =(C35-B35)/B35 -> 0.10296928 | I35: =(D35-C35)/C35 -> -0.57161904 | J35: =(E35-D35)/D35 -> 0.13439974 | K35: =(F35-E35)/E35 -> 0.24926129
A36: CURRENT ASSETS
A37: Current Investments | B37: 0 | C37: 0 | D37: 0 | E37: 4.89 | F37: 3.6 | K37: =(F37-E37)/E37 -> -0.26380368
A38: Inventories | B38: 921.72 | C38: 2164.9 | D38: 2660.58 | E38: 2766.95 | F38: 2637.72 | H38: =(C38-B38)/B38 -> 1.348761 | I38: =(D38-C38)/C38 -> 0.22896208 | J38: =(E38-D38)/D38 -> 0.039980004 | K38: =(F38-E38)/E38 -> -0.046704856
A39: Trade Receivables | B39: 2139.89 | C39: 2954.3 | D39: 2656.02 | E39: 3508.93 | F39: 7744.61 | H39: =(C39-B39)/B39 -> 0.38058498 | I39: =(D39-C39)/C39 -> -0.1009647 | J39: =(E39-D39)/D39 -> 0.32112333 | K39: =(F39-E39)/E39 -> 1.2071144
A40: Cash And Cash Equivalents | B40: 5861.82 | C40: 7978.29 | D40: 7097.75 | E40: 12363.65 | F40: 10088.55 | H40: =(C40-B40)/B40 -> 0.36106022 | I40: =(D40-C40)/C40 -> -0.11036701 | J40: =(E40-D40)/D40 -> 0.74191117 | K40: =(F40-E40)/E40 -> -0.18401524
A41: Short Term Loans And Advances | B41: 0 | C41: 0 | D41: 0 | E41: 0 | F41: 53.91
A42: OtherCurrentAssets | B42: 1676.77 | C42: 2713.34 | D42: 3392.86 | E42: 2904.11 | F42: 2848.29 | H42: =(C42-B42)/B42 -> 0.6181945 | I42: =(D42-C42)/C42 -> 0.25043673 | J42: =(E42-D42)/D42 -> -0.14405251 | K42: =(F42-E42)/E42 -> -0.019221035
A43: Total Current Assets | B43: 10600.2 | C43: 15810.83 | D43: 15807.21 | E43: 21548.53 | F43: 23376.68 | H43: =(C43-B43)/B43 -> 0.49155959 | I43: =(D43-C43)/C43 -> -0.00022895699 | J43: =(E43-D43)/D43 -> 0.36320894 | K43: =(F43-E43)/E43 -> 0.084838734
A44: Total Assets | B44: 36929.8 | C44: 44851.57 | D44: 28247.71 | E44: 35661.03 | F44: 41006.88 | H44: =(C44-B44)/B44 -> 0.21450888 | I44: =(D44-C44)/C44 -> -0.37019574 | J44: =(E44-D44)/D44 -> 0.26243968 | K44: =(F44-E44)/E44 -> 0.14990734
A46: OTHER ADDITIONAL INFORMATION
A47: CONTINGENT LIABILITIES, COMMITMENTS
A48: Contingent Liabilities | B48: 9854.61 | C48: 11844.86 | D48: 8756.7 | E48: 7742.6 | F48: 25543.54 | H48: =(C48-B48)/B48 -> 0.20196132 | I48: =(D48-C48)/C48 -> -0.26071731 | J48: =(E48-D48)/D48 -> -0.11580847 | K48: =(F48-E48)/E48 -> 2.2990907
A49: Other Earnings | B49: 0 | C49: 0 | D49: 0 | E49: 0 | F49: 448.19
A50: BONUS DETAILS
A51: Bonus Equity Share Capital | B51: 255.79 | C51: 255.79 | D51: 255.79 | E51: 255.79 | F51: 841.9 | H51: =(C51-B51)/B51 -> 0 | I51: =(D51-C51)/C51 -> 0 | J51: =(E51-D51)/D51 -> 0 | K51: =(F51-E51)/E51 -> 2.2913718
A52: NON-CURRENT INVESTMENTS
A53: Non-Current Investments Unquoted Book Value | B53: 880.15 | C53: 0 | D53: 934.68 | E53: 951.17 | F53: 974.53 | H53: =(C53-B53)/B53 -> -1 | J53: =(E53-D53)/D53 -> 0.017642402 | K53: =(F53-E53)/E53 -> 0.024559227
A54: CURRENT INVESTMENTS
A55: Current Investments Unquoted Book Value | B55: 0 | C55: 0 | D55: 0 | E55: 4.89 | F55: 3.6 | K55: =(F55-E55)/E55 -> -0.26380368

Sheet Consolidated P&L
A1: NMDC - Consolidated Profit & Loss (Rs. Cr.)
A2: Particulars (Rs. Cr.) | B2: Mar 21 | C2: Mar 22 | D2: Mar 23 | E2: Mar 24 | F2: Mar 25 | G2: % Chg Mar 22/Mar 21 | H2: % Chg Mar 23/Mar 22 | I2: % Chg Mar 24/Mar 23 | J2: % Chg Mar 25/Mar 24 | K2: % Chg Mar 25/Mar 24
A3: 12 Months Ended | B3: 12 mths | C3: 12 mths | D3: 12 mths | E3: 12 mths | F3: 12 mths
A4: INCOME
A5: Revenue From Operations [Gross] | B5: 15370.05 | C5: 25881.73 | D5: 17661.1 | E5: 21301.23 | F5: 23900.78 | H5: =(C5-B5)/B5 -> 0.68390669 | I5: =(D5-C5)/C5 -> -0.31762289 | J5: =(E5-D5)/D5 -> 0.20611004 | K5: =(F5-E5)/E5 -> 0.12203755
A6: Revenue From Operations [Net] | B6: 15370.05 | C6: 25881.73 | D6: 17661.1 | E6: 21301.23 | F6: 23900.78 | H6: =(C6-B6)/B6 -> 0.68390669 | I6: =(D6-C6)/C6 -> -0.31762289 | J6: =(E6-D6)/D6 -> 0.20611004 | K6: =(F6-E6)/E6 -> 0.12203755
A7: Other Operating Revenues | B7: 0.01 | C7: 0 | D7: 5.78 | E7: 6.62 | F7: 4.74 | H7: =(C7-B7)/B7 -> -1 | J7: =(E7-D7)/D7 -> 0.14532872 | K7: =(F7-E7)/E7 -> -0.28398792
A8: Total Operating Revenues | B8: 15370.06 | C8: 25881.73 | D8: 17666.88 | E8: 21307.85 | F8: 23905.52 | H8: =(C8-B8)/B8 -> 0.68390559 | I8: =(D8-C8)/C8 -> -0.31739957 | J8: =(E8-D8)/D8 -> 0.20609015 | K8: =(F8-E8)/E8 -> 0.12191141
A9: Other Income | B9: 351.6 | C9: 718.52 | D9: 768.22 | E9: 1370.88 | F9: 1593.32 | H9: =(C9-B9)/B9 -> 1.0435722 | I9: =(D9-C9)/C9 -> 0.06916996 | J9: =(E9-D9)/D9 -> 0.78448882 | K9: =(F9-E9)/E9 -> 0.16226074
A10: Total Revenue | B10: 15721.66 | C10: 26600.25 | D10: 18435.1 | E10: 22678.73 | F10: 25498.84 | H10: =(C10-B10)/B10 -> 0.6919492 | I10: =(D10-C10)/C10 -> -0.30695764 | J10: =(E10-D10)/D10 -> 0.23019295 | K10: =(F10-E10)/E10 -> 0.12435044
A11: EXPENSES
A12: Cost Of Materials Consumed | B12: 410.24 | C12: 626.02 | D12: 771.03 | E12: 841.79 | F12: 896.39 | H12: =(C12-B12)/B12 -> 0.52598479 | I12: =(D12-C12)/C12 -> 0.23163797 | J12: =(E12-D12)/D12 -> 0.091773342 | K12: =(F12-E12)/E12 -> 0.064861783
A13: Purchase Of Stock-In Trade | B13: 0 | C13: 0 | D13: 0 | E13: 0 | F13: 197.09
A14: Operating And Direct Expenses | B14: 2969.38 | C14: 10178.99 | D14: 7935.05 | E14: 9460.47 | F14: 10502.91 | H14: =(C14-B14)/B14 -> 2.427985 | I14: =(D14-C14)/C14 -> -0.2204482 | J14: =(E14-D14)/D14 -> 0.19223823 | K14: =(F14-E14)/E14 -> 0.11018903
A15: Changes In Inventories Of FG,WIP And Stock-In Trade | B15: -161.81 | C15: -1200.5 | D15: -496.6 | E15: -93.36 | F15: 99.31 | H15: =(C15-B15)/B15 -> 6.4191954 | I15: =(D15-C15)/C15 -> -0.58633903 | J15: =(E15-D15)/D15 -> -0.81200161 | K15: =(F15-E15)/E15 -> -2.0637318
A16: Employee Benefit Expenses | B16: 1085.24 | C16: 1337.07 | D16: 1530.57 | E16: 1625.54 | F16: 1795.04 | H16: =(C16-B16)/B16 -> 0.23205005 | I16: =(D16-C16)/C16 -> 0.14471942 | J16: =(E16-D16)/D16 -> 0.062048779 | K16: =(F16-E16)/E16 -> 0.10427304
A17: Finance Costs | B17: 16.81 | C17: 39.06 | D17: 75.23 | E17: 78.24 | F17: 177.68 | H17: =(C17-B17)/B17 -> 1.3236169 | I17: =(D17-C17)/C17 -> 0.92601126 | J17: =(E17-D17)/D17 -> 0.040010634 | K17: =(F17-E17)/E17 -> 1.2709611
A18: Depreciation And Amortisation Expenses | B18: 228.54 | C18: 287.74 | D18: 336.18 | E18: 350.66 | F18: 420.42 | H18: =(C18-B18)/B18 -> 0.25903562 | I18: =(D18-C18)/C18 -> 0.16834642 | J18: =(E18-D18)/D18 -> 0.043072164 | K18: =(F18-E18)/E18 -> 0.19893914
A19: Other Expenses | B19: 2277.74 | C19: 2357.63 | D19: 1874.3 | E19: 2180.58 | F19: 2266.11 | H19: =(C19-B19)/B19 -> 0.03507424 | I19: =(D19-C19)/C19 -> -0.20500672 | J19: =(E19-D19)/D19 -> 0.16341034 | K19: =(F19-E19)/E19 -> 0.039223509
A20: Total Expenses | B20: 6826.14 | C20: 13626.01 | D20: 12025.76 | E20: 14443.92 | F20: 16354.95 | H20: =(C20-B20)/B20 -> 0.99615156 | I20: =(D20-C20)/C20 -> -0.11744084 | J20: =(E20-D20)/D20 -> 0.20108168 | K20: =(F20-E20)/E20 -> 0.13230688
A21: Profit/Loss Before Exceptional, ExtraOrdinary Items And Tax | B21: 8895.52 | C21: 12974.24 | D21: 6409.34 | E21: 8234.81 | F21: 9143.89 | H21: =(C21-B21)/B21 -> 0.45851395 | I21: =(D21-C21)/C21 -> -0.50599496 | J21: =(E21-D21)/D21 -> 0.28481404 | K21: =(F21-E21)/E21 -> 0.11039478
A22: Exceptional Items | B22: 0 | C22: 0 | D22: 1237.27 | E22: -282.15 | F22: 0 | J22: =(E22-D22)/D22 -> -1.2280424 | K22: =(F22-E22)/E22 -> -1
A23: Profit/Loss Before Tax | B23: 8895.52 | C23: 12974.24 | D23: 7646.61 | E23: 7952.66 | F23: 9143.89 | H23: =(C23-B23)/B23 -> 0.45851395 | I23: =(D23-C23)/C23 -> -0.41063137 | J23: =(E23-D23)/D23 -> 0.040024272 | K23: =(F23-E23)/E23 -> 0.14979013
A24: Tax Expenses-Continued Operations
A25: Current Tax | B25: 2316.46 | C25: 3444.39 | D25: 1664.65 | E25: 2117.62 | F25: 2410.81 | H25: =(C25-B25)/B25 -> 0.4869197 | I25: =(D25-C25)/C25 -> -0.51670688 | J25: =(E25-D25)/D25 -> 0.27211125 | K25: =(F25-E25)/E25 -> 0.1384526
A26: Deferred Tax | B26: -11.21 | C26: -122.67 | D26: 271.43 | E26: 31.62 | F26: -30.36 | H26: =(C26-B26)/B26 -> 9.9429081 | I26: =(D26-C26)/C26 -> -3.2126844 | J26: =(E26-D26)/D26 -> -0.88350588 | K26: =(F26-E26)/E26 -> -1.9601518
A27: Tax For Earlier Years | B27: 343.2 | C27: 260.53 | D27: 172.13 | E27: 231.18 | F27: 223.69 | H27: =(C27-B27)/B27 -> -0.24087995 | I27: =(D27-C27)/C27 -> -0.33930833 | J27: =(E27-D27)/D27 -> 0.34305467 | K27: =(F27-E27)/E27 -> -0.032398996
A28: Total Tax Expenses | B28: 2648.45 | C28: 3582.25 | D28: 2108.21 | E28: 2380.42 | F28: 2604.14 | H28: =(C28-B28)/B28 -> 0.35258359 | I28: =(D28-C28)/C28 -> -0.4114844 | J28: =(E28-D28)/D28 -> 0.12911902 | K28: =(F28-E28)/E28 -> 0.093983415
A29: Profit/Loss After Tax And Before ExtraOrdinary Items | B29: 6247.07 | C29: 9391.99 | D29: 5538.4 | E29: 5572.24 | F29: 6539.75 | H29: =(C29-B29)/B29 -> 0.5034232 | I29: =(D29-C29)/C29 -> -0.41030602 | J29: =(E29-D29)/D29 -> 0.0061100679 | K29: =(F29-E29)/E29 -> 0.17363035
A30: Profit/Loss From Continuing Operations | B30: 6247.07 | C30: 9391.99 | D30: 5538.4 | E30: 5572.24 | F30: 6539.75 | H30: =(C30-B30)/B30 -> 0.5034232 | I30: =(D30-C30)/C30 -> -0.41030602 | J30: =(E30-D30)/D30 -> 0.0061100679 | K30: =(F30-E30)/E30 -> 0.17363035
A31: Profit Loss From Discontinuing Operations | B31: 0.53 | C31: -0.91 | D31: -0.91 | E31: -1.32 | F31: -1.24 | H31: =(C31-B31)/B31 -> -2.7169811 | I31: =(D31-C31)/C31 -> 0 | J31: =(E31-D31)/D31 -> 0.45054945 | K31: =(F31-E31)/E31 -> -0.060606061
A32: Total Tax Expenses Discontinuing Operations | B32: 0.13 | C32: -0.23 | D32: -0.23 | E32: -0.33 | F32: -0.31 | H32: =(C32-B32)/B32 -> -2.7692308 | I32: =(D32-C32)/C32 -> 0 | J32: =(E32-D32)/D32 -> 0.43478261 | K32: =(F32-E32)/E32 -> -0.060606061
A33: Net Profit Loss From Discontinuing Operations | B33: 0.4 | C33: -0.68 | D33: -0.68 | E33: -0.99 | F33: -0.93 | H33: =(C33-B33)/B33 -> -2.7 | I33: =(D33-C33)/C33 -> 0 | J33: =(E33-D33)/D33 -> 0.45588235 | K33: =(F33-E33)/E33 -> -0.060606061
A34: Profit/Loss For The Period | B34: 6247.47 | C34: 9391.31 | D34: 5537.72 | E34: 5571.25 | F34: 6538.82 | H34: =(C34-B34)/B34 -> 0.5032181 | I34: =(D34-C34)/C34 -> -0.41033573 | J34: =(E34-D34)/D34 -> 0.0060548385 | K34: =(F34-E34)/E34 -> 0.17367198
A35: Minority Interest | B35: 0.37 | C35: 0.55 | D35: -1.1 | E35: 4.19 | F35: 10.95 | H35: =(C35-B35)/B35 -> 0.48648649 | I35: =(D35-C35)/C35 -> -3 | J35: =(E35-D35)/D35 -> -4.8090909 | K35: =(F35-E35)/E35 -> 1.6133652
A36: Share Of Profit/Loss Of Associates | B36: 29.17 | C36: -12.26 | D36: 64.84 | E36: -0.38 | F36: -7.79 | H36: =(C36-B36)/B36 -> -1.4202948 | I36: =(D36-C36)/C36 -> -6.2887439 | J36: =(E36-D36)/D36 -> -1.0058606 | K36: =(F36-E36)/E36 -> 19.5
A37: Consolidated Profit/Loss After MI And Associates | B37: 6277.01 | C37: 9379.6 | D37: 5601.46 | E37: 5575.06 | F37: 6541.98 | H37: =(C37-B37)/B37 -> 0.49427833 | I37: =(D37-C37)/C37 -> -0.40280396 | J37: =(E37-D37)/D37 -> -0.004713057 | K37: =(F37-E37)/E37 -> 0.1734367
A39: OTHER ADDITIONAL INFORMATION
A40: EARNINGS PER SHARE
A41: Basic EPS (Rs.) | B41: 21 | C41: 32 | D41: 19 | E41: 19 | F41: 7 | H41: =(C41-B41)/B41 -> 0.52380952 | I41: =(D41-C41)/C41 -> -0.40625 | J41: =(E41-D41)/D41 -> 0 | K41: =(F41-E41)/E41 -> -0.63157895
A42: Diluted EPS (Rs.) | B42: 21 | C42: 32 | D42: 19 | E42: 19 | F42: 7 | H42: =(C42-B42)/B42 -> 0.52380952 | I42: =(D42-C42)/C42 -> -0.40625 | J42: =(E42-D42)/D42 -> 0 | K42: =(F42-E42)/E42 -> -0.63157895
A43: Indigenous Raw Materials | B43: 42.01 | C43: 106.95 | D43: 70.59 | E43: 20.97 | F43: 12.42 | H43: =(C43-B43)/B43 -> 1.5458224 | I43: =(D43-C43)/C43 -> -0.33997195 | J43: =(E43-D43)/D43 -> -0.70293243 | K43: =(F43-E43)/E43 -> -0.40772532
A44: Imported Stores And Spares | B44: 6.01 | C44: 2.07 | D44: 1.69 | E44: 1.85 | F44: 1.12 | H44: =(C44-B44)/B44 -> -0.65557404 | I44: =(D44-C44)/C44 -> -0.18357488 | J44: =(E44-D44)/D44 -> 0.094674556 | K44: =(F44-E44)/E44 -> -0.39459459
A45: Indigenous Stores And Spares | B45: 251.4 | C45: 394.46 | D45: 554.65 | E45: 586.49 | F45: 595.47 | H45: =(C45-B45)/B45 -> 0.5690533 | I45: =(D45-C45)/C45 -> 0.40609948 | J45: =(E45-D45)/D45 -> 0.057405571 | K45: =(F45-E45)/E45 -> 0.015311429
A46: DIVIDEND AND DIVIDEND PERCENTAGE
A47: Equity Share Dividend | B47: 2274.15 | C47: 4319.72 | D47: 1098.98 | E47: 2520.34 | F47: 2461.71 | H47: =(C47-B47)/B47 -> 0.89948772 | I47: =(D47-C47)/C47 -> -0.74558999 | J47: =(E47-D47)/D47 -> 1.2933447 | K47: =(F47-E47)/E47 -> -0.023262734

Sheet Peers
F2: Attribute | G2: LTP (₹) | H2: Sales (₹ crore) | I2: PAT (₹ crore) | J2: Equity (₹ crore) | K2: Operating Profit Margin (OPM%) | L2: Net Profit Margin (NPM%) | M2: Earnings Per Share (EPS) | N2: Cash Earnings Per Share (CEPS)
F3: NMDC | G3: 90.66 | H3: 23905.52 | I3: 6538.82 | J3: 879.18 | K3: 34.08 | L3: 27.36 | M3: 7 | N3: 7.92
F4: JSW Steel | G4: 1265 | H4: 168824 | I4: 3802 | J4: 271.57 | K4: 13.56 | L4: 2.07 | M4: 14 | N4: 48.28
F5: TATA Steel | G5: 211.39 | H5: 218542.51 | I5: 2982.97 | J5: 994.32 | K5: 11.57 | L5: 1.56 | M5: 3 | N5: 13.48
F6: Hindalco | G6: 1039.3 | H6: 238496 | I6: 15999 | J6: 222.21 | K6: 13.33 | L6: 6.7 | M6: 72 | N6: 107.47
F8: NMDC | L8: JSW Steel
F9: Metric | G9: 44986 | H9: 45352 | I9: 45717 | L9: Metric | M9: 44986 | N9: 45352 | O9: 45717
F10: Debtor Days | G10: 57.9 | H10: 52.8 | I10: 85.9 | L10: Debtor Days | M10: 16 | N10: 15.3 | O10: 17.3
F11: Inventory Days | G11: 55 | H11: 47.4 | I11: 40.3 | L11: Inventory Days | M11: 72.9 | N11: 78.8 | O11: 75.6
F12: Days Payable | G12: -37.5 | H12: -106.9 | I12: -74.1 | L12: Days Payable | M12: 78.9 | N12: 84.4 | O12: 86.2
F13: Cash Conversion Cycle | G13: 150.4 | H13: 207.1 | I13: 200.3 | L13: Cash Conversion Cycle | M13: 10 | N13: 9.7 | O13: 6.7
F14: Working Capital Days | G14: 150.4 | H14: 207.1 | I14: 200.3 | L14: Working Capital Days | M14: 10 | N14: 9.7 | O14: 6.7
F15: ROCE % | G15: 28.14 | H15: 28.65 | I15: 27.85 | L15: ROCE % | M15: 8.37 | N15: 12.9 | O15: 8.14
F19: TATA Steel | L19: Hindalco
F20: Metric | G20: 44986 | H20: 45352 | I20: 45717 | L20: Metric | M20: 44986 | N20: 45352 | O20: 45717
F21: Debtor Days | G21: 15.4 | H21: 11.6 | I21: 9.6 | L21: Debtor Days | M21: 30.5 | N21: 27.6 | O21: 27.7
F22: Inventory Days | G22: 81.7 | H22: 78.3 | I22: 74.5 | L22: Inventory Days | M22: 70.2 | N22: 69 | O22: 74.6
F23: Days Payable | G23: 119 | H23: 125.3 | I23: 122.5 | L23: Days Payable | M23: 81.8 | N23: 80.1 | O23: 87.6
F24: Cash Conversion Cycle | G24: -21.9 | H24: -35.4 | I24: -38.4 | L24: Cash Conversion Cycle | M24: 18.9 | N24: 16.5 | O24: 14.7
F25: Working Capital Days | G25: -21.9 | H25: -35.4 | I25: -38.4 | L25: Working Capital Days | M25: 18.9 | N25: 16.5 | O25: 14.7
F26: ROCE % | G26: 13.25 | H26: 8.19 | I26: 9.11 | L26: ROCE % | M26: 10.99 | N26: 11.1 | O26: 14.34
F29: Peer Comparison — NMDC vs JSW Steel, TATA Steel, Hindalco Profitability: NMDC is the clear outlier in terms of margin quality. Its OPM of 34.1% and NPM of 27.4% are nearly 3x that of JSW Steel (13.6% / 2.1%) and Tata Steel (11.6% / 1.6%). Even Hindalco, a diversified metals major, earns only 6.7% NPM against NMDC's 27.4%. This difference exists because NMDC is a pure-play iron ore miner — it sells a raw material, not a finished product — which means no conversion costs, no capex-heavy manufacturing, and very low raw material expense. Peers are steel/metals manufacturers with high input costs, energy bills, and thin conversion margins. Comparing margins directly would be misleading; NMDC's margin advantage is structural, not cyclical. ROCE: NMDC's 3-year ROCE has held steady at 28–29%, which is significantly above JSW Steel (8–13%), Tata Steel (8–13%), and Hindalco (11–14%). This confirms that NMDC generates far more operating profit per rupee of capital employed than any of its listed peers — a direct outcome of its low-cost, asset-light mining model relative to integrated steel and aluminium producers. Working Capital: NMDC's Cash Conversion Cycle (CCC) of 200 days looks alarming at first glance, but context matters. NMDC has negative days payable (it receives advance payments from customers before delivering ore) which distorts the CCC calculation upward. Tata Steel runs a negative CCC (-38 days) because it stretches payables beyond its receivables+inventory cycle — a typical integrated steel manufacturer pattern. JSW Steel's CCC of 7–10 days reflects tightly managed working capital. NMDC's debtor days have risen from 58 to 86 days over 3 years, suggesting receivables are piling up — this is worth monitoring as it can pressure cash flows if not managed. Overall Positioning: NMDC is not directly comparable to steel or metals manufacturers. It sits upstream — supplying the raw material that feeds JSW Steel and Tata Steel's furnaces. Its profitability metrics will always look superior on paper. The right peer for valuation purposes is a pure mining company, not a steel producer. Among the listed companies here, NMDC stands alone in its margin and return profile, which justifies a modest valuation premium over the steel names.

Sheet Stock Analysis
C1: Metric | D1: Value | F1: Financial Year | G1: Revenue (₹ Crore) | H1: Profit After Tax (PAT) (₹ Crore) | I1: Revenue Change (%) | J1: PAT Change (%) | K1: Nifty 50 Change (%) | L1: Nifty 50 Prices
C2: Market Cap | D2: 78598 | F2: FY 2025-26 | G2: 32070.89 | H2: 7415.37 | I2: =(G2-G3)/G3 -> 0.34183445 | J2: =(H2-H3)/H3 -> 0.13389197 | K2: =(L2-L3)/L3 -> -0.050509474 | L2: 22331.4
C3: Current Price | D3: 89.45 | F3: FY 2024-25 | G3: 23900.78 | H3: 6539.75 | I3: =(G3-G4)/G4 -> 0.12203755 | J3: =(H3-H4)/H4 -> 0.17363035 | K3: =(L3-L4)/L4 -> 0.053408668 | L3: 23519.35
C4: High / Low | D4: 90.77/89.20 | F4: FY 2023-24 | G4: 21301.23 | H4: 5572.24 | I4: =(G4-G5)/G5 -> 0.20611004 | J4: =(H4-H5)/H5 -> 0.0061100679 | K4: =(L4-L5)/L5 -> 0.28613027 | L4: 22326.9
C5: Stock P/E | D5: 10.56 | F5: FY 2022-23 | G5: 17661.1 | H5: 5538.4 | I5: =(G5-G6)/G6 -> -0.31762289 | J5: =(H5-H6)/H6 -> -0.41030037 | K5: =(L5-L6)/L6 -> -0.0060121101 | L5: 17359.75
C6: Book Value | D6: 38.9 | F6: FY 2021-22 | G6: 25881.73 | H6: 9391.9 | L6: 17464.75
C7: Dividend Yield | D7: 3.91
C8: ROCE | D8: 0.2836
C9: ROE | D9: 0.2187
C10: Face Value | D10: 1
F12: NMDC is India's largest iron ore producer — a Navratna PSU with GoI holding 60.79%. FY25 revenue was ₹23,668 Cr with PAT of ₹6,693 Cr. ROCE stands at 32% and ROE at 22%, strong numbers for a commodity mining PSU. No long-term debt as of FY25. H1 FY26 revenue of ₹13,745 Cr is 21% ahead of H1 FY25 — earnings momentum is intact. Dividend yield at 3.91% adds an income component on top of any capital appreciation. Stock trades at 10.56x P/E and ~2.3x P/B — reasonable for a company generating this level of returns. Key risk: iron ore price cyclicality. FY23 revenue fell 32% from FY22 peak, showing how sharply earnings swing when global steel demand softens. Government ownership also means pricing is occasionally influenced by policy. Beta of 1.09 means slight outperformance vs market in rallies, similar downside in corrections. FII + DII together hold ~27%, reflecting genuine institutional conviction.
F21: ACCUMULATE / HOLD — Not a Sell. At ₹89-90, the stock is in fair-to-cheap territory. 32% ROCE, 3.91% dividend yield, and a clean balance sheet at just 10.5x earnings is not expensive for a market leader in iron ore. Existing investors: hold and collect dividends — business fundamentals are not broken. Fresh entry: wait for ₹80-85 zone and accumulate in tranches, since iron ore cycle always creates periodic dips worth using. This is not a re-rating story — it will not double overnight. It is a steady dividend compounder for long-term investors. Single metric to watch: FY26 iron ore realization per tonne — that number determines whether the stock breaks above ₹100 or corrects toward ₹70 in the next commodity cycle.

Sheet Beta
A1: Date | B1: Close (Nifty) | D1: Date | E1: Close | H1: Rm Nifty | I1: Rm NMDC
A2: 43922 | B2: 8253.8 | D2: 43922 | E2: 13.81
A3: 43924 | B3: 8083.8 | D3: 43924 | E3: 13.93 | H3: =(B3-B2)/B2 -> -0.020596574 | I3: =(E3-E2)/E2 -> 0.0086893555 | J3: =SLOPE(I3:I1482,H3:H1482) -> 1.0887937 | K3: =_xlfn.COVARIANCE.S(I3:I1482,H3:H1482)/_xlfn.VAR.S(H3:H1482) -> 1.0887937
A4: 43928 | B4: 8792.2 | D4: 43928 | E4: 13.87 | H4: =(B4-B3)/B3 -> 0.087632054 | I4: =(E4-E3)/E3 -> -0.0043072505
A5: 43929 | B5: 8748.75 | D5: 43929 | E5: 13.23 | H5: =(B5-B4)/B4 -> -0.0049418803 | I5: =(E5-E4)/E4 -> -0.046142754
A6: 43930 | B6: 9111.9 | D6: 43930 | E6: 14.02 | H6: =(B6-B5)/B5 -> 0.041508787 | I6: =(E6-E5)/E5 -> 0.059712774
A7: 43934 | B7: 8993.85 | D7: 43934 | E7: 14.57 | H7: =(B7-B6)/B6 -> -0.012955586 | I7: =(E7-E6)/E6 -> 0.039229672 | L7: SUMMARY OUTPUT
A8: 43936 | B8: 8925.3 | D8: 43936 | E8: 14.49 | H8: =(B8-B7)/B7 -> -0.0076218749 | I8: =(E8-E7)/E7 -> -0.0054907344
A9: 43937 | B9: 8992.8 | D9: 43937 | E9: 14.14 | H9: =(B9-B8)/B8 -> 0.007562771 | I9: =(E9-E8)/E8 -> -0.024154589 | L9: Regression Statistics
A10: 43938 | B10: 9266.75 | D10: 43938 | E10: 14.14 | H10: =(B10-B9)/B9 -> 0.030463259 | I10: =(E10-E9)/E9 -> 0 | L10: Multiple R | M10: 0.45993118
A11: 43941 | B11: 9261.85 | D11: 43941 | E11: 13.53 | H11: =(B11-B10)/B10 -> -0.00052877222 | I11: =(E11-E10)/E10 -> -0.043140028 | L11: R Square | M11: 0.21153669
A12: 43942 | B12: 8981.45 | D12: 43942 | E12: 13.04 | H12: =(B12-B11)/B11 -> -0.030274729 | I12: =(E12-E11)/E11 -> -0.036215817 | L12: Adjusted R Square | M12: 0.21100322
A13: 43943 | B13: 9187.3 | D13: 43943 | E13: 13.1 | H13: =(B13-B12)/B12 -> 0.022919462 | I13: =(E13-E12)/E12 -> 0.004601227 | L13: Standard Error | M13: 0.020609783
A14: 43944 | B14: 9313.9 | D14: 43944 | E14: 13.53 | H14: =(B14-B13)/B13 -> 0.013779892 | I14: =(E14-E13)/E13 -> 0.032824427 | L14: Observations | M14: 1480
A15: 43945 | B15: 9154.4 | D15: 43945 | E15: 12.97 | H15: =(B15-B14)/B14 -> -0.017124942 | I15: =(E15-E14)/E14 -> -0.041389505
A16: 43948 | B16: 9282.3 | D16: 43948 | E16: 13.02 | H16: =(B16-B15)/B15 -> 0.013971424 | I16: =(E16-E15)/E15 -> 0.0038550501 | L16: ANOVA
A17: 43949 | B17: 9380.9 | D17: 43949 | E17: 12.87 | H17: =(B17-B16)/B16 -> 0.010622367 | I17: =(E17-E16)/E16 -> -0.011520737 | M17: df | N17: SS | O17: MS | P17: F | Q17: Significance F
A18: 43950 | B18: 9553.35 | D18: 43950 | E18: 13.25 | H18: =(B18-B17)/B17 -> 0.018383098 | I18: =(E18-E17)/E17 -> 0.02952603 | L18: Regression | M18: 1 | N18: 0.16843234 | O18: 0.16843234 | P18: 396.53237 | Q18: 2.3701233e-78
A19: 43951 | B19: 9859.9 | D19: 43951 | E19: 14.16 | H19: =(B19-B18)/B18 -> 0.03208822 | I19: =(E19-E18)/E18 -> 0.068679245 | L19: Residual | M19: 1478 | N19: 0.62779995 | O19: 0.00042476316
A20: 43955 | B20: 9293.5 | D20: 43955 | E20: 13.13 | H20: =(B20-B19)/B19 -> -0.057444802 | I20: =(E20-E19)/E19 -> -0.072740113 | L20: Total | M20: 1479 | N20: 0.79623229
A21: 43956 | B21: 9205.6 | D21: 43956 | E21: 12.81 | H21: =(B21-B20)/B20 -> -0.0094582235 | I21: =(E21-E20)/E20 -> -0.024371668
A22: 43957 | B22: 9270.9 | D22: 43957 | E22: 12.86 | H22: =(B22-B21)/B21 -> 0.0070935083 | I22: =(E22-E21)/E21 -> 0.0039032006 | M22: Coefficients | N22: Standard Error | O22: t Stat | P22: P-value | Q22: Lower 95% | R22: Upper 95% | S22: Lower 95.0% | T22: Upper 95.0%
A23: 43958 | B23: 9199.05 | D23: 43958 | E23: 12.83 | H23: =(B23-B22)/B22 -> -0.0077500566 | I23: =(E23-E22)/E22 -> -0.0023328149 | L23: Intercept | M23: 0.00064043039 | N23: 0.00053717317 | O23: 1.1922233 | P23: 0.23336507 | Q23: -0.00041327257 | R23: 0.0016941334 | S23: -0.00041327257 | T23: 0.0016941334
A24: 43959 | B24: 9251.5 | D24: 43959 | E24: 12.86 | H24: =(B24-B23)/B23 -> 0.0057016757 | I24: =(E24-E23)/E23 -> 0.0023382697 | L24: X Variable 1 | M24: 1.0887937 | N24: 0.054677202 | O24: 19.91312 | P24: 2.3701233e-78 | Q24: 0.98154054 | R24: 1.1960469 | S24: 0.98154054 | T24: 1.1960469
A25: 43962 | B25: 9239.2 | D25: 43962 | E25: 12.72 | H25: =(B25-B24)/B24 -> -0.0013295141 | I25: =(E25-E24)/E24 -> -0.01088647
A26: 43963 | B26: 9196.55 | D26: 43963 | E26: 12.47 | H26: =(B26-B25)/B25 -> -0.0046162005 | I26: =(E26-E25)/E25 -> -0.019654088
A27: 43964 | B27: 9383.55 | D27: 43964 | E27: 13.17 | H27: =(B27-B26)/B26 -> 0.020333712 | I27: =(E27-E26)/E26 -> 0.056134723
A28: 43965 | B28: 9142.75 | D28: 43965 | E28: 12.71 | H28: =(B28-B27)/B27 -> -0.02566193 | I28: =(E28-E27)/E27 -> -0.034927866
A29: 43966 | B29: 9136.85 | D29: 43966 | E29: 12.98 | H29: =(B29-B28)/B28 -> -0.00064532006 | I29: =(E29-E28)/E28 -> 0.021243116
A30: 43969 | B30: 8823.25 | D30: 43969 | E30: 12.5 | H30: =(B30-B29)/B29 -> -0.034322551 | I30: =(E30-E29)/E29 -> -0.036979969
A31: 43970 | B31: 8879.1 | D31: 43970 | E31: 12.55 | H31: =(B31-B30)/B30 -> 0.0063298671 | I31: =(E31-E30)/E30 -> 0.004
A32: 43971 | B32: 9066.55 | D32: 43971 | E32: 12.5 | H32: =(B32-B31)/B31 -> 0.021111374 | I32: =(E32-E31)/E31 -> -0.0039840637
A33: 43972 | B33: 9106.25 | D33: 43972 | E33: 13.05 | H33: =(B33-B32)/B32 -> 0.0043787328 | I33: =(E33-E32)/E32 -> 0.044
A34: 43973 | B34: 9039.25 | D34: 43973 | E34: 12.73 | H34: =(B34-B33)/B33 -> -0.0073575841 | I34: =(E34-E33)/E33 -> -0.024521073
A35: 43977 | B35: 9029.05 | D35: 43977 | E35: 13.32 | H35: =(B35-B34)/B34 -> -0.0011284122 | I35: =(E35-E34)/E34 -> 0.046347211
A36: 43978 | B36: 9314.95 | D36: 43978 | E36: 13.19 | H36: =(B36-B35)/B35 -> 0.031664461 | I36: =(E36-E35)/E35 -> -0.0097597598
... A1482: 46111 | B1482: 22331.4 | D1482: 46111 | E1482: 76.27 | H1482: =(B1482-B1481)/B1481 -> -0.021393889 | I1482: =(E1482-E1481)/E1481 -> -0.012046632

Sheet Ratio Analysis
A1: Ratio Analysis- NMDC
A2: Years | B2: 44256 | C2: 44621 | D2: 44986 | E2: 45352 | F2: 45717 | G2: Trends | H2: Mean | I2: Median
A4: Sales Growth | C4: =(Assumptions!C3-Assumptions!B3)/Assumptions!B3 -> 0.68390559 | D4: =(Assumptions!D3-Assumptions!C3)/Assumptions!C3 -> -0.31739957 | E4: =(Assumptions!E3-Assumptions!D3)/Assumptions!D3 -> 0.20609015 | F4: =(Assumptions!F3-Assumptions!E3)/Assumptions!E3 -> 0.12191141 | H4: =AVERAGE(C4:F4) -> 0.1736269 | I4: =MEDIAN(B4:F4) -> 0.16400078
A5: EBITDA Growth | C5: =(Assumptions!C9-Assumptions!B9)/Assumptions!B9 -> 0.43157737 | D5: =(Assumptions!D9-Assumptions!C9)/Assumptions!C9 -> -0.51897315 | E5: =(Assumptions!E9-Assumptions!D9)/Assumptions!D9 -> 0.20492257 | F5: =(Assumptions!F9-Assumptions!E9)/Assumptions!E9 -> 0.11735362 | H5: =AVERAGE(B5:F5) -> 0.058720102 | I5: =MEDIAN(B5:F5) -> 0.16113809
A6: EBIT Growth | C6: =(Assumptions!C11-Assumptions!B11)/Assumptions!B11 -> 0.4361836 | D6: =(Assumptions!D11-Assumptions!C11)/Assumptions!C11 -> -0.53505878 | E6: =(Assumptions!E11-Assumptions!D11)/Assumptions!D11 -> 0.21444103 | F6: =(Assumptions!F11-Assumptions!E11)/Assumptions!E11 -> 0.11323261 | H6: =AVERAGE(B6:F6) -> 0.057199614 | I6: =MEDIAN(B6:F6) -> 0.16383682
A7: Net Profit Growth | C7: =(Assumptions!C17-Assumptions!B17)/Assumptions!B17 -> 0.50342421 | D7: =(Assumptions!D17-Assumptions!C17)/Assumptions!C17 -> -0.54189879 | E7: =(Assumptions!E17-Assumptions!D17)/Assumptions!D17 -> 0.35980643 | F7: =(Assumptions!F17-Assumptions!E17)/Assumptions!E17 -> 0.11599603 | H7: =AVERAGE(B7:F7) -> 0.10933197 | I7: =MEDIAN(B7:F7) -> 0.23790123
A8: Dividend Growth
A10: Gross Margin | B10: =(Assumptions!B3-Assumptions!B8)/Assumptions!B3 -> 0.57184357 | C10: =(Assumptions!C3-Assumptions!C8)/Assumptions!C3 -> 0.48615452 | D10: =(Assumptions!D3-Assumptions!D8)/Assumptions!D3 -> 0.3425919 | E10: =(Assumptions!E3-Assumptions!E8)/Assumptions!E3 -> 0.34226025 | F10: =(Assumptions!F3-Assumptions!F8)/Assumptions!F3 -> 0.34086981 | H10: =AVERAGE(B10:F10) -> 0.41674401 | I10: =MEDIAN(B10:F10) -> 0.3425919
A11: EBITDA Margin | B11: =Assumptions!B28 -> 0.57184357 | C11: =Assumptions!C28 -> 0.48615452 | D11: =Assumptions!D28 -> 0.3425919 | E11: =Assumptions!E28 -> 0.34226025 | F11: =Assumptions!F28 -> 0.34086981 | H11: =AVERAGE(B11:F11) -> 0.41674401 | I11: =MEDIAN(B11:F11) -> 0.3425919
A12: EBIT Margin | B12: =Assumptions!B29 -> 0.5569744 | C12: =Assumptions!C29 -> 0.47503702 | D12: =Assumptions!D29 -> 0.32356307 | E12: =Assumptions!E29 -> 0.3258034 | F12: =Assumptions!F29 -> 0.32328307 | H12: =AVERAGE(B12:F12) -> 0.4009322 | I12: =MEDIAN(B12:F12) -> 0.3258034
A13: EBT Margin | B13: =Assumptions!B30 -> 0.57875636 | C13: =Assumptions!C30 -> 0.50128952 | D13: =Assumptions!D30 -> 0.36278845 | E13: =Assumptions!E30 -> 0.38646837 | F13: =Assumptions!F30 -> 0.3825012 | H13: =AVERAGE(B13:F13) -> 0.44236078 | I13: =MEDIAN(B13:F13) -> 0.38646837
A14: Net Profit Margin | B14: =Assumptions!B31 -> 0.40642001 | C14: =Assumptions!C31 -> 0.36285982 | D14: =Assumptions!D31 -> 0.24351951 | E14: =Assumptions!E31 -> 0.27455609 | F14: =Assumptions!F31 -> 0.27310847 | H14: =AVERAGE(B14:F14) -> 0.31209278 | I14: =MEDIAN(B14:F14) -> 0.27455609
A16: Sales Expenses%Sales | B16: =Assumptions!B8/Assumptions!B3 -> 0.42815643 | C16: =Assumptions!C8/Assumptions!C3 -> 0.51384548 | D16: =Assumptions!D8/Assumptions!D3 -> 0.6574081 | E16: =Assumptions!E8/Assumptions!E3 -> 0.65773975 | F16: =Assumptions!F8/Assumptions!F3 -> 0.65913019 | H16: =AVERAGE(B16:F16) -> 0.58325599 | I16: =MEDIAN(B16:F16) -> 0.6574081
A17: Depriciation%Sales | B17: =Assumptions!B10/Assumptions!B3 -> 0.014869168 | C17: =Assumptions!C10/Assumptions!C3 -> 0.011117495 | D17: =Assumptions!D10/Assumptions!D3 -> 0.019028827 | E17: =Assumptions!E10/Assumptions!E3 -> 0.016456846 | F17: =Assumptions!F10/Assumptions!F3 -> 0.017586733 | H17: =AVERAGE(B17:F17) -> 0.015811814 | I17: =MEDIAN(B17:F17) -> 0.016456846
A18: Operating Income%Sales | B18: =Assumptions!B9/Assumptions!B3 -> 0.57184357 | C18: =Assumptions!C9/Assumptions!C3 -> 0.48615452 | D18: =Assumptions!D9/Assumptions!D3 -> 0.3425919 | E18: =Assumptions!E9/Assumptions!E3 -> 0.34226025 | F18: =Assumptions!F9/Assumptions!F3 -> 0.34086981 | H18: =AVERAGE(B18:F18) -> 0.41674401 | I18: =MEDIAN(B18:F18) -> 0.3425919
A20: Return on Capital Employed | B20: =Assumptions!B44 -> 0.3290475 | C20: =Assumptions!C44 -> 0.40321383 | D20: =Assumptions!D44 -> 0.35863784 | E20: =Assumptions!E44 -> 0.41697745 | F20: =Assumptions!F44 -> 0.33058256 | H20: =AVERAGE(B20:F20) -> 0.36769183 | I20: =MEDIAN(B20:F20) -> 0.35863784
A21: Retained Earning % | B21: =Assumptions!B17/Assumptions!B3 -> 0.40642001 | C21: =Assumptions!C17/Assumptions!C3 -> 0.36285982 | D21: =Assumptions!D17/Assumptions!D3 -> 0.24351951 | E21: =Assumptions!E17/Assumptions!E3 -> 0.27455609 | F21: =Assumptions!F17/Assumptions!F3 -> 0.27310847 | H21: =AVERAGE(B21:F21) -> 0.31209278 | I21: =MEDIAN(B21:F21) -> 0.27455609
A22: Return on Equity % | B22: =Assumptions!B17/Assumptions!B39 -> 0.20903124 | C22: =Assumptions!C17/Assumptions!C39 -> 0.26842733 | D22: =Assumptions!D17/Assumptions!D39 -> 0.19018887 | E22: =Assumptions!E17/Assumptions!E39 -> 0.22802552 | F22: =Assumptions!F17/Assumptions!F39 -> 0.21985623 | H22: =AVERAGE(B22:F22) -> 0.22310584 | I22: =MEDIAN(B22:F22) -> 0.21985623
A23: Self Sustained Growth Rate | B23: =B22*B21 -> 0.084954479 | C23: =C22*C21 -> 0.097401492 | D23: =D22*D21 -> 0.0463147 | E23: =E22*E21 -> 0.062605796 | F23: =F22*F21 -> 0.060044598 | H23: =AVERAGE(B23:F23) -> 0.070264213 | I23: =MEDIAN(B23:F23) -> 0.062605796
A24: Interest Coverage Ratio | B24: =IF(Assumptions!B13=0,"",Assumptions!B11/Assumptions!B13) -> 509.26413 | C24: =IF(Assumptions!C13=0,"",Assumptions!C11/Assumptions!C13) -> 314.76651 | D24: =IF(Assumptions!D13=0,"",Assumptions!D11/Assumptions!D13) -> 75.984979 | E24: =IF(Assumptions!E13=0,"",Assumptions!E11/Assumptions!E13) -> 88.729167 | F24: =IF(Assumptions!F13=0,"",Assumptions!F11/Assumptions!F13) -> 43.495329 | H24: =AVERAGE(B24:F24) -> 206.44802 | I24: =MEDIAN(B24:F24) -> 88.729167
A26: Debtor Turnover Ratio | B26: =Assumptions!B3/'Historical FS'!B39 -> 7.1826402 | C26: =Assumptions!C3/'Historical FS'!C39 -> 8.760698 | D26: =Assumptions!D3/'Historical FS'!D39 -> 6.6516367 | E26: =Assumptions!E3/'Historical FS'!E39 -> 6.0724637 | F26: =Assumptions!F3/'Historical FS'!F39 -> 3.08673 | H26: =AVERAGE(B26:F26) -> 6.3508337 | I26: =MEDIAN(B26:F26) -> 6.6516367
A27: Creditor Turnover Ratio | B27: =Assumptions!B8/'Historical FS'!B19 -> 18.240451 | C27: =Assumptions!C8/'Historical FS'!C19 -> 13.745527 | D27: =Assumptions!D8/'Historical FS'!D19 -> 27.269494 | E27: =Assumptions!E8/'Historical FS'!E19 -> 33.971688 | F27: =Assumptions!F8/'Historical FS'!F19 -> 49.016518 | H27: =AVERAGE(B27:F27) -> 28.448736 | I27: =MEDIAN(B27:F27) -> 27.269494
A28: Inventory Turnover | B28: =Assumptions!B8/'Historical FS'!B38 -> 7.1396845 | C28: =Assumptions!C8/'Historical FS'!C38 -> 6.1431059 | D28: =Assumptions!D8/'Historical FS'!D38 -> 4.3653452 | E28: =Assumptions!E8/'Historical FS'!E38 -> 5.0651512 | F28: =Assumptions!F8/'Historical FS'!F38 -> 5.9736629 | H28: =AVERAGE(B28:F28) -> 5.7373899 | I28: =MEDIAN(B28:F28) -> 5.9736629
A29: Fixed Asset Turnover | B29: =Assumptions!B3/'Historical FS'!B30 -> 0.7319965 | C29: =Assumptions!C3/'Historical FS'!C30 -> 1.1238082 | D29: =Assumptions!D3/'Historical FS'!D30 -> 3.4622476 | E29: =Assumptions!E3/'Historical FS'!E30 -> 3.2693889 | F29: =Assumptions!F3/'Historical FS'!F30 -> 2.4690556 | H29: =AVERAGE(B29:F29) -> 2.2112994 | I29: =MEDIAN(B29:F29) -> 2.4690556
A30: Capital Turnover Ratio | B30: =Assumptions!B3/Assumptions!B42 -> 0.59077669 | C30: =Assumptions!C3/Assumptions!C42 -> 0.84880506 | D30: =Assumptions!D3/Assumptions!D42 -> 1.1084016 | E30: =Assumptions!E3/Assumptions!E42 -> 1.2798438 | F30: =Assumptions!F3/Assumptions!F42 -> 1.0225792 | H30: =AVERAGE(B30:F30) -> 0.97008128 | I30: =MEDIAN(B30:F30) -> 1.0225792
A32: (In days)
A33: Debtors Day | B33: =365/B26 -> 50.816968 | C33: =365/C26 -> 41.663347 | D33: =365/D26 -> 54.873713 | E33: =365/E26 -> 60.107399 | F33: =365/F26 -> 118.24811 | H33: =AVERAGE(B33:F33) -> 65.141908 | I33: =MEDIAN(B33:F33) -> 54.873713
A34: Payable Days | B34: =365/B27 -> 20.01047 | C34: =365/C27 -> 26.554092 | D34: =365/D27 -> 13.38492 | E34: =365/E27 -> 10.744241 | F34: =365/F27 -> 7.4464693 | H34: =AVERAGE(B34:F34) -> 15.628039 | I34: =MEDIAN(B34:F34) -> 13.38492
A35: Inventory Days | B35: =365/B28 -> 51.122707 | C35: =365/C28 -> 59.416198 | D35: =365/D28 -> 83.613091 | E35: =365/E28 -> 72.061028 | F35: =365/F28 -> 61.10154 | H35: =AVERAGE(B35:F35) -> 65.462913 | I35: =MEDIAN(B35:F35) -> 61.10154
A36: Cash Conversion Cycle | B36: =B33+B35-B34 -> 81.929205 | C36: =C33+C35-C34 -> 74.525453 | D36: =D33+D35-D34 -> 125.10188 | E36: =E33+E35-E34 -> 121.42419 | F36: =F33+F35-F34 -> 171.90318 | H36: =AVERAGE(B36:F36) -> 114.97678 | I36: =MEDIAN(B36:F36) -> 121.42419
A38: CFO/Sales | B38: =(Assumptions!B17+Assumptions!B10)/Assumptions!B3 -> 0.42128918 | C38: =(Assumptions!C17+Assumptions!C10)/Assumptions!C3 -> 0.37397732 | D38: =(Assumptions!D17+Assumptions!D10)/Assumptions!D3 -> 0.26254834 | E38: =(Assumptions!E17+Assumptions!E10)/Assumptions!E3 -> 0.29101294 | F38: =(Assumptions!F17+Assumptions!F10)/Assumptions!F3 -> 0.2906952 | H38: =AVERAGE(B38:F38) -> 0.3279046 | I38: =MEDIAN(B38:F38) -> 0.29101294
A39: CFO/Total Assets | B39: =(Assumptions!B17+Assumptions!B10)/'Historical FS'!B44 -> 0.17533916 | C39: =(Assumptions!C17+Assumptions!C10)/'Historical FS'!C44 -> 0.21580471 | D39: =(Assumptions!D17+Assumptions!D10)/'Historical FS'!D44 -> 0.16420482 | E39: =(Assumptions!E17+Assumptions!E10)/'Historical FS'!E44 -> 0.17388337 | F39: =(Assumptions!F17+Assumptions!F10)/'Historical FS'!F44 -> 0.16946473 | H39: =AVERAGE(B39:F39) -> 0.17973936 | I39: =MEDIAN(B39:F39) -> 0.17388337
A40: CFO/Total Debt | B40: =IF(Assumptions!B40=0,"",(Assumptions!B17+Assumptions!B10)/Assumptions!B40) -> 3.2465968 | C40: =IF(Assumptions!C40=0,"",(Assumptions!C17+Assumptions!C10)/Assumptions!C40) -> 2.7786987 | D40: =IF(Assumptions!D40=0,"",(Assumptions!D17+Assumptions!D10)/Assumptions!D40) -> 11.15056 | E40: =IF(Assumptions!E40=0,"",(Assumptions!E17+Assumptions!E10)/Assumptions!E40) -> 1.8473964 | F40: =IF(Assumptions!F40=0,"",(Assumptions!F17+Assumptions!F10)/Assumptions!F40) -> 1.8430744 | H40: =AVERAGE(B40:F40) -> 4.1732653 | I40: =MEDIAN(B40:F40) -> 2.7786987

Sheet FCFF
A1: Particular | B1: 44256 | C1: 44621 | D1: 44986 | E1: 45352 | F1: 45717
A2: EBIT | B2: =Assumptions!B11 -> 8560.73 | C2: =Assumptions!C11 -> 12294.78 | D2: =Assumptions!D11 -> 5716.35 | E2: =Assumptions!E11 -> 6942.17 | F2: =Assumptions!F11 -> 7728.25
A3: Less: Tax on EBIT | B3: =B2*Assumptions!$G$34 -> 2528.1971 | C3: =C2*Assumptions!$G$34 -> 3630.9553 | D3: =D2*Assumptions!$G$34 -> 1688.1808 | E3: =E2*Assumptions!$G$34 -> 2050.196 | F3: =F2*Assumptions!$G$34 -> 2282.345
A4: EBIT * (1- Tax) NOPAT | B4: =B2-B3 -> 6032.5329 | C4: =C2-C3 -> 8663.8247 | D4: =D2-D3 -> 4028.1692 | E4: =E2-E3 -> 4891.974 | F4: =F2-F3 -> 5445.905
A5: Less: Net Capital expenditure | C5: ='Fixed Asset Scheduled'!C8 -> 2032.93 | D5: ='Fixed Asset Scheduled'!D8 -> -17927.66 | E5: ='Fixed Asset Scheduled'!E8 -> 1414.66 | F5: ='Fixed Asset Scheduled'!F8 -> 3164.67
A6: Less: Net Change in working Capital | C6: ='Change in working Capital'!C6 -> 1450.84 | D6: ='Change in working Capital'!D6 -> 739.02 | E6: ='Change in working Capital'!E6 -> 972.64 | F6: ='Change in working Capital'!F6 -> 4197.54
A7: Reinvestment | C7: =C5+C6 -> 3483.77 | D7: =D5+D6 -> -17188.64 | E7: =E5+E6 -> 2387.3 | F7: =F5+F6 -> 7362.21
A8: Free Cash Flow | C8: =C4-C7 -> 5180.0547 | D8: =D4-D7 -> 21216.809 | E8: =E4-E7 -> 2504.674 | F8: =F4-F7 -> -1916.305
A10: Reinvestment Rate | C10: =IF(C4=0,"",C7/C4) -> 0.40210532 | D10: =IF(D4=0,"",D7/D4) -> -4.2671097 | E10: =IF(E4=0,"",E7/E4) -> 0.48800341 | F10: =IF(F4=0,"",F7/F4) -> 1.35188
A12: Median Reinvestment rate /Sales percentage | C12: =MEDIAN(C10:F10) -> 0.44505436
A13: Average Reinvestment rate /Sales percentage | C13: =AVERAGE(C10:F10) -> -0.50628024

Sheet Change in working Capital
A1: Particular | B1: 44256 | C1: 44621 | D1: 44986 | E1: 45352 | F1: 45717
A2: Inventory | B2: ='Historical FS'!B38 -> 921.72 | C2: ='Historical FS'!C38 -> 2164.9 | D2: ='Historical FS'!D38 -> 2660.58 | E2: ='Historical FS'!E38 -> 2766.95 | F2: ='Historical FS'!F38 -> 2637.72
A3: Trade Receivables | B3: ='Historical FS'!B39 -> 2139.89 | C3: ='Historical FS'!C39 -> 2954.3 | D3: ='Historical FS'!D39 -> 2656.02 | E3: ='Historical FS'!E39 -> 3508.93 | F3: ='Historical FS'!F39 -> 7744.61
A4: Trade Payable | B4: ='Historical FS'!B19 -> 360.78 | C4: ='Historical FS'!C19 -> 967.53 | D4: ='Historical FS'!D19 -> 425.91 | E4: ='Historical FS'!E19 -> 412.55 | F4: ='Historical FS'!F19 -> 321.46
A5: Non Cash working Capital | B5: =B2+B3-B4 -> 2700.83 | C5: =C2+C3-C4 -> 4151.67 | D5: =D2+D3-D4 -> 4890.69 | E5: =E2+E3-E4 -> 5863.33 | F5: =F2+F3-F4 -> 10060.87
A6: Change in Working Capital | C6: =C5-B5 -> 1450.84 | D6: =D5-C5 -> 739.02 | E6: =E5-D5 -> 972.64 | F6: =F5-E5 -> 4197.54
A7: change in working Capital /percentage of sales | C7: =C6/Assumptions!C3 -> 0.056056531 | D7: =D6/Assumptions!D3 -> 0.041830816 | E7: =E6/Assumptions!E3 -> 0.045647027 | F7: =F6/Assumptions!F3 -> 0.17558873
A9: Median Non Cash working Capital /Sales percentage | C9: =MEDIAN(C5:F5)/MEDIAN(Assumptions!C3:F3) -> 0.23785044
A10: Average Non Cash working Capital /Sales percentage | C10: =AVERAGE(C5:F5)/AVERAGE(Assumptions!C3:F3) -> 0.28127538

Sheet Fixed Asset Scheduled
A1: Particular | B1: 44256 | C1: 44621 | D1: 44986 | E1: 45352 | F1: 45717
A2: Beginning balance | C2: =B6 -> 20997.45 | D2: =C6 -> 23030.38 | E2: =D6 -> 5102.72 | F2: =E6 -> 6517.38
A3: Add: Net Purchases | C3: =C6+C5-C2 -> 2320.67 | D3: =D6+D5-D2 -> -17591.48 | E3: =E6+E5-E2 -> 1765.32 | F3: =F6+F5-F2 -> 3585.09
A4: Total Fixed Assets | B4: ='Historical FS'!B30 -> 20997.45 | C4: =C2+C3 -> 23318.12 | D4: =D2+D3 -> 5438.9 | E4: =E2+E3 -> 6868.04 | F4: =F2+F3 -> 10102.47
A5: Less: Depreciation | B5: ='Historical FS'!B62 -> 228.54 | C5: ='Historical FS'!C62 -> 287.74 | D5: ='Historical FS'!D62 -> 336.18 | E5: ='Historical FS'!E62 -> 350.66 | F5: ='Historical FS'!F62 -> 420.42
A6: Closing Balance(Fixed Asests ) | B6: ='Historical FS'!B30 -> 20997.45 | C6: ='Historical FS'!C30 -> 23030.38 | D6: ='Historical FS'!D30 -> 5102.72 | E6: ='Historical FS'!E30 -> 6517.38 | F6: ='Historical FS'!F30 -> 9682.05
A8: Net Capital expenditure | C8: =C3-C5 -> 2032.93 | D8: =D3-D5 -> -17927.66 | E8: =E3-E5 -> 1414.66 | F8: =F3-F5 -> 3164.67
A9: Net Capital expenditure / Sales percentage | C9: =C8/Assumptions!C3 -> 0.078546913 | D9: =D8/Assumptions!D3 -> -1.014761 | E9: =E8/Assumptions!E3 -> 0.066391494 | F9: =F8/Assumptions!F3 -> 0.1323824
A11: Median Capital expenditure /Sales percentage | C11: =MEDIAN(C9:F9) -> 0.072469204
A12: Average Capital expenditure /Sales percentage | C12: =AVERAGE(C9:F9) -> -0.18436004

Sheet Forecasting
E3: Sales Forecasting | J3: EBITDA Forecasting | O3: Earning per share Forecasting
E4: Year Weight | F4: Year | G4: Sales | H4: Sales Growth | J4: Year Weight | K4: Year | L4: EBITDA | M4: EBITDA Growth | O4: Year Weight | P4: Year | Q4: EPS | R4: EPS Growth
E5: 1 | F5: ='Ratio Analysis'!B2 -> 44256 | G5: =Assumptions!B3 -> 15370.06 | J5: 1 | K5: ='Ratio Analysis'!B2 -> 44256 | L5: =Assumptions!B9 -> 8789.27 | O5: 1 | P5: ='Ratio Analysis'!B2 -> 44256 | Q5: ='Standalone P&L '!F38 -> 20.62
E6: =E5+1 -> 2 | F6: =F5+365 -> 44621 | G6: =Assumptions!C3 -> 25881.73 | H6: =(G6-G5)/G5 -> 0.68390559 | J6: =J5+1 -> 2 | K6: =K5+365 -> 44621 | L6: =Assumptions!C9 -> 12582.52 | M6: =(L6-L5)/L5 -> 0.43157737 | O6: =O5+1 -> 2 | P6: =P5+365 -> 44621 | Q6: ='Standalone P&L '!E38 -> 32.07 | R6: =(Q6-Q5)/Q5 -> 0.55528613
E7: =E6+1 -> 3 | F7: =F6+365 -> 44986 | G7: =Assumptions!D3 -> 17666.88 | H7: =(G7-G6)/G6 -> -0.31739957 | J7: =J6+1 -> 3 | K7: =K6+365 -> 44986 | L7: =Assumptions!D9 -> 6052.53 | M7: =(L7-L6)/L6 -> -0.51897315 | O7: =O6+1 -> 3 | P7: =P6+365 -> 44986 | Q7: ='Standalone P&L '!D38 -> 18.86 | R7: =(Q7-Q6)/Q6 -> -0.41191144
E8: =E7+1 -> 4 | F8: =F7+365 -> 45351 | G8: =Assumptions!E3 -> 21307.85 | H8: =(G8-G7)/G7 -> 0.20609015 | J8: =J7+1 -> 4 | K8: =K7+365 -> 45351 | L8: =Assumptions!E9 -> 7292.83 | M8: =(L8-L7)/L7 -> 0.20492257 | O8: =O7+1 -> 4 | P8: =P7+365 -> 45351 | Q8: ='Standalone P&L '!C38 -> 19.22 | R8: =(Q8-Q7)/Q7 -> 0.019088017
E9: =E8+1 -> 5 | F9: =F8+365 -> 45716 | G9: =Assumptions!F3 -> 23905.52 | H9: =(G9-G8)/G8 -> 0.12191141 | J9: =J8+1 -> 5 | K9: =K8+365 -> 45716 | L9: =Assumptions!F9 -> 8148.67 | M9: =(L9-L8)/L8 -> 0.11735362 | O9: =O8+1 -> 5 | P9: =P8+365 -> 45716 | Q9: ='Standalone P&L '!B38 -> 7.61 | R9: =(Q9-Q8)/Q8 -> -0.60405827
E10: =E9+1 -> 6 | F10: =F9+365 -> 46081 | G10: =FORECAST(E10,$G$5:$G$9,$E$5:$E$9) -> 24575.52 | H10: =(G10-G9)/G9 -> 0.028027 | J10: =J9+1 -> 6 | K10: =K9+365 -> 46081 | L10: =FORECAST(J10,$L$5:$L$9,$J$5:$J$9) -> 6601.897 | M10: =(L10-L9)/L9 -> -0.18981907 | O10: =O9+1 -> 6 | P10: =P9+365 -> 46081 | Q10: =FORECAST(O10,$Q$5:$Q$9,$O$5:$O$9) -> 8.015 | R10: =(Q10-Q9)/Q9 -> 0.053219448
E11: =E10+1 -> 7 | F11: =F10+365 -> 46446 | G11: =FORECAST(E11,$G$5:$G$9,$E$5:$E$9) -> 25825.224 | H11: =(G11-G10)/G10 -> 0.050851579 | J11: =J10+1 -> 7 | K11: =K10+365 -> 46446 | L11: =FORECAST(J11,$L$5:$L$9,$J$5:$J$9) -> 5944.808 | M11: =(L11-L10)/L10 -> -0.099530332 | O11: =O10+1 -> 7 | P11: =P10+365 -> 46446 | Q11: =FORECAST(O11,$Q$5:$Q$9,$O$5:$O$9) -> 4.128 | R11: =(Q11-Q10)/Q10 -> -0.48496569
E12: =E11+1 -> 8 | F12: =F11+365 -> 46811 | G12: =FORECAST(E12,$G$5:$G$9,$E$5:$E$9) -> 27074.928 | H12: =(G12-G11)/G11 -> 0.048390829 | J12: =J11+1 -> 8 | K12: =K11+365 -> 46811 | L12: =FORECAST(J12,$L$5:$L$9,$J$5:$J$9) -> 5287.719 | M12: =(L12-L11)/L11 -> -0.11053158 | O12: =O11+1 -> 8 | P12: =P11+365 -> 46811 | Q12: =FORECAST(O12,$Q$5:$Q$9,$O$5:$O$9) -> 0.241 | R12: =(Q12-Q11)/Q11 -> -0.94161822
E13: =E12+1 -> 9 | F13: =F12+365 -> 47176 | G13: =FORECAST(E13,$G$5:$G$9,$E$5:$E$9) -> 28324.632 | H13: =(G13-G12)/G12 -> 0.046157242 | J13: =J12+1 -> 9 | K13: =K12+365 -> 47176 | L13: =FORECAST(J13,$L$5:$L$9,$J$5:$J$9) -> 4630.63 | M13: =(L13-L12)/L12 -> -0.124267 | O13: =O12+1 -> 9 | P13: =P12+365 -> 47176 | Q13: =FORECAST(O13,$Q$5:$Q$9,$O$5:$O$9) -> -3.646 | R13: =(Q13-Q12)/Q12 -> -16.128631
E14: =E13+1 -> 10 | F14: =F13+365 -> 47541 | G14: =FORECAST(E14,$G$5:$G$9,$E$5:$E$9) -> 29574.336 | H14: =(G14-G13)/G13 -> 0.04412075 | J14: =J13+1 -> 10 | K14: =K13+365 -> 47541 | L14: =FORECAST(J14,$L$5:$L$9,$J$5:$J$9) -> 3973.541 | M14: =(L14-L13)/L13 -> -0.14190056 | O14: =O13+1 -> 10 | P14: =P13+365 -> 47541 | Q14: =FORECAST(O14,$Q$5:$Q$9,$O$5:$O$9) -> -7.533 | R14: =(Q14-Q13)/Q13 -> 1.0660998

Sheet Assumptions
A1: NMDC
A2: Particulars (in RS Cr.) | B2: 44256 | C2: Mar 22 | D2: Mar 23 | E2: Mar 24 | F2: Mar 25
A3: Revenue from operations | B3: ='Historical FS'!B52 -> 15370.06 | C3: ='Historical FS'!C52 -> 25881.73 | D3: ='Historical FS'!D52 -> 17666.88 | E3: ='Historical FS'!E52 -> 21307.85 | F3: ='Historical FS'!F52 -> 23905.52
A4: Revenue growth in % | C4: =(C3-B3)/B3 -> 0.68390559 | D4: =(D3-C3)/C3 -> -0.31739957 | E4: =(E3-D3)/D3 -> 0.20609015 | F4: =(F3-E3)/E3 -> 0.12191141
A5: Less: Material cost | B5: ='Historical FS'!B56+'Historical FS'!B57+'Historical FS'!B58+'Historical FS'!B59 -> 3217.81 | C5: ='Historical FS'!C56+'Historical FS'!C57+'Historical FS'!C58+'Historical FS'!C59 -> 9604.51 | D5: ='Historical FS'!D56+'Historical FS'!D57+'Historical FS'!D58+'Historical FS'!D59 -> 8209.48 | E5: ='Historical FS'!E56+'Historical FS'!E57+'Historical FS'!E58+'Historical FS'!E59 -> 10208.9 | F5: ='Historical FS'!F56+'Historical FS'!F57+'Historical FS'!F58+'Historical FS'!F59 -> 11695.7
A6: Less: Employee costs | B6: ='Historical FS'!B60 -> 1085.24 | C6: ='Historical FS'!C60 -> 1337.07 | D6: ='Historical FS'!D60 -> 1530.57 | E6: ='Historical FS'!E60 -> 1625.54 | F6: ='Historical FS'!F60 -> 1795.04
A7: Less: Other Expenses | B7: ='Historical FS'!B63 -> 2277.74 | C7: ='Historical FS'!C63 -> 2357.63 | D7: ='Historical FS'!D63 -> 1874.3 | E7: ='Historical FS'!E63 -> 2180.58 | F7: ='Historical FS'!F63 -> 2266.11
A8: Total Expenses | B8: =B5+B6+B7 -> 6580.79 | C8: =C5+C6+C7 -> 13299.21 | D8: =D5+D6+D7 -> 11614.35 | E8: =E5+E6+E7 -> 14015.02 | F8: =F5+F6+F7 -> 15756.85
A9: EBITDA | B9: =B3-B8 -> 8789.27 | C9: =C3-C8 -> 12582.52 | D9: =D3-D8 -> 6052.53 | E9: =E3-E8 -> 7292.83 | F9: =F3-F8 -> 8148.67
A10: Less: Depreciation And Amortization | B10: ='Historical FS'!B62 -> 228.54 | C10: ='Historical FS'!C62 -> 287.74 | D10: ='Historical FS'!D62 -> 336.18 | E10: ='Historical FS'!E62 -> 350.66 | F10: ='Historical FS'!F62 -> 420.42
A11: EBIT | B11: =B9-B10 -> 8560.73 | C11: =C9-C10 -> 12294.78 | D11: =D9-D10 -> 5716.35 | E11: =E9-E10 -> 6942.17 | F11: =F9-F10 -> 7728.25
A12: ADD: Non operating income/ Other Income | B12: ='Historical FS'!B53 -> 351.6 | C12: ='Historical FS'!C53 -> 718.52 | D12: ='Historical FS'!D53 -> 768.22 | E12: ='Historical FS'!E53 -> 1370.88 | F12: ='Historical FS'!F53 -> 1593.32
A13: Less: Interest Expenses | B13: ='Historical FS'!B61 -> 16.81 | C13: ='Historical FS'!C61 -> 39.06 | D13: ='Historical FS'!D61 -> 75.23 | E13: ='Historical FS'!E61 -> 78.24 | F13: ='Historical FS'!F61 -> 177.68
A14: EBT | B14: =B11+B12-B13 -> 8895.52 | C14: =C11+C12-C13 -> 12974.24 | D14: =D11+D12-D13 -> 6409.34 | E14: =E11+E12-E13 -> 8234.81 | F14: =F11+F12-F13 -> 9143.89
A15: Less: TAX | B15: ='Historical FS'!B72 -> 2648.45 | C15: ='Historical FS'!C72 -> 3582.25 | D15: ='Historical FS'!D72 -> 2108.21 | E15: ='Historical FS'!E72 -> 2380.42 | F15: ='Historical FS'!F72 -> 2604.14
A16: Less:Non Controlling Interest/Minority Interest | B16: ='Historical FS'!B79 -> 0.37 | C16: ='Historical FS'!C79 -> 0.55 | D16: ='Historical FS'!D79 -> -1.1 | E16: ='Historical FS'!E79 -> 4.19 | F16: ='Historical FS'!F79 -> 10.95
A17: Net Profit- Pat | B17: =B14-B15-B16 -> 6246.7 | C17: =C14-C15-C16 -> 9391.44 | D17: =D14-D15-D16 -> 4302.23 | E17: =E14-E15-E16 -> 5850.2 | F17: =F14-F15-F16 -> 6528.8
A23: Historical Growth
A24: Average Growth | B24: =AVERAGE(C4:F4) -> 0.1736269
A25: CAGR | B25: =(F3/B3)^(1/5)-1 -> 0.092356825 | C25: =_xlfn.RRI(5,B3,F3) -> 0.092356825 | D25: RRI
A27: Margins
A28: EBITDA | B28: =B9/B3 -> 0.57184357 | C28: =C9/C3 -> 0.48615452 | D28: =D9/D3 -> 0.3425919 | E28: =E9/E3 -> 0.34226025 | F28: =F9/F3 -> 0.34086981
A29: EBIT | B29: =B11/B3 -> 0.5569744 | C29: =C11/C3 -> 0.47503702 | D29: =D11/D3 -> 0.32356307 | E29: =E11/E3 -> 0.3258034 | F29: =F11/F3 -> 0.32328307
A30: EBT | B30: =B14/B3 -> 0.57875636 | C30: =C14/C3 -> 0.50128952 | D30: =D14/D3 -> 0.36278845 | E30: =E14/E3 -> 0.38646837 | F30: =F14/F3 -> 0.3825012
A31: Net Proftt | B31: =B17/B3 -> 0.40642001 | C31: =C17/C3 -> 0.36285982 | D31: =D17/D3 -> 0.24351951 | E31: =E17/E3 -> 0.27455609 | F31: =F17/F3 -> 0.27310847
A33: Tax Rate
A34: Effective tax rate | B34: =B15/B14 -> 0.29772852 | C34: =C15/C14 -> 0.2761048 | D34: =D15/D14 -> 0.32892778 | E34: =E15/E14 -> 0.28906799 | F34: =F15/F14 -> 0.28479564 | G34: =AVERAGE(B34:F34) -> 0.29532495 | H34: Effective tax rate
A35: Marginal Tax rate | B35: 0.3 | C35: =B35 -> 0.3 | D35: =C35 -> 0.3 | E35: =D35 -> 0.3 | F35: =E35 -> 0.3
A37: Return On Capital
A38: EBIT*(1-T) | B38: =B11*(1-B35) -> 5992.511 | C38: =C11*(1-C35) -> 8606.346 | D38: =D11*(1-D35) -> 4001.445 | E38: =E11*(1-E35) -> 4859.519 | F38: =F11*(1-F35) -> 5409.775
A39: Book Equity | B39: ='Historical FS'!B11 -> 29884.05 | C39: ='Historical FS'!C11 -> 34986.9 | D39: ='Historical FS'!D11 -> 22620.83 | E39: ='Historical FS'!E11 -> 25655.9 | F39: ='Historical FS'!F11 -> 29695.77
A40: Book Debt | B40: ='Historical FS'!B13+'Historical FS'!B18 -> 1994.47 | C40: ='Historical FS'!C13+'Historical FS'!C18 -> 3483.35 | D40: ='Historical FS'!D13+'Historical FS'!D18 -> 415.98 | E40: ='Historical FS'!E13+'Historical FS'!E18 -> 3356.54 | F40: ='Historical FS'!F13+'Historical FS'!F18 -> 3770.45
A41: Cash and Cash equivalents | B41: ='Historical FS'!B40 -> 5861.82 | C41: ='Historical FS'!C40 -> 7978.29 | D41: ='Historical FS'!D40 -> 7097.75 | E41: ='Historical FS'!E40 -> 12363.65 | F41: ='Historical FS'!F40 -> 10088.55
A42: Capital Employed | B42: =B39+B40-B41 -> 26016.7 | C42: =C39+C40-C41 -> 30491.96 | D42: =D39+D40-D41 -> 15939.06 | E42: =E39+E40-E41 -> 16648.79 | F42: =F39+F40-F41 -> 23377.67
A44: Pre-Tax Return on capital | B44: =B11/B42 -> 0.3290475 | C44: =C11/C42 -> 0.40321383 | D44: =D11/D42 -> 0.35863784 | E44: =E11/E42 -> 0.41697745 | F44: =F11/F42 -> 0.33058256
A45: Post Tax return On capital | B45: =B38/B42 -> 0.23033325 | C45: =C38/C42 -> 0.28224968 | D45: =D38/D42 -> 0.25104649 | E45: =E38/E42 -> 0.29188422 | F45: =F38/F42 -> 0.23140779
A47: Growth In EBIT Margin
A48: Growth In EBIT | B48: =FCFF!C12*Assumptions!F45 -> 0.10298905

Sheet Growth scenario
A1: Scenario 1: High Growth
A2: INR Cr. | B2: LTM | C2: Y1E | D2: Y2E | E2: Y3E | F2: Y4W | G2: Y5E | H2: Y6E | I2: Y7E | J2: Y8E | K2: Y9E | L2: Y10E
A3: Sales | B3: =Assumptions!F3 -> 23905.52 | C3: =B3*(1+C4) -> 26113.358 | D3: =C3*(1+D4) -> 28470.972 | E3: =D3*(1+E4) -> 30982.421 | F3: =E3*(1+F4) -> 33651.182 | G3: =F3*(1+G4) -> 36480.065 | H3: =G3*(1+H4) -> 39471.135 | I3: =H3*(1+I4) -> 42625.627 | J3: =I3*(1+J4) -> 45943.86 | ... L3: =K3*(1+L4) -> 53067.797 | M3: =Assumptions!B25 -> 0.092356825 | P3: Risk free rate
A4: Sales Growth % | C4: =M3 -> 0.092356825 | D4: =C4-$O$4 -> 0.090283844 | E4: =D4-$O$4 -> 0.088210864 | F4: =E4-$O$4 -> 0.086137883 | G4: =F4-$O$4 -> 0.084064903 | H4: =G4-$O$4 -> 0.081991922 | I4: =H4-$O$4 -> 0.079918942 | J4: =I4-$O$4 -> 0.077845961 | K4: =J4-$O$4 -> 0.075772981 | L4: =K4-$O$4 -> 0.0737 | M4: 0.0737 | N4: =M3-M4 -> 0.018656825 | O4: =N4/9 -> 0.0020729805 | P4: =M4 -> 0.0737
A6: Scenario 2: Average Growth
A7: INR Cr. | B7: LTM | C7: Y1E | D7: Y2E | E7: Y3E | F7: Y4W | G7: Y5E | H7: Y6E | I7: Y7E | J7: Y8E | K7: Y9E | L7: Y10E | N7: =Assumptions!B24 -> 0.1736269
A8: Sales | B8: =B3 -> 23905.52 | C8: =B8*(1+C9) -> 28056.161 | D8: =C8*(1+D9) -> 32615.958 | E8: =D8*(1+E9) -> 37554.697 | F8: =E8*(1+F9) -> 42824.294 | G8: =F8*(1+G9) -> 48357.832 | H8: =G8*(1+H9) -> 54069.471 | I8: =H8*(1+I9) -> 59855.389 | J8: =I8*(1+J9) -> 65595.878 | ... L8: =K8*(1+L9) -> 76402.994 | N8: =M4 -> 0.0737 | O8: =N7-N8 -> 0.099926896 | P8: =O8/9 -> 0.011102988
A9: Sales Growth % | C9: =N7 -> 0.1736269 | D9: =C9-$P$8 -> 0.16252391 | E9: =D9-$P$8 -> 0.15142092 | F9: =E9-$P$8 -> 0.14031793 | G9: =F9-$P$8 -> 0.12921494 | H9: =G9-$P$8 -> 0.11811195 | I9: =H9-$P$8 -> 0.10700897 | J9: =I9-$P$8 -> 0.095905977 | K9: =J9-$P$8 -> 0.084802988 | L9: =K9-$P$8 -> 0.0737
A11: Scenario 3: EBIT Growth
A12: INR Cr. | B12: LTM | C12: Y1E | D12: Y2E | E12: Y3E | F12: Y4W | G12: Y5E | H12: Y6E | I12: Y7E | J12: Y8E | K12: Y9E | L12: Y10E | N12: =FCFF!C12*Assumptions!F45 -> 0.10298905
A13: Sales | B13: =B8 -> 23905.52 | C13: =B13*(1+C14) -> 26367.527 | D13: =C13*(1+D14) -> 28997.284 | E13: =D13*(1+E14) -> 31794.953 | F13: =E13*(1+F14) -> 34759.07 | G13: =F13*(1+G14) -> 37886.403 | H13: =G13*(1+H14) -> 41171.811 | I13: =H13*(1+I14) -> 44608.135 | J13: =I13*(1+J14) -> 48186.095 | ... L13: =K13*(1+L14) -> 55718.828 | N13: =N8 -> 0.0737 | O13: =N12-N13 -> 0.029289048 | P13: =O13/9 -> 0.0032543386
A14: Sales Growth % | C14: =N12 -> 0.10298905 | D14: =C14-($P$13) -> 0.099734709 | E14: =D14-($P$13) -> 0.096480371 | F14: =E14-($P$13) -> 0.093226032 | G14: =F14-($P$13) -> 0.089971693 | H14: =G14-($P$13) -> 0.086717355 | I14: =H14-($P$13) -> 0.083463016 | J14: =I14-($P$13) -> 0.080208677 | K14: =J14-($P$13) -> 0.076954339 | L14: =K14-($P$13) -> 0.0737 | P14: 0.00294
A16: Live Scenario | B16: 3
A17: INR Cr. | B17: LTM | C17: Y1E | D17: Y2E | E17: Y3E | F17: Y4W | G17: Y5E | H17: Y6E | I17: Y7E | J17: Y8E | K17: Y9E | L17: Y10E
A18: Sales | B18: =B13 -> 23905.52 | C18: =B18*(1+C19) -> 26367.527 | D18: =C18*(1+D19) -> 28997.284 | E18: =D18*(1+E19) -> 31794.953 | F18: =E18*(1+F19) -> 34759.07 | G18: =F18*(1+G19) -> 37886.403 | H18: =G18*(1+H19) -> 41171.811 | I18: =H18*(1+I19) -> 44608.135 | J18: =I18*(1+J19) -> 48186.095 | ... L18: =K18*(1+L19) -> 55718.828
A19: Sales Growth % | C19: =CHOOSE($B$16,C4,C9,C14) -> 0.10298905 | D19: =CHOOSE($B$16,D4,D9,D14) -> 0.099734709 | E19: =CHOOSE($B$16,E4,E9,E14) -> 0.096480371 | F19: =CHOOSE($B$16,F4,F9,F14) -> 0.093226032 | G19: =CHOOSE($B$16,G4,G9,G14) -> 0.089971693 | H19: =CHOOSE($B$16,H4,H9,H14) -> 0.086717355 | I19: =CHOOSE($B$16,I4,I9,I14) -> 0.083463016 | J19: =CHOOSE($B$16,J4,J9,J14) -> 0.080208677 | ... L19: =CHOOSE($B$16,L4,L9,L14) -> 0.0737

Sheet Historical FS
A1: NMDC - Consolidated Balance Sheet (Rs. Cr.)
A2: Particulars (Rs. Cr.) | B2: Mar 21 | C2: Mar 22 | D2: Mar 23 | E2: Mar 24 | F2: Mar 25
A3: 12 Months Ended | B3: 12 mths | C3: 12 mths | D3: 12 mths | E3: 12 mths | F3: 12 mths
A4: EQUITIES AND LIABILITIES
A5: SHAREHOLDER'S FUNDS
A6: Equity Share Capital | B6: 293.07 | C6: 293.07 | D6: 293.07 | E6: 293.07 | F6: 879.18
A7: Total Share Capital | B7: 293.07 | C7: 293.07 | D7: 293.07 | E7: 293.07 | F7: 879.18
A8: Reserves and Surplus | B8: 29590.98 | C8: 34693.83 | D8: 22327.76 | E8: 25362.83 | F8: 28816.59
A9: Total Reserves and Surplus | B9: 29590.98 | C9: 34693.83 | D9: 22327.76 | E9: 25362.83 | F9: 28816.59
A10: Minority Interest | B10: 13.54 | C10: 13.45 | D10: 14.23 | E10: 17.01 | F10: 11.41
A11: Total Shareholders Funds | B11: 29884.05 | C11: 34986.9 | D11: 22620.83 | E11: 25655.9 | F11: 29695.77
A12: NON-CURRENT LIABILITIES
A13: Long Term Borrowings | B13: 546.43 | C13: 1668.22 | D13: 0 | E13: 0 | F13: 0
A14: Other Long Term Liabilities | B14: 4.7 | C14: 156.13 | D14: 155.3 | E14: 152.04 | F14: 152.25
A15: Long Term Provisions | B15: 945.41 | C15: 1092.46 | D15: 1255.99 | E15: 1431.26 | F15: 1479.09
A16: Total Non-Current Liabilities | B16: 1496.54 | C16: 2916.81 | D16: 1411.29 | E16: 1583.3 | F16: 1631.34
A17: CURRENT LIABILITIES
A18: Short Term Borrowings | B18: 1448.04 | C18: 1815.13 | D18: 415.98 | E18: 3356.54 | F18: 3770.45
A19: Trade Payables | B19: 360.78 | C19: 967.53 | D19: 425.91 | E19: 412.55 | F19: 321.46
A20: Other Current Liabilities | B20: 3628.29 | C20: 4136.62 | D20: 3235.61 | E20: 4380.44 | F20: 5192.7
A21: Short Term Provisions | B21: 98.56 | C21: 15.13 | D21: 123.86 | E21: 255.29 | F21: 383.75
A22: Total Current Liabilities | B22: 5535.67 | C22: 6934.41 | D22: 4201.36 | E22: 8404.82 | F22: 9668.36
A23: Total Capital And Liabilities | B23: 36929.8 | C23: 44851.57 | D23: 28247.71 | E23: 35661.03 | F23: 41006.88
A24: ASSETS
A25: NON-CURRENT ASSETS
A26: Tangible Assets | B26: 3320.95 | C26: 4165.13 | D26: 2388.75 | E26: 2520.49 | F26: 4177.3
A27: Intangible Assets | B27: 518.57 | C27: 535.73 | D27: 715.93 | E27: 762.24 | F27: 767.27
A28: Capital Work-In-Progress | B28: 17106.51 | C28: 18324.52 | D28: 1991.55 | E28: 3230.51 | F28: 4737.48
A29: Intangible Assets Under Development | B29: 51.42 | C29: 5 | D29: 6.49 | E29: 4.14 | F29: 0
A30: Fixed Assets | B30: 20997.45 | C30: 23030.38 | D30: 5102.72 | E30: 6517.38 | F30: 9682.05
A31: Non-Current Investments | B31: 874.9 | C31: 894.95 | D31: 934.68 | E31: 951.17 | F31: 974.53
A32: Deferred Tax Assets [Net] | B32: 408.28 | C32: 530.95 | D32: 297.5 | E32: 265.89 | F32: 296.25
A33: Long Term Loans And Advances | B33: 259.17 | C33: 40.77 | D33: 62.62 | E33: 81.74 | F33: 126.72
A34: Other Non-Current Assets | B34: 3695.91 | C34: 4449.8 | D34: 5949.09 | E34: 6202.43 | F34: 6456.76
A35: Total Non-Current Assets | B35: 26329.6 | C35: 29040.74 | D35: 12440.5 | E35: 14112.5 | F35: 17630.2
A36: CURRENT ASSETS
A37: Current Investments | B37: 0 | C37: 0 | D37: 0 | E37: 4.89 | F37: 3.6
A38: Inventories | B38: 921.72 | C38: 2164.9 | D38: 2660.58 | E38: 2766.95 | F38: 2637.72
A39: Trade Receivables | B39: 2139.89 | C39: 2954.3 | D39: 2656.02 | E39: 3508.93 | F39: 7744.61
A40: Cash And Cash Equivalents | B40: 5861.82 | C40: 7978.29 | D40: 7097.75 | E40: 12363.65 | F40: 10088.55
A41: Short Term Loans And Advances | B41: 0 | C41: 0 | D41: 0 | E41: 0 | F41: 53.91
A42: OtherCurrentAssets | B42: 1676.77 | C42: 2713.34 | D42: 3392.86 | E42: 2904.11 | F42: 2848.29
A43: Total Current Assets | B43: 10600.2 | C43: 15810.83 | D43: 15807.21 | E43: 21548.53 | F43: 23376.68
A44: Total Assets | B44: 36929.8 | C44: 44851.57 | D44: 28247.71 | E44: 35661.03 | F44: 41006.88
A45: NMDC - Consolidated Profit & Loss (Rs. Cr.)
A46: Particulars (Rs. Cr.) | B46: Mar 21 | C46: Mar 22 | D46: Mar 23 | E46: Mar 24 | F46: Mar 25
A47: 12 Months Ended | B47: 12 mths | C47: 12 mths | D47: 12 mths | E47: 12 mths | F47: 12 mths
A48: INCOME
A49: Revenue From Operations [Gross] | B49: 15370.05 | C49: 25881.73 | D49: 17661.1 | E49: 21301.23 | F49: 23900.78
A50: Revenue From Operations [Net] | B50: 15370.05 | C50: 25881.73 | D50: 17661.1 | E50: 21301.23 | F50: 23900.78
A51: Other Operating Revenues | B51: 0.01 | C51: 0 | D51: 5.78 | E51: 6.62 | F51: 4.74
A52: Total Operating Revenues | B52: 15370.06 | C52: 25881.73 | D52: 17666.88 | E52: 21307.85 | F52: 23905.52
A53: Other Income | B53: 351.6 | C53: 718.52 | D53: 768.22 | E53: 1370.88 | F53: 1593.32
A54: Total Revenue | B54: 15721.66 | C54: 26600.25 | D54: 18435.1 | E54: 22678.73 | F54: 25498.84
A55: EXPENSES
A56: Cost Of Materials Consumed | B56: 410.24 | C56: 626.02 | D56: 771.03 | E56: 841.79 | F56: 896.39
A57: Purchase Of Stock-In Trade | B57: 0 | C57: 0 | D57: 0 | E57: 0 | F57: 197.09
A58: Operating And Direct Expenses | B58: 2969.38 | C58: 10178.99 | D58: 7935.05 | E58: 9460.47 | F58: 10502.91
A59: Changes In Inventories Of FG,WIP And Stock-In Trade | B59: -161.81 | C59: -1200.5 | D59: -496.6 | E59: -93.36 | F59: 99.31
A60: Employee Benefit Expenses | B60: 1085.24 | C60: 1337.07 | D60: 1530.57 | E60: 1625.54 | F60: 1795.04
A61: Finance Costs | B61: 16.81 | C61: 39.06 | D61: 75.23 | E61: 78.24 | F61: 177.68
A62: Depreciation And Amortisation Expenses | B62: 228.54 | C62: 287.74 | D62: 336.18 | E62: 350.66 | F62: 420.42
A63: Other Expenses | B63: 2277.74 | C63: 2357.63 | D63: 1874.3 | E63: 2180.58 | F63: 2266.11
A64: Total Expenses | B64: 6826.14 | C64: 13626.01 | D64: 12025.76 | E64: 14443.92 | F64: 16354.95
A65: Profit/Loss Before Exceptional, ExtraOrdinary Items And Tax | B65: 8895.52 | C65: 12974.24 | D65: 6409.34 | E65: 8234.81 | F65: 9143.89
A66: Exceptional Items | B66: 0 | C66: 0 | D66: 1237.27 | E66: -282.15 | F66: 0
A67: Profit/Loss Before Tax | B67: 8895.52 | C67: 12974.24 | D67: 7646.61 | E67: 7952.66 | F67: 9143.89
A68: Tax Expenses-Continued Operations
A69: Current Tax | B69: 2316.46 | C69: 3444.39 | D69: 1664.65 | E69: 2117.62 | F69: 2410.81
A70: Deferred Tax | B70: -11.21 | C70: -122.67 | D70: 271.43 | E70: 31.62 | F70: -30.36
A71: Tax For Earlier Years | B71: 343.2 | C71: 260.53 | D71: 172.13 | E71: 231.18 | F71: 223.69
A72: Total Tax Expenses | B72: 2648.45 | C72: 3582.25 | D72: 2108.21 | E72: 2380.42 | F72: 2604.14
A73: Profit/Loss After Tax And Before ExtraOrdinary Items | B73: 6247.07 | C73: 9391.99 | D73: 5538.4 | E73: 5572.24 | F73: 6539.75
A74: Profit/Loss From Continuing Operations | B74: 6247.07 | C74: 9391.99 | D74: 5538.4 | E74: 5572.24 | F74: 6539.75
A75: Profit Loss From Discontinuing Operations | B75: 0.53 | C75: -0.91 | D75: -0.91 | E75: -1.32 | F75: -1.24
A76: Total Tax Expenses Discontinuing Operations | B76: 0.13 | C76: -0.23 | D76: -0.23 | E76: -0.33 | F76: -0.31
A77: Net Profit Loss From Discontinuing Operations | B77: 0.4 | C77: -0.68 | D77: -0.68 | E77: -0.99 | F77: -0.93
A78: Profit/Loss For The Period | B78: 6247.47 | C78: 9391.31 | D78: 5537.72 | E78: 5571.25 | F78: 6538.82
A79: Minority Interest | B79: 0.37 | C79: 0.55 | D79: -1.1 | E79: 4.19 | F79: 10.95
A80: Share Of Profit/Loss Of Associates | B80: 29.17 | C80: -12.26 | D80: 64.84 | E80: -0.38 | F80: -7.79
A81: Consolidated Profit/Loss After MI And Associates | B81: 6277.01 | C81: 9379.6 | D81: 5601.46 | E81: 5575.06 | F81: 6541.98

Sheet WACC
B3: Capital Structure
B4: Total Debt | C4: ='Consolidated Balance sheet'!F13+'Consolidated Balance sheet'!F18 -> 3770.45
B5: Total Equity | C5: ='Consolidated Balance sheet'!F7*92.02 -> 80902.144
B6: Total Mix (Debt + Equity) | C6: =C4+C5 -> 84672.594
B7: % of Debt | C7: =C4/C6 -> 0.044529757
B8: % of Equity | C8: =C5/C6 -> 0.95547024
B9: Debt to Equity | C9: =C4/C5 -> 0.046605069
B11: Cost of Equity (CAPM)
B12: Risk-free Rate (Rf) | C12: 0.0707 | E12: Source: RBI 10-year Government Securities yield (FY2025)
B13: Beta (β) | C13: =Beta!J3 -> 1.0887937
B14: Market Risk Premium (Rm - Rf) | C14: 0.0685 | E14: Source: India Equity Risk Premium (Damodaran estimate)
B15: Cost of Equity [Ke = Rf + β×(Rm-Rf)] | C15: =C12+C13*(C14) -> 0.14528237
B17: Cost of Debt
B18: Finance Cost (FY2025) | C18: ='Consolidated P&L'!F17 -> 177.68
B19: Total Debt (FY2025) | C19: =C4 -> 3770.45
B20: Pre-tax Cost of Debt [Kd = FC/Debt] | C20: =C18/C19 -> 0.047124349
B21: Tax Rate | C21: =Assumptions!G34 -> 0.29532495
B22: Post-tax Cost of Debt [Kd*(1-T)] | C22: =C20*(1-C21) -> 0.033207353
B24: WACC
B25: Source | C25: Weight | D25: Cost | E25: Weighted Cost
B26: Debt | C26: =C7 -> 0.044529757 | D26: =C22 -> 0.033207353 | E26: =D26*C26 -> 0.0014787153
B27: Equity | C27: =C8 -> 0.95547024 | D27: =C15 -> 0.14528237 | E27: =D27*C27 -> 0.13881298
B28: WACC | C28: =SUM(C26:C27) -> 1 | D28: (Check: weights = 100%) | E28: =E26+E27 -> 0.1402917 | G28: wacc = we*ke+wd*kd

Sheet DCF Valuation
C1: 1 | D1: 2 | E1: 3 | F1: 4 | G1: 5 | H1: 6 | I1: 7 | J1: 8 | K1: 9 | L1: 10
A2: INR Cr | B2: LTM | C2: Y1E | D2: Y2E | E2: Y3E | F2: Y4E | G2: Y5E | H2: Y6E | I2: Y7E | J2: Y8E | K2: Y9E | L2: Y10E | N2: Terminal Year | P2: Terminal growth rate % | Q2: 0.04
A3: Sales | B3: ='Growth scenario'!B18 -> 23905.52 | C3: ='Growth scenario'!C18 -> 26367.527 | D3: ='Growth scenario'!D18 -> 28997.284 | E3: ='Growth scenario'!E18 -> 31794.953 | F3: ='Growth scenario'!F18 -> 34759.07 | G3: ='Growth scenario'!G18 -> 37886.403 | H3: ='Growth scenario'!H18 -> 41171.811 | I3: ='Growth scenario'!I18 -> 44608.135 | ... L3: ='Growth scenario'!L18 -> 55718.828 | N3: =L3*(1+$Q$2) -> 57947.581 | P3: Cost of Capital % | Q3: =WACC!E28 -> 0.1402917
A4: Sales Growth | C4: ='Growth scenario'!C19 -> 0.10298905 | D4: ='Growth scenario'!D19 -> 0.099734709 | E4: ='Growth scenario'!E19 -> 0.096480371 | F4: ='Growth scenario'!F19 -> 0.093226032 | G4: ='Growth scenario'!G19 -> 0.089971693 | H4: ='Growth scenario'!H19 -> 0.086717355 | I4: ='Growth scenario'!I19 -> 0.083463016 | J4: ='Growth scenario'!J19 -> 0.080208677 | ... L4: ='Growth scenario'!L19 -> 0.0737 | N4: =$Q$2 -> 0.04 | P4: Terminal reinvestment rate % | Q4: =Q2*Q3 -> 0.0056116679
A5: EBIT | C5: =C3*C6 -> 10571.59 | D5: =D3*D6 -> 11625.945 | E5: =E3*E6 -> 12747.62 | F5: =F3*F6 -> 13936.03 | G5: =G3*G6 -> 15189.879 | H5: =H3*H6 -> 16507.105 | I5: =I3*I6 -> 17884.838 | J5: =J3*J6 -> 19319.357 | ... L5: =L3*L6 -> 22339.472 | N5: =N6*N3 -> 23233.051
A6: EBIT Margin % | C6: =AVERAGE(Assumptions!B29:F29) -> 0.4009322 | D6: =C6 -> 0.4009322 | E6: =D6 -> 0.4009322 | F6: =E6 -> 0.4009322 | G6: =F6 -> 0.4009322 | H6: =G6 -> 0.4009322 | I6: =H6 -> 0.4009322 | J6: =I6 -> 0.4009322 | K6: =J6 -> 0.4009322 | L6: =K6 -> 0.4009322 | N6: =L6 -> 0.4009322 | P6: Enterprise value = Equity Value + Minority interest
A7: Less: Tax on EBIT | C7: =Assumptions!$B$35*'DCF Valuation'!C5 -> 3171.4771 | D7: =Assumptions!$B$35*'DCF Valuation'!D5 -> 3487.7835 | E7: =Assumptions!$B$35*'DCF Valuation'!E5 -> 3824.2861 | F7: =Assumptions!$B$35*'DCF Valuation'!F5 -> 4180.8091 | G7: =Assumptions!$B$35*'DCF Valuation'!G5 -> 4556.9636 | H7: =Assumptions!$B$35*'DCF Valuation'!H5 -> 4952.1314 | I7: =Assumptions!$B$35*'DCF Valuation'!I5 -> 5365.4513 | J7: =Assumptions!$B$35*'DCF Valuation'!J5 -> 5795.807 | ... L7: =Assumptions!$B$35*'DCF Valuation'!L5 -> 6701.8416 | N7: =Assumptions!$B$35*N5 -> 6969.9153
A8: EBIT(1-T) | C8: =C5-C7 -> 7400.1133 | D8: =D5-D7 -> 8138.1614 | E8: =E5-E7 -> 8923.3342 | F8: =F5-F7 -> 9755.2213 | G8: =G5-G7 -> 10632.915 | H8: =H5-H7 -> 11554.973 | I8: =I5-I7 -> 12519.386 | J8: =J5-J7 -> 13523.55 | ... L8: =L5-L7 -> 15637.63 | N8: =N5-N7 -> 16263.136
A9: Less: Net Capital Expenditure | C9: =C3*'Fixed Asset Scheduled'!$C$11 -> 1910.8337 | D9: =D3*'Fixed Asset Scheduled'!$C$11 -> 2101.4101 | E9: =E3*'Fixed Asset Scheduled'!$C$11 -> 2304.1549 | F9: =F3*'Fixed Asset Scheduled'!$C$11 -> 2518.9622 | G9: =G3*'Fixed Asset Scheduled'!$C$11 -> 2745.5974 | H9: =H3*'Fixed Asset Scheduled'!$C$11 -> 2983.6884 | I9: =I3*'Fixed Asset Scheduled'!$C$11 -> 3232.716 | J9: =J3*'Fixed Asset Scheduled'!$C$11 -> 3492.0079 | ... L9: =L3*'Fixed Asset Scheduled'!$C$11 -> 4037.8991
A10: Non Cash Working Capital | B10: ='Change in working Capital'!F5 -> 10060.87 | C10: ='Change in working Capital'!$C$9*'DCF Valuation'!C3 -> 6271.5279 | D10: ='Change in working Capital'!$C$9*'DCF Valuation'!D3 -> 6897.0169 | E10: ='Change in working Capital'!$C$9*'DCF Valuation'!E3 -> 7562.4436 | F10: ='Change in working Capital'!$C$9*'DCF Valuation'!F3 -> 8267.4602 | G10: ='Change in working Capital'!$C$9*'DCF Valuation'!G3 -> 9011.2976 | H10: ='Change in working Capital'!$C$9*'DCF Valuation'!H3 -> 9792.7335 | I10: ='Change in working Capital'!$C$9*'DCF Valuation'!I3 -> 10610.065 | J10: ='Change in working Capital'!$C$9*'DCF Valuation'!J3 -> 11461.084 | ... L10: ='Change in working Capital'!$C$9*'DCF Valuation'!L3 -> 13252.748
A11: Less: Change in Working Capital | C11: =C10-B10 -> -3789.3421 | D11: =D10-C10 -> 625.48901 | E11: =E10-D10 -> 665.42674 | F11: =F10-E10 -> 705.01661 | G11: =G10-F10 -> 743.8374 | H11: =H10-G10 -> 781.43589 | I11: =I10-H10 -> 817.33107 | J11: =J10-I10 -> 851.01925 | ... L11: =L10-K10 -> 909.68381
A12: Reinvestment | C12: =C9+C11 -> -1878.5085 | D12: =D9+D11 -> 2726.8991 | E12: =E9+E11 -> 2969.5817 | F12: =F9+F11 -> 3223.9788 | G12: =G9+G11 -> 3489.4348 | H12: =H9+H11 -> 3765.1243 | I12: =I9+I11 -> 4050.0471 | J12: =J9+J11 -> 4343.0271 | ... L12: =L9+L11 -> 4947.5829 | N12: =N8*N14 -> 91.263315
A13: Free Cash Flow To Firm (FCFF) | C13: =C8-C12 -> 9278.6217 | D13: =D8-(D12) -> 5411.2623 | E13: =E8-(E12) -> 5953.7526 | F13: =F8-(F12) -> 6531.2425 | G13: =G8-(G12) -> 7143.4802 | H13: =H8-(H12) -> 7789.849 | I13: =I8-(I12) -> 8469.3392 | J13: =J8-(J12) -> 9180.5225 | K13: =K8-(K12) -> 9921.5323 | L13: =L8-(L12) -> 10690.047 | N13: =N8-N12 -> 16171.872
A14: Implied Reinvestment rate % | C14: =C13/C8 -> 1.2538486 | D14: =D13/D8 -> 0.66492443 | E14: =E13/E8 -> 0.66721165 | F14: =F13/F8 -> 0.66951249 | G14: =G13/G8 -> 0.67182707 | H14: =H13/H8 -> 0.67415552 | I14: =I13/I8 -> 0.67649795 | J14: =J13/J8 -> 0.6788545 | ... L14: =L13/L8 -> 0.68361045 | N14: =$Q$4 -> 0.0056116679
A16: Terminal Value | L16: =L13/(Q3-Q2) -> 106589.56
A18: Present Value Interest Factor(PVIF) | C18: =1/(1+$Q$3)^C1 -> 0.87696859 | D18: =1/(1+$Q$3)^D1 -> 0.76907391 | E18: =1/(1+$Q$3)^E1 -> 0.67445366 | F18: =1/(1+$Q$3)^F1 -> 0.59147467 | G18: =1/(1+$Q$3)^G1 -> 0.51870471 | H18: =1/(1+$Q$3)^H1 -> 0.45488774 | I18: =1/(1+$Q$3)^I1 -> 0.39892226 | J18: =1/(1+$Q$3)^J1 -> 0.34984229 | ... L18: =1/(1+$Q$3)^L1 -> 0.26905458
A20: Present value of FCFF | C20: =SUMPRODUCT(C18:L18,C13:L13) -> 39936.661
A21: Present value of Terminal value | C21: =L16*L18 -> 28678.408
H22: Calculation of Sensitivity Analysis
A23: Value of operating assets | C23: =C20+C21 -> 68615.069 | H23: Terminal Growth ↓ / WACC →
A24: Add: Cash | C24: ='Historical FS'!F40 -> 10088.55 | H24: =C30 -> 85.218293 | I24: =J24-1% -> 0.1202917 | J24: =K24-1% -> 0.1302917 | K24: =$Q$3 -> 0.1402917 | L24: =K24+1% -> 0.1502917 | M24: =L24+1% -> 0.1602917
A25: Less: Debt | C25: ='Historical FS'!F18+'Historical FS'!F13 -> 3770.45 | H25: =H26-1% -> 0.02 | I25: 95.574103 | J25: 106.18098 | K25: 106.18098 | L25: 95.574103 | M25: 79.794894
A26: Less: Minority Interest | C26: ='Historical FS'!F79 -> 10.95 | H26: =H27-1% -> 0.03 | I26: 92.044036 | J26: 101.4645 | K26: 101.4645 | L26: 92.044036 | M26: 77.70757
A27: Equity Value | C27: =C23+C24-C25-C26 -> 74922.219 | H27: =$Q$2 -> 0.04 | I27: 92.044036 | J27: 101.4645 | K27: 101.4645 | L27: 92.044036 | M27: 77.70757
H28: =H27+1% -> 0.05 | I28: 95.574103 | J28: 106.18098 | K28: 106.18098 | L28: 95.574103 | M28: 79.794894
A29: No. of Shares outstanding (Cr) | C29: ='Relative Valuation'!D5/'Relative Valuation'!B5 -> 879.18 | H29: =H28+1% -> 0.06 | I29: 105.27217 | J29: 119.63986 | K29: 119.63986 | L29: 105.27217 | M29: 85.218293
A30: intrinsic value per share | C30: =C27/C29 -> 85.218293

Sheet Relative Valuation
A1: RELATIVE VALUATION – NMDC (FY2025 | INR Crores)
A3: Company | B3: Market Data | F3: Financial Data | J3: Valuation Ratios
B4: Price (₹) | C4: Shares (Cr.) | D4: Mkt Cap (Cr.) | E4: EV (Cr.) | F4: Revenue (Cr.) | G4: EBITDA (Cr.) | H4: EBIT (Cr.) | I4: EPS (₹) | J4: P/E | K4: EV/Sales | L4: EV/EBITDA | M4: EV/EBIT
A5: NMDC | B5: 89 | C5: ='Historical FS'!F6 -> 879.18 | D5: =B5*C5 -> 78247.02 | E5: =D5+'Historical FS'!F13+'Historical FS'!F18-'Historical FS'!F40-'Historical FS'!F37 -> 71925.32 | F5: =Assumptions!F3 -> 23905.52 | G5: =Assumptions!F9 -> 8148.67 | H5: =Assumptions!F11 -> 7728.25 | I5: ='Consolidated P&L'!F41 -> 7 | J5: =B5/I5 -> 12.714286 | K5: =E5/F5 -> 3.0087327 | L5: =E5/G5 -> 8.8266331 | M5: =E5/H5 -> 9.3068056
A6: JSW Steel | B6: 1270.3 | C6: 305 | D6: 310157 | E6: 379433.75 | F6: 168824 | G6: 23107 | H6: 13798 | I6: 85.19 | J6: =B6/I6 -> 14.911375 | K6: =E6/F6 -> 2.2475107 | L6: =E6/G6 -> 16.420727 | M6: =E6/H6 -> 27.499185
A7: Tata Steel | B7: 208.28 | C7: 1247.44 | D7: 259907 | E7: 248133.35 | F7: 218542.51 | G7: 25933.85 | H7: 22767.25 | I7: 2.59 | J7: =B7/I7 -> 80.416988 | K7: =E7/F7 -> 1.1354008 | L7: =E7/G7 -> 9.5679334 | M7: =E7/H7 -> 10.898697
A8: Hindalco | B8: 1048.8 | C8: 222 | D8: 235240 | E8: 161568.7 | F8: 238496 | G8: 33650 | H8: 25769 | I8: 72.04 | J8: =B8/I8 -> 14.558579 | K8: =E8/F8 -> 0.67744826 | L8: =E8/G8 -> 4.8014473 | M8: =E8/H8 -> 6.2698863
A9: Jindal steel | B9: 1210 | C9: 101.18 | D9: 123318 | E9: 95634.4 | F9: 57876.54 | G9: 8432.25 | H9: 7535.6 | I9: 27.88 | J9: =B9/I9 -> 43.400287 | K9: =E9/F9 -> 1.6523863 | L9: =E9/G9 -> 11.341504 | M9: =E9/H9 -> 12.691013
A10: Lloyds steel | B10: 1668.3 | C10: 52.32 | D10: 93647 | E10: 67277.84 | F10: 6626.31 | G10: 2004.13 | H10: 1923.33 | I10: 27.71 | J10: =B10/I10 -> 60.205702 | K10: =E10/F10 -> 10.153138 | L10: =E10/G10 -> 33.569599 | M10: =E10/H10 -> 34.979873
A11: Peer Average | B11: =AVERAGE(B6:B10) -> 1081.136 | C11: =AVERAGE(C6:C10) -> 385.588 | D11: =AVERAGE(D6:D10) -> 204453.8 | E11: =AVERAGE(E6:E10) -> 190409.61 | F11: =AVERAGE(F6:F10) -> 138073.07 | G11: =AVERAGE(G6:G10) -> 18625.446 | H11: =AVERAGE(H6:H10) -> 14358.636 | I11: =AVERAGE(I6:I10) -> 43.082 | ... M11: =AVERAGE(M6:M10) -> 18.467731
A12: Peer Median | B12: =MEDIAN(B6:B10) -> 1210 | C12: =MEDIAN(C6:C10) -> 222 | D12: =MEDIAN(D6:D10) -> 235240 | E12: =MEDIAN(E6:E10) -> 161568.7 | F12: =MEDIAN(F6:F10) -> 168824 | G12: =MEDIAN(G6:G10) -> 23107 | H12: =MEDIAN(H6:H10) -> 13798 | I12: =MEDIAN(I6:I10) -> 27.88 | ... M12: =MEDIAN(M6:M10) -> 12.691013
A14: NMDC — IMPLIED SHARE PRICE FROM PEER MULTIPLES
A15: Valuation Basis | B15: Peer Avg Multiple | C15: Peer Median Multiple | D15: NMDC Actual | E15: Implied EV (Avg) | F15: Implied EV (Median) | G15: Implied Equity (Avg) | H15: Implied Equity (Median) | I15: Implied Price (Avg) ₹ | J15: Implied Price (Med) ₹ | K15: CMP ₹ | L15: Premium/Disc (vs Avg) | M15: Premium/Disc (vs Med)
A16: EV / Sales | B16: =K11 -> 3.1731768 | C16: =K12 -> 1.6523863 | D16: =K5 -> 3.0087327 | E16: =B16*F5 -> 75856.442 | F16: =C16*F5 -> 39501.153 | G16: =E16-(E5-D5) -> 82178.142 | H16: =F16-(E5-D5) -> 45822.853 | I16: =G16/C5 -> 93.471351 | J16: =H16/C5 -> 52.11999 | K16: =B5 -> 89 | L16: =(B5-I16)/I16 -> -0.047836589 | M16: =(B5-J16)/J16 -> 0.70759817
A17: EV / EBITDA | B17: =L11 -> 15.140242 | C17: =L12 -> 11.341504 | D17: =L5 -> 8.8266331 | E17: =B17*G5 -> 123372.84 | F17: =C17*G5 -> 92418.176 | G17: =E17-(E5-D5) -> 129694.54 | H17: =F17-(E5-D5) -> 98739.876 | I17: =G17/C5 -> 147.51762 | J17: =H17/C5 -> 112.30906 | K17: =K16 -> 89 | L17: =(B5-I17)/I17 -> -0.39668223 | M17: =(B5-J17)/J17 -> -0.20754387
A18: P / E | B18: =J11 -> 42.698586 | C18: =J12 -> 43.400287 | D18: =J5 -> 12.714286 | E18: =B18*I5 -> 298.8901 | F18: =C18*I5 -> 303.80201 | G18: =E18*C5 -> 262778.2 | H18: =F18*C5 -> 267096.65 | I18: =E18 -> 298.8901 | J18: =F18 -> 303.80201 | K18: =K17 -> 89 | L18: =(B5-I18)/I18 -> -0.70223169 | M18: =(B5-J18)/J18 -> -0.70704604
O20: EV/Revenue | P20: EV/EBITDA | Q20: P/E Ratio
A21: Max | O21: =MAX(K6:K10) -> 10.153138 | P21: =MAX(L6:L10) -> 33.569599 | Q21: =MAX(J6:J10) -> 80.416988
A22: 75th Percentile | O22: =QUARTILE(K6:K10,3) -> 2.2475107 | P22: =QUARTILE(L6:L10,3) -> 16.420727 | Q22: =QUARTILE(J6:J10,3) -> 60.205702
A23: Average | O23: =AVERAGE(K6:K10) -> 3.1731768 | P23: =AVERAGE(L6:L10) -> 15.140242 | Q23: =AVERAGE(J6:J10) -> 42.698586
A24: median | O24: =MEDIAN(K6:K10) -> 1.6523863 | P24: =MEDIAN(L6:L10) -> 11.341504 | Q24: =MEDIAN(J6:J10) -> 43.400287
A25: 25th Percentile | O25: =QUARTILE(K6:K10,1) -> 1.1354008 | P25: =QUARTILE(L6:L10,1) -> 9.5679334 | Q25: =QUARTILE(J6:J10,1) -> 14.911375
A26: Min. | O26: =MIN(K6:K10) -> 0.67744826 | P26: =MIN(L6:L10) -> 4.8014473 | Q26: =MIN(J6:J10) -> 14.558579
A28: Industry Comparable comps | O28: EV/Revenue | P28: EV/EBITDA | Q28: P/E Ratio
A30: Implied Enterprise Value | O30: =O23*F5 -> 75856.442 | P30: =P23*G5 -> 123372.84 | Q30: =Q23*I5*C5 -> 262778.2
A31: Net Debt | O31: =E5-D5 -> -6321.7 | P31: =E5-D5 -> -6321.7 | Q31: =E5-D5 -> -6321.7
A32: Implied Market Value | O32: =O30-O31 -> 82178.142 | P32: =P30-P31 -> 129694.54 | Q32: =Q30-Q31 -> 269099.9
A33: Share Outstanding | O33: =C5 -> 879.18 | P33: =C5 -> 879.18 | Q33: =C5 -> 879.18
A35: Implied Value per Share | O35: =O32/O33 -> 93.471351 | P35: =P32/P33 -> 147.51762 | Q35: =Q23*I5 -> 298.8901
